Workbook

Sheet TRA balance
A1: 0.041868 | B1: ktoe to PJ
L2: =SUM(L16:L24) -> 11358.936 | Z2: =SUM(Z16:Z24) -> 26443.057 | AA2: =Z2/L2 -> 2.3279519
B4: Sector | C4: Sub-Sector | D4: sectfuel | E4: Africa_North | F4: Africa_Other | G4: Australia | H4: Austria | I4: Baltics | J4: BeNeLux | K4: Brazil | L4: China | M4: CroSloven | N4: CzechSlovak | O4: France | P4: Germany | Q4: GreeceCyp | R4: HunRomBul | S4: Iceland | T4: India | U4: Ireland | V4: ItalyMal | W4: Japan | X4: LatAm | Y4: MidEast | Z4: NorthAm | AA4: Norway | AB4: Poland | AC4: ROW | AD4: Russia | AE4: SaudiArabia | AF4: SouthAfrica | AG4: SpainPor | AH4: SweFinDen | AI4: Switzerland | AJ4: Turkey | AK4: UK | AL4: Ukraine | AM4: WestBalkans | AN4: \I: | AO4: \I: | AP4: \I: | AQ4: \I: | AR4: \I: | AS4: \I: | AT4: \I: | AU4: \I: | AV4: \I: | AW4: \I: | AX4: \I:
A5: =IF(OR(C5="TT",C5="TR"),"RR","") | B5: TRA | C5: NEU | D5: COACOK | K5: 6.1607004 | Z5: 2.5819619 | AB5: 0.023990364 | BA5: Bio Diesel | BB5: TRABDS | BC5: bdl
A6: =IF(OR(C6="TT",C6="TR"),"RR","") | B6: TRA | C6: NEU | D6: OILASP | F6: 2.3701893 | L6: 1314.758 | Q6: 0.011388096 | R6: 0.04711406 | X6: 0.37424549 | Y6: 1.7316019 | Z6: 22.480001 | AA6: 0.079440343 | AB6: 0.011036405 | AC6: 0.50052775 | AF6: 3.601925 | AL6: 15.369902 | BA6: Bio Gasoline | BB6: TRABGS | BC6: eth
A7: =IF(OR(C7="TT",C7="TR"),"RR","") | B7: TRA | C7: NEU | D7: OILKER | E7: 0.27722059 | J7: 0.075379147 | R7: 0.0033159456 | X7: 0.23994969 | AC7: 0.69119881 | BA7: Biogas | BB7: TRANGA | BC7: nga
A8: =IF(OR(C8="TT",C8="TR"),"RR","") | B8: TRA | C8: NEU | D8: OILLUB | E8: 2.5678105 | F8: 2.1184789 | H8: 0.61794237 | I8: 2.2514098 | J8: 5.7442561 | L8: 99.093555 | M8: 0.77719987 | N8: 8.4419998 | O8: 12.396298 | P8: 13.188001 | Q8: 0.84525212 | R8: 5.9773855 | S8: 0.14898309 | U8: 1.2904513 | V8: 9.2316009 | W8: 56.685228 | X8: 2.2883667 | Y8: 8.2227203 | Z8: 126.706 | AA8: 1.894033 | AB8: 16.821855 | AC8: 41.817867 | AF8: 6.0861251 | AG8: 10.991359 | AH8: 1.7354412 | AI8: 1.237907 | AJ8: 7.5179981 | AK8: 5.7178709 | AL8: 2.0426644 | AM8: 1.3844157 | BA8: Coal | BB8: TRACOA | BC8: coa
A9: =IF(OR(C9="TT",C9="TR"),"RR","") | B9: TRA | C9: NEU | D9: OILNSP | F9: 0.14324718 | Z9: 261.44 | AC9: 3.0110796 | AL9: 0.035998106 | BA9: Diesel | BB9: TRADST | BC9: dsl
A10: =IF(OR(C10="TT",C10="TR"),"RR","") | B10: TRA | C10: TAD | D10: TRADST | F10: 0.046243206 | X10: 0.30864252 | AC10: 0.068814245 | AF10: 0.74616312 | BA10: Electricity | BB10: TRAELC | BC10: elc
A11: =IF(OR(C11="TT",C11="TR"),"RR","") | B11: TRA | C11: TAD | D11: TRAGSL | U11: 0.030932078 | X11: 0.6908848 | AC11: 0.008959752 | AH11: 4.60548e-05 | BA11: Gasoline | BB11: TRAGSL | BC11: gsl
A12: =IF(OR(C12="TT",C12="TR"),"RR","") | B12: TRA | C12: TAD | D12: TRAHFO | E12: 0.011999369 | AC12: 0.0005945256 | AL12: 7.6400015 | BA12: Heavy Fuel Oil | BB12: TRAHFO | BC12: hfo
A13: =IF(OR(C13="TT",C13="TR"),"RR","") | B13: TRA | C13: TAD | D13: TRAJTK | E13: 28.892667 | F13: 22.625924 | G13: 123.7187 | H13: 1.3079814 | I13: 0.088663864 | J13: 0.552532 | K13: 140.16919 | L13: 1141.751 | M13: 0.46967522 | N13: 1.9810012 | O13: 67.799231 | P13: 30.753001 | Q13: 9.4633277 | R13: 3.1982965 | S13: 0.37972601 | T13: 179.28629 | U13: 0.2140962 | V13: 37.984525 | W13: 147.59977 | X13: 89.066462 | Y13: 60.200674 | Z13: 2814.8465 | AA13: 14.700114 | AB13: 1.416206 | AC13: 364.07691 | AD13: 245.7902 | AE13: 40.847534 | AF13: 51.997134 | AG13: 104.06785 | AH13: 10.771347 | AI13: 2.7698194 | AJ13: 50.438999 | AK13: 37.125494 | BA13: Liquified Petroleum Gases | BB13: TRALPG | BC13: lpg
A14: =IF(OR(C14="TT",C14="TR"),"RR","") | B14: TRA | C14: TAI | D14: TRAHFO | AL14: -5.0799994 | BA14: Natural Gas | BB14: TRANGA | BC14: nga
A15: =IF(OR(C15="TT",C15="TR"),"RR","") | B15: TRA | C15: TAI | D15: TRAJTK | E15: -99.12303 | F15: -192.0928 | G15: -211.35653 | H15: -39.679409 | I15: -14.533446 | J15: -260.82317 | K15: -101.44622 | L15: -449.18389 | M15: -9.49395 | N15: -19.306997 | O15: -260.04602 | P15: -409.876 | Q15: -60.35572 | R15: -28.180049 | S15: -13.042242 | T15: -177.46911 | U15: -45.331459 | V15: -173.05438 | W15: -305.52365 | X15: -322.41766 | Y15: -762.82424 | Z15: -1284.859 | AA15: -22.942529 | AB15: -45.054661 | AC15: -1737.5926 | AD15: -253.11288 | AE15: -153.09619 | AF15: -46.072598 | AG15: -260.69911 | AH15: -115.46579 | AI15: -77.950186 | AJ15: -184.427 | AK15: -493.23921 | AL15: -2.2117399 | AM15: -9.5715565
A16: =IF(OR(C16="TT",C16="TR"),"RR","") -> RR | B16: TRA | C16: TR | D16: TRABDS | G16: 0.036801972 | H16: 17.82448 | I16: 4.5833402 | J16: 36.929908 | K16: 651.02992 | L16: 37.904001 | M16: 6.3832958 | N16: 16.72985 | O16: 105.70326 | P16: 79.09389 | Q16: 7.1657333 | R16: 25.91164 | S16: 0.64893307 | T16: 1.6369383 | U16: 6.7818205 | V16: 52.609281 | W16: 0.51924694 | X16: 74.263528 | Z16: 204.23943 | AA16: 17.542525 | AB16: 35.076408 | AC16: 285.06459 | AD16: 0.0720004 | AG16: 73.584672 | AH16: 71.665049 | AI16: 6.2732499 | AJ16: 4.7795002 | AK16: 52.885602 | AM16: 5.0352592
A17: =IF(OR(C17="TT",C17="TR"),"RR","") -> RR | B17: TRA | C17: TR | D17: TRABGS | F17: 1.9221473 | G17: 5.3332003 | H17: 2.3656341 | I17: 1.0224877 | J17: 14.558935 | K17: 235.95355 | L17: 85.76 | M17: 0.21750426 | N17: 3.9087002 | O17: 27.351933 | P17: 30.097494 | Q17: 1.0531602 | R17: 7.3426089 | S17: 0.16850614 | T17: 36.820817 | U17: 1.096703 | V17: 1.2742944 | W17: 16.636849 | X17: 53.089533 | Z17: 1435.2023 | AA17: 1.7838866 | AB17: 7.8426342 | AC17: 53.43862 | AG17: 5.7976587 | AH17: 9.3798262 | AI17: 1.3390098 | AJ17: 2.2267998 | AK17: 16.015121 | AL17: 3.6889769
A18: =IF(OR(C18="TT",C18="TR"),"RR","") -> RR | B18: TRA | C18: TR | D18: TRADST | E18: 1112.0205 | F18: 988.22762 | G18: 575.63791 | H18: 258.65054 | I18: 121.27005 | J18: 548.23218 | K18: 1435.9916 | L18: 3881.3716 | M18: 120.49403 | N18: 258.1986 | O18: 1286.4001 | P18: 1389.2712 | Q18: 112.34776 | R18: 402.84348 | S18: 7.7045954 | T18: 2433.6589 | U18: 123.34464 | V18: 900.04498 | W18: 913.27098 | X18: 1474.3679 | Y18: 1497.7659 | Z18: 6300.1461 | AA18: 88.600161 | AB18: 592.79821 | AC18: 4015.3714 | AD18: 701.32953 | AE18: 851.79872 | AF18: 347.12819 | AG18: 1074.1823 | AH18: 322.46291 | AI18: 113.81519 | AJ18: 822.3504 | AK18: 1014.1394 | AL18: 181.7944 | AM18: 187.7206 | BA18: =31536000/10^9 -> 0.031536 | BB18: GJ/lt Gasoline | BD18: =1/BA18 -> 31.709792 | BE18: km/l | BF18: equivalent to Bvkm/PJ = 1 | BJ18: =100/BD18 -> 3.1536 | BK18: l/100km
A19: =IF(OR(C19="TT",C19="TR"),"RR","") -> RR | B19: TRA | C19: TR | D19: TRAELC | G19: 0.086398805 | H19: 0.051355289 | I19: 0.29186601 | J19: 2.3190267 | L19: 245.36301 | M19: 0.01288697 | N19: 0.33488538 | O19: 1.1790573 | P19: 1.2096 | Q19: 0.073859339 | R19: 0.42334828 | S19: 0.081198799 | U19: 0.097590121 | V19: 0.49744627 | X19: 2.9411098 | Z19: 28.044514 | AA19: 3.0923998 | AB19: 0.11810544 | AC19: 1.767265 | AD19: 0.55079866 | AF19: 0.19335061 | AG19: 0.60042061 | AH19: 1.3584366 | AK19: 1.3193653 | AM19: 0.013138178 | BA19: 0.038 | BB19: GJ/lt Diesel | BD19: =1/BA19 -> 26.315789 | BE19: km/l | BF19: equivalent to Bvkm/PJ = 1 | BJ19: =100/BD19 -> 3.8 | BK19: l/100km
A20: =IF(OR(C20="TT",C20="TR"),"RR","") -> RR | B20: TRA | C20: TR | D20: TRAGSL | E20: 715.67029 | F20: 1242.7522 | G20: 568.92184 | H20: 69.244171 | I20: 28.915921 | J20: 267.91204 | K20: 898.18184 | L20: 6001.8947 | M20: 37.58546 | N20: 89.100003 | O20: 329.10323 | P20: 722.612 | Q20: 113.01532 | R20: 138.86752 | S20: 5.224737 | T20: 1342.88 | U20: 32.232683 | V20: 326.47973 | W20: 1584.5382 | X20: 1707.7906 | Y20: 2359.6239 | Z20: 18347.249 | AA20: 27.89587 | AB20: 194.31689 | AC20: 4523.0065 | AD20: 1546.967 | AE20: 1019.3707 | AF20: 316.57445 | AG20: 271.13869 | AH20: 190.16307 | AI20: 99.873313 | AJ20: 99.307999 | AK20: 515.39092 | AL20: 77.150482 | AM20: 39.119211
A21: =IF(OR(C21="TT",C21="TR"),"RR","") -> RR | B21: TRA | C21: TR | D21: TRAHFO | Q21: 0.0020808396 | T21: 0.064200391 | X21: 0.090451627 | AC21: 0.35676141 | AF21: 0.7493116
A22: =IF(OR(C22="TT",C22="TR"),"RR","") -> RR | B22: TRA | C22: TR | D22: TRAJTK | X22: 0.32455655 | AC22: 0.028315328 | AF22: 2.5273995 | BJ22: =BJ18/7.96 -> 0.3961809
A23: =IF(OR(C23="TT",C23="TR"),"RR","") -> RR | B23: TRA | C23: TR | D23: TRALPG | E23: 42.939992 | F23: 0.024643505 | G23: 15.20776 | H23: 0.21937576 | I23: 6.9182599 | J23: 8.1889663 | L23: 78.302157 | M23: 3.6899357 | N23: 4.0479992 | O23: 2.4205649 | P23: 15.594 | Q23: 10.084603 | R23: 23.316779 | T23: 8.1308703 | U23: 0.066515692 | V23: 76.071765 | W23: 29.848275 | X23: 34.59714 | Y23: 2.8085347 | Z23: 73.826506 | AA23: 0.21472841 | AB23: 89.009999 | AC23: 232.23175 | AD23: 59.523082 | AF23: 0.65408283 | AG23: 5.6658625 | AI23: 0.070748546 | AJ23: 154.284 | AK23: 2.8979983 | AL23: 83.334339 | AM23: 10.48134
A24: =IF(OR(C24="TT",C24="TR"),"RR","") -> RR | B24: TRA | C24: TR | D24: TRANGA | E24: 20.348053 | F24: 0.074688325 | G24: 3.1234533 | H24: 0.78398667 | I24: 0.80425079 | J24: 3.8368882 | K24: 84.173068 | L24: 1028.3403 | M24: 0.35124321 | N24: 3.1564536 | O24: 6.8120701 | P24: 8.336551 | Q24: 0.74906039 | R24: 4.0482462 | S24: 0.074441304 | T24: 123.38074 | V24: 40.18888 | W24: 1.3990067 | X24: 161.88196 | Y24: 279.44311 | Z24: 54.348445 | AA24: 2.3698251 | AB24: 0.71836696 | AC24: 364.89504 | AD24: 8.9056167 | AF24: 0.0073310868 | AG24: 8.8681657 | AH24: 5.276063 | AI24: 0.58408791 | AJ24: 3.343591 | AK24: 0.56970206 | AL24: 1.3454994 | AM24: 0.54971847 | BA24: mtoe | BB24: 41.868 | BC24: PJ | BJ24: =BJ18/14.35 -> 0.21976307
A25: =IF(OR(C25="TT",C25="TR"),"RR","") -> RR | B25: TRA | C25: TT | D25: TRABDS | H25: 0.077011999 | I25: 0.12838822 | J25: 0.069345968 | K25: 4.392284 | N25: 0.18499794 | O25: 0.34193177 | P25: 0.59372592 | Z25: 17.209033 | AC25: 0.0012602268 | AI25: 0.012983267
A26: =IF(OR(C26="TT",C26="TR"),"RR","") -> RR | B26: TRA | C26: TT | D26: TRACOA | F26: 0.146157 | H26: 0.0042998436 | J26: 0.0026293104 | M26: 0.0042998436 | N26: 0.013163299 | W26: 0.035989733 | AC26: 1.4617459 | AD26: 0.24252458 | AK26: 0.41068321 | AL26: 0.19784723
A27: =IF(OR(C27="TT",C27="TR"),"RR","") -> RR | B27: TRA | C27: TT | D27: TRADST | E27: 2.6678206 | F27: 15.084555 | G27: 47.668292 | H27: 1.3269476 | I27: 4.6106423 | J27: 1.8967628 | K27: 40.785771 | L27: 114.11818 | M27: 0.92079455 | N27: 3.2801987 | O27: 4.9130172 | P27: 10.735198 | Q27: 0.4441483 | R27: 7.4542708 | T27: 109.95602 | U27: 1.6395048 | V27: 1.8318004 | W27: 6.6902008 | X27: 1.9532134 | Y27: 3.4297931 | Z27: 683.88749 | AA27: 0.56947598 | AB27: 3.5821926 | AC27: 77.80904 | AD27: 172.01398 | AF27: 5.0480499 | AG27: 3.8659069 | AH27: 4.553258 | AI27: 0.37943712 | AJ27: 4.8563991 | AK27: 27.030977 | AL27: 1.4202295 | AM27: 0.78320793 | BA27: 1489
A28: =IF(OR(C28="TT",C28="TR"),"RR","") -> RR | B28: TRA | C28: TT | D28: TRAELC | E28: 7.7860747 | F28: 0.18188715 | G28: 11.664002 | H28: 7.1522058 | I28: 0.3407176 | J28: 12.159903 | K28: 8.1020442 | L28: 351.09232 | M28: 1.663558 | N28: 7.4760924 | O28: 30.492908 | P28: 40.568401 | Q28: 0.65615948 | R28: 8.8579374 | T28: 68.932798 | U28: 0.18660986 | V28: 19.979468 | W28: 62.294204 | X28: 5.2044101 | Z28: 30.383122 | AA28: 2.1131994 | AB28: 11.327773 | AC28: 50.950467 | AD28: 192.82644 | AF28: 9.3600017 | AG28: 14.232742 | AH28: 13.254643 | AI28: 10.950002 | AJ28: 4.6356208 | AK28: 20.356774 | AL28: 19.267557 | AM28: 1.6868575
A29: =IF(OR(C29="TT",C29="TR"),"RR","") -> RR | B29: TRA | C29: TT | D29: TRAGSL | G29: 0.044555926 | Q29: 0.010111122 | X29: 0.022219348 | AC29: 0.08267674 | AD29: 1.196801 | AF29: 1.3372053 | AH29: 8.79228e-05 | BA29: 6344
A30: =IF(OR(C30="TT",C30="TR"),"RR","") -> RR | B30: TRA | C30: TT | D30: TRAHFO | E30: 4.2400017 | G30: 0.0017040276 | AC30: 0.022303084 | AD30: 0.087198484 | AF30: 3.0902729 | BA30: 39.45
A31: =IF(OR(C31="TT",C31="TR"),"RR","") | B31: TRA | C31: TWD | D31: TRABDS | J31: 0.11824779 | O31: 0.1783828 | Q31: 0.016964914 | S31: 4.1868e-05 | Z31: 4.5131527 | AC31: 0.25656292 | AG31: 0.10596372 | AH31: 0.16820469 | AI31: 0.028968469 | BA31: 14164
A32: =IF(OR(C32="TT",C32="TR"),"RR","") | B32: TRA | C32: TWD | D32: TRADST | E32: 2.2515982 | F32: 20.462294 | G32: 12.196211 | H32: 1.0391428 | I32: 0.51737544 | J32: 17.810082 | K32: 13.32218 | L32: 622.70791 | M32: 2.0970593 | N32: 0.21299926 | O32: 7.330823 | P32: 11.246398 | Q32: 12.483463 | R32: 2.0379668 | S32: 0.50608782 | T32: 35.081662 | U32: 3.6805991 | V32: 10.836217 | W32: 42.246633 | X32: 34.985403 | Z32: 204.48558 | AA32: 36.0773 | AB32: 0.077958216 | AC32: 246.6528 | AD32: 17.148957 | AF32: 11.016965 | AG32: 20.691115 | AH32: 10.993741 | AI32: 0.99500977 | AJ32: 14.824801 | AK32: 36.848575 | AL32: 5.6338711 | AM32: 1.5225466
A33: =IF(OR(C33="TT",C33="TR"),"RR","") | B33: TRA | C33: TWD | D33: TRAGSL | F33: 2.8287654 | G33: 11.24232 | H33: 0.098561459 | I33: 0.0038267352 | J33: 0.0018463788 | O33: 13.110286 | Q33: 0.0027716616 | V33: 0.01746733 | X33: 0.33602838 | Z33: 198.209 | AA33: 2.6370978 | AC33: 9.0982597 | AD33: 0.5852016 | AF33: 0.038229671 | AH33: 1.3640008 | AI33: 0.52469815 | AM33: 0.29920129
A34: =IF(OR(C34="TT",C34="TR"),"RR","") | B34: TRA | C34: TWD | D34: TRAHFO | E34: 9.7814743 | F34: 0.26331623 | G34: 5.748401 | J34: 0.028001318 | K34: 40.989354 | L34: 395.31816 | O34: 0.47387877 | Q34: 14.360243 | S34: 0.19288169 | T34: 29.293742 | V34: 15.08628 | W34: 88.755182 | X34: 16.624213 | Z34: 38.472564 | AA34: 0.13216053 | AC34: 24.92101 | AD34: 7.8600011 | AG34: 25.903359 | AH34: 3.9209173 | AJ34: 1.3999989 | AK34: 0.33040132
A35: =IF(OR(C35="TT",C35="TR"),"RR","") | B35: TRA | C35: TWD | D35: TRANGA | AA35: 3.1542221 | BA35: 89.6
A36: =IF(OR(C36="TT",C36="TR"),"RR","") | B36: TRA | C36: TWI | D36: TRABDS | J36: -1.9816836 | Q36: -0.0015449292 | Z36: -8.5687467
A37: =IF(OR(C37="TT",C37="TR"),"RR","") | B37: TRA | C37: TWI | D37: TRADST | E37: -9.1431003 | F37: -35.018965 | G37: -3.2613707 | H37: -0.61301451 | I37: -16.595299 | J37: -133.05518 | K37: -19.71809 | L37: -32.562561 | M37: -2.0533784 | O37: -5.9298779 | P37: -30.075601 | Q37: -21.637881 | R37: -3.9072557 | S37: -1.9252204 | T37: -2.3815021 | U37: -5.4310332 | V37: -38.059729 | W37: -5.2803126 | X37: -69.303602 | Y37: -35.604874 | Z37: -461.73995 | AA37: -10.150599 | AB37: -8.1779215 | AC37: -407.61819 | AD37: -364.01444 | AF37: -68.67503 | AG37: -74.435618 | AH37: -38.84979 | AI37: -0.11148611 | AJ37: -6.1769996 | AK37: -67.570501 | AM37: -2.0118118
A38: =IF(OR(C38="TT",C38="TR"),"RR","") | B38: TRA | C38: TWI | D38: TRAHFO | E38: -26.703469 | F38: -53.407918 | G38: -28.83594 | I38: -10.737241 | J38: -673.11487 | K38: -119.43586 | L38: -443.04395 | M38: -6.7915506 | O38: -65.158239 | P38: -26.719999 | Q38: -95.445018 | R38: -0.70021718 | S38: -0.77315961 | T38: -65.767439 | U38: -0.4159209 | V38: -167.76879 | W38: -182.88818 | X38: -291.7926 | Y38: -833.70405 | Z38: -544.79755 | AA38: -1.4256012 | AB38: -3.2242003 | AC38: -2460.6436 | AD38: -88.48 | AE38: -135.01029 | AF38: -57.689934 | AG38: -261.79841 | AH38: -88.967679 | AJ38: -30.72 | AK38: -27.651319
A39: =IF(OR(C39="TT",C39="TR"),"RR","") | B39: TRA | C39: TWI | D39: TRAJTK | AC39: -6.9025134
A40: =IF(OR(C40="TT",C40="TR"),"RR","") | B40: TRA | C40: TWI | D40: TRANGA | I40: -0.8522985 | J40: -2.8695364 | AA40: -2.2015199 | AG40: -1.4913005 | AH40: -0.74190096
E42: =SUMIF($A$5:$A$40,"RR",E$5:E$40) -> 1905.6728 | F42: =SUMIF($A$5:$A$40,"RR",F$5:F$40) -> 2248.4139 | G42: =SUMIF($A$5:$A$40,"RR",G$5:G$40) -> 1227.7259 | H42: =SUMIF($A$5:$A$40,"RR",H$5:H$40) -> 357.70001 | I42: =SUMIF($A$5:$A$40,"RR",I$5:I$40) -> 168.88593 | J42: =SUMIF($A$5:$A$40,"RR",J$5:J$40) -> 896.10659 | K42: =SUMIF($A$5:$A$40,"RR",K$5:K$40) -> 3358.6101 | L42: =SUMIF($A$5:$A$40,"RR",L$5:L$40) -> 11824.146 | ... AY42: =SUMIF($A$5:$A$40,"RR",AY$5:AY$40) -> 0
E43: =SUM(Assumptions!BD3:BD103) -> 1905.6728 | F43: =SUM(Assumptions!BU3:BU103) -> 1417.7034 | G43: =SUM(Assumptions!BV3:BV103) -> 2598.5961 | H43: =SUM(Assumptions!BW3:BW103) -> 3463.0221 | I43: =SUM(Assumptions!BX3:BX103) -> 4143.0713 | J43: =SUM(Assumptions!BY3:BY103) -> 25739.334 | K43: =SUM(Assumptions!BZ3:BZ103) -> 142.39818 | L43: =SUM(Assumptions!CA3:CA103) -> 926.94795 | M43: =SUM(Assumptions!CB3:CB103) -> 9552.664 | ... AJ43: =SUM(Assumptions!CY3:CY103) -> 75.3 | AK43: =SUM(Assumptions!DP3:DP103) -> 74.136 | AL43: =SUM(Assumptions!DQ3:DQ103) -> 73.96 | AM43: =SUM(Assumptions!DR3:DR103) -> 75 | AN43: =SUM(Assumptions!DS3:DS103) -> 74.436 | AO43: =SUM(Assumptions!DT3:DT103) -> 73.603231 | AP43: =SUM(Assumptions!DU3:DU103) -> 74.136 | AQ43: =SUM(Assumptions!DV3:DV103) -> 75.86 | AR43: =SUM(Assumptions!DW3:DW103) -> 73.8 | ... AX43: =SUM(Assumptions!EC3:EC103) -> 74.136 | AY43: =SUM(Assumptions!CX3:CX103) -> 0
E45: =E4 -> Africa_North | F45: =F4 -> Africa_Other | G45: =G4 -> Australia | H45: =H4 -> Austria | I45: =I4 -> Baltics | J45: =J4 -> BeNeLux | K45: =K4 -> Brazil | L45: =L4 -> China | ... AY45: =AY4 -> 0
A46: TRABGS | B46: TRAGSL | C46: Road | D46: BGS/GSL | E46: =IFERROR(SUMIFS(E$5:E$39,$C$5:$C$39,"TR",$D$5:$D$39,$A46)/SUMIFS(E$5:E$39,$C$5:$C$39,"TR",$D$5:$D$39,$B46),"") -> 0 | F46: =IFERROR(SUMIFS(F$5:F$39,$C$5:$C$39,"TR",$D$5:$D$39,$A46)/SUMIFS(F$5:F$39,$C$5:$C$39,"TR",$D$5:$D$39,$B46),"") -> 0.0015466859 | G46: =IFERROR(SUMIFS(G$5:G$39,$C$5:$C$39,"TR",$D$5:$D$39,$A46)/SUMIFS(G$5:G$39,$C$5:$C$39,"TR",$D$5:$D$39,$B46),"") -> 0.0093742232 | H46: =IFERROR(SUMIFS(H$5:H$39,$C$5:$C$39,"TR",$D$5:$D$39,$A46)/SUMIFS(H$5:H$39,$C$5:$C$39,"TR",$D$5:$D$39,$B46),"") -> 0.034163657 | I46: =IFERROR(SUMIFS(I$5:I$39,$C$5:$C$39,"TR",$D$5:$D$39,$A46)/SUMIFS(I$5:I$39,$C$5:$C$39,"TR",$D$5:$D$39,$B46),"") -> 0.035360719 | J46: =IFERROR(SUMIFS(J$5:J$39,$C$5:$C$39,"TR",$D$5:$D$39,$A46)/SUMIFS(J$5:J$39,$C$5:$C$39,"TR",$D$5:$D$39,$B46),"") -> 0.054342222 | K46: =IFERROR(SUMIFS(K$5:K$39,$C$5:$C$39,"TR",$D$5:$D$39,$A46)/SUMIFS(K$5:K$39,$C$5:$C$39,"TR",$D$5:$D$39,$B46),"") -> 0.26270131 | L46: =IFERROR(SUMIFS(L$5:L$39,$C$5:$C$39,"TR",$D$5:$D$39,$A46)/SUMIFS(L$5:L$39,$C$5:$C$39,"TR",$D$5:$D$39,$B46),"") -> 0.014288821 | ... AY46: =IFERROR(SUMIFS(AY$5:AY$39,$C$5:$C$39,"TR",$D$5:$D$39,$A46)/SUMIFS(AY$5:AY$39,$C$5:$C$39,"TR",$D$5:$D$39,$B46),"")
A47: TRABDS | B47: TRADST | D47: BDS/DST | E47: =IFERROR(SUMIFS(E$5:E$39,$C$5:$C$39,"TR",$D$5:$D$39,$A47)/SUMIFS(E$5:E$39,$C$5:$C$39,"TR",$D$5:$D$39,$B47),"") -> 0 | F47: =IFERROR(SUMIFS(F$5:F$39,$C$5:$C$39,"TR",$D$5:$D$39,$A47)/SUMIFS(F$5:F$39,$C$5:$C$39,"TR",$D$5:$D$39,$B47),"") -> 0 | G47: =IFERROR(SUMIFS(G$5:G$39,$C$5:$C$39,"TR",$D$5:$D$39,$A47)/SUMIFS(G$5:G$39,$C$5:$C$39,"TR",$D$5:$D$39,$B47),"") -> 6.3932502e-05 | H47: =IFERROR(SUMIFS(H$5:H$39,$C$5:$C$39,"TR",$D$5:$D$39,$A47)/SUMIFS(H$5:H$39,$C$5:$C$39,"TR",$D$5:$D$39,$B47),"") -> 0.068913369 | I47: =IFERROR(SUMIFS(I$5:I$39,$C$5:$C$39,"TR",$D$5:$D$39,$A47)/SUMIFS(I$5:I$39,$C$5:$C$39,"TR",$D$5:$D$39,$B47),"") -> 0.037794493 | J47: =IFERROR(SUMIFS(J$5:J$39,$C$5:$C$39,"TR",$D$5:$D$39,$A47)/SUMIFS(J$5:J$39,$C$5:$C$39,"TR",$D$5:$D$39,$B47),"") -> 0.067361803 | K47: =IFERROR(SUMIFS(K$5:K$39,$C$5:$C$39,"TR",$D$5:$D$39,$A47)/SUMIFS(K$5:K$39,$C$5:$C$39,"TR",$D$5:$D$39,$B47),"") -> 0.4533661 | L47: =IFERROR(SUMIFS(L$5:L$39,$C$5:$C$39,"TR",$D$5:$D$39,$A47)/SUMIFS(L$5:L$39,$C$5:$C$39,"TR",$D$5:$D$39,$B47),"") -> 0.0097656201 | ... AY47: =IFERROR(SUMIFS(AY$5:AY$39,$C$5:$C$39,"TR",$D$5:$D$39,$A47)/SUMIFS(AY$5:AY$39,$C$5:$C$39,"TR",$D$5:$D$39,$B47),"")
D52: Bvkm | E52: =Cars!D44 -> Africa_North | F52: =Cars!E44 -> Africa_Other | G52: =Cars!F44 -> Australia | H52: =Cars!G44 -> Austria | I52: =Cars!H44 -> Baltics | J52: =Cars!I44 -> BeNeLux | K52: =Cars!J44 -> Brazil | L52: =Cars!K44 -> China | ... AX52: =Cars!AW44 -> \I:
C53: Bvkm/POP | D53: Cars | E53: =IFERROR(Cars!D45/E59,"") -> 0 | F53: =IFERROR(Cars!E45/F59,"") -> 0 | G53: =IFERROR(Cars!F45/G59,"") -> 0 | H53: =IFERROR(Cars!G45/H59,"") -> 0 | I53: =IFERROR(Cars!H45/I59,"") -> 0 | J53: =IFERROR(Cars!I45/J59,"") -> 0 | K53: =IFERROR(Cars!J45/K59,"") -> 0 | L53: =IFERROR(Cars!K45/L59,"") -> 0 | ... AX53: =IFERROR(Cars!AW45/AX59,"")
C54: Bvkm/GDP | D54: H Trucks | E54: =IFERROR('Trucks-hdt'!D45/E58,"") -> 0 | F54: =IFERROR('Trucks-hdt'!E45/F58,"") -> 0 | G54: =IFERROR('Trucks-hdt'!F45/G58,"") -> 0 | H54: =IFERROR('Trucks-hdt'!G45/H58,"") -> 0 | I54: =IFERROR('Trucks-hdt'!H45/I58,"") -> 0 | J54: =IFERROR('Trucks-hdt'!I45/J58,"") -> 0 | K54: =IFERROR('Trucks-hdt'!J45/K58,"") -> 0 | L54: =IFERROR('Trucks-hdt'!K45/L58,"") -> 0 | ... AX54: =IFERROR('Trucks-hdt'!AW45/AX58,"")
C57: Year | D57: Drvr | E57: Africa_North | F57: Africa_Other | G57: Australia_d | H57: Austria_d | I57: Baltics | J57: BeNeLux | K57: Brazil_d | L57: China_d | M57: CroSloven | N57: CzechSlovak | O57: France_d | P57: Germany_d | Q57: GreeceCyp | R57: HunRomBul | S57: Iceland_d | T57: India_d | U57: Ireland_d | V57: ItalyMal | W57: Japan_d | X57: LatAm | Y57: MidEast | Z57: NorthAm | AA57: Norway_d | AB57: Poland_d | AC57: ROW | AD57: Russia_d | AE57: SaudiArabia_d | AF57: SouthAfrica_d | AG57: SpainPor | AH57: SweFinDen | AI57: Switzerland_d | AJ57: Turkey_d | AK57: UK_d | AL57: Ukraine_d | AM57: WestBalkans | AN57: PRT | AO57: ROM | AP57: ROW | AQ57: Russia | AR57: SRB | AS57: SVK | AT57: SVN | AU57: SWE | AV57: TUR | AW57: UKR | AX57: XXK
C58: 2019 | D58: GDP | E58: 2018.274 | F58: 2792.8094 | G58: 964.981 | H58: 350.867 | I58: 142.6773 | J58: 1215.2069 | K58: 2724.93 | L58: 21308.9 | M58: 137.786 | N58: 458.463 | O58: 2250.3 | P58: 3218.77 | Q58: 269.2231 | R58: 667.972 | S58: 15.8709 | T58: 8348.05 | U58: 302.74 | V58: 1746.1618 | W58: 4399.22 | X58: 3684.5449 | Y58: 3897.7243 | Z58: 20059.15 | AA58: 265.438 | AB58: 919.784 | AC58: 13965.3 | AD58: 2457.317 | AE58: 1712.87 | AF58: 625.812 | AG58: 1655.67 | AH58: 819.16 | AI58: 410.763 | AJ58: 1542.4 | AK58: 2363.72 | AL58: 385.6139 | AM58: 189.0739 | AN58: 261.55 | AO58: 330.101 | AP58: 48028.07 | AQ58: 2457.317 | AR58: 94.7031 | AS58: 143.645 | AT58: 62.0465 | AU58: 405.629 | AV58: 1542.4 | AW58: 385.6139 | AX58: NULL
C59: 2019 | D59: POP | E59: 198.38505 | F59: 1039.1569 | G59: 25.3657 | H59: 8.87992 | I59: 6.03486 | J59: 29.453901 | K59: 211.05 | L59: 1397.72 | M59: 6.15364 | N59: 16.12605 | O59: 67.2489 | P59: 83.093 | Q59: 11.92017 | R59: 36.1185 | S59: 0.360563 | T59: 1366.42 | U59: 4.93434 | V59: 60.233162 | W59: 126.265 | X59: 308.82149 | Y59: 222.57825 | Z59: 493.4994 | AA59: 5.3479 | AB59: 37.9655 | AC59: 1349.4624 | AD59: 153.82385 | AE59: 34.2685 | AF59: 58.5583 | AG59: 57.4198 | AH59: 21.61493 | AI59: 8.57528 | AJ59: 83.4296 | AK59: 66.8363 | AL59: 47.04945 | AM59: 15.805908 | AN59: 10.2863 | AO59: 19.3716 | AP59: 4241.809 | AQ59: 153.82385 | AR59: 6.94523 | AS59: 5.45415 | AT59: 2.08839 | AU59: 10.2789 | AV59: 83.4296 | AW59: 47.04945 | AX59: NULL

Sheet 2-w
AY2: ~FI_T | BD2: ~FI_Process
C3: comm-in | D3: ='TRA balance'!E4 -> Africa_North | E3: ='TRA balance'!F4 -> Africa_Other | F3: ='TRA balance'!G4 -> Australia | G3: ='TRA balance'!H4 -> Austria | H3: ='TRA balance'!I4 -> Baltics | I3: ='TRA balance'!J4 -> BeNeLux | J3: ='TRA balance'!K4 -> Brazil | K3: ='TRA balance'!L4 -> China | ... AW3: ='TRA balance'!AX4 -> \I: | AX3: * | AY3: attribute | AZ3: process | BA3: comm-out | BB3: LIFE | BD3: Sets | BE3: TechName | BF3: TechDesc | BG3: Tact | BH3: Tcap | BI3: Vintage
A4: TR | C4: TRABDS | D4: {=SUM(SUMIFS(Assumptions!BD$3:BD$102,Assumptions!$B$3:$B$102,'2-w'!$C4,Assumptions!$G$3:$G$102,{"TRW"}))} -> 0 | E4: {=SUM(SUMIFS(Assumptions!BE$3:BE$102,Assumptions!$B$3:$B$102,'2-w'!$C4,Assumptions!$G$3:$G$102,{"TRW"}))} -> 0 | F4: {=SUM(SUMIFS(Assumptions!BF$3:BF$102,Assumptions!$B$3:$B$102,'2-w'!$C4,Assumptions!$G$3:$G$102,{"TRW"}))} -> 0 | G4: {=SUM(SUMIFS(Assumptions!BG$3:BG$102,Assumptions!$B$3:$B$102,'2-w'!$C4,Assumptions!$G$3:$G$102,{"TRW"}))} -> 0 | H4: {=SUM(SUMIFS(Assumptions!BH$3:BH$102,Assumptions!$B$3:$B$102,'2-w'!$C4,Assumptions!$G$3:$G$102,{"TRW"}))} -> 0 | I4: {=SUM(SUMIFS(Assumptions!BI$3:BI$102,Assumptions!$B$3:$B$102,'2-w'!$C4,Assumptions!$G$3:$G$102,{"TRW"}))} -> 0 | J4: {=SUM(SUMIFS(Assumptions!BJ$3:BJ$102,Assumptions!$B$3:$B$102,'2-w'!$C4,Assumptions!$G$3:$G$102,{"TRW"}))} -> 0 | K4: {=SUM(SUMIFS(Assumptions!BK$3:BK$102,Assumptions!$B$3:$B$102,'2-w'!$C4,Assumptions!$G$3:$G$102,{"TRW"}))} -> 0 | ... AW4: {=SUM(SUMIFS(Assumptions!CW$3:CW$102,Assumptions!$B$3:$B$102,'2-w'!$C4,Assumptions!$G$3:$G$102,{"TRW"}))} -> 0 | AX4: =IF(SUM(D4:AW4)=0,"zero","") -> zero | AY4: * | BA4: =IF($AZ4="","",$BA$45) | BB4: =IF($AZ4="","",25) | BD4: =IF($AZ4="","*","DMD") -> * | BE4: =AZ4 -> 0 | BG4: Bvkm | BH4: million Vehicles | BI4: yes
A5: TR | C5: TRABGS | D5: {=SUM(SUMIFS(Assumptions!BD$3:BD$102,Assumptions!$B$3:$B$102,'2-w'!$C5,Assumptions!$G$3:$G$102,{"TRW"}))} -> 0 | E5: {=SUM(SUMIFS(Assumptions!BE$3:BE$102,Assumptions!$B$3:$B$102,'2-w'!$C5,Assumptions!$G$3:$G$102,{"TRW"}))} -> 0 | F5: {=SUM(SUMIFS(Assumptions!BF$3:BF$102,Assumptions!$B$3:$B$102,'2-w'!$C5,Assumptions!$G$3:$G$102,{"TRW"}))} -> 0 | G5: {=SUM(SUMIFS(Assumptions!BG$3:BG$102,Assumptions!$B$3:$B$102,'2-w'!$C5,Assumptions!$G$3:$G$102,{"TRW"}))} -> 0 | H5: {=SUM(SUMIFS(Assumptions!BH$3:BH$102,Assumptions!$B$3:$B$102,'2-w'!$C5,Assumptions!$G$3:$G$102,{"TRW"}))} -> 0 | I5: {=SUM(SUMIFS(Assumptions!BI$3:BI$102,Assumptions!$B$3:$B$102,'2-w'!$C5,Assumptions!$G$3:$G$102,{"TRW"}))} -> 0 | J5: {=SUM(SUMIFS(Assumptions!BJ$3:BJ$102,Assumptions!$B$3:$B$102,'2-w'!$C5,Assumptions!$G$3:$G$102,{"TRW"}))} -> 0 | K5: {=SUM(SUMIFS(Assumptions!BK$3:BK$102,Assumptions!$B$3:$B$102,'2-w'!$C5,Assumptions!$G$3:$G$102,{"TRW"}))} -> 0 | ... AW5: {=SUM(SUMIFS(Assumptions!CW$3:CW$102,Assumptions!$B$3:$B$102,'2-w'!$C5,Assumptions!$G$3:$G$102,{"TRW"}))} -> 0 | AX5: =IF(SUM(D5:AW5)=0,"zero","") -> zero | AY5: * | BA5: =IF($AZ5="","",$BA$45) | BB5: =IF($AZ5="","",25) | BD5: =IF(AZ5="","*","DMD") -> * | BE5: =AZ5 -> 0 | BG5: Bvkm | BH5: million Vehicles | BI5: yes
A6: TR | C6: TRADST | D6: {=SUM(SUMIFS(Assumptions!BD$3:BD$102,Assumptions!$B$3:$B$102,'2-w'!$C6,Assumptions!$G$3:$G$102,{"TRW"}))} -> 0 | E6: {=SUM(SUMIFS(Assumptions!BE$3:BE$102,Assumptions!$B$3:$B$102,'2-w'!$C6,Assumptions!$G$3:$G$102,{"TRW"}))} -> 0 | F6: {=SUM(SUMIFS(Assumptions!BF$3:BF$102,Assumptions!$B$3:$B$102,'2-w'!$C6,Assumptions!$G$3:$G$102,{"TRW"}))} -> 0 | G6: {=SUM(SUMIFS(Assumptions!BG$3:BG$102,Assumptions!$B$3:$B$102,'2-w'!$C6,Assumptions!$G$3:$G$102,{"TRW"}))} -> 0 | H6: {=SUM(SUMIFS(Assumptions!BH$3:BH$102,Assumptions!$B$3:$B$102,'2-w'!$C6,Assumptions!$G$3:$G$102,{"TRW"}))} -> 0 | I6: {=SUM(SUMIFS(Assumptions!BI$3:BI$102,Assumptions!$B$3:$B$102,'2-w'!$C6,Assumptions!$G$3:$G$102,{"TRW"}))} -> 0 | J6: {=SUM(SUMIFS(Assumptions!BJ$3:BJ$102,Assumptions!$B$3:$B$102,'2-w'!$C6,Assumptions!$G$3:$G$102,{"TRW"}))} -> 0 | K6: {=SUM(SUMIFS(Assumptions!BK$3:BK$102,Assumptions!$B$3:$B$102,'2-w'!$C6,Assumptions!$G$3:$G$102,{"TRW"}))} -> 0 | ... AW6: {=SUM(SUMIFS(Assumptions!CW$3:CW$102,Assumptions!$B$3:$B$102,'2-w'!$C6,Assumptions!$G$3:$G$102,{"TRW"}))} -> 0 | AX6: =IF(SUM(D6:AW6)=0,"zero","") -> zero | AY6: * | BA6: =IF($AZ6="","",$BA$45) | BB6: =IF($AZ6="","",25) | BD6: =IF(AZ6="","*","DMD") -> * | BE6: =AZ6 -> 0 | BG6: Bvkm | BH6: million Vehicles | BI6: yes
A7: TR | C7: TRAELC | D7: {=SUM(SUMIFS(Assumptions!BD$3:BD$102,Assumptions!$B$3:$B$102,'2-w'!$C7,Assumptions!$G$3:$G$102,{"TRW"}))} -> 0 | E7: {=SUM(SUMIFS(Assumptions!BE$3:BE$102,Assumptions!$B$3:$B$102,'2-w'!$C7,Assumptions!$G$3:$G$102,{"TRW"}))} -> 0 | F7: {=SUM(SUMIFS(Assumptions!BF$3:BF$102,Assumptions!$B$3:$B$102,'2-w'!$C7,Assumptions!$G$3:$G$102,{"TRW"}))} -> 0.064799104 | G7: {=SUM(SUMIFS(Assumptions!BG$3:BG$102,Assumptions!$B$3:$B$102,'2-w'!$C7,Assumptions!$G$3:$G$102,{"TRW"}))} -> 0.038516467 | H7: {=SUM(SUMIFS(Assumptions!BH$3:BH$102,Assumptions!$B$3:$B$102,'2-w'!$C7,Assumptions!$G$3:$G$102,{"TRW"}))} -> 0 | I7: {=SUM(SUMIFS(Assumptions!BI$3:BI$102,Assumptions!$B$3:$B$102,'2-w'!$C7,Assumptions!$G$3:$G$102,{"TRW"}))} -> 1.73927 | J7: {=SUM(SUMIFS(Assumptions!BJ$3:BJ$102,Assumptions!$B$3:$B$102,'2-w'!$C7,Assumptions!$G$3:$G$102,{"TRW"}))} -> 0 | K7: {=SUM(SUMIFS(Assumptions!BK$3:BK$102,Assumptions!$B$3:$B$102,'2-w'!$C7,Assumptions!$G$3:$G$102,{"TRW"}))} -> 147.21781 | ... AW7: {=SUM(SUMIFS(Assumptions!CW$3:CW$102,Assumptions!$B$3:$B$102,'2-w'!$C7,Assumptions!$G$3:$G$102,{"TRW"}))} -> 0 | AX7: =IF(SUM(D7:AW7)=0,"zero","") | AY7: * | BA7: =IF($AZ7="","",$BA$45) | BB7: =IF($AZ7="","",25) | BD7: =IF(AZ7="","*","DMD") -> * | BE7: =AZ7 -> 0 | BG7: Bvkm | BH7: million Vehicles | BI7: yes
A8: TR | C8: TRAGSL | D8: {=SUM(SUMIFS(Assumptions!BD$3:BD$102,Assumptions!$B$3:$B$102,'2-w'!$C8,Assumptions!$G$3:$G$102,{"TRW"}))} -> 250.4846 | E8: {=SUM(SUMIFS(Assumptions!BE$3:BE$102,Assumptions!$B$3:$B$102,'2-w'!$C8,Assumptions!$G$3:$G$102,{"TRW"}))} -> 434.96326 | F8: {=SUM(SUMIFS(Assumptions!BF$3:BF$102,Assumptions!$B$3:$B$102,'2-w'!$C8,Assumptions!$G$3:$G$102,{"TRW"}))} -> 10.240593 | G8: {=SUM(SUMIFS(Assumptions!BG$3:BG$102,Assumptions!$B$3:$B$102,'2-w'!$C8,Assumptions!$G$3:$G$102,{"TRW"}))} -> 0.33583423 | H8: {=SUM(SUMIFS(Assumptions!BH$3:BH$102,Assumptions!$B$3:$B$102,'2-w'!$C8,Assumptions!$G$3:$G$102,{"TRW"}))} -> 0.30361717 | I8: {=SUM(SUMIFS(Assumptions!BI$3:BI$102,Assumptions!$B$3:$B$102,'2-w'!$C8,Assumptions!$G$3:$G$102,{"TRW"}))} -> 1.2993734 | J8: {=SUM(SUMIFS(Assumptions!BJ$3:BJ$102,Assumptions!$B$3:$B$102,'2-w'!$C8,Assumptions!$G$3:$G$102,{"TRW"}))} -> 12.125455 | K8: {=SUM(SUMIFS(Assumptions!BK$3:BK$102,Assumptions!$B$3:$B$102,'2-w'!$C8,Assumptions!$G$3:$G$102,{"TRW"}))} -> 540.17053 | ... AW8: {=SUM(SUMIFS(Assumptions!CW$3:CW$102,Assumptions!$B$3:$B$102,'2-w'!$C8,Assumptions!$G$3:$G$102,{"TRW"}))} -> 0 | AX8: =IF(SUM(D8:AW8)=0,"zero","") | AY8: * | BA8: =IF($AZ8="","",$BA$45) | BB8: =IF($AZ8="","",25) | BD8: =IF(AZ8="","*","DMD") -> * | BE8: =AZ8 -> 0 | BG8: Bvkm | BH8: million Vehicles | BI8: yes
A9: TR | C9: TRALPG | D9: {=SUM(SUMIFS(Assumptions!BD$3:BD$102,Assumptions!$B$3:$B$102,'2-w'!$C9,Assumptions!$G$3:$G$102,{"TRW"}))} -> 0 | E9: {=SUM(SUMIFS(Assumptions!BE$3:BE$102,Assumptions!$B$3:$B$102,'2-w'!$C9,Assumptions!$G$3:$G$102,{"TRW"}))} -> 0 | F9: {=SUM(SUMIFS(Assumptions!BF$3:BF$102,Assumptions!$B$3:$B$102,'2-w'!$C9,Assumptions!$G$3:$G$102,{"TRW"}))} -> 0 | G9: {=SUM(SUMIFS(Assumptions!BG$3:BG$102,Assumptions!$B$3:$B$102,'2-w'!$C9,Assumptions!$G$3:$G$102,{"TRW"}))} -> 0 | H9: {=SUM(SUMIFS(Assumptions!BH$3:BH$102,Assumptions!$B$3:$B$102,'2-w'!$C9,Assumptions!$G$3:$G$102,{"TRW"}))} -> 0 | I9: {=SUM(SUMIFS(Assumptions!BI$3:BI$102,Assumptions!$B$3:$B$102,'2-w'!$C9,Assumptions!$G$3:$G$102,{"TRW"}))} -> 0 | J9: {=SUM(SUMIFS(Assumptions!BJ$3:BJ$102,Assumptions!$B$3:$B$102,'2-w'!$C9,Assumptions!$G$3:$G$102,{"TRW"}))} -> 0 | K9: {=SUM(SUMIFS(Assumptions!BK$3:BK$102,Assumptions!$B$3:$B$102,'2-w'!$C9,Assumptions!$G$3:$G$102,{"TRW"}))} -> 0 | ... AW9: {=SUM(SUMIFS(Assumptions!CW$3:CW$102,Assumptions!$B$3:$B$102,'2-w'!$C9,Assumptions!$G$3:$G$102,{"TRW"}))} -> 0 | AX9: =IF(SUM(D9:AW9)=0,"zero","") -> zero | AY9: * | BA9: =IF($AZ9="","",$BA$45) | BB9: =IF($AZ9="","",25) | BD9: =IF(AZ9="","*","DMD") -> * | BE9: =AZ9 -> 0 | BG9: Bvkm | BH9: million Vehicles | BI9: yes
A10: TR | C10: TRANGA | D10: {=SUM(SUMIFS(Assumptions!BD$3:BD$102,Assumptions!$B$3:$B$102,'2-w'!$C10,Assumptions!$G$3:$G$102,{"TRW"}))} -> 0 | E10: {=SUM(SUMIFS(Assumptions!BE$3:BE$102,Assumptions!$B$3:$B$102,'2-w'!$C10,Assumptions!$G$3:$G$102,{"TRW"}))} -> 0 | F10: {=SUM(SUMIFS(Assumptions!BF$3:BF$102,Assumptions!$B$3:$B$102,'2-w'!$C10,Assumptions!$G$3:$G$102,{"TRW"}))} -> 0 | G10: {=SUM(SUMIFS(Assumptions!BG$3:BG$102,Assumptions!$B$3:$B$102,'2-w'!$C10,Assumptions!$G$3:$G$102,{"TRW"}))} -> 0 | H10: {=SUM(SUMIFS(Assumptions!BH$3:BH$102,Assumptions!$B$3:$B$102,'2-w'!$C10,Assumptions!$G$3:$G$102,{"TRW"}))} -> 0 | I10: {=SUM(SUMIFS(Assumptions!BI$3:BI$102,Assumptions!$B$3:$B$102,'2-w'!$C10,Assumptions!$G$3:$G$102,{"TRW"}))} -> 0 | J10: {=SUM(SUMIFS(Assumptions!BJ$3:BJ$102,Assumptions!$B$3:$B$102,'2-w'!$C10,Assumptions!$G$3:$G$102,{"TRW"}))} -> 0 | K10: {=SUM(SUMIFS(Assumptions!BK$3:BK$102,Assumptions!$B$3:$B$102,'2-w'!$C10,Assumptions!$G$3:$G$102,{"TRW"}))} -> 0 | ... AW10: {=SUM(SUMIFS(Assumptions!CW$3:CW$102,Assumptions!$B$3:$B$102,'2-w'!$C10,Assumptions!$G$3:$G$102,{"TRW"}))} -> 0 | AX10: =IF(SUM(D10:AW10)=0,"zero","") -> zero | AY10: * | BA10: =IF($AZ10="","",$BA$45) | BB10: =IF($AZ10="","",25) | BD10: =IF(AZ10="","*","DMD") -> * | BE10: =AZ10 -> 0 | BG10: Bvkm | BH10: million Vehicles | BI10: yes
A11: Share of PJ | D11: =SUM(D$4:D$10)/SUM($D$4:$AJ$10) -> 0.065977858 | E11: =SUM(E$4:E$10)/SUM($D$4:$AJ$10) -> 0.11456969 | F11: =SUM(F$4:F$10)/SUM($D$4:$AJ$10) -> 0.0027144491 | G11: =SUM(G$4:G$10)/SUM($D$4:$AJ$10) -> 9.8604292e-05 | H11: =SUM(H$4:H$10)/SUM($D$4:$AJ$10) -> 7.9973021e-05 | I11: =SUM(I$4:I$10)/SUM($D$4:$AJ$10) -> 0.00080038126 | J11: =SUM(J$4:J$10)/SUM($D$4:$AJ$10) -> 0.0031938552 | K11: =SUM(K$4:K$10)/SUM($D$4:$AJ$10) -> 0.18105867 | ... AW11: =SUM(AW$4:AW$10)/SUM($D$4:$AJ$10) -> 0 | AY11: * | BA11: =IF($AZ11="","",$BA$45) | BB11: =IF($AZ11="","",25) | BD11: =IF(AZ11="","*","DMD") -> * | BE11: =AZ11 -> 0 | BG11: Bvkm | BH11: million Vehicles | BI11: yes
AY12: * | BA12: =IF($AZ12="","",$BA$45) | BB12: =IF($AZ12="","",12) | BD12: =IF(AZ12="","*","DMD") -> * | BE12: =AZ12 -> 0 | BG12: Bvkm | BH12: million Vehicles | BI12: yes
A13: m Vehicles | C13: =SUM(D13:AJ13) -> 596.338 | D13: =SUM(D19:D25) -> 35.426 | E13: =SUM(E19:E25) -> 61.516 | F13: =SUM(F19:F25) -> 1.476 | G13: =SUM(G19:G25) -> 0.064 | H13: =SUM(H19:H25) -> 0.043 | I13: =SUM(I19:I25) -> 0.929 | J13: =SUM(J19:J25) -> 1.715 | K13: =SUM(K19:K25) -> 139.489 | ... AW13: =SUM(AW19:AW25) -> 0 | AY13: * | BA13: =IF($AZ13="","",$BA$45) | BB13: =IF($AZ13="","",12) | BD13: =IF(AZ13="","*","DMD") -> * | BE13: =AZ13 -> 0 | BG13: Bvkm | BH13: million Vehicles | BI13: yes
A14: Share of Veh | D14: =D13/SUM($D$13:$AJ$13) -> 0.059405907 | E14: =E13/SUM($D$13:$AJ$13) -> 0.10315626 | F14: =F13/SUM($D$13:$AJ$13) -> 0.0024751064 | G14: =G13/SUM($D$13:$AJ$13) -> 0.00010732169 | H14: =H13/SUM($D$13:$AJ$13) -> 7.2106758e-05 | I14: =I13/SUM($D$13:$AJ$13) -> 0.0015578414 | J14: =J13/SUM($D$13:$AJ$13) -> 0.0028758858 | K14: =K13/SUM($D$13:$AJ$13) -> 0.23390929 | ... AW14: =AW13/SUM($D$13:$AJ$13) -> 0 | AY14: * | BA14: =IF($AZ14="","",$BA$45) | BB14: =IF($AZ14="","",12) | BD14: =IF(AZ14="","*","DMD") -> * | BE14: =AZ14 -> 0 | BG14: Bvkm | BH14: million Vehicles | BI14: yes
AY15: * | BA15: =IF($AZ15="","",$BA$45) | BB15: =IF($AZ15="","",12) | BD15: =IF(AZ15="","*","DMD") -> * | BE15: =AZ15 -> 0 | BG15: Bvkm | BH15: million Vehicles | BI15: yes
AY16: * | BA16: =IF($AZ16="","",$BA$45) | BB16: =IF($AZ16="","",12) | BD16: =IF(AZ16="","*","DMD") -> * | BE16: =AZ16 -> 0 | BG16: Bvkm | BH16: million Vehicles | BI16: yes
A17: PJ share/Veh share | D17: =IFERROR(D11/D14,"") -> 1.1106279 | E17: =IFERROR(E11/E14,"") -> 1.1106422 | F17: =IFERROR(F11/F14,"") -> 1.0967 | G17: =IFERROR(G11/G14,"") -> 0.91877323 | H17: =IFERROR(H11/H14,"") -> 1.1090919 | I17: =IFERROR(I11/I14,"") -> 0.51377584 | J17: =IFERROR(J11/J14,"") -> 1.110564 | K17: =IFERROR(K11/K14,"") -> 0.77405507 | ... AW17: =IFERROR(AW11/AW14,"") | AY17: * | BA17: =IF($AZ17="","",$BA$45) | BB17: =IF($AZ17="","",12) | BD17: =IF(AZ17="","*","DMD") -> * | BE17: =AZ17 -> 0 | BG17: Bvkm | BH17: million Vehicles | BI17: yes
AY18: * | BA18: =IF($AZ18="","",$BA$45) | BB18: =IF($AZ18="","",12) | BD18: =IF(AZ18="","*","DMD") -> * | BE18: =AZ18 -> 0 | BG18: Bvkm | BH18: million Vehicles | BI18: yes
A19: mVeh | C19: =C4 -> TRABDS | D19: =ROUND(D4*D28/D36,3) -> 0 | E19: =ROUND(E4*E28/E36,3) -> 0 | F19: =ROUND(F4*F28/F36,3) -> 0 | G19: =ROUND(G4*G28/G36,3) -> 0 | H19: =ROUND(H4*H28/H36,3) -> 0 | I19: =ROUND(I4*I28/I36,3) -> 0 | J19: =ROUND(J4*J28/J36,3) -> 0 | K19: =ROUND(K4*K28/K36,3) -> 0 | ... AW19: =ROUND(AW4*AW28/AW36,3) -> 0 | AY19: PASTI | AZ19: =IF(AX4="zero","\I:",$BA$45&"_"&VLOOKUP(C19,'TRA balance'!$BB$5:$BC$15,2,FALSE)) -> \I: | BA19: =IF($AZ19="","",$BA$45) -> Trd_2w | BB19: =IF($AZ19="","",25) -> 25 | BD19: =IF(AZ19="","*","DMD") -> DMD | BE19: =AZ19 -> \I: | BG19: Bvkm | BH19: million Vehicles | BI19: yes
C20: =C5 -> TRABGS | D20: =ROUND(D5*D29/D37,3) -> 0 | E20: =ROUND(E5*E29/E37,3) -> 0 | F20: =ROUND(F5*F29/F37,3) -> 0 | G20: =ROUND(G5*G29/G37,3) -> 0 | H20: =ROUND(H5*H29/H37,3) -> 0 | I20: =ROUND(I5*I29/I37,3) -> 0 | J20: =ROUND(J5*J29/J37,3) -> 0 | K20: =ROUND(K5*K29/K37,3) -> 0 | ... AW20: =ROUND(AW5*AW29/AW37,3) -> 0 | AY20: PASTI | AZ20: =IF(AX5="zero","\I:",$BA$45&"_"&VLOOKUP(C20,'TRA balance'!$BB$5:$BC$15,2,FALSE)) -> \I: | BA20: =IF($AZ20="","",$BA$45) -> Trd_2w | BB20: =IF($AZ20="","",25) -> 25 | BD20: =IF(AZ20="","*","DMD") -> DMD | BE20: =AZ20 -> \I: | BG20: Bvkm | BH20: million Vehicles | BI20: yes
C21: =C6 -> TRADST | D21: =ROUND(D6*D30/D38,3) -> 0 | E21: =ROUND(E6*E30/E38,3) -> 0 | F21: =ROUND(F6*F30/F38,3) -> 0 | G21: =ROUND(G6*G30/G38,3) -> 0 | H21: =ROUND(H6*H30/H38,3) -> 0 | I21: =ROUND(I6*I30/I38,3) -> 0 | J21: =ROUND(J6*J30/J38,3) -> 0 | K21: =ROUND(K6*K30/K38,3) -> 0 | ... AW21: =ROUND(AW6*AW30/AW38,3) -> 0 | AY21: PASTI | AZ21: =IF(AX6="zero","\I:",$BA$45&"_"&VLOOKUP(C21,'TRA balance'!$BB$5:$BC$15,2,FALSE)) -> \I: | BA21: =IF($AZ21="","",$BA$45) -> Trd_2w | BB21: =IF($AZ21="","",25) -> 25 | BD21: =IF(AZ21="","*","DMD") -> DMD | BE21: =AZ21 -> \I: | BG21: Bvkm | BH21: million Vehicles | BI21: yes
C22: =C7 -> TRAELC | D22: =ROUND(D7*D31/D39,3) -> 0 | E22: =ROUND(E7*E31/E39,3) -> 0 | F22: =ROUND(F7*F31/F39,3) -> 0.028 | G22: =ROUND(G7*G31/G39,3) -> 0.017 | H22: =ROUND(H7*H31/H39,3) -> 0 | I22: =ROUND(I7*I31/I39,3) -> 0.745 | J22: =ROUND(J7*J31/J39,3) -> 0 | K22: =ROUND(K7*K31/K39,3) -> 63.093 | ... AW22: =ROUND(AW7*AW31/AW39,3) -> 0 | AY22: PASTI | AZ22: =IF(AX7="zero","\I:",$BA$45&"_"&VLOOKUP(C22,'TRA balance'!$BB$5:$BC$15,2,FALSE)) -> Trd_2w_elc | BA22: =IF($AZ22="","",$BA$45) -> Trd_2w | BB22: =IF($AZ22="","",25) -> 25 | BD22: =IF(AZ22="","*","DMD") -> DMD | BE22: =AZ22 -> Trd_2w_elc | BG22: Bvkm | BH22: million Vehicles | BI22: yes
C23: =C8 -> TRAGSL | D23: =ROUND(D8*D32/D40,3) -> 35.426 | E23: =ROUND(E8*E32/E40,3) -> 61.516 | F23: =ROUND(F8*F32/F40,3) -> 1.448 | G23: =ROUND(G8*G32/G40,3) -> 0.047 | H23: =ROUND(H8*H32/H40,3) -> 0.043 | I23: =ROUND(I8*I32/I40,3) -> 0.184 | J23: =ROUND(J8*J32/J40,3) -> 1.715 | K23: =ROUND(K8*K32/K40,3) -> 76.396 | ... AW23: =ROUND(AW8*AW32/AW40,3) -> 0 | AY23: PASTI | AZ23: =IF(AX8="zero","\I:",$BA$45&"_"&VLOOKUP(C23,'TRA balance'!$BB$5:$BC$15,2,FALSE)) -> Trd_2w_gsl | BA23: =IF($AZ23="","",$BA$45) -> Trd_2w | BB23: =IF($AZ23="","",25) -> 25 | BD23: =IF(AZ23="","*","DMD") -> DMD | BE23: =AZ23 -> Trd_2w_gsl | BG23: Bvkm | BH23: million Vehicles | BI23: yes
C24: =C9 -> TRALPG | D24: =ROUND(D9*D33/D41,3) -> 0 | E24: =ROUND(E9*E33/E41,3) -> 0 | F24: =ROUND(F9*F33/F41,3) -> 0 | G24: =ROUND(G9*G33/G41,3) -> 0 | H24: =ROUND(H9*H33/H41,3) -> 0 | I24: =ROUND(I9*I33/I41,3) -> 0 | J24: =ROUND(J9*J33/J41,3) -> 0 | K24: =ROUND(K9*K33/K41,3) -> 0 | ... AW24: =ROUND(AW9*AW33/AW41,3) -> 0 | AY24: PASTI | AZ24: =IF(AX9="zero","\I:",$BA$45&"_"&VLOOKUP(C24,'TRA balance'!$BB$5:$BC$15,2,FALSE)) -> \I: | BA24: =IF($AZ24="","",$BA$45) -> Trd_2w | BB24: =IF($AZ24="","",25) -> 25 | BD24: =IF(AZ24="","*","DMD") -> DMD | BE24: =AZ24 -> \I: | BG24: Bvkm | BH24: million Vehicles | BI24: yes
C25: =C10 -> TRANGA | D25: =ROUND(D10*D34/D42,3) -> 0 | E25: =ROUND(E10*E34/E42,3) -> 0 | F25: =ROUND(F10*F34/F42,3) -> 0 | G25: =ROUND(G10*G34/G42,3) -> 0 | H25: =ROUND(H10*H34/H42,3) -> 0 | I25: =ROUND(I10*I34/I42,3) -> 0 | J25: =ROUND(J10*J34/J42,3) -> 0 | K25: =ROUND(K10*K34/K42,3) -> 0 | ... AW25: =ROUND(AW10*AW34/AW42,3) -> 0 | AY25: PASTI | AZ25: =IF(AX10="zero","\I:",$BA$45&"_"&VLOOKUP(C25,'TRA balance'!$BB$5:$BC$15,2,FALSE)) -> \I: | BA25: =IF($AZ25="","",$BA$45) -> Trd_2w | BB25: =IF($AZ25="","",25) -> 25 | BD25: =IF(AZ25="","*","DMD") -> DMD | BE25: =AZ25 -> \I: | BG25: Bvkm | BH25: million Vehicles | BI25: yes
AY26: * | BA26: =IF($AZ26="","",$BA$45) | BB26: =IF($AZ26="","",25) | BD26: =IF(AZ26="","*","DMD") -> * | BE26: =AZ26 -> 0 | BG26: Bvkm | BH26: million Vehicles | BI26: yes
D27: 1 | E27: 1 | F27: 1 | G27: 1 | H27: 1 | I27: 1 | J27: 1 | K27: 1 | L27: 1 | M27: 1 | N27: 1 | O27: 1 | P27: 1 | Q27: 1 | R27: 1 | S27: 1 | T27: 1 | U27: 1 | V27: 1 | W27: 1 | X27: 1 | Y27: 1 | Z27: 1 | AA27: 1 | AB27: 1 | AC27: 1 | AD27: 1 | AE27: 1 | AF27: 1 | AG27: 1 | AH27: 1 | AI27: 1 | AJ27: 1 | AK27: 1 | AL27: 1 | AM27: 1 | AN27: 1 | AO27: 1 | AP27: 1 | AQ27: 1 | AR27: 1 | AS27: 1 | AT27: 1 | AU27: 1 | AV27: 1 | AW27: 1 | AY27: * | BA27: =IF($AZ27="","",$BA$45) | BB27: =IF($AZ27="","",25) | BD27: =IF(AZ27="","*","DMD") -> * | BE27: =AZ27 -> 0 | BG27: Bvkm | BH27: million Vehicles | BI27: yes
A28: Efficiency | C28: =C19 -> TRABDS | D28: =$AX28*D$27 -> 0.99 | E28: =$AX28*E$27 -> 0.99 | F28: =$AX28*F$27 -> 0.99 | G28: =$AX28*G$27 -> 0.99 | H28: =$AX28*H$27 -> 0.99 | I28: =$AX28*I$27 -> 0.99 | J28: =$AX28*J$27 -> 0.99 | K28: =$AX28*K$27 -> 0.99 | ... AW28: =$AX28*AW$27 -> 0.99 | AX28: 0.99 | AY28: EFF | AZ28: =AZ19 -> \I: | BA28: =IF($AZ28="","",$BA$45) -> Trd_2w | BB28: =IF($AZ28="","",25) -> 25 | BD28: =IF(AZ28="","*","DMD") -> DMD | BE28: =AZ28 -> \I: | BG28: Bvkm | BH28: million Vehicles | BI28: yes
C29: =C20 -> TRABGS | D29: =$AX29*D$27 -> 0.99 | E29: =$AX29*E$27 -> 0.99 | F29: =$AX29*F$27 -> 0.99 | G29: =$AX29*G$27 -> 0.99 | H29: =$AX29*H$27 -> 0.99 | I29: =$AX29*I$27 -> 0.99 | J29: =$AX29*J$27 -> 0.99 | K29: =$AX29*K$27 -> 0.99 | ... AW29: =$AX29*AW$27 -> 0.99 | AX29: 0.99 | AY29: EFF | AZ29: =AZ20 -> \I: | BA29: =IF($AZ29="","",$BA$45) -> Trd_2w | BB29: =IF($AZ29="","",25) -> 25 | BD29: =IF(AZ29="","*","DMD") -> DMD | BE29: =AZ29 -> \I: | BG29: Bvkm | BH29: million Vehicles | BI29: yes
C30: =C21 -> TRADST | D30: =$AX30*D$27 -> 0.99 | E30: =$AX30*E$27 -> 0.99 | F30: =$AX30*F$27 -> 0.99 | G30: =$AX30*G$27 -> 0.99 | H30: =$AX30*H$27 -> 0.99 | I30: =$AX30*I$27 -> 0.99 | J30: =$AX30*J$27 -> 0.99 | K30: =$AX30*K$27 -> 0.99 | ... AW30: =$AX30*AW$27 -> 0.99 | AX30: 0.99 | AY30: EFF | AZ30: =AZ21 -> \I: | BA30: =IF($AZ30="","",$BA$45) -> Trd_2w | BB30: =IF($AZ30="","",25) -> 25 | BD30: =IF(AZ30="","*","DMD") -> DMD | BE30: =AZ30 -> \I: | BG30: Bvkm | BH30: million Vehicles | BI30: yes
C31: =C22 -> TRAELC | D31: =$AX31*D$27 -> 3 | E31: =$AX31*E$27 -> 3 | F31: =$AX31*F$27 -> 3 | G31: =$AX31*G$27 -> 3 | H31: =$AX31*H$27 -> 3 | I31: =$AX31*I$27 -> 3 | J31: =$AX31*J$27 -> 3 | K31: =$AX31*K$27 -> 3 | ... AW31: =$AX31*AW$27 -> 3 | AX31: 3 | AY31: EFF | AZ31: =AZ22 -> Trd_2w_elc | BA31: =IF($AZ31="","",$BA$45) -> Trd_2w | BB31: =IF($AZ31="","",25) -> 25 | BD31: =IF(AZ31="","*","DMD") -> DMD | BE31: =AZ31 -> Trd_2w_elc | BG31: Bvkm | BH31: million Vehicles | BI31: yes
C32: =C23 -> TRAGSL | D32: =$AX32*D$27 -> 0.99 | E32: =$AX32*E$27 -> 0.99 | F32: =$AX32*F$27 -> 0.99 | G32: =$AX32*G$27 -> 0.99 | H32: =$AX32*H$27 -> 0.99 | I32: =$AX32*I$27 -> 0.99 | J32: =$AX32*J$27 -> 0.99 | K32: =$AX32*K$27 -> 0.99 | ... AW32: =$AX32*AW$27 -> 0.99 | AX32: 0.99 | AY32: EFF | AZ32: =AZ23 -> Trd_2w_gsl | BA32: =IF($AZ32="","",$BA$45) -> Trd_2w | BB32: =IF($AZ32="","",25) -> 25 | BD32: =IF(AZ32="","*","DMD") -> DMD | BE32: =AZ32 -> Trd_2w_gsl | BG32: Bvkm | BH32: million Vehicles | BI32: yes
C33: =C24 -> TRALPG | D33: =$AX33*D$27 -> 0.99 | E33: =$AX33*E$27 -> 0.99 | F33: =$AX33*F$27 -> 0.99 | G33: =$AX33*G$27 -> 0.99 | H33: =$AX33*H$27 -> 0.99 | I33: =$AX33*I$27 -> 0.99 | J33: =$AX33*J$27 -> 0.99 | K33: =$AX33*K$27 -> 0.99 | ... AW33: =$AX33*AW$27 -> 0.99 | AX33: 0.99 | AY33: EFF | AZ33: =AZ24 -> \I: | BA33: =IF($AZ33="","",$BA$45) -> Trd_2w | BB33: =IF($AZ33="","",25) -> 25 | BD33: =IF(AZ33="","*","DMD") -> DMD | BE33: =AZ33 -> \I: | BG33: Bvkm | BH33: million Vehicles | BI33: yes
C34: =C25 -> TRANGA | D34: =$AX34*D$27 -> 0.99 | E34: =$AX34*E$27 -> 0.99 | F34: =$AX34*F$27 -> 0.99 | G34: =$AX34*G$27 -> 0.99 | H34: =$AX34*H$27 -> 0.99 | I34: =$AX34*I$27 -> 0.99 | J34: =$AX34*J$27 -> 0.99 | K34: =$AX34*K$27 -> 0.99 | ... AW34: =$AX34*AW$27 -> 0.99 | AX34: 0.99 | AY34: EFF | AZ34: =AZ25 -> \I: | BA34: =IF($AZ34="","",$BA$45) -> Trd_2w | BB34: =IF($AZ34="","",25) -> 25 | BD34: =IF(AZ34="","*","DMD") -> DMD | BE34: =AZ34 -> \I: | BG34: Bvkm | BH34: million Vehicles | BI34: yes
AY35: * | BA35: =IF($AZ35="","",$BA$45) | BB35: =IF($AZ35="","",25) | BD35: =IF(AZ35="","*","DMD") -> * | BE35: =AZ35 -> 0 | BG35: Bvkm | BH35: million Vehicles | BI35: yes
A36: 000km/veh | C36: =C28 -> TRABDS | D36: 7 | E36: 7 | F36: 7 | G36: 7 | H36: 7 | I36: 7 | J36: 7 | K36: 7 | L36: 7 | M36: 7 | N36: 7 | O36: 7 | P36: 7 | Q36: 7 | R36: 7 | S36: 7 | T36: 7 | U36: 7 | V36: 4 | W36: 7 | X36: 5 | Y36: 7 | Z36: 4 | AA36: 7 | AB36: 7 | AC36: 3 | AD36: 7 | AE36: 7 | AF36: 6.5 | AG36: 7 | AH36: 7 | AI36: 7 | AJ36: 4 | AK36: 4 | AL36: 4 | AM36: 4 | AN36: 4 | AO36: 4 | AP36: 4 | AQ36: 4 | AR36: 4 | AS36: 4 | AT36: 4 | AU36: 4 | AV36: 4 | AW36: 4 | AY36: AF | AZ36: =AZ28 -> \I: | BA36: =IF($AZ36="","",$BA$45) -> Trd_2w | BB36: =IF($AZ36="","",25) -> 25 | BD36: =IF(AZ36="","*","DMD") -> DMD | BE36: =AZ36 -> \I: | BG36: Bvkm | BH36: million Vehicles | BI36: yes
C37: =C29 -> TRABGS | D37: 7 | E37: 7 | F37: 7 | G37: 7 | H37: 7 | I37: 7 | J37: 7 | K37: 7 | L37: 7 | M37: 7 | N37: 7 | O37: 7 | P37: 7 | Q37: 7 | R37: 7 | S37: 7 | T37: 7 | U37: 7 | V37: 4 | W37: 7 | X37: 5 | Y37: 7 | Z37: 4 | AA37: 7 | AB37: 7 | AC37: 3 | AD37: 7 | AE37: 7 | AF37: 6.5 | AG37: 7 | AH37: 7 | AI37: 7 | AJ37: 4 | AK37: 4 | AL37: 4 | AM37: 4 | AN37: 4 | AO37: 4 | AP37: 4 | AQ37: 4 | AR37: 4 | AS37: 4 | AT37: 4 | AU37: 4 | AV37: 4 | AW37: 4 | AY37: AF | AZ37: =AZ29 -> \I: | BA37: =IF($AZ37="","",$BA$45) -> Trd_2w | BB37: =IF($AZ37="","",25) -> 25 | BD37: =IF(AZ37="","*","DMD") -> DMD | BE37: =AZ37 -> \I: | BG37: Bvkm | BH37: million Vehicles | BI37: yes
C38: =C30 -> TRADST | D38: 7 | E38: 7 | F38: 7 | G38: 7 | H38: 7 | I38: 7 | J38: 7 | K38: 7 | L38: 7 | M38: 7 | N38: 7 | O38: 7 | P38: 7 | Q38: 7 | R38: 7 | S38: 7 | T38: 7 | U38: 7 | V38: 4 | W38: 7 | X38: 5 | Y38: 7 | Z38: 4 | AA38: 7 | AB38: 7 | AC38: 3 | AD38: 7 | AE38: 7 | AF38: 6.5 | AG38: 7 | AH38: 7 | AI38: 7 | AJ38: 4 | AK38: 4 | AL38: 4 | AM38: 4 | AN38: 4 | AO38: 4 | AP38: 4 | AQ38: 4 | AR38: 4 | AS38: 4 | AT38: 4 | AU38: 4 | AV38: 4 | AW38: 4 | AY38: AF | AZ38: =AZ30 -> \I: | BA38: =IF($AZ38="","",$BA$45) -> Trd_2w | BB38: =IF($AZ38="","",25) -> 25 | BD38: =IF(AZ38="","*","DMD") -> DMD | BE38: =AZ38 -> \I: | BG38: Bvkm | BH38: million Vehicles | BI38: yes
C39: =C31 -> TRAELC | D39: 7 | E39: 7 | F39: 7 | G39: 7 | H39: 7 | I39: 7 | J39: 7 | K39: 7 | L39: 7 | M39: 7 | N39: 7 | O39: 7 | P39: 7 | Q39: 7 | R39: 7 | S39: 7 | T39: 7 | U39: 7 | V39: 4 | W39: 7 | X39: 5 | Y39: 7 | Z39: 4 | AA39: 7 | AB39: 7 | AC39: 3 | AD39: 7 | AE39: 7 | AF39: 6.5 | AG39: 7 | AH39: 7 | AI39: 7 | AJ39: 4 | AK39: 4 | AL39: 4 | AM39: 4 | AN39: 4 | AO39: 4 | AP39: 4 | AQ39: 4 | AR39: 4 | AS39: 4 | AT39: 4 | AU39: 4 | AV39: 4 | AW39: 4 | AY39: AF | AZ39: =AZ31 -> Trd_2w_elc | BA39: =IF($AZ39="","",$BA$45) -> Trd_2w | BB39: =IF($AZ39="","",25) -> 25 | BD39: =IF(AZ39="","*","DMD") -> DMD | BE39: =AZ39 -> Trd_2w_elc | BG39: Bvkm | BH39: million Vehicles | BI39: yes
C40: =C32 -> TRAGSL | D40: 7 | E40: 7 | F40: 7 | G40: 7 | H40: 7 | I40: 7 | J40: 7 | K40: 7 | L40: 7 | M40: 7 | N40: 7 | O40: 7 | P40: 7 | Q40: 7 | R40: 7 | S40: 7 | T40: 7 | U40: 7 | V40: 4 | W40: 7 | X40: 5 | Y40: 7 | Z40: 4 | AA40: 7 | AB40: 7 | AC40: 3 | AD40: 7 | AE40: 7 | AF40: 6.5 | AG40: 7 | AH40: 7 | AI40: 7 | AJ40: 4 | AK40: 4 | AL40: 4 | AM40: 4 | AN40: 4 | AO40: 4 | AP40: 4 | AQ40: 4 | AR40: 4 | AS40: 4 | AT40: 4 | AU40: 4 | AV40: 4 | AW40: 4 | AY40: AF | AZ40: =AZ32 -> Trd_2w_gsl | BA40: =IF($AZ40="","",$BA$45) -> Trd_2w | BB40: =IF($AZ40="","",25) -> 25 | BD40: =IF(AZ40="","*","DMD") -> DMD | BE40: =AZ40 -> Trd_2w_gsl | BG40: Bvkm | BH40: million Vehicles | BI40: yes
C41: =C33 -> TRALPG | D41: 7 | E41: 7 | F41: 7 | G41: 7 | H41: 7 | I41: 7 | J41: 7 | K41: 7 | L41: 7 | M41: 7 | N41: 7 | O41: 7 | P41: 7 | Q41: 7 | R41: 7 | S41: 7 | T41: 7 | U41: 7 | V41: 4 | W41: 7 | X41: 5 | Y41: 7 | Z41: 4 | AA41: 7 | AB41: 7 | AC41: 3 | AD41: 7 | AE41: 7 | AF41: 6.5 | AG41: 7 | AH41: 7 | AI41: 7 | AJ41: 4 | AK41: 4 | AL41: 4 | AM41: 4 | AN41: 4 | AO41: 4 | AP41: 4 | AQ41: 4 | AR41: 4 | AS41: 4 | AT41: 4 | AU41: 4 | AV41: 4 | AW41: 4 | AY41: AF | AZ41: =AZ33 -> \I: | BA41: =IF($AZ41="","",$BA$45) -> Trd_2w | BB41: =IF($AZ41="","",25) -> 25 | BD41: =IF(AZ41="","*","DMD") -> DMD | BE41: =AZ41 -> \I: | BG41: Bvkm | BH41: million Vehicles | BI41: yes
C42: =C34 -> TRANGA | D42: 7 | E42: 7 | F42: 7 | G42: 7 | H42: 7 | I42: 7 | J42: 7 | K42: 7 | L42: 7 | M42: 7 | N42: 7 | O42: 7 | P42: 7 | Q42: 7 | R42: 7 | S42: 7 | T42: 7 | U42: 7 | V42: 4 | W42: 7 | X42: 5 | Y42: 7 | Z42: 4 | AA42: 7 | AB42: 7 | AC42: 3 | AD42: 7 | AE42: 7 | AF42: 6.5 | AG42: 7 | AH42: 7 | AI42: 7 | AJ42: 4 | AK42: 4 | AL42: 4 | AM42: 4 | AN42: 4 | AO42: 4 | AP42: 4 | AQ42: 4 | AR42: 4 | AS42: 4 | AT42: 4 | AU42: 4 | AV42: 4 | AW42: 4 | AY42: AF | AZ42: =AZ34 -> \I: | BA42: =IF($AZ42="","",$BA$45) -> Trd_2w | BB42: =IF($AZ42="","",25) -> 25 | BD42: =IF(AZ42="","*","DMD") -> DMD | BE42: =AZ42 -> \I: | BG42: Bvkm | BH42: million Vehicles | BI42: yes
AY43: * | BB43: =IF($AZ43="","",25)
D44: =D3 -> Africa_North | E44: =E3 -> Africa_Other | F44: =F3 -> Australia | G44: =G3 -> Austria | H44: =H3 -> Baltics | I44: =I3 -> BeNeLux | J44: =J3 -> Brazil | K44: =K3 -> China | ... AW44: =AW3 -> \I: | AY44: * | BB44: =IF($AZ44="","",25)
A45: Dem Bvkm | AY45: Demand | BA45: Trd_2w | BB45: =IF($AZ45="","",25)
AY46: *
AY48: ~FI_Comm
AY49: CSet | AZ49: CommName | BA49: CommDesc | BB49: Unit
AY50: DEM | AZ50: =BA45 -> Trd_2w | BB50: Bvkm

Sheet 3-w
AY2: ~FI_T | BD2: ~FI_Process
C3: comm-in | D3: ='TRA balance'!E4 -> Africa_North | E3: ='TRA balance'!F4 -> Africa_Other | F3: ='TRA balance'!G4 -> Australia | G3: ='TRA balance'!H4 -> Austria | H3: ='TRA balance'!I4 -> Baltics | I3: ='TRA balance'!J4 -> BeNeLux | J3: ='TRA balance'!K4 -> Brazil | K3: ='TRA balance'!L4 -> China | ... AW3: ='TRA balance'!AX4 -> \I: | AX3: * | AY3: attribute | AZ3: process | BA3: comm-out | BB3: LIFE | BD3: Sets | BE3: TechName | BF3: TechDesc | BG3: Tact | BH3: Tcap | BI3: Vintage
A4: TR | C4: TRABDS | D4: {=SUM(SUMIFS(Assumptions!BD$3:BD$102,Assumptions!$B$3:$B$102,'3-w'!$C4,Assumptions!$G$3:$G$102,{"TRE"}))} -> 0 | E4: {=SUM(SUMIFS(Assumptions!BE$3:BE$102,Assumptions!$B$3:$B$102,'3-w'!$C4,Assumptions!$G$3:$G$102,{"TRE"}))} -> 0 | F4: {=SUM(SUMIFS(Assumptions!BF$3:BF$102,Assumptions!$B$3:$B$102,'3-w'!$C4,Assumptions!$G$3:$G$102,{"TRE"}))} -> 0 | G4: {=SUM(SUMIFS(Assumptions!BG$3:BG$102,Assumptions!$B$3:$B$102,'3-w'!$C4,Assumptions!$G$3:$G$102,{"TRE"}))} -> 0 | H4: {=SUM(SUMIFS(Assumptions!BH$3:BH$102,Assumptions!$B$3:$B$102,'3-w'!$C4,Assumptions!$G$3:$G$102,{"TRE"}))} -> 0 | I4: {=SUM(SUMIFS(Assumptions!BI$3:BI$102,Assumptions!$B$3:$B$102,'3-w'!$C4,Assumptions!$G$3:$G$102,{"TRE"}))} -> 0 | J4: {=SUM(SUMIFS(Assumptions!BJ$3:BJ$102,Assumptions!$B$3:$B$102,'3-w'!$C4,Assumptions!$G$3:$G$102,{"TRE"}))} -> 0.45572095 | K4: {=SUM(SUMIFS(Assumptions!BK$3:BK$102,Assumptions!$B$3:$B$102,'3-w'!$C4,Assumptions!$G$3:$G$102,{"TRE"}))} -> 2.27424 | ... AW4: {=SUM(SUMIFS(Assumptions!CW$3:CW$102,Assumptions!$B$3:$B$102,'3-w'!$C4,Assumptions!$G$3:$G$102,{"TRE"}))} -> 0 | AX4: =IF(SUM(D4:AW4)=0,"zero","") | AY4: * | BA4: =IF($AZ4="","",$BA$45) | BB4: =IF($AZ4="","",25) | BD4: =IF($AZ4="","*","DMD") -> * | BE4: =AZ4 -> 0 | BG4: Bvkm | BH4: million Vehicles | BI4: yes
A5: TR | C5: TRABGS | D5: {=SUM(SUMIFS(Assumptions!BD$3:BD$102,Assumptions!$B$3:$B$102,'3-w'!$C5,Assumptions!$G$3:$G$102,{"TRE"}))} -> 0 | E5: {=SUM(SUMIFS(Assumptions!BE$3:BE$102,Assumptions!$B$3:$B$102,'3-w'!$C5,Assumptions!$G$3:$G$102,{"TRE"}))} -> 0 | F5: {=SUM(SUMIFS(Assumptions!BF$3:BF$102,Assumptions!$B$3:$B$102,'3-w'!$C5,Assumptions!$G$3:$G$102,{"TRE"}))} -> 0 | G5: {=SUM(SUMIFS(Assumptions!BG$3:BG$102,Assumptions!$B$3:$B$102,'3-w'!$C5,Assumptions!$G$3:$G$102,{"TRE"}))} -> 0 | H5: {=SUM(SUMIFS(Assumptions!BH$3:BH$102,Assumptions!$B$3:$B$102,'3-w'!$C5,Assumptions!$G$3:$G$102,{"TRE"}))} -> 0 | I5: {=SUM(SUMIFS(Assumptions!BI$3:BI$102,Assumptions!$B$3:$B$102,'3-w'!$C5,Assumptions!$G$3:$G$102,{"TRE"}))} -> 0 | J5: {=SUM(SUMIFS(Assumptions!BJ$3:BJ$102,Assumptions!$B$3:$B$102,'3-w'!$C5,Assumptions!$G$3:$G$102,{"TRE"}))} -> 0 | K5: {=SUM(SUMIFS(Assumptions!BK$3:BK$102,Assumptions!$B$3:$B$102,'3-w'!$C5,Assumptions!$G$3:$G$102,{"TRE"}))} -> 0 | ... AW5: {=SUM(SUMIFS(Assumptions!CW$3:CW$102,Assumptions!$B$3:$B$102,'3-w'!$C5,Assumptions!$G$3:$G$102,{"TRE"}))} -> 0 | AX5: =IF(SUM(D5:AW5)=0,"zero","") -> zero | AY5: * | BA5: =IF($AZ5="","",$BA$45) | BB5: =IF($AZ5="","",25) | BD5: =IF(AZ5="","*","DMD") -> * | BE5: =AZ5 -> 0 | BG5: Bvkm | BH5: million Vehicles | BI5: yes
A6: TR | C6: TRADST | D6: {=SUM(SUMIFS(Assumptions!BD$3:BD$102,Assumptions!$B$3:$B$102,'3-w'!$C6,Assumptions!$G$3:$G$102,{"TRE"}))} -> 0 | E6: {=SUM(SUMIFS(Assumptions!BE$3:BE$102,Assumptions!$B$3:$B$102,'3-w'!$C6,Assumptions!$G$3:$G$102,{"TRE"}))} -> 0 | F6: {=SUM(SUMIFS(Assumptions!BF$3:BF$102,Assumptions!$B$3:$B$102,'3-w'!$C6,Assumptions!$G$3:$G$102,{"TRE"}))} -> 0 | G6: {=SUM(SUMIFS(Assumptions!BG$3:BG$102,Assumptions!$B$3:$B$102,'3-w'!$C6,Assumptions!$G$3:$G$102,{"TRE"}))} -> 0 | H6: {=SUM(SUMIFS(Assumptions!BH$3:BH$102,Assumptions!$B$3:$B$102,'3-w'!$C6,Assumptions!$G$3:$G$102,{"TRE"}))} -> 0 | I6: {=SUM(SUMIFS(Assumptions!BI$3:BI$102,Assumptions!$B$3:$B$102,'3-w'!$C6,Assumptions!$G$3:$G$102,{"TRE"}))} -> 0 | J6: {=SUM(SUMIFS(Assumptions!BJ$3:BJ$102,Assumptions!$B$3:$B$102,'3-w'!$C6,Assumptions!$G$3:$G$102,{"TRE"}))} -> 1.0051941 | K6: {=SUM(SUMIFS(Assumptions!BK$3:BK$102,Assumptions!$B$3:$B$102,'3-w'!$C6,Assumptions!$G$3:$G$102,{"TRE"}))} -> 232.8823 | ... AW6: {=SUM(SUMIFS(Assumptions!CW$3:CW$102,Assumptions!$B$3:$B$102,'3-w'!$C6,Assumptions!$G$3:$G$102,{"TRE"}))} -> 0 | AX6: =IF(SUM(D6:AW6)=0,"zero","") | AY6: * | BA6: =IF($AZ6="","",$BA$45) | BB6: =IF($AZ6="","",25) | BD6: =IF(AZ6="","*","DMD") -> * | BE6: =AZ6 -> 0 | BG6: Bvkm | BH6: million Vehicles | BI6: yes
A7: TR | C7: TRAELC | D7: {=SUM(SUMIFS(Assumptions!BD$3:BD$102,Assumptions!$B$3:$B$102,'3-w'!$C7,Assumptions!$G$3:$G$102,{"TRE"}))} -> 0 | E7: {=SUM(SUMIFS(Assumptions!BE$3:BE$102,Assumptions!$B$3:$B$102,'3-w'!$C7,Assumptions!$G$3:$G$102,{"TRE"}))} -> 0 | F7: {=SUM(SUMIFS(Assumptions!BF$3:BF$102,Assumptions!$B$3:$B$102,'3-w'!$C7,Assumptions!$G$3:$G$102,{"TRE"}))} -> 0 | G7: {=SUM(SUMIFS(Assumptions!BG$3:BG$102,Assumptions!$B$3:$B$102,'3-w'!$C7,Assumptions!$G$3:$G$102,{"TRE"}))} -> 0 | H7: {=SUM(SUMIFS(Assumptions!BH$3:BH$102,Assumptions!$B$3:$B$102,'3-w'!$C7,Assumptions!$G$3:$G$102,{"TRE"}))} -> 0 | I7: {=SUM(SUMIFS(Assumptions!BI$3:BI$102,Assumptions!$B$3:$B$102,'3-w'!$C7,Assumptions!$G$3:$G$102,{"TRE"}))} -> 0 | J7: {=SUM(SUMIFS(Assumptions!BJ$3:BJ$102,Assumptions!$B$3:$B$102,'3-w'!$C7,Assumptions!$G$3:$G$102,{"TRE"}))} -> 0 | K7: {=SUM(SUMIFS(Assumptions!BK$3:BK$102,Assumptions!$B$3:$B$102,'3-w'!$C7,Assumptions!$G$3:$G$102,{"TRE"}))} -> 0 | ... AW7: {=SUM(SUMIFS(Assumptions!CW$3:CW$102,Assumptions!$B$3:$B$102,'3-w'!$C7,Assumptions!$G$3:$G$102,{"TRE"}))} -> 0 | AX7: =IF(SUM(D7:AW7)=0,"zero","") -> zero | AY7: * | BA7: =IF($AZ7="","",$BA$45) | BB7: =IF($AZ7="","",25) | BD7: =IF(AZ7="","*","DMD") -> * | BE7: =AZ7 -> 0 | BG7: Bvkm | BH7: million Vehicles | BI7: yes
A8: TR | C8: TRAGSL | D8: {=SUM(SUMIFS(Assumptions!BD$3:BD$102,Assumptions!$B$3:$B$102,'3-w'!$C8,Assumptions!$G$3:$G$102,{"TRE"}))} -> 71.567029 | E8: {=SUM(SUMIFS(Assumptions!BE$3:BE$102,Assumptions!$B$3:$B$102,'3-w'!$C8,Assumptions!$G$3:$G$102,{"TRE"}))} -> 124.27522 | F8: {=SUM(SUMIFS(Assumptions!BF$3:BF$102,Assumptions!$B$3:$B$102,'3-w'!$C8,Assumptions!$G$3:$G$102,{"TRE"}))} -> 0 | G8: {=SUM(SUMIFS(Assumptions!BG$3:BG$102,Assumptions!$B$3:$B$102,'3-w'!$C8,Assumptions!$G$3:$G$102,{"TRE"}))} -> 0.33583423 | H8: {=SUM(SUMIFS(Assumptions!BH$3:BH$102,Assumptions!$B$3:$B$102,'3-w'!$C8,Assumptions!$G$3:$G$102,{"TRE"}))} -> 0.10120572 | I8: {=SUM(SUMIFS(Assumptions!BI$3:BI$102,Assumptions!$B$3:$B$102,'3-w'!$C8,Assumptions!$G$3:$G$102,{"TRE"}))} -> 1.2993734 | J8: {=SUM(SUMIFS(Assumptions!BJ$3:BJ$102,Assumptions!$B$3:$B$102,'3-w'!$C8,Assumptions!$G$3:$G$102,{"TRE"}))} -> 4.0418183 | K8: {=SUM(SUMIFS(Assumptions!BK$3:BK$102,Assumptions!$B$3:$B$102,'3-w'!$C8,Assumptions!$G$3:$G$102,{"TRE"}))} -> 0 | ... AW8: {=SUM(SUMIFS(Assumptions!CW$3:CW$102,Assumptions!$B$3:$B$102,'3-w'!$C8,Assumptions!$G$3:$G$102,{"TRE"}))} -> 0 | AX8: =IF(SUM(D8:AW8)=0,"zero","") | AY8: * | BA8: =IF($AZ8="","",$BA$45) | BB8: =IF($AZ8="","",25) | BD8: =IF(AZ8="","*","DMD") -> * | BE8: =AZ8 -> 0 | BG8: Bvkm | BH8: million Vehicles | BI8: yes
A9: TR | C9: TRALPG | D9: {=SUM(SUMIFS(Assumptions!BD$3:BD$102,Assumptions!$B$3:$B$102,'3-w'!$C9,Assumptions!$G$3:$G$102,{"TRE"}))} -> 0 | E9: {=SUM(SUMIFS(Assumptions!BE$3:BE$102,Assumptions!$B$3:$B$102,'3-w'!$C9,Assumptions!$G$3:$G$102,{"TRE"}))} -> 0 | F9: {=SUM(SUMIFS(Assumptions!BF$3:BF$102,Assumptions!$B$3:$B$102,'3-w'!$C9,Assumptions!$G$3:$G$102,{"TRE"}))} -> 0 | G9: {=SUM(SUMIFS(Assumptions!BG$3:BG$102,Assumptions!$B$3:$B$102,'3-w'!$C9,Assumptions!$G$3:$G$102,{"TRE"}))} -> 0 | H9: {=SUM(SUMIFS(Assumptions!BH$3:BH$102,Assumptions!$B$3:$B$102,'3-w'!$C9,Assumptions!$G$3:$G$102,{"TRE"}))} -> 0 | I9: {=SUM(SUMIFS(Assumptions!BI$3:BI$102,Assumptions!$B$3:$B$102,'3-w'!$C9,Assumptions!$G$3:$G$102,{"TRE"}))} -> 0 | J9: {=SUM(SUMIFS(Assumptions!BJ$3:BJ$102,Assumptions!$B$3:$B$102,'3-w'!$C9,Assumptions!$G$3:$G$102,{"TRE"}))} -> 0 | K9: {=SUM(SUMIFS(Assumptions!BK$3:BK$102,Assumptions!$B$3:$B$102,'3-w'!$C9,Assumptions!$G$3:$G$102,{"TRE"}))} -> 0 | ... AW9: {=SUM(SUMIFS(Assumptions!CW$3:CW$102,Assumptions!$B$3:$B$102,'3-w'!$C9,Assumptions!$G$3:$G$102,{"TRE"}))} -> 0 | AX9: =IF(SUM(D9:AW9)=0,"zero","") -> zero | AY9: * | BA9: =IF($AZ9="","",$BA$45) | BB9: =IF($AZ9="","",25) | BD9: =IF(AZ9="","*","DMD") -> * | BE9: =AZ9 -> 0 | BG9: Bvkm | BH9: million Vehicles | BI9: yes
A10: TR | C10: TRANGA | D10: {=SUM(SUMIFS(Assumptions!BD$3:BD$102,Assumptions!$B$3:$B$102,'3-w'!$C10,Assumptions!$G$3:$G$102,{"TRE"}))} -> 0 | E10: {=SUM(SUMIFS(Assumptions!BE$3:BE$102,Assumptions!$B$3:$B$102,'3-w'!$C10,Assumptions!$G$3:$G$102,{"TRE"}))} -> 0 | F10: {=SUM(SUMIFS(Assumptions!BF$3:BF$102,Assumptions!$B$3:$B$102,'3-w'!$C10,Assumptions!$G$3:$G$102,{"TRE"}))} -> 0 | G10: {=SUM(SUMIFS(Assumptions!BG$3:BG$102,Assumptions!$B$3:$B$102,'3-w'!$C10,Assumptions!$G$3:$G$102,{"TRE"}))} -> 0 | H10: {=SUM(SUMIFS(Assumptions!BH$3:BH$102,Assumptions!$B$3:$B$102,'3-w'!$C10,Assumptions!$G$3:$G$102,{"TRE"}))} -> 0 | I10: {=SUM(SUMIFS(Assumptions!BI$3:BI$102,Assumptions!$B$3:$B$102,'3-w'!$C10,Assumptions!$G$3:$G$102,{"TRE"}))} -> 0 | J10: {=SUM(SUMIFS(Assumptions!BJ$3:BJ$102,Assumptions!$B$3:$B$102,'3-w'!$C10,Assumptions!$G$3:$G$102,{"TRE"}))} -> 0 | K10: {=SUM(SUMIFS(Assumptions!BK$3:BK$102,Assumptions!$B$3:$B$102,'3-w'!$C10,Assumptions!$G$3:$G$102,{"TRE"}))} -> 0 | ... AW10: {=SUM(SUMIFS(Assumptions!CW$3:CW$102,Assumptions!$B$3:$B$102,'3-w'!$C10,Assumptions!$G$3:$G$102,{"TRE"}))} -> 0 | AX10: =IF(SUM(D10:AW10)=0,"zero","") -> zero | AY10: * | BA10: =IF($AZ10="","",$BA$45) | BB10: =IF($AZ10="","",25) | BD10: =IF(AZ10="","*","DMD") -> * | BE10: =AZ10 -> 0 | BG10: Bvkm | BH10: million Vehicles | BI10: yes
A11: Share of PJ | D11: =SUM(D$4:D$10)/SUM($D$4:$AJ$10) -> 0.055723378 | E11: =SUM(E$4:E$10)/SUM($D$4:$AJ$10) -> 0.096762923 | F11: =SUM(F$4:F$10)/SUM($D$4:$AJ$10) -> 0 | G11: =SUM(G$4:G$10)/SUM($D$4:$AJ$10) -> 0.00026148658 | H11: =SUM(H$4:H$10)/SUM($D$4:$AJ$10) -> 7.8800598e-05 | I11: =SUM(I$4:I$10)/SUM($D$4:$AJ$10) -> 0.0010117155 | J11: =SUM(J$4:J$10)/SUM($D$4:$AJ$10) -> 0.0042845273 | K11: =SUM(K$4:K$10)/SUM($D$4:$AJ$10) -> 0.18309711 | ... AW11: =SUM(AW$4:AW$10)/SUM($D$4:$AJ$10) -> 0 | AY11: * | BA11: =IF($AZ11="","",$BA$45) | BB11: =IF($AZ11="","",25) | BD11: =IF(AZ11="","*","DMD") -> * | BE11: =AZ11 -> 0 | BG11: Bvkm | BH11: million Vehicles | BI11: yes
AY12: * | BA12: =IF($AZ12="","",$BA$45) | BB12: =IF($AZ12="","",25) | BD12: =IF(AZ12="","*","DMD") -> * | BE12: =AZ12 -> 0 | BG12: Bvkm | BH12: million Vehicles | BI12: yes
A13: m Vehicles | C13: =SUM(D13:AJ13) -> 50.243 | D13: =SUM(D19:D25) -> 2.801 | E13: =SUM(E19:E25) -> 4.863 | F13: =SUM(F19:F25) -> 0 | G13: =SUM(G19:G25) -> 0.013 | H13: =SUM(H19:H25) -> 0.004 | I13: =SUM(I19:I25) -> 0.051 | J13: =SUM(J19:J25) -> 0.215 | K13: =SUM(K19:K25) -> 9.202 | ... AW13: =SUM(AW19:AW25) -> 0 | AY13: * | BA13: =IF($AZ13="","",$BA$45) | BB13: =IF($AZ13="","",25) | BD13: =IF(AZ13="","*","DMD") -> * | BE13: =AZ13 -> 0 | BG13: Bvkm | BH13: million Vehicles | BI13: yes
A14: Share of Veh | D14: =D13/SUM($D$13:$AJ$13) -> 0.05574906 | E14: =E13/SUM($D$13:$AJ$13) -> 0.096789603 | F14: =F13/SUM($D$13:$AJ$13) -> 0 | G14: =G13/SUM($D$13:$AJ$13) -> 0.00025874251 | H14: =H13/SUM($D$13:$AJ$13) -> 7.961308e-05 | I14: =I13/SUM($D$13:$AJ$13) -> 0.0010150668 | J14: =J13/SUM($D$13:$AJ$13) -> 0.0042792031 | K14: =K13/SUM($D$13:$AJ$13) -> 0.18314989 | ... AW14: =AW13/SUM($D$13:$AJ$13) -> 0 | AY14: * | BA14: =IF($AZ14="","",$BA$45) | BB14: =IF($AZ14="","",25) | BD14: =IF(AZ14="","*","DMD") -> * | BE14: =AZ14 -> 0 | BG14: Bvkm | BH14: million Vehicles | BI14: yes
AY15: * | BA15: =IF($AZ15="","",$BA$45) | BB15: =IF($AZ15="","",25) | BD15: =IF(AZ15="","*","DMD") -> * | BE15: =AZ15 -> 0 | BG15: Bvkm | BH15: million Vehicles | BI15: yes
AY16: * | BA16: =IF($AZ16="","",$BA$45) | BB16: =IF($AZ16="","",25) | BD16: =IF(AZ16="","*","DMD") -> * | BE16: =AZ16 -> 0 | BG16: Bvkm | BH16: million Vehicles | BI16: yes
A17: PJ share/Veh share | D17: =IFERROR(D11/D14,"") -> 0.99953934 | E17: =IFERROR(E11/E14,"") -> 0.99972435 | F17: =IFERROR(F11/F14,"") | G17: =IFERROR(G11/G14,"") -> 1.0106054 | H17: =IFERROR(H11/H14,"") -> 0.98979461 | I17: =IFERROR(I11/I14,"") -> 0.99669849 | J17: =IFERROR(J11/J14,"") -> 1.0012442 | K17: =IFERROR(K11/K14,"") -> 0.99971184 | ... AW17: =IFERROR(AW11/AW14,"") | AY17: * | BA17: =IF($AZ17="","",$BA$45) | BB17: =IF($AZ17="","",25) | BD17: =IF(AZ17="","*","DMD") -> * | BE17: =AZ17 -> 0 | BG17: Bvkm | BH17: million Vehicles | BI17: yes
AY18: * | BA18: =IF($AZ18="","",$BA$45) | BB18: =IF($AZ18="","",25) | BD18: =IF(AZ18="","*","DMD") -> * | BE18: =AZ18 -> 0 | BG18: Bvkm | BH18: million Vehicles | BI18: yes
A19: mVeh | C19: =C4 -> TRABDS | D19: =ROUND(D4*D28/D36,3) -> 0 | E19: =ROUND(E4*E28/E36,3) -> 0 | F19: =ROUND(F4*F28/F36,3) -> 0 | G19: =ROUND(G4*G28/G36,3) -> 0 | H19: =ROUND(H4*H28/H36,3) -> 0 | I19: =ROUND(I4*I28/I36,3) -> 0 | J19: =ROUND(J4*J28/J36,3) -> 0.018 | K19: =ROUND(K4*K28/K36,3) -> 0.089 | ... AW19: =ROUND(AW4*AW28/AW36,3) -> 0 | AY19: PASTI | AZ19: =IF(AX4="zero","\I:",$BA$45&"_"&VLOOKUP(C19,'TRA balance'!$BB$5:$BC$15,2,FALSE)) -> Trd_3w_bdl | BA19: =IF($AZ19="","",$BA$45) -> Trd_3w | BB19: =IF($AZ19="","",25) -> 25 | BD19: =IF(AZ19="","*","DMD") -> DMD | BE19: =AZ19 -> Trd_3w_bdl | BG19: Bvkm | BH19: million Vehicles | BI19: yes
C20: =C5 -> TRABGS | D20: =ROUND(D5*D29/D37,3) -> 0 | E20: =ROUND(E5*E29/E37,3) -> 0 | F20: =ROUND(F5*F29/F37,3) -> 0 | G20: =ROUND(G5*G29/G37,3) -> 0 | H20: =ROUND(H5*H29/H37,3) -> 0 | I20: =ROUND(I5*I29/I37,3) -> 0 | J20: =ROUND(J5*J29/J37,3) -> 0 | K20: =ROUND(K5*K29/K37,3) -> 0 | ... AW20: =ROUND(AW5*AW29/AW37,3) -> 0 | AY20: PASTI | AZ20: =IF(AX5="zero","\I:",$BA$45&"_"&VLOOKUP(C20,'TRA balance'!$BB$5:$BC$15,2,FALSE)) -> \I: | BA20: =IF($AZ20="","",$BA$45) -> Trd_3w | BB20: =IF($AZ20="","",25) -> 25 | BD20: =IF(AZ20="","*","DMD") -> DMD | BE20: =AZ20 -> \I: | BG20: Bvkm | BH20: million Vehicles | BI20: yes
C21: =C6 -> TRADST | D21: =ROUND(D6*D30/D38,3) -> 0 | E21: =ROUND(E6*E30/E38,3) -> 0 | F21: =ROUND(F6*F30/F38,3) -> 0 | G21: =ROUND(G6*G30/G38,3) -> 0 | H21: =ROUND(H6*H30/H38,3) -> 0 | I21: =ROUND(I6*I30/I38,3) -> 0 | J21: =ROUND(J6*J30/J38,3) -> 0.039 | K21: =ROUND(K6*K30/K38,3) -> 9.113 | ... AW21: =ROUND(AW6*AW30/AW38,3) -> 0 | AY21: PASTI | AZ21: =IF(AX6="zero","\I:",$BA$45&"_"&VLOOKUP(C21,'TRA balance'!$BB$5:$BC$15,2,FALSE)) -> Trd_3w_dsl | BA21: =IF($AZ21="","",$BA$45) -> Trd_3w | BB21: =IF($AZ21="","",25) -> 25 | BD21: =IF(AZ21="","*","DMD") -> DMD | BE21: =AZ21 -> Trd_3w_dsl | BG21: Bvkm | BH21: million Vehicles | BI21: yes
C22: =C7 -> TRAELC | D22: =ROUND(D7*D31/D39,3) -> 0 | E22: =ROUND(E7*E31/E39,3) -> 0 | F22: =ROUND(F7*F31/F39,3) -> 0 | G22: =ROUND(G7*G31/G39,3) -> 0 | H22: =ROUND(H7*H31/H39,3) -> 0 | I22: =ROUND(I7*I31/I39,3) -> 0 | J22: =ROUND(J7*J31/J39,3) -> 0 | K22: =ROUND(K7*K31/K39,3) -> 0 | ... AW22: =ROUND(AW7*AW31/AW39,3) -> 0 | AY22: PASTI | AZ22: =IF(AX7="zero","\I:",$BA$45&"_"&VLOOKUP(C22,'TRA balance'!$BB$5:$BC$15,2,FALSE)) -> \I: | BA22: =IF($AZ22="","",$BA$45) -> Trd_3w | BB22: =IF($AZ22="","",25) -> 25 | BD22: =IF(AZ22="","*","DMD") -> DMD | BE22: =AZ22 -> \I: | BG22: Bvkm | BH22: million Vehicles | BI22: yes
C23: =C8 -> TRAGSL | D23: =ROUND(D8*D32/D40,3) -> 2.801 | E23: =ROUND(E8*E32/E40,3) -> 4.863 | F23: =ROUND(F8*F32/F40,3) -> 0 | G23: =ROUND(G8*G32/G40,3) -> 0.013 | H23: =ROUND(H8*H32/H40,3) -> 0.004 | I23: =ROUND(I8*I32/I40,3) -> 0.051 | J23: =ROUND(J8*J32/J40,3) -> 0.158 | K23: =ROUND(K8*K32/K40,3) -> 0 | ... AW23: =ROUND(AW8*AW32/AW40,3) -> 0 | AY23: PASTI | AZ23: =IF(AX8="zero","\I:",$BA$45&"_"&VLOOKUP(C23,'TRA balance'!$BB$5:$BC$15,2,FALSE)) -> Trd_3w_gsl | BA23: =IF($AZ23="","",$BA$45) -> Trd_3w | BB23: =IF($AZ23="","",25) -> 25 | BD23: =IF(AZ23="","*","DMD") -> DMD | BE23: =AZ23 -> Trd_3w_gsl | BG23: Bvkm | BH23: million Vehicles | BI23: yes
C24: =C9 -> TRALPG | D24: =ROUND(D9*D33/D41,3) -> 0 | E24: =ROUND(E9*E33/E41,3) -> 0 | F24: =ROUND(F9*F33/F41,3) -> 0 | G24: =ROUND(G9*G33/G41,3) -> 0 | H24: =ROUND(H9*H33/H41,3) -> 0 | I24: =ROUND(I9*I33/I41,3) -> 0 | J24: =ROUND(J9*J33/J41,3) -> 0 | K24: =ROUND(K9*K33/K41,3) -> 0 | ... AW24: =ROUND(AW9*AW33/AW41,3) -> 0 | AY24: PASTI | AZ24: =IF(AX9="zero","\I:",$BA$45&"_"&VLOOKUP(C24,'TRA balance'!$BB$5:$BC$15,2,FALSE)) -> \I: | BA24: =IF($AZ24="","",$BA$45) -> Trd_3w | BB24: =IF($AZ24="","",25) -> 25 | BD24: =IF(AZ24="","*","DMD") -> DMD | BE24: =AZ24 -> \I: | BG24: Bvkm | BH24: million Vehicles | BI24: yes
C25: =C10 -> TRANGA | D25: =ROUND(D10*D34/D42,3) -> 0 | E25: =ROUND(E10*E34/E42,3) -> 0 | F25: =ROUND(F10*F34/F42,3) -> 0 | G25: =ROUND(G10*G34/G42,3) -> 0 | H25: =ROUND(H10*H34/H42,3) -> 0 | I25: =ROUND(I10*I34/I42,3) -> 0 | J25: =ROUND(J10*J34/J42,3) -> 0 | K25: =ROUND(K10*K34/K42,3) -> 0 | ... AW25: =ROUND(AW10*AW34/AW42,3) -> 0 | AY25: PASTI | AZ25: =IF(AX10="zero","\I:",$BA$45&"_"&VLOOKUP(C25,'TRA balance'!$BB$5:$BC$15,2,FALSE)) -> \I: | BA25: =IF($AZ25="","",$BA$45) -> Trd_3w | BB25: =IF($AZ25="","",25) -> 25 | BD25: =IF(AZ25="","*","DMD") -> DMD | BE25: =AZ25 -> \I: | BG25: Bvkm | BH25: million Vehicles | BI25: yes
AY26: * | BA26: =IF($AZ26="","",$BA$45) | BB26: =IF($AZ26="","",25) | BD26: =IF(AZ26="","*","DMD") -> * | BE26: =AZ26 -> 0 | BG26: Bvkm | BH26: million Vehicles | BI26: yes
D27: 1 | E27: 1 | F27: 1 | G27: 1 | H27: 1 | I27: 1 | J27: 1 | K27: 1 | L27: 1 | M27: 1 | N27: 1 | O27: 1 | P27: 1 | Q27: 1 | R27: 1 | S27: 1 | T27: 1 | U27: 1 | V27: 1 | W27: 1 | X27: 1 | Y27: 1 | Z27: 1 | AA27: 1 | AB27: 1 | AC27: 1 | AD27: 1 | AE27: 1 | AF27: 1 | AG27: 1 | AH27: 1 | AI27: 1 | AJ27: 1 | AK27: 1 | AL27: 1 | AM27: 1 | AN27: 1 | AO27: 1 | AP27: 1 | AQ27: 1 | AR27: 1 | AS27: 1 | AT27: 1 | AU27: 1 | AV27: 1 | AW27: 1 | AY27: * | BA27: =IF($AZ27="","",$BA$45) | BB27: =IF($AZ27="","",25) | BD27: =IF(AZ27="","*","DMD") -> * | BE27: =AZ27 -> 0 | BG27: Bvkm | BH27: million Vehicles | BI27: yes
A28: Efficiency | C28: =C19 -> TRABDS | D28: =$AX28*D$27 -> 0.58697 | E28: =$AX28*E$27 -> 0.58697 | F28: =$AX28*F$27 -> 0.58697 | G28: =$AX28*G$27 -> 0.58697 | H28: =$AX28*H$27 -> 0.58697 | I28: =$AX28*I$27 -> 0.58697 | J28: =$AX28*J$27 -> 0.58697 | K28: =$AX28*K$27 -> 0.58697 | ... AW28: =$AX28*AW$27 -> 0.58697 | AX28: 0.58697 | AY28: EFF | AZ28: =AZ19 -> Trd_3w_bdl | BA28: =IF($AZ28="","",$BA$45) -> Trd_3w | BB28: =IF($AZ28="","",25) -> 25 | BD28: =IF(AZ28="","*","DMD") -> DMD | BE28: =AZ28 -> Trd_3w_bdl | BG28: Bvkm | BH28: million Vehicles | BI28: yes
C29: =C20 -> TRABGS | D29: =$AX29*D$27 -> 0.58697 | E29: =$AX29*E$27 -> 0.58697 | F29: =$AX29*F$27 -> 0.58697 | G29: =$AX29*G$27 -> 0.58697 | H29: =$AX29*H$27 -> 0.58697 | I29: =$AX29*I$27 -> 0.58697 | J29: =$AX29*J$27 -> 0.58697 | K29: =$AX29*K$27 -> 0.58697 | ... AW29: =$AX29*AW$27 -> 0.58697 | AX29: 0.58697 | AY29: EFF | AZ29: =AZ20 -> \I: | BA29: =IF($AZ29="","",$BA$45) -> Trd_3w | BB29: =IF($AZ29="","",25) -> 25 | BD29: =IF(AZ29="","*","DMD") -> DMD | BE29: =AZ29 -> \I: | BG29: Bvkm | BH29: million Vehicles | BI29: yes
C30: =C21 -> TRADST | D30: =$AX30*D$27 -> 0.58697 | E30: =$AX30*E$27 -> 0.58697 | F30: =$AX30*F$27 -> 0.58697 | G30: =$AX30*G$27 -> 0.58697 | H30: =$AX30*H$27 -> 0.58697 | I30: =$AX30*I$27 -> 0.58697 | J30: =$AX30*J$27 -> 0.58697 | K30: =$AX30*K$27 -> 0.58697 | ... AW30: =$AX30*AW$27 -> 0.58697 | AX30: 0.58697 | AY30: EFF | AZ30: =AZ21 -> Trd_3w_dsl | BA30: =IF($AZ30="","",$BA$45) -> Trd_3w | BB30: =IF($AZ30="","",25) -> 25 | BD30: =IF(AZ30="","*","DMD") -> DMD | BE30: =AZ30 -> Trd_3w_dsl | BG30: Bvkm | BH30: million Vehicles | BI30: yes
C31: =C22 -> TRAELC | D31: =$AX31*D$27 -> 0.58697 | E31: =$AX31*E$27 -> 0.58697 | F31: =$AX31*F$27 -> 0.58697 | G31: =$AX31*G$27 -> 0.58697 | H31: =$AX31*H$27 -> 0.58697 | I31: =$AX31*I$27 -> 0.58697 | J31: =$AX31*J$27 -> 0.58697 | K31: =$AX31*K$27 -> 0.58697 | ... AW31: =$AX31*AW$27 -> 0.58697 | AX31: 0.58697 | AY31: EFF | AZ31: =AZ22 -> \I: | BA31: =IF($AZ31="","",$BA$45) -> Trd_3w | BB31: =IF($AZ31="","",25) -> 25 | BD31: =IF(AZ31="","*","DMD") -> DMD | BE31: =AZ31 -> \I: | BG31: Bvkm | BH31: million Vehicles | BI31: yes
C32: =C23 -> TRAGSL | D32: =$AX32*D$27 -> 0.58697 | E32: =$AX32*E$27 -> 0.58697 | F32: =$AX32*F$27 -> 0.58697 | G32: =$AX32*G$27 -> 0.58697 | H32: =$AX32*H$27 -> 0.58697 | I32: =$AX32*I$27 -> 0.58697 | J32: =$AX32*J$27 -> 0.58697 | K32: =$AX32*K$27 -> 0.58697 | ... AW32: =$AX32*AW$27 -> 0.58697 | AX32: 0.58697 | AY32: EFF | AZ32: =AZ23 -> Trd_3w_gsl | BA32: =IF($AZ32="","",$BA$45) -> Trd_3w | BB32: =IF($AZ32="","",25) -> 25 | BD32: =IF(AZ32="","*","DMD") -> DMD | BE32: =AZ32 -> Trd_3w_gsl | BG32: Bvkm | BH32: million Vehicles | BI32: yes
C33: =C24 -> TRALPG | D33: =$AX33*D$27 -> 0.58697 | E33: =$AX33*E$27 -> 0.58697 | F33: =$AX33*F$27 -> 0.58697 | G33: =$AX33*G$27 -> 0.58697 | H33: =$AX33*H$27 -> 0.58697 | I33: =$AX33*I$27 -> 0.58697 | J33: =$AX33*J$27 -> 0.58697 | K33: =$AX33*K$27 -> 0.58697 | ... AW33: =$AX33*AW$27 -> 0.58697 | AX33: 0.58697 | AY33: EFF | AZ33: =AZ24 -> \I: | BA33: =IF($AZ33="","",$BA$45) -> Trd_3w | BB33: =IF($AZ33="","",25) -> 25 | BD33: =IF(AZ33="","*","DMD") -> DMD | BE33: =AZ33 -> \I: | BG33: Bvkm | BH33: million Vehicles | BI33: yes
C34: =C25 -> TRANGA | D34: =$AX34*D$27 -> 0.58697 | E34: =$AX34*E$27 -> 0.58697 | F34: =$AX34*F$27 -> 0.58697 | G34: =$AX34*G$27 -> 0.58697 | H34: =$AX34*H$27 -> 0.58697 | I34: =$AX34*I$27 -> 0.58697 | J34: =$AX34*J$27 -> 0.58697 | K34: =$AX34*K$27 -> 0.58697 | ... AW34: =$AX34*AW$27 -> 0.58697 | AX34: 0.58697 | AY34: EFF | AZ34: =AZ25 -> \I: | BA34: =IF($AZ34="","",$BA$45) -> Trd_3w | BB34: =IF($AZ34="","",25) -> 25 | BD34: =IF(AZ34="","*","DMD") -> DMD | BE34: =AZ34 -> \I: | BG34: Bvkm | BH34: million Vehicles | BI34: yes
AY35: * | BA35: =IF($AZ35="","",$BA$45) | BB35: =IF($AZ35="","",25) | BD35: =IF(AZ35="","*","DMD") -> * | BE35: =AZ35 -> 0 | BG35: Bvkm | BH35: million Vehicles | BI35: yes
A36: 000km/veh | C36: =C28 -> TRABDS | D36: 15 | E36: 15 | F36: 15 | G36: 15 | H36: 15 | I36: 15 | J36: 15 | K36: 15 | L36: 15 | M36: 15 | N36: 15 | O36: 15 | P36: 15 | Q36: 15 | R36: 15 | S36: 15 | T36: 15 | U36: 15 | V36: 15 | W36: 15 | X36: 15 | Y36: 15 | Z36: 15 | AA36: 15 | AB36: 15 | AC36: 15 | AD36: 15 | AE36: 15 | AF36: 20 | AG36: 15 | AH36: 15 | AI36: 15 | AJ36: 15 | AK36: 15 | AL36: 15 | AM36: 15 | AN36: 15 | AO36: 15 | AP36: 15 | AQ36: 15 | AR36: 15 | AS36: 15 | AT36: 15 | AU36: 15 | AV36: 15 | AW36: 15 | AY36: AF | AZ36: =AZ28 -> Trd_3w_bdl | BA36: =IF($AZ36="","",$BA$45) -> Trd_3w | BB36: =IF($AZ36="","",25) -> 25 | BD36: =IF(AZ36="","*","DMD") -> DMD | BE36: =AZ36 -> Trd_3w_bdl | BG36: Bvkm | BH36: million Vehicles | BI36: yes
C37: =C29 -> TRABGS | D37: 15 | E37: 15 | F37: 15 | G37: 15 | H37: 15 | I37: 15 | J37: 15 | K37: 15 | L37: 15 | M37: 15 | N37: 15 | O37: 15 | P37: 15 | Q37: 15 | R37: 15 | S37: 15 | T37: 15 | U37: 15 | V37: 15 | W37: 15 | X37: 15 | Y37: 15 | Z37: 15 | AA37: 15 | AB37: 15 | AC37: 15 | AD37: 15 | AE37: 15 | AF37: 20 | AG37: 15 | AH37: 15 | AI37: 15 | AJ37: 15 | AK37: 15 | AL37: 15 | AM37: 15 | AN37: 15 | AO37: 15 | AP37: 15 | AQ37: 15 | AR37: 15 | AS37: 15 | AT37: 15 | AU37: 15 | AV37: 15 | AW37: 15 | AY37: AF | AZ37: =AZ29 -> \I: | BA37: =IF($AZ37="","",$BA$45) -> Trd_3w | BB37: =IF($AZ37="","",25) -> 25 | BD37: =IF(AZ37="","*","DMD") -> DMD | BE37: =AZ37 -> \I: | BG37: Bvkm | BH37: million Vehicles | BI37: yes
C38: =C30 -> TRADST | D38: 15 | E38: 15 | F38: 15 | G38: 15 | H38: 15 | I38: 15 | J38: 15 | K38: 15 | L38: 15 | M38: 15 | N38: 15 | O38: 15 | P38: 15 | Q38: 15 | R38: 15 | S38: 15 | T38: 15 | U38: 15 | V38: 15 | W38: 15 | X38: 15 | Y38: 15 | Z38: 15 | AA38: 15 | AB38: 15 | AC38: 15 | AD38: 15 | AE38: 15 | AF38: 20 | AG38: 15 | AH38: 15 | AI38: 15 | AJ38: 15 | AK38: 15 | AL38: 15 | AM38: 15 | AN38: 15 | AO38: 15 | AP38: 15 | AQ38: 15 | AR38: 15 | AS38: 15 | AT38: 15 | AU38: 15 | AV38: 15 | AW38: 15 | AY38: AF | AZ38: =AZ30 -> Trd_3w_dsl | BA38: =IF($AZ38="","",$BA$45) -> Trd_3w | BB38: =IF($AZ38="","",25) -> 25 | BD38: =IF(AZ38="","*","DMD") -> DMD | BE38: =AZ38 -> Trd_3w_dsl | BG38: Bvkm | BH38: million Vehicles | BI38: yes
C39: =C31 -> TRAELC | D39: 15 | E39: 15 | F39: 15 | G39: 15 | H39: 15 | I39: 15 | J39: 15 | K39: 15 | L39: 15 | M39: 15 | N39: 15 | O39: 15 | P39: 15 | Q39: 15 | R39: 15 | S39: 15 | T39: 15 | U39: 15 | V39: 15 | W39: 15 | X39: 15 | Y39: 15 | Z39: 15 | AA39: 15 | AB39: 15 | AC39: 15 | AD39: 15 | AE39: 15 | AF39: 20 | AG39: 15 | AH39: 15 | AI39: 15 | AJ39: 15 | AK39: 15 | AL39: 15 | AM39: 15 | AN39: 15 | AO39: 15 | AP39: 15 | AQ39: 15 | AR39: 15 | AS39: 15 | AT39: 15 | AU39: 15 | AV39: 15 | AW39: 15 | AY39: AF | AZ39: =AZ31 -> \I: | BA39: =IF($AZ39="","",$BA$45) -> Trd_3w | BB39: =IF($AZ39="","",25) -> 25 | BD39: =IF(AZ39="","*","DMD") -> DMD | BE39: =AZ39 -> \I: | BG39: Bvkm | BH39: million Vehicles | BI39: yes
C40: =C32 -> TRAGSL | D40: 15 | E40: 15 | F40: 15 | G40: 15 | H40: 15 | I40: 15 | J40: 15 | K40: 15 | L40: 15 | M40: 15 | N40: 15 | O40: 15 | P40: 15 | Q40: 15 | R40: 15 | S40: 15 | T40: 15 | U40: 15 | V40: 15 | W40: 15 | X40: 15 | Y40: 15 | Z40: 15 | AA40: 15 | AB40: 15 | AC40: 15 | AD40: 15 | AE40: 15 | AF40: 20 | AG40: 15 | AH40: 15 | AI40: 15 | AJ40: 15 | AK40: 15 | AL40: 15 | AM40: 15 | AN40: 15 | AO40: 15 | AP40: 15 | AQ40: 15 | AR40: 15 | AS40: 15 | AT40: 15 | AU40: 15 | AV40: 15 | AW40: 15 | AY40: AF | AZ40: =AZ32 -> Trd_3w_gsl | BA40: =IF($AZ40="","",$BA$45) -> Trd_3w | BB40: =IF($AZ40="","",25) -> 25 | BD40: =IF(AZ40="","*","DMD") -> DMD | BE40: =AZ40 -> Trd_3w_gsl | BG40: Bvkm | BH40: million Vehicles | BI40: yes
C41: =C33 -> TRALPG | D41: 15 | E41: 15 | F41: 15 | G41: 15 | H41: 15 | I41: 15 | J41: 15 | K41: 15 | L41: 15 | M41: 15 | N41: 15 | O41: 15 | P41: 15 | Q41: 15 | R41: 15 | S41: 15 | T41: 15 | U41: 15 | V41: 15 | W41: 15 | X41: 15 | Y41: 15 | Z41: 15 | AA41: 15 | AB41: 15 | AC41: 15 | AD41: 15 | AE41: 15 | AF41: 20 | AG41: 15 | AH41: 15 | AI41: 15 | AJ41: 15 | AK41: 15 | AL41: 15 | AM41: 15 | AN41: 15 | AO41: 15 | AP41: 15 | AQ41: 15 | AR41: 15 | AS41: 15 | AT41: 15 | AU41: 15 | AV41: 15 | AW41: 15 | AY41: AF | AZ41: =AZ33 -> \I: | BA41: =IF($AZ41="","",$BA$45) -> Trd_3w | BB41: =IF($AZ41="","",25) -> 25 | BD41: =IF(AZ41="","*","DMD") -> DMD | BE41: =AZ41 -> \I: | BG41: Bvkm | BH41: million Vehicles | BI41: yes
C42: =C34 -> TRANGA | D42: 15 | E42: 15 | F42: 15 | G42: 15 | H42: 15 | I42: 15 | J42: 15 | K42: 15 | L42: 15 | M42: 15 | N42: 15 | O42: 15 | P42: 15 | Q42: 15 | R42: 15 | S42: 15 | T42: 15 | U42: 15 | V42: 15 | W42: 15 | X42: 15 | Y42: 15 | Z42: 15 | AA42: 15 | AB42: 15 | AC42: 15 | AD42: 15 | AE42: 15 | AF42: 20 | AG42: 15 | AH42: 15 | AI42: 15 | AJ42: 15 | AK42: 15 | AL42: 15 | AM42: 15 | AN42: 15 | AO42: 15 | AP42: 15 | AQ42: 15 | AR42: 15 | AS42: 15 | AT42: 15 | AU42: 15 | AV42: 15 | AW42: 15 | AY42: AF | AZ42: =AZ34 -> \I: | BA42: =IF($AZ42="","",$BA$45) -> Trd_3w | BB42: =IF($AZ42="","",25) -> 25 | BD42: =IF(AZ42="","*","DMD") -> DMD | BE42: =AZ42 -> \I: | BG42: Bvkm | BH42: million Vehicles | BI42: yes
AY43: * | BB43: =IF($AZ43="","",25)
D44: =D3 -> Africa_North | E44: =E3 -> Africa_Other | F44: =F3 -> Australia | G44: =G3 -> Austria | H44: =H3 -> Baltics | I44: =I3 -> BeNeLux | J44: =J3 -> Brazil | K44: =K3 -> China | ... AW44: =AW3 -> \I: | AY44: * | BB44: =IF($AZ44="","",25)
A45: Dem Bvkm | AY45: Demand | BA45: Trd_3w | BB45: =IF($AZ45="","",25)
AY46: *
AY48: ~FI_Comm
AY49: CSet | AZ49: CommName | BA49: CommDesc | BB49: Unit
AY50: DEM | AZ50: =BA45 -> Trd_3w | BB50: Bvkm

Sheet Cars
AY2: ~FI_T | BD2: ~FI_Process
C3: comm-in | D3: ='TRA balance'!E4 -> Africa_North | E3: ='TRA balance'!F4 -> Africa_Other | F3: ='TRA balance'!G4 -> Australia | G3: ='TRA balance'!H4 -> Austria | H3: ='TRA balance'!I4 -> Baltics | I3: ='TRA balance'!J4 -> BeNeLux | J3: ='TRA balance'!K4 -> Brazil | K3: ='TRA balance'!L4 -> China | ... AW3: ='TRA balance'!AX4 -> \I: | AX3: * | AY3: attribute | AZ3: process | BA3: comm-out | BB3: LIFE | BD3: Sets | BE3: TechName | BF3: TechDesc | BG3: Tact | BH3: Tcap | BI3: Vintage
A4: TR | C4: TRABDS | D4: {=SUM(SUMIFS(Assumptions!BD$3:BD$102,Assumptions!$B$3:$B$102,Cars!$C4,Assumptions!$G$3:$G$102,{"TRL","TRT"}))} -> 0 | E4: {=SUM(SUMIFS(Assumptions!BE$3:BE$102,Assumptions!$B$3:$B$102,Cars!$C4,Assumptions!$G$3:$G$102,{"TRL","TRT"}))} -> 0 | F4: {=SUM(SUMIFS(Assumptions!BF$3:BF$102,Assumptions!$B$3:$B$102,Cars!$C4,Assumptions!$G$3:$G$102,{"TRL","TRT"}))} -> 0.00073603944 | G4: {=SUM(SUMIFS(Assumptions!BG$3:BG$102,Assumptions!$B$3:$B$102,Cars!$C4,Assumptions!$G$3:$G$102,{"TRL","TRT"}))} -> 3.5648961 | H4: {=SUM(SUMIFS(Assumptions!BH$3:BH$102,Assumptions!$B$3:$B$102,Cars!$C4,Assumptions!$G$3:$G$102,{"TRL","TRT"}))} -> 0.22916701 | I4: {=SUM(SUMIFS(Assumptions!BI$3:BI$102,Assumptions!$B$3:$B$102,Cars!$C4,Assumptions!$G$3:$G$102,{"TRL","TRT"}))} -> 7.3859816 | J4: {=SUM(SUMIFS(Assumptions!BJ$3:BJ$102,Assumptions!$B$3:$B$102,Cars!$C4,Assumptions!$G$3:$G$102,{"TRL","TRT"}))} -> 45.116374 | K4: {=SUM(SUMIFS(Assumptions!BK$3:BK$102,Assumptions!$B$3:$B$102,Cars!$C4,Assumptions!$G$3:$G$102,{"TRL","TRT"}))} -> 1.51616 | ... AW4: {=SUM(SUMIFS(Assumptions!CW$3:CW$102,Assumptions!$B$3:$B$102,Cars!$C4,Assumptions!$G$3:$G$102,{"TRL","TRT"}))} -> 0 | AY4: * | BA4: =IF($AZ4="","",$BA$45) | BB4: =IF($AZ4="","",25) | BD4: =IF($AZ4="","*","DMD") -> * | BE4: =AZ4 -> 0 | BG4: Bvkm | BH4: million Vehicles | BI4: yes
A5: TR | C5: TRABGS | D5: {=SUM(SUMIFS(Assumptions!BD$3:BD$102,Assumptions!$B$3:$B$102,Cars!$C5,Assumptions!$G$3:$G$102,{"TRL","TRT"}))} -> 0 | E5: {=SUM(SUMIFS(Assumptions!BE$3:BE$102,Assumptions!$B$3:$B$102,Cars!$C5,Assumptions!$G$3:$G$102,{"TRL","TRT"}))} -> 0 | F5: {=SUM(SUMIFS(Assumptions!BF$3:BF$102,Assumptions!$B$3:$B$102,Cars!$C5,Assumptions!$G$3:$G$102,{"TRL","TRT"}))} -> 0 | G5: {=SUM(SUMIFS(Assumptions!BG$3:BG$102,Assumptions!$B$3:$B$102,Cars!$C5,Assumptions!$G$3:$G$102,{"TRL","TRT"}))} -> 0 | H5: {=SUM(SUMIFS(Assumptions!BH$3:BH$102,Assumptions!$B$3:$B$102,Cars!$C5,Assumptions!$G$3:$G$102,{"TRL","TRT"}))} -> 0 | I5: {=SUM(SUMIFS(Assumptions!BI$3:BI$102,Assumptions!$B$3:$B$102,Cars!$C5,Assumptions!$G$3:$G$102,{"TRL","TRT"}))} -> 0 | J5: {=SUM(SUMIFS(Assumptions!BJ$3:BJ$102,Assumptions!$B$3:$B$102,Cars!$C5,Assumptions!$G$3:$G$102,{"TRL","TRT"}))} -> 0 | K5: {=SUM(SUMIFS(Assumptions!BK$3:BK$102,Assumptions!$B$3:$B$102,Cars!$C5,Assumptions!$G$3:$G$102,{"TRL","TRT"}))} -> 0 | ... AW5: {=SUM(SUMIFS(Assumptions!CW$3:CW$102,Assumptions!$B$3:$B$102,Cars!$C5,Assumptions!$G$3:$G$102,{"TRL","TRT"}))} -> 0 | AY5: * | BA5: =IF($AZ5="","",$BA$45) | BB5: =IF($AZ5="","",25) | BD5: =IF(AZ5="","*","DMD") -> * | BE5: =AZ5 -> 0 | BG5: Bvkm | BH5: million Vehicles | BI5: yes
A6: TR | C6: TRADST | D6: {=SUM(SUMIFS(Assumptions!BD$3:BD$102,Assumptions!$B$3:$B$102,Cars!$C6,Assumptions!$G$3:$G$102,{"TRL","TRT"}))} -> 111.20205 | E6: {=SUM(SUMIFS(Assumptions!BE$3:BE$102,Assumptions!$B$3:$B$102,Cars!$C6,Assumptions!$G$3:$G$102,{"TRL","TRT"}))} -> 98.822762 | F6: {=SUM(SUMIFS(Assumptions!BF$3:BF$102,Assumptions!$B$3:$B$102,Cars!$C6,Assumptions!$G$3:$G$102,{"TRL","TRT"}))} -> 11.512758 | G6: {=SUM(SUMIFS(Assumptions!BG$3:BG$102,Assumptions!$B$3:$B$102,Cars!$C6,Assumptions!$G$3:$G$102,{"TRL","TRT"}))} -> 51.730109 | H6: {=SUM(SUMIFS(Assumptions!BH$3:BH$102,Assumptions!$B$3:$B$102,Cars!$C6,Assumptions!$G$3:$G$102,{"TRL","TRT"}))} -> 6.0635027 | I6: {=SUM(SUMIFS(Assumptions!BI$3:BI$102,Assumptions!$B$3:$B$102,Cars!$C6,Assumptions!$G$3:$G$102,{"TRL","TRT"}))} -> 109.64644 | J6: {=SUM(SUMIFS(Assumptions!BJ$3:BJ$102,Assumptions!$B$3:$B$102,Cars!$C6,Assumptions!$G$3:$G$102,{"TRL","TRT"}))} -> 99.51422 | K6: {=SUM(SUMIFS(Assumptions!BK$3:BK$102,Assumptions!$B$3:$B$102,Cars!$C6,Assumptions!$G$3:$G$102,{"TRL","TRT"}))} -> 155.25486 | ... AW6: {=SUM(SUMIFS(Assumptions!CW$3:CW$102,Assumptions!$B$3:$B$102,Cars!$C6,Assumptions!$G$3:$G$102,{"TRL","TRT"}))} -> 0 | AY6: * | BA6: =IF($AZ6="","",$BA$45) | BB6: =IF($AZ6="","",25) | BD6: =IF(AZ6="","*","DMD") -> * | BE6: =AZ6 -> 0 | BG6: Bvkm | BH6: million Vehicles | BI6: yes
A7: TR | C7: TRAELC | D7: {=SUM(SUMIFS(Assumptions!BD$3:BD$102,Assumptions!$B$3:$B$102,Cars!$C7,Assumptions!$G$3:$G$102,{"TRL","TRT"}))} -> 0 | E7: {=SUM(SUMIFS(Assumptions!BE$3:BE$102,Assumptions!$B$3:$B$102,Cars!$C7,Assumptions!$G$3:$G$102,{"TRL","TRT"}))} -> 0 | F7: {=SUM(SUMIFS(Assumptions!BF$3:BF$102,Assumptions!$B$3:$B$102,Cars!$C7,Assumptions!$G$3:$G$102,{"TRL","TRT"}))} -> 0.021599701 | G7: {=SUM(SUMIFS(Assumptions!BG$3:BG$102,Assumptions!$B$3:$B$102,Cars!$C7,Assumptions!$G$3:$G$102,{"TRL","TRT"}))} -> 0.012838822 | H7: {=SUM(SUMIFS(Assumptions!BH$3:BH$102,Assumptions!$B$3:$B$102,Cars!$C7,Assumptions!$G$3:$G$102,{"TRL","TRT"}))} -> 0 | I7: {=SUM(SUMIFS(Assumptions!BI$3:BI$102,Assumptions!$B$3:$B$102,Cars!$C7,Assumptions!$G$3:$G$102,{"TRL","TRT"}))} -> 0.57975666 | J7: {=SUM(SUMIFS(Assumptions!BJ$3:BJ$102,Assumptions!$B$3:$B$102,Cars!$C7,Assumptions!$G$3:$G$102,{"TRL","TRT"}))} -> 0 | K7: {=SUM(SUMIFS(Assumptions!BK$3:BK$102,Assumptions!$B$3:$B$102,Cars!$C7,Assumptions!$G$3:$G$102,{"TRL","TRT"}))} -> 49.072603 | ... AW7: {=SUM(SUMIFS(Assumptions!CW$3:CW$102,Assumptions!$B$3:$B$102,Cars!$C7,Assumptions!$G$3:$G$102,{"TRL","TRT"}))} -> 0 | AY7: * | BA7: =IF($AZ7="","",$BA$45) | BB7: =IF($AZ7="","",25) | BD7: =IF(AZ7="","*","DMD") -> * | BE7: =AZ7 -> 0 | BG7: Bvkm | BH7: million Vehicles | BI7: yes
A8: TR | C8: TRAGSL | D8: {=SUM(SUMIFS(Assumptions!BD$3:BD$102,Assumptions!$B$3:$B$102,Cars!$C8,Assumptions!$G$3:$G$102,{"TRL","TRT"}))} -> 393.61866 | E8: {=SUM(SUMIFS(Assumptions!BE$3:BE$102,Assumptions!$B$3:$B$102,Cars!$C8,Assumptions!$G$3:$G$102,{"TRL","TRT"}))} -> 683.5137 | F8: {=SUM(SUMIFS(Assumptions!BF$3:BF$102,Assumptions!$B$3:$B$102,Cars!$C8,Assumptions!$G$3:$G$102,{"TRL","TRT"}))} -> 501.78906 | G8: {=SUM(SUMIFS(Assumptions!BG$3:BG$102,Assumptions!$B$3:$B$102,Cars!$C8,Assumptions!$G$3:$G$102,{"TRL","TRT"}))} -> 66.495177 | H8: {=SUM(SUMIFS(Assumptions!BH$3:BH$102,Assumptions!$B$3:$B$102,Cars!$C8,Assumptions!$G$3:$G$102,{"TRL","TRT"}))} -> 19.836322 | I8: {=SUM(SUMIFS(Assumptions!BI$3:BI$102,Assumptions!$B$3:$B$102,Cars!$C8,Assumptions!$G$3:$G$102,{"TRL","TRT"}))} -> 257.27593 | J8: {=SUM(SUMIFS(Assumptions!BJ$3:BJ$102,Assumptions!$B$3:$B$102,Cars!$C8,Assumptions!$G$3:$G$102,{"TRL","TRT"}))} -> 792.19638 | K8: {=SUM(SUMIFS(Assumptions!BK$3:BK$102,Assumptions!$B$3:$B$102,Cars!$C8,Assumptions!$G$3:$G$102,{"TRL","TRT"}))} -> 4861.5347 | ... AW8: {=SUM(SUMIFS(Assumptions!CW$3:CW$102,Assumptions!$B$3:$B$102,Cars!$C8,Assumptions!$G$3:$G$102,{"TRL","TRT"}))} -> 0 | AY8: * | BA8: =IF($AZ8="","",$BA$45) | BB8: =IF($AZ8="","",25) | BD8: =IF(AZ8="","*","DMD") -> * | BE8: =AZ8 -> 0 | BG8: Bvkm | BH8: million Vehicles | BI8: yes
A9: TR | C9: TRALPG | D9: {=SUM(SUMIFS(Assumptions!BD$3:BD$102,Assumptions!$B$3:$B$102,Cars!$C9,Assumptions!$G$3:$G$102,{"TRL","TRT"}))} -> 25.763995 | E9: {=SUM(SUMIFS(Assumptions!BE$3:BE$102,Assumptions!$B$3:$B$102,Cars!$C9,Assumptions!$G$3:$G$102,{"TRL","TRT"}))} -> 0.014786103 | F9: {=SUM(SUMIFS(Assumptions!BF$3:BF$102,Assumptions!$B$3:$B$102,Cars!$C9,Assumptions!$G$3:$G$102,{"TRL","TRT"}))} -> 3.8019399 | G9: {=SUM(SUMIFS(Assumptions!BG$3:BG$102,Assumptions!$B$3:$B$102,Cars!$C9,Assumptions!$G$3:$G$102,{"TRL","TRT"}))} -> 0.16453182 | H9: {=SUM(SUMIFS(Assumptions!BH$3:BH$102,Assumptions!$B$3:$B$102,Cars!$C9,Assumptions!$G$3:$G$102,{"TRL","TRT"}))} -> 3.9434082 | I9: {=SUM(SUMIFS(Assumptions!BI$3:BI$102,Assumptions!$B$3:$B$102,Cars!$C9,Assumptions!$G$3:$G$102,{"TRL","TRT"}))} -> 6.1417247 | J9: {=SUM(SUMIFS(Assumptions!BJ$3:BJ$102,Assumptions!$B$3:$B$102,Cars!$C9,Assumptions!$G$3:$G$102,{"TRL","TRT"}))} -> 0 | K9: {=SUM(SUMIFS(Assumptions!BK$3:BK$102,Assumptions!$B$3:$B$102,Cars!$C9,Assumptions!$G$3:$G$102,{"TRL","TRT"}))} -> 31.320863 | ... AW9: {=SUM(SUMIFS(Assumptions!CW$3:CW$102,Assumptions!$B$3:$B$102,Cars!$C9,Assumptions!$G$3:$G$102,{"TRL","TRT"}))} -> 0 | AY9: * | BA9: =IF($AZ9="","",$BA$45) | BB9: =IF($AZ9="","",25) | BD9: =IF(AZ9="","*","DMD") -> * | BE9: =AZ9 -> 0 | BG9: Bvkm | BH9: million Vehicles | BI9: yes
A10: TR | C10: TRANGA | D10: {=SUM(SUMIFS(Assumptions!BD$3:BD$102,Assumptions!$B$3:$B$102,Cars!$C10,Assumptions!$G$3:$G$102,{"TRL","TRT"}))} -> 5.0870133 | E10: {=SUM(SUMIFS(Assumptions!BE$3:BE$102,Assumptions!$B$3:$B$102,Cars!$C10,Assumptions!$G$3:$G$102,{"TRL","TRT"}))} -> 0.018672081 | F10: {=SUM(SUMIFS(Assumptions!BF$3:BF$102,Assumptions!$B$3:$B$102,Cars!$C10,Assumptions!$G$3:$G$102,{"TRL","TRT"}))} -> 0.78086332 | G10: {=SUM(SUMIFS(Assumptions!BG$3:BG$102,Assumptions!$B$3:$B$102,Cars!$C10,Assumptions!$G$3:$G$102,{"TRL","TRT"}))} -> 0.53467891 | H10: {=SUM(SUMIFS(Assumptions!BH$3:BH$102,Assumptions!$B$3:$B$102,Cars!$C10,Assumptions!$G$3:$G$102,{"TRL","TRT"}))} -> 0.56297555 | I10: {=SUM(SUMIFS(Assumptions!BI$3:BI$102,Assumptions!$B$3:$B$102,Cars!$C10,Assumptions!$G$3:$G$102,{"TRL","TRT"}))} -> 2.6167577 | J10: {=SUM(SUMIFS(Assumptions!BJ$3:BJ$102,Assumptions!$B$3:$B$102,Cars!$C10,Assumptions!$G$3:$G$102,{"TRL","TRT"}))} -> 42.086534 | K10: {=SUM(SUMIFS(Assumptions!BK$3:BK$102,Assumptions!$B$3:$B$102,Cars!$C10,Assumptions!$G$3:$G$102,{"TRL","TRT"}))} -> 411.33613 | ... AW10: {=SUM(SUMIFS(Assumptions!CW$3:CW$102,Assumptions!$B$3:$B$102,Cars!$C10,Assumptions!$G$3:$G$102,{"TRL","TRT"}))} -> 0 | AY10: * | BA10: =IF($AZ10="","",$BA$45) | BB10: =IF($AZ10="","",25) | BD10: =IF(AZ10="","*","DMD") -> * | BE10: =AZ10 -> 0 | BG10: Bvkm | BH10: million Vehicles | BI10: yes
A11: Share of PJ | D11: =SUM(D$4:D$10)/SUM($D$4:$AJ$10) -> 0.013202975 | E11: =SUM(E$4:E$10)/SUM($D$4:$AJ$10) -> 0.019283471 | F11: =SUM(F$4:F$10)/SUM($D$4:$AJ$10) -> 0.012765117 | G11: =SUM(G$4:G$10)/SUM($D$4:$AJ$10) -> 0.0030193751 | H11: =SUM(H$4:H$10)/SUM($D$4:$AJ$10) -> 0.00075508574 | I11: =SUM(I$4:I$10)/SUM($D$4:$AJ$10) -> 0.0094559335 | J11: =SUM(J$4:J$10)/SUM($D$4:$AJ$10) -> 0.024127782 | K11: =SUM(K$4:K$10)/SUM($D$4:$AJ$10) -> 0.13580866 | ... AW11: =SUM(AW$4:AW$10)/SUM($D$4:$AJ$10) -> 0 | AY11: * | BA11: =IF($AZ11="","",$BA$45) | BB11: =IF($AZ11="","",25) | BD11: =IF(AZ11="","*","DMD") -> * | BE11: =AZ11 -> 0 | BG11: Bvkm | BH11: million Vehicles | BI11: yes
C12: =SUM(D12:AW12) -> 1082.923 | D12: =IFERROR('vehicle population data'!G45,"") -> 16.480099 | E12: =IFERROR('vehicle population data'!H45,"") -> 12.648214 | F12: =IFERROR('vehicle population data'!I45,"") -> 14.647347 | G12: =IFERROR('vehicle population data'!J45,"") -> 4.9848656 | H12: =IFERROR('vehicle population data'!K45,"") -> 2.1780474 | I12: =IFERROR('vehicle population data'!L45,"") -> 15.049034 | J12: =IFERROR('vehicle population data'!M45,"") -> 42.624361 | K12: =IFERROR('vehicle population data'!N45,"") -> 194.58406 | ... AW12: =IFERROR('vehicle population data'!AZ45,"") -> 0 | AY12: * | BA12: =IF($AZ12="","",$BA$45) | BB12: =IF($AZ12="","",25) | BD12: =IF(AZ12="","*","DMD") -> * | BE12: =AZ12 -> 0 | BG12: Bvkm | BH12: million Vehicles | BI12: yes
A13: m Vehicles | C13: =SUM(D13:AW13) -> 1360.5603 | D13: =SUM(D19:D25) -> 21.38 | E13: =SUM(E19:E25) -> 30.894 | F13: =SUM(F19:F25) -> 20.188 | G13: =SUM(G19:G25) -> 5.071 | H13: =SUM(H19:H25) -> 1.223 | I13: =SUM(I19:I25) -> 15.636 | J13: =SUM(J19:J25) -> 38.641 | K13: =SUM(K19:K25) -> 320.096 | ... AW13: =SUM(AW19:AW25) -> 0 | AY13: * | BA13: =IF($AZ13="","",$BA$45) | BB13: =IF($AZ13="","",25) | BD13: =IF(AZ13="","*","DMD") -> * | BE13: =AZ13 -> 0 | BG13: Bvkm | BH13: million Vehicles | BI13: yes
A14: Share of Veh | D14: =D13/SUM($D$13:$AW$13) -> 0.015714114 | E14: =E13/SUM($D$13:$AW$13) -> 0.022706822 | F14: =F13/SUM($D$13:$AW$13) -> 0.014838005 | G14: =G13/SUM($D$13:$AW$13) -> 0.0037271409 | H14: =H13/SUM($D$13:$AW$13) -> 0.00089889437 | I14: =I13/SUM($D$13:$AW$13) -> 0.011492324 | J14: =J13/SUM($D$13:$AW$13) -> 0.028400799 | K14: =K13/SUM($D$13:$AW$13) -> 0.23526778 | ... AW14: =AW13/SUM($D$13:$AW$13) -> 0 | AY14: * | BA14: =IF($AZ14="","",$BA$45) | BB14: =IF($AZ14="","",25) | BD14: =IF(AZ14="","*","DMD") -> * | BE14: =AZ14 -> 0 | BG14: Bvkm | BH14: million Vehicles | BI14: yes
D15: =D13/'non-road'!DB21 -> 0.10777022 | E15: =E13/'non-road'!DC21 -> 0.029729869 | F15: =F13/'non-road'!DD21 -> 0.7958779 | G15: =G13/'non-road'!DE21 -> 0.5710637 | H15: =H13/'non-road'!DF21 -> 0.2026559 | I15: =I13/'non-road'!DG21 -> 0.53086347 | J15: =J13/'non-road'!DH21 -> 0.18308932 | K15: =K13/'non-road'!DI21 -> 0.22901296 | ... AW15: =AW13/'non-road'!EU21 -> #VALUE! | AY15: * | BA15: =IF($AZ15="","",$BA$45) | BB15: =IF($AZ15="","",25) | BD15: =IF(AZ15="","*","DMD") -> * | BE15: =AZ15 -> 0 | BG15: Bvkm | BH15: million Vehicles | BI15: yes
AY16: * | BA16: =IF($AZ16="","",$BA$45) | BB16: =IF($AZ16="","",25) | BD16: =IF(AZ16="","*","DMD") -> * | BE16: =AZ16 -> 0 | BG16: Bvkm | BH16: million Vehicles | BI16: yes
A17: PJ share/Veh share | D17: =D11/D14 -> 0.84019847 | E17: =E11/E14 -> 0.84923692 | F17: =F11/F14 -> 0.86029879 | G17: =G11/G14 -> 0.81010489 | H17: =H11/H14 -> 0.8400161 | I17: =I11/I14 -> 0.82280428 | J17: =J11/J14 -> 0.84954586 | K17: =K11/K14 -> 0.57725141 | ... AW17: =AW11/AW14 -> #DIV/0! | AY17: * | BA17: =IF($AZ17="","",$BA$45) | BB17: =IF($AZ17="","",25) | BD17: =IF(AZ17="","*","DMD") -> * | BE17: =AZ17 -> 0 | BG17: Bvkm | BH17: million Vehicles | BI17: yes
AY18: * | BA18: =IF($AZ18="","",$BA$45) | BB18: =IF($AZ18="","",25) | BD18: =IF(AZ18="","*","DMD") -> * | BE18: =AZ18 -> 0 | BG18: Bvkm | BH18: million Vehicles | BI18: yes
A19: mVeh | C19: =C4 -> TRABDS | D19: =ROUND(D4*D28/D36,3) -> 0 | E19: =ROUND(E4*E28/E36,3) -> 0 | F19: =ROUND(F4*F28/F36,3) -> 0 | G19: =ROUND(G4*G28/G36,3) -> 0.157 | H19: =ROUND(H4*H28/H36,3) -> 0.01 | I19: =ROUND(I4*I28/I36,3) -> 0.325 | J19: =ROUND(J4*J28/J36,3) -> 1.984 | K19: =ROUND(K4*K28/K36,3) -> 0.1 | ... AW19: =ROUND(AW4*AW28/AW36,3) -> 0 | AY19: PASTI | AZ19: =IF(AX4="zero","\I:",$BA$45&"_"&VLOOKUP(C19,'TRA balance'!$BB$5:$BC$15,2,FALSE)) -> Trd_car_bdl | BA19: =IF($AZ19="","",$BA$45) -> Trd_car | BB19: =IF($AZ19="","",25) -> 25 | BD19: =IF(AZ19="","*","DMD") -> DMD | BE19: =AZ19 -> Trd_car_bdl | BG19: Bvkm | BH19: million Vehicles | BI19: yes
C20: =C5 -> TRABGS | D20: =ROUND(D5*D29/D37,3) -> 0 | E20: =ROUND(E5*E29/E37,3) -> 0 | F20: =ROUND(F5*F29/F37,3) -> 0 | G20: =ROUND(G5*G29/G37,3) -> 0 | H20: =ROUND(H5*H29/H37,3) -> 0 | I20: =ROUND(I5*I29/I37,3) -> 0 | J20: =ROUND(J5*J29/J37,3) -> 0 | K20: =ROUND(K5*K29/K37,3) -> 0 | ... AW20: =ROUND(AW5*AW29/AW37,3) -> 0 | AY20: PASTI | AZ20: =IF(AX5="zero","\I:",$BA$45&"_"&VLOOKUP(C20,'TRA balance'!$BB$5:$BC$15,2,FALSE)) -> Trd_car_eth | BA20: =IF($AZ20="","",$BA$45) -> Trd_car | BB20: =IF($AZ20="","",25) -> 25 | BD20: =IF(AZ20="","*","DMD") -> DMD | BE20: =AZ20 -> Trd_car_eth | BG20: Bvkm | BH20: million Vehicles | BI20: yes
C21: =C6 -> TRADST | D21: =ROUND(D6*D30/D38,3) -> 4.89 | E21: =ROUND(E6*E30/E38,3) -> 4.346 | F21: =ROUND(F6*F30/F38,3) -> 0.506 | G21: =ROUND(G6*G30/G38,3) -> 2.275 | H21: =ROUND(H6*H30/H38,3) -> 0.267 | I21: =ROUND(I6*I30/I38,3) -> 4.822 | J21: =ROUND(J6*J30/J38,3) -> 4.376 | K21: =ROUND(K6*K30/K38,3) -> 10.241 | ... AW21: =ROUND(AW6*AW30/AW38,3) -> 0 | AY21: PASTI | AZ21: =IF(AX6="zero","\I:",$BA$45&"_"&VLOOKUP(C21,'TRA balance'!$BB$5:$BC$15,2,FALSE)) -> Trd_car_dsl | BA21: =IF($AZ21="","",$BA$45) -> Trd_car | BB21: =IF($AZ21="","",25) -> 25 | BD21: =IF(AZ21="","*","DMD") -> DMD | BE21: =AZ21 -> Trd_car_dsl | BG21: Bvkm | BH21: million Vehicles | BI21: yes
A22: calibrated to estimated stock in 2018 | C22: =C7 -> TRAELC | D22: =SUMIFS('EV data'!$D$2:$D$145,'EV data'!$C$2:$C$145,2018,'EV data'!$B$2:$B$145,Cars!D$3) -> 0 | E22: =SUMIFS('EV data'!$D$2:$D$145,'EV data'!$C$2:$C$145,2018,'EV data'!$B$2:$B$145,Cars!E$3) -> 0 | F22: =SUMIFS('EV data'!$D$2:$D$145,'EV data'!$C$2:$C$145,2018,'EV data'!$B$2:$B$145,Cars!F$3) -> 0.015 | G22: =SUMIFS('EV data'!$D$2:$D$145,'EV data'!$C$2:$C$145,2018,'EV data'!$B$2:$B$145,Cars!G$3) -> 0.03 | H22: =SUMIFS('EV data'!$D$2:$D$145,'EV data'!$C$2:$C$145,2018,'EV data'!$B$2:$B$145,Cars!H$3) -> 0 | I22: =SUMIFS('EV data'!$D$2:$D$145,'EV data'!$C$2:$C$145,2018,'EV data'!$B$2:$B$145,Cars!I$3) -> 0.16 | J22: =SUMIFS('EV data'!$D$2:$D$145,'EV data'!$C$2:$C$145,2018,'EV data'!$B$2:$B$145,Cars!J$3) -> 0.008 | K22: =SUMIFS('EV data'!$D$2:$D$145,'EV data'!$C$2:$C$145,2018,'EV data'!$B$2:$B$145,Cars!K$3) -> 2.6 | ... AL22: =SUMIFS('EV data'!$D$2:$D$145,'EV data'!$C$2:$C$145,2018,'EV data'!$B$2:$B$145,Cars!AL$3) -> 0 | AM22: =ROUND(AM7*AM31/AM39,3) -> 0 | AN22: =ROUND(AN7*AN31/AN39,3) -> 0 | AO22: =ROUND(AO7*AO31/AO39,3) -> 0 | AP22: =ROUND(AP7*AP31/AP39,3) -> 0 | AQ22: =ROUND(AQ7*AQ31/AQ39,3) -> 0 | AR22: =ROUND(AR7*AR31/AR39,3) -> 0 | AS22: =ROUND(AS7*AS31/AS39,3) -> 0 | AT22: =ROUND(AT7*AT31/AT39,3) -> 0 | ... AW22: =ROUND(AW7*AW31/AW39,3) -> 0 | AY22: PASTI | AZ22: =IF(AX7="zero","\I:",$BA$45&"_"&VLOOKUP(C22,'TRA balance'!$BB$5:$BC$15,2,FALSE)) -> Trd_car_elc | BA22: =IF($AZ22="","",$BA$45) -> Trd_car | BB22: =IF($AZ22="","",25) -> 25 | BD22: =IF(AZ22="","*","DMD") -> DMD | BE22: =AZ22 -> Trd_car_elc | BG22: Bvkm | BH22: million Vehicles | BI22: yes
C23: =C8 -> TRAGSL | D23: =ROUND(D8*D32/D40,3) -> 15.287 | E23: =ROUND(E8*E32/E40,3) -> 26.546 | F23: =ROUND(F8*F32/F40,3) -> 19.488 | G23: =ROUND(G8*G32/G40,3) -> 2.583 | H23: =ROUND(H8*H32/H40,3) -> 0.77 | I23: =ROUND(I8*I32/I40,3) -> 9.992 | J23: =ROUND(J8*J32/J40,3) -> 30.767 | K23: =ROUND(K8*K32/K40,3) -> 283.217 | ... AW23: =ROUND(AW8*AW32/AW40,3) -> 0 | AY23: PASTI | AZ23: =IF(AX8="zero","\I:",$BA$45&"_"&VLOOKUP(C23,'TRA balance'!$BB$5:$BC$15,2,FALSE)) -> Trd_car_gsl | BA23: =IF($AZ23="","",$BA$45) -> Trd_car | BB23: =IF($AZ23="","",25) -> 25 | BD23: =IF(AZ23="","*","DMD") -> DMD | BE23: =AZ23 -> Trd_car_gsl | BG23: Bvkm | BH23: million Vehicles | BI23: yes
C24: =C9 -> TRALPG | D24: =ROUND(D9*D33/D41,3) -> 1.021 | E24: =ROUND(E9*E33/E41,3) -> 0.001 | F24: =ROUND(F9*F33/F41,3) -> 0.151 | G24: =ROUND(G9*G33/G41,3) -> 0.007 | H24: =ROUND(H9*H33/H41,3) -> 0.156 | I24: =ROUND(I9*I33/I41,3) -> 0.243 | J24: =ROUND(J9*J33/J41,3) -> 0 | K24: =ROUND(K9*K33/K41,3) -> 1.862 | ... AW24: =ROUND(AW9*AW33/AW41,3) -> 0 | AY24: PASTI | AZ24: =IF(AX9="zero","\I:",$BA$45&"_"&VLOOKUP(C24,'TRA balance'!$BB$5:$BC$15,2,FALSE)) -> Trd_car_lpg | BA24: =IF($AZ24="","",$BA$45) -> Trd_car | BB24: =IF($AZ24="","",25) -> 25 | BD24: =IF(AZ24="","*","DMD") -> DMD | BE24: =AZ24 -> Trd_car_lpg | BG24: Bvkm | BH24: million Vehicles | BI24: yes
C25: =C10 -> TRANGA | D25: =ROUND(D10*D34/D42,3) -> 0.182 | E25: =ROUND(E10*E34/E42,3) -> 0.001 | F25: =ROUND(F10*F34/F42,3) -> 0.028 | G25: =ROUND(G10*G34/G42,3) -> 0.019 | H25: =ROUND(H10*H34/H42,3) -> 0.02 | I25: =ROUND(I10*I34/I42,3) -> 0.094 | J25: =ROUND(J10*J34/J42,3) -> 1.506 | K25: =ROUND(K10*K34/K42,3) -> 22.076 | ... AW25: =ROUND(AW10*AW34/AW42,3) -> 0 | AY25: PASTI | AZ25: =IF(AX10="zero","\I:",$BA$45&"_"&VLOOKUP(C25,'TRA balance'!$BB$5:$BC$15,2,FALSE)) -> Trd_car_nga | BA25: =IF($AZ25="","",$BA$45) -> Trd_car | BB25: =IF($AZ25="","",25) -> 25 | BD25: =IF(AZ25="","*","DMD") -> DMD | BE25: =AZ25 -> Trd_car_nga | BG25: Bvkm | BH25: million Vehicles | BI25: yes
AY26: * | BA26: =IF($AZ26="","",$BA$45) | BB26: =IF($AZ26="","",25) | BD26: =IF(AZ26="","*","DMD") -> * | BE26: =AZ26 -> 0 | BG26: Bvkm | BH26: million Vehicles | BI26: yes
D27: 1 | E27: 1 | F27: 1 | G27: 1 | H27: 1 | I27: 1 | J27: 1 | K27: 1 | L27: 1 | M27: 1 | N27: 1 | O27: 1 | P27: 1 | Q27: 1 | R27: 1 | S27: 1 | T27: 1 | U27: 1 | V27: 1 | W27: 1 | X27: 1 | Y27: 0.6 | Z27: 1 | AA27: 1 | AB27: 1 | AC27: 1 | AD27: 1 | AE27: 1 | AF27: 1 | AG27: 1 | AH27: 1 | AI27: 1 | AJ27: 1 | AK27: 1 | AL27: 1 | AM27: 1 | AN27: 1 | AO27: 1 | AP27: 1 | AQ27: 1 | AR27: 1 | AS27: 1 | AT27: 1 | AU27: 1 | AV27: 1 | AW27: 1 | AY27: * | BA27: =IF($AZ27="","",$BA$45) | BB27: =IF($AZ27="","",25) | BD27: =IF(AZ27="","*","DMD") -> * | BE27: =AZ27 -> 0 | BG27: Bvkm | BH27: million Vehicles | BI27: yes
A28: Efficiency | C28: =C19 -> TRABDS | D28: =$AX28*D$27 -> 0.52772281 | E28: =$AX28*E$27 -> 0.52772281 | F28: =$AX28*F$27 -> 0.52772281 | G28: =$AX28*G$27 -> 0.52772281 | H28: =$AX28*H$27 -> 0.52772281 | I28: =$AX28*I$27 -> 0.52772281 | J28: =$AX28*J$27 -> 0.52772281 | K28: =$AX28*K$27 -> 0.52772281 | ... AW28: =$AX28*AW$27 -> 0.52772281 | AX28: =AX30 -> 0.52772281 | AY28: EFF | AZ28: =AZ19 -> Trd_car_bdl | BA28: =IF($AZ28="","",$BA$45) -> Trd_car | BB28: =IF($AZ28="","",25) -> 25 | BD28: =IF(AZ28="","*","DMD") -> DMD | BE28: =AZ28 -> Trd_car_bdl | BG28: Bvkm | BH28: million Vehicles | BI28: yes
C29: =C20 -> TRABGS | D29: =$AX29*D$27 -> 0.46605287 | E29: =$AX29*E$27 -> 0.46605287 | F29: =$AX29*F$27 -> 0.46605287 | G29: =$AX29*G$27 -> 0.46605287 | H29: =$AX29*H$27 -> 0.46605287 | I29: =$AX29*I$27 -> 0.46605287 | J29: =$AX29*J$27 -> 0.46605287 | K29: =$AX29*K$27 -> 0.46605287 | ... AW29: =$AX29*AW$27 -> 0.46605287 | AX29: =AX32 -> 0.46605287 | AY29: EFF | AZ29: =AZ20 -> Trd_car_eth | BA29: =IF($AZ29="","",$BA$45) -> Trd_car | BB29: =IF($AZ29="","",25) -> 25 | BD29: =IF(AZ29="","*","DMD") -> DMD | BE29: =AZ29 -> Trd_car_eth | BG29: Bvkm | BH29: million Vehicles | BI29: yes
C30: =C21 -> TRADST | D30: =$AX30*D$27 -> 0.52772281 | E30: =$AX30*E$27 -> 0.52772281 | F30: =$AX30*F$27 -> 0.52772281 | G30: =$AX30*G$27 -> 0.52772281 | H30: =$AX30*H$27 -> 0.52772281 | I30: =$AX30*I$27 -> 0.52772281 | J30: =$AX30*J$27 -> 0.52772281 | K30: =$AX30*K$27 -> 0.52772281 | ... AW30: =$AX30*AW$27 -> 0.52772281 | AX30: 0.52772281 | AY30: EFF | AZ30: =AZ21 -> Trd_car_dsl | BA30: =IF($AZ30="","",$BA$45) -> Trd_car | BB30: =IF($AZ30="","",25) -> 25 | BD30: =IF(AZ30="","*","DMD") -> DMD | BE30: =AZ30 -> Trd_car_dsl | BG30: Bvkm | BH30: million Vehicles | BI30: yes
C31: =C22 -> TRAELC | D31: =$AX31*D$27 -> 0.93210574 | E31: =$AX31*E$27 -> 0.93210574 | F31: =$AX31*F$27 -> 0.93210574 | G31: =$AX31*G$27 -> 0.93210574 | H31: =$AX31*H$27 -> 0.93210574 | I31: =$AX31*I$27 -> 0.93210574 | J31: =$AX31*J$27 -> 0.93210574 | K31: =$AX31*K$27 -> 0.93210574 | ... AW31: =$AX31*AW$27 -> 0.93210574 | AX31: =AX32*2 -> 0.93210574 | AY31: EFF | AZ31: =AZ22 -> Trd_car_elc | BA31: =IF($AZ31="","",$BA$45) -> Trd_car | BB31: =IF($AZ31="","",25) -> 25 | BD31: =IF(AZ31="","*","DMD") -> DMD | BE31: =AZ31 -> Trd_car_elc | BG31: Bvkm | BH31: million Vehicles | BI31: yes
C32: =C23 -> TRAGSL | D32: =$AX32*D$27 -> 0.46605287 | E32: =$AX32*E$27 -> 0.46605287 | F32: =$AX32*F$27 -> 0.46605287 | G32: =$AX32*G$27 -> 0.46605287 | H32: =$AX32*H$27 -> 0.46605287 | I32: =$AX32*I$27 -> 0.46605287 | J32: =$AX32*J$27 -> 0.46605287 | K32: =$AX32*K$27 -> 0.46605287 | ... AW32: =$AX32*AW$27 -> 0.46605287 | AX32: 0.46605287 | AY32: EFF | AZ32: =AZ23 -> Trd_car_gsl | BA32: =IF($AZ32="","",$BA$45) -> Trd_car | BB32: =IF($AZ32="","",25) -> 25 | BD32: =IF(AZ32="","*","DMD") -> DMD | BE32: =AZ32 -> Trd_car_gsl | BG32: Bvkm | BH32: million Vehicles | BI32: yes
C33: =C24 -> TRALPG | D33: =$AX33*D$27 -> 0.47553149 | E33: =$AX33*E$27 -> 0.47553149 | F33: =$AX33*F$27 -> 0.47553149 | G33: =$AX33*G$27 -> 0.47553149 | H33: =$AX33*H$27 -> 0.47553149 | I33: =$AX33*I$27 -> 0.47553149 | J33: =$AX33*J$27 -> 0.47553149 | K33: =$AX33*K$27 -> 0.47553149 | ... AW33: =$AX33*AW$27 -> 0.47553149 | AX33: 0.47553149 | AY33: EFF | AZ33: =AZ24 -> Trd_car_lpg | BA33: =IF($AZ33="","",$BA$45) -> Trd_car | BB33: =IF($AZ33="","",25) -> 25 | BD33: =IF(AZ33="","*","DMD") -> DMD | BE33: =AZ33 -> Trd_car_lpg | BG33: Bvkm | BH33: million Vehicles | BI33: yes
C34: =C25 -> TRANGA | D34: =$AX34*D$27 -> 0.42934544 | E34: =$AX34*E$27 -> 0.42934544 | F34: =$AX34*F$27 -> 0.42934544 | G34: =$AX34*G$27 -> 0.42934544 | H34: =$AX34*H$27 -> 0.42934544 | I34: =$AX34*I$27 -> 0.42934544 | J34: =$AX34*J$27 -> 0.42934544 | K34: =$AX34*K$27 -> 0.42934544 | ... AW34: =$AX34*AW$27 -> 0.42934544 | AX34: 0.42934544 | AY34: EFF | AZ34: =AZ25 -> Trd_car_nga | BA34: =IF($AZ34="","",$BA$45) -> Trd_car | BB34: =IF($AZ34="","",25) -> 25 | BD34: =IF(AZ34="","*","DMD") -> DMD | BE34: =AZ34 -> Trd_car_nga | BG34: Bvkm | BH34: million Vehicles | BI34: yes
AY35: * | BA35: =IF($AZ35="","",$BA$45) | BB35: =IF($AZ35="","",25) | BD35: =IF(AZ35="","*","DMD") -> * | BE35: =AZ35 -> 0 | BG35: Bvkm | BH35: million Vehicles | BI35: yes
A36: 000km/veh | C36: =C28 -> TRABDS | D36: 12 | E36: 12 | F36: 12 | G36: 12 | H36: 12 | I36: 12 | J36: 12 | K36: 8 | L36: 12 | M36: 12 | N36: 12 | O36: 12 | P36: 12 | Q36: 12 | R36: 12 | S36: 12 | T36: 12 | U36: 12 | V36: 12 | W36: 12 | X36: 12 | Y36: 18 | Z36: 12 | AA36: 12 | AB36: 12 | AC36: 12 | AD36: 12 | AE36: 12 | AF36: 12 | AG36: 12 | AH36: 12 | AI36: 12 | AJ36: 12 | AK36: 12 | AL36: 12 | AM36: 12 | AN36: 12 | AO36: 12 | AP36: 12 | AQ36: 12 | AR36: 12 | AS36: 12 | AT36: 12 | AU36: 12 | AV36: 12 | AW36: 12 | AY36: AF | AZ36: =AZ28 -> Trd_car_bdl | BA36: =IF($AZ36="","",$BA$45) -> Trd_car | BB36: =IF($AZ36="","",25) -> 25 | BD36: =IF(AZ36="","*","DMD") -> DMD | BE36: =AZ36 -> Trd_car_bdl | BG36: Bvkm | BH36: million Vehicles | BI36: yes
C37: =C29 -> TRABGS | D37: =D$36 -> 12 | E37: =E$36 -> 12 | F37: =F$36 -> 12 | G37: =G$36 -> 12 | H37: =H$36 -> 12 | I37: =I$36 -> 12 | J37: =J$36 -> 12 | K37: =K$36 -> 8 | ... AW37: =AW$36 -> 12 | AY37: AF | AZ37: =AZ29 -> Trd_car_eth | BA37: =IF($AZ37="","",$BA$45) -> Trd_car | BB37: =IF($AZ37="","",25) -> 25 | BD37: =IF(AZ37="","*","DMD") -> DMD | BE37: =AZ37 -> Trd_car_eth | BG37: Bvkm | BH37: million Vehicles | BI37: yes
C38: =C30 -> TRADST | D38: =D$36 -> 12 | E38: =E$36 -> 12 | F38: =F$36 -> 12 | G38: =G$36 -> 12 | H38: =H$36 -> 12 | I38: =I$36 -> 12 | J38: =J$36 -> 12 | K38: =K$36 -> 8 | ... AW38: =AW$36 -> 12 | AY38: AF | AZ38: =AZ30 -> Trd_car_dsl | BA38: =IF($AZ38="","",$BA$45) -> Trd_car | BB38: =IF($AZ38="","",25) -> 25 | BD38: =IF(AZ38="","*","DMD") -> DMD | BE38: =AZ38 -> Trd_car_dsl | BG38: Bvkm | BH38: million Vehicles | BI38: yes
C39: =C31 -> TRAELC | D39: =D$36 -> 12 | E39: =E$36 -> 12 | F39: =F$36 -> 12 | G39: =G$36 -> 12 | H39: =H$36 -> 12 | I39: =I$36 -> 12 | J39: =J$36 -> 12 | K39: =K$36 -> 8 | ... AW39: =AW$36 -> 12 | AY39: AF | AZ39: =AZ31 -> Trd_car_elc | BA39: =IF($AZ39="","",$BA$45) -> Trd_car | BB39: =IF($AZ39="","",25) -> 25 | BD39: =IF(AZ39="","*","DMD") -> DMD | BE39: =AZ39 -> Trd_car_elc | BG39: Bvkm | BH39: million Vehicles | BI39: yes
C40: =C32 -> TRAGSL | D40: =D$36 -> 12 | E40: =E$36 -> 12 | F40: =F$36 -> 12 | G40: =G$36 -> 12 | H40: =H$36 -> 12 | I40: =I$36 -> 12 | J40: =J$36 -> 12 | K40: =K$36 -> 8 | ... AW40: =AW$36 -> 12 | AY40: AF | AZ40: =AZ32 -> Trd_car_gsl | BA40: =IF($AZ40="","",$BA$45) -> Trd_car | BB40: =IF($AZ40="","",25) -> 25 | BD40: =IF(AZ40="","*","DMD") -> DMD | BE40: =AZ40 -> Trd_car_gsl | BG40: Bvkm | BH40: million Vehicles | BI40: yes
C41: =C33 -> TRALPG | D41: =D$36 -> 12 | E41: =E$36 -> 12 | F41: =F$36 -> 12 | G41: =G$36 -> 12 | H41: =H$36 -> 12 | I41: =I$36 -> 12 | J41: =J$36 -> 12 | K41: =K$36 -> 8 | ... AW41: =AW$36 -> 12 | AY41: AF | AZ41: =AZ33 -> Trd_car_lpg | BA41: =IF($AZ41="","",$BA$45) -> Trd_car | BB41: =IF($AZ41="","",25) -> 25 | BD41: =IF(AZ41="","*","DMD") -> DMD | BE41: =AZ41 -> Trd_car_lpg | BG41: Bvkm | BH41: million Vehicles | BI41: yes
C42: =C34 -> TRANGA | D42: =D$36 -> 12 | E42: =E$36 -> 12 | F42: =F$36 -> 12 | G42: =G$36 -> 12 | H42: =H$36 -> 12 | I42: =I$36 -> 12 | J42: =J$36 -> 12 | K42: =K$36 -> 8 | ... AW42: =AW$36 -> 12 | AY42: AF | AZ42: =AZ34 -> Trd_car_nga | BA42: =IF($AZ42="","",$BA$45) -> Trd_car | BB42: =IF($AZ42="","",25) -> 25 | BD42: =IF(AZ42="","*","DMD") -> DMD | BE42: =AZ42 -> Trd_car_nga | BG42: Bvkm | BH42: million Vehicles | BI42: yes
AY43: * | BB43: =IF($AZ43="","",25)
D44: =D3 -> Africa_North | E44: =E3 -> Africa_Other | F44: =F3 -> Australia | G44: =G3 -> Austria | H44: =H3 -> Baltics | I44: =I3 -> BeNeLux | J44: =J3 -> Brazil | K44: =K3 -> China | ... AW44: =AW3 -> \I: | AY44: * | BB44: =IF($AZ44="","",25)
A45: Dem Bvkm | AY45: Demand | BA45: Trd_car | BB45: =IF($AZ45="","",25)
AY47: ~FI_Comm
AY48: CSet | AZ48: CommName | BA48: CommDesc | BB48: Unit
AG49: =AG36*AG23/AG32*1000/41.868 -> 4361.4668 | AY49: DEM | AZ49: =BA45 -> Trd_car | BB49: Bvkm

Sheet Bus
AY2: ~FI_T | BD2: ~FI_Process
C3: comm-in | D3: ='TRA balance'!E4 -> Africa_North | E3: ='TRA balance'!F4 -> Africa_Other | F3: ='TRA balance'!G4 -> Australia | G3: ='TRA balance'!H4 -> Austria | H3: ='TRA balance'!I4 -> Baltics | I3: ='TRA balance'!J4 -> BeNeLux | J3: ='TRA balance'!K4 -> Brazil | K3: ='TRA balance'!L4 -> China | ... AW3: ='TRA balance'!AX4 -> \I: | AX3: * | AY3: attribute | AZ3: process | BA3: comm-out | BB3: LIFE | BD3: Sets | BE3: TechName | BF3: TechDesc | BG3: Tact | BH3: Tcap | BI3: Vintage
A4: TR | C4: TRABDS | D4: {=SUM(SUMIFS(Assumptions!BD$3:BD$102,Assumptions!$B$3:$B$102,Bus!$C4,Assumptions!$G$3:$G$102,{"TRB"}))} -> 0 | E4: {=SUM(SUMIFS(Assumptions!BE$3:BE$102,Assumptions!$B$3:$B$102,Bus!$C4,Assumptions!$G$3:$G$102,{"TRB"}))} -> 0 | F4: {=SUM(SUMIFS(Assumptions!BF$3:BF$102,Assumptions!$B$3:$B$102,Bus!$C4,Assumptions!$G$3:$G$102,{"TRB"}))} -> 0.0054098899 | G4: {=SUM(SUMIFS(Assumptions!BG$3:BG$102,Assumptions!$B$3:$B$102,Bus!$C4,Assumptions!$G$3:$G$102,{"TRB"}))} -> 0.71297922 | H4: {=SUM(SUMIFS(Assumptions!BH$3:BH$102,Assumptions!$B$3:$B$102,Bus!$C4,Assumptions!$G$3:$G$102,{"TRB"}))} -> 0.43541732 | I4: {=SUM(SUMIFS(Assumptions!BI$3:BI$102,Assumptions!$B$3:$B$102,Bus!$C4,Assumptions!$G$3:$G$102,{"TRB"}))} -> 1.4771963 | J4: {=SUM(SUMIFS(Assumptions!BJ$3:BJ$102,Assumptions!$B$3:$B$102,Bus!$C4,Assumptions!$G$3:$G$102,{"TRB"}))} -> 60.545783 | K4: {=SUM(SUMIFS(Assumptions!BK$3:BK$102,Assumptions!$B$3:$B$102,Bus!$C4,Assumptions!$G$3:$G$102,{"TRB"}))} -> 11.93976 | ... AW4: {=SUM(SUMIFS(Assumptions!CW$3:CW$102,Assumptions!$B$3:$B$102,Bus!$C4,Assumptions!$G$3:$G$102,{"TRB"}))} -> 0 | AY4: * | BA4: =IF($AZ4="","",$BA$45) | BB4: =IF($AZ4="","",25) | BD4: =IF($AZ4="","*","DMD") -> * | BE4: =AZ4 -> 0 | BG4: Bvkm | BH4: million Vehicles | BI4: yes
A5: TR | C5: TRABGS | D5: {=SUM(SUMIFS(Assumptions!BD$3:BD$102,Assumptions!$B$3:$B$102,Bus!$C5,Assumptions!$G$3:$G$102,{"TRB"}))} -> 0 | E5: {=SUM(SUMIFS(Assumptions!BE$3:BE$102,Assumptions!$B$3:$B$102,Bus!$C5,Assumptions!$G$3:$G$102,{"TRB"}))} -> 0 | F5: {=SUM(SUMIFS(Assumptions!BF$3:BF$102,Assumptions!$B$3:$B$102,Bus!$C5,Assumptions!$G$3:$G$102,{"TRB"}))} -> 0 | G5: {=SUM(SUMIFS(Assumptions!BG$3:BG$102,Assumptions!$B$3:$B$102,Bus!$C5,Assumptions!$G$3:$G$102,{"TRB"}))} -> 0 | H5: {=SUM(SUMIFS(Assumptions!BH$3:BH$102,Assumptions!$B$3:$B$102,Bus!$C5,Assumptions!$G$3:$G$102,{"TRB"}))} -> 0 | I5: {=SUM(SUMIFS(Assumptions!BI$3:BI$102,Assumptions!$B$3:$B$102,Bus!$C5,Assumptions!$G$3:$G$102,{"TRB"}))} -> 0 | J5: {=SUM(SUMIFS(Assumptions!BJ$3:BJ$102,Assumptions!$B$3:$B$102,Bus!$C5,Assumptions!$G$3:$G$102,{"TRB"}))} -> 0 | K5: {=SUM(SUMIFS(Assumptions!BK$3:BK$102,Assumptions!$B$3:$B$102,Bus!$C5,Assumptions!$G$3:$G$102,{"TRB"}))} -> 0 | ... AW5: {=SUM(SUMIFS(Assumptions!CW$3:CW$102,Assumptions!$B$3:$B$102,Bus!$C5,Assumptions!$G$3:$G$102,{"TRB"}))} -> 0 | AY5: * | BA5: =IF($AZ5="","",$BA$45) | BB5: =IF($AZ5="","",25) | BD5: =IF(AZ5="","*","DMD") -> * | BE5: =AZ5 -> 0 | BG5: Bvkm | BH5: million Vehicles | BI5: yes
A6: TR | C6: TRADST | D6: {=SUM(SUMIFS(Assumptions!BD$3:BD$102,Assumptions!$B$3:$B$102,Bus!$C6,Assumptions!$G$3:$G$102,{"TRB"}))} -> 350.28647 | E6: {=SUM(SUMIFS(Assumptions!BE$3:BE$102,Assumptions!$B$3:$B$102,Bus!$C6,Assumptions!$G$3:$G$102,{"TRB"}))} -> 311.2917 | F6: {=SUM(SUMIFS(Assumptions!BF$3:BF$102,Assumptions!$B$3:$B$102,Bus!$C6,Assumptions!$G$3:$G$102,{"TRB"}))} -> 84.618773 | G6: {=SUM(SUMIFS(Assumptions!BG$3:BG$102,Assumptions!$B$3:$B$102,Bus!$C6,Assumptions!$G$3:$G$102,{"TRB"}))} -> 10.346022 | H6: {=SUM(SUMIFS(Assumptions!BH$3:BH$102,Assumptions!$B$3:$B$102,Bus!$C6,Assumptions!$G$3:$G$102,{"TRB"}))} -> 11.520655 | I6: {=SUM(SUMIFS(Assumptions!BI$3:BI$102,Assumptions!$B$3:$B$102,Bus!$C6,Assumptions!$G$3:$G$102,{"TRB"}))} -> 21.929287 | J6: {=SUM(SUMIFS(Assumptions!BJ$3:BJ$102,Assumptions!$B$3:$B$102,Bus!$C6,Assumptions!$G$3:$G$102,{"TRB"}))} -> 133.54722 | K6: {=SUM(SUMIFS(Assumptions!BK$3:BK$102,Assumptions!$B$3:$B$102,Bus!$C6,Assumptions!$G$3:$G$102,{"TRB"}))} -> 1222.6321 | ... AW6: {=SUM(SUMIFS(Assumptions!CW$3:CW$102,Assumptions!$B$3:$B$102,Bus!$C6,Assumptions!$G$3:$G$102,{"TRB"}))} -> 0 | AY6: * | BA6: =IF($AZ6="","",$BA$45) | BB6: =IF($AZ6="","",25) | BD6: =IF(AZ6="","*","DMD") -> * | BE6: =AZ6 -> 0 | BG6: Bvkm | BH6: million Vehicles | BI6: yes
A7: TR | C7: TRAELC | D7: {=SUM(SUMIFS(Assumptions!BD$3:BD$102,Assumptions!$B$3:$B$102,Bus!$C7,Assumptions!$G$3:$G$102,{"TRB"}))} -> 0 | E7: {=SUM(SUMIFS(Assumptions!BE$3:BE$102,Assumptions!$B$3:$B$102,Bus!$C7,Assumptions!$G$3:$G$102,{"TRB"}))} -> 0 | F7: {=SUM(SUMIFS(Assumptions!BF$3:BF$102,Assumptions!$B$3:$B$102,Bus!$C7,Assumptions!$G$3:$G$102,{"TRB"}))} -> 0 | G7: {=SUM(SUMIFS(Assumptions!BG$3:BG$102,Assumptions!$B$3:$B$102,Bus!$C7,Assumptions!$G$3:$G$102,{"TRB"}))} -> 0 | H7: {=SUM(SUMIFS(Assumptions!BH$3:BH$102,Assumptions!$B$3:$B$102,Bus!$C7,Assumptions!$G$3:$G$102,{"TRB"}))} -> 0.29186601 | I7: {=SUM(SUMIFS(Assumptions!BI$3:BI$102,Assumptions!$B$3:$B$102,Bus!$C7,Assumptions!$G$3:$G$102,{"TRB"}))} -> 0 | J7: {=SUM(SUMIFS(Assumptions!BJ$3:BJ$102,Assumptions!$B$3:$B$102,Bus!$C7,Assumptions!$G$3:$G$102,{"TRB"}))} -> 0 | K7: {=SUM(SUMIFS(Assumptions!BK$3:BK$102,Assumptions!$B$3:$B$102,Bus!$C7,Assumptions!$G$3:$G$102,{"TRB"}))} -> 24.536301 | ... AW7: {=SUM(SUMIFS(Assumptions!CW$3:CW$102,Assumptions!$B$3:$B$102,Bus!$C7,Assumptions!$G$3:$G$102,{"TRB"}))} -> 0 | AY7: * | BA7: =IF($AZ7="","",$BA$45) | BB7: =IF($AZ7="","",25) | BD7: =IF(AZ7="","*","DMD") -> * | BE7: =AZ7 -> 0 | BG7: Bvkm | BH7: million Vehicles | BI7: yes
A8: TR | C8: TRAGSL | D8: {=SUM(SUMIFS(Assumptions!BD$3:BD$102,Assumptions!$B$3:$B$102,Bus!$C8,Assumptions!$G$3:$G$102,{"TRB"}))} -> 0 | E8: {=SUM(SUMIFS(Assumptions!BE$3:BE$102,Assumptions!$B$3:$B$102,Bus!$C8,Assumptions!$G$3:$G$102,{"TRB"}))} -> 0 | F8: {=SUM(SUMIFS(Assumptions!BF$3:BF$102,Assumptions!$B$3:$B$102,Bus!$C8,Assumptions!$G$3:$G$102,{"TRB"}))} -> 2.8446092 | G8: {=SUM(SUMIFS(Assumptions!BG$3:BG$102,Assumptions!$B$3:$B$102,Bus!$C8,Assumptions!$G$3:$G$102,{"TRB"}))} -> 0.10386626 | H8: {=SUM(SUMIFS(Assumptions!BH$3:BH$102,Assumptions!$B$3:$B$102,Bus!$C8,Assumptions!$G$3:$G$102,{"TRB"}))} -> 0.43373881 | I8: {=SUM(SUMIFS(Assumptions!BI$3:BI$102,Assumptions!$B$3:$B$102,Bus!$C8,Assumptions!$G$3:$G$102,{"TRB"}))} -> 0.40186806 | J8: {=SUM(SUMIFS(Assumptions!BJ$3:BJ$102,Assumptions!$B$3:$B$102,Bus!$C8,Assumptions!$G$3:$G$102,{"TRB"}))} -> 10.778182 | K8: {=SUM(SUMIFS(Assumptions!BK$3:BK$102,Assumptions!$B$3:$B$102,Bus!$C8,Assumptions!$G$3:$G$102,{"TRB"}))} -> 60.018947 | ... AW8: {=SUM(SUMIFS(Assumptions!CW$3:CW$102,Assumptions!$B$3:$B$102,Bus!$C8,Assumptions!$G$3:$G$102,{"TRB"}))} -> 0 | AY8: * | BA8: =IF($AZ8="","",$BA$45) | BB8: =IF($AZ8="","",25) | BD8: =IF(AZ8="","*","DMD") -> * | BE8: =AZ8 -> 0 | BG8: Bvkm | BH8: million Vehicles | BI8: yes
A9: TR | C9: TRALPG | D9: {=SUM(SUMIFS(Assumptions!BD$3:BD$102,Assumptions!$B$3:$B$102,Bus!$C9,Assumptions!$G$3:$G$102,{"TRB"}))} -> 5.1527991 | E9: {=SUM(SUMIFS(Assumptions!BE$3:BE$102,Assumptions!$B$3:$B$102,Bus!$C9,Assumptions!$G$3:$G$102,{"TRB"}))} -> 0.0029572206 | F9: {=SUM(SUMIFS(Assumptions!BF$3:BF$102,Assumptions!$B$3:$B$102,Bus!$C9,Assumptions!$G$3:$G$102,{"TRB"}))} -> 9.1246558 | G9: {=SUM(SUMIFS(Assumptions!BG$3:BG$102,Assumptions!$B$3:$B$102,Bus!$C9,Assumptions!$G$3:$G$102,{"TRB"}))} -> 0 | H9: {=SUM(SUMIFS(Assumptions!BH$3:BH$102,Assumptions!$B$3:$B$102,Bus!$C9,Assumptions!$G$3:$G$102,{"TRB"}))} -> 0 | I9: {=SUM(SUMIFS(Assumptions!BI$3:BI$102,Assumptions!$B$3:$B$102,Bus!$C9,Assumptions!$G$3:$G$102,{"TRB"}))} -> 0 | J9: {=SUM(SUMIFS(Assumptions!BJ$3:BJ$102,Assumptions!$B$3:$B$102,Bus!$C9,Assumptions!$G$3:$G$102,{"TRB"}))} -> 0 | K9: {=SUM(SUMIFS(Assumptions!BK$3:BK$102,Assumptions!$B$3:$B$102,Bus!$C9,Assumptions!$G$3:$G$102,{"TRB"}))} -> 37.585036 | ... AW9: {=SUM(SUMIFS(Assumptions!CW$3:CW$102,Assumptions!$B$3:$B$102,Bus!$C9,Assumptions!$G$3:$G$102,{"TRB"}))} -> 0 | AY9: * | BA9: =IF($AZ9="","",$BA$45) | BB9: =IF($AZ9="","",25) | BD9: =IF(AZ9="","*","DMD") -> * | BE9: =AZ9 -> 0 | BG9: Bvkm | BH9: million Vehicles | BI9: yes
A10: TR | C10: TRANGA | D10: {=SUM(SUMIFS(Assumptions!BD$3:BD$102,Assumptions!$B$3:$B$102,Bus!$C10,Assumptions!$G$3:$G$102,{"TRB"}))} -> 12.208832 | E10: {=SUM(SUMIFS(Assumptions!BE$3:BE$102,Assumptions!$B$3:$B$102,Bus!$C10,Assumptions!$G$3:$G$102,{"TRB"}))} -> 0.044812995 | F10: {=SUM(SUMIFS(Assumptions!BF$3:BF$102,Assumptions!$B$3:$B$102,Bus!$C10,Assumptions!$G$3:$G$102,{"TRB"}))} -> 1.874072 | G10: {=SUM(SUMIFS(Assumptions!BG$3:BG$102,Assumptions!$B$3:$B$102,Bus!$C10,Assumptions!$G$3:$G$102,{"TRB"}))} -> 0.24930776 | H10: {=SUM(SUMIFS(Assumptions!BH$3:BH$102,Assumptions!$B$3:$B$102,Bus!$C10,Assumptions!$G$3:$G$102,{"TRB"}))} -> 0 | I10: {=SUM(SUMIFS(Assumptions!BI$3:BI$102,Assumptions!$B$3:$B$102,Bus!$C10,Assumptions!$G$3:$G$102,{"TRB"}))} -> 1.2201304 | J10: {=SUM(SUMIFS(Assumptions!BJ$3:BJ$102,Assumptions!$B$3:$B$102,Bus!$C10,Assumptions!$G$3:$G$102,{"TRB"}))} -> 25.251921 | K10: {=SUM(SUMIFS(Assumptions!BK$3:BK$102,Assumptions!$B$3:$B$102,Bus!$C10,Assumptions!$G$3:$G$102,{"TRB"}))} -> 493.60336 | ... AW10: {=SUM(SUMIFS(Assumptions!CW$3:CW$102,Assumptions!$B$3:$B$102,Bus!$C10,Assumptions!$G$3:$G$102,{"TRB"}))} -> 0 | AY10: * | BA10: =IF($AZ10="","",$BA$45) | BB10: =IF($AZ10="","",25) | BD10: =IF(AZ10="","*","DMD") -> * | BE10: =AZ10 -> 0 | BG10: Bvkm | BH10: million Vehicles | BI10: yes
A11: Share of PJ | D11: =SUM(D$4:D$10)/SUM($D$4:$AJ$10) -> 0.063482485 | E11: =SUM(E$4:E$10)/SUM($D$4:$AJ$10) -> 0.053759568 | F11: =SUM(F$4:F$10)/SUM($D$4:$AJ$10) -> 0.017002571 | G11: =SUM(G$4:G$10)/SUM($D$4:$AJ$10) -> 0.0019705616 | H11: =SUM(H$4:H$10)/SUM($D$4:$AJ$10) -> 0.0021897689 | I11: =SUM(I$4:I$10)/SUM($D$4:$AJ$10) -> 0.0043217148 | J11: =SUM(J$4:J$10)/SUM($D$4:$AJ$10) -> 0.039735787 | K11: =SUM(K$4:K$10)/SUM($D$4:$AJ$10) -> 0.31949743 | ... AW11: =SUM(AW$4:AW$10)/SUM($D$4:$AJ$10) -> 0 | AY11: * | BA11: =IF($AZ11="","",$BA$45) | BB11: =IF($AZ11="","",25) | BD11: =IF(AZ11="","*","DMD") -> * | BE11: =AZ11 -> 0 | BG11: Bvkm | BH11: million Vehicles | BI11: yes
AY12: * | BA12: =IF($AZ12="","",$BA$45) | BB12: =IF($AZ12="","",25) | BD12: =IF(AZ12="","*","DMD") -> * | BE12: =AZ12 -> 0 | BG12: Bvkm | BH12: million Vehicles | BI12: yes
A13: m Vehicles | C13: =SUM(D13:AJ13) -> 11.939 | D13: =SUM(D19:D25) -> 0.753 | E13: =SUM(E19:E25) -> 0.641 | F13: =SUM(F19:F25) -> 0.204 | G13: =SUM(G19:G25) -> 0.022 | H13: =SUM(H19:H25) -> 0.029 | I13: =SUM(I19:I25) -> 0.051 | J13: =SUM(J19:J25) -> 0.469 | K13: =SUM(K19:K25) -> 3.844 | ... AW13: =SUM(AW19:AW25) -> 0 | AY13: * | BA13: =IF($AZ13="","",$BA$45) | BB13: =IF($AZ13="","",25) | BD13: =IF(AZ13="","*","DMD") -> * | BE13: =AZ13 -> 0 | BG13: Bvkm | BH13: million Vehicles | BI13: yes
A14: Share of Veh | D14: =D13/SUM($D$13:$AW$13) -> 0.062557116 | E14: =E13/SUM($D$13:$AW$13) -> 0.053252472 | F14: =F13/SUM($D$13:$AW$13) -> 0.016947744 | G14: =G13/SUM($D$13:$AW$13) -> 0.0018276979 | H14: =H13/SUM($D$13:$AW$13) -> 0.0024092382 | I14: =I13/SUM($D$13:$AW$13) -> 0.0042369361 | J14: =J13/SUM($D$13:$AW$13) -> 0.038963197 | K14: =K13/SUM($D$13:$AW$13) -> 0.31934867 | ... AW14: =AW13/SUM($D$13:$AW$13) -> 0 | AY14: * | BA14: =IF($AZ14="","",$BA$45) | BB14: =IF($AZ14="","",25) | BD14: =IF(AZ14="","*","DMD") -> * | BE14: =AZ14 -> 0 | BG14: Bvkm | BH14: million Vehicles | BI14: yes
AY15: * | BA15: =IF($AZ15="","",$BA$45) | BB15: =IF($AZ15="","",25) | BD15: =IF(AZ15="","*","DMD") -> * | BE15: =AZ15 -> 0 | BG15: Bvkm | BH15: million Vehicles | BI15: yes
AY16: * | BA16: =IF($AZ16="","",$BA$45) | BB16: =IF($AZ16="","",25) | BD16: =IF(AZ16="","*","DMD") -> * | BE16: =AZ16 -> 0 | BG16: Bvkm | BH16: million Vehicles | BI16: yes
A17: PJ share/Veh share | D17: =IFERROR(D11/D14,"") -> 1.0147924 | E17: =IFERROR(E11/E14,"") -> 1.0095225 | F17: =IFERROR(F11/F14,"") -> 1.003235 | G17: =IFERROR(G11/G14,"") -> 1.0781659 | H17: =IFERROR(H11/H14,"") -> 0.90890513 | I17: =IFERROR(I11/I14,"") -> 1.0200094 | J17: =IFERROR(J11/J14,"") -> 1.0198287 | K17: =IFERROR(K11/K14,"") -> 1.0004658 | ... AW17: =IFERROR(AW11/AW14,"") | AY17: * | BA17: =IF($AZ17="","",$BA$45) | BB17: =IF($AZ17="","",25) | BD17: =IF(AZ17="","*","DMD") -> * | BE17: =AZ17 -> 0 | BG17: Bvkm | BH17: million Vehicles | BI17: yes
AY18: * | BA18: =IF($AZ18="","",$BA$45) | BB18: =IF($AZ18="","",25) | BD18: =IF(AZ18="","*","DMD") -> * | BE18: =AZ18 -> 0 | BG18: Bvkm | BH18: million Vehicles | BI18: yes
A19: mVeh | C19: =C4 -> TRABDS | D19: =ROUND(D4*D28/D36,3) -> 0 | E19: =ROUND(E4*E28/E36,3) -> 0 | F19: =ROUND(F4*F28/F36,3) -> 0 | G19: =ROUND(G4*G28/G36,3) -> 0.001 | H19: =ROUND(H4*H28/H36,3) -> 0.001 | I19: =ROUND(I4*I28/I36,3) -> 0.003 | J19: =ROUND(J4*J28/J36,3) -> 0.125 | K19: =ROUND(K4*K28/K36,3) -> 0.025 | ... AW19: =ROUND(AW4*AW28/AW36,3) -> 0 | AY19: PASTI | AZ19: =IF(AX4="zero","\I:",$BA$45&"_"&VLOOKUP(C19,'TRA balance'!$BB$5:$BC$15,2,FALSE)) -> Trd_bus_bdl | BA19: =IF($AZ19="","",$BA$45) -> Trd_bus | BB19: =IF($AZ19="","",25) -> 25 | BD19: =IF(AZ19="","*","DMD") -> DMD | BE19: =AZ19 -> Trd_bus_bdl | BG19: Bvkm | BH19: million Vehicles | BI19: yes
C20: =C5 -> TRABGS | D20: =ROUND(D5*D29/D37,3) -> 0 | E20: =ROUND(E5*E29/E37,3) -> 0 | F20: =ROUND(F5*F29/F37,3) -> 0 | G20: =ROUND(G5*G29/G37,3) -> 0 | H20: =ROUND(H5*H29/H37,3) -> 0 | I20: =ROUND(I5*I29/I37,3) -> 0 | J20: =ROUND(J5*J29/J37,3) -> 0 | K20: =ROUND(K5*K29/K37,3) -> 0 | ... AW20: =ROUND(AW5*AW29/AW37,3) -> 0 | AY20: PASTI | AZ20: =IF(AX5="zero","\I:",$BA$45&"_"&VLOOKUP(C20,'TRA balance'!$BB$5:$BC$15,2,FALSE)) -> Trd_bus_eth | BA20: =IF($AZ20="","",$BA$45) -> Trd_bus | BB20: =IF($AZ20="","",25) -> 25 | BD20: =IF(AZ20="","*","DMD") -> DMD | BE20: =AZ20 -> Trd_bus_eth | BG20: Bvkm | BH20: million Vehicles | BI20: yes
C21: =C6 -> TRADST | D21: =ROUND(D6*D30/D38,3) -> 0.721 | E21: =ROUND(E6*E30/E38,3) -> 0.641 | F21: =ROUND(F6*F30/F38,3) -> 0.174 | G21: =ROUND(G6*G30/G38,3) -> 0.021 | H21: =ROUND(H6*H30/H38,3) -> 0.024 | I21: =ROUND(I6*I30/I38,3) -> 0.045 | J21: =ROUND(J6*J30/J38,3) -> 0.275 | K21: =ROUND(K6*K30/K38,3) -> 2.518 | ... AW21: =ROUND(AW6*AW30/AW38,3) -> 0 | AY21: PASTI | AZ21: =IF(AX6="zero","\I:",$BA$45&"_"&VLOOKUP(C21,'TRA balance'!$BB$5:$BC$15,2,FALSE)) -> Trd_bus_dsl | BA21: =IF($AZ21="","",$BA$45) -> Trd_bus | BB21: =IF($AZ21="","",25) -> 25 | BD21: =IF(AZ21="","*","DMD") -> DMD | BE21: =AZ21 -> Trd_bus_dsl | BG21: Bvkm | BH21: million Vehicles | BI21: yes
C22: =C7 -> TRAELC | D22: =ROUND(D7*D31/D39,3) -> 0 | E22: =ROUND(E7*E31/E39,3) -> 0 | F22: =ROUND(F7*F31/F39,3) -> 0 | G22: =ROUND(G7*G31/G39,3) -> 0 | H22: =ROUND(H7*H31/H39,3) -> 0.003 | I22: =ROUND(I7*I31/I39,3) -> 0 | J22: =ROUND(J7*J31/J39,3) -> 0 | K22: =ROUND(K7*K31/K39,3) -> 0.219 | ... AW22: =ROUND(AW7*AW31/AW39,3) -> 0 | AY22: PASTI | AZ22: =IF(AX7="zero","\I:",$BA$45&"_"&VLOOKUP(C22,'TRA balance'!$BB$5:$BC$15,2,FALSE)) -> Trd_bus_elc | BA22: =IF($AZ22="","",$BA$45) -> Trd_bus | BB22: =IF($AZ22="","",25) -> 25 | BD22: =IF(AZ22="","*","DMD") -> DMD | BE22: =AZ22 -> Trd_bus_elc | BG22: Bvkm | BH22: million Vehicles | BI22: yes
C23: =C8 -> TRAGSL | D23: =ROUND(D8*D32/D40,3) -> 0 | E23: =ROUND(E8*E32/E40,3) -> 0 | F23: =ROUND(F8*F32/F40,3) -> 0.007 | G23: =ROUND(G8*G32/G40,3) -> 0 | H23: =ROUND(H8*H32/H40,3) -> 0.001 | I23: =ROUND(I8*I32/I40,3) -> 0.001 | J23: =ROUND(J8*J32/J40,3) -> 0.025 | K23: =ROUND(K8*K32/K40,3) -> 0.137 | ... AW23: =ROUND(AW8*AW32/AW40,3) -> 0 | AY23: PASTI | AZ23: =IF(AX8="zero","\I:",$BA$45&"_"&VLOOKUP(C23,'TRA balance'!$BB$5:$BC$15,2,FALSE)) -> Trd_bus_gsl | BA23: =IF($AZ23="","",$BA$45) -> Trd_bus | BB23: =IF($AZ23="","",25) -> 25 | BD23: =IF(AZ23="","*","DMD") -> DMD | BE23: =AZ23 -> Trd_bus_gsl | BG23: Bvkm | BH23: million Vehicles | BI23: yes
C24: =C9 -> TRALPG | D24: =ROUND(D9*D33/D41,3) -> 0.011 | E24: =ROUND(E9*E33/E41,3) -> 0 | F24: =ROUND(F9*F33/F41,3) -> 0.02 | G24: =ROUND(G9*G33/G41,3) -> 0 | H24: =ROUND(H9*H33/H41,3) -> 0 | I24: =ROUND(I9*I33/I41,3) -> 0 | J24: =ROUND(J9*J33/J41,3) -> 0 | K24: =ROUND(K9*K33/K41,3) -> 0.082 | ... AW24: =ROUND(AW9*AW33/AW41,3) -> 0 | AY24: PASTI | AZ24: =IF(AX9="zero","\I:",$BA$45&"_"&VLOOKUP(C24,'TRA balance'!$BB$5:$BC$15,2,FALSE)) -> Trd_bus_lpg | BA24: =IF($AZ24="","",$BA$45) -> Trd_bus | BB24: =IF($AZ24="","",25) -> 25 | BD24: =IF(AZ24="","*","DMD") -> DMD | BE24: =AZ24 -> Trd_bus_lpg | BG24: Bvkm | BH24: million Vehicles | BI24: yes
C25: =C10 -> TRANGA | D25: =ROUND(D10*D34/D42,3) -> 0.021 | E25: =ROUND(E10*E34/E42,3) -> 0 | F25: =ROUND(F10*F34/F42,3) -> 0.003 | G25: =ROUND(G10*G34/G42,3) -> 0 | H25: =ROUND(H10*H34/H42,3) -> 0 | I25: =ROUND(I10*I34/I42,3) -> 0.002 | J25: =ROUND(J10*J34/J42,3) -> 0.044 | K25: =ROUND(K10*K34/K42,3) -> 0.863 | ... AW25: =ROUND(AW10*AW34/AW42,3) -> 0 | AY25: PASTI | AZ25: =IF(AX10="zero","\I:",$BA$45&"_"&VLOOKUP(C25,'TRA balance'!$BB$5:$BC$15,2,FALSE)) -> Trd_bus_nga | BA25: =IF($AZ25="","",$BA$45) -> Trd_bus | BB25: =IF($AZ25="","",25) -> 25 | BD25: =IF(AZ25="","*","DMD") -> DMD | BE25: =AZ25 -> Trd_bus_nga | BG25: Bvkm | BH25: million Vehicles | BI25: yes
AY26: * | BA26: =IF($AZ26="","",$BA$45) | BB26: =IF($AZ26="","",25) | BD26: =IF(AZ26="","*","DMD") -> * | BE26: =AZ26 -> 0 | BG26: Bvkm | BH26: million Vehicles | BI26: yes
D27: 1 | E27: 1 | F27: 1 | G27: 1 | H27: 1 | I27: 1 | J27: 1 | K27: 1 | L27: 1 | M27: 1 | N27: 1 | O27: 1 | P27: 1 | Q27: 1 | R27: 1 | S27: 1 | T27: 1 | U27: 1 | V27: 1 | W27: 1 | X27: 1 | Y27: 1 | Z27: 1 | AA27: 1 | AB27: 1 | AC27: 1 | AD27: 1 | AE27: 1 | AF27: 1 | AG27: 1 | AH27: 1 | AI27: 1 | AJ27: 1 | AK27: 1 | AL27: 1 | AM27: 1 | AN27: 1 | AO27: 1 | AP27: 1 | AQ27: 1 | AR27: 1 | AS27: 1 | AT27: 1 | AU27: 1 | AV27: 1 | AW27: 1 | AY27: * | BA27: =IF($AZ27="","",$BA$45) | BB27: =IF($AZ27="","",25) | BD27: =IF(AZ27="","*","DMD") -> * | BE27: =AZ27 -> 0 | BG27: Bvkm | BH27: million Vehicles | BI27: yes
A28: Efficiency | C28: =C19 -> TRABDS | D28: =$AX28*D$27 -> 0.07207 | E28: =$AX28*E$27 -> 0.07207 | F28: =$AX28*F$27 -> 0.07207 | G28: =$AX28*G$27 -> 0.07207 | H28: =$AX28*H$27 -> 0.07207 | I28: =$AX28*I$27 -> 0.07207 | J28: =$AX28*J$27 -> 0.07207 | K28: =$AX28*K$27 -> 0.07207 | ... AW28: =$AX28*AW$27 -> 0.07207 | AX28: =AX30 -> 0.07207 | AY28: EFF | AZ28: =AZ19 -> Trd_bus_bdl | BA28: =IF($AZ28="","",$BA$45) -> Trd_bus | BB28: =IF($AZ28="","",25) -> 25 | BD28: =IF(AZ28="","*","DMD") -> DMD | BE28: =AZ28 -> Trd_bus_bdl | BG28: Bvkm | BH28: million Vehicles | BI28: yes
C29: =C20 -> TRABGS | D29: =$AX29*D$27 -> 0.08 | E29: =$AX29*E$27 -> 0.08 | F29: =$AX29*F$27 -> 0.08 | G29: =$AX29*G$27 -> 0.08 | H29: =$AX29*H$27 -> 0.08 | I29: =$AX29*I$27 -> 0.08 | J29: =$AX29*J$27 -> 0.08 | K29: =$AX29*K$27 -> 0.08 | ... AW29: =$AX29*AW$27 -> 0.08 | AX29: =AX32 -> 0.08 | AY29: EFF | AZ29: =AZ20 -> Trd_bus_eth | BA29: =IF($AZ29="","",$BA$45) -> Trd_bus | BB29: =IF($AZ29="","",25) -> 25 | BD29: =IF(AZ29="","*","DMD") -> DMD | BE29: =AZ29 -> Trd_bus_eth | BG29: Bvkm | BH29: million Vehicles | BI29: yes
C30: =C21 -> TRADST | D30: =$AX30*D$27 -> 0.07207 | E30: =$AX30*E$27 -> 0.07207 | F30: =$AX30*F$27 -> 0.07207 | G30: =$AX30*G$27 -> 0.07207 | H30: =$AX30*H$27 -> 0.07207 | I30: =$AX30*I$27 -> 0.07207 | J30: =$AX30*J$27 -> 0.07207 | K30: =$AX30*K$27 -> 0.07207 | ... AW30: =$AX30*AW$27 -> 0.07207 | AX30: 0.07207 | AY30: EFF | AZ30: =AZ21 -> Trd_bus_dsl | BA30: =IF($AZ30="","",$BA$45) -> Trd_bus | BB30: =IF($AZ30="","",25) -> 25 | BD30: =IF(AZ30="","*","DMD") -> DMD | BE30: =AZ30 -> Trd_bus_dsl | BG30: Bvkm | BH30: million Vehicles | BI30: yes
C31: =C22 -> TRAELC | D31: =$AX31*D$27 -> 0.313 | E31: =$AX31*E$27 -> 0.313 | F31: =$AX31*F$27 -> 0.313 | G31: =$AX31*G$27 -> 0.313 | H31: =$AX31*H$27 -> 0.313 | I31: =$AX31*I$27 -> 0.313 | J31: =$AX31*J$27 -> 0.313 | K31: =$AX31*K$27 -> 0.313 | ... AW31: =$AX31*AW$27 -> 0.313 | AX31: 0.313 | AY31: EFF | AZ31: =AZ22 -> Trd_bus_elc | BA31: =IF($AZ31="","",$BA$45) -> Trd_bus | BB31: =IF($AZ31="","",25) -> 25 | BD31: =IF(AZ31="","*","DMD") -> DMD | BE31: =AZ31 -> Trd_bus_elc | BG31: Bvkm | BH31: million Vehicles | BI31: yes
C32: =C23 -> TRAGSL | D32: =$AX32*D$27 -> 0.08 | E32: =$AX32*E$27 -> 0.08 | F32: =$AX32*F$27 -> 0.08 | G32: =$AX32*G$27 -> 0.08 | H32: =$AX32*H$27 -> 0.08 | I32: =$AX32*I$27 -> 0.08 | J32: =$AX32*J$27 -> 0.08 | K32: =$AX32*K$27 -> 0.08 | ... AW32: =$AX32*AW$27 -> 0.08 | AX32: 0.08 | AY32: EFF | AZ32: =AZ23 -> Trd_bus_gsl | BA32: =IF($AZ32="","",$BA$45) -> Trd_bus | BB32: =IF($AZ32="","",25) -> 25 | BD32: =IF(AZ32="","*","DMD") -> DMD | BE32: =AZ32 -> Trd_bus_gsl | BG32: Bvkm | BH32: million Vehicles | BI32: yes
C33: =C24 -> TRALPG | D33: =$AX33*D$27 -> 0.076 | E33: =$AX33*E$27 -> 0.076 | F33: =$AX33*F$27 -> 0.076 | G33: =$AX33*G$27 -> 0.076 | H33: =$AX33*H$27 -> 0.076 | I33: =$AX33*I$27 -> 0.076 | J33: =$AX33*J$27 -> 0.076 | K33: =$AX33*K$27 -> 0.076 | ... AW33: =$AX33*AW$27 -> 0.076 | AX33: 0.076 | AY33: EFF | AZ33: =AZ24 -> Trd_bus_lpg | BA33: =IF($AZ33="","",$BA$45) -> Trd_bus | BB33: =IF($AZ33="","",25) -> 25 | BD33: =IF(AZ33="","*","DMD") -> DMD | BE33: =AZ33 -> Trd_bus_lpg | BG33: Bvkm | BH33: million Vehicles | BI33: yes
C34: =C25 -> TRANGA | D34: =$AX34*D$27 -> 0.0612 | E34: =$AX34*E$27 -> 0.0612 | F34: =$AX34*F$27 -> 0.0612 | G34: =$AX34*G$27 -> 0.0612 | H34: =$AX34*H$27 -> 0.0612 | I34: =$AX34*I$27 -> 0.0612 | J34: =$AX34*J$27 -> 0.0612 | K34: =$AX34*K$27 -> 0.0612 | ... AW34: =$AX34*AW$27 -> 0.0612 | AX34: 0.0612 | AY34: EFF | AZ34: =AZ25 -> Trd_bus_nga | BA34: =IF($AZ34="","",$BA$45) -> Trd_bus | BB34: =IF($AZ34="","",25) -> 25 | BD34: =IF(AZ34="","*","DMD") -> DMD | BE34: =AZ34 -> Trd_bus_nga | BG34: Bvkm | BH34: million Vehicles | BI34: yes
AY35: * | BA35: =IF($AZ35="","",$BA$45) | BB35: =IF($AZ35="","",25) | BD35: =IF(AZ35="","*","DMD") -> * | BE35: =AZ35 -> 0 | BG35: Bvkm | BH35: million Vehicles | BI35: yes
A36: 000km/veh | C36: =C28 -> TRABDS | D36: 35 | E36: 35 | F36: 35 | G36: 35 | H36: 35 | I36: 35 | J36: 35 | K36: 35 | L36: 35 | M36: 35 | N36: 35 | O36: 35 | P36: 35 | Q36: 35 | R36: 35 | S36: 35 | T36: 35 | U36: 35 | V36: 35 | W36: 35 | X36: 35 | Y36: 35 | Z36: 35 | AA36: 35 | AB36: 35 | AC36: 35 | AD36: 35 | AE36: 35 | AF36: 35 | AG36: 35 | AH36: 35 | AI36: 35 | AJ36: 35 | AK36: 35 | AL36: 20 | AM36: 35 | AN36: 35 | AO36: 35 | AP36: 35 | AQ36: 35 | AR36: 35 | AS36: 35 | AT36: 35 | AU36: 35 | AV36: 35 | AW36: 35 | AY36: AF | AZ36: =AZ28 -> Trd_bus_bdl | BA36: =IF($AZ36="","",$BA$45) -> Trd_bus | BB36: =IF($AZ36="","",25) -> 25 | BD36: =IF(AZ36="","*","DMD") -> DMD | BE36: =AZ36 -> Trd_bus_bdl | BG36: Bvkm | BH36: million Vehicles | BI36: yes
C37: =C29 -> TRABGS | D37: 35 | E37: 35 | F37: 35 | G37: 35 | H37: 35 | I37: 35 | J37: 35 | K37: 35 | L37: 35 | M37: 35 | N37: 35 | O37: 35 | P37: 35 | Q37: 35 | R37: 35 | S37: 35 | T37: 35 | U37: 35 | V37: 35 | W37: 35 | X37: 35 | Y37: 35 | Z37: 35 | AA37: 35 | AB37: 35 | AC37: 35 | AD37: 35 | AE37: 35 | AF37: 35 | AG37: 35 | AH37: 35 | AI37: 35 | AJ37: 35 | AK37: 35 | AL37: 20 | AM37: 35 | AN37: 35 | AO37: 35 | AP37: 35 | AQ37: 35 | AR37: 35 | AS37: 35 | AT37: 35 | AU37: 35 | AV37: 35 | AW37: 35 | AY37: AF | AZ37: =AZ29 -> Trd_bus_eth | BA37: =IF($AZ37="","",$BA$45) -> Trd_bus | BB37: =IF($AZ37="","",25) -> 25 | BD37: =IF(AZ37="","*","DMD") -> DMD | BE37: =AZ37 -> Trd_bus_eth | BG37: Bvkm | BH37: million Vehicles | BI37: yes
C38: =C30 -> TRADST | D38: 35 | E38: 35 | F38: 35 | G38: 35 | H38: 35 | I38: 35 | J38: 35 | K38: 35 | L38: 35 | M38: 35 | N38: 35 | O38: 35 | P38: 35 | Q38: 35 | R38: 35 | S38: 35 | T38: 35 | U38: 35 | V38: 35 | W38: 35 | X38: 35 | Y38: 35 | Z38: 35 | AA38: 35 | AB38: 35 | AC38: 35 | AD38: 35 | AE38: 35 | AF38: 35 | AG38: 35 | AH38: 35 | AI38: 35 | AJ38: 35 | AK38: 35 | AL38: 20 | AM38: 35 | AN38: 35 | AO38: 35 | AP38: 35 | AQ38: 35 | AR38: 35 | AS38: 35 | AT38: 35 | AU38: 35 | AV38: 35 | AW38: 35 | AY38: AF | AZ38: =AZ30 -> Trd_bus_dsl | BA38: =IF($AZ38="","",$BA$45) -> Trd_bus | BB38: =IF($AZ38="","",25) -> 25 | BD38: =IF(AZ38="","*","DMD") -> DMD | BE38: =AZ38 -> Trd_bus_dsl | BG38: Bvkm | BH38: million Vehicles | BI38: yes
C39: =C31 -> TRAELC | D39: 35 | E39: 35 | F39: 35 | G39: 35 | H39: 35 | I39: 35 | J39: 35 | K39: 35 | L39: 35 | M39: 35 | N39: 35 | O39: 35 | P39: 35 | Q39: 35 | R39: 35 | S39: 35 | T39: 35 | U39: 35 | V39: 35 | W39: 35 | X39: 35 | Y39: 35 | Z39: 35 | AA39: 35 | AB39: 35 | AC39: 35 | AD39: 35 | AE39: 35 | AF39: 35 | AG39: 35 | AH39: 35 | AI39: 35 | AJ39: 35 | AK39: 35 | AL39: 20 | AM39: 35 | AN39: 35 | AO39: 35 | AP39: 35 | AQ39: 35 | AR39: 35 | AS39: 35 | AT39: 35 | AU39: 35 | AV39: 35 | AW39: 35 | AY39: AF | AZ39: =AZ31 -> Trd_bus_elc | BA39: =IF($AZ39="","",$BA$45) -> Trd_bus | BB39: =IF($AZ39="","",25) -> 25 | BD39: =IF(AZ39="","*","DMD") -> DMD | BE39: =AZ39 -> Trd_bus_elc | BG39: Bvkm | BH39: million Vehicles | BI39: yes
C40: =C32 -> TRAGSL | D40: 35 | E40: 35 | F40: 35 | G40: 35 | H40: 35 | I40: 35 | J40: 35 | K40: 35 | L40: 35 | M40: 35 | N40: 35 | O40: 35 | P40: 35 | Q40: 35 | R40: 35 | S40: 35 | T40: 35 | U40: 35 | V40: 35 | W40: 35 | X40: 35 | Y40: 35 | Z40: 35 | AA40: 35 | AB40: 35 | AC40: 35 | AD40: 35 | AE40: 35 | AF40: 35 | AG40: 35 | AH40: 35 | AI40: 35 | AJ40: 35 | AK40: 35 | AL40: 20 | AM40: 35 | AN40: 35 | AO40: 35 | AP40: 35 | AQ40: 35 | AR40: 35 | AS40: 35 | AT40: 35 | AU40: 35 | AV40: 35 | AW40: 35 | AY40: AF | AZ40: =AZ32 -> Trd_bus_gsl | BA40: =IF($AZ40="","",$BA$45) -> Trd_bus | BB40: =IF($AZ40="","",25) -> 25 | BD40: =IF(AZ40="","*","DMD") -> DMD | BE40: =AZ40 -> Trd_bus_gsl | BG40: Bvkm | BH40: million Vehicles | BI40: yes
C41: =C33 -> TRALPG | D41: 35 | E41: 35 | F41: 35 | G41: 35 | H41: 35 | I41: 35 | J41: 35 | K41: 35 | L41: 35 | M41: 35 | N41: 35 | O41: 35 | P41: 35 | Q41: 35 | R41: 35 | S41: 35 | T41: 35 | U41: 35 | V41: 35 | W41: 35 | X41: 35 | Y41: 35 | Z41: 35 | AA41: 35 | AB41: 35 | AC41: 35 | AD41: 35 | AE41: 35 | AF41: 35 | AG41: 35 | AH41: 35 | AI41: 35 | AJ41: 35 | AK41: 35 | AL41: 20 | AM41: 35 | AN41: 35 | AO41: 35 | AP41: 35 | AQ41: 35 | AR41: 35 | AS41: 35 | AT41: 35 | AU41: 35 | AV41: 35 | AW41: 35 | AY41: AF | AZ41: =AZ33 -> Trd_bus_lpg | BA41: =IF($AZ41="","",$BA$45) -> Trd_bus | BB41: =IF($AZ41="","",25) -> 25 | BD41: =IF(AZ41="","*","DMD") -> DMD | BE41: =AZ41 -> Trd_bus_lpg | BG41: Bvkm | BH41: million Vehicles | BI41: yes
C42: =C34 -> TRANGA | D42: 35 | E42: 35 | F42: 35 | G42: 35 | H42: 35 | I42: 35 | J42: 35 | K42: 35 | L42: 35 | M42: 35 | N42: 35 | O42: 35 | P42: 35 | Q42: 35 | R42: 35 | S42: 35 | T42: 35 | U42: 35 | V42: 35 | W42: 35 | X42: 35 | Y42: 35 | Z42: 35 | AA42: 35 | AB42: 35 | AC42: 35 | AD42: 35 | AE42: 35 | AF42: 35 | AG42: 35 | AH42: 35 | AI42: 35 | AJ42: 35 | AK42: 35 | AL42: 20 | AM42: 35 | AN42: 35 | AO42: 35 | AP42: 35 | AQ42: 35 | AR42: 35 | AS42: 35 | AT42: 35 | AU42: 35 | AV42: 35 | AW42: 35 | AY42: AF | AZ42: =AZ34 -> Trd_bus_nga | BA42: =IF($AZ42="","",$BA$45) -> Trd_bus | BB42: =IF($AZ42="","",25) -> 25 | BD42: =IF(AZ42="","*","DMD") -> DMD | BE42: =AZ42 -> Trd_bus_nga | BG42: Bvkm | BH42: million Vehicles | BI42: yes
AY43: * | BB43: =IF($AZ43="","",25)
D44: =D3 -> Africa_North | E44: =E3 -> Africa_Other | F44: =F3 -> Australia | G44: =G3 -> Austria | H44: =H3 -> Baltics | I44: =I3 -> BeNeLux | J44: =J3 -> Brazil | K44: =K3 -> China | ... AW44: =AW3 -> \I: | AY44: * | BB44: =IF($AZ44="","",25)
A45: Dem Bvkm | AY45: Demand | BA45: Trd_bus | BB45: =IF($AZ45="","",25)
AY47: ~FI_Comm
AY48: CSet | AZ48: CommName | BA48: CommDesc | BB48: Unit
AY49: DEM | AZ49: =BA45 -> Trd_bus | BB49: Bvkm

Sheet Trucks-lcv
A1: 0.5
AY2: ~FI_T | BD2: ~FI_Process
C3: comm-in | D3: ='TRA balance'!E4 -> Africa_North | E3: ='TRA balance'!F4 -> Africa_Other | F3: ='TRA balance'!G4 -> Australia | G3: ='TRA balance'!H4 -> Austria | H3: ='TRA balance'!I4 -> Baltics | I3: ='TRA balance'!J4 -> BeNeLux | J3: ='TRA balance'!K4 -> Brazil | K3: ='TRA balance'!L4 -> China | ... AW3: ='TRA balance'!AX4 -> \I: | AX3: * | AY3: attribute | AZ3: process | BA3: comm-out | BB3: LIFE | BD3: Sets | BE3: TechName | BF3: TechDesc | BG3: Tact | BH3: Tcap | BI3: Vintage
A4: TR | C4: TRABDS | D4: {=SUM(SUMIFS(Assumptions!BD$3:BD$102,Assumptions!$B$3:$B$102,'Trucks-lcv'!$C4,Assumptions!$G$3:$G$102,{"TRC"}))} -> 0 | E4: {=SUM(SUMIFS(Assumptions!BE$3:BE$102,Assumptions!$B$3:$B$102,'Trucks-lcv'!$C4,Assumptions!$G$3:$G$102,{"TRC"}))} -> 0 | F4: {=SUM(SUMIFS(Assumptions!BF$3:BF$102,Assumptions!$B$3:$B$102,'Trucks-lcv'!$C4,Assumptions!$G$3:$G$102,{"TRC"}))} -> 0.0072131865 | G4: {=SUM(SUMIFS(Assumptions!BG$3:BG$102,Assumptions!$B$3:$B$102,'Trucks-lcv'!$C4,Assumptions!$G$3:$G$102,{"TRC"}))} -> 2.1389376 | H4: {=SUM(SUMIFS(Assumptions!BH$3:BH$102,Assumptions!$B$3:$B$102,'Trucks-lcv'!$C4,Assumptions!$G$3:$G$102,{"TRC"}))} -> 0.43541732 | I4: {=SUM(SUMIFS(Assumptions!BI$3:BI$102,Assumptions!$B$3:$B$102,'Trucks-lcv'!$C4,Assumptions!$G$3:$G$102,{"TRC"}))} -> 4.431589 | J4: {=SUM(SUMIFS(Assumptions!BJ$3:BJ$102,Assumptions!$B$3:$B$102,'Trucks-lcv'!$C4,Assumptions!$G$3:$G$102,{"TRC"}))} -> 60.545783 | K4: {=SUM(SUMIFS(Assumptions!BK$3:BK$102,Assumptions!$B$3:$B$102,'Trucks-lcv'!$C4,Assumptions!$G$3:$G$102,{"TRC"}))} -> 3.4113601 | ... AW4: {=SUM(SUMIFS(Assumptions!CW$3:CW$102,Assumptions!$B$3:$B$102,'Trucks-lcv'!$C4,Assumptions!$G$3:$G$102,{"TRC"}))} -> 0 | AX4: =IF(SUM(D4:AW4)=0,"zero","") | AY4: * | BA4: =IF($AZ4="","",$BA$45) | BB4: =IF($AZ4="","",25) | BD4: =IF($AZ4="","*","DMD") -> * | BE4: =AZ4 -> 0 | BG4: Bvkm | BH4: million Vehicles | BI4: yes
A5: TR | C5: TRABGS | D5: {=SUM(SUMIFS(Assumptions!BD$3:BD$102,Assumptions!$B$3:$B$102,'Trucks-lcv'!$C5,Assumptions!$G$3:$G$102,{"TRC"}))} -> 0 | E5: {=SUM(SUMIFS(Assumptions!BE$3:BE$102,Assumptions!$B$3:$B$102,'Trucks-lcv'!$C5,Assumptions!$G$3:$G$102,{"TRC"}))} -> 0 | F5: {=SUM(SUMIFS(Assumptions!BF$3:BF$102,Assumptions!$B$3:$B$102,'Trucks-lcv'!$C5,Assumptions!$G$3:$G$102,{"TRC"}))} -> 0 | G5: {=SUM(SUMIFS(Assumptions!BG$3:BG$102,Assumptions!$B$3:$B$102,'Trucks-lcv'!$C5,Assumptions!$G$3:$G$102,{"TRC"}))} -> 0 | H5: {=SUM(SUMIFS(Assumptions!BH$3:BH$102,Assumptions!$B$3:$B$102,'Trucks-lcv'!$C5,Assumptions!$G$3:$G$102,{"TRC"}))} -> 0 | I5: {=SUM(SUMIFS(Assumptions!BI$3:BI$102,Assumptions!$B$3:$B$102,'Trucks-lcv'!$C5,Assumptions!$G$3:$G$102,{"TRC"}))} -> 0 | J5: {=SUM(SUMIFS(Assumptions!BJ$3:BJ$102,Assumptions!$B$3:$B$102,'Trucks-lcv'!$C5,Assumptions!$G$3:$G$102,{"TRC"}))} -> 0 | K5: {=SUM(SUMIFS(Assumptions!BK$3:BK$102,Assumptions!$B$3:$B$102,'Trucks-lcv'!$C5,Assumptions!$G$3:$G$102,{"TRC"}))} -> 0 | ... AW5: {=SUM(SUMIFS(Assumptions!CW$3:CW$102,Assumptions!$B$3:$B$102,'Trucks-lcv'!$C5,Assumptions!$G$3:$G$102,{"TRC"}))} -> 0 | AX5: =IF(SUM(D5:AW5)=0,"zero","") -> zero | AY5: * | BA5: =IF($AZ5="","",$BA$45) | BB5: =IF($AZ5="","",25) | BD5: =IF(AZ5="","*","DMD") -> * | BE5: =AZ5 -> 0 | BG5: Bvkm | BH5: million Vehicles | BI5: yes
A6: TR | C6: TRADST | D6: {=SUM(SUMIFS(Assumptions!BD$3:BD$102,Assumptions!$B$3:$B$102,'Trucks-lcv'!$C6,Assumptions!$G$3:$G$102,{"TRC"}))} -> 200.1637 | E6: {=SUM(SUMIFS(Assumptions!BE$3:BE$102,Assumptions!$B$3:$B$102,'Trucks-lcv'!$C6,Assumptions!$G$3:$G$102,{"TRC"}))} -> 177.88097 | F6: {=SUM(SUMIFS(Assumptions!BF$3:BF$102,Assumptions!$B$3:$B$102,'Trucks-lcv'!$C6,Assumptions!$G$3:$G$102,{"TRC"}))} -> 112.82503 | G6: {=SUM(SUMIFS(Assumptions!BG$3:BG$102,Assumptions!$B$3:$B$102,'Trucks-lcv'!$C6,Assumptions!$G$3:$G$102,{"TRC"}))} -> 31.038065 | H6: {=SUM(SUMIFS(Assumptions!BH$3:BH$102,Assumptions!$B$3:$B$102,'Trucks-lcv'!$C6,Assumptions!$G$3:$G$102,{"TRC"}))} -> 11.520655 | I6: {=SUM(SUMIFS(Assumptions!BI$3:BI$102,Assumptions!$B$3:$B$102,'Trucks-lcv'!$C6,Assumptions!$G$3:$G$102,{"TRC"}))} -> 65.787862 | J6: {=SUM(SUMIFS(Assumptions!BJ$3:BJ$102,Assumptions!$B$3:$B$102,'Trucks-lcv'!$C6,Assumptions!$G$3:$G$102,{"TRC"}))} -> 133.54722 | K6: {=SUM(SUMIFS(Assumptions!BK$3:BK$102,Assumptions!$B$3:$B$102,'Trucks-lcv'!$C6,Assumptions!$G$3:$G$102,{"TRC"}))} -> 349.32345 | ... AW6: {=SUM(SUMIFS(Assumptions!CW$3:CW$102,Assumptions!$B$3:$B$102,'Trucks-lcv'!$C6,Assumptions!$G$3:$G$102,{"TRC"}))} -> 0 | AX6: =IF(SUM(D6:AW6)=0,"zero","") | AY6: * | BA6: =IF($AZ6="","",$BA$45) | BB6: =IF($AZ6="","",25) | BD6: =IF(AZ6="","*","DMD") -> * | BE6: =AZ6 -> 0 | BG6: Bvkm | BH6: million Vehicles | BI6: yes
A7: TR | C7: TRAELC | D7: {=SUM(SUMIFS(Assumptions!BD$3:BD$102,Assumptions!$B$3:$B$102,'Trucks-lcv'!$C7,Assumptions!$G$3:$G$102,{"TRC"}))} -> 0 | E7: {=SUM(SUMIFS(Assumptions!BE$3:BE$102,Assumptions!$B$3:$B$102,'Trucks-lcv'!$C7,Assumptions!$G$3:$G$102,{"TRC"}))} -> 0 | F7: {=SUM(SUMIFS(Assumptions!BF$3:BF$102,Assumptions!$B$3:$B$102,'Trucks-lcv'!$C7,Assumptions!$G$3:$G$102,{"TRC"}))} -> 0 | G7: {=SUM(SUMIFS(Assumptions!BG$3:BG$102,Assumptions!$B$3:$B$102,'Trucks-lcv'!$C7,Assumptions!$G$3:$G$102,{"TRC"}))} -> 0 | H7: {=SUM(SUMIFS(Assumptions!BH$3:BH$102,Assumptions!$B$3:$B$102,'Trucks-lcv'!$C7,Assumptions!$G$3:$G$102,{"TRC"}))} -> 0 | I7: {=SUM(SUMIFS(Assumptions!BI$3:BI$102,Assumptions!$B$3:$B$102,'Trucks-lcv'!$C7,Assumptions!$G$3:$G$102,{"TRC"}))} -> 0 | J7: {=SUM(SUMIFS(Assumptions!BJ$3:BJ$102,Assumptions!$B$3:$B$102,'Trucks-lcv'!$C7,Assumptions!$G$3:$G$102,{"TRC"}))} -> 0 | K7: {=SUM(SUMIFS(Assumptions!BK$3:BK$102,Assumptions!$B$3:$B$102,'Trucks-lcv'!$C7,Assumptions!$G$3:$G$102,{"TRC"}))} -> 24.536301 | ... AW7: {=SUM(SUMIFS(Assumptions!CW$3:CW$102,Assumptions!$B$3:$B$102,'Trucks-lcv'!$C7,Assumptions!$G$3:$G$102,{"TRC"}))} -> 0 | AX7: =IF(SUM(D7:AW7)=0,"zero","") | AY7: * | BA7: =IF($AZ7="","",$BA$45) | BB7: =IF($AZ7="","",25) | BD7: =IF(AZ7="","*","DMD") -> * | BE7: =AZ7 -> 0 | BG7: Bvkm | BH7: million Vehicles | BI7: yes
A8: TR | C8: TRAGSL | D8: {=SUM(SUMIFS(Assumptions!BD$3:BD$102,Assumptions!$B$3:$B$102,'Trucks-lcv'!$C8,Assumptions!$G$3:$G$102,{"TRC"}))} -> 0 | E8: {=SUM(SUMIFS(Assumptions!BE$3:BE$102,Assumptions!$B$3:$B$102,'Trucks-lcv'!$C8,Assumptions!$G$3:$G$102,{"TRC"}))} -> 0 | F8: {=SUM(SUMIFS(Assumptions!BF$3:BF$102,Assumptions!$B$3:$B$102,'Trucks-lcv'!$C8,Assumptions!$G$3:$G$102,{"TRC"}))} -> 54.047574 | G8: {=SUM(SUMIFS(Assumptions!BG$3:BG$102,Assumptions!$B$3:$B$102,'Trucks-lcv'!$C8,Assumptions!$G$3:$G$102,{"TRC"}))} -> 1.9734589 | H8: {=SUM(SUMIFS(Assumptions!BH$3:BH$102,Assumptions!$B$3:$B$102,'Trucks-lcv'!$C8,Assumptions!$G$3:$G$102,{"TRC"}))} -> 4.7711269 | I8: {=SUM(SUMIFS(Assumptions!BI$3:BI$102,Assumptions!$B$3:$B$102,'Trucks-lcv'!$C8,Assumptions!$G$3:$G$102,{"TRC"}))} -> 7.6354931 | J8: {=SUM(SUMIFS(Assumptions!BJ$3:BJ$102,Assumptions!$B$3:$B$102,'Trucks-lcv'!$C8,Assumptions!$G$3:$G$102,{"TRC"}))} -> 52.094547 | K8: {=SUM(SUMIFS(Assumptions!BK$3:BK$102,Assumptions!$B$3:$B$102,'Trucks-lcv'!$C8,Assumptions!$G$3:$G$102,{"TRC"}))} -> 480.15158 | ... AW8: {=SUM(SUMIFS(Assumptions!CW$3:CW$102,Assumptions!$B$3:$B$102,'Trucks-lcv'!$C8,Assumptions!$G$3:$G$102,{"TRC"}))} -> 0 | AX8: =IF(SUM(D8:AW8)=0,"zero","") | AY8: * | BA8: =IF($AZ8="","",$BA$45) | BB8: =IF($AZ8="","",25) | BD8: =IF(AZ8="","*","DMD") -> * | BE8: =AZ8 -> 0 | BG8: Bvkm | BH8: million Vehicles | BI8: yes
A9: TR | C9: TRALPG | D9: {=SUM(SUMIFS(Assumptions!BD$3:BD$102,Assumptions!$B$3:$B$102,'Trucks-lcv'!$C9,Assumptions!$G$3:$G$102,{"TRC"}))} -> 12.023198 | E9: {=SUM(SUMIFS(Assumptions!BE$3:BE$102,Assumptions!$B$3:$B$102,'Trucks-lcv'!$C9,Assumptions!$G$3:$G$102,{"TRC"}))} -> 0.0069001813 | F9: {=SUM(SUMIFS(Assumptions!BF$3:BF$102,Assumptions!$B$3:$B$102,'Trucks-lcv'!$C9,Assumptions!$G$3:$G$102,{"TRC"}))} -> 2.281164 | G9: {=SUM(SUMIFS(Assumptions!BG$3:BG$102,Assumptions!$B$3:$B$102,'Trucks-lcv'!$C9,Assumptions!$G$3:$G$102,{"TRC"}))} -> 0.05484394 | H9: {=SUM(SUMIFS(Assumptions!BH$3:BH$102,Assumptions!$B$3:$B$102,'Trucks-lcv'!$C9,Assumptions!$G$3:$G$102,{"TRC"}))} -> 2.9748518 | I9: {=SUM(SUMIFS(Assumptions!BI$3:BI$102,Assumptions!$B$3:$B$102,'Trucks-lcv'!$C9,Assumptions!$G$3:$G$102,{"TRC"}))} -> 2.0472416 | J9: {=SUM(SUMIFS(Assumptions!BJ$3:BJ$102,Assumptions!$B$3:$B$102,'Trucks-lcv'!$C9,Assumptions!$G$3:$G$102,{"TRC"}))} -> 0 | K9: {=SUM(SUMIFS(Assumptions!BK$3:BK$102,Assumptions!$B$3:$B$102,'Trucks-lcv'!$C9,Assumptions!$G$3:$G$102,{"TRC"}))} -> 9.3962589 | ... AW9: {=SUM(SUMIFS(Assumptions!CW$3:CW$102,Assumptions!$B$3:$B$102,'Trucks-lcv'!$C9,Assumptions!$G$3:$G$102,{"TRC"}))} -> 0 | AX9: =IF(SUM(D9:AW9)=0,"zero","") | AY9: * | BA9: =IF($AZ9="","",$BA$45) | BB9: =IF($AZ9="","",25) | BD9: =IF(AZ9="","*","DMD") -> * | BE9: =AZ9 -> 0 | BG9: Bvkm | BH9: million Vehicles | BI9: yes
A10: TR | C10: TRANGA | D10: {=SUM(SUMIFS(Assumptions!BD$3:BD$102,Assumptions!$B$3:$B$102,'Trucks-lcv'!$C10,Assumptions!$G$3:$G$102,{"TRC"}))} -> 3.052208 | E10: {=SUM(SUMIFS(Assumptions!BE$3:BE$102,Assumptions!$B$3:$B$102,'Trucks-lcv'!$C10,Assumptions!$G$3:$G$102,{"TRC"}))} -> 0.011203249 | F10: {=SUM(SUMIFS(Assumptions!BF$3:BF$102,Assumptions!$B$3:$B$102,'Trucks-lcv'!$C10,Assumptions!$G$3:$G$102,{"TRC"}))} -> 0.46851799 | G10: {=SUM(SUMIFS(Assumptions!BG$3:BG$102,Assumptions!$B$3:$B$102,'Trucks-lcv'!$C10,Assumptions!$G$3:$G$102,{"TRC"}))} -> 0 | H10: {=SUM(SUMIFS(Assumptions!BH$3:BH$102,Assumptions!$B$3:$B$102,'Trucks-lcv'!$C10,Assumptions!$G$3:$G$102,{"TRC"}))} -> 0.24127524 | I10: {=SUM(SUMIFS(Assumptions!BI$3:BI$102,Assumptions!$B$3:$B$102,'Trucks-lcv'!$C10,Assumptions!$G$3:$G$102,{"TRC"}))} -> 0 | J10: {=SUM(SUMIFS(Assumptions!BJ$3:BJ$102,Assumptions!$B$3:$B$102,'Trucks-lcv'!$C10,Assumptions!$G$3:$G$102,{"TRC"}))} -> 16.834614 | K10: {=SUM(SUMIFS(Assumptions!BK$3:BK$102,Assumptions!$B$3:$B$102,'Trucks-lcv'!$C10,Assumptions!$G$3:$G$102,{"TRC"}))} -> 123.40084 | ... AW10: {=SUM(SUMIFS(Assumptions!CW$3:CW$102,Assumptions!$B$3:$B$102,'Trucks-lcv'!$C10,Assumptions!$G$3:$G$102,{"TRC"}))} -> 0 | AX10: =IF(SUM(D10:AW10)=0,"zero","") | AY10: * | BA10: =IF($AZ10="","",$BA$45) | BB10: =IF($AZ10="","",25) | BD10: =IF(AZ10="","*","DMD") -> * | BE10: =AZ10 -> 0 | BG10: Bvkm | BH10: million Vehicles | BI10: yes
A11: Share of PJ | D11: =SUM(D$4:D$10)/SUM($D$4:$AJ$10) -> 0.024016407 | E11: =SUM(E$4:E$10)/SUM($D$4:$AJ$10) -> 0.019850002 | F11: =SUM(F$4:F$10)/SUM($D$4:$AJ$10) -> 0.018927282 | G11: =SUM(G$4:G$10)/SUM($D$4:$AJ$10) -> 0.0039282126 | H11: =SUM(H$4:H$10)/SUM($D$4:$AJ$10) -> 0.002225279 | I11: =SUM(I$4:I$10)/SUM($D$4:$AJ$10) -> 0.0089154963 | J11: =SUM(J$4:J$10)/SUM($D$4:$AJ$10) -> 0.029348048 | K11: =SUM(K$4:K$10)/SUM($D$4:$AJ$10) -> 0.11048885 | ... AW11: =SUM(AW$4:AW$10)/SUM($D$4:$AJ$10) -> 0 | AX11: =IF(SUM(D11:AW11)=0,"zero","") | AY11: * | BA11: =IF($AZ11="","",$BA$45) | BB11: =IF($AZ11="","",25) | BD11: =IF(AZ11="","*","DMD") -> * | BE11: =AZ11 -> 0 | BG11: Bvkm | BH11: million Vehicles | BI11: yes
AY12: * | BA12: =IF($AZ12="","",$BA$45) | BB12: =IF($AZ12="","",25) | BD12: =IF(AZ12="","*","DMD") -> * | BE12: =AZ12 -> 0 | BG12: Bvkm | BH12: million Vehicles | BI12: yes
A13: m Vehicles | C13: =SUM(D13:AW13) -> 86.909 | D13: =SUM(D19:D25) -> 2.057 | E13: =SUM(E19:E25) -> 1.688 | F13: =SUM(F19:F25) -> 1.604 | G13: =SUM(G19:G25) -> 0.334 | H13: =SUM(H19:H25) -> 0.192 | I13: =SUM(I19:I25) -> 0.76 | J13: =SUM(J19:J25) -> 2.466 | K13: =SUM(K19:K25) -> 9.398 | ... AW13: =SUM(AW19:AW25) -> 0 | AY13: * | BA13: =IF($AZ13="","",$BA$45) | BB13: =IF($AZ13="","",25) | BD13: =IF(AZ13="","*","DMD") -> * | BE13: =AZ13 -> 0 | BG13: Bvkm | BH13: million Vehicles | BI13: yes
A14: Share of Veh | D14: =D13/SUM($D$13:$AJ$13) -> 0.024069177 | E14: =E13/SUM($D$13:$AJ$13) -> 0.019751468 | F14: =F13/SUM($D$13:$AJ$13) -> 0.018768576 | G14: =G13/SUM($D$13:$AJ$13) -> 0.0039081697 | H14: =H13/SUM($D$13:$AJ$13) -> 0.0022466125 | I14: =I13/SUM($D$13:$AJ$13) -> 0.0088928413 | J14: =J13/SUM($D$13:$AJ$13) -> 0.02885493 | K14: =K13/SUM($D$13:$AJ$13) -> 0.109967 | ... AW14: =AW13/SUM($D$13:$AJ$13) -> 0 | AY14: * | BA14: =IF($AZ14="","",$BA$45) | BB14: =IF($AZ14="","",25) | BD14: =IF(AZ14="","*","DMD") -> * | BE14: =AZ14 -> 0 | BG14: Bvkm | BH14: million Vehicles | BI14: yes
D15: =D13/'non-road'!DB21 -> 0.010368725 | E15: =E13/'non-road'!DC21 -> 0.0016243937 | F15: =F13/'non-road'!DD21 -> 0.063234998 | G15: =G13/'non-road'!DE21 -> 0.037612951 | H15: =H13/'non-road'!DF21 -> 0.031815154 | I15: =I13/'non-road'!DG21 -> 0.025803034 | J15: =J13/'non-road'!DH21 -> 0.011684435 | K15: =K13/'non-road'!DI21 -> 0.0067238073 | ... AW15: =AW13/'non-road'!EU21 -> #VALUE! | AY15: * | BA15: =IF($AZ15="","",$BA$45) | BB15: =IF($AZ15="","",25) | BD15: =IF(AZ15="","*","DMD") -> * | BE15: =AZ15 -> 0 | BG15: Bvkm | BH15: million Vehicles | BI15: yes
AY16: * | BA16: =IF($AZ16="","",$BA$45) | BB16: =IF($AZ16="","",25) | BD16: =IF(AZ16="","*","DMD") -> * | BE16: =AZ16 -> 0 | BG16: Bvkm | BH16: million Vehicles | BI16: yes
A17: PJ share/Veh share | D17: =D11/D14 -> 0.99780759 | E17: =E11/E14 -> 1.0049887 | F17: =F11/F14 -> 1.008456 | G17: =G11/G14 -> 1.0051285 | H17: =H11/H14 -> 0.99050412 | I17: =I11/I14 -> 1.0025476 | J17: =J11/J14 -> 1.0170896 | K17: =K11/K14 -> 1.0047455 | ... AW17: =AW11/AW14 -> #DIV/0! | AY17: * | BA17: =IF($AZ17="","",$BA$45) | BB17: =IF($AZ17="","",25) | BD17: =IF(AZ17="","*","DMD") -> * | BE17: =AZ17 -> 0 | BG17: Bvkm | BH17: million Vehicles | BI17: yes
AY18: * | BA18: =IF($AZ18="","",$BA$45) | BB18: =IF($AZ18="","",25) | BD18: =IF(AZ18="","*","DMD") -> * | BE18: =AZ18 -> 0 | BG18: Bvkm | BH18: million Vehicles | BI18: yes
A19: mVeh | C19: =C4 -> TRABDS | D19: =ROUND(D4*D28/D36,3) -> 0 | E19: =ROUND(E4*E28/E36,3) -> 0 | F19: =ROUND(F4*F28/F36,3) -> 0 | G19: =ROUND(G4*G28/G36,3) -> 0.02 | H19: =ROUND(H4*H28/H36,3) -> 0.004 | I19: =ROUND(I4*I28/I36,3) -> 0.042 | J19: =ROUND(J4*J28/J36,3) -> 0.575 | K19: =ROUND(K4*K28/K36,3) -> 0.032 | ... AW19: =ROUND(AW4*AW28/AW36,3) -> 0 | AY19: PASTI | AZ19: =IF(AX4="zero","\I:",$BA$45&"_"&VLOOKUP(C19,'TRA balance'!$BB$5:$BC$15,2,FALSE)) -> Trd_lcv_bdl | BA19: =IF($AZ19="","",$BA$45) -> Trd_lcv | BB19: =IF($AZ19="","",25) -> 25 | BD19: =IF(AZ19="","*","DMD") -> DMD | BE19: =AZ19 -> Trd_lcv_bdl | BG19: Bvkm | BH19: million Vehicles | BI19: yes
C20: =C5 -> TRABGS | D20: =ROUND(D5*D29/D37,3) -> 0 | E20: =ROUND(E5*E29/E37,3) -> 0 | F20: =ROUND(F5*F29/F37,3) -> 0 | G20: =ROUND(G5*G29/G37,3) -> 0 | H20: =ROUND(H5*H29/H37,3) -> 0 | I20: =ROUND(I5*I29/I37,3) -> 0 | J20: =ROUND(J5*J29/J37,3) -> 0 | K20: =ROUND(K5*K29/K37,3) -> 0 | ... AW20: =ROUND(AW5*AW29/AW37,3) -> 0 | AY20: PASTI | AZ20: =IF(AX5="zero","\I:",$BA$45&"_"&VLOOKUP(C20,'TRA balance'!$BB$5:$BC$15,2,FALSE)) -> \I: | BA20: =IF($AZ20="","",$BA$45) -> Trd_lcv | BB20: =IF($AZ20="","",25) -> 25 | BD20: =IF(AZ20="","*","DMD") -> DMD | BE20: =AZ20 -> \I: | BG20: Bvkm | BH20: million Vehicles | BI20: yes
C21: =C6 -> TRADST | D21: =ROUND(D6*D30/D38,3) -> 1.9 | E21: =ROUND(E6*E30/E38,3) -> 1.688 | F21: =ROUND(F6*F30/F38,3) -> 1.071 | G21: =ROUND(G6*G30/G38,3) -> 0.295 | H21: =ROUND(H6*H30/H38,3) -> 0.109 | I21: =ROUND(I6*I30/I38,3) -> 0.624 | J21: =ROUND(J6*J30/J38,3) -> 1.267 | K21: =ROUND(K6*K30/K38,3) -> 3.315 | ... AW21: =ROUND(AW6*AW30/AW38,3) -> 0 | AY21: PASTI | AZ21: =IF(AX6="zero","\I:",$BA$45&"_"&VLOOKUP(C21,'TRA balance'!$BB$5:$BC$15,2,FALSE)) -> Trd_lcv_dsl | BA21: =IF($AZ21="","",$BA$45) -> Trd_lcv | BB21: =IF($AZ21="","",25) -> 25 | BD21: =IF(AZ21="","*","DMD") -> DMD | BE21: =AZ21 -> Trd_lcv_dsl | BG21: Bvkm | BH21: million Vehicles | BI21: yes
C22: =C7 -> TRAELC | D22: =ROUND(D7*D31/D39,3) -> 0 | E22: =ROUND(E7*E31/E39,3) -> 0 | F22: =ROUND(F7*F31/F39,3) -> 0 | G22: =ROUND(G7*G31/G39,3) -> 0 | H22: =ROUND(H7*H31/H39,3) -> 0 | I22: =ROUND(I7*I31/I39,3) -> 0 | J22: =ROUND(J7*J31/J39,3) -> 0 | K22: =ROUND(K7*K31/K39,3) -> 0.457 | ... AW22: =ROUND(AW7*AW31/AW39,3) -> 0 | AY22: PASTI | AZ22: =IF(AX7="zero","\I:",$BA$45&"_"&VLOOKUP(C22,'TRA balance'!$BB$5:$BC$15,2,FALSE)) -> Trd_lcv_elc | BA22: =IF($AZ22="","",$BA$45) -> Trd_lcv | BB22: =IF($AZ22="","",25) -> 25 | BD22: =IF(AZ22="","*","DMD") -> DMD | BE22: =AZ22 -> Trd_lcv_elc | BG22: Bvkm | BH22: million Vehicles | BI22: yes
C23: =C8 -> TRAGSL | D23: =ROUND(D8*D32/D40,3) -> 0 | E23: =ROUND(E8*E32/E40,3) -> 0 | F23: =ROUND(F8*F32/F40,3) -> 0.504 | G23: =ROUND(G8*G32/G40,3) -> 0.018 | H23: =ROUND(H8*H32/H40,3) -> 0.044 | I23: =ROUND(I8*I32/I40,3) -> 0.071 | J23: =ROUND(J8*J32/J40,3) -> 0.485 | K23: =ROUND(K8*K32/K40,3) -> 4.474 | ... AW23: =ROUND(AW8*AW32/AW40,3) -> 0 | AY23: PASTI | AZ23: =IF(AX8="zero","\I:",$BA$45&"_"&VLOOKUP(C23,'TRA balance'!$BB$5:$BC$15,2,FALSE)) -> Trd_lcv_gsl | BA23: =IF($AZ23="","",$BA$45) -> Trd_lcv | BB23: =IF($AZ23="","",25) -> 25 | BD23: =IF(AZ23="","*","DMD") -> DMD | BE23: =AZ23 -> Trd_lcv_gsl | BG23: Bvkm | BH23: million Vehicles | BI23: yes
C24: =C9 -> TRALPG | D24: =ROUND(D9*D33/D41,3) -> 0.132 | E24: =ROUND(E9*E33/E41,3) -> 0 | F24: =ROUND(F9*F33/F41,3) -> 0.025 | G24: =ROUND(G9*G33/G41,3) -> 0.001 | H24: =ROUND(H9*H33/H41,3) -> 0.033 | I24: =ROUND(I9*I33/I41,3) -> 0.023 | J24: =ROUND(J9*J33/J41,3) -> 0 | K24: =ROUND(K9*K33/K41,3) -> 0.104 | ... AW24: =ROUND(AW9*AW33/AW41,3) -> 0 | AY24: PASTI | AZ24: =IF(AX9="zero","\I:",$BA$45&"_"&VLOOKUP(C24,'TRA balance'!$BB$5:$BC$15,2,FALSE)) -> Trd_lcv_lpg | BA24: =IF($AZ24="","",$BA$45) -> Trd_lcv | BB24: =IF($AZ24="","",25) -> 25 | BD24: =IF(AZ24="","*","DMD") -> DMD | BE24: =AZ24 -> Trd_lcv_lpg | BG24: Bvkm | BH24: million Vehicles | BI24: yes
C25: =C10 -> TRANGA | D25: =ROUND(D10*D34/D42,3) -> 0.025 | E25: =ROUND(E10*E34/E42,3) -> 0 | F25: =ROUND(F10*F34/F42,3) -> 0.004 | G25: =ROUND(G10*G34/G42,3) -> 0 | H25: =ROUND(H10*H34/H42,3) -> 0.002 | I25: =ROUND(I10*I34/I42,3) -> 0 | J25: =ROUND(J10*J34/J42,3) -> 0.139 | K25: =ROUND(K10*K34/K42,3) -> 1.016 | ... AW25: =ROUND(AW10*AW34/AW42,3) -> 0 | AY25: PASTI | AZ25: =IF(AX10="zero","\I:",$BA$45&"_"&VLOOKUP(C25,'TRA balance'!$BB$5:$BC$15,2,FALSE)) -> Trd_lcv_nga | BA25: =IF($AZ25="","",$BA$45) -> Trd_lcv | BB25: =IF($AZ25="","",25) -> 25 | BD25: =IF(AZ25="","*","DMD") -> DMD | BE25: =AZ25 -> Trd_lcv_nga | BG25: Bvkm | BH25: million Vehicles | BI25: yes
AY26: * | BA26: =IF($AZ26="","",$BA$45) | BB26: =IF($AZ26="","",25) | BD26: =IF(AZ26="","*","DMD") -> * | BE26: =AZ26 -> 0 | BG26: Bvkm | BH26: million Vehicles | BI26: yes
D27: 1 | E27: 1 | F27: 1 | G27: 1 | H27: 1 | I27: 1 | J27: 1 | K27: 1 | L27: 1 | M27: 1 | N27: 1 | O27: 1 | P27: 1 | Q27: 1 | R27: 1 | S27: 1 | T27: 1 | U27: 1 | V27: 1 | W27: 1 | X27: 1 | Y27: 1 | Z27: 1 | AA27: 1 | AB27: 1 | AC27: 1 | AD27: 1 | AE27: 1 | AF27: 1 | AG27: 1 | AH27: 1 | AI27: 1 | AJ27: 1 | AK27: 1 | AL27: 1 | AM27: 1 | AN27: 1 | AO27: 1 | AP27: 1 | AQ27: 1 | AR27: 1 | AS27: 1 | AT27: 1 | AU27: 1 | AV27: 1 | AW27: 1 | AY27: * | BA27: =IF($AZ27="","",$BA$45) | BB27: =IF($AZ27="","",25) | BD27: =IF(AZ27="","*","DMD") -> * | BE27: =AZ27 -> 0 | BG27: Bvkm | BH27: million Vehicles | BI27: yes
A28: Efficiency | C28: =C19 -> TRABDS | D28: =$AX28*D$27 -> 0.37962602 | E28: =$AX28*E$27 -> 0.37962602 | F28: =$AX28*F$27 -> 0.37962602 | G28: =$AX28*G$27 -> 0.37962602 | H28: =$AX28*H$27 -> 0.37962602 | I28: =$AX28*I$27 -> 0.37962602 | J28: =$AX28*J$27 -> 0.37962602 | K28: =$AX28*K$27 -> 0.37962602 | ... AW28: =$AX28*AW$27 -> 0.37962602 | AX28: =AX30 -> 0.37962602 | AY28: EFF | AZ28: =AZ19 -> Trd_lcv_bdl | BA28: =IF($AZ28="","",$BA$45) -> Trd_lcv | BB28: =IF($AZ28="","",25) -> 25 | BD28: =IF(AZ28="","*","DMD") -> DMD | BE28: =AZ28 -> Trd_lcv_bdl | BG28: Bvkm | BH28: million Vehicles | BI28: yes
C29: =C20 -> TRABGS | D29: =$AX29*D$27 -> 0.37271324 | E29: =$AX29*E$27 -> 0.37271324 | F29: =$AX29*F$27 -> 0.37271324 | G29: =$AX29*G$27 -> 0.37271324 | H29: =$AX29*H$27 -> 0.37271324 | I29: =$AX29*I$27 -> 0.37271324 | J29: =$AX29*J$27 -> 0.37271324 | K29: =$AX29*K$27 -> 0.37271324 | ... AW29: =$AX29*AW$27 -> 0.37271324 | AX29: =AX32 -> 0.37271324 | AY29: EFF | AZ29: =AZ20 -> \I: | BA29: =IF($AZ29="","",$BA$45) -> Trd_lcv | BB29: =IF($AZ29="","",25) -> 25 | BD29: =IF(AZ29="","*","DMD") -> DMD | BE29: =AZ29 -> \I: | BG29: Bvkm | BH29: million Vehicles | BI29: yes
C30: =C21 -> TRADST | D30: =$AX30*D$27 -> 0.37962602 | E30: =$AX30*E$27 -> 0.37962602 | F30: =$AX30*F$27 -> 0.37962602 | G30: =$AX30*G$27 -> 0.37962602 | H30: =$AX30*H$27 -> 0.37962602 | I30: =$AX30*I$27 -> 0.37962602 | J30: =$AX30*J$27 -> 0.37962602 | K30: =$AX30*K$27 -> 0.37962602 | ... AW30: =$AX30*AW$27 -> 0.37962602 | AX30: 0.37962602 | AY30: EFF | AZ30: =AZ21 -> Trd_lcv_dsl | BA30: =IF($AZ30="","",$BA$45) -> Trd_lcv | BB30: =IF($AZ30="","",25) -> 25 | BD30: =IF(AZ30="","*","DMD") -> DMD | BE30: =AZ30 -> Trd_lcv_dsl | BG30: Bvkm | BH30: million Vehicles | BI30: yes
C31: =C22 -> TRAELC | D31: =$AX31*D$27 -> 0.74542647 | E31: =$AX31*E$27 -> 0.74542647 | F31: =$AX31*F$27 -> 0.74542647 | G31: =$AX31*G$27 -> 0.74542647 | H31: =$AX31*H$27 -> 0.74542647 | I31: =$AX31*I$27 -> 0.74542647 | J31: =$AX31*J$27 -> 0.74542647 | K31: =$AX31*K$27 -> 0.74542647 | ... AW31: =$AX31*AW$27 -> 0.74542647 | AX31: =AX32*2 -> 0.74542647 | AY31: EFF | AZ31: =AZ22 -> Trd_lcv_elc | BA31: =IF($AZ31="","",$BA$45) -> Trd_lcv | BB31: =IF($AZ31="","",25) -> 25 | BD31: =IF(AZ31="","*","DMD") -> DMD | BE31: =AZ31 -> Trd_lcv_elc | BG31: Bvkm | BH31: million Vehicles | BI31: yes
C32: =C23 -> TRAGSL | D32: =$AX32*D$27 -> 0.37271324 | E32: =$AX32*E$27 -> 0.37271324 | F32: =$AX32*F$27 -> 0.37271324 | G32: =$AX32*G$27 -> 0.37271324 | H32: =$AX32*H$27 -> 0.37271324 | I32: =$AX32*I$27 -> 0.37271324 | J32: =$AX32*J$27 -> 0.37271324 | K32: =$AX32*K$27 -> 0.37271324 | ... AW32: =$AX32*AW$27 -> 0.37271324 | AX32: 0.37271324 | AY32: EFF | AZ32: =AZ23 -> Trd_lcv_gsl | BA32: =IF($AZ32="","",$BA$45) -> Trd_lcv | BB32: =IF($AZ32="","",25) -> 25 | BD32: =IF(AZ32="","*","DMD") -> DMD | BE32: =AZ32 -> Trd_lcv_gsl | BG32: Bvkm | BH32: million Vehicles | BI32: yes
C33: =C24 -> TRALPG | D33: =$AX33*D$27 -> 0.44075734 | E33: =$AX33*E$27 -> 0.44075734 | F33: =$AX33*F$27 -> 0.44075734 | G33: =$AX33*G$27 -> 0.44075734 | H33: =$AX33*H$27 -> 0.44075734 | I33: =$AX33*I$27 -> 0.44075734 | J33: =$AX33*J$27 -> 0.44075734 | K33: =$AX33*K$27 -> 0.44075734 | ... AW33: =$AX33*AW$27 -> 0.44075734 | AX33: 0.44075734 | AY33: EFF | AZ33: =AZ24 -> Trd_lcv_lpg | BA33: =IF($AZ33="","",$BA$45) -> Trd_lcv | BB33: =IF($AZ33="","",25) -> 25 | BD33: =IF(AZ33="","*","DMD") -> DMD | BE33: =AZ33 -> Trd_lcv_lpg | BG33: Bvkm | BH33: million Vehicles | BI33: yes
C34: =C25 -> TRANGA | D34: =$AX34*D$27 -> 0.32948443 | E34: =$AX34*E$27 -> 0.32948443 | F34: =$AX34*F$27 -> 0.32948443 | G34: =$AX34*G$27 -> 0.32948443 | H34: =$AX34*H$27 -> 0.32948443 | I34: =$AX34*I$27 -> 0.32948443 | J34: =$AX34*J$27 -> 0.32948443 | K34: =$AX34*K$27 -> 0.32948443 | ... AW34: =$AX34*AW$27 -> 0.32948443 | AX34: 0.32948443 | AY34: EFF | AZ34: =AZ25 -> Trd_lcv_nga | BA34: =IF($AZ34="","",$BA$45) -> Trd_lcv | BB34: =IF($AZ34="","",25) -> 25 | BD34: =IF(AZ34="","*","DMD") -> DMD | BE34: =AZ34 -> Trd_lcv_nga | BG34: Bvkm | BH34: million Vehicles | BI34: yes
AY35: * | BA35: =IF($AZ35="","",$BA$45) | BB35: =IF($AZ35="","",25) | BD35: =IF(AZ35="","*","DMD") -> * | BE35: =AZ35 -> 0 | BG35: Bvkm | BH35: million Vehicles | BI35: yes
A36: 000km/veh | C36: =C28 -> TRABDS | D36: 40 | E36: 40 | F36: 40 | G36: 40 | H36: 40 | I36: 40 | J36: 40 | K36: 40 | L36: 40 | M36: 40 | N36: 40 | O36: 40 | P36: 40 | Q36: 40 | R36: 40 | S36: 40 | T36: 40 | U36: 40 | V36: 40 | W36: 40 | X36: 40 | Y36: 40 | Z36: 40 | AA36: 40 | AB36: 40 | AC36: 40 | AD36: 40 | AE36: 40 | AF36: 25 | AG36: 40 | AH36: 40 | AI36: 40 | AJ36: 40 | AK36: 40 | AL36: 15 | AM36: 40 | AN36: 40 | AO36: 40 | AP36: 40 | AQ36: 40 | AR36: 40 | AS36: 40 | AT36: 40 | AU36: 40 | AV36: 40 | AW36: 40 | AY36: AF | AZ36: =AZ28 -> Trd_lcv_bdl | BA36: =IF($AZ36="","",$BA$45) -> Trd_lcv | BB36: =IF($AZ36="","",25) -> 25 | BD36: =IF(AZ36="","*","DMD") -> DMD | BE36: =AZ36 -> Trd_lcv_bdl | BG36: Bvkm | BH36: million Vehicles | BI36: yes
C37: =C29 -> TRABGS | D37: 40 | E37: 40 | F37: 40 | G37: 40 | H37: 40 | I37: 40 | J37: 40 | K37: 40 | L37: 40 | M37: 40 | N37: 40 | O37: 40 | P37: 40 | Q37: 40 | R37: 40 | S37: 40 | T37: 40 | U37: 40 | V37: 40 | W37: 40 | X37: 40 | Y37: 40 | Z37: 40 | AA37: 40 | AB37: 40 | AC37: 40 | AD37: 40 | AE37: 40 | AF37: 25 | AG37: 40 | AH37: 40 | AI37: 40 | AJ37: 40 | AK37: 40 | AL37: 15 | AM37: 40 | AN37: 40 | AO37: 40 | AP37: 40 | AQ37: 40 | AR37: 40 | AS37: 40 | AT37: 40 | AU37: 40 | AV37: 40 | AW37: 40 | AY37: AF | AZ37: =AZ29 -> \I: | BA37: =IF($AZ37="","",$BA$45) -> Trd_lcv | BB37: =IF($AZ37="","",25) -> 25 | BD37: =IF(AZ37="","*","DMD") -> DMD | BE37: =AZ37 -> \I: | BG37: Bvkm | BH37: million Vehicles | BI37: yes
C38: =C30 -> TRADST | D38: 40 | E38: 40 | F38: 40 | G38: 40 | H38: 40 | I38: 40 | J38: 40 | K38: 40 | L38: 40 | M38: 40 | N38: 40 | O38: 40 | P38: 40 | Q38: 40 | R38: 40 | S38: 40 | T38: 40 | U38: 40 | V38: 40 | W38: 40 | X38: 40 | Y38: 40 | Z38: 40 | AA38: 40 | AB38: 40 | AC38: 40 | AD38: 40 | AE38: 40 | AF38: 25 | AG38: 40 | AH38: 40 | AI38: 40 | AJ38: 40 | AK38: 40 | AL38: 15 | AM38: 40 | AN38: 40 | AO38: 40 | AP38: 40 | AQ38: 40 | AR38: 40 | AS38: 40 | AT38: 40 | AU38: 40 | AV38: 40 | AW38: 40 | AY38: AF | AZ38: =AZ30 -> Trd_lcv_dsl | BA38: =IF($AZ38="","",$BA$45) -> Trd_lcv | BB38: =IF($AZ38="","",25) -> 25 | BD38: =IF(AZ38="","*","DMD") -> DMD | BE38: =AZ38 -> Trd_lcv_dsl | BG38: Bvkm | BH38: million Vehicles | BI38: yes
C39: =C31 -> TRAELC | D39: 40 | E39: 40 | F39: 40 | G39: 40 | H39: 40 | I39: 40 | J39: 40 | K39: 40 | L39: 40 | M39: 40 | N39: 40 | O39: 40 | P39: 40 | Q39: 40 | R39: 40 | S39: 40 | T39: 40 | U39: 40 | V39: 40 | W39: 40 | X39: 40 | Y39: 40 | Z39: 40 | AA39: 40 | AB39: 40 | AC39: 40 | AD39: 40 | AE39: 40 | AF39: 25 | AG39: 40 | AH39: 40 | AI39: 40 | AJ39: 40 | AK39: 40 | AL39: 15 | AM39: 40 | AN39: 40 | AO39: 40 | AP39: 40 | AQ39: 40 | AR39: 40 | AS39: 40 | AT39: 40 | AU39: 40 | AV39: 40 | AW39: 40 | AY39: AF | AZ39: =AZ31 -> Trd_lcv_elc | BA39: =IF($AZ39="","",$BA$45) -> Trd_lcv | BB39: =IF($AZ39="","",25) -> 25 | BD39: =IF(AZ39="","*","DMD") -> DMD | BE39: =AZ39 -> Trd_lcv_elc | BG39: Bvkm | BH39: million Vehicles | BI39: yes
C40: =C32 -> TRAGSL | D40: 40 | E40: 40 | F40: 40 | G40: 40 | H40: 40 | I40: 40 | J40: 40 | K40: 40 | L40: 40 | M40: 40 | N40: 40 | O40: 40 | P40: 40 | Q40: 40 | R40: 40 | S40: 40 | T40: 40 | U40: 40 | V40: 40 | W40: 40 | X40: 40 | Y40: 40 | Z40: 40 | AA40: 40 | AB40: 40 | AC40: 40 | AD40: 40 | AE40: 40 | AF40: 25 | AG40: 40 | AH40: 40 | AI40: 40 | AJ40: 40 | AK40: 40 | AL40: 15 | AM40: 40 | AN40: 40 | AO40: 40 | AP40: 40 | AQ40: 40 | AR40: 40 | AS40: 40 | AT40: 40 | AU40: 40 | AV40: 40 | AW40: 40 | AY40: AF | AZ40: =AZ32 -> Trd_lcv_gsl | BA40: =IF($AZ40="","",$BA$45) -> Trd_lcv | BB40: =IF($AZ40="","",25) -> 25 | BD40: =IF(AZ40="","*","DMD") -> DMD | BE40: =AZ40 -> Trd_lcv_gsl | BG40: Bvkm | BH40: million Vehicles | BI40: yes
C41: =C33 -> TRALPG | D41: 40 | E41: 40 | F41: 40 | G41: 40 | H41: 40 | I41: 40 | J41: 40 | K41: 40 | L41: 40 | M41: 40 | N41: 40 | O41: 40 | P41: 40 | Q41: 40 | R41: 40 | S41: 40 | T41: 40 | U41: 40 | V41: 40 | W41: 40 | X41: 40 | Y41: 40 | Z41: 40 | AA41: 40 | AB41: 40 | AC41: 40 | AD41: 40 | AE41: 40 | AF41: 25 | AG41: 40 | AH41: 40 | AI41: 40 | AJ41: 40 | AK41: 40 | AL41: 15 | AM41: 40 | AN41: 40 | AO41: 40 | AP41: 40 | AQ41: 40 | AR41: 40 | AS41: 40 | AT41: 40 | AU41: 40 | AV41: 40 | AW41: 40 | AY41: AF | AZ41: =AZ33 -> Trd_lcv_lpg | BA41: =IF($AZ41="","",$BA$45) -> Trd_lcv | BB41: =IF($AZ41="","",25) -> 25 | BD41: =IF(AZ41="","*","DMD") -> DMD | BE41: =AZ41 -> Trd_lcv_lpg | BG41: Bvkm | BH41: million Vehicles | BI41: yes
C42: =C34 -> TRANGA | D42: 40 | E42: 40 | F42: 40 | G42: 40 | H42: 40 | I42: 40 | J42: 40 | K42: 40 | L42: 40 | M42: 40 | N42: 40 | O42: 40 | P42: 40 | Q42: 40 | R42: 40 | S42: 40 | T42: 40 | U42: 40 | V42: 40 | W42: 40 | X42: 40 | Y42: 40 | Z42: 40 | AA42: 40 | AB42: 40 | AC42: 40 | AD42: 40 | AE42: 40 | AF42: 25 | AG42: 40 | AH42: 40 | AI42: 40 | AJ42: 40 | AK42: 40 | AL42: 15 | AM42: 40 | AN42: 40 | AO42: 40 | AP42: 40 | AQ42: 40 | AR42: 40 | AS42: 40 | AT42: 40 | AU42: 40 | AV42: 40 | AW42: 40 | AY42: AF | AZ42: =AZ34 -> Trd_lcv_nga | BA42: =IF($AZ42="","",$BA$45) -> Trd_lcv | BB42: =IF($AZ42="","",25) -> 25 | BD42: =IF(AZ42="","*","DMD") -> DMD | BE42: =AZ42 -> Trd_lcv_nga | BG42: Bvkm | BH42: million Vehicles | BI42: yes
AY43: * | BB43: =IF($AZ43="","",25)
D44: =D3 -> Africa_North | E44: =E3 -> Africa_Other | F44: =F3 -> Australia | G44: =G3 -> Austria | H44: =H3 -> Baltics | I44: =I3 -> BeNeLux | J44: =J3 -> Brazil | K44: =K3 -> China | ... AW44: =AW3 -> \I: | AY44: * | BB44: =IF($AZ44="","",25)
A45: Dem Bvkm | AY45: Demand | BA45: Trd_lcv | BB45: =IF($AZ45="","",25)
AY47: ~FI_Comm
AY48: CSet | AZ48: CommName | BA48: CommDesc | BB48: Unit
AY49: DEM | AZ49: =BA45 -> Trd_lcv | BB49: Bvkm

Sheet Trucks-hdt
A1: =1-'Trucks-lcv'!$A$1 -> 0.5
AY2: ~FI_T | BD2: ~FI_Process
C3: comm-in | D3: ='TRA balance'!E4 -> Africa_North | E3: ='TRA balance'!F4 -> Africa_Other | F3: ='TRA balance'!G4 -> Australia | G3: ='TRA balance'!H4 -> Austria | H3: ='TRA balance'!I4 -> Baltics | I3: ='TRA balance'!J4 -> BeNeLux | J3: ='TRA balance'!K4 -> Brazil | K3: ='TRA balance'!L4 -> China | ... AW3: ='TRA balance'!AX4 -> \I: | AX3: * | AY3: attribute | AZ3: process | BA3: comm-out | BB3: LIFE | BD3: Sets | BE3: TechName | BF3: TechDesc | BG3: Tact | BH3: Tcap | BI3: Vintage
A4: TR | C4: TRABDS | D4: {=SUM(SUMIFS(Assumptions!BD$3:BD$102,Assumptions!$B$3:$B$102,'Trucks-hdt'!$C4,Assumptions!$G$3:$G$102,{"TRH","TRM"}))} -> 0 | E4: {=SUM(SUMIFS(Assumptions!BE$3:BE$102,Assumptions!$B$3:$B$102,'Trucks-hdt'!$C4,Assumptions!$G$3:$G$102,{"TRH","TRM"}))} -> 0 | F4: {=SUM(SUMIFS(Assumptions!BF$3:BF$102,Assumptions!$B$3:$B$102,'Trucks-hdt'!$C4,Assumptions!$G$3:$G$102,{"TRH","TRM"}))} -> 0.023442856 | G4: {=SUM(SUMIFS(Assumptions!BG$3:BG$102,Assumptions!$B$3:$B$102,'Trucks-hdt'!$C4,Assumptions!$G$3:$G$102,{"TRH","TRM"}))} -> 11.407667 | H4: {=SUM(SUMIFS(Assumptions!BH$3:BH$102,Assumptions!$B$3:$B$102,'Trucks-hdt'!$C4,Assumptions!$G$3:$G$102,{"TRH","TRM"}))} -> 3.4833386 | I4: {=SUM(SUMIFS(Assumptions!BI$3:BI$102,Assumptions!$B$3:$B$102,'Trucks-hdt'!$C4,Assumptions!$G$3:$G$102,{"TRH","TRM"}))} -> 23.635141 | J4: {=SUM(SUMIFS(Assumptions!BJ$3:BJ$102,Assumptions!$B$3:$B$102,'Trucks-hdt'!$C4,Assumptions!$G$3:$G$102,{"TRH","TRM"}))} -> 484.36626 | K4: {=SUM(SUMIFS(Assumptions!BK$3:BK$102,Assumptions!$B$3:$B$102,'Trucks-hdt'!$C4,Assumptions!$G$3:$G$102,{"TRH","TRM"}))} -> 18.76248 | ... AW4: {=SUM(SUMIFS(Assumptions!CW$3:CW$102,Assumptions!$B$3:$B$102,'Trucks-hdt'!$C4,Assumptions!$G$3:$G$102,{"TRH","TRM"}))} -> 0 | AX4: =IF(SUM(D4:AW4)=0,"zero","") | AY4: * | BA4: =IF($AZ4="","",$BA$45) | BB4: =IF($AZ4="","",25) | BD4: =IF($AZ4="","*","DMD") -> * | BE4: =AZ4 -> 0 | BG4: Bvkm | BH4: million Vehicles | BI4: yes
A5: TR | C5: TRABGS | D5: {=SUM(SUMIFS(Assumptions!BD$3:BD$102,Assumptions!$B$3:$B$102,'Trucks-hdt'!$C5,Assumptions!$G$3:$G$102,{"TRH","TRM"}))} -> 0 | E5: {=SUM(SUMIFS(Assumptions!BE$3:BE$102,Assumptions!$B$3:$B$102,'Trucks-hdt'!$C5,Assumptions!$G$3:$G$102,{"TRH","TRM"}))} -> 0 | F5: {=SUM(SUMIFS(Assumptions!BF$3:BF$102,Assumptions!$B$3:$B$102,'Trucks-hdt'!$C5,Assumptions!$G$3:$G$102,{"TRH","TRM"}))} -> 0 | G5: {=SUM(SUMIFS(Assumptions!BG$3:BG$102,Assumptions!$B$3:$B$102,'Trucks-hdt'!$C5,Assumptions!$G$3:$G$102,{"TRH","TRM"}))} -> 0 | H5: {=SUM(SUMIFS(Assumptions!BH$3:BH$102,Assumptions!$B$3:$B$102,'Trucks-hdt'!$C5,Assumptions!$G$3:$G$102,{"TRH","TRM"}))} -> 0 | I5: {=SUM(SUMIFS(Assumptions!BI$3:BI$102,Assumptions!$B$3:$B$102,'Trucks-hdt'!$C5,Assumptions!$G$3:$G$102,{"TRH","TRM"}))} -> 0 | J5: {=SUM(SUMIFS(Assumptions!BJ$3:BJ$102,Assumptions!$B$3:$B$102,'Trucks-hdt'!$C5,Assumptions!$G$3:$G$102,{"TRH","TRM"}))} -> 0 | K5: {=SUM(SUMIFS(Assumptions!BK$3:BK$102,Assumptions!$B$3:$B$102,'Trucks-hdt'!$C5,Assumptions!$G$3:$G$102,{"TRH","TRM"}))} -> 0 | ... AW5: {=SUM(SUMIFS(Assumptions!CW$3:CW$102,Assumptions!$B$3:$B$102,'Trucks-hdt'!$C5,Assumptions!$G$3:$G$102,{"TRH","TRM"}))} -> 0 | AX5: =IF(SUM(D5:AW5)=0,"zero","") -> zero | AY5: * | BA5: =IF($AZ5="","",$BA$45) | BB5: =IF($AZ5="","",25) | BD5: =IF(AZ5="","*","DMD") -> * | BE5: =AZ5 -> 0 | BG5: Bvkm | BH5: million Vehicles | BI5: yes
A6: TR | C6: TRADST | D6: {=SUM(SUMIFS(Assumptions!BD$3:BD$102,Assumptions!$B$3:$B$102,'Trucks-hdt'!$C6,Assumptions!$G$3:$G$102,{"TRH","TRM"}))} -> 450.36832 | E6: {=SUM(SUMIFS(Assumptions!BE$3:BE$102,Assumptions!$B$3:$B$102,'Trucks-hdt'!$C6,Assumptions!$G$3:$G$102,{"TRH","TRM"}))} -> 400.23219 | F6: {=SUM(SUMIFS(Assumptions!BF$3:BF$102,Assumptions!$B$3:$B$102,'Trucks-hdt'!$C6,Assumptions!$G$3:$G$102,{"TRH","TRM"}))} -> 366.68135 | G6: {=SUM(SUMIFS(Assumptions!BG$3:BG$102,Assumptions!$B$3:$B$102,'Trucks-hdt'!$C6,Assumptions!$G$3:$G$102,{"TRH","TRM"}))} -> 165.53635 | H6: {=SUM(SUMIFS(Assumptions!BH$3:BH$102,Assumptions!$B$3:$B$102,'Trucks-hdt'!$C6,Assumptions!$G$3:$G$102,{"TRH","TRM"}))} -> 92.165242 | I6: {=SUM(SUMIFS(Assumptions!BI$3:BI$102,Assumptions!$B$3:$B$102,'Trucks-hdt'!$C6,Assumptions!$G$3:$G$102,{"TRH","TRM"}))} -> 350.8686 | J6: {=SUM(SUMIFS(Assumptions!BJ$3:BJ$102,Assumptions!$B$3:$B$102,'Trucks-hdt'!$C6,Assumptions!$G$3:$G$102,{"TRH","TRM"}))} -> 1068.3778 | K6: {=SUM(SUMIFS(Assumptions!BK$3:BK$102,Assumptions!$B$3:$B$102,'Trucks-hdt'!$C6,Assumptions!$G$3:$G$102,{"TRH","TRM"}))} -> 1921.2789 | ... AW6: {=SUM(SUMIFS(Assumptions!CW$3:CW$102,Assumptions!$B$3:$B$102,'Trucks-hdt'!$C6,Assumptions!$G$3:$G$102,{"TRH","TRM"}))} -> 0 | AX6: =IF(SUM(D6:AW6)=0,"zero","") | AY6: * | BA6: =IF($AZ6="","",$BA$45) | BB6: =IF($AZ6="","",25) | BD6: =IF(AZ6="","*","DMD") -> * | BE6: =AZ6 -> 0 | BG6: Bvkm | BH6: million Vehicles | BI6: yes
A7: TR | C7: TRAELC | D7: {=SUM(SUMIFS(Assumptions!BD$3:BD$102,Assumptions!$B$3:$B$102,'Trucks-hdt'!$C7,Assumptions!$G$3:$G$102,{"TRH","TRM"}))} -> 0 | E7: {=SUM(SUMIFS(Assumptions!BE$3:BE$102,Assumptions!$B$3:$B$102,'Trucks-hdt'!$C7,Assumptions!$G$3:$G$102,{"TRH","TRM"}))} -> 0 | F7: {=SUM(SUMIFS(Assumptions!BF$3:BF$102,Assumptions!$B$3:$B$102,'Trucks-hdt'!$C7,Assumptions!$G$3:$G$102,{"TRH","TRM"}))} -> 0 | G7: {=SUM(SUMIFS(Assumptions!BG$3:BG$102,Assumptions!$B$3:$B$102,'Trucks-hdt'!$C7,Assumptions!$G$3:$G$102,{"TRH","TRM"}))} -> 0 | H7: {=SUM(SUMIFS(Assumptions!BH$3:BH$102,Assumptions!$B$3:$B$102,'Trucks-hdt'!$C7,Assumptions!$G$3:$G$102,{"TRH","TRM"}))} -> 0 | I7: {=SUM(SUMIFS(Assumptions!BI$3:BI$102,Assumptions!$B$3:$B$102,'Trucks-hdt'!$C7,Assumptions!$G$3:$G$102,{"TRH","TRM"}))} -> 0 | J7: {=SUM(SUMIFS(Assumptions!BJ$3:BJ$102,Assumptions!$B$3:$B$102,'Trucks-hdt'!$C7,Assumptions!$G$3:$G$102,{"TRH","TRM"}))} -> 0 | K7: {=SUM(SUMIFS(Assumptions!BK$3:BK$102,Assumptions!$B$3:$B$102,'Trucks-hdt'!$C7,Assumptions!$G$3:$G$102,{"TRH","TRM"}))} -> 0 | ... AW7: {=SUM(SUMIFS(Assumptions!CW$3:CW$102,Assumptions!$B$3:$B$102,'Trucks-hdt'!$C7,Assumptions!$G$3:$G$102,{"TRH","TRM"}))} -> 0 | AX7: =IF(SUM(D7:AW7)=0,"zero","") -> zero | AY7: * | BA7: =IF($AZ7="","",$BA$45) | BB7: =IF($AZ7="","",25) | BD7: =IF(AZ7="","*","DMD") -> * | BE7: =AZ7 -> 0 | BG7: Bvkm | BH7: million Vehicles | BI7: yes
A8: TR | C8: TRAGSL | D8: {=SUM(SUMIFS(Assumptions!BD$3:BD$102,Assumptions!$B$3:$B$102,'Trucks-hdt'!$C8,Assumptions!$G$3:$G$102,{"TRH","TRM"}))} -> 0 | E8: {=SUM(SUMIFS(Assumptions!BE$3:BE$102,Assumptions!$B$3:$B$102,'Trucks-hdt'!$C8,Assumptions!$G$3:$G$102,{"TRH","TRM"}))} -> 0 | F8: {=SUM(SUMIFS(Assumptions!BF$3:BF$102,Assumptions!$B$3:$B$102,'Trucks-hdt'!$C8,Assumptions!$G$3:$G$102,{"TRH","TRM"}))} -> 0 | G8: {=SUM(SUMIFS(Assumptions!BG$3:BG$102,Assumptions!$B$3:$B$102,'Trucks-hdt'!$C8,Assumptions!$G$3:$G$102,{"TRH","TRM"}))} -> 0 | H8: {=SUM(SUMIFS(Assumptions!BH$3:BH$102,Assumptions!$B$3:$B$102,'Trucks-hdt'!$C8,Assumptions!$G$3:$G$102,{"TRH","TRM"}))} -> 3.4699105 | I8: {=SUM(SUMIFS(Assumptions!BI$3:BI$102,Assumptions!$B$3:$B$102,'Trucks-hdt'!$C8,Assumptions!$G$3:$G$102,{"TRH","TRM"}))} -> 0 | J8: {=SUM(SUMIFS(Assumptions!BJ$3:BJ$102,Assumptions!$B$3:$B$102,'Trucks-hdt'!$C8,Assumptions!$G$3:$G$102,{"TRH","TRM"}))} -> 26.945455 | K8: {=SUM(SUMIFS(Assumptions!BK$3:BK$102,Assumptions!$B$3:$B$102,'Trucks-hdt'!$C8,Assumptions!$G$3:$G$102,{"TRH","TRM"}))} -> 60.018947 | ... AW8: {=SUM(SUMIFS(Assumptions!CW$3:CW$102,Assumptions!$B$3:$B$102,'Trucks-hdt'!$C8,Assumptions!$G$3:$G$102,{"TRH","TRM"}))} -> 0 | AX8: =IF(SUM(D8:AW8)=0,"zero","") | AY8: * | BA8: =IF($AZ8="","",$BA$45) | BB8: =IF($AZ8="","",25) | BD8: =IF(AZ8="","*","DMD") -> * | BE8: =AZ8 -> 0 | BG8: Bvkm | BH8: million Vehicles | BI8: yes
A9: TR | C9: TRALPG | D9: {=SUM(SUMIFS(Assumptions!BD$3:BD$102,Assumptions!$B$3:$B$102,'Trucks-hdt'!$C9,Assumptions!$G$3:$G$102,{"TRH","TRM"}))} -> 0 | E9: {=SUM(SUMIFS(Assumptions!BE$3:BE$102,Assumptions!$B$3:$B$102,'Trucks-hdt'!$C9,Assumptions!$G$3:$G$102,{"TRH","TRM"}))} -> 0 | F9: {=SUM(SUMIFS(Assumptions!BF$3:BF$102,Assumptions!$B$3:$B$102,'Trucks-hdt'!$C9,Assumptions!$G$3:$G$102,{"TRH","TRM"}))} -> 0 | G9: {=SUM(SUMIFS(Assumptions!BG$3:BG$102,Assumptions!$B$3:$B$102,'Trucks-hdt'!$C9,Assumptions!$G$3:$G$102,{"TRH","TRM"}))} -> 0 | H9: {=SUM(SUMIFS(Assumptions!BH$3:BH$102,Assumptions!$B$3:$B$102,'Trucks-hdt'!$C9,Assumptions!$G$3:$G$102,{"TRH","TRM"}))} -> 0 | I9: {=SUM(SUMIFS(Assumptions!BI$3:BI$102,Assumptions!$B$3:$B$102,'Trucks-hdt'!$C9,Assumptions!$G$3:$G$102,{"TRH","TRM"}))} -> 0 | J9: {=SUM(SUMIFS(Assumptions!BJ$3:BJ$102,Assumptions!$B$3:$B$102,'Trucks-hdt'!$C9,Assumptions!$G$3:$G$102,{"TRH","TRM"}))} -> 0 | K9: {=SUM(SUMIFS(Assumptions!BK$3:BK$102,Assumptions!$B$3:$B$102,'Trucks-hdt'!$C9,Assumptions!$G$3:$G$102,{"TRH","TRM"}))} -> 0 | ... AW9: {=SUM(SUMIFS(Assumptions!CW$3:CW$102,Assumptions!$B$3:$B$102,'Trucks-hdt'!$C9,Assumptions!$G$3:$G$102,{"TRH","TRM"}))} -> 0 | AX9: =IF(SUM(D9:AW9)=0,"zero","") -> zero | AY9: * | BA9: =IF($AZ9="","",$BA$45) | BB9: =IF($AZ9="","",25) | BD9: =IF(AZ9="","*","DMD") -> * | BE9: =AZ9 -> 0 | BG9: Bvkm | BH9: million Vehicles | BI9: yes
A10: TR | C10: TRANGA | D10: {=SUM(SUMIFS(Assumptions!BD$3:BD$102,Assumptions!$B$3:$B$102,'Trucks-hdt'!$C10,Assumptions!$G$3:$G$102,{"TRH","TRM"}))} -> 0 | E10: {=SUM(SUMIFS(Assumptions!BE$3:BE$102,Assumptions!$B$3:$B$102,'Trucks-hdt'!$C10,Assumptions!$G$3:$G$102,{"TRH","TRM"}))} -> 0 | F10: {=SUM(SUMIFS(Assumptions!BF$3:BF$102,Assumptions!$B$3:$B$102,'Trucks-hdt'!$C10,Assumptions!$G$3:$G$102,{"TRH","TRM"}))} -> 0 | G10: {=SUM(SUMIFS(Assumptions!BG$3:BG$102,Assumptions!$B$3:$B$102,'Trucks-hdt'!$C10,Assumptions!$G$3:$G$102,{"TRH","TRM"}))} -> 0 | H10: {=SUM(SUMIFS(Assumptions!BH$3:BH$102,Assumptions!$B$3:$B$102,'Trucks-hdt'!$C10,Assumptions!$G$3:$G$102,{"TRH","TRM"}))} -> 0 | I10: {=SUM(SUMIFS(Assumptions!BI$3:BI$102,Assumptions!$B$3:$B$102,'Trucks-hdt'!$C10,Assumptions!$G$3:$G$102,{"TRH","TRM"}))} -> 0 | J10: {=SUM(SUMIFS(Assumptions!BJ$3:BJ$102,Assumptions!$B$3:$B$102,'Trucks-hdt'!$C10,Assumptions!$G$3:$G$102,{"TRH","TRM"}))} -> 0 | K10: {=SUM(SUMIFS(Assumptions!BK$3:BK$102,Assumptions!$B$3:$B$102,'Trucks-hdt'!$C10,Assumptions!$G$3:$G$102,{"TRH","TRM"}))} -> 0 | ... AW10: {=SUM(SUMIFS(Assumptions!CW$3:CW$102,Assumptions!$B$3:$B$102,'Trucks-hdt'!$C10,Assumptions!$G$3:$G$102,{"TRH","TRM"}))} -> 0 | AX10: =IF(SUM(D10:AW10)=0,"zero","") -> zero | AY10: * | BA10: =IF($AZ10="","",$BA$45) | BB10: =IF($AZ10="","",25) | BD10: =IF(AZ10="","*","DMD") -> * | BE10: =AZ10 -> 0 | BG10: Bvkm | BH10: million Vehicles | BI10: yes
A11: Share of PJ | D11: =SUM(D$4:D$10)/SUM($D$4:$AJ$10) -> 0.016815037 | E11: =SUM(E$4:E$10)/SUM($D$4:$AJ$10) -> 0.014943145 | F11: =SUM(F$4:F$10)/SUM($D$4:$AJ$10) -> 0.01369136 | G11: =SUM(G$4:G$10)/SUM($D$4:$AJ$10) -> 0.0066064154 | H11: =SUM(H$4:H$10)/SUM($D$4:$AJ$10) -> 0.0037007068 | I11: =SUM(I$4:I$10)/SUM($D$4:$AJ$10) -> 0.013982543 | J11: =SUM(J$4:J$10)/SUM($D$4:$AJ$10) -> 0.058979588 | K11: =SUM(K$4:K$10)/SUM($D$4:$AJ$10) -> 0.074674635 | ... AW11: =SUM(AW$4:AW$10)/SUM($D$4:$AJ$10) -> 0 | AY11: * | BA11: =IF($AZ11="","",$BA$45) | BB11: =IF($AZ11="","",25) | BD11: =IF(AZ11="","*","DMD") -> * | BE11: =AZ11 -> 0 | BG11: Bvkm | BH11: million Vehicles | BI11: yes
AY12: * | BA12: =IF($AZ12="","",$BA$45) | BB12: =IF($AZ12="","",25) | BD12: =IF(AZ12="","*","DMD") -> * | BE12: =AZ12 -> 0 | BG12: Bvkm | BH12: million Vehicles | BI12: yes
A13: m Vehicles | C13: =SUM(D13:AW13) -> 39.905 | D13: =SUM(D19:D25) -> 0.628 | E13: =SUM(E19:E25) -> 0.558 | F13: =SUM(F19:F25) -> 0.511 | G13: =SUM(G19:G25) -> 0.247 | H13: =SUM(H19:H25) -> 0.138 | I13: =SUM(I19:I25) -> 0.522 | J13: =SUM(J19:J25) -> 2.202 | K13: =SUM(K19:K25) -> 2.788 | ... AW13: =SUM(AW19:AW25) -> 0 | AY13: * | BA13: =IF($AZ13="","",$BA$45) | BB13: =IF($AZ13="","",25) | BD13: =IF(AZ13="","*","DMD") -> * | BE13: =AZ13 -> 0 | BG13: Bvkm | BH13: million Vehicles | BI13: yes
A14: Share of Veh | D14: =D13/SUM($D$13:$AJ$13) -> 0.016006933 | E14: =E13/SUM($D$13:$AJ$13) -> 0.014222721 | F14: =F13/SUM($D$13:$AJ$13) -> 0.01302475 | G14: =G13/SUM($D$13:$AJ$13) -> 0.0062957204 | H14: =H13/SUM($D$13:$AJ$13) -> 0.003517447 | I14: =I13/SUM($D$13:$AJ$13) -> 0.013305126 | J14: =J13/SUM($D$13:$AJ$13) -> 0.05612622 | K14: =K13/SUM($D$13:$AJ$13) -> 0.071062626 | ... AW14: =AW13/SUM($D$13:$AJ$13) -> 0 | AY14: * | BA14: =IF($AZ14="","",$BA$45) | BB14: =IF($AZ14="","",25) | BD14: =IF(AZ14="","*","DMD") -> * | BE14: =AZ14 -> 0 | BG14: Bvkm | BH14: million Vehicles | BI14: yes
D15: =D13/'non-road'!DB21 -> 0.0031655611 | E15: =E13/'non-road'!DC21 -> 0.00053697375 | F15: =F13/'non-road'!DD21 -> 0.020145314 | G15: =G13/'non-road'!DE21 -> 0.027815566 | H15: =H13/'non-road'!DF21 -> 0.022867142 | I15: =I13/'non-road'!DG21 -> 0.01772261 | J15: =J13/'non-road'!DH21 -> 0.010433547 | K15: =K13/'non-road'!DI21 -> 0.001994677 | ... AW15: =AW13/'non-road'!EU21 -> #VALUE! | AY15: * | BA15: =IF($AZ15="","",$BA$45) | BB15: =IF($AZ15="","",25) | BD15: =IF(AZ15="","*","DMD") -> * | BE15: =AZ15 -> 0 | BG15: Bvkm | BH15: million Vehicles | BI15: yes
AY16: * | BA16: =IF($AZ16="","",$BA$45) | BB16: =IF($AZ16="","",25) | BD16: =IF(AZ16="","*","DMD") -> * | BE16: =AZ16 -> 0 | BG16: Bvkm | BH16: million Vehicles | BI16: yes
A17: PJ share/Veh share | D17: =D11/D14 -> 1.0504847 | E17: =E11/E14 -> 1.0506531 | F17: =F11/F14 -> 1.0511803 | G17: =G11/G14 -> 1.0493502 | H17: =H11/H14 -> 1.0521002 | I17: =I11/I14 -> 1.050914 | J17: =J11/J14 -> 1.0508384 | K17: =K11/K14 -> 1.0508285 | ... AW17: =AW11/AW14 -> #DIV/0! | AY17: * | BA17: =IF($AZ17="","",$BA$45) | BB17: =IF($AZ17="","",25) | BD17: =IF(AZ17="","*","DMD") -> * | BE17: =AZ17 -> 0 | BG17: Bvkm | BH17: million Vehicles | BI17: yes
AY18: * | BA18: =IF($AZ18="","",$BA$45) | BB18: =IF($AZ18="","",25) | BD18: =IF(AZ18="","*","DMD") -> * | BE18: =AZ18 -> 0 | BG18: Bvkm | BH18: million Vehicles | BI18: yes
A19: mVeh | C19: =C4 -> TRABDS | D19: =ROUND(D4*D28/D36,3) -> 0 | E19: =ROUND(E4*E28/E36,3) -> 0 | F19: =ROUND(F4*F28/F36,3) -> 0 | G19: =ROUND(G4*G28/G36,3) -> 0.016 | H19: =ROUND(H4*H28/H36,3) -> 0.005 | I19: =ROUND(I4*I28/I36,3) -> 0.033 | J19: =ROUND(J4*J28/J36,3) -> 0.675 | K19: =ROUND(K4*K28/K36,3) -> 0.026 | ... AW19: =ROUND(AW4*AW28/AW36,3) -> 0 | AY19: PASTI | AZ19: =IF(AX4="zero","\I:",$BA$45&"_"&VLOOKUP(C19,'TRA balance'!$BB$5:$BC$15,2,FALSE)) -> Trd_hdt_bdl | BA19: =IF($AZ19="","",$BA$45) -> Trd_hdt | BB19: =IF($AZ19="","",25) -> 25 | BD19: =IF(AZ19="","*","DMD") -> DMD | BE19: =AZ19 -> Trd_hdt_bdl | BG19: Bvkm | BH19: million Vehicles | BI19: yes
C20: =C5 -> TRABGS | D20: =ROUND(D5*D29/D37,3) -> 0 | E20: =ROUND(E5*E29/E37,3) -> 0 | F20: =ROUND(F5*F29/F37,3) -> 0 | G20: =ROUND(G5*G29/G37,3) -> 0 | H20: =ROUND(H5*H29/H37,3) -> 0 | I20: =ROUND(I5*I29/I37,3) -> 0 | J20: =ROUND(J5*J29/J37,3) -> 0 | K20: =ROUND(K5*K29/K37,3) -> 0 | ... AW20: =ROUND(AW5*AW29/AW37,3) -> 0 | AY20: PASTI | AZ20: =IF(AX5="zero","\I:",$BA$45&"_"&VLOOKUP(C20,'TRA balance'!$BB$5:$BC$15,2,FALSE)) -> \I: | BA20: =IF($AZ20="","",$BA$45) -> Trd_hdt | BB20: =IF($AZ20="","",25) -> 25 | BD20: =IF(AZ20="","*","DMD") -> DMD | BE20: =AZ20 -> \I: | BG20: Bvkm | BH20: million Vehicles | BI20: yes
C21: =C6 -> TRADST | D21: =ROUND(D6*D30/D38,3) -> 0.628 | E21: =ROUND(E6*E30/E38,3) -> 0.558 | F21: =ROUND(F6*F30/F38,3) -> 0.511 | G21: =ROUND(G6*G30/G38,3) -> 0.231 | H21: =ROUND(H6*H30/H38,3) -> 0.128 | I21: =ROUND(I6*I30/I38,3) -> 0.489 | J21: =ROUND(J6*J30/J38,3) -> 1.489 | K21: =ROUND(K6*K30/K38,3) -> 2.678 | ... AW21: =ROUND(AW6*AW30/AW38,3) -> 0 | AY21: PASTI | AZ21: =IF(AX6="zero","\I:",$BA$45&"_"&VLOOKUP(C21,'TRA balance'!$BB$5:$BC$15,2,FALSE)) -> Trd_hdt_dsl | BA21: =IF($AZ21="","",$BA$45) -> Trd_hdt | BB21: =IF($AZ21="","",25) -> 25 | BD21: =IF(AZ21="","*","DMD") -> DMD | BE21: =AZ21 -> Trd_hdt_dsl | BG21: Bvkm | BH21: million Vehicles | BI21: yes
C22: =C7 -> TRAELC | D22: =ROUND(D7*D31/D39,3) -> 0 | E22: =ROUND(E7*E31/E39,3) -> 0 | F22: =ROUND(F7*F31/F39,3) -> 0 | G22: =ROUND(G7*G31/G39,3) -> 0 | H22: =ROUND(H7*H31/H39,3) -> 0 | I22: =ROUND(I7*I31/I39,3) -> 0 | J22: =ROUND(J7*J31/J39,3) -> 0 | K22: =ROUND(K7*K31/K39,3) -> 0 | ... AW22: =ROUND(AW7*AW31/AW39,3) -> 0 | AY22: PASTI | AZ22: =IF(AX7="zero","\I:",$BA$45&"_"&VLOOKUP(C22,'TRA balance'!$BB$5:$BC$15,2,FALSE)) -> \I: | BA22: =IF($AZ22="","",$BA$45) -> Trd_hdt | BB22: =IF($AZ22="","",25) -> 25 | BD22: =IF(AZ22="","*","DMD") -> DMD | BE22: =AZ22 -> \I: | BG22: Bvkm | BH22: million Vehicles | BI22: yes
C23: =C8 -> TRAGSL | D23: =ROUND(D8*D32/D40,3) -> 0 | E23: =ROUND(E8*E32/E40,3) -> 0 | F23: =ROUND(F8*F32/F40,3) -> 0 | G23: =ROUND(G8*G32/G40,3) -> 0 | H23: =ROUND(H8*H32/H40,3) -> 0.005 | I23: =ROUND(I8*I32/I40,3) -> 0 | J23: =ROUND(J8*J32/J40,3) -> 0.038 | K23: =ROUND(K8*K32/K40,3) -> 0.084 | ... AW23: =ROUND(AW8*AW32/AW40,3) -> 0 | AY23: PASTI | AZ23: =IF(AX8="zero","\I:",$BA$45&"_"&VLOOKUP(C23,'TRA balance'!$BB$5:$BC$15,2,FALSE)) -> Trd_hdt_gsl | BA23: =IF($AZ23="","",$BA$45) -> Trd_hdt | BB23: =IF($AZ23="","",25) -> 25 | BD23: =IF(AZ23="","*","DMD") -> DMD | BE23: =AZ23 -> Trd_hdt_gsl | BG23: Bvkm | BH23: million Vehicles | BI23: yes
C24: =C9 -> TRALPG | D24: =ROUND(D9*D33/D41,3) -> 0 | E24: =ROUND(E9*E33/E41,3) -> 0 | F24: =ROUND(F9*F33/F41,3) -> 0 | G24: =ROUND(G9*G33/G41,3) -> 0 | H24: =ROUND(H9*H33/H41,3) -> 0 | I24: =ROUND(I9*I33/I41,3) -> 0 | J24: =ROUND(J9*J33/J41,3) -> 0 | K24: =ROUND(K9*K33/K41,3) -> 0 | ... AW24: =ROUND(AW9*AW33/AW41,3) -> 0 | AY24: PASTI | AZ24: =IF(AX9="zero","\I:",$BA$45&"_"&VLOOKUP(C24,'TRA balance'!$BB$5:$BC$15,2,FALSE)) -> \I: | BA24: =IF($AZ24="","",$BA$45) -> Trd_hdt | BB24: =IF($AZ24="","",25) -> 25 | BD24: =IF(AZ24="","*","DMD") -> DMD | BE24: =AZ24 -> \I: | BG24: Bvkm | BH24: million Vehicles | BI24: yes
C25: =C10 -> TRANGA | D25: =ROUND(D10*D34/D42,3) -> 0 | E25: =ROUND(E10*E34/E42,3) -> 0 | F25: =ROUND(F10*F34/F42,3) -> 0 | G25: =ROUND(G10*G34/G42,3) -> 0 | H25: =ROUND(H10*H34/H42,3) -> 0 | I25: =ROUND(I10*I34/I42,3) -> 0 | J25: =ROUND(J10*J34/J42,3) -> 0 | K25: =ROUND(K10*K34/K42,3) -> 0 | ... AW25: =ROUND(AW10*AW34/AW42,3) -> 0 | AY25: PASTI | AZ25: =IF(AX10="zero","\I:",$BA$45&"_"&VLOOKUP(C25,'TRA balance'!$BB$5:$BC$15,2,FALSE)) -> \I: | BA25: =IF($AZ25="","",$BA$45) -> Trd_hdt | BB25: =IF($AZ25="","",25) -> 25 | BD25: =IF(AZ25="","*","DMD") -> DMD | BE25: =AZ25 -> \I: | BG25: Bvkm | BH25: million Vehicles | BI25: yes
AY26: * | BA26: =IF($AZ26="","",$BA$45) | BB26: =IF($AZ26="","",25) | BD26: =IF(AZ26="","*","DMD") -> * | BE26: =AZ26 -> 0 | BG26: Bvkm | BH26: million Vehicles | BI26: yes
D27: 1 | E27: 1 | F27: 1 | G27: 1 | H27: 1 | I27: 1 | J27: 1 | K27: 1 | L27: 1 | M27: 1 | N27: 1 | O27: 1 | P27: 1 | Q27: 1 | R27: 1 | S27: 1 | T27: 1 | U27: 1 | V27: 1 | W27: 1 | X27: 1 | Y27: 1 | Z27: 1 | AA27: 1 | AB27: 1 | AC27: 1 | AD27: 1 | AE27: 1 | AF27: 1 | AG27: 1 | AH27: 1 | AI27: 1 | AJ27: 1 | AK27: 1 | AL27: 1 | AM27: 1 | AN27: 1 | AO27: 1 | AP27: 1 | AQ27: 1 | AR27: 1 | AS27: 1 | AT27: 1 | AU27: 1 | AV27: 1 | AW27: 1 | AY27: * | BA27: =IF($AZ27="","",$BA$45) | BB27: =IF($AZ27="","",25) | BD27: =IF(AZ27="","*","DMD") -> * | BE27: =AZ27 -> 0 | BG27: Bvkm | BH27: million Vehicles | BI27: yes
A28: Efficiency | C28: =C19 -> TRABDS | D28: =$AX28*D$27 -> 0.1393659 | E28: =$AX28*E$27 -> 0.1393659 | F28: =$AX28*F$27 -> 0.1393659 | G28: =$AX28*G$27 -> 0.1393659 | H28: =$AX28*H$27 -> 0.1393659 | I28: =$AX28*I$27 -> 0.1393659 | J28: =$AX28*J$27 -> 0.1393659 | K28: =$AX28*K$27 -> 0.1393659 | ... AW28: =$AX28*AW$27 -> 0.1393659 | AX28: =AX30 -> 0.1393659 | AY28: EFF | AZ28: =AZ19 -> Trd_hdt_bdl | BA28: =IF($AZ28="","",$BA$45) -> Trd_hdt | BB28: =IF($AZ28="","",25) -> 25 | BD28: =IF(AZ28="","*","DMD") -> DMD | BE28: =AZ28 -> Trd_hdt_bdl | BG28: Bvkm | BH28: million Vehicles | BI28: yes
C29: =C20 -> TRABGS | D29: =$AX29*D$27 -> 0.1393659 | E29: =$AX29*E$27 -> 0.1393659 | F29: =$AX29*F$27 -> 0.1393659 | G29: =$AX29*G$27 -> 0.1393659 | H29: =$AX29*H$27 -> 0.1393659 | I29: =$AX29*I$27 -> 0.1393659 | J29: =$AX29*J$27 -> 0.1393659 | K29: =$AX29*K$27 -> 0.1393659 | ... AW29: =$AX29*AW$27 -> 0.1393659 | AX29: =AX32 -> 0.1393659 | AY29: EFF | AZ29: =AZ20 -> \I: | BA29: =IF($AZ29="","",$BA$45) -> Trd_hdt | BB29: =IF($AZ29="","",25) -> 25 | BD29: =IF(AZ29="","*","DMD") -> DMD | BE29: =AZ29 -> \I: | BG29: Bvkm | BH29: million Vehicles | BI29: yes
C30: =C21 -> TRADST | D30: =$AX30*D$27 -> 0.1393659 | E30: =$AX30*E$27 -> 0.1393659 | F30: =$AX30*F$27 -> 0.1393659 | G30: =$AX30*G$27 -> 0.1393659 | H30: =$AX30*H$27 -> 0.1393659 | I30: =$AX30*I$27 -> 0.1393659 | J30: =$AX30*J$27 -> 0.1393659 | K30: =$AX30*K$27 -> 0.1393659 | ... AW30: =$AX30*AW$27 -> 0.1393659 | AX30: 0.1393659 | AY30: EFF | AZ30: =AZ21 -> Trd_hdt_dsl | BA30: =IF($AZ30="","",$BA$45) -> Trd_hdt | BB30: =IF($AZ30="","",25) -> 25 | BD30: =IF(AZ30="","*","DMD") -> DMD | BE30: =AZ30 -> Trd_hdt_dsl | BG30: Bvkm | BH30: million Vehicles | BI30: yes
C31: =C22 -> TRAELC | D31: =$AX31*D$27 -> 0 | E31: =$AX31*E$27 -> 0 | F31: =$AX31*F$27 -> 0 | G31: =$AX31*G$27 -> 0 | H31: =$AX31*H$27 -> 0 | I31: =$AX31*I$27 -> 0 | J31: =$AX31*J$27 -> 0 | K31: =$AX31*K$27 -> 0 | ... AW31: =$AX31*AW$27 -> 0 | AY31: EFF | AZ31: =AZ22 -> \I: | BA31: =IF($AZ31="","",$BA$45) -> Trd_hdt | BB31: =IF($AZ31="","",25) -> 25 | BD31: =IF(AZ31="","*","DMD") -> DMD | BE31: =AZ31 -> \I: | BG31: Bvkm | BH31: million Vehicles | BI31: yes
C32: =C23 -> TRAGSL | D32: =$AX32*D$27 -> 0.1393659 | E32: =$AX32*E$27 -> 0.1393659 | F32: =$AX32*F$27 -> 0.1393659 | G32: =$AX32*G$27 -> 0.1393659 | H32: =$AX32*H$27 -> 0.1393659 | I32: =$AX32*I$27 -> 0.1393659 | J32: =$AX32*J$27 -> 0.1393659 | K32: =$AX32*K$27 -> 0.1393659 | ... AW32: =$AX32*AW$27 -> 0.1393659 | AX32: 0.1393659 | AY32: EFF | AZ32: =AZ23 -> Trd_hdt_gsl | BA32: =IF($AZ32="","",$BA$45) -> Trd_hdt | BB32: =IF($AZ32="","",25) -> 25 | BD32: =IF(AZ32="","*","DMD") -> DMD | BE32: =AZ32 -> Trd_hdt_gsl | BG32: Bvkm | BH32: million Vehicles | BI32: yes
C33: =C24 -> TRALPG | D33: =$AX33*D$27 -> 0 | E33: =$AX33*E$27 -> 0 | F33: =$AX33*F$27 -> 0 | G33: =$AX33*G$27 -> 0 | H33: =$AX33*H$27 -> 0 | I33: =$AX33*I$27 -> 0 | J33: =$AX33*J$27 -> 0 | K33: =$AX33*K$27 -> 0 | ... AW33: =$AX33*AW$27 -> 0 | AY33: EFF | AZ33: =AZ24 -> \I: | BA33: =IF($AZ33="","",$BA$45) -> Trd_hdt | BB33: =IF($AZ33="","",25) -> 25 | BD33: =IF(AZ33="","*","DMD") -> DMD | BE33: =AZ33 -> \I: | BG33: Bvkm | BH33: million Vehicles | BI33: yes
C34: =C25 -> TRANGA | D34: =$AX34*D$27 -> 0 | E34: =$AX34*E$27 -> 0 | F34: =$AX34*F$27 -> 0 | G34: =$AX34*G$27 -> 0 | H34: =$AX34*H$27 -> 0 | I34: =$AX34*I$27 -> 0 | J34: =$AX34*J$27 -> 0 | K34: =$AX34*K$27 -> 0 | ... AW34: =$AX34*AW$27 -> 0 | AY34: EFF | AZ34: =AZ25 -> \I: | BA34: =IF($AZ34="","",$BA$45) -> Trd_hdt | BB34: =IF($AZ34="","",25) -> 25 | BD34: =IF(AZ34="","*","DMD") -> DMD | BE34: =AZ34 -> \I: | BG34: Bvkm | BH34: million Vehicles | BI34: yes
AY35: * | BA35: =IF($AZ35="","",$BA$45) | BB35: =IF($AZ35="","",25) | BD35: =IF(AZ35="","*","DMD") -> * | BE35: =AZ35 -> 0 | BG35: Bvkm | BH35: million Vehicles | BI35: yes
A36: 000km/veh | C36: =C28 -> TRABDS | D36: =62.5*1.6 -> 100 | E36: =62.5*1.6 -> 100 | F36: =62.5*1.6 -> 100 | G36: =62.5*1.6 -> 100 | H36: =62.5*1.6 -> 100 | I36: =62.5*1.6 -> 100 | J36: =62.5*1.6 -> 100 | K36: =62.5*1.6 -> 100 | ... AE36: =62.5*1.6 -> 100 | AF36: 35 | AG36: =62.5*1.6 -> 100 | AH36: =62.5*1.6 -> 100 | AI36: =62.5*1.6 -> 100 | AJ36: =62.5*1.6 -> 100 | AK36: =62.5*1.6 -> 100 | AL36: 35 | AM36: =62.5*1.6 -> 100 | AN36: =62.5*1.6 -> 100 | AO36: =62.5*1.6 -> 100 | AP36: =62.5*1.6 -> 100 | AQ36: =62.5*1.6 -> 100 | AR36: =62.5*1.6 -> 100 | AS36: =62.5*1.6 -> 100 | AT36: =62.5*1.6 -> 100 | ... AW36: =62.5*1.6 -> 100 | AY36: AF | AZ36: =AZ28 -> Trd_hdt_bdl | BA36: =IF($AZ36="","",$BA$45) -> Trd_hdt | BB36: =IF($AZ36="","",25) -> 25 | BD36: =IF(AZ36="","*","DMD") -> DMD | BE36: =AZ36 -> Trd_hdt_bdl | BG36: Bvkm | BH36: million Vehicles | BI36: yes
C37: =C29 -> TRABGS | D37: =62.5*1.6 -> 100 | E37: =62.5*1.6 -> 100 | F37: =62.5*1.6 -> 100 | G37: =62.5*1.6 -> 100 | H37: =62.5*1.6 -> 100 | I37: =62.5*1.6 -> 100 | J37: =62.5*1.6 -> 100 | K37: =62.5*1.6 -> 100 | ... AE37: =62.5*1.6 -> 100 | AF37: 35 | AG37: =62.5*1.6 -> 100 | AH37: =62.5*1.6 -> 100 | AI37: =62.5*1.6 -> 100 | AJ37: =62.5*1.6 -> 100 | AK37: =62.5*1.6 -> 100 | AL37: 35 | AM37: =62.5*1.6 -> 100 | AN37: =62.5*1.6 -> 100 | AO37: =62.5*1.6 -> 100 | AP37: =62.5*1.6 -> 100 | AQ37: =62.5*1.6 -> 100 | AR37: =62.5*1.6 -> 100 | AS37: =62.5*1.6 -> 100 | AT37: =62.5*1.6 -> 100 | ... AW37: =62.5*1.6 -> 100 | AY37: AF | AZ37: =AZ29 -> \I: | BA37: =IF($AZ37="","",$BA$45) -> Trd_hdt | BB37: =IF($AZ37="","",25) -> 25 | BD37: =IF(AZ37="","*","DMD") -> DMD | BE37: =AZ37 -> \I: | BG37: Bvkm | BH37: million Vehicles | BI37: yes
C38: =C30 -> TRADST | D38: =62.5*1.6 -> 100 | E38: =62.5*1.6 -> 100 | F38: =62.5*1.6 -> 100 | G38: =62.5*1.6 -> 100 | H38: =62.5*1.6 -> 100 | I38: =62.5*1.6 -> 100 | J38: =62.5*1.6 -> 100 | K38: =62.5*1.6 -> 100 | ... AE38: =62.5*1.6 -> 100 | AF38: 35 | AG38: =62.5*1.6 -> 100 | AH38: =62.5*1.6 -> 100 | AI38: =62.5*1.6 -> 100 | AJ38: =62.5*1.6 -> 100 | AK38: =62.5*1.6 -> 100 | AL38: 35 | AM38: =62.5*1.6 -> 100 | AN38: =62.5*1.6 -> 100 | AO38: =62.5*1.6 -> 100 | AP38: =62.5*1.6 -> 100 | AQ38: =62.5*1.6 -> 100 | AR38: =62.5*1.6 -> 100 | AS38: =62.5*1.6 -> 100 | AT38: =62.5*1.6 -> 100 | ... AW38: =62.5*1.6 -> 100 | AY38: AF | AZ38: =AZ30 -> Trd_hdt_dsl | BA38: =IF($AZ38="","",$BA$45) -> Trd_hdt | BB38: =IF($AZ38="","",25) -> 25 | BD38: =IF(AZ38="","*","DMD") -> DMD | BE38: =AZ38 -> Trd_hdt_dsl | BG38: Bvkm | BH38: million Vehicles | BI38: yes
C39: =C31 -> TRAELC | D39: =62.5*1.6 -> 100 | E39: =62.5*1.6 -> 100 | F39: =62.5*1.6 -> 100 | G39: =62.5*1.6 -> 100 | H39: =62.5*1.6 -> 100 | I39: =62.5*1.6 -> 100 | J39: =62.5*1.6 -> 100 | K39: =62.5*1.6 -> 100 | ... AE39: =62.5*1.6 -> 100 | AF39: 35 | AG39: =62.5*1.6 -> 100 | AH39: =62.5*1.6 -> 100 | AI39: =62.5*1.6 -> 100 | AJ39: =62.5*1.6 -> 100 | AK39: =62.5*1.6 -> 100 | AL39: 35 | AM39: =62.5*1.6 -> 100 | AN39: =62.5*1.6 -> 100 | AO39: =62.5*1.6 -> 100 | AP39: =62.5*1.6 -> 100 | AQ39: =62.5*1.6 -> 100 | AR39: =62.5*1.6 -> 100 | AS39: =62.5*1.6 -> 100 | AT39: =62.5*1.6 -> 100 | ... AW39: =62.5*1.6 -> 100 | AY39: AF | AZ39: =AZ31 -> \I: | BA39: =IF($AZ39="","",$BA$45) -> Trd_hdt | BB39: =IF($AZ39="","",25) -> 25 | BD39: =IF(AZ39="","*","DMD") -> DMD | BE39: =AZ39 -> \I: | BG39: Bvkm | BH39: million Vehicles | BI39: yes
C40: =C32 -> TRAGSL | D40: =62.5*1.6 -> 100 | E40: =62.5*1.6 -> 100 | F40: =62.5*1.6 -> 100 | G40: =62.5*1.6 -> 100 | H40: =62.5*1.6 -> 100 | I40: =62.5*1.6 -> 100 | J40: =62.5*1.6 -> 100 | K40: =62.5*1.6 -> 100 | ... AE40: =62.5*1.6 -> 100 | AF40: 35 | AG40: =62.5*1.6 -> 100 | AH40: =62.5*1.6 -> 100 | AI40: =62.5*1.6 -> 100 | AJ40: =62.5*1.6 -> 100 | AK40: =62.5*1.6 -> 100 | AL40: 35 | AM40: =62.5*1.6 -> 100 | AN40: =62.5*1.6 -> 100 | AO40: =62.5*1.6 -> 100 | AP40: =62.5*1.6 -> 100 | AQ40: =62.5*1.6 -> 100 | AR40: =62.5*1.6 -> 100 | AS40: =62.5*1.6 -> 100 | AT40: =62.5*1.6 -> 100 | ... AW40: =62.5*1.6 -> 100 | AY40: AF | AZ40: =AZ32 -> Trd_hdt_gsl | BA40: =IF($AZ40="","",$BA$45) -> Trd_hdt | BB40: =IF($AZ40="","",25) -> 25 | BD40: =IF(AZ40="","*","DMD") -> DMD | BE40: =AZ40 -> Trd_hdt_gsl | BG40: Bvkm | BH40: million Vehicles | BI40: yes
C41: =C33 -> TRALPG | D41: =62.5*1.6 -> 100 | E41: =62.5*1.6 -> 100 | F41: =62.5*1.6 -> 100 | G41: =62.5*1.6 -> 100 | H41: =62.5*1.6 -> 100 | I41: =62.5*1.6 -> 100 | J41: =62.5*1.6 -> 100 | K41: =62.5*1.6 -> 100 | ... AE41: =62.5*1.6 -> 100 | AF41: 35 | AG41: =62.5*1.6 -> 100 | AH41: =62.5*1.6 -> 100 | AI41: =62.5*1.6 -> 100 | AJ41: =62.5*1.6 -> 100 | AK41: =62.5*1.6 -> 100 | AL41: 35 | AM41: =62.5*1.6 -> 100 | AN41: =62.5*1.6 -> 100 | AO41: =62.5*1.6 -> 100 | AP41: =62.5*1.6 -> 100 | AQ41: =62.5*1.6 -> 100 | AR41: =62.5*1.6 -> 100 | AS41: =62.5*1.6 -> 100 | AT41: =62.5*1.6 -> 100 | ... AW41: =62.5*1.6 -> 100 | AY41: AF | AZ41: =AZ33 -> \I: | BA41: =IF($AZ41="","",$BA$45) -> Trd_hdt | BB41: =IF($AZ41="","",25) -> 25 | BD41: =IF(AZ41="","*","DMD") -> DMD | BE41: =AZ41 -> \I: | BG41: Bvkm | BH41: million Vehicles | BI41: yes
C42: =C34 -> TRANGA | D42: =62.5*1.6 -> 100 | E42: =62.5*1.6 -> 100 | F42: =62.5*1.6 -> 100 | G42: =62.5*1.6 -> 100 | H42: =62.5*1.6 -> 100 | I42: =62.5*1.6 -> 100 | J42: =62.5*1.6 -> 100 | K42: =62.5*1.6 -> 100 | ... AE42: =62.5*1.6 -> 100 | AF42: 35 | AG42: =62.5*1.6 -> 100 | AH42: =62.5*1.6 -> 100 | AI42: =62.5*1.6 -> 100 | AJ42: =62.5*1.6 -> 100 | AK42: =62.5*1.6 -> 100 | AL42: 35 | AM42: =62.5*1.6 -> 100 | AN42: =62.5*1.6 -> 100 | AO42: =62.5*1.6 -> 100 | AP42: =62.5*1.6 -> 100 | AQ42: =62.5*1.6 -> 100 | AR42: =62.5*1.6 -> 100 | AS42: =62.5*1.6 -> 100 | AT42: =62.5*1.6 -> 100 | ... AW42: =62.5*1.6 -> 100 | AY42: AF | AZ42: =AZ34 -> \I: | BA42: =IF($AZ42="","",$BA$45) -> Trd_hdt | BB42: =IF($AZ42="","",25) -> 25 | BD42: =IF(AZ42="","*","DMD") -> DMD | BE42: =AZ42 -> \I: | BG42: Bvkm | BH42: million Vehicles | BI42: yes
AY43: * | BB43: =IF($AZ43="","",25)
D44: =D3 -> Africa_North | E44: =E3 -> Africa_Other | F44: =F3 -> Australia | G44: =G3 -> Austria | H44: =H3 -> Baltics | I44: =I3 -> BeNeLux | J44: =J3 -> Brazil | K44: =K3 -> China | ... AW44: =AW3 -> \I: | AY44: * | BB44: =IF($AZ44="","",25)
A45: Dem Bvkm | AY45: Demand | BA45: Trd_hdt | BB45: =IF($AZ45="","",25)
AY47: ~FI_Comm
AY48: CSet | AZ48: CommName | BA48: CommDesc | BB48: Unit
AY49: DEM | AZ49: =BA45 -> Trd_hdt | BB49: Bvkm

Sheet Trucks
D3: ='TRA balance'!E4 -> Africa_North | E3: ='TRA balance'!F4 -> Africa_Other | F3: ='TRA balance'!G4 -> Australia | G3: ='TRA balance'!H4 -> Austria | H3: ='TRA balance'!I4 -> Baltics | I3: ='TRA balance'!J4 -> BeNeLux | J3: ='TRA balance'!K4 -> Brazil | K3: ='TRA balance'!L4 -> China | ... AW3: ='TRA balance'!AX4 -> \I:
A4: TR | C4: TRABDS | D4: {=SUM(SUMIFS(Assumptions!BD$3:BD$102,Assumptions!$B$3:$B$102,Trucks!$C4,Assumptions!$G$3:$G$102,{"TRH","TRM","TRC"}))} -> 0 | E4: {=SUM(SUMIFS(Assumptions!BE$3:BE$102,Assumptions!$B$3:$B$102,Trucks!$C4,Assumptions!$G$3:$G$102,{"TRH","TRM","TRC"}))} -> 0 | F4: {=SUM(SUMIFS(Assumptions!BF$3:BF$102,Assumptions!$B$3:$B$102,Trucks!$C4,Assumptions!$G$3:$G$102,{"TRH","TRM","TRC"}))} -> 0.030656043 | G4: {=SUM(SUMIFS(Assumptions!BG$3:BG$102,Assumptions!$B$3:$B$102,Trucks!$C4,Assumptions!$G$3:$G$102,{"TRH","TRM","TRC"}))} -> 13.546605 | H4: {=SUM(SUMIFS(Assumptions!BH$3:BH$102,Assumptions!$B$3:$B$102,Trucks!$C4,Assumptions!$G$3:$G$102,{"TRH","TRM","TRC"}))} -> 3.9187559 | I4: {=SUM(SUMIFS(Assumptions!BI$3:BI$102,Assumptions!$B$3:$B$102,Trucks!$C4,Assumptions!$G$3:$G$102,{"TRH","TRM","TRC"}))} -> 28.06673 | J4: {=SUM(SUMIFS(Assumptions!BJ$3:BJ$102,Assumptions!$B$3:$B$102,Trucks!$C4,Assumptions!$G$3:$G$102,{"TRH","TRM","TRC"}))} -> 544.91205 | K4: {=SUM(SUMIFS(Assumptions!BK$3:BK$102,Assumptions!$B$3:$B$102,Trucks!$C4,Assumptions!$G$3:$G$102,{"TRH","TRM","TRC"}))} -> 22.17384 | ... AW4: {=SUM(SUMIFS(Assumptions!CW$3:CW$102,Assumptions!$B$3:$B$102,Trucks!$C4,Assumptions!$G$3:$G$102,{"TRH","TRM","TRC"}))} -> 0
A5: TR | C5: TRABGS | D5: {=SUM(SUMIFS(Assumptions!BD$3:BD$102,Assumptions!$B$3:$B$102,Trucks!$C5,Assumptions!$G$3:$G$102,{"TRH","TRM","TRC"}))} -> 0 | E5: {=SUM(SUMIFS(Assumptions!BE$3:BE$102,Assumptions!$B$3:$B$102,Trucks!$C5,Assumptions!$G$3:$G$102,{"TRH","TRM","TRC"}))} -> 0 | F5: {=SUM(SUMIFS(Assumptions!BF$3:BF$102,Assumptions!$B$3:$B$102,Trucks!$C5,Assumptions!$G$3:$G$102,{"TRH","TRM","TRC"}))} -> 0 | G5: {=SUM(SUMIFS(Assumptions!BG$3:BG$102,Assumptions!$B$3:$B$102,Trucks!$C5,Assumptions!$G$3:$G$102,{"TRH","TRM","TRC"}))} -> 0 | H5: {=SUM(SUMIFS(Assumptions!BH$3:BH$102,Assumptions!$B$3:$B$102,Trucks!$C5,Assumptions!$G$3:$G$102,{"TRH","TRM","TRC"}))} -> 0 | I5: {=SUM(SUMIFS(Assumptions!BI$3:BI$102,Assumptions!$B$3:$B$102,Trucks!$C5,Assumptions!$G$3:$G$102,{"TRH","TRM","TRC"}))} -> 0 | J5: {=SUM(SUMIFS(Assumptions!BJ$3:BJ$102,Assumptions!$B$3:$B$102,Trucks!$C5,Assumptions!$G$3:$G$102,{"TRH","TRM","TRC"}))} -> 0 | K5: {=SUM(SUMIFS(Assumptions!BK$3:BK$102,Assumptions!$B$3:$B$102,Trucks!$C5,Assumptions!$G$3:$G$102,{"TRH","TRM","TRC"}))} -> 0 | ... AW5: {=SUM(SUMIFS(Assumptions!CW$3:CW$102,Assumptions!$B$3:$B$102,Trucks!$C5,Assumptions!$G$3:$G$102,{"TRH","TRM","TRC"}))} -> 0
A6: TR | C6: TRADST | D6: {=SUM(SUMIFS(Assumptions!BD$3:BD$102,Assumptions!$B$3:$B$102,Trucks!$C6,Assumptions!$G$3:$G$102,{"TRH","TRM","TRC"}))} -> 650.53202 | E6: {=SUM(SUMIFS(Assumptions!BE$3:BE$102,Assumptions!$B$3:$B$102,Trucks!$C6,Assumptions!$G$3:$G$102,{"TRH","TRM","TRC"}))} -> 578.11316 | F6: {=SUM(SUMIFS(Assumptions!BF$3:BF$102,Assumptions!$B$3:$B$102,Trucks!$C6,Assumptions!$G$3:$G$102,{"TRH","TRM","TRC"}))} -> 479.50638 | G6: {=SUM(SUMIFS(Assumptions!BG$3:BG$102,Assumptions!$B$3:$B$102,Trucks!$C6,Assumptions!$G$3:$G$102,{"TRH","TRM","TRC"}))} -> 196.57441 | H6: {=SUM(SUMIFS(Assumptions!BH$3:BH$102,Assumptions!$B$3:$B$102,Trucks!$C6,Assumptions!$G$3:$G$102,{"TRH","TRM","TRC"}))} -> 103.6859 | I6: {=SUM(SUMIFS(Assumptions!BI$3:BI$102,Assumptions!$B$3:$B$102,Trucks!$C6,Assumptions!$G$3:$G$102,{"TRH","TRM","TRC"}))} -> 416.65646 | J6: {=SUM(SUMIFS(Assumptions!BJ$3:BJ$102,Assumptions!$B$3:$B$102,Trucks!$C6,Assumptions!$G$3:$G$102,{"TRH","TRM","TRC"}))} -> 1201.925 | K6: {=SUM(SUMIFS(Assumptions!BK$3:BK$102,Assumptions!$B$3:$B$102,Trucks!$C6,Assumptions!$G$3:$G$102,{"TRH","TRM","TRC"}))} -> 2270.6024 | ... AW6: {=SUM(SUMIFS(Assumptions!CW$3:CW$102,Assumptions!$B$3:$B$102,Trucks!$C6,Assumptions!$G$3:$G$102,{"TRH","TRM","TRC"}))} -> 0
A7: TR | C7: TRAELC | D7: {=SUM(SUMIFS(Assumptions!BD$3:BD$102,Assumptions!$B$3:$B$102,Trucks!$C7,Assumptions!$G$3:$G$102,{"TRH","TRM","TRC"}))} -> 0 | E7: {=SUM(SUMIFS(Assumptions!BE$3:BE$102,Assumptions!$B$3:$B$102,Trucks!$C7,Assumptions!$G$3:$G$102,{"TRH","TRM","TRC"}))} -> 0 | F7: {=SUM(SUMIFS(Assumptions!BF$3:BF$102,Assumptions!$B$3:$B$102,Trucks!$C7,Assumptions!$G$3:$G$102,{"TRH","TRM","TRC"}))} -> 0 | G7: {=SUM(SUMIFS(Assumptions!BG$3:BG$102,Assumptions!$B$3:$B$102,Trucks!$C7,Assumptions!$G$3:$G$102,{"TRH","TRM","TRC"}))} -> 0 | H7: {=SUM(SUMIFS(Assumptions!BH$3:BH$102,Assumptions!$B$3:$B$102,Trucks!$C7,Assumptions!$G$3:$G$102,{"TRH","TRM","TRC"}))} -> 0 | I7: {=SUM(SUMIFS(Assumptions!BI$3:BI$102,Assumptions!$B$3:$B$102,Trucks!$C7,Assumptions!$G$3:$G$102,{"TRH","TRM","TRC"}))} -> 0 | J7: {=SUM(SUMIFS(Assumptions!BJ$3:BJ$102,Assumptions!$B$3:$B$102,Trucks!$C7,Assumptions!$G$3:$G$102,{"TRH","TRM","TRC"}))} -> 0 | K7: {=SUM(SUMIFS(Assumptions!BK$3:BK$102,Assumptions!$B$3:$B$102,Trucks!$C7,Assumptions!$G$3:$G$102,{"TRH","TRM","TRC"}))} -> 24.536301 | ... AW7: {=SUM(SUMIFS(Assumptions!CW$3:CW$102,Assumptions!$B$3:$B$102,Trucks!$C7,Assumptions!$G$3:$G$102,{"TRH","TRM","TRC"}))} -> 0
A8: TR | C8: TRAGSL | D8: {=SUM(SUMIFS(Assumptions!BD$3:BD$102,Assumptions!$B$3:$B$102,Trucks!$C8,Assumptions!$G$3:$G$102,{"TRH","TRM","TRC"}))} -> 0 | E8: {=SUM(SUMIFS(Assumptions!BE$3:BE$102,Assumptions!$B$3:$B$102,Trucks!$C8,Assumptions!$G$3:$G$102,{"TRH","TRM","TRC"}))} -> 0 | F8: {=SUM(SUMIFS(Assumptions!BF$3:BF$102,Assumptions!$B$3:$B$102,Trucks!$C8,Assumptions!$G$3:$G$102,{"TRH","TRM","TRC"}))} -> 54.047574 | G8: {=SUM(SUMIFS(Assumptions!BG$3:BG$102,Assumptions!$B$3:$B$102,Trucks!$C8,Assumptions!$G$3:$G$102,{"TRH","TRM","TRC"}))} -> 1.9734589 | H8: {=SUM(SUMIFS(Assumptions!BH$3:BH$102,Assumptions!$B$3:$B$102,Trucks!$C8,Assumptions!$G$3:$G$102,{"TRH","TRM","TRC"}))} -> 8.2410374 | I8: {=SUM(SUMIFS(Assumptions!BI$3:BI$102,Assumptions!$B$3:$B$102,Trucks!$C8,Assumptions!$G$3:$G$102,{"TRH","TRM","TRC"}))} -> 7.6354931 | J8: {=SUM(SUMIFS(Assumptions!BJ$3:BJ$102,Assumptions!$B$3:$B$102,Trucks!$C8,Assumptions!$G$3:$G$102,{"TRH","TRM","TRC"}))} -> 79.040002 | K8: {=SUM(SUMIFS(Assumptions!BK$3:BK$102,Assumptions!$B$3:$B$102,Trucks!$C8,Assumptions!$G$3:$G$102,{"TRH","TRM","TRC"}))} -> 540.17053 | ... AW8: {=SUM(SUMIFS(Assumptions!CW$3:CW$102,Assumptions!$B$3:$B$102,Trucks!$C8,Assumptions!$G$3:$G$102,{"TRH","TRM","TRC"}))} -> 0
A9: TR | C9: TRALPG | D9: {=SUM(SUMIFS(Assumptions!BD$3:BD$102,Assumptions!$B$3:$B$102,Trucks!$C9,Assumptions!$G$3:$G$102,{"TRH","TRM","TRC"}))} -> 12.023198 | E9: {=SUM(SUMIFS(Assumptions!BE$3:BE$102,Assumptions!$B$3:$B$102,Trucks!$C9,Assumptions!$G$3:$G$102,{"TRH","TRM","TRC"}))} -> 0.0069001813 | F9: {=SUM(SUMIFS(Assumptions!BF$3:BF$102,Assumptions!$B$3:$B$102,Trucks!$C9,Assumptions!$G$3:$G$102,{"TRH","TRM","TRC"}))} -> 2.281164 | G9: {=SUM(SUMIFS(Assumptions!BG$3:BG$102,Assumptions!$B$3:$B$102,Trucks!$C9,Assumptions!$G$3:$G$102,{"TRH","TRM","TRC"}))} -> 0.05484394 | H9: {=SUM(SUMIFS(Assumptions!BH$3:BH$102,Assumptions!$B$3:$B$102,Trucks!$C9,Assumptions!$G$3:$G$102,{"TRH","TRM","TRC"}))} -> 2.9748518 | I9: {=SUM(SUMIFS(Assumptions!BI$3:BI$102,Assumptions!$B$3:$B$102,Trucks!$C9,Assumptions!$G$3:$G$102,{"TRH","TRM","TRC"}))} -> 2.0472416 | J9: {=SUM(SUMIFS(Assumptions!BJ$3:BJ$102,Assumptions!$B$3:$B$102,Trucks!$C9,Assumptions!$G$3:$G$102,{"TRH","TRM","TRC"}))} -> 0 | K9: {=SUM(SUMIFS(Assumptions!BK$3:BK$102,Assumptions!$B$3:$B$102,Trucks!$C9,Assumptions!$G$3:$G$102,{"TRH","TRM","TRC"}))} -> 9.3962589 | ... AW9: {=SUM(SUMIFS(Assumptions!CW$3:CW$102,Assumptions!$B$3:$B$102,Trucks!$C9,Assumptions!$G$3:$G$102,{"TRH","TRM","TRC"}))} -> 0
A10: TR | C10: TRANGA | D10: {=SUM(SUMIFS(Assumptions!BD$3:BD$102,Assumptions!$B$3:$B$102,Trucks!$C10,Assumptions!$G$3:$G$102,{"TRH","TRM","TRC"}))} -> 3.052208 | E10: {=SUM(SUMIFS(Assumptions!BE$3:BE$102,Assumptions!$B$3:$B$102,Trucks!$C10,Assumptions!$G$3:$G$102,{"TRH","TRM","TRC"}))} -> 0.011203249 | F10: {=SUM(SUMIFS(Assumptions!BF$3:BF$102,Assumptions!$B$3:$B$102,Trucks!$C10,Assumptions!$G$3:$G$102,{"TRH","TRM","TRC"}))} -> 0.46851799 | G10: {=SUM(SUMIFS(Assumptions!BG$3:BG$102,Assumptions!$B$3:$B$102,Trucks!$C10,Assumptions!$G$3:$G$102,{"TRH","TRM","TRC"}))} -> 0 | H10: {=SUM(SUMIFS(Assumptions!BH$3:BH$102,Assumptions!$B$3:$B$102,Trucks!$C10,Assumptions!$G$3:$G$102,{"TRH","TRM","TRC"}))} -> 0.24127524 | I10: {=SUM(SUMIFS(Assumptions!BI$3:BI$102,Assumptions!$B$3:$B$102,Trucks!$C10,Assumptions!$G$3:$G$102,{"TRH","TRM","TRC"}))} -> 0 | J10: {=SUM(SUMIFS(Assumptions!BJ$3:BJ$102,Assumptions!$B$3:$B$102,Trucks!$C10,Assumptions!$G$3:$G$102,{"TRH","TRM","TRC"}))} -> 16.834614 | K10: {=SUM(SUMIFS(Assumptions!BK$3:BK$102,Assumptions!$B$3:$B$102,Trucks!$C10,Assumptions!$G$3:$G$102,{"TRH","TRM","TRC"}))} -> 123.40084 | ... AW10: {=SUM(SUMIFS(Assumptions!CW$3:CW$102,Assumptions!$B$3:$B$102,Trucks!$C10,Assumptions!$G$3:$G$102,{"TRH","TRM","TRC"}))} -> 0
