Workbook
Name FID_1: [1]AGR_Fuels!$A$2
Name GROWTH: '[2]TechRep-Doc'!#REF!
Name DISCRATE: '[2]TechRep-Doc'!#REF!
Name FuelList: #REF!

Sheet TechSelection
A3: ~TFM_AVA
A4: Region | B4: Process
A5: Africa_North | B5: *
A6: Africa_Other | B6: *
A7: Australia | B7: *
A8: Austria | B8: *
A9: Baltics | B9: *
A10: BeNeLux | B10: *
A11: Brazil | B11: *
A12: China | B12: *
A13: CroSloven | B13: *
A14: CzechSlovak | B14: *
A15: France | B15: *
... A39: WestBalkans | B39: *

Sheet InvCost_for_packManufacturing
B1: *The original pack CAPEX price is 10million USD/GWh is too rough, and we also wanna project cost trends over time, so we sourced from NREL's ATB report | R1: *Downloaded from ATB 2024: output file, only representative vehicle battery type is presented below | S1: year | T1: scenario | U1: vehicle_weight_category | V1: vehicle_class | W1: vehicle_powertrain | X1: vehicle_detail | Y1: fuel_category | Z1: fuel2_category | AA1: metric | AB1: value | AC1: reference | AH1: 2023 | AI1: 2025 | AJ1: 2030 | AK1: 2035 | AL1: 2040 | AM1: 2045 | AN1: 2050 | AW1: ~TFM_INS: attribute=INVCOST | BD1: ~TFM_INS: attribute=ACT_COST | BO1: ~TFM_INS: attribute=INVCOST
B2: Battery Electric Vehicle Assumptions | Transportation | 2024 | ATB | NLR | S2: 2023 | T2: Mid | U2: Light Duty | V2: Compact | W2: Battery Electric | X2: Battery Electric Vehicle (300-mile range) | Y2: Electricity | AA2: Battery Cost (2022$/kWh) (pack-level, rated capacity) | AB2: 132.92732 | AC2: ANL, Autonomie (2023) | AG2: Whole pack CAPEX in NREL | AH2: 132.92732 | AI2: 120.58407 | AJ2: 104.4429 | AK2: 94.948087 | AL2: 92.108475 | AM2: 88.961165 | AN2: 85.453278
F3: Sourced from before calculations | S3: 2025 | T3: Mid | U3: Light Duty | V3: Compact | W3: Battery Electric | X3: Battery Electric Vehicle (300-mile range) | Y3: Electricity | AA3: Battery Cost (2022$/kWh) (pack-level, rated capacity) | AB3: 120.58407 | AC3: ANL, Autonomie (2023) | AH3: =AH2 -> 132.92732 | AI3: =AI2 -> 120.58407 | AJ3: =AJ2 -> 104.4429 | AK3: =AK2 -> 94.948087 | AL3: =AL2 -> 92.108475 | AM3: =AM2 -> 88.961165 | AN3: =AN2 -> 85.453278 | AS3: AllRegions | AT3: China | AU3: NorthAm | AW3: process | AX3: year | AY3: AllRegions | AZ3: China | BA3: NorthAm | BD3: process | BE3: year | BF3: AllRegions | BG3: China | BH3: NorthAm | BO3: process | BP3: year | BQ3: AllRegions | BR3: China | BS3: NorthAm
F4: process | G4: AllRegions | H4: China | I4: NorthAm | S4: 2030 | T4: Mid | U4: Light Duty | V4: Compact | W4: Battery Electric | X4: Battery Electric Vehicle (300-mile range) | Y4: Electricity | AA4: Battery Cost (2022$/kWh) (pack-level, rated capacity) | AB4: 104.4429 | AC4: ANL, Autonomie (2023) | AH4: =AH3 -> 132.92732 | AI4: =AI3 -> 120.58407 | AJ4: =AJ3 -> 104.4429 | AK4: =AK3 -> 94.948087 | AL4: =AL3 -> 92.108475 | AM4: =AM3 -> 88.961165 | AN4: =AN3 -> 85.453278 | AS4: 80.383177 | AT4: 55.48673 | AU4: 106.82505 | AW4: Tra_EV_Batt-LFP_fromrecy | AX4: 2023 | AY4: =G5 -> 80.383177 | AZ4: =H5 -> 55.48673 | BA4: =I5 -> 106.82505 | BD4: Tra_EV_Batt-LFP_virgin | BE4: 2023 | BF4: =AS4*70% -> 56.268224 | BG4: =AT4*70% -> 38.840711 | BH4: =AU4*70% -> 74.777535 | BO4: Tra_EV_Batt-LFP_virgin_pack | BP4: 2023 | BQ4: =AS4*30% -> 24.114953 | BR4: =AT4*30% -> 16.646019 | BS4: =AU4*30% -> 32.047515
B5: *However, (1) as suggested by Sally Benson's Nature energy in 2025, the learning-by-doing reduction only applied to other cost components (conversion cost) = whole pack CAPEX-material costs (2) Argonne lab / EverBatt model/ Anna's provided data has its own CAPEX , we have already made the deduction in the SubRES_Transport table (avoiding Double-counting learning) (3) energy economic cost only accounts for negligible proportion of CAPEX, so to make the paper cleaner we do not need to deduct this part (4) but Argonne database do not have future cost projections | F5: Tra_EV_Batt-LFP | G5: =[3]R_strategies_n_GridBattery!$D$131 -> 80.383177 | H5: =[3]R_strategies_n_GridBattery!$E$131 -> 55.48673 | I5: =[3]R_strategies_n_GridBattery!$F$131 -> 106.82505 | S5: 2035 | T5: Mid | U5: Light Duty | V5: Compact | W5: Battery Electric | X5: Battery Electric Vehicle (300-mile range) | Y5: Electricity | AA5: Battery Cost (2022$/kWh) (pack-level, rated capacity) | AB5: 94.948087 | AC5: ANL, Autonomie (2023) | AH5: =AH4 -> 132.92732 | AI5: =AI4 -> 120.58407 | AJ5: =AJ4 -> 104.4429 | AK5: =AK4 -> 94.948087 | AL5: =AL4 -> 92.108475 | AM5: =AM4 -> 88.961165 | AN5: =AN4 -> 85.453278 | AS5: 95.4086 | AT5: 66.32565 | AU5: 126.26355 | AW5: Tra_EV_Batt-LMO_fromrecy | AX5: =AX4 -> 2023 | AY5: =G6 -> 95.4086 | AZ5: =H6 -> 66.32565 | BA5: =I6 -> 126.26355 | BD5: Tra_EV_Batt-LMO_virgin | BE5: 2023 | BF5: =AS5*70% -> 66.78602 | BG5: =AT5*70% -> 46.427955 | BH5: =AU5*70% -> 88.384485 | BO5: Tra_EV_Batt-LMO_virgin_pack | BP5: 2023 | BQ5: =AS5*30% -> 28.62258 | BR5: =AT5*30% -> 19.897695 | BS5: =AU5*30% -> 37.879065
F6: Tra_EV_Batt-LMO | G6: =[3]R_strategies_n_GridBattery!$D$132 -> 95.4086 | H6: =[3]R_strategies_n_GridBattery!$E$132 -> 66.32565 | I6: =[3]R_strategies_n_GridBattery!$F$132 -> 126.26355 | S6: 2040 | T6: Mid | U6: Light Duty | V6: Compact | W6: Battery Electric | X6: Battery Electric Vehicle (300-mile range) | Y6: Electricity | AA6: Battery Cost (2022$/kWh) (pack-level, rated capacity) | AB6: 92.108475 | AC6: ANL, Autonomie (2023) | AH6: =AH5 -> 132.92732 | AI6: =AI5 -> 120.58407 | AJ6: =AJ5 -> 104.4429 | AK6: =AK5 -> 94.948087 | AL6: =AL5 -> 92.108475 | AM6: =AM5 -> 88.961165 | AN6: =AN5 -> 85.453278 | AS6: 85.347697 | AT6: 56.10147 | AU6: 116.32796 | AW6: Tra_EV_Batt-NCA_fromrecy | AX6: =AX5 -> 2023 | AY6: =G7 -> 85.347697 | AZ6: =H7 -> 56.10147 | BA6: =I7 -> 116.32796 | BD6: Tra_EV_Batt-NCA_virgin | BE6: 2023 | BF6: =AS6*70% -> 59.743388 | BG6: =AT6*70% -> 39.271029 | BH6: =AU6*70% -> 81.429572 | BO6: Tra_EV_Batt-NCA_virgin_pack | BP6: 2023 | BQ6: =AS6*30% -> 25.604309 | BR6: =AT6*30% -> 16.830441 | BS6: =AU6*30% -> 34.898388
F7: Tra_EV_Batt-NCA | G7: =[3]R_strategies_n_GridBattery!$D$133 -> 85.347697 | H7: =[3]R_strategies_n_GridBattery!$E$133 -> 56.10147 | I7: =[3]R_strategies_n_GridBattery!$F$133 -> 116.32796 | S7: 2045 | T7: Mid | U7: Light Duty | V7: Compact | W7: Battery Electric | X7: Battery Electric Vehicle (300-mile range) | Y7: Electricity | AA7: Battery Cost (2022$/kWh) (pack-level, rated capacity) | AB7: 88.961165 | AC7: ANL, Autonomie (2023) | AH7: =AH6 -> 132.92732 | AI7: =AI6 -> 120.58407 | AJ7: =AJ6 -> 104.4429 | AK7: =AK6 -> 94.948087 | AL7: =AL6 -> 92.108475 | AM7: =AM6 -> 88.961165 | AN7: =AN6 -> 85.453278 | AS7: 85.52157 | AT7: 55.55951 | AU7: 117.30431 | AW7: Tra_EV_Batt-NMC111_fromrecy | AX7: =AX6 -> 2023 | AY7: =G8 -> 85.52157 | AZ7: =H8 -> 55.55951 | BA7: =I8 -> 117.30431 | BD7: Tra_EV_Batt-NMC111_virgin | BE7: 2023 | BF7: =AS7*70% -> 59.865099 | BG7: =AT7*70% -> 38.891657 | BH7: =AU7*70% -> 82.113017 | BO7: Tra_EV_Batt-NMC111_virgin_pack | BP7: 2023 | BQ7: =AS7*30% -> 25.656471 | BR7: =AT7*30% -> 16.667853 | BS7: =AU7*30% -> 35.191293
B8: So we use Argonne baseline cost → deduct material cost → get conversion CAPEX → apply NREL learning rate to conversion component.----no it seems that NorthAmerica too high so we included the regional learning rate differences in | F8: Tra_EV_Batt-NMC111 | G8: =[3]R_strategies_n_GridBattery!$D$134 -> 85.52157 | H8: =[3]R_strategies_n_GridBattery!$E$134 -> 55.55951 | I8: =[3]R_strategies_n_GridBattery!$F$134 -> 117.30431 | S8: 2050 | T8: Mid | U8: Light Duty | V8: Compact | W8: Battery Electric | X8: Battery Electric Vehicle (300-mile range) | Y8: Electricity | AA8: Battery Cost (2022$/kWh) (pack-level, rated capacity) | AB8: 85.453278 | AC8: ANL, Autonomie (2023) | AH8: =AH7 -> 132.92732 | AI8: =AI7 -> 120.58407 | AJ8: =AJ7 -> 104.4429 | AK8: =AK7 -> 94.948087 | AL8: =AL7 -> 92.108475 | AM8: =AM7 -> 88.961165 | AN8: =AN7 -> 85.453278 | AS8: 90.092917 | AT8: 59.3677 | AU8: 122.66905 | AW8: Tra_EV_Batt-NMC532_fromrecy | AX8: =AX7 -> 2023 | AY8: =G9 -> 90.092917 | AZ8: =H9 -> 59.3677 | BA8: =I9 -> 122.66905 | BD8: Tra_EV_Batt-NMC532_virgin | BE8: 2023 | BF8: =AS8*70% -> 63.065042 | BG8: =AT8*70% -> 41.55739 | BH8: =AU8*70% -> 85.868335 | BO8: Tra_EV_Batt-NMC532_virgin_pack | BP8: 2023 | BQ8: =AS8*30% -> 27.027875 | BR8: =AT8*30% -> 17.81031 | BS8: =AU8*30% -> 36.800715
F9: Tra_EV_Batt-NMC532 | G9: =[3]R_strategies_n_GridBattery!$D$135 -> 90.092917 | H9: =[3]R_strategies_n_GridBattery!$E$135 -> 59.3677 | I9: =[3]R_strategies_n_GridBattery!$F$135 -> 122.66905 | AH9: =AH8 -> 132.92732 | AI9: =AI8 -> 120.58407 | AJ9: =AJ8 -> 104.4429 | AK9: =AK8 -> 94.948087 | AL9: =AL8 -> 92.108475 | AM9: =AM8 -> 88.961165 | AN9: =AN8 -> 85.453278 | AS9: 86.922217 | AT9: 57.33755 | AU9: 118.2723 | AW9: Tra_EV_Batt-NMC622_fromrecy | AX9: =AX8 -> 2023 | AY9: =G10 -> 86.922217 | AZ9: =H10 -> 57.33755 | BA9: =I10 -> 118.2723 | BD9: Tra_EV_Batt-NMC622_virgin | BE9: 2023 | BF9: =AS9*70% -> 60.845552 | BG9: =AT9*70% -> 40.136285 | BH9: =AU9*70% -> 82.79061 | BO9: Tra_EV_Batt-NMC622_virgin_pack | BP9: 2023 | BQ9: =AS9*30% -> 26.076665 | BR9: =AT9*30% -> 17.201265 | BS9: =AU9*30% -> 35.48169
F10: Tra_EV_Batt-NMC622 | G10: =[3]R_strategies_n_GridBattery!$D$136 -> 86.922217 | H10: =[3]R_strategies_n_GridBattery!$E$136 -> 57.33755 | I10: =[3]R_strategies_n_GridBattery!$F$136 -> 118.2723 | AH10: =AH9 -> 132.92732 | AI10: =AI9 -> 120.58407 | AJ10: =AJ9 -> 104.4429 | AK10: =AK9 -> 94.948087 | AL10: =AL9 -> 92.108475 | AM10: =AM9 -> 88.961165 | AN10: =AN9 -> 85.453278 | AS10: 89.552667 | AT10: 59.98948 | AU10: 120.87452 | AW10: Tra_EV_Batt-NMC811_fromrecy | AX10: =AX9 -> 2023 | AY10: =G11 -> 89.552667 | AZ10: =H11 -> 59.98948 | BA10: =I11 -> 120.87452 | BD10: Tra_EV_Batt-NMC811_virgin | BE10: 2023 | BF10: =AS10*70% -> 62.686867 | BG10: =AT10*70% -> 41.992636 | BH10: =AU10*70% -> 84.612164 | BO10: Tra_EV_Batt-NMC811_virgin_pack | BP10: 2023 | BQ10: =AS10*30% -> 26.8658 | BR10: =AT10*30% -> 17.996844 | BS10: =AU10*30% -> 36.262356
F11: Tra_EV_Batt-NMC811 | G11: =[3]R_strategies_n_GridBattery!$D$137 -> 89.552667 | H11: =[3]R_strategies_n_GridBattery!$E$137 -> 59.98948 | I11: =[3]R_strategies_n_GridBattery!$F$137 -> 120.87452 | AH11: =AH10 -> 132.92732 | AI11: =AI10 -> 120.58407 | AJ11: =AJ10 -> 104.4429 | AK11: =AK10 -> 94.948087 | AL11: =AL10 -> 92.108475 | AM11: =AM10 -> 88.961165 | AN11: =AN10 -> 85.453278 | AS11: 162.09333 | AT11: 162.09333 | AU11: 162.09333 | BD11: Tra_EV_Batt-Sodium_virgin | BE11: 2023 | BF11: =AS11*70% -> 113.46533 | BG11: =AT11*70% -> 113.46533 | BH11: =AU11*70% -> 113.46533 | BO11: Tra_EV_Batt-Sodium_virgin_pack | BP11: 2023 | BQ11: =AS11*30% -> 48.628 | BR11: =AT11*30% -> 48.628 | BS11: =AU11*30% -> 48.628
AH12: =AH11 -> 132.92732 | AI12: =AI11 -> 120.58407 | AJ12: =AJ11 -> 104.4429 | AK12: =AK11 -> 94.948087 | AL12: =AL11 -> 92.108475 | AM12: =AM11 -> 88.961165 | AN12: =AN11 -> 85.453278
AL14: =AL2/AK2 -> 0.970093 | AM14: =AM2/AL2 -> 0.96583039 | AN14: =AN2/AM2 -> 0.96056834
AS16: AllRegions | AT16: China | AU16: NorthAm | AW16: process | AX16: year | AY16: AllRegions | AZ16: China | BA16: NorthAm | BD16: process | BE16: year | BF16: AllRegions | BG16: China | BH16: NorthAm | BO16: process | BP16: year | BQ16: AllRegions | BR16: China | BS16: NorthAm
AS17: 72.919025 | AT17: 50.334391 | AU17: 96.905581 | AW17: Tra_EV_Batt-LFP_fromrecy | AX17: 2025 | AY17: =AY4*AI2/AH2 -> 72.919025 | AZ17: =AZ4*AI2/AH2 -> 50.334391 | BA17: =BA4*AI2/AH2 -> 96.905581 | BD17: Tra_EV_Batt-LFP_virgin | BE17: 2025 | BF17: =AS17*70% -> 51.043317 | BG17: =AT17*70% -> 35.234074 | BH17: =AU17*70% -> 67.833907 | BO17: Tra_EV_Batt-LFP_virgin_pack | BP17: 2025 | BQ17: =AS17*30% -> 21.875707 | BR17: =AT17*30% -> 15.100317 | BS17: =AU17*30% -> 29.071674
AS18: 86.54923 | AT18: 60.16684 | AU18: 114.53908 | AW18: Tra_EV_Batt-LMO_fromrecy | AX18: =AX17 -> 2025 | AY18: =AY5*AI3/AH3 -> 86.54923 | AZ18: =AZ5*AI3/AH3 -> 60.16684 | BA18: =BA5*AI3/AH3 -> 114.53908 | BD18: Tra_EV_Batt-LMO_virgin | BE18: 2025 | BF18: =AS18*70% -> 60.584461 | BG18: =AT18*70% -> 42.116788 | BH18: =AU18*70% -> 80.177354 | BO18: Tra_EV_Batt-LMO_virgin_pack | BP18: 2025 | BQ18: =AS18*30% -> 25.964769 | BR18: =AT18*30% -> 18.050052 | BS18: =AU18*30% -> 34.361723
AS19: 77.422553 | AT19: 50.892048 | AU19: 105.52608 | AW19: Tra_EV_Batt-NCA_fromrecy | AX19: =AX18 -> 2025 | AY19: =AY6*AI4/AH4 -> 77.422553 | AZ19: =AZ6*AI4/AH4 -> 50.892048 | BA19: =BA6*AI4/AH4 -> 105.52608 | BD19: Tra_EV_Batt-NCA_virgin | BE19: 2025 | BF19: =AS19*70% -> 54.195787 | BG19: =AT19*70% -> 35.624433 | BH19: =AU19*70% -> 73.868255 | BO19: Tra_EV_Batt-NCA_virgin_pack | BP19: 2025 | BQ19: =AS19*30% -> 23.226766 | BR19: =AT19*30% -> 15.267614 | BS19: =AU19*30% -> 31.657823
AS20: 77.580281 | AT20: 50.400413 | AU20: 106.41177 | AW20: Tra_EV_Batt-NMC111_fromrecy | AX20: =AX19 -> 2025 | AY20: =AY7*AI5/AH5 -> 77.580281 | AZ20: =AZ7*AI5/AH5 -> 50.400413 | BA20: =BA7*AI5/AH5 -> 106.41177 | BD20: Tra_EV_Batt-NMC111_virgin | BE20: 2025 | BF20: =AS20*70% -> 54.306197 | BG20: =AT20*70% -> 35.280289 | BH20: =AU20*70% -> 74.488237 | BO20: Tra_EV_Batt-NMC111_virgin_pack | BP20: 2025 | BQ20: =AS20*30% -> 23.274084 | BR20: =AT20*30% -> 15.120124 | BS20: =AU20*30% -> 31.92353
AS21: 81.727146 | AT21: 53.854985 | AU21: 111.27835 | AW21: Tra_EV_Batt-NMC532_fromrecy | AX21: =AX20 -> 2025 | AY21: =AY8*AI6/AH6 -> 81.727146 | AZ21: =AZ8*AI6/AH6 -> 53.854985 | BA21: =BA8*AI6/AH6 -> 111.27835 | BD21: Tra_EV_Batt-NMC532_virgin | BE21: 2025 | BF21: =AS21*70% -> 57.209002 | BG21: =AT21*70% -> 37.698489 | BH21: =AU21*70% -> 77.894847 | BO21: Tra_EV_Batt-NMC532_virgin_pack | BP21: 2025 | BQ21: =AS21*30% -> 24.518144 | BR21: =AT21*30% -> 16.156495 | BS21: =AU21*30% -> 33.383506
AS22: 78.850868 | AT22: 52.013349 | AU22: 107.28987 | AW22: Tra_EV_Batt-NMC622_fromrecy | AX22: =AX21 -> 2025 | AY22: =AY9*AI7/AH7 -> 78.850868 | AZ22: =AZ9*AI7/AH7 -> 52.013349 | BA22: =BA9*AI7/AH7 -> 107.28987 | BD22: Tra_EV_Batt-NMC622_virgin | BE22: 2025 | BF22: =AS22*70% -> 55.195608 | BG22: =AT22*70% -> 36.409344 | BH22: =AU22*70% -> 75.10291 | BO22: Tra_EV_Batt-NMC622_virgin_pack | BP22: 2025 | BQ22: =AS22*30% -> 23.65526 | BR22: =AT22*30% -> 15.604005 | BS22: =AU22*30% -> 32.186962
AS23: 81.237062 | AT23: 54.419028 | AU23: 109.65046 | AW23: Tra_EV_Batt-NMC811_fromrecy | AX23: =AX22 -> 2025 | AY23: =AY10*AI8/AH8 -> 81.237062 | AZ23: =AZ10*AI8/AH8 -> 54.419028 | BA23: =BA10*AI8/AH8 -> 109.65046 | BD23: Tra_EV_Batt-NMC811_virgin | BE23: 2025 | BF23: =AS23*70% -> 56.865943 | BG23: =AT23*70% -> 38.09332 | BH23: =AU23*70% -> 76.75532 | BO23: Tra_EV_Batt-NMC811_virgin_pack | BP23: 2025 | BQ23: =AS23*30% -> 24.371119 | BR23: =AT23*30% -> 16.325708 | BS23: =AU23*30% -> 32.895137
AS24: 147.04181 | AT24: 147.04181 | AU24: 147.04181 | BD24: Tra_EV_Batt-Sodium_virgin | BE24: 2025 | BF24: =AS24*70% -> 102.92927 | BG24: =AT24*70% -> 102.92927 | BH24: =AU24*70% -> 102.92927 | BO24: Tra_EV_Batt-Sodium_virgin_pack | BP24: 2025 | BQ24: =AS24*30% -> 44.112543 | BR24: =AT24*30% -> 44.112543 | BS24: =AU24*30% -> 44.112543
F27: Total CAPEX for batteries before deducting material flow costs (USD/kWh)
G28: AllRegions | H28: China | I28: NorthAm
F29: Tra_EV_Batt-LFP | G29: 99.076927 | H29: 74.18048 | I29: 125.5188
F30: Tra_EV_Batt-LMO | G30: 115.8002 | H30: 86.71725 | I30: 146.65515
F31: Tra_EV_Batt-NCA | G31: 116.6095 | H31: 87.36327 | I31: 147.58976 | AS31: AllRegions | AT31: China | AU31: NorthAm | AW31: process | AX31: year | AY31: AllRegions | AZ31: China | BA31: NorthAm | BD31: process | BE31: year | BF31: AllRegions | BG31: China | BH31: NorthAm | BO31: process | BP31: year | BQ31: AllRegions | BR31: China | BS31: NorthAm
B32: Cell cost for Na-ion (USD24/kWh) | C32: Pack cost for Na-ion | F32: Tra_EV_Batt-NMC111 | G32: 119.49202 | H32: 89.52996 | I32: 151.27476 | AS32: 63.15821 | AT32: 43.596716 | AU32: 83.933968 | AW32: Tra_EV_Batt-LFP_fromrecy | AX32: 2030 | AY32: =AY17*AJ2/AI2 -> 63.15821 | AZ32: =AZ17*AJ2/AI2 -> 43.596716 | BA32: =BA17*AJ2/AI2 -> 83.933968 | BD32: Tra_EV_Batt-LFP_virgin | BE32: 2030 | BF32: =AS32*70% -> 44.210747 | BG32: =AT32*70% -> 30.517702 | BH32: =AU32*70% -> 58.753777 | BO32: Tra_EV_Batt-LFP_virgin_pack | BP32: 2030 | BQ32: =AS32*30% -> 18.947463 | BR32: =AT32*30% -> 13.079015 | BS32: =AU32*30% -> 25.18019
B33: 121.57 | C33: =B33/0.75 -> 162.09333 | F33: Tra_EV_Batt-NMC532 | G33: 122.49172 | H33: 91.7665 | I33: 155.06785 | AS33: 74.9639 | AT33: 52.113011 | AU33: 99.207075 | AW33: Tra_EV_Batt-LMO_fromrecy | AX33: =AX32 -> 2030 | AY33: =AY18*AJ3/AI3 -> 74.9639 | AZ33: =AZ18*AJ3/AI3 -> 52.113011 | BA33: =BA18*AJ3/AI3 -> 99.207075 | BD33: Tra_EV_Batt-LMO_virgin | BE33: 2030 | BF33: =AS33*70% -> 52.47473 | BG33: =AT33*70% -> 36.479107 | BH33: =AU33*70% -> 69.444952 | BO33: Tra_EV_Batt-LMO_virgin_pack | BP33: 2030 | BQ33: =AS33*30% -> 22.48917 | BR33: =AT33*30% -> 15.633903 | BS33: =AU33*30% -> 29.762123
F34: Tra_EV_Batt-NMC622 | G34: 117.94842 | H34: 88.36375 | I34: 149.2985 | AS34: 67.058905 | AT34: 44.079726 | AU34: 91.40054 | AW34: Tra_EV_Batt-NCA_fromrecy | AX34: =AX33 -> 2030 | AY34: =AY19*AJ4/AI4 -> 67.058905 | AZ34: =AZ19*AJ4/AI4 -> 44.079726 | BA34: =BA19*AJ4/AI4 -> 91.40054 | BD34: Tra_EV_Batt-NCA_virgin | BE34: 2030 | BF34: =AS34*70% -> 46.941233 | BG34: =AT34*70% -> 30.855808 | BH34: =AU34*70% -> 63.980378 | BO34: Tra_EV_Batt-NCA_virgin_pack | BP34: 2030 | BQ34: =AS34*30% -> 20.117671 | BR34: =AT34*30% -> 13.223918 | BS34: =AU34*30% -> 27.420162
F35: Tra_EV_Batt-NMC811 | G35: 117.83067 | H35: 88.26748 | I35: 149.15252 | AS35: 67.195519 | AT35: 43.653901 | AU35: 92.167672 | AW35: Tra_EV_Batt-NMC111_fromrecy | AX35: =AX34 -> 2030 | AY35: =AY20*AJ5/AI5 -> 67.195519 | AZ35: =AZ20*AJ5/AI5 -> 43.653901 | BA35: =BA20*AJ5/AI5 -> 92.167672 | BD35: Tra_EV_Batt-NMC111_virgin | BE35: 2030 | BF35: =AS35*70% -> 47.036863 | BG35: =AT35*70% -> 30.557731 | BH35: =AU35*70% -> 64.51737 | BO35: Tra_EV_Batt-NMC111_virgin_pack | BP35: 2030 | BQ35: =AS35*30% -> 20.158656 | BR35: =AT35*30% -> 13.09617 | BS35: =AU35*30% -> 27.650302
AS36: 70.787292 | AT36: 46.64605 | AU36: 96.382825 | AW36: Tra_EV_Batt-NMC532_fromrecy | AX36: =AX35 -> 2030 | AY36: =AY21*AJ6/AI6 -> 70.787292 | AZ36: =AZ21*AJ6/AI6 -> 46.64605 | BA36: =BA21*AJ6/AI6 -> 96.382825 | BD36: Tra_EV_Batt-NMC532_virgin | BE36: 2030 | BF36: =AS36*70% -> 49.551104 | BG36: =AT36*70% -> 32.652235 | BH36: =AU36*70% -> 67.467977 | BO36: Tra_EV_Batt-NMC532_virgin_pack | BP36: 2030 | BQ36: =AS36*30% -> 21.236187 | BR36: =AT36*30% -> 13.993815 | BS36: =AU36*30% -> 28.914848
AS37: 68.296027 | AT37: 45.050932 | AU37: 92.928236 | AW37: Tra_EV_Batt-NMC622_fromrecy | AX37: =AX36 -> 2030 | AY37: =AY22*AJ7/AI7 -> 68.296027 | AZ37: =AZ22*AJ7/AI7 -> 45.050932 | BA37: =BA22*AJ7/AI7 -> 92.928236 | BD37: Tra_EV_Batt-NMC622_virgin | BE37: 2030 | BF37: =AS37*70% -> 47.807219 | BG37: =AT37*70% -> 31.535653 | BH37: =AU37*70% -> 65.049765 | BO37: Tra_EV_Batt-NMC622_virgin_pack | BP37: 2030 | BQ37: =AS37*30% -> 20.488808 | BR37: =AT37*30% -> 13.51528 | BS37: =AU37*30% -> 27.878471
AS38: 70.36281 | AT38: 47.134591 | AU38: 94.972837 | AW38: Tra_EV_Batt-NMC811_fromrecy | AX38: =AX37 -> 2030 | AY38: =AY23*AJ8/AI8 -> 70.36281 | AZ38: =AZ23*AJ8/AI8 -> 47.134591 | BA38: =BA23*AJ8/AI8 -> 94.972837 | BD38: Tra_EV_Batt-NMC811_virgin | BE38: 2030 | BF38: =AS38*70% -> 49.253967 | BG38: =AT38*70% -> 32.994214 | BH38: =AU38*70% -> 66.480986 | BO38: Tra_EV_Batt-NMC811_virgin_pack | BP38: 2030 | BQ38: =AS38*30% -> 21.108843 | BR38: =AT38*30% -> 14.140377 | BS38: =AU38*30% -> 28.491851
AS39: 127.35905 | AT39: 127.35905 | AU39: 127.35905 | BD39: Tra_EV_Batt-Sodium_virgin | BE39: 2030 | BF39: =AS39*70% -> 89.151333 | BG39: =AT39*70% -> 89.151333 | BH39: =AU39*70% -> 89.151333 | BO39: Tra_EV_Batt-Sodium_virgin_pack | BP39: 2030 | BQ39: =AS39*30% -> 38.207714 | BR39: =AT39*30% -> 38.207714 | BS39: =AU39*30% -> 38.207714
AG41: ~TFM_INS: attribute=INVCOST
AG45: process | AH45: year | AI45: AllRegions | AJ45: China | AK45: NorthAm | AS45: AllRegions | AT45: China | AU45: NorthAm | AW45: process | AX45: year | AY45: AllRegions | AZ45: China | BA45: NorthAm | BD45: process | BE45: year | BF45: AllRegions | BG45: China | BH45: NorthAm | BO45: process | BP45: year | BQ45: AllRegions | BR45: China | BS45: NorthAm
AG46: Tra_EV_Batt-LFP_virgin | AH46: 2023 | AI46: 0.1 | AJ46: =AI46 -> 0.1 | AK46: =AJ46 -> 0.1 | AS46: 57.416555 | AT46: 39.633379 | AU46: 76.303607 | AW46: Tra_EV_Batt-LFP_fromrecy | AX46: 2035 | AY46: =AY32*AK2/AJ2 -> 57.416555 | AZ46: =AZ32*AK2/AJ2 -> 39.633379 | BA46: =BA32*AK2/AJ2 -> 76.303607 | BD46: Tra_EV_Batt-LFP_virgin | BE46: 2035 | BF46: =AS46*70% -> 40.191588 | BG46: =AT46*70% -> 27.743365 | BH46: =AU46*70% -> 53.412525 | BO46: Tra_EV_Batt-LFP_virgin_pack | BP46: 2035 | BQ46: =AS46*30% -> 17.224966 | BR46: =AT46*30% -> 11.890014 | BS46: =AU46*30% -> 22.891082
AG47: Tra_EV_Batt-LMO_virgin | AH47: 2023 | AI47: 0.1 | AJ47: =AJ46 -> 0.1 | AK47: =AK46 -> 0.1 | AS47: 68.149 | AT47: 47.375464 | AU47: 90.18825 | AW47: Tra_EV_Batt-LMO_fromrecy | AX47: =AX46 -> 2035 | AY47: =AY33*AK3/AJ3 -> 68.149 | AZ47: =AZ33*AK3/AJ3 -> 47.375464 | BA47: =BA33*AK3/AJ3 -> 90.18825 | BD47: Tra_EV_Batt-LMO_virgin | BE47: 2035 | BF47: =AS47*70% -> 47.7043 | BG47: =AT47*70% -> 33.162825 | BH47: =AU47*70% -> 63.131775 | BO47: Tra_EV_Batt-LMO_virgin_pack | BP47: 2035 | BQ47: =AS47*30% -> 20.4447 | BR47: =AT47*30% -> 14.212639 | BS47: =AU47*30% -> 27.056475
AG48: Tra_EV_Batt-NCA_virgin | AH48: 2023 | AI48: =AI47 -> 0.1 | AJ48: =AJ47 -> 0.1 | AK48: =AK47 -> 0.1 | AS48: 60.96264 | AT48: 40.072479 | AU48: 83.0914 | AW48: Tra_EV_Batt-NCA_fromrecy | AX48: =AX47 -> 2035 | AY48: =AY34*AK4/AJ4 -> 60.96264 | AZ48: =AZ34*AK4/AJ4 -> 40.072479 | BA48: =BA34*AK4/AJ4 -> 83.0914 | BD48: Tra_EV_Batt-NCA_virgin | BE48: 2035 | BF48: =AS48*70% -> 42.673848 | BG48: =AT48*70% -> 28.050735 | BH48: =AU48*70% -> 58.16398 | BO48: Tra_EV_Batt-NCA_virgin_pack | BP48: 2035 | BQ48: =AS48*30% -> 18.288792 | BR48: =AT48*30% -> 12.021744 | BS48: =AU48*30% -> 24.92742
AG49: Tra_EV_Batt-NMC111_virgin | AH49: 2023 | AI49: =AI48 -> 0.1 | AJ49: =AJ48 -> 0.1 | AK49: =AK48 -> 0.1 | AS49: 61.086836 | AT49: 39.685364 | AU49: 83.788793 | AW49: Tra_EV_Batt-NMC111_fromrecy | AX49: =AX48 -> 2035 | AY49: =AY35*AK5/AJ5 -> 61.086836 | AZ49: =AZ35*AK5/AJ5 -> 39.685364 | BA49: =BA35*AK5/AJ5 -> 83.788793 | BD49: Tra_EV_Batt-NMC111_virgin | BE49: 2035 | BF49: =AS49*70% -> 42.760785 | BG49: =AT49*70% -> 27.779755 | BH49: =AU49*70% -> 58.652155 | BO49: Tra_EV_Batt-NMC111_virgin_pack | BP49: 2035 | BQ49: =AS49*30% -> 18.326051 | BR49: =AT49*30% -> 11.905609 | BS49: =AU49*30% -> 25.136638
AG50: Tra_EV_Batt-NMC532_virgin | AH50: 2023 | AI50: =AI49 -> 0.1 | AJ50: =AJ49 -> 0.1 | AK50: =AK49 -> 0.1 | AS50: 64.352083 | AT50: 42.4055 | AU50: 87.62075 | AW50: Tra_EV_Batt-NMC532_fromrecy | AX50: =AX49 -> 2035 | AY50: =AY36*AK6/AJ6 -> 64.352083 | AZ50: =AZ36*AK6/AJ6 -> 42.4055 | BA50: =BA36*AK6/AJ6 -> 87.62075 | BD50: Tra_EV_Batt-NMC532_virgin | BE50: 2035 | BF50: =AS50*70% -> 45.046458 | BG50: =AT50*70% -> 29.68385 | BH50: =AU50*70% -> 61.334525 | BO50: Tra_EV_Batt-NMC532_virgin_pack | BP50: 2035 | BQ50: =AS50*30% -> 19.305625 | BR50: =AT50*30% -> 12.72165 | BS50: =AU50*30% -> 26.286225
AG51: Tra_EV_Batt-NMC622_virgin | AH51: 2023 | AI51: =AI50 -> 0.1 | AJ51: =AJ50 -> 0.1 | AK51: =AK50 -> 0.1 | AS51: 62.087298 | AT51: 40.955393 | AU51: 84.480214 | AW51: Tra_EV_Batt-NMC622_fromrecy | AX51: =AX50 -> 2035 | AY51: =AY37*AK7/AJ7 -> 62.087298 | AZ51: =AZ37*AK7/AJ7 -> 40.955393 | BA51: =BA37*AK7/AJ7 -> 84.480214 | BD51: Tra_EV_Batt-NMC622_virgin | BE51: 2035 | BF51: =AS51*70% -> 43.461108 | BG51: =AT51*70% -> 28.668775 | BH51: =AU51*70% -> 59.13615 | BO51: Tra_EV_Batt-NMC622_virgin_pack | BP51: 2035 | BQ51: =AS51*30% -> 18.626189 | BR51: =AT51*30% -> 12.286618 | BS51: =AU51*30% -> 25.344064
AG52: Tra_EV_Batt-NMC811_virgin | AH52: 2023 | AI52: =AI51 -> 0.1 | AJ52: =AJ51 -> 0.1 | AK52: =AK51 -> 0.1 | AS52: 63.96619 | AT52: 42.849629 | AU52: 86.338943 | AW52: Tra_EV_Batt-NMC811_fromrecy | AX52: =AX51 -> 2035 | AY52: =AY38*AK8/AJ8 -> 63.96619 | AZ52: =AZ38*AK8/AJ8 -> 42.849629 | BA52: =BA38*AK8/AJ8 -> 86.338943 | BD52: Tra_EV_Batt-NMC811_virgin | BE52: 2035 | BF52: =AS52*70% -> 44.776333 | BG52: =AT52*70% -> 29.99474 | BH52: =AU52*70% -> 60.43726 | BO52: Tra_EV_Batt-NMC811_virgin_pack | BP52: 2035 | BQ52: =AS52*30% -> 19.189857 | BR52: =AT52*30% -> 12.854889 | BS52: =AU52*30% -> 25.901683
AG53: Tra_EV_Batt-Sodium_virgin | AH53: 2023 | AI53: =AI52 -> 0.1 | AJ53: =AJ52 -> 0.1 | AK53: =AK52 -> 0.1 | AS53: 115.78095 | AT53: 115.78095 | AU53: 115.78095 | BD53: Tra_EV_Batt-Sodium_virgin | BE53: 2035 | BF53: =AS53*70% -> 81.046667 | BG53: =AT53*70% -> 81.046667 | BH53: =AU53*70% -> 81.046667 | BO53: Tra_EV_Batt-Sodium_virgin_pack | BP53: 2035 | BQ53: =AS53*30% -> 34.734286 | BR53: =AT53*30% -> 34.734286 | BS53: =AU53*30% -> 34.734286
AS59: AllRegions | AT59: China | AU59: NorthAm | AW59: process | AX59: year | AY59: AllRegions | AZ59: China | BA59: NorthAm | BD59: process | BE59: year | BF59: AllRegions | BG59: China | BH59: NorthAm | BO59: process | BP59: year | BQ59: AllRegions | BR59: China | BS59: NorthAm
AS60: 55.694058 | AT60: 38.444377 | AU60: 74.014499 | AW60: Tra_EV_Batt-LFP_fromrecy | AX60: 2040 | AY60: =AY46*0.97 -> 55.694058 | AZ60: =AZ46*0.97 -> 38.444377 | BA60: =BA46*0.97 -> 74.014499 | BD60: Tra_EV_Batt-LFP_virgin | BE60: 2040 | BF60: =AS60*70% -> 38.985841 | BG60: =AT60*70% -> 26.911064 | BH60: =AU60*70% -> 51.810149 | BO60: Tra_EV_Batt-LFP_virgin_pack | BP60: 2040 | BQ60: =AS60*30% -> 16.708217 | BR60: =AT60*30% -> 11.533313 | BS60: =AU60*30% -> 22.20435
AS61: 66.10453 | AT61: 45.9542 | AU61: 87.482603 | AW61: Tra_EV_Batt-LMO_fromrecy | AX61: =AX60 -> 2040 | AY61: =AY47*0.97 -> 66.10453 | AZ61: =AZ47*0.97 -> 45.9542 | BA61: =BA47*0.97 -> 87.482603 | BD61: Tra_EV_Batt-LMO_virgin | BE61: 2040 | BF61: =AS61*70% -> 46.273171 | BG61: =AT61*70% -> 32.16794 | BH61: =AU61*70% -> 61.237822 | BO61: Tra_EV_Batt-LMO_virgin_pack | BP61: 2040 | BQ61: =AS61*30% -> 19.831359 | BR61: =AT61*30% -> 13.78626 | BS61: =AU61*30% -> 26.244781
AS62: 59.133761 | AT62: 38.870304 | AU62: 80.598658 | AW62: Tra_EV_Batt-NCA_fromrecy | AX62: =AX61 -> 2040 | AY62: =AY48*0.97 -> 59.133761 | AZ62: =AZ48*0.97 -> 38.870304 | BA62: =BA48*0.97 -> 80.598658 | BD62: Tra_EV_Batt-NCA_virgin | BE62: 2040 | BF62: =AS62*70% -> 41.393633 | BG62: =AT62*70% -> 27.209213 | BH62: =AU62*70% -> 56.419061 | BO62: Tra_EV_Batt-NCA_virgin_pack | BP62: 2040 | BQ62: =AS62*30% -> 17.740128 | BR62: =AT62*30% -> 11.661091 | BS62: =AU62*30% -> 24.179597
AS63: 59.254231 | AT63: 38.494803 | AU63: 81.275129 | AW63: Tra_EV_Batt-NMC111_fromrecy | AX63: =AX62 -> 2040 | AY63: =AY49*0.97 -> 59.254231 | AZ63: =AZ49*0.97 -> 38.494803 | BA63: =BA49*0.97 -> 81.275129 | BD63: Tra_EV_Batt-NMC111_virgin | BE63: 2040 | BF63: =AS63*70% -> 41.477961 | BG63: =AT63*70% -> 26.946362 | BH63: =AU63*70% -> 56.89259 | BO63: Tra_EV_Batt-NMC111_virgin_pack | BP63: 2040 | BQ63: =AS63*30% -> 17.776269 | BR63: =AT63*30% -> 11.548441 | BS63: =AU63*30% -> 24.382539
AS64: 62.421521 | AT64: 41.133335 | AU64: 84.992128 | AW64: Tra_EV_Batt-NMC532_fromrecy | AX64: =AX63 -> 2040 | AY64: =AY50*0.97 -> 62.421521 | AZ64: =AZ50*0.97 -> 41.133335 | BA64: =BA50*0.97 -> 84.992128 | BD64: Tra_EV_Batt-NMC532_virgin | BE64: 2040 | BF64: =AS64*70% -> 43.695065 | BG64: =AT64*70% -> 28.793335 | BH64: =AU64*70% -> 59.494489 | BO64: Tra_EV_Batt-NMC532_virgin_pack | BP64: 2040 | BQ64: =AS64*30% -> 18.726456 | BR64: =AT64*30% -> 12.340001 | BS64: =AU64*30% -> 25.497638
AS65: 60.224679 | AT65: 39.726731 | AU65: 81.945808 | AW65: Tra_EV_Batt-NMC622_fromrecy | AX65: =AX64 -> 2040 | AY65: =AY51*0.97 -> 60.224679 | AZ65: =AZ51*0.97 -> 39.726731 | BA65: =BA51*0.97 -> 81.945808 | BD65: Tra_EV_Batt-NMC622_virgin | BE65: 2040 | BF65: =AS65*70% -> 42.157275 | BG65: =AT65*70% -> 27.808712 | BH65: =AU65*70% -> 57.362066 | BO65: Tra_EV_Batt-NMC622_virgin_pack | BP65: 2040 | BQ65: =AS65*30% -> 18.067404 | BR65: =AT65*30% -> 11.918019 | BS65: =AU65*30% -> 24.583742
AS66: 62.047205 | AT66: 41.56414 | AU66: 83.748775 | AW66: Tra_EV_Batt-NMC811_fromrecy | AX66: =AX65 -> 2040 | AY66: =AY52*0.97 -> 62.047205 | AZ66: =AZ52*0.97 -> 41.56414 | BA66: =BA52*0.97 -> 83.748775 | BD66: Tra_EV_Batt-NMC811_virgin | BE66: 2040 | BF66: =AS66*70% -> 43.433043 | BG66: =AT66*70% -> 29.094898 | BH66: =AU66*70% -> 58.624142 | BO66: Tra_EV_Batt-NMC811_virgin_pack | BP66: 2040 | BQ66: =AS66*30% -> 18.614161 | BR66: =AT66*30% -> 12.469242 | BS66: =AU66*30% -> 25.124632
AS67: 112.30752 | AT67: 112.30752 | AU67: 112.30752 | BD67: Tra_EV_Batt-Sodium_virgin | BE67: 2040 | BF67: =AS67*70% -> 78.615267 | BG67: =AT67*70% -> 78.615267 | BH67: =AU67*70% -> 78.615267 | BO67: Tra_EV_Batt-Sodium_virgin_pack | BP67: 2040 | BQ67: =AS67*30% -> 33.692257 | BR67: =AT67*30% -> 33.692257 | BS67: =AU67*30% -> 33.692257
AS75: AllRegions | AT75: China | AU75: NorthAm | AW75: process | AX75: year | AY75: AllRegions | AZ75: China | BA75: NorthAm | BD75: process | BE75: year | BF75: AllRegions | BG75: China | BH75: NorthAm | BO75: process | BP75: year | BQ75: AllRegions | BR75: China | BS75: NorthAm
AS76: 53.466296 | AT76: 36.906602 | AU76: 71.053919 | AW76: Tra_EV_Batt-LFP_fromrecy | AX76: 2045 | AY76: =AY60*0.96 -> 53.466296 | AZ76: =AZ60*0.96 -> 36.906602 | BA76: =BA60*0.96 -> 71.053919 | BD76: Tra_EV_Batt-LFP_virgin | BE76: 2045 | BF76: =AS76*70% -> 37.426407 | BG76: =AT76*70% -> 25.834621 | BH76: =AU76*70% -> 49.737743 | BO76: Tra_EV_Batt-LFP_virgin_pack | BP76: 2045 | BQ76: =AS76*30% -> 16.039889 | BR76: =AT76*30% -> 11.071981 | BS76: =AU76*30% -> 21.316176
AS77: 63.460349 | AT77: 44.116032 | AU77: 83.983298 | AW77: Tra_EV_Batt-LMO_fromrecy | AX77: =AX76 -> 2045 | AY77: =AY61*0.96 -> 63.460349 | AZ77: =AZ61*0.96 -> 44.116032 | BA77: =BA61*0.96 -> 83.983298 | BD77: Tra_EV_Batt-LMO_virgin | BE77: 2045 | BF77: =AS77*70% -> 44.422244 | BG77: =AT77*70% -> 30.881223 | BH77: =AU77*70% -> 58.788309 | BO77: Tra_EV_Batt-LMO_virgin_pack | BP77: 2045 | BQ77: =AS77*30% -> 19.038105 | BR77: =AT77*30% -> 13.23481 | BS77: =AU77*30% -> 25.19499
AS78: 56.768411 | AT78: 37.315492 | AU78: 77.374712 | AW78: Tra_EV_Batt-NCA_fromrecy | AX78: =AX77 -> 2045 | AY78: =AY62*0.96 -> 56.768411 | AZ78: =AZ62*0.96 -> 37.315492 | BA78: =BA62*0.96 -> 77.374712 | BD78: Tra_EV_Batt-NCA_virgin | BE78: 2045 | BF78: =AS78*70% -> 39.737888 | BG78: =AT78*70% -> 26.120844 | BH78: =AU78*70% -> 54.162298 | BO78: Tra_EV_Batt-NCA_virgin_pack | BP78: 2045 | BQ78: =AS78*30% -> 17.030523 | BR78: =AT78*30% -> 11.194648 | BS78: =AU78*30% -> 23.212414
AS79: 56.884061 | AT79: 36.955011 | AU79: 78.024124 | AW79: Tra_EV_Batt-NMC111_fromrecy | AX79: =AX78 -> 2045 | AY79: =AY63*0.96 -> 56.884061 | AZ79: =AZ63*0.96 -> 36.955011 | BA79: =BA63*0.96 -> 78.024124 | BD79: Tra_EV_Batt-NMC111_virgin | BE79: 2045 | BF79: =AS79*70% -> 39.818843 | BG79: =AT79*70% -> 25.868508 | BH79: =AU79*70% -> 54.616887 | BO79: Tra_EV_Batt-NMC111_virgin_pack | BP79: 2045 | BQ79: =AS79*30% -> 17.065218 | BR79: =AT79*30% -> 11.086503 | BS79: =AU79*30% -> 23.407237
AS80: 59.92466 | AT80: 39.488002 | AU80: 81.592442 | AW80: Tra_EV_Batt-NMC532_fromrecy | AX80: =AX79 -> 2045 | AY80: =AY64*0.96 -> 59.92466 | AZ80: =AZ64*0.96 -> 39.488002 | BA80: =BA64*0.96 -> 81.592442 | BD80: Tra_EV_Batt-NMC532_virgin | BE80: 2045 | BF80: =AS80*70% -> 41.947262 | BG80: =AT80*70% -> 27.641601 | BH80: =AU80*70% -> 57.11471 | BO80: Tra_EV_Batt-NMC532_virgin_pack | BP80: 2045 | BQ80: =AS80*30% -> 17.977398 | BR80: =AT80*30% -> 11.8464 | BS80: =AU80*30% -> 24.477733
AS81: 57.815692 | AT81: 38.137662 | AU81: 78.667976 | AW81: Tra_EV_Batt-NMC622_fromrecy | AX81: =AX80 -> 2045 | AY81: =AY65*0.96 -> 57.815692 | AZ81: =AZ65*0.96 -> 38.137662 | BA81: =BA65*0.96 -> 78.667976 | BD81: Tra_EV_Batt-NMC622_virgin | BE81: 2045 | BF81: =AS81*70% -> 40.470984 | BG81: =AT81*70% -> 26.696363 | BH81: =AU81*70% -> 55.067583 | BO81: Tra_EV_Batt-NMC622_virgin_pack | BP81: 2045 | BQ81: =AS81*30% -> 17.344707 | BR81: =AT81*30% -> 11.441299 | BS81: =AU81*30% -> 23.600393
AS82: 59.565317 | AT82: 39.901574 | AU82: 80.398824 | AW82: Tra_EV_Batt-NMC811_fromrecy | AX82: =AX81 -> 2045 | AY82: =AY66*0.96 -> 59.565317 | AZ82: =AZ66*0.96 -> 39.901574 | BA82: =BA66*0.96 -> 80.398824 | BD82: Tra_EV_Batt-NMC811_virgin | BE82: 2045 | BF82: =AS82*70% -> 41.695722 | BG82: =AT82*70% -> 27.931102 | BH82: =AU82*70% -> 56.279177 | BO82: Tra_EV_Batt-NMC811_virgin_pack | BP82: 2045 | BQ82: =AS82*30% -> 17.869595 | BR82: =AT82*30% -> 11.970472 | BS82: =AU82*30% -> 24.119647
AS83: 107.81522 | AT83: 107.81522 | AU83: 107.81522 | BD83: Tra_EV_Batt-Sodium_virgin | BE83: 2045 | BF83: =AS83*70% -> 75.470656 | BG83: =AT83*70% -> 75.470656 | BH83: =AU83*70% -> 75.470656 | BO83: Tra_EV_Batt-Sodium_virgin_pack | BP83: 2045 | BQ83: =AS83*30% -> 32.344567 | BR83: =AT83*30% -> 32.344567 | BS83: =AU83*30% -> 32.344567
AW85: ~TFM_INS: attribute=INVCOST | BD85: ~TFM_INS: attribute=ACT_COST | BO85: ~TFM_INS: attribute=INVCOST
AS88: AllRegions | AT88: China | AU88: NorthAm | AW88: process | AX88: year | AY88: AllRegions | AZ88: China | BA88: NorthAm | BD88: process | BE88: year | BF88: AllRegions | BG88: China | BH88: NorthAm | BO88: process | BP88: year | BQ88: AllRegions | BR88: China | BS88: NorthAm
AS89: 51.327644 | AT89: 35.430338 | AU89: 68.211762 | AW89: Tra_EV_Batt-LFP_fromrecy | AX89: 2050 | AY89: =AY76*0.96 -> 51.327644 | AZ89: =AZ76*0.96 -> 35.430338 | BA89: =BA76*0.96 -> 68.211762 | BD89: Tra_EV_Batt-LFP_virgin | BE89: 2050 | BF89: =AS89*70% -> 35.929351 | BG89: =AT89*70% -> 24.801237 | BH89: =AU89*70% -> 47.748234 | BO89: Tra_EV_Batt-LFP_virgin_pack | BP89: 2050 | BQ89: =AS89*30% -> 15.398293 | BR89: =AT89*30% -> 10.629101 | BS89: =AU89*30% -> 20.463529
AS90: 60.921935 | AT90: 42.351391 | AU90: 80.623966 | AW90: Tra_EV_Batt-LMO_fromrecy | AX90: =AX89 -> 2050 | AY90: =AY77*0.96 -> 60.921935 | AZ90: =AZ77*0.96 -> 42.351391 | BA90: =BA77*0.96 -> 80.623966 | BD90: Tra_EV_Batt-LMO_virgin | BE90: 2050 | BF90: =AS90*70% -> 42.645354 | BG90: =AT90*70% -> 29.645974 | BH90: =AU90*70% -> 56.436777 | BO90: Tra_EV_Batt-LMO_virgin_pack | BP90: 2050 | BQ90: =AS90*30% -> 18.27658 | BR90: =AT90*30% -> 12.705417 | BS90: =AU90*30% -> 24.18719
AS91: 54.497674 | AT91: 35.822872 | AU91: 74.279723 | AW91: Tra_EV_Batt-NCA_fromrecy | AX91: =AX90 -> 2050 | AY91: =AY78*0.96 -> 54.497674 | AZ91: =AZ78*0.96 -> 35.822872 | BA91: =BA78*0.96 -> 74.279723 | BD91: Tra_EV_Batt-NCA_virgin | BE91: 2050 | BF91: =AS91*70% -> 38.148372 | BG91: =AT91*70% -> 25.076011 | BH91: =AU91*70% -> 51.995806 | BO91: Tra_EV_Batt-NCA_virgin_pack | BP91: 2050 | BQ91: =AS91*30% -> 16.349302 | BR91: =AT91*30% -> 10.746862 | BS91: =AU91*30% -> 22.283917
AS92: 54.608699 | AT92: 35.476811 | AU92: 74.903159 | AW92: Tra_EV_Batt-NMC111_fromrecy | AX92: =AX91 -> 2050 | AY92: =AY79*0.96 -> 54.608699 | AZ92: =AZ79*0.96 -> 35.476811 | BA92: =BA79*0.96 -> 74.903159 | BD92: Tra_EV_Batt-NMC111_virgin | BE92: 2050 | BF92: =AS92*70% -> 38.226089 | BG92: =AT92*70% -> 24.833768 | BH92: =AU92*70% -> 52.432211 | BO92: Tra_EV_Batt-NMC111_virgin_pack | BP92: 2050 | BQ92: =AS92*30% -> 16.38261 | BR92: =AT92*30% -> 10.643043 | BS92: =AU92*30% -> 22.470948
AS93: 57.527674 | AT93: 37.908482 | AU93: 78.328745 | AW93: Tra_EV_Batt-NMC532_fromrecy | AX93: =AX92 -> 2050 | AY93: =AY80*0.96 -> 57.527674 | AZ93: =AZ80*0.96 -> 37.908482 | BA93: =BA80*0.96 -> 78.328745 | BD93: Tra_EV_Batt-NMC532_virgin | BE93: 2050 | BF93: =AS93*70% -> 40.269372 | BG93: =AT93*70% -> 26.535937 | BH93: =AU93*70% -> 54.830121 | BO93: Tra_EV_Batt-NMC532_virgin_pack | BP93: 2050 | BQ93: =AS93*30% -> 17.258302 | BR93: =AT93*30% -> 11.372544 | BS93: =AU93*30% -> 23.498623
AS94: 55.503064 | AT94: 36.612155 | AU94: 75.521257 | AW94: Tra_EV_Batt-NMC622_fromrecy | AX94: =AX93 -> 2050 | AY94: =AY81*0.96 -> 55.503064 | AZ94: =AZ81*0.96 -> 36.612155 | BA94: =BA81*0.96 -> 75.521257 | BD94: Tra_EV_Batt-NMC622_virgin | BE94: 2050 | BF94: =AS94*70% -> 38.852145 | BG94: =AT94*70% -> 25.628509 | BH94: =AU94*70% -> 52.86488 | BO94: Tra_EV_Batt-NMC622_virgin_pack | BP94: 2050 | BQ94: =AS94*30% -> 16.650919 | BR94: =AT94*30% -> 10.983647 | BS94: =AU94*30% -> 22.656377
AS95: 57.182704 | AT95: 38.305511 | AU95: 77.182871 | AW95: Tra_EV_Batt-NMC811_fromrecy | AX95: =AX94 -> 2050 | AY95: =AY82*0.96 -> 57.182704 | AZ95: =AZ82*0.96 -> 38.305511 | BA95: =BA82*0.96 -> 77.182871 | BD95: Tra_EV_Batt-NMC811_virgin | BE95: 2050 | BF95: =AS95*70% -> 40.027893 | BG95: =AT95*70% -> 26.813858 | BH95: =AU95*70% -> 54.028009 | BO95: Tra_EV_Batt-NMC811_virgin_pack | BP95: 2050 | BQ95: =AS95*30% -> 17.154811 | BR95: =AT95*30% -> 11.491653 | BS95: =AU95*30% -> 23.154861
AS96: 103.50261 | AT96: 103.50261 | AU96: 103.50261 | BD96: Tra_EV_Batt-Sodium_virgin | BE96: 2050 | BF96: =AS96*70% -> 72.45183 | BG96: =AT96*70% -> 72.45183 | BH96: =AU96*70% -> 72.45183 | BO96: Tra_EV_Batt-Sodium_virgin_pack | BP96: 2050 | BQ96: =AS96*30% -> 31.050784 | BR96: =AT96*30% -> 31.050784 | BS96: =AU96*30% -> 31.050784
AW102: ~TFM_INS: attribute=INVCOST | BD102: ~TFM_INS: attribute=ACT_COST | BO102: ~TFM_INS: attribute=INVCOST
AS105: AllRegions | AT105: China | AU105: NorthAm | AW105: process | AX105: year | AY105: AllRegions | AZ105: China | BA105: NorthAm | BD105: process | BE105: year | BF105: AllRegions | BG105: China | BH105: NorthAm | BO105: process | BP105: year | BQ105: AllRegions | BR105: China | BS105: NorthAm
AS106: =AS89*80% -> 41.062115 | AT106: =AT89*80% -> 28.34427 | AU106: =AU89*80% -> 54.56941 | AW106: Tra_EV_Batt-LFP_fromrecy | AX106: 2100 | AY106: =AS106 -> 41.062115 | AZ106: =AT106 -> 28.34427 | BA106: =AU106 -> 54.56941 | BD106: Tra_EV_Batt-LFP_virgin | BE106: 2100 | BF106: =AS106*70% -> 28.743481 | BG106: =AT106*70% -> 19.840989 | BH106: =AU106*70% -> 38.198587 | BO106: Tra_EV_Batt-LFP_virgin_pack | BP106: 2100 | BQ106: =AS106*30% -> 12.318635 | BR106: =AT106*30% -> 8.5032811 | BS106: =AU106*30% -> 16.370823
AS107: =AS90*80% -> 48.737548 | AT107: =AT90*80% -> 33.881113 | AU107: =AU90*80% -> 64.499173 | AW107: Tra_EV_Batt-LMO_fromrecy | AX107: =AX106 -> 2100 | AY107: =AS107 -> 48.737548 | AZ107: =AT107 -> 33.881113 | BA107: =AU107 -> 64.499173 | BD107: Tra_EV_Batt-LMO_virgin | BE107: 2100 | BF107: =AS107*70% -> 34.116284 | BG107: =AT107*70% -> 23.716779 | BH107: =AU107*70% -> 45.149421 | BO107: Tra_EV_Batt-LMO_virgin_pack | BP107: 2100 | BQ107: =AS107*30% -> 14.621264 | BR107: =AT107*30% -> 10.164334 | BS107: =AU107*30% -> 19.349752
AS108: =AS91*80% -> 43.59814 | AT108: =AT91*80% -> 28.658298 | AU108: =AU91*80% -> 59.423779 | AW108: Tra_EV_Batt-NCA_fromrecy | AX108: =AX107 -> 2100 | AY108: =AS108 -> 43.59814 | AZ108: =AT108 -> 28.658298 | BA108: =AU108 -> 59.423779 | BD108: Tra_EV_Batt-NCA_virgin | BE108: 2100 | BF108: =AS108*70% -> 30.518698 | BG108: =AT108*70% -> 20.060809 | BH108: =AU108*70% -> 41.596645 | BO108: Tra_EV_Batt-NCA_virgin_pack | BP108: 2100 | BQ108: =AS108*30% -> 13.079442 | BR108: =AT108*30% -> 8.5974894 | BS108: =AU108*30% -> 17.827134
AS109: =AS92*80% -> 43.686959 | AT109: =AT92*80% -> 28.381449 | AU109: =AU92*80% -> 59.922527 | AW109: Tra_EV_Batt-NMC111_fromrecy | AX109: =AX108 -> 2100 | AY109: =AS109 -> 43.686959 | AZ109: =AT109 -> 28.381449 | BA109: =AU109 -> 59.922527 | BD109: Tra_EV_Batt-NMC111_virgin | BE109: 2100 | BF109: =AS109*70% -> 30.580871 | BG109: =AT109*70% -> 19.867014 | BH109: =AU109*70% -> 41.945769 | BO109: Tra_EV_Batt-NMC111_virgin_pack | BP109: 2100 | BQ109: =AS109*30% -> 13.106088 | BR109: =AT109*30% -> 8.5144346 | BS109: =AU109*30% -> 17.976758
AS110: =AS93*80% -> 46.022139 | AT110: =AT93*80% -> 30.326785 | AU110: =AU93*80% -> 62.662996 | AW110: Tra_EV_Batt-NMC532_fromrecy | AX110: =AX109 -> 2100 | AY110: =AS110 -> 46.022139 | AZ110: =AT110 -> 30.326785 | BA110: =AU110 -> 62.662996 | BD110: Tra_EV_Batt-NMC532_virgin | BE110: 2100 | BF110: =AS110*70% -> 32.215497 | BG110: =AT110*70% -> 21.22875 | BH110: =AU110*70% -> 43.864097 | BO110: Tra_EV_Batt-NMC532_virgin_pack | BP110: 2100 | BQ110: =AS110*30% -> 13.806642 | BR110: =AT110*30% -> 9.0980356 | BS110: =AU110*30% -> 18.798899
AS111: =AS94*80% -> 44.402451 | AT111: =AT94*80% -> 29.289724 | AU111: =AU94*80% -> 60.417005 | AW111: Tra_EV_Batt-NMC622_fromrecy | AX111: =AX110 -> 2100 | AY111: =AS111 -> 44.402451 | AZ111: =AT111 -> 29.289724 | BA111: =AU111 -> 60.417005 | BD111: Tra_EV_Batt-NMC622_virgin | BE111: 2100 | BF111: =AS111*70% -> 31.081716 | BG111: =AT111*70% -> 20.502807 | BH111: =AU111*70% -> 42.291904 | BO111: Tra_EV_Batt-NMC622_virgin_pack | BP111: 2100 | BQ111: =AS111*30% -> 13.320735 | BR111: =AT111*30% -> 8.7869173 | BS111: =AU111*30% -> 18.125102
AS112: =AS95*80% -> 45.746163 | AT112: =AT95*80% -> 30.644409 | AU112: =AU95*80% -> 61.746297 | AW112: Tra_EV_Batt-NMC811_fromrecy | AX112: =AX111 -> 2100 | AY112: =AS112 -> 45.746163 | AZ112: =AT112 -> 30.644409 | BA112: =AU112 -> 61.746297 | BD112: Tra_EV_Batt-NMC811_virgin | BE112: 2100 | BF112: =AS112*70% -> 32.022314 | BG112: =AT112*70% -> 21.451086 | BH112: =AU112*70% -> 43.222408 | BO112: Tra_EV_Batt-NMC811_virgin_pack | BP112: 2100 | BQ112: =AS112*30% -> 13.723849 | BR112: =AT112*30% -> 9.1933227 | BS112: =AU112*30% -> 18.523889
AS113: =AS96*80% -> 82.802091 | AT113: =AT96*80% -> 82.802091 | AU113: =AU96*80% -> 82.802091 | BD113: Tra_EV_Batt-Sodium_virgin | BE113: 2100 | BF113: =AS113*70% -> 57.961464 | BG113: =AT113*70% -> 57.961464 | BH113: =AU113*70% -> 57.961464 | BO113: Tra_EV_Batt-Sodium_virgin_pack | BP113: 2100 | BQ113: =AS113*30% -> 24.840627 | BR113: =AT113*30% -> 24.840627 | BS113: =AU113*30% -> 24.840627
AS119: AllRegions | AT119: China | AU119: NorthAm
AS120: 3 | AT120: 3 | AU120: 3
AS121: 3 | AT121: 3 | AU121: 3
AS122: 3 | AT122: 3 | AU122: 3
AS123: 3 | AT123: 3 | AU123: 3
AS124: 3 | AT124: 3 | AU124: 3
AS125: 3 | AT125: 3 | AU125: 3
AS126: 3 | AT126: 3 | AU126: 3
AS127: 3 | AT127: 3 | AU127: 3

Sheet Revised__InvCost
A1: EV battery INVCOST (million $ per GWh) - virgin and recycled routes, 35 regions
A2: Blue = editable input. Black = formula. Yellow = key assumption to test. INVCOST = BaseCost(chem) x FrontierIndex(route,year) x RegionMultiplier(tier,year).
A4: 1. BASE COST BY CHEMISTRY (2023, China frontier)
A5: Process - recycled | B5: Process - virgin | C5: Base 2023 recy | D5: Virgin/recy ratio | E5: Base 2023 virgin
A6: Tra_EV_Batt-LFP_fromrecy | B6: Tra_EV_Batt-LFP | C6: 55.48673 | D6: 1 | E6: =C6*D6 -> 55.48673
A7: Tra_EV_Batt-LMO_fromrecy | B7: Tra_EV_Batt-LMO | C7: 66.32565 | D7: 1 | E7: =C7*D7 -> 66.32565
A8: Tra_EV_Batt-NCA_fromrecy | B8: Tra_EV_Batt-NCA | C8: 56.10147 | D8: 1 | E8: =C8*D8 -> 56.10147
A9: Tra_EV_Batt-NMC111_fromrecy | B9: Tra_EV_Batt-NMC111 | C9: 55.55951 | D9: 1 | E9: =C9*D9 -> 55.55951
A10: Tra_EV_Batt-NMC532_fromrecy | B10: Tra_EV_Batt-NMC532 | C10: 59.3677 | D10: 1 | E10: =C10*D10 -> 59.3677
A11: Tra_EV_Batt-NMC622_fromrecy | B11: Tra_EV_Batt-NMC622 | C11: 57.33755 | D11: 1 | E11: =C11*D11 -> 57.33755
A12: Tra_EV_Batt-NMC811_fromrecy | B12: Tra_EV_Batt-NMC811 | C12: 59.98948 | D12: 1 | E12: =C12*D12 -> 59.98948
A13: Base costs are your own 2023 China values. Virgin ratio defaults to 1.000 - REPLACE with real virgin capex data. Virgin process names are placeholders; overwrite column B.
A15: 2. FRONTIER DECAY - Index(t) = Floor + (1-Floor) x EXP(-lambda x (t-2023))
A16: Route | B16: Floor | C16: Lambda
A17: recy | B17: 0.38 | C17: 0.0479
A18: virgin | B18: 0.46 | C18: 0.0451
A20: Frontier index (2023 = 1.000)
A21: Route | B21: 2023 | C21: 2050 | D21: 2100
A22: recy | B22: =$B$17+(1-$B$17)*EXP(-$C$17*(2023-2023)) -> 1 | C22: =$B$17+(1-$B$17)*EXP(-$C$17*(2050-2023)) -> 0.55010561 | D22: =$B$17+(1-$B$17)*EXP(-$C$17*(2100-2023)) -> 0.39550898
A23: virgin | B23: =$B$18+(1-$B$18)*EXP(-$C$18*(2023-2023)) -> 1 | C23: =$B$18+(1-$B$18)*EXP(-$C$18*(2050-2023)) -> 0.61979139 | D23: =$B$18+(1-$B$18)*EXP(-$C$18*(2100-2023)) -> 0.47675789
A24: Recycling declines faster than virgin: less mature technology, more learning headroom. Anchor lambda to a published Li-ion learning rate (~15-20% per doubling) and cite it.
A26: 3. REGION TIERS - Mult(t) = Mfloor + (M2023 - Mfloor) x EXP(-k x (t-2023))
A27: Tier | B27: M 2023 | C27: M floor | D27: k | E27: Rationale
A28: Frontier | B28: 1 | C28: 1 | D28: 0 | E28: China. Global cost frontier, already near its floor.
A29: Developed | B29: 1.75 | C29: 1.18 | D29: 0.04484 | E29: High labour, energy, permitting costs; strong catch-up potential.
A30: Emerging | B30: 1.45 | C30: 1.08 | D30: 0.04846 | E30: Higher capital cost, no scale today; fastest convergence.
A31: Floors stay above 1.00: industrial electricity price, permitting and labour differences do not vanish, so full convergence to parity would not be credible. Tier column below is editable.
A33: 4. MULTIPLIER BY REGION
A34: Region | B34: Tier | C34: 2023 | D34: 2050 | E34: 2100
A35: Africa_North | B35: Emerging | C35: =INDEX($C$28:$C$30,MATCH($B35,$A$28:$A$30,0))+(INDEX($B$28:$B$30,MATCH($B35,$A$28:$A$30,0))-INDEX($C$28:$C$30,MATCH($B35,$A$28:$A$30,0)))*EXP(-INDEX($D$28:$D$30,MATCH($B35,$A$28:$A$30,0))*(2023-2023)) -> 1.45 | D35: =INDEX($C$28:$C$30,MATCH($B35,$A$28:$A$30,0))+(INDEX($B$28:$B$30,MATCH($B35,$A$28:$A$30,0))-INDEX($C$28:$C$30,MATCH($B35,$A$28:$A$30,0)))*EXP(-INDEX($D$28:$D$30,MATCH($B35,$A$28:$A$30,0))*(2050-2023)) -> 1.1799913 | E35: =INDEX($C$28:$C$30,MATCH($B35,$A$28:$A$30,0))+(INDEX($B$28:$B$30,MATCH($B35,$A$28:$A$30,0))-INDEX($C$28:$C$30,MATCH($B35,$A$28:$A$30,0)))*EXP(-INDEX($D$28:$D$30,MATCH($B35,$A$28:$A$30,0))*(2100-2023)) -> 1.0888648
A36: Africa_Other | B36: Emerging | C36: =INDEX($C$28:$C$30,MATCH($B36,$A$28:$A$30,0))+(INDEX($B$28:$B$30,MATCH($B36,$A$28:$A$30,0))-INDEX($C$28:$C$30,MATCH($B36,$A$28:$A$30,0)))*EXP(-INDEX($D$28:$D$30,MATCH($B36,$A$28:$A$30,0))*(2023-2023)) -> 1.45 | D36: =INDEX($C$28:$C$30,MATCH($B36,$A$28:$A$30,0))+(INDEX($B$28:$B$30,MATCH($B36,$A$28:$A$30,0))-INDEX($C$28:$C$30,MATCH($B36,$A$28:$A$30,0)))*EXP(-INDEX($D$28:$D$30,MATCH($B36,$A$28:$A$30,0))*(2050-2023)) -> 1.1799913 | E36: =INDEX($C$28:$C$30,MATCH($B36,$A$28:$A$30,0))+(INDEX($B$28:$B$30,MATCH($B36,$A$28:$A$30,0))-INDEX($C$28:$C$30,MATCH($B36,$A$28:$A$30,0)))*EXP(-INDEX($D$28:$D$30,MATCH($B36,$A$28:$A$30,0))*(2100-2023)) -> 1.0888648
A37: Australia | B37: Developed | C37: =INDEX($C$28:$C$30,MATCH($B37,$A$28:$A$30,0))+(INDEX($B$28:$B$30,MATCH($B37,$A$28:$A$30,0))-INDEX($C$28:$C$30,MATCH($B37,$A$28:$A$30,0)))*EXP(-INDEX($D$28:$D$30,MATCH($B37,$A$28:$A$30,0))*(2023-2023)) -> 1.75 | D37: =INDEX($C$28:$C$30,MATCH($B37,$A$28:$A$30,0))+(INDEX($B$28:$B$30,MATCH($B37,$A$28:$A$30,0))-INDEX($C$28:$C$30,MATCH($B37,$A$28:$A$30,0)))*EXP(-INDEX($D$28:$D$30,MATCH($B37,$A$28:$A$30,0))*(2050-2023)) -> 1.3498569 | E37: =INDEX($C$28:$C$30,MATCH($B37,$A$28:$A$30,0))+(INDEX($B$28:$B$30,MATCH($B37,$A$28:$A$30,0))-INDEX($C$28:$C$30,MATCH($B37,$A$28:$A$30,0)))*EXP(-INDEX($D$28:$D$30,MATCH($B37,$A$28:$A$30,0))*(2100-2023)) -> 1.1980466
A38: Austria | B38: Developed | C38: =INDEX($C$28:$C$30,MATCH($B38,$A$28:$A$30,0))+(INDEX($B$28:$B$30,MATCH($B38,$A$28:$A$30,0))-INDEX($C$28:$C$30,MATCH($B38,$A$28:$A$30,0)))*EXP(-INDEX($D$28:$D$30,MATCH($B38,$A$28:$A$30,0))*(2023-2023)) -> 1.75 | D38: =INDEX($C$28:$C$30,MATCH($B38,$A$28:$A$30,0))+(INDEX($B$28:$B$30,MATCH($B38,$A$28:$A$30,0))-INDEX($C$28:$C$30,MATCH($B38,$A$28:$A$30,0)))*EXP(-INDEX($D$28:$D$30,MATCH($B38,$A$28:$A$30,0))*(2050-2023)) -> 1.3498569 | E38: =INDEX($C$28:$C$30,MATCH($B38,$A$28:$A$30,0))+(INDEX($B$28:$B$30,MATCH($B38,$A$28:$A$30,0))-INDEX($C$28:$C$30,MATCH($B38,$A$28:$A$30,0)))*EXP(-INDEX($D$28:$D$30,MATCH($B38,$A$28:$A$30,0))*(2100-2023)) -> 1.1980466
A39: Baltics | B39: Emerging | C39: =INDEX($C$28:$C$30,MATCH($B39,$A$28:$A$30,0))+(INDEX($B$28:$B$30,MATCH($B39,$A$28:$A$30,0))-INDEX($C$28:$C$30,MATCH($B39,$A$28:$A$30,0)))*EXP(-INDEX($D$28:$D$30,MATCH($B39,$A$28:$A$30,0))*(2023-2023)) -> 1.45 | D39: =INDEX($C$28:$C$30,MATCH($B39,$A$28:$A$30,0))+(INDEX($B$28:$B$30,MATCH($B39,$A$28:$A$30,0))-INDEX($C$28:$C$30,MATCH($B39,$A$28:$A$30,0)))*EXP(-INDEX($D$28:$D$30,MATCH($B39,$A$28:$A$30,0))*(2050-2023)) -> 1.1799913 | E39: =INDEX($C$28:$C$30,MATCH($B39,$A$28:$A$30,0))+(INDEX($B$28:$B$30,MATCH($B39,$A$28:$A$30,0))-INDEX($C$28:$C$30,MATCH($B39,$A$28:$A$30,0)))*EXP(-INDEX($D$28:$D$30,MATCH($B39,$A$28:$A$30,0))*(2100-2023)) -> 1.0888648
A40: BeNeLux | B40: Developed | C40: =INDEX($C$28:$C$30,MATCH($B40,$A$28:$A$30,0))+(INDEX($B$28:$B$30,MATCH($B40,$A$28:$A$30,0))-INDEX($C$28:$C$30,MATCH($B40,$A$28:$A$30,0)))*EXP(-INDEX($D$28:$D$30,MATCH($B40,$A$28:$A$30,0))*(2023-2023)) -> 1.75 | D40: =INDEX($C$28:$C$30,MATCH($B40,$A$28:$A$30,0))+(INDEX($B$28:$B$30,MATCH($B40,$A$28:$A$30,0))-INDEX($C$28:$C$30,MATCH($B40,$A$28:$A$30,0)))*EXP(-INDEX($D$28:$D$30,MATCH($B40,$A$28:$A$30,0))*(2050-2023)) -> 1.3498569 | E40: =INDEX($C$28:$C$30,MATCH($B40,$A$28:$A$30,0))+(INDEX($B$28:$B$30,MATCH($B40,$A$28:$A$30,0))-INDEX($C$28:$C$30,MATCH($B40,$A$28:$A$30,0)))*EXP(-INDEX($D$28:$D$30,MATCH($B40,$A$28:$A$30,0))*(2100-2023)) -> 1.1980466
A41: Brazil | B41: Emerging | C41: =INDEX($C$28:$C$30,MATCH($B41,$A$28:$A$30,0))+(INDEX($B$28:$B$30,MATCH($B41,$A$28:$A$30,0))-INDEX($C$28:$C$30,MATCH($B41,$A$28:$A$30,0)))*EXP(-INDEX($D$28:$D$30,MATCH($B41,$A$28:$A$30,0))*(2023-2023)) -> 1.45 | D41: =INDEX($C$28:$C$30,MATCH($B41,$A$28:$A$30,0))+(INDEX($B$28:$B$30,MATCH($B41,$A$28:$A$30,0))-INDEX($C$28:$C$30,MATCH($B41,$A$28:$A$30,0)))*EXP(-INDEX($D$28:$D$30,MATCH($B41,$A$28:$A$30,0))*(2050-2023)) -> 1.1799913 | E41: =INDEX($C$28:$C$30,MATCH($B41,$A$28:$A$30,0))+(INDEX($B$28:$B$30,MATCH($B41,$A$28:$A$30,0))-INDEX($C$28:$C$30,MATCH($B41,$A$28:$A$30,0)))*EXP(-INDEX($D$28:$D$30,MATCH($B41,$A$28:$A$30,0))*(2100-2023)) -> 1.0888648
A42: China | B42: Frontier | C42: =INDEX($C$28:$C$30,MATCH($B42,$A$28:$A$30,0))+(INDEX($B$28:$B$30,MATCH($B42,$A$28:$A$30,0))-INDEX($C$28:$C$30,MATCH($B42,$A$28:$A$30,0)))*EXP(-INDEX($D$28:$D$30,MATCH($B42,$A$28:$A$30,0))*(2023-2023)) -> 1 | D42: =INDEX($C$28:$C$30,MATCH($B42,$A$28:$A$30,0))+(INDEX($B$28:$B$30,MATCH($B42,$A$28:$A$30,0))-INDEX($C$28:$C$30,MATCH($B42,$A$28:$A$30,0)))*EXP(-INDEX($D$28:$D$30,MATCH($B42,$A$28:$A$30,0))*(2050-2023)) -> 1 | E42: =INDEX($C$28:$C$30,MATCH($B42,$A$28:$A$30,0))+(INDEX($B$28:$B$30,MATCH($B42,$A$28:$A$30,0))-INDEX($C$28:$C$30,MATCH($B42,$A$28:$A$30,0)))*EXP(-INDEX($D$28:$D$30,MATCH($B42,$A$28:$A$30,0))*(2100-2023)) -> 1
A43: CroSloven | B43: Emerging | C43: =INDEX($C$28:$C$30,MATCH($B43,$A$28:$A$30,0))+(INDEX($B$28:$B$30,MATCH($B43,$A$28:$A$30,0))-INDEX($C$28:$C$30,MATCH($B43,$A$28:$A$30,0)))*EXP(-INDEX($D$28:$D$30,MATCH($B43,$A$28:$A$30,0))*(2023-2023)) -> 1.45 | D43: =INDEX($C$28:$C$30,MATCH($B43,$A$28:$A$30,0))+(INDEX($B$28:$B$30,MATCH($B43,$A$28:$A$30,0))-INDEX($C$28:$C$30,MATCH($B43,$A$28:$A$30,0)))*EXP(-INDEX($D$28:$D$30,MATCH($B43,$A$28:$A$30,0))*(2050-2023)) -> 1.1799913 | E43: =INDEX($C$28:$C$30,MATCH($B43,$A$28:$A$30,0))+(INDEX($B$28:$B$30,MATCH($B43,$A$28:$A$30,0))-INDEX($C$28:$C$30,MATCH($B43,$A$28:$A$30,0)))*EXP(-INDEX($D$28:$D$30,MATCH($B43,$A$28:$A$30,0))*(2100-2023)) -> 1.0888648
A44: CzechSlovak | B44: Emerging | C44: =INDEX($C$28:$C$30,MATCH($B44,$A$28:$A$30,0))+(INDEX($B$28:$B$30,MATCH($B44,$A$28:$A$30,0))-INDEX($C$28:$C$30,MATCH($B44,$A$28:$A$30,0)))*EXP(-INDEX($D$28:$D$30,MATCH($B44,$A$28:$A$30,0))*(2023-2023)) -> 1.45 | D44: =INDEX($C$28:$C$30,MATCH($B44,$A$28:$A$30,0))+(INDEX($B$28:$B$30,MATCH($B44,$A$28:$A$30,0))-INDEX($C$28:$C$30,MATCH($B44,$A$28:$A$30,0)))*EXP(-INDEX($D$28:$D$30,MATCH($B44,$A$28:$A$30,0))*(2050-2023)) -> 1.1799913 | E44: =INDEX($C$28:$C$30,MATCH($B44,$A$28:$A$30,0))+(INDEX($B$28:$B$30,MATCH($B44,$A$28:$A$30,0))-INDEX($C$28:$C$30,MATCH($B44,$A$28:$A$30,0)))*EXP(-INDEX($D$28:$D$30,MATCH($B44,$A$28:$A$30,0))*(2100-2023)) -> 1.0888648
A45: France | B45: Developed | C45: =INDEX($C$28:$C$30,MATCH($B45,$A$28:$A$30,0))+(INDEX($B$28:$B$30,MATCH($B45,$A$28:$A$30,0))-INDEX($C$28:$C$30,MATCH($B45,$A$28:$A$30,0)))*EXP(-INDEX($D$28:$D$30,MATCH($B45,$A$28:$A$30,0))*(2023-2023)) -> 1.75 | D45: =INDEX($C$28:$C$30,MATCH($B45,$A$28:$A$30,0))+(INDEX($B$28:$B$30,MATCH($B45,$A$28:$A$30,0))-INDEX($C$28:$C$30,MATCH($B45,$A$28:$A$30,0)))*EXP(-INDEX($D$28:$D$30,MATCH($B45,$A$28:$A$30,0))*(2050-2023)) -> 1.3498569 | E45: =INDEX($C$28:$C$30,MATCH($B45,$A$28:$A$30,0))+(INDEX($B$28:$B$30,MATCH($B45,$A$28:$A$30,0))-INDEX($C$28:$C$30,MATCH($B45,$A$28:$A$30,0)))*EXP(-INDEX($D$28:$D$30,MATCH($B45,$A$28:$A$30,0))*(2100-2023)) -> 1.1980466
A46: Germany | B46: Developed | C46: =INDEX($C$28:$C$30,MATCH($B46,$A$28:$A$30,0))+(INDEX($B$28:$B$30,MATCH($B46,$A$28:$A$30,0))-INDEX($C$28:$C$30,MATCH($B46,$A$28:$A$30,0)))*EXP(-INDEX($D$28:$D$30,MATCH($B46,$A$28:$A$30,0))*(2023-2023)) -> 1.75 | D46: =INDEX($C$28:$C$30,MATCH($B46,$A$28:$A$30,0))+(INDEX($B$28:$B$30,MATCH($B46,$A$28:$A$30,0))-INDEX($C$28:$C$30,MATCH($B46,$A$28:$A$30,0)))*EXP(-INDEX($D$28:$D$30,MATCH($B46,$A$28:$A$30,0))*(2050-2023)) -> 1.3498569 | E46: =INDEX($C$28:$C$30,MATCH($B46,$A$28:$A$30,0))+(INDEX($B$28:$B$30,MATCH($B46,$A$28:$A$30,0))-INDEX($C$28:$C$30,MATCH($B46,$A$28:$A$30,0)))*EXP(-INDEX($D$28:$D$30,MATCH($B46,$A$28:$A$30,0))*(2100-2023)) -> 1.1980466
... A49: Iceland | B49: Developed | C49: =INDEX($C$28:$C$30,MATCH($B49,$A$28:$A$30,0))+(INDEX($B$28:$B$30,MATCH($B49,$A$28:$A$30,0))-INDEX($C$28:$C$30,MATCH($B49,$A$28:$A$30,0)))*EXP(-INDEX($D$28:$D$30,MATCH($B49,$A$28:$A$30,0))*(2023-2023)) -> 1.75 | D49: =INDEX($C$28:$C$30,MATCH($B49,$A$28:$A$30,0))+(INDEX($B$28:$B$30,MATCH($B49,$A$28:$A$30,0))-INDEX($C$28:$C$30,MATCH($B49,$A$28:$A$30,0)))*EXP(-INDEX($D$28:$D$30,MATCH($B49,$A$28:$A$30,0))*(2050-2023)) -> 1.3498569 | E49: =INDEX($C$28:$C$30,MATCH($B49,$A$28:$A$30,0))+(INDEX($B$28:$B$30,MATCH($B49,$A$28:$A$30,0))-INDEX($C$28:$C$30,MATCH($B49,$A$28:$A$30,0)))*EXP(-INDEX($D$28:$D$30,MATCH($B49,$A$28:$A$30,0))*(2100-2023)) -> 1.1980466
A50: India | B50: Emerging | C50: 1.2 | D50: 1.1 | E50: 1.05
A51: Ireland | B51: Developed | C51: =INDEX($C$28:$C$30,MATCH($B51,$A$28:$A$30,0))+(INDEX($B$28:$B$30,MATCH($B51,$A$28:$A$30,0))-INDEX($C$28:$C$30,MATCH($B51,$A$28:$A$30,0)))*EXP(-INDEX($D$28:$D$30,MATCH($B51,$A$28:$A$30,0))*(2023-2023)) -> 1.75 | D51: =INDEX($C$28:$C$30,MATCH($B51,$A$28:$A$30,0))+(INDEX($B$28:$B$30,MATCH($B51,$A$28:$A$30,0))-INDEX($C$28:$C$30,MATCH($B51,$A$28:$A$30,0)))*EXP(-INDEX($D$28:$D$30,MATCH($B51,$A$28:$A$30,0))*(2050-2023)) -> 1.3498569 | E51: =INDEX($C$28:$C$30,MATCH($B51,$A$28:$A$30,0))+(INDEX($B$28:$B$30,MATCH($B51,$A$28:$A$30,0))-INDEX($C$28:$C$30,MATCH($B51,$A$28:$A$30,0)))*EXP(-INDEX($D$28:$D$30,MATCH($B51,$A$28:$A$30,0))*(2100-2023)) -> 1.1980466
A52: ItalyMal | B52: Developed | C52: =INDEX($C$28:$C$30,MATCH($B52,$A$28:$A$30,0))+(INDEX($B$28:$B$30,MATCH($B52,$A$28:$A$30,0))-INDEX($C$28:$C$30,MATCH($B52,$A$28:$A$30,0)))*EXP(-INDEX($D$28:$D$30,MATCH($B52,$A$28:$A$30,0))*(2023-2023)) -> 1.75 | D52: =INDEX($C$28:$C$30,MATCH($B52,$A$28:$A$30,0))+(INDEX($B$28:$B$30,MATCH($B52,$A$28:$A$30,0))-INDEX($C$28:$C$30,MATCH($B52,$A$28:$A$30,0)))*EXP(-INDEX($D$28:$D$30,MATCH($B52,$A$28:$A$30,0))*(2050-2023)) -> 1.3498569 | E52: =INDEX($C$28:$C$30,MATCH($B52,$A$28:$A$30,0))+(INDEX($B$28:$B$30,MATCH($B52,$A$28:$A$30,0))-INDEX($C$28:$C$30,MATCH($B52,$A$28:$A$30,0)))*EXP(-INDEX($D$28:$D$30,MATCH($B52,$A$28:$A$30,0))*(2100-2023)) -> 1.1980466
A53: Japan | B53: Developed | C53: 1.2 | D53: 1.1 | E53: 1.05
A54: LatAm | B54: Emerging | C54: =INDEX($C$28:$C$30,MATCH($B54,$A$28:$A$30,0))+(INDEX($B$28:$B$30,MATCH($B54,$A$28:$A$30,0))-INDEX($C$28:$C$30,MATCH($B54,$A$28:$A$30,0)))*EXP(-INDEX($D$28:$D$30,MATCH($B54,$A$28:$A$30,0))*(2023-2023)) -> 1.45 | D54: =INDEX($C$28:$C$30,MATCH($B54,$A$28:$A$30,0))+(INDEX($B$28:$B$30,MATCH($B54,$A$28:$A$30,0))-INDEX($C$28:$C$30,MATCH($B54,$A$28:$A$30,0)))*EXP(-INDEX($D$28:$D$30,MATCH($B54,$A$28:$A$30,0))*(2050-2023)) -> 1.1799913 | E54: =INDEX($C$28:$C$30,MATCH($B54,$A$28:$A$30,0))+(INDEX($B$28:$B$30,MATCH($B54,$A$28:$A$30,0))-INDEX($C$28:$C$30,MATCH($B54,$A$28:$A$30,0)))*EXP(-INDEX($D$28:$D$30,MATCH($B54,$A$28:$A$30,0))*(2100-2023)) -> 1.0888648
A55: MidEast | B55: Emerging | C55: =INDEX($C$28:$C$30,MATCH($B55,$A$28:$A$30,0))+(INDEX($B$28:$B$30,MATCH($B55,$A$28:$A$30,0))-INDEX($C$28:$C$30,MATCH($B55,$A$28:$A$30,0)))*EXP(-INDEX($D$28:$D$30,MATCH($B55,$A$28:$A$30,0))*(2023-2023)) -> 1.45 | D55: =INDEX($C$28:$C$30,MATCH($B55,$A$28:$A$30,0))+(INDEX($B$28:$B$30,MATCH($B55,$A$28:$A$30,0))-INDEX($C$28:$C$30,MATCH($B55,$A$28:$A$30,0)))*EXP(-INDEX($D$28:$D$30,MATCH($B55,$A$28:$A$30,0))*(2050-2023)) -> 1.1799913 | E55: =INDEX($C$28:$C$30,MATCH($B55,$A$28:$A$30,0))+(INDEX($B$28:$B$30,MATCH($B55,$A$28:$A$30,0))-INDEX($C$28:$C$30,MATCH($B55,$A$28:$A$30,0)))*EXP(-INDEX($D$28:$D$30,MATCH($B55,$A$28:$A$30,0))*(2100-2023)) -> 1.0888648
A56: NorthAm | B56: Developed, second tier | C56: 1.2 | D56: 1.1 | E56: 1.05
A57: Norway | B57: Developed | C57: =INDEX($C$28:$C$30,MATCH($B57,$A$28:$A$30,0))+(INDEX($B$28:$B$30,MATCH($B57,$A$28:$A$30,0))-INDEX($C$28:$C$30,MATCH($B57,$A$28:$A$30,0)))*EXP(-INDEX($D$28:$D$30,MATCH($B57,$A$28:$A$30,0))*(2023-2023)) -> 1.75 | D57: =INDEX($C$28:$C$30,MATCH($B57,$A$28:$A$30,0))+(INDEX($B$28:$B$30,MATCH($B57,$A$28:$A$30,0))-INDEX($C$28:$C$30,MATCH($B57,$A$28:$A$30,0)))*EXP(-INDEX($D$28:$D$30,MATCH($B57,$A$28:$A$30,0))*(2050-2023)) -> 1.3498569 | E57: =INDEX($C$28:$C$30,MATCH($B57,$A$28:$A$30,0))+(INDEX($B$28:$B$30,MATCH($B57,$A$28:$A$30,0))-INDEX($C$28:$C$30,MATCH($B57,$A$28:$A$30,0)))*EXP(-INDEX($D$28:$D$30,MATCH($B57,$A$28:$A$30,0))*(2100-2023)) -> 1.1980466
A58: Poland | B58: Emerging | C58: =INDEX($C$28:$C$30,MATCH($B58,$A$28:$A$30,0))+(INDEX($B$28:$B$30,MATCH($B58,$A$28:$A$30,0))-INDEX($C$28:$C$30,MATCH($B58,$A$28:$A$30,0)))*EXP(-INDEX($D$28:$D$30,MATCH($B58,$A$28:$A$30,0))*(2023-2023)) -> 1.45 | D58: =INDEX($C$28:$C$30,MATCH($B58,$A$28:$A$30,0))+(INDEX($B$28:$B$30,MATCH($B58,$A$28:$A$30,0))-INDEX($C$28:$C$30,MATCH($B58,$A$28:$A$30,0)))*EXP(-INDEX($D$28:$D$30,MATCH($B58,$A$28:$A$30,0))*(2050-2023)) -> 1.1799913 | E58: =INDEX($C$28:$C$30,MATCH($B58,$A$28:$A$30,0))+(INDEX($B$28:$B$30,MATCH($B58,$A$28:$A$30,0))-INDEX($C$28:$C$30,MATCH($B58,$A$28:$A$30,0)))*EXP(-INDEX($D$28:$D$30,MATCH($B58,$A$28:$A$30,0))*(2100-2023)) -> 1.0888648
A59: ROW | B59: Emerging | C59: =INDEX($C$28:$C$30,MATCH($B59,$A$28:$A$30,0))+(INDEX($B$28:$B$30,MATCH($B59,$A$28:$A$30,0))-INDEX($C$28:$C$30,MATCH($B59,$A$28:$A$30,0)))*EXP(-INDEX($D$28:$D$30,MATCH($B59,$A$28:$A$30,0))*(2023-2023)) -> 1.45 | D59: =INDEX($C$28:$C$30,MATCH($B59,$A$28:$A$30,0))+(INDEX($B$28:$B$30,MATCH($B59,$A$28:$A$30,0))-INDEX($C$28:$C$30,MATCH($B59,$A$28:$A$30,0)))*EXP(-INDEX($D$28:$D$30,MATCH($B59,$A$28:$A$30,0))*(2050-2023)) -> 1.1799913 | E59: =INDEX($C$28:$C$30,MATCH($B59,$A$28:$A$30,0))+(INDEX($B$28:$B$30,MATCH($B59,$A$28:$A$30,0))-INDEX($C$28:$C$30,MATCH($B59,$A$28:$A$30,0)))*EXP(-INDEX($D$28:$D$30,MATCH($B59,$A$28:$A$30,0))*(2100-2023)) -> 1.0888648
A60: Russia | B60: Emerging | C60: =INDEX($C$28:$C$30,MATCH($B60,$A$28:$A$30,0))+(INDEX($B$28:$B$30,MATCH($B60,$A$28:$A$30,0))-INDEX($C$28:$C$30,MATCH($B60,$A$28:$A$30,0)))*EXP(-INDEX($D$28:$D$30,MATCH($B60,$A$28:$A$30,0))*(2023-2023)) -> 1.45 | D60: =INDEX($C$28:$C$30,MATCH($B60,$A$28:$A$30,0))+(INDEX($B$28:$B$30,MATCH($B60,$A$28:$A$30,0))-INDEX($C$28:$C$30,MATCH($B60,$A$28:$A$30,0)))*EXP(-INDEX($D$28:$D$30,MATCH($B60,$A$28:$A$30,0))*(2050-2023)) -> 1.1799913 | E60: =INDEX($C$28:$C$30,MATCH($B60,$A$28:$A$30,0))+(INDEX($B$28:$B$30,MATCH($B60,$A$28:$A$30,0))-INDEX($C$28:$C$30,MATCH($B60,$A$28:$A$30,0)))*EXP(-INDEX($D$28:$D$30,MATCH($B60,$A$28:$A$30,0))*(2100-2023)) -> 1.0888648
A61: SaudiArabia | B61: Emerging | C61: =INDEX($C$28:$C$30,MATCH($B61,$A$28:$A$30,0))+(INDEX($B$28:$B$30,MATCH($B61,$A$28:$A$30,0))-INDEX($C$28:$C$30,MATCH($B61,$A$28:$A$30,0)))*EXP(-INDEX($D$28:$D$30,MATCH($B61,$A$28:$A$30,0))*(2023-2023)) -> 1.45 | D61: =INDEX($C$28:$C$30,MATCH($B61,$A$28:$A$30,0))+(INDEX($B$28:$B$30,MATCH($B61,$A$28:$A$30,0))-INDEX($C$28:$C$30,MATCH($B61,$A$28:$A$30,0)))*EXP(-INDEX($D$28:$D$30,MATCH($B61,$A$28:$A$30,0))*(2050-2023)) -> 1.1799913 | E61: =INDEX($C$28:$C$30,MATCH($B61,$A$28:$A$30,0))+(INDEX($B$28:$B$30,MATCH($B61,$A$28:$A$30,0))-INDEX($C$28:$C$30,MATCH($B61,$A$28:$A$30,0)))*EXP(-INDEX($D$28:$D$30,MATCH($B61,$A$28:$A$30,0))*(2100-2023)) -> 1.0888648
A62: SouthAfrica | B62: Emerging | C62: =INDEX($C$28:$C$30,MATCH($B62,$A$28:$A$30,0))+(INDEX($B$28:$B$30,MATCH($B62,$A$28:$A$30,0))-INDEX($C$28:$C$30,MATCH($B62,$A$28:$A$30,0)))*EXP(-INDEX($D$28:$D$30,MATCH($B62,$A$28:$A$30,0))*(2023-2023)) -> 1.45 | D62: =INDEX($C$28:$C$30,MATCH($B62,$A$28:$A$30,0))+(INDEX($B$28:$B$30,MATCH($B62,$A$28:$A$30,0))-INDEX($C$28:$C$30,MATCH($B62,$A$28:$A$30,0)))*EXP(-INDEX($D$28:$D$30,MATCH($B62,$A$28:$A$30,0))*(2050-2023)) -> 1.1799913 | E62: =INDEX($C$28:$C$30,MATCH($B62,$A$28:$A$30,0))+(INDEX($B$28:$B$30,MATCH($B62,$A$28:$A$30,0))-INDEX($C$28:$C$30,MATCH($B62,$A$28:$A$30,0)))*EXP(-INDEX($D$28:$D$30,MATCH($B62,$A$28:$A$30,0))*(2100-2023)) -> 1.0888648
A63: SpainPor | B63: Emerging | C63: =INDEX($C$28:$C$30,MATCH($B63,$A$28:$A$30,0))+(INDEX($B$28:$B$30,MATCH($B63,$A$28:$A$30,0))-INDEX($C$28:$C$30,MATCH($B63,$A$28:$A$30,0)))*EXP(-INDEX($D$28:$D$30,MATCH($B63,$A$28:$A$30,0))*(2023-2023)) -> 1.45 | D63: =INDEX($C$28:$C$30,MATCH($B63,$A$28:$A$30,0))+(INDEX($B$28:$B$30,MATCH($B63,$A$28:$A$30,0))-INDEX($C$28:$C$30,MATCH($B63,$A$28:$A$30,0)))*EXP(-INDEX($D$28:$D$30,MATCH($B63,$A$28:$A$30,0))*(2050-2023)) -> 1.1799913 | E63: =INDEX($C$28:$C$30,MATCH($B63,$A$28:$A$30,0))+(INDEX($B$28:$B$30,MATCH($B63,$A$28:$A$30,0))-INDEX($C$28:$C$30,MATCH($B63,$A$28:$A$30,0)))*EXP(-INDEX($D$28:$D$30,MATCH($B63,$A$28:$A$30,0))*(2100-2023)) -> 1.0888648
A64: SweFinDen | B64: Developed | C64: =INDEX($C$28:$C$30,MATCH($B64,$A$28:$A$30,0))+(INDEX($B$28:$B$30,MATCH($B64,$A$28:$A$30,0))-INDEX($C$28:$C$30,MATCH($B64,$A$28:$A$30,0)))*EXP(-INDEX($D$28:$D$30,MATCH($B64,$A$28:$A$30,0))*(2023-2023)) -> 1.75 | D64: =INDEX($C$28:$C$30,MATCH($B64,$A$28:$A$30,0))+(INDEX($B$28:$B$30,MATCH($B64,$A$28:$A$30,0))-INDEX($C$28:$C$30,MATCH($B64,$A$28:$A$30,0)))*EXP(-INDEX($D$28:$D$30,MATCH($B64,$A$28:$A$30,0))*(2050-2023)) -> 1.3498569 | E64: =INDEX($C$28:$C$30,MATCH($B64,$A$28:$A$30,0))+(INDEX($B$28:$B$30,MATCH($B64,$A$28:$A$30,0))-INDEX($C$28:$C$30,MATCH($B64,$A$28:$A$30,0)))*EXP(-INDEX($D$28:$D$30,MATCH($B64,$A$28:$A$30,0))*(2100-2023)) -> 1.1980466
A65: Switzerland | B65: Developed | C65: =INDEX($C$28:$C$30,MATCH($B65,$A$28:$A$30,0))+(INDEX($B$28:$B$30,MATCH($B65,$A$28:$A$30,0))-INDEX($C$28:$C$30,MATCH($B65,$A$28:$A$30,0)))*EXP(-INDEX($D$28:$D$30,MATCH($B65,$A$28:$A$30,0))*(2023-2023)) -> 1.75 | D65: =INDEX($C$28:$C$30,MATCH($B65,$A$28:$A$30,0))+(INDEX($B$28:$B$30,MATCH($B65,$A$28:$A$30,0))-INDEX($C$28:$C$30,MATCH($B65,$A$28:$A$30,0)))*EXP(-INDEX($D$28:$D$30,MATCH($B65,$A$28:$A$30,0))*(2050-2023)) -> 1.3498569 | E65: =INDEX($C$28:$C$30,MATCH($B65,$A$28:$A$30,0))+(INDEX($B$28:$B$30,MATCH($B65,$A$28:$A$30,0))-INDEX($C$28:$C$30,MATCH($B65,$A$28:$A$30,0)))*EXP(-INDEX($D$28:$D$30,MATCH($B65,$A$28:$A$30,0))*(2100-2023)) -> 1.1980466
A66: Turkey | B66: Emerging | C66: =INDEX($C$28:$C$30,MATCH($B66,$A$28:$A$30,0))+(INDEX($B$28:$B$30,MATCH($B66,$A$28:$A$30,0))-INDEX($C$28:$C$30,MATCH($B66,$A$28:$A$30,0)))*EXP(-INDEX($D$28:$D$30,MATCH($B66,$A$28:$A$30,0))*(2023-2023)) -> 1.45 | D66: =INDEX($C$28:$C$30,MATCH($B66,$A$28:$A$30,0))+(INDEX($B$28:$B$30,MATCH($B66,$A$28:$A$30,0))-INDEX($C$28:$C$30,MATCH($B66,$A$28:$A$30,0)))*EXP(-INDEX($D$28:$D$30,MATCH($B66,$A$28:$A$30,0))*(2050-2023)) -> 1.1799913 | E66: =INDEX($C$28:$C$30,MATCH($B66,$A$28:$A$30,0))+(INDEX($B$28:$B$30,MATCH($B66,$A$28:$A$30,0))-INDEX($C$28:$C$30,MATCH($B66,$A$28:$A$30,0)))*EXP(-INDEX($D$28:$D$30,MATCH($B66,$A$28:$A$30,0))*(2100-2023)) -> 1.0888648
A67: UK | B67: Developed | C67: =INDEX($C$28:$C$30,MATCH($B67,$A$28:$A$30,0))+(INDEX($B$28:$B$30,MATCH($B67,$A$28:$A$30,0))-INDEX($C$28:$C$30,MATCH($B67,$A$28:$A$30,0)))*EXP(-INDEX($D$28:$D$30,MATCH($B67,$A$28:$A$30,0))*(2023-2023)) -> 1.75 | D67: =INDEX($C$28:$C$30,MATCH($B67,$A$28:$A$30,0))+(INDEX($B$28:$B$30,MATCH($B67,$A$28:$A$30,0))-INDEX($C$28:$C$30,MATCH($B67,$A$28:$A$30,0)))*EXP(-INDEX($D$28:$D$30,MATCH($B67,$A$28:$A$30,0))*(2050-2023)) -> 1.3498569 | E67: =INDEX($C$28:$C$30,MATCH($B67,$A$28:$A$30,0))+(INDEX($B$28:$B$30,MATCH($B67,$A$28:$A$30,0))-INDEX($C$28:$C$30,MATCH($B67,$A$28:$A$30,0)))*EXP(-INDEX($D$28:$D$30,MATCH($B67,$A$28:$A$30,0))*(2100-2023)) -> 1.1980466
A68: Ukraine | B68: Emerging | C68: =INDEX($C$28:$C$30,MATCH($B68,$A$28:$A$30,0))+(INDEX($B$28:$B$30,MATCH($B68,$A$28:$A$30,0))-INDEX($C$28:$C$30,MATCH($B68,$A$28:$A$30,0)))*EXP(-INDEX($D$28:$D$30,MATCH($B68,$A$28:$A$30,0))*(2023-2023)) -> 1.45 | D68: =INDEX($C$28:$C$30,MATCH($B68,$A$28:$A$30,0))+(INDEX($B$28:$B$30,MATCH($B68,$A$28:$A$30,0))-INDEX($C$28:$C$30,MATCH($B68,$A$28:$A$30,0)))*EXP(-INDEX($D$28:$D$30,MATCH($B68,$A$28:$A$30,0))*(2050-2023)) -> 1.1799913 | E68: =INDEX($C$28:$C$30,MATCH($B68,$A$28:$A$30,0))+(INDEX($B$28:$B$30,MATCH($B68,$A$28:$A$30,0))-INDEX($C$28:$C$30,MATCH($B68,$A$28:$A$30,0)))*EXP(-INDEX($D$28:$D$30,MATCH($B68,$A$28:$A$30,0))*(2100-2023)) -> 1.0888648
A69: WestBalkans | B69: Emerging | C69: =INDEX($C$28:$C$30,MATCH($B69,$A$28:$A$30,0))+(INDEX($B$28:$B$30,MATCH($B69,$A$28:$A$30,0))-INDEX($C$28:$C$30,MATCH($B69,$A$28:$A$30,0)))*EXP(-INDEX($D$28:$D$30,MATCH($B69,$A$28:$A$30,0))*(2023-2023)) -> 1.45 | D69: =INDEX($C$28:$C$30,MATCH($B69,$A$28:$A$30,0))+(INDEX($B$28:$B$30,MATCH($B69,$A$28:$A$30,0))-INDEX($C$28:$C$30,MATCH($B69,$A$28:$A$30,0)))*EXP(-INDEX($D$28:$D$30,MATCH($B69,$A$28:$A$30,0))*(2050-2023)) -> 1.1799913 | E69: =INDEX($C$28:$C$30,MATCH($B69,$A$28:$A$30,0))+(INDEX($B$28:$B$30,MATCH($B69,$A$28:$A$30,0))-INDEX($C$28:$C$30,MATCH($B69,$A$28:$A$30,0)))*EXP(-INDEX($D$28:$D$30,MATCH($B69,$A$28:$A$30,0))*(2100-2023)) -> 1.0888648
A70: 5. INVCOST - RECYCLED ROUTE (paste each block into VEDA) | E70: same as virgin conversion cost)
A72: ~TFM_INS: attribute=INVCOST
A73: process | B73: year | C73: Africa_North | D73: Africa_Other | E73: Australia | F73: Austria | G73: Baltics | H73: BeNeLux | I73: Brazil | J73: China | K73: CroSloven | L73: CzechSlovak | M73: France | N73: Germany | O73: GreeceCyp | P73: HunRomBul | Q73: Iceland | R73: India | S73: Ireland | T73: ItalyMal | U73: Japan | V73: LatAm | W73: MidEast | X73: NorthAm | Y73: Norway | Z73: Poland | AA73: ROW | AB73: Russia | AC73: SaudiArabia | AD73: SouthAfrica | AE73: SpainPor | AF73: SweFinDen | AG73: Switzerland | AH73: Turkey | AI73: UK | AJ73: Ukraine | AK73: WestBalkans
A74: =A6 -> Tra_EV_Batt-LFP_fromrecy | B74: 2023 | C74: =C106 -> 80.455759 | D74: =D106 -> 80.455759 | E74: =E106 -> 97.101777 | F74: =F106 -> 97.101777 | G74: =G106 -> 80.455759 | H74: =H106 -> 97.101777 | I74: =I106 -> 80.455759 | J74: =J106 -> 55.48673 | ... AK74: =AK106 -> 80.455759
A75: =A7 -> Tra_EV_Batt-LMO_fromrecy | B75: 2023 | C75: =C107 -> 96.172192 | D75: =D107 -> 96.172192 | E75: =E107 -> 116.06989 | F75: =F107 -> 116.06989 | G75: =G107 -> 96.172192 | H75: =H107 -> 116.06989 | I75: =I107 -> 96.172192 | J75: =J107 -> 66.32565 | ... AK75: =AK107 -> 96.172192
A76: =A8 -> Tra_EV_Batt-NCA_fromrecy | B76: 2023 | C76: =C108 -> 81.347132 | D76: =D108 -> 81.347132 | E76: =E108 -> 98.177572 | F76: =F108 -> 98.177572 | G76: =G108 -> 81.347132 | H76: =H108 -> 98.177572 | I76: =I108 -> 81.347132 | J76: =J108 -> 56.10147 | ... AK76: =AK108 -> 81.347132
A77: =A9 -> Tra_EV_Batt-NMC111_fromrecy | B77: 2023 | C77: =C109 -> 80.56129 | D77: =D109 -> 80.56129 | E77: =E109 -> 97.229142 | F77: =F109 -> 97.229142 | G77: =G109 -> 80.56129 | H77: =H109 -> 97.229142 | I77: =I109 -> 80.56129 | J77: =J109 -> 55.55951 | ... AK77: =AK109 -> 80.56129
A78: =A10 -> Tra_EV_Batt-NMC532_fromrecy | B78: 2023 | C78: =C110 -> 86.083165 | D78: =D110 -> 86.083165 | E78: =E110 -> 103.89347 | F78: =F110 -> 103.89347 | G78: =G110 -> 86.083165 | H78: =H110 -> 103.89347 | I78: =I110 -> 86.083165 | J78: =J110 -> 59.3677 | ... AK78: =AK110 -> 86.083165
A79: =A11 -> Tra_EV_Batt-NMC622_fromrecy | B79: 2023 | C79: =C111 -> 83.139448 | D79: =D111 -> 83.139448 | E79: =E111 -> 100.34071 | F79: =F111 -> 100.34071 | G79: =G111 -> 83.139448 | H79: =H111 -> 100.34071 | I79: =I111 -> 83.139448 | J79: =J111 -> 57.33755 | ... AK79: =AK111 -> 83.139448
A80: =A12 -> Tra_EV_Batt-NMC811_fromrecy | B80: 2023 | C80: =C112 -> 86.984746 | D80: =D112 -> 86.984746 | E80: =E112 -> 104.98159 | F80: =F112 -> 104.98159 | G80: =G112 -> 86.984746 | H80: =H112 -> 104.98159 | I80: =I112 -> 86.984746 | J80: =J112 -> 59.98948 | ... AK80: =AK112 -> 86.984746
A82: ~TFM_INS: attribute=INVCOST
A83: process | B83: year | C83: Africa_North | D83: Africa_Other | E83: Australia | F83: Austria | G83: Baltics | H83: BeNeLux | I83: Brazil | J83: China | K83: CroSloven | L83: CzechSlovak | M83: France | N83: Germany | O83: GreeceCyp | P83: HunRomBul | Q83: Iceland | R83: India | S83: Ireland | T83: ItalyMal | U83: Japan | V83: LatAm | W83: MidEast | X83: NorthAm | Y83: Norway | Z83: Poland | AA83: ROW | AB83: Russia | AC83: SaudiArabia | AD83: SouthAfrica | AE83: SpainPor | AF83: SweFinDen | AG83: Switzerland | AH83: Turkey | AI83: UK | AJ83: Ukraine | AK83: WestBalkans
A84: =A6 -> Tra_EV_Batt-LFP_fromrecy | B84: 2050 | C84: =C116 -> 40.580133 | D84: =D116 -> 40.580133 | E84: =E116 -> 46.421846 | F84: =F116 -> 46.421846 | G84: =G116 -> 40.580133 | H84: =H116 -> 46.421846 | I84: =I116 -> 40.580133 | J84: =J116 -> 34.390197 | ... AK84: =AK116 -> 40.580133
A85: =A7 -> Tra_EV_Batt-LMO_fromrecy | B85: 2050 | C85: =C117 -> 48.50716 | D85: =D117 -> 48.50716 | E85: =E117 -> 55.490008 | F85: =F117 -> 55.490008 | G85: =G117 -> 48.50716 | H85: =H117 -> 55.490008 | I85: =I117 -> 48.50716 | J85: =J117 -> 41.108067 | ... AK85: =AK117 -> 48.50716
A86: =A8 -> Tra_EV_Batt-NCA_fromrecy | B86: 2050 | C86: =C118 -> 41.029722 | D86: =D118 -> 41.029722 | E86: =E118 -> 46.936155 | F86: =F118 -> 46.936155 | G86: =G118 -> 41.029722 | H86: =H118 -> 46.936155 | I86: =I118 -> 41.029722 | J86: =J118 -> 34.771208 | ... AK86: =AK118 -> 41.029722
A87: =A9 -> Tra_EV_Batt-NMC111_fromrecy | B87: 2050 | C87: =C119 -> 40.633361 | D87: =D119 -> 40.633361 | E87: =E119 -> 46.482735 | F87: =F119 -> 46.482735 | G87: =G119 -> 40.633361 | H87: =H119 -> 46.482735 | I87: =I119 -> 40.633361 | J87: =J119 -> 34.435306 | ... AK87: =AK119 -> 40.633361
A88: =A10 -> Tra_EV_Batt-NMC532_fromrecy | B88: 2050 | C88: =C120 -> 43.418474 | D88: =D120 -> 43.418474 | E88: =E120 -> 49.66878 | F88: =F120 -> 49.66878 | G88: =G120 -> 43.418474 | H88: =H120 -> 49.66878 | I88: =I120 -> 43.418474 | J88: =J120 -> 36.795589 | ... AK88: =AK120 -> 43.418474
A89: =A11 -> Tra_EV_Batt-NMC622_fromrecy | B89: 2050 | C89: =C121 -> 41.933727 | D89: =D121 -> 41.933727 | E89: =E121 -> 47.970296 | F89: =F121 -> 47.970296 | G89: =G121 -> 41.933727 | H89: =H121 -> 47.970296 | I89: =I121 -> 41.933727 | J89: =J121 -> 35.53732 | ... AK89: =AK121 -> 41.933727
A90: =A12 -> Tra_EV_Batt-NMC811_fromrecy | B90: 2050 | C90: =C122 -> 43.873212 | D90: =D122 -> 43.873212 | E90: =E122 -> 50.18898 | F90: =F122 -> 50.18898 | G90: =G122 -> 43.873212 | H90: =H122 -> 50.18898 | I90: =I122 -> 43.873212 | J90: =J122 -> 37.180963 | ... AK90: =AK122 -> 43.873212
A92: ~TFM_INS: attribute=INVCOST
A93: process | B93: year | C93: Africa_North | D93: Africa_Other | E93: Australia | F93: Austria | G93: Baltics | H93: BeNeLux | I93: Brazil | J93: China | K93: CroSloven | L93: CzechSlovak | M93: France | N93: Germany | O93: GreeceCyp | P93: HunRomBul | Q93: Iceland | R93: India | S93: Ireland | T93: ItalyMal | U93: Japan | V93: LatAm | W93: MidEast | X93: NorthAm | Y93: Norway | Z93: Poland | AA93: ROW | AB93: Russia | AC93: SaudiArabia | AD93: SouthAfrica | AE93: SpainPor | AF93: SweFinDen | AG93: Switzerland | AH93: Turkey | AI93: UK | AJ93: Ukraine | AK93: WestBalkans
A94: =A6 -> Tra_EV_Batt-LFP_fromrecy | B94: 2100 | C94: =C126 -> 28.804541 | D94: =D126 -> 28.804541 | E94: =E126 -> 31.692808 | F94: =F126 -> 31.692808 | G94: =G126 -> 28.804541 | H94: =H126 -> 31.692808 | I94: =I126 -> 28.804541 | J94: =J126 -> 26.453736 | ... AK94: =AK126 -> 28.804541
A95: =A7 -> Tra_EV_Batt-LMO_fromrecy | B95: 2100 | C95: =C127 -> 34.431294 | D95: =D127 -> 34.431294 | E95: =E127 -> 37.883763 | F95: =F127 -> 37.883763 | G95: =G127 -> 34.431294 | H95: =H127 -> 37.883763 | I95: =I127 -> 34.431294 | J95: =J127 -> 31.621277 | ... AK95: =AK127 -> 34.431294
A96: =A8 -> Tra_EV_Batt-NCA_fromrecy | B96: 2100 | C96: =C128 -> 29.123668 | D96: =D128 -> 29.123668 | E96: =E128 -> 32.043934 | F96: =F128 -> 32.043934 | G96: =G128 -> 29.123668 | H96: =H128 -> 32.043934 | I96: =I128 -> 29.123668 | J96: =J128 -> 26.746818 | ... AK96: =AK128 -> 29.123668
A97: =A9 -> Tra_EV_Batt-NMC111_fromrecy | B97: 2100 | C97: =C129 -> 28.842323 | D97: =D129 -> 28.842323 | E97: =E129 -> 31.734379 | F97: =F129 -> 31.734379 | G97: =G129 -> 28.842323 | H97: =H129 -> 31.734379 | I97: =I129 -> 28.842323 | J97: =J129 -> 26.488435 | ... AK97: =AK129 -> 28.842323
A98: =A10 -> Tra_EV_Batt-NMC532_fromrecy | B98: 2100 | C98: =C130 -> 30.819249 | D98: =D130 -> 30.819249 | E98: =E130 -> 33.909534 | F98: =F130 -> 33.909534 | G98: =G130 -> 30.819249 | H98: =H130 -> 33.909534 | I98: =I130 -> 30.819249 | J98: =J130 -> 28.304019 | ... AK98: =AK130 -> 30.819249
A99: =A11 -> Tra_EV_Batt-NMC622_fromrecy | B99: 2100 | C99: =C131 -> 29.765348 | D99: =D131 -> 29.765348 | E99: =E131 -> 32.749956 | F99: =F131 -> 32.749956 | G99: =G131 -> 29.765348 | H99: =H131 -> 32.749956 | I99: =I131 -> 29.765348 | J99: =J131 -> 27.336129 | ... AK99: =AK131 -> 29.765348
A100: =A12 -> Tra_EV_Batt-NMC811_fromrecy | B100: 2100 | C100: =C132 -> 31.14203 | D100: =D132 -> 31.14203 | E100: =E132 -> 34.264681 | F100: =F132 -> 34.264681 | G100: =G132 -> 31.14203 | H100: =H132 -> 34.264681 | I100: =I132 -> 31.14203 | J100: =J132 -> 28.600458 | ... AK100: =AK132 -> 31.14203
A102: 6. INVCOST - VIRGIN ROUTE (paste each block into VEDA)
A105: process | B105: year | C105: Africa_North | D105: Africa_Other | E105: Australia | F105: Austria | G105: Baltics | H105: BeNeLux | I105: Brazil | J105: China | K105: CroSloven | L105: CzechSlovak | M105: France | N105: Germany | O105: GreeceCyp | P105: HunRomBul | Q105: Iceland | R105: India | S105: Ireland | T105: ItalyMal | U105: Japan | V105: LatAm | W105: MidEast | X105: NorthAm | Y105: Norway | Z105: Poland | AA105: ROW | AB105: Russia | AC105: SaudiArabia | AD105: SouthAfrica | AE105: SpainPor | AF105: SweFinDen | AG105: Switzerland | AH105: Turkey | AI105: UK | AJ105: Ukraine | AK105: WestBalkans
A106: =B6 -> Tra_EV_Batt-LFP | B106: 2023 | C106: =$E$6*B$23*C$35 -> 80.455759 | D106: =$E$6*B$23*C$36 -> 80.455759 | E106: =$E$6*B$23*C$37 -> 97.101777 | F106: =$E$6*B$23*C$38 -> 97.101777 | G106: =$E$6*B$23*C$39 -> 80.455759 | H106: =$E$6*B$23*C$40 -> 97.101777 | I106: =$E$6*B$23*C$41 -> 80.455759 | J106: =$E$6*B$23*C$42 -> 55.48673 | K106: =$E$6*B$23*C$43 -> 80.455759 | L106: =$E$6*B$23*C$44 -> 80.455759 | M106: =$E$6*B$23*C$45 -> 97.101777 | N106: =$E$6*B$23*C$46 -> 97.101777 | O106: =$E$6*B$23*C$47 -> 80.455759 | P106: =$E$6*B$23*C$48 -> 80.455759 | Q106: =$E$6*B$23*C$49 -> 97.101777 | R106: =$E$6*B$23*C$50 -> 66.584076 | S106: =$E$6*B$23*C$51 -> 97.101777 | T106: =$E$6*B$23*C$52 -> 97.101777 | U106: =$E$6*B$23*C$53 -> 66.584076 | V106: =$E$6*B$23*C$54 -> 80.455759 | W106: =$E$6*B$23*C$55 -> 80.455759 | X106: =$E$6*B$23*C$56 -> 66.584076 | Y106: =$E$6*B$23*C$57 -> 97.101777 | Z106: =$E$6*B$23*C$58 -> 80.455759 | AA106: =$E$6*B$23*C$59 -> 80.455759 | AB106: =$E$6*B$23*C$60 -> 80.455759 | AC106: =$E$6*B$23*C$61 -> 80.455759 | AD106: =$E$6*B$23*C$62 -> 80.455759 | AE106: =$E$6*B$23*C$63 -> 80.455759 | AF106: =$E$6*B$23*C$64 -> 97.101777 | AG106: =$E$6*B$23*C$65 -> 97.101777 | AH106: =$E$6*B$23*C$66 -> 80.455759 | AI106: =$E$6*B$23*C$67 -> 97.101777 | AJ106: =$E$6*B$23*C$68 -> 80.455759 | AK106: =$E$6*B$23*C$69 -> 80.455759
A107: =B7 -> Tra_EV_Batt-LMO | B107: 2023 | C107: =$E$7*B$23*C$35 -> 96.172192 | D107: =$E$7*B$23*C$36 -> 96.172192 | E107: =$E$7*B$23*C$37 -> 116.06989 | F107: =$E$7*B$23*C$38 -> 116.06989 | G107: =$E$7*B$23*C$39 -> 96.172192 | H107: =$E$7*B$23*C$40 -> 116.06989 | I107: =$E$7*B$23*C$41 -> 96.172192 | J107: =$E$7*B$23*C$42 -> 66.32565 | K107: =$E$7*B$23*C$43 -> 96.172192 | L107: =$E$7*B$23*C$44 -> 96.172192 | M107: =$E$7*B$23*C$45 -> 116.06989 | N107: =$E$7*B$23*C$46 -> 116.06989 | O107: =$E$7*B$23*C$47 -> 96.172192 | P107: =$E$7*B$23*C$48 -> 96.172192 | Q107: =$E$7*B$23*C$49 -> 116.06989 | R107: =$E$7*B$23*C$50 -> 79.59078 | S107: =$E$7*B$23*C$51 -> 116.06989 | T107: =$E$7*B$23*C$52 -> 116.06989 | U107: =$E$7*B$23*C$53 -> 79.59078 | V107: =$E$7*B$23*C$54 -> 96.172192 | W107: =$E$7*B$23*C$55 -> 96.172192 | X107: =$E$7*B$23*C$56 -> 79.59078 | Y107: =$E$7*B$23*C$57 -> 116.06989 | Z107: =$E$7*B$23*C$58 -> 96.172192 | AA107: =$E$7*B$23*C$59 -> 96.172192 | AB107: =$E$7*B$23*C$60 -> 96.172192 | AC107: =$E$7*B$23*C$61 -> 96.172192 | AD107: =$E$7*B$23*C$62 -> 96.172192 | AE107: =$E$7*B$23*C$63 -> 96.172192 | AF107: =$E$7*B$23*C$64 -> 116.06989 | AG107: =$E$7*B$23*C$65 -> 116.06989 | AH107: =$E$7*B$23*C$66 -> 96.172192 | AI107: =$E$7*B$23*C$67 -> 116.06989 | AJ107: =$E$7*B$23*C$68 -> 96.172192 | AK107: =$E$7*B$23*C$69 -> 96.172192
A108: =B8 -> Tra_EV_Batt-NCA | B108: 2023 | C108: =$E$8*B$23*C$35 -> 81.347132 | D108: =$E$8*B$23*C$36 -> 81.347132 | E108: =$E$8*B$23*C$37 -> 98.177572 | F108: =$E$8*B$23*C$38 -> 98.177572 | G108: =$E$8*B$23*C$39 -> 81.347132 | H108: =$E$8*B$23*C$40 -> 98.177572 | I108: =$E$8*B$23*C$41 -> 81.347132 | J108: =$E$8*B$23*C$42 -> 56.10147 | K108: =$E$8*B$23*C$43 -> 81.347132 | L108: =$E$8*B$23*C$44 -> 81.347132 | M108: =$E$8*B$23*C$45 -> 98.177572 | N108: =$E$8*B$23*C$46 -> 98.177572 | O108: =$E$8*B$23*C$47 -> 81.347132 | P108: =$E$8*B$23*C$48 -> 81.347132 | Q108: =$E$8*B$23*C$49 -> 98.177572 | R108: =$E$8*B$23*C$50 -> 67.321764 | S108: =$E$8*B$23*C$51 -> 98.177572 | T108: =$E$8*B$23*C$52 -> 98.177572 | U108: =$E$8*B$23*C$53 -> 67.321764 | V108: =$E$8*B$23*C$54 -> 81.347132 | W108: =$E$8*B$23*C$55 -> 81.347132 | X108: =$E$8*B$23*C$56 -> 67.321764 | Y108: =$E$8*B$23*C$57 -> 98.177572 | Z108: =$E$8*B$23*C$58 -> 81.347132 | AA108: =$E$8*B$23*C$59 -> 81.347132 | AB108: =$E$8*B$23*C$60 -> 81.347132 | AC108: =$E$8*B$23*C$61 -> 81.347132 | AD108: =$E$8*B$23*C$62 -> 81.347132 | AE108: =$E$8*B$23*C$63 -> 81.347132 | AF108: =$E$8*B$23*C$64 -> 98.177572 | AG108: =$E$8*B$23*C$65 -> 98.177572 | AH108: =$E$8*B$23*C$66 -> 81.347132 | AI108: =$E$8*B$23*C$67 -> 98.177572 | AJ108: =$E$8*B$23*C$68 -> 81.347132 | AK108: =$E$8*B$23*C$69 -> 81.347132
A109: =B9 -> Tra_EV_Batt-NMC111 | B109: 2023 | C109: =$E$9*B$23*C$35 -> 80.56129 | D109: =$E$9*B$23*C$36 -> 80.56129 | E109: =$E$9*B$23*C$37 -> 97.229142 | F109: =$E$9*B$23*C$38 -> 97.229142 | G109: =$E$9*B$23*C$39 -> 80.56129 | H109: =$E$9*B$23*C$40 -> 97.229142 | I109: =$E$9*B$23*C$41 -> 80.56129 | J109: =$E$9*B$23*C$42 -> 55.55951 | K109: =$E$9*B$23*C$43 -> 80.56129 | L109: =$E$9*B$23*C$44 -> 80.56129 | M109: =$E$9*B$23*C$45 -> 97.229142 | N109: =$E$9*B$23*C$46 -> 97.229142 | O109: =$E$9*B$23*C$47 -> 80.56129 | P109: =$E$9*B$23*C$48 -> 80.56129 | Q109: =$E$9*B$23*C$49 -> 97.229142 | R109: =$E$9*B$23*C$50 -> 66.671412 | S109: =$E$9*B$23*C$51 -> 97.229142 | T109: =$E$9*B$23*C$52 -> 97.229142 | U109: =$E$9*B$23*C$53 -> 66.671412 | V109: =$E$9*B$23*C$54 -> 80.56129 | W109: =$E$9*B$23*C$55 -> 80.56129 | X109: =$E$9*B$23*C$56 -> 66.671412 | Y109: =$E$9*B$23*C$57 -> 97.229142 | Z109: =$E$9*B$23*C$58 -> 80.56129 | AA109: =$E$9*B$23*C$59 -> 80.56129 | AB109: =$E$9*B$23*C$60 -> 80.56129 | AC109: =$E$9*B$23*C$61 -> 80.56129 | AD109: =$E$9*B$23*C$62 -> 80.56129 | AE109: =$E$9*B$23*C$63 -> 80.56129 | AF109: =$E$9*B$23*C$64 -> 97.229142 | AG109: =$E$9*B$23*C$65 -> 97.229142 | AH109: =$E$9*B$23*C$66 -> 80.56129 | AI109: =$E$9*B$23*C$67 -> 97.229142 | AJ109: =$E$9*B$23*C$68 -> 80.56129 | AK109: =$E$9*B$23*C$69 -> 80.56129
A110: =B10 -> Tra_EV_Batt-NMC532 | B110: 2023 | C110: =$E$10*B$23*C$35 -> 86.083165 | D110: =$E$10*B$23*C$36 -> 86.083165 | E110: =$E$10*B$23*C$37 -> 103.89347 | F110: =$E$10*B$23*C$38 -> 103.89347 | G110: =$E$10*B$23*C$39 -> 86.083165 | H110: =$E$10*B$23*C$40 -> 103.89347 | I110: =$E$10*B$23*C$41 -> 86.083165 | J110: =$E$10*B$23*C$42 -> 59.3677 | K110: =$E$10*B$23*C$43 -> 86.083165 | L110: =$E$10*B$23*C$44 -> 86.083165 | M110: =$E$10*B$23*C$45 -> 103.89347 | N110: =$E$10*B$23*C$46 -> 103.89347 | O110: =$E$10*B$23*C$47 -> 86.083165 | P110: =$E$10*B$23*C$48 -> 86.083165 | Q110: =$E$10*B$23*C$49 -> 103.89347 | R110: =$E$10*B$23*C$50 -> 71.24124 | S110: =$E$10*B$23*C$51 -> 103.89347 | T110: =$E$10*B$23*C$52 -> 103.89347 | U110: =$E$10*B$23*C$53 -> 71.24124 | V110: =$E$10*B$23*C$54 -> 86.083165 | W110: =$E$10*B$23*C$55 -> 86.083165 | X110: =$E$10*B$23*C$56 -> 71.24124 | Y110: =$E$10*B$23*C$57 -> 103.89347 | Z110: =$E$10*B$23*C$58 -> 86.083165 | AA110: =$E$10*B$23*C$59 -> 86.083165 | AB110: =$E$10*B$23*C$60 -> 86.083165 | AC110: =$E$10*B$23*C$61 -> 86.083165 | AD110: =$E$10*B$23*C$62 -> 86.083165 | AE110: =$E$10*B$23*C$63 -> 86.083165 | AF110: =$E$10*B$23*C$64 -> 103.89347 | AG110: =$E$10*B$23*C$65 -> 103.89347 | AH110: =$E$10*B$23*C$66 -> 86.083165 | AI110: =$E$10*B$23*C$67 -> 103.89347 | AJ110: =$E$10*B$23*C$68 -> 86.083165 | AK110: =$E$10*B$23*C$69 -> 86.083165
A111: =B11 -> Tra_EV_Batt-NMC622 | B111: 2023 | C111: =$E$11*B$23*C$35 -> 83.139448 | D111: =$E$11*B$23*C$36 -> 83.139448 | E111: =$E$11*B$23*C$37 -> 100.34071 | F111: =$E$11*B$23*C$38 -> 100.34071 | G111: =$E$11*B$23*C$39 -> 83.139448 | H111: =$E$11*B$23*C$40 -> 100.34071 | I111: =$E$11*B$23*C$41 -> 83.139448 | J111: =$E$11*B$23*C$42 -> 57.33755 | K111: =$E$11*B$23*C$43 -> 83.139448 | L111: =$E$11*B$23*C$44 -> 83.139448 | M111: =$E$11*B$23*C$45 -> 100.34071 | N111: =$E$11*B$23*C$46 -> 100.34071 | O111: =$E$11*B$23*C$47 -> 83.139448 | P111: =$E$11*B$23*C$48 -> 83.139448 | Q111: =$E$11*B$23*C$49 -> 100.34071 | R111: =$E$11*B$23*C$50 -> 68.80506 | S111: =$E$11*B$23*C$51 -> 100.34071 | T111: =$E$11*B$23*C$52 -> 100.34071 | U111: =$E$11*B$23*C$53 -> 68.80506 | V111: =$E$11*B$23*C$54 -> 83.139448 | W111: =$E$11*B$23*C$55 -> 83.139448 | X111: =$E$11*B$23*C$56 -> 68.80506 | Y111: =$E$11*B$23*C$57 -> 100.34071 | Z111: =$E$11*B$23*C$58 -> 83.139448 | AA111: =$E$11*B$23*C$59 -> 83.139448 | AB111: =$E$11*B$23*C$60 -> 83.139448 | AC111: =$E$11*B$23*C$61 -> 83.139448 | AD111: =$E$11*B$23*C$62 -> 83.139448 | AE111: =$E$11*B$23*C$63 -> 83.139448 | AF111: =$E$11*B$23*C$64 -> 100.34071 | AG111: =$E$11*B$23*C$65 -> 100.34071 | AH111: =$E$11*B$23*C$66 -> 83.139448 | AI111: =$E$11*B$23*C$67 -> 100.34071 | AJ111: =$E$11*B$23*C$68 -> 83.139448 | AK111: =$E$11*B$23*C$69 -> 83.139448
A112: =B12 -> Tra_EV_Batt-NMC811 | B112: 2023 | C112: =$E$12*B$23*C$35 -> 86.984746 | D112: =$E$12*B$23*C$36 -> 86.984746 | E112: =$E$12*B$23*C$37 -> 104.98159 | F112: =$E$12*B$23*C$38 -> 104.98159 | G112: =$E$12*B$23*C$39 -> 86.984746 | H112: =$E$12*B$23*C$40 -> 104.98159 | I112: =$E$12*B$23*C$41 -> 86.984746 | J112: =$E$12*B$23*C$42 -> 59.98948 | K112: =$E$12*B$23*C$43 -> 86.984746 | L112: =$E$12*B$23*C$44 -> 86.984746 | M112: =$E$12*B$23*C$45 -> 104.98159 | N112: =$E$12*B$23*C$46 -> 104.98159 | O112: =$E$12*B$23*C$47 -> 86.984746 | P112: =$E$12*B$23*C$48 -> 86.984746 | Q112: =$E$12*B$23*C$49 -> 104.98159 | R112: =$E$12*B$23*C$50 -> 71.987376 | S112: =$E$12*B$23*C$51 -> 104.98159 | T112: =$E$12*B$23*C$52 -> 104.98159 | U112: =$E$12*B$23*C$53 -> 71.987376 | V112: =$E$12*B$23*C$54 -> 86.984746 | W112: =$E$12*B$23*C$55 -> 86.984746 | X112: =$E$12*B$23*C$56 -> 71.987376 | Y112: =$E$12*B$23*C$57 -> 104.98159 | Z112: =$E$12*B$23*C$58 -> 86.984746 | AA112: =$E$12*B$23*C$59 -> 86.984746 | AB112: =$E$12*B$23*C$60 -> 86.984746 | AC112: =$E$12*B$23*C$61 -> 86.984746 | AD112: =$E$12*B$23*C$62 -> 86.984746 | AE112: =$E$12*B$23*C$63 -> 86.984746 | AF112: =$E$12*B$23*C$64 -> 104.98159 | AG112: =$E$12*B$23*C$65 -> 104.98159 | AH112: =$E$12*B$23*C$66 -> 86.984746 | AI112: =$E$12*B$23*C$67 -> 104.98159 | AJ112: =$E$12*B$23*C$68 -> 86.984746 | AK112: =$E$12*B$23*C$69 -> 86.984746
A113: na | C113: =C106 -> 80.455759 | D113: =D106 -> 80.455759 | E113: =E106 -> 97.101777 | F113: =F106 -> 97.101777 | G113: =G106 -> 80.455759 | H113: =H106 -> 97.101777 | I113: =I106 -> 80.455759 | J113: =J106 -> 55.48673 | ... AK113: =AK106 -> 80.455759
...

Sheet Road transport
B2: ~TFM_FILL-R:w=RoadTra_BY; hcol=region | K2: ~TFM_TOPINS | P2: TFM_TOPINS
B3: Scenario | C3: Attribute | D3: PSET_CO | E3: AllRegions | K3: process | L3: IO | M3: commodity | P3: pset_ci | Q3: pset_co | R3: cset_cn | S3: IO
B4: BASE | C4: AF | D4: Trd[_]* | E4: *1 | K4: Trd[_]*gsl* | L4: IN | M4: TRAGSL,TRABGS | P4: TRAELC | Q4: TRDELC | R4: ELC | S4: Out
B5: BASE | C5: EFF | D5: Trd[_]* | E5: *1 | K5: Trd[_]*dsl* | L5: IN | M5: TRADST,TRABDS
K6: Trd[_]*hh2* | L6: IN | M6: TRAGH2
K7: Trd[_]*cng* | L7: IN | M7: TRANGA
B8: ~TFM_INS | K8: Trd[_]*elc* | L8: IN | M8: TRDELC
B9: attribute | C9: PSET_PN | D9: PSET_CI | E9: CSET_CN | F9: value | G9: limtype | H9: year | K9: Trd[_]*lng* | L9: IN | M9: TRANGA
B10: Share | C10: Trd[_]*-pih* | E10: TRDELC | F10: 0.25 | G10: FX | K10: Trd[_]*-pih* | L10: IN | M10: TRDELC
B11: Share | C11: Trd[_]*-pih* | E11: TRDELC | F11: 3 | G11: FX | H11: 0
B12: LIFE | C12: Trd[_]* | F12: 15 | K12: ~TFM_MIG
B13: *START | C13: Trd[_]* | E13: -TRDELC | F13: 2019 | K13: attribute | L13: value | M13: attribute2 | N13: pset_pn
K14: INVCOST | L14: *.03 | M14: FIXOM | N14: Trd[_]*
B15: CEFF | D15: TRAGSL | E15: TRABGS | F15: 0.93 | K15: INVCOST | L15: *.02 | M15: FIXOM | N15: Trd[_]*elc*
B16: ~TFM_INS-TS: attribute=FLO_MARK
B18: pset_ci | C18: 2019 | D18: 0 | E18: attrib_cond | F18: commodity | G18: top_check
B19: -TRDELC | C19: 0.2 | D19: 3 | E19: -FLO_MARK | F19: Trd[_]* | G19: OUT
C21: ~TFM_INS
C22: attribute | D22: =IF(RoadTra_BY!L$1="","\I:",RoadTra_BY!L$1) -> Africa_North | E22: =IF(RoadTra_BY!M$1="","\I:",RoadTra_BY!M$1) -> Africa_Other | F22: =IF(RoadTra_BY!N$1="","\I:",RoadTra_BY!N$1) -> Australia | G22: =IF(RoadTra_BY!O$1="","\I:",RoadTra_BY!O$1) -> Austria | H22: =IF(RoadTra_BY!P$1="","\I:",RoadTra_BY!P$1) -> Baltics | I22: =IF(RoadTra_BY!Q$1="","\I:",RoadTra_BY!Q$1) -> BeNeLux | J22: =IF(RoadTra_BY!R$1="","\I:",RoadTra_BY!R$1) -> Brazil | K22: =IF(RoadTra_BY!S$1="","\I:",RoadTra_BY!S$1) -> China | ... AW22: =IF(RoadTra_BY!BE$1="","\I:",RoadTra_BY!BE$1) -> \I: | AX22: process
C23: AF | D23: =AVERAGEIFS(RoadTra_BY!L$2:L$999,RoadTra_BY!$B$2:$B$999,'Road transport'!$C23,RoadTra_BY!$C$2:$C$999,'Road transport'!$AX23) -> 7 | E23: =AVERAGEIFS(RoadTra_BY!M$2:M$999,RoadTra_BY!$B$2:$B$999,'Road transport'!$C23,RoadTra_BY!$C$2:$C$999,'Road transport'!$AX23) -> 7 | F23: =AVERAGEIFS(RoadTra_BY!N$2:N$999,RoadTra_BY!$B$2:$B$999,'Road transport'!$C23,RoadTra_BY!$C$2:$C$999,'Road transport'!$AX23) -> 7 | G23: =AVERAGEIFS(RoadTra_BY!O$2:O$999,RoadTra_BY!$B$2:$B$999,'Road transport'!$C23,RoadTra_BY!$C$2:$C$999,'Road transport'!$AX23) -> 7 | H23: =AVERAGEIFS(RoadTra_BY!P$2:P$999,RoadTra_BY!$B$2:$B$999,'Road transport'!$C23,RoadTra_BY!$C$2:$C$999,'Road transport'!$AX23) -> 7 | I23: =AVERAGEIFS(RoadTra_BY!Q$2:Q$999,RoadTra_BY!$B$2:$B$999,'Road transport'!$C23,RoadTra_BY!$C$2:$C$999,'Road transport'!$AX23) -> 7 | J23: =AVERAGEIFS(RoadTra_BY!R$2:R$999,RoadTra_BY!$B$2:$B$999,'Road transport'!$C23,RoadTra_BY!$C$2:$C$999,'Road transport'!$AX23) -> 7 | K23: =AVERAGEIFS(RoadTra_BY!S$2:S$999,RoadTra_BY!$B$2:$B$999,'Road transport'!$C23,RoadTra_BY!$C$2:$C$999,'Road transport'!$AX23) -> 7 | ... AW23: =AVERAGEIFS(RoadTra_BY!BE$2:BE$999,RoadTra_BY!$B$2:$B$999,'Road transport'!$C23,RoadTra_BY!$C$2:$C$999,'Road transport'!$AX23) -> #DIV/0! | AX23: Trd_2w_*
C24: AF | D24: =AVERAGEIFS(RoadTra_BY!L$2:L$999,RoadTra_BY!$B$2:$B$999,'Road transport'!$C24,RoadTra_BY!$C$2:$C$999,'Road transport'!$AX24) -> 15 | E24: =AVERAGEIFS(RoadTra_BY!M$2:M$999,RoadTra_BY!$B$2:$B$999,'Road transport'!$C24,RoadTra_BY!$C$2:$C$999,'Road transport'!$AX24) -> 15 | F24: =AVERAGEIFS(RoadTra_BY!N$2:N$999,RoadTra_BY!$B$2:$B$999,'Road transport'!$C24,RoadTra_BY!$C$2:$C$999,'Road transport'!$AX24) -> 15 | G24: =AVERAGEIFS(RoadTra_BY!O$2:O$999,RoadTra_BY!$B$2:$B$999,'Road transport'!$C24,RoadTra_BY!$C$2:$C$999,'Road transport'!$AX24) -> 15 | H24: =AVERAGEIFS(RoadTra_BY!P$2:P$999,RoadTra_BY!$B$2:$B$999,'Road transport'!$C24,RoadTra_BY!$C$2:$C$999,'Road transport'!$AX24) -> 15 | I24: =AVERAGEIFS(RoadTra_BY!Q$2:Q$999,RoadTra_BY!$B$2:$B$999,'Road transport'!$C24,RoadTra_BY!$C$2:$C$999,'Road transport'!$AX24) -> 15 | J24: =AVERAGEIFS(RoadTra_BY!R$2:R$999,RoadTra_BY!$B$2:$B$999,'Road transport'!$C24,RoadTra_BY!$C$2:$C$999,'Road transport'!$AX24) -> 15 | K24: =AVERAGEIFS(RoadTra_BY!S$2:S$999,RoadTra_BY!$B$2:$B$999,'Road transport'!$C24,RoadTra_BY!$C$2:$C$999,'Road transport'!$AX24) -> 15 | ... AW24: =AVERAGEIFS(RoadTra_BY!BE$2:BE$999,RoadTra_BY!$B$2:$B$999,'Road transport'!$C24,RoadTra_BY!$C$2:$C$999,'Road transport'!$AX24) -> #DIV/0! | AX24: Trd_3w_*
C25: AF | D25: =AVERAGEIFS(RoadTra_BY!L$2:L$999,RoadTra_BY!$B$2:$B$999,'Road transport'!$C25,RoadTra_BY!$C$2:$C$999,'Road transport'!$AX25) -> 35 | E25: =AVERAGEIFS(RoadTra_BY!M$2:M$999,RoadTra_BY!$B$2:$B$999,'Road transport'!$C25,RoadTra_BY!$C$2:$C$999,'Road transport'!$AX25) -> 35 | F25: =AVERAGEIFS(RoadTra_BY!N$2:N$999,RoadTra_BY!$B$2:$B$999,'Road transport'!$C25,RoadTra_BY!$C$2:$C$999,'Road transport'!$AX25) -> 35 | G25: =AVERAGEIFS(RoadTra_BY!O$2:O$999,RoadTra_BY!$B$2:$B$999,'Road transport'!$C25,RoadTra_BY!$C$2:$C$999,'Road transport'!$AX25) -> 35 | H25: =AVERAGEIFS(RoadTra_BY!P$2:P$999,RoadTra_BY!$B$2:$B$999,'Road transport'!$C25,RoadTra_BY!$C$2:$C$999,'Road transport'!$AX25) -> 35 | I25: =AVERAGEIFS(RoadTra_BY!Q$2:Q$999,RoadTra_BY!$B$2:$B$999,'Road transport'!$C25,RoadTra_BY!$C$2:$C$999,'Road transport'!$AX25) -> 35 | J25: =AVERAGEIFS(RoadTra_BY!R$2:R$999,RoadTra_BY!$B$2:$B$999,'Road transport'!$C25,RoadTra_BY!$C$2:$C$999,'Road transport'!$AX25) -> 35 | K25: =AVERAGEIFS(RoadTra_BY!S$2:S$999,RoadTra_BY!$B$2:$B$999,'Road transport'!$C25,RoadTra_BY!$C$2:$C$999,'Road transport'!$AX25) -> 35 | ... AW25: =AVERAGEIFS(RoadTra_BY!BE$2:BE$999,RoadTra_BY!$B$2:$B$999,'Road transport'!$C25,RoadTra_BY!$C$2:$C$999,'Road transport'!$AX25) -> #DIV/0! | AX25: Trd_bus*
C26: AF | D26: =AVERAGEIFS(RoadTra_BY!L$2:L$999,RoadTra_BY!$B$2:$B$999,'Road transport'!$C26,RoadTra_BY!$C$2:$C$999,'Road transport'!$AX26) -> 12 | E26: =AVERAGEIFS(RoadTra_BY!M$2:M$999,RoadTra_BY!$B$2:$B$999,'Road transport'!$C26,RoadTra_BY!$C$2:$C$999,'Road transport'!$AX26) -> 12 | F26: =AVERAGEIFS(RoadTra_BY!N$2:N$999,RoadTra_BY!$B$2:$B$999,'Road transport'!$C26,RoadTra_BY!$C$2:$C$999,'Road transport'!$AX26) -> 12 | G26: =AVERAGEIFS(RoadTra_BY!O$2:O$999,RoadTra_BY!$B$2:$B$999,'Road transport'!$C26,RoadTra_BY!$C$2:$C$999,'Road transport'!$AX26) -> 12 | H26: =AVERAGEIFS(RoadTra_BY!P$2:P$999,RoadTra_BY!$B$2:$B$999,'Road transport'!$C26,RoadTra_BY!$C$2:$C$999,'Road transport'!$AX26) -> 12 | I26: =AVERAGEIFS(RoadTra_BY!Q$2:Q$999,RoadTra_BY!$B$2:$B$999,'Road transport'!$C26,RoadTra_BY!$C$2:$C$999,'Road transport'!$AX26) -> 12 | J26: =AVERAGEIFS(RoadTra_BY!R$2:R$999,RoadTra_BY!$B$2:$B$999,'Road transport'!$C26,RoadTra_BY!$C$2:$C$999,'Road transport'!$AX26) -> 12 | K26: =AVERAGEIFS(RoadTra_BY!S$2:S$999,RoadTra_BY!$B$2:$B$999,'Road transport'!$C26,RoadTra_BY!$C$2:$C$999,'Road transport'!$AX26) -> 8 | ... AW26: =AVERAGEIFS(RoadTra_BY!BE$2:BE$999,RoadTra_BY!$B$2:$B$999,'Road transport'!$C26,RoadTra_BY!$C$2:$C$999,'Road transport'!$AX26) -> #DIV/0! | AX26: Trd_car*
C27: AF | D27: =AVERAGEIFS(RoadTra_BY!L$2:L$999,RoadTra_BY!$B$2:$B$999,'Road transport'!$C27,RoadTra_BY!$C$2:$C$999,'Road transport'!$AX27) -> 100 | E27: =AVERAGEIFS(RoadTra_BY!M$2:M$999,RoadTra_BY!$B$2:$B$999,'Road transport'!$C27,RoadTra_BY!$C$2:$C$999,'Road transport'!$AX27) -> 100 | F27: =AVERAGEIFS(RoadTra_BY!N$2:N$999,RoadTra_BY!$B$2:$B$999,'Road transport'!$C27,RoadTra_BY!$C$2:$C$999,'Road transport'!$AX27) -> 100 | G27: =AVERAGEIFS(RoadTra_BY!O$2:O$999,RoadTra_BY!$B$2:$B$999,'Road transport'!$C27,RoadTra_BY!$C$2:$C$999,'Road transport'!$AX27) -> 100 | H27: =AVERAGEIFS(RoadTra_BY!P$2:P$999,RoadTra_BY!$B$2:$B$999,'Road transport'!$C27,RoadTra_BY!$C$2:$C$999,'Road transport'!$AX27) -> 100 | I27: =AVERAGEIFS(RoadTra_BY!Q$2:Q$999,RoadTra_BY!$B$2:$B$999,'Road transport'!$C27,RoadTra_BY!$C$2:$C$999,'Road transport'!$AX27) -> 100 | J27: =AVERAGEIFS(RoadTra_BY!R$2:R$999,RoadTra_BY!$B$2:$B$999,'Road transport'!$C27,RoadTra_BY!$C$2:$C$999,'Road transport'!$AX27) -> 100 | K27: =AVERAGEIFS(RoadTra_BY!S$2:S$999,RoadTra_BY!$B$2:$B$999,'Road transport'!$C27,RoadTra_BY!$C$2:$C$999,'Road transport'!$AX27) -> 100 | ... AW27: =AVERAGEIFS(RoadTra_BY!BE$2:BE$999,RoadTra_BY!$B$2:$B$999,'Road transport'!$C27,RoadTra_BY!$C$2:$C$999,'Road transport'!$AX27) -> #DIV/0! | AX27: Trd_hdt*
C28: AF | D28: =AVERAGEIFS(RoadTra_BY!L$2:L$999,RoadTra_BY!$B$2:$B$999,'Road transport'!$C28,RoadTra_BY!$C$2:$C$999,'Road transport'!$AX28) -> 40 | E28: =AVERAGEIFS(RoadTra_BY!M$2:M$999,RoadTra_BY!$B$2:$B$999,'Road transport'!$C28,RoadTra_BY!$C$2:$C$999,'Road transport'!$AX28) -> 40 | F28: =AVERAGEIFS(RoadTra_BY!N$2:N$999,RoadTra_BY!$B$2:$B$999,'Road transport'!$C28,RoadTra_BY!$C$2:$C$999,'Road transport'!$AX28) -> 40 | G28: =AVERAGEIFS(RoadTra_BY!O$2:O$999,RoadTra_BY!$B$2:$B$999,'Road transport'!$C28,RoadTra_BY!$C$2:$C$999,'Road transport'!$AX28) -> 40 | H28: =AVERAGEIFS(RoadTra_BY!P$2:P$999,RoadTra_BY!$B$2:$B$999,'Road transport'!$C28,RoadTra_BY!$C$2:$C$999,'Road transport'!$AX28) -> 40 | I28: =AVERAGEIFS(RoadTra_BY!Q$2:Q$999,RoadTra_BY!$B$2:$B$999,'Road transport'!$C28,RoadTra_BY!$C$2:$C$999,'Road transport'!$AX28) -> 40 | J28: =AVERAGEIFS(RoadTra_BY!R$2:R$999,RoadTra_BY!$B$2:$B$999,'Road transport'!$C28,RoadTra_BY!$C$2:$C$999,'Road transport'!$AX28) -> 40 | K28: =AVERAGEIFS(RoadTra_BY!S$2:S$999,RoadTra_BY!$B$2:$B$999,'Road transport'!$C28,RoadTra_BY!$C$2:$C$999,'Road transport'!$AX28) -> 40 | ... AW28: =AVERAGEIFS(RoadTra_BY!BE$2:BE$999,RoadTra_BY!$B$2:$B$999,'Road transport'!$C28,RoadTra_BY!$C$2:$C$999,'Road transport'!$AX28) -> #DIV/0! | AX28: Trd_lcv*
C31: ~TFM_UPD
C32: attribute | D32: =IF(RoadTra_BY!L$1="","\I:",RoadTra_BY!L$1) -> Africa_North | E32: =IF(RoadTra_BY!M$1="","\I:",RoadTra_BY!M$1) -> Africa_Other | F32: =IF(RoadTra_BY!N$1="","\I:",RoadTra_BY!N$1) -> Australia | G32: =IF(RoadTra_BY!O$1="","\I:",RoadTra_BY!O$1) -> Austria | H32: =IF(RoadTra_BY!P$1="","\I:",RoadTra_BY!P$1) -> Baltics | I32: =IF(RoadTra_BY!Q$1="","\I:",RoadTra_BY!Q$1) -> BeNeLux | J32: =IF(RoadTra_BY!R$1="","\I:",RoadTra_BY!R$1) -> Brazil | K32: =IF(RoadTra_BY!S$1="","\I:",RoadTra_BY!S$1) -> China | ... AW32: =IF(RoadTra_BY!BE$1="","\I:",RoadTra_BY!BE$1) -> \I: | AX32: process
C33: EFF | D33: ="*"&ROUND(SUMIFS(RoadTra_BY!L$2:L$79,RoadTra_BY!$B$2:$B$79,'Road transport'!$C33,RoadTra_BY!$C$2:$C$79,'Road transport'!$BA33),3) -> *0.99 | E33: ="*"&ROUND(SUMIFS(RoadTra_BY!M$2:M$79,RoadTra_BY!$B$2:$B$79,'Road transport'!$C33,RoadTra_BY!$C$2:$C$79,'Road transport'!$BA33),3) -> *0.99 | F33: ="*"&ROUND(SUMIFS(RoadTra_BY!N$2:N$79,RoadTra_BY!$B$2:$B$79,'Road transport'!$C33,RoadTra_BY!$C$2:$C$79,'Road transport'!$BA33),3) -> *0.99 | G33: ="*"&ROUND(SUMIFS(RoadTra_BY!O$2:O$79,RoadTra_BY!$B$2:$B$79,'Road transport'!$C33,RoadTra_BY!$C$2:$C$79,'Road transport'!$BA33),3) -> *0.99 | H33: ="*"&ROUND(SUMIFS(RoadTra_BY!P$2:P$79,RoadTra_BY!$B$2:$B$79,'Road transport'!$C33,RoadTra_BY!$C$2:$C$79,'Road transport'!$BA33),3) -> *0.99 | I33: ="*"&ROUND(SUMIFS(RoadTra_BY!Q$2:Q$79,RoadTra_BY!$B$2:$B$79,'Road transport'!$C33,RoadTra_BY!$C$2:$C$79,'Road transport'!$BA33),3) -> *0.99 | J33: ="*"&ROUND(SUMIFS(RoadTra_BY!R$2:R$79,RoadTra_BY!$B$2:$B$79,'Road transport'!$C33,RoadTra_BY!$C$2:$C$79,'Road transport'!$BA33),3) -> *0.99 | K33: ="*"&ROUND(SUMIFS(RoadTra_BY!S$2:S$79,RoadTra_BY!$B$2:$B$79,'Road transport'!$C33,RoadTra_BY!$C$2:$C$79,'Road transport'!$BA33),3) -> *0.99 | ... AW33: ="*"&ROUND(SUMIFS(RoadTra_BY!BE$2:BE$79,RoadTra_BY!$B$2:$B$79,'Road transport'!$C33,RoadTra_BY!$C$2:$C$79,'Road transport'!$BA33),3) -> *0 | AX33: =SUBSTITUTE(SUBSTITUTE(BA33,"gsl",""),"dsl","")&"*" -> Trd_2w_* | AZ33: =IFERROR(IF(FIND("gsl",BA33)>0,1,0),2) -> 1 | BA33: Trd_2w_gsl
C34: EFF | D34: ="*"&ROUND(SUMIFS(RoadTra_BY!L$2:L$79,RoadTra_BY!$B$2:$B$79,'Road transport'!$C34,RoadTra_BY!$C$2:$C$79,'Road transport'!$BA34),3) -> *0.587 | E34: ="*"&ROUND(SUMIFS(RoadTra_BY!M$2:M$79,RoadTra_BY!$B$2:$B$79,'Road transport'!$C34,RoadTra_BY!$C$2:$C$79,'Road transport'!$BA34),3) -> *0.587 | F34: ="*"&ROUND(SUMIFS(RoadTra_BY!N$2:N$79,RoadTra_BY!$B$2:$B$79,'Road transport'!$C34,RoadTra_BY!$C$2:$C$79,'Road transport'!$BA34),3) -> *0.587 | G34: ="*"&ROUND(SUMIFS(RoadTra_BY!O$2:O$79,RoadTra_BY!$B$2:$B$79,'Road transport'!$C34,RoadTra_BY!$C$2:$C$79,'Road transport'!$BA34),3) -> *0.587 | H34: ="*"&ROUND(SUMIFS(RoadTra_BY!P$2:P$79,RoadTra_BY!$B$2:$B$79,'Road transport'!$C34,RoadTra_BY!$C$2:$C$79,'Road transport'!$BA34),3) -> *0.587 | I34: ="*"&ROUND(SUMIFS(RoadTra_BY!Q$2:Q$79,RoadTra_BY!$B$2:$B$79,'Road transport'!$C34,RoadTra_BY!$C$2:$C$79,'Road transport'!$BA34),3) -> *0.587 | J34: ="*"&ROUND(SUMIFS(RoadTra_BY!R$2:R$79,RoadTra_BY!$B$2:$B$79,'Road transport'!$C34,RoadTra_BY!$C$2:$C$79,'Road transport'!$BA34),3) -> *0.587 | K34: ="*"&ROUND(SUMIFS(RoadTra_BY!S$2:S$79,RoadTra_BY!$B$2:$B$79,'Road transport'!$C34,RoadTra_BY!$C$2:$C$79,'Road transport'!$BA34),3) -> *0.587 | ... AW34: ="*"&ROUND(SUMIFS(RoadTra_BY!BE$2:BE$79,RoadTra_BY!$B$2:$B$79,'Road transport'!$C34,RoadTra_BY!$C$2:$C$79,'Road transport'!$BA34),3) -> *0 | AX34: =SUBSTITUTE(SUBSTITUTE(BA34,"gsl",""),"dsl","")&"*" -> Trd_3w_* | AZ34: =IFERROR(IF(FIND("gsl",BA34)>0,1,0),2) -> 1 | BA34: Trd_3w_gsl
C35: EFF | D35: ="*"&ROUND(SUMIFS(RoadTra_BY!L$2:L$79,RoadTra_BY!$B$2:$B$79,'Road transport'!$C35,RoadTra_BY!$C$2:$C$79,'Road transport'!$BA35),3) -> *0.072 | E35: ="*"&ROUND(SUMIFS(RoadTra_BY!M$2:M$79,RoadTra_BY!$B$2:$B$79,'Road transport'!$C35,RoadTra_BY!$C$2:$C$79,'Road transport'!$BA35),3) -> *0.072 | F35: ="*"&ROUND(SUMIFS(RoadTra_BY!N$2:N$79,RoadTra_BY!$B$2:$B$79,'Road transport'!$C35,RoadTra_BY!$C$2:$C$79,'Road transport'!$BA35),3) -> *0.072 | G35: ="*"&ROUND(SUMIFS(RoadTra_BY!O$2:O$79,RoadTra_BY!$B$2:$B$79,'Road transport'!$C35,RoadTra_BY!$C$2:$C$79,'Road transport'!$BA35),3) -> *0.072 | H35: ="*"&ROUND(SUMIFS(RoadTra_BY!P$2:P$79,RoadTra_BY!$B$2:$B$79,'Road transport'!$C35,RoadTra_BY!$C$2:$C$79,'Road transport'!$BA35),3) -> *0.072 | I35: ="*"&ROUND(SUMIFS(RoadTra_BY!Q$2:Q$79,RoadTra_BY!$B$2:$B$79,'Road transport'!$C35,RoadTra_BY!$C$2:$C$79,'Road transport'!$BA35),3) -> *0.072 | J35: ="*"&ROUND(SUMIFS(RoadTra_BY!R$2:R$79,RoadTra_BY!$B$2:$B$79,'Road transport'!$C35,RoadTra_BY!$C$2:$C$79,'Road transport'!$BA35),3) -> *0.072 | K35: ="*"&ROUND(SUMIFS(RoadTra_BY!S$2:S$79,RoadTra_BY!$B$2:$B$79,'Road transport'!$C35,RoadTra_BY!$C$2:$C$79,'Road transport'!$BA35),3) -> *0.072 | ... AW35: ="*"&ROUND(SUMIFS(RoadTra_BY!BE$2:BE$79,RoadTra_BY!$B$2:$B$79,'Road transport'!$C35,RoadTra_BY!$C$2:$C$79,'Road transport'!$BA35),3) -> *0 | AX35: =SUBSTITUTE(SUBSTITUTE(BA35,"gsl",""),"dsl","")&"*" -> Trd_bus_* | AZ35: =IFERROR(IF(FIND("gsl",BA35)>0,1,0),2) -> 2 | BA35: Trd_bus_dsl
C36: EFF | D36: ="*"&ROUND(SUMIFS(RoadTra_BY!L$2:L$79,RoadTra_BY!$B$2:$B$79,'Road transport'!$C36,RoadTra_BY!$C$2:$C$79,'Road transport'!$BA36),3) -> *0.466 | E36: ="*"&ROUND(SUMIFS(RoadTra_BY!M$2:M$79,RoadTra_BY!$B$2:$B$79,'Road transport'!$C36,RoadTra_BY!$C$2:$C$79,'Road transport'!$BA36),3) -> *0.466 | F36: ="*"&ROUND(SUMIFS(RoadTra_BY!N$2:N$79,RoadTra_BY!$B$2:$B$79,'Road transport'!$C36,RoadTra_BY!$C$2:$C$79,'Road transport'!$BA36),3) -> *0.466 | G36: ="*"&ROUND(SUMIFS(RoadTra_BY!O$2:O$79,RoadTra_BY!$B$2:$B$79,'Road transport'!$C36,RoadTra_BY!$C$2:$C$79,'Road transport'!$BA36),3) -> *0.466 | H36: ="*"&ROUND(SUMIFS(RoadTra_BY!P$2:P$79,RoadTra_BY!$B$2:$B$79,'Road transport'!$C36,RoadTra_BY!$C$2:$C$79,'Road transport'!$BA36),3) -> *0.466 | I36: ="*"&ROUND(SUMIFS(RoadTra_BY!Q$2:Q$79,RoadTra_BY!$B$2:$B$79,'Road transport'!$C36,RoadTra_BY!$C$2:$C$79,'Road transport'!$BA36),3) -> *0.466 | J36: ="*"&ROUND(SUMIFS(RoadTra_BY!R$2:R$79,RoadTra_BY!$B$2:$B$79,'Road transport'!$C36,RoadTra_BY!$C$2:$C$79,'Road transport'!$BA36),3) -> *0.466 | K36: ="*"&ROUND(SUMIFS(RoadTra_BY!S$2:S$79,RoadTra_BY!$B$2:$B$79,'Road transport'!$C36,RoadTra_BY!$C$2:$C$79,'Road transport'!$BA36),3) -> *0.466 | ... AW36: ="*"&ROUND(SUMIFS(RoadTra_BY!BE$2:BE$79,RoadTra_BY!$B$2:$B$79,'Road transport'!$C36,RoadTra_BY!$C$2:$C$79,'Road transport'!$BA36),3) -> *0 | AX36: =SUBSTITUTE(SUBSTITUTE(BA36,"gsl",""),"dsl","")&"*" -> Trd_car_* | AZ36: =IFERROR(IF(FIND("gsl",BA36)>0,1,0),2) -> 1 | BA36: Trd_car_gsl
C37: EFF | D37: ="*"&ROUND(SUMIFS(RoadTra_BY!L$2:L$79,RoadTra_BY!$B$2:$B$79,'Road transport'!$C37,RoadTra_BY!$C$2:$C$79,'Road transport'!$BA37),3) -> *0.139 | E37: ="*"&ROUND(SUMIFS(RoadTra_BY!M$2:M$79,RoadTra_BY!$B$2:$B$79,'Road transport'!$C37,RoadTra_BY!$C$2:$C$79,'Road transport'!$BA37),3) -> *0.139 | F37: ="*"&ROUND(SUMIFS(RoadTra_BY!N$2:N$79,RoadTra_BY!$B$2:$B$79,'Road transport'!$C37,RoadTra_BY!$C$2:$C$79,'Road transport'!$BA37),3) -> *0.139 | G37: ="*"&ROUND(SUMIFS(RoadTra_BY!O$2:O$79,RoadTra_BY!$B$2:$B$79,'Road transport'!$C37,RoadTra_BY!$C$2:$C$79,'Road transport'!$BA37),3) -> *0.139 | H37: ="*"&ROUND(SUMIFS(RoadTra_BY!P$2:P$79,RoadTra_BY!$B$2:$B$79,'Road transport'!$C37,RoadTra_BY!$C$2:$C$79,'Road transport'!$BA37),3) -> *0.139 | I37: ="*"&ROUND(SUMIFS(RoadTra_BY!Q$2:Q$79,RoadTra_BY!$B$2:$B$79,'Road transport'!$C37,RoadTra_BY!$C$2:$C$79,'Road transport'!$BA37),3) -> *0.139 | J37: ="*"&ROUND(SUMIFS(RoadTra_BY!R$2:R$79,RoadTra_BY!$B$2:$B$79,'Road transport'!$C37,RoadTra_BY!$C$2:$C$79,'Road transport'!$BA37),3) -> *0.139 | K37: ="*"&ROUND(SUMIFS(RoadTra_BY!S$2:S$79,RoadTra_BY!$B$2:$B$79,'Road transport'!$C37,RoadTra_BY!$C$2:$C$79,'Road transport'!$BA37),3) -> *0.139 | ... AW37: ="*"&ROUND(SUMIFS(RoadTra_BY!BE$2:BE$79,RoadTra_BY!$B$2:$B$79,'Road transport'!$C37,RoadTra_BY!$C$2:$C$79,'Road transport'!$BA37),3) -> *0 | AX37: =SUBSTITUTE(SUBSTITUTE(BA37,"gsl",""),"dsl","")&"*" -> Trd_hdt_* | AZ37: =IFERROR(IF(FIND("gsl",BA37)>0,1,0),2) -> 2 | BA37: Trd_hdt_dsl
C38: EFF | D38: ="*"&ROUND(SUMIFS(RoadTra_BY!L$2:L$79,RoadTra_BY!$B$2:$B$79,'Road transport'!$C38,RoadTra_BY!$C$2:$C$79,'Road transport'!$BA38),3) -> *0.38 | E38: ="*"&ROUND(SUMIFS(RoadTra_BY!M$2:M$79,RoadTra_BY!$B$2:$B$79,'Road transport'!$C38,RoadTra_BY!$C$2:$C$79,'Road transport'!$BA38),3) -> *0.38 | F38: ="*"&ROUND(SUMIFS(RoadTra_BY!N$2:N$79,RoadTra_BY!$B$2:$B$79,'Road transport'!$C38,RoadTra_BY!$C$2:$C$79,'Road transport'!$BA38),3) -> *0.38 | G38: ="*"&ROUND(SUMIFS(RoadTra_BY!O$2:O$79,RoadTra_BY!$B$2:$B$79,'Road transport'!$C38,RoadTra_BY!$C$2:$C$79,'Road transport'!$BA38),3) -> *0.38 | H38: ="*"&ROUND(SUMIFS(RoadTra_BY!P$2:P$79,RoadTra_BY!$B$2:$B$79,'Road transport'!$C38,RoadTra_BY!$C$2:$C$79,'Road transport'!$BA38),3) -> *0.38 | I38: ="*"&ROUND(SUMIFS(RoadTra_BY!Q$2:Q$79,RoadTra_BY!$B$2:$B$79,'Road transport'!$C38,RoadTra_BY!$C$2:$C$79,'Road transport'!$BA38),3) -> *0.38 | J38: ="*"&ROUND(SUMIFS(RoadTra_BY!R$2:R$79,RoadTra_BY!$B$2:$B$79,'Road transport'!$C38,RoadTra_BY!$C$2:$C$79,'Road transport'!$BA38),3) -> *0.38 | K38: ="*"&ROUND(SUMIFS(RoadTra_BY!S$2:S$79,RoadTra_BY!$B$2:$B$79,'Road transport'!$C38,RoadTra_BY!$C$2:$C$79,'Road transport'!$BA38),3) -> *0.38 | ... AW38: ="*"&ROUND(SUMIFS(RoadTra_BY!BE$2:BE$79,RoadTra_BY!$B$2:$B$79,'Road transport'!$C38,RoadTra_BY!$C$2:$C$79,'Road transport'!$BA38),3) -> *0 | AX38: =SUBSTITUTE(SUBSTITUTE(BA38,"gsl",""),"dsl","")&"*" -> Trd_lcv_* | AZ38: =IFERROR(IF(FIND("gsl",BA38)>0,1,0),2) -> 2 | BA38: Trd_lcv_dsl
B48: ~TFM_UPD
B49: attribute | C49: value | D49: pset_ci | E49: pset_co | I49: tempering the Eff improvement in smaller Evs
B50: EFF | C50: *.5 | D50: TRDELC | E50: Trd_2w,Trd_3w
B53: ~TFM_INS
B54: attribute | C54: value | D54: pset_set | E54: attrib_cond | F54: cset_cn | G54: other_indexes | H54: pset_co | I54: pset_pn
B55: INVCOST | C55: 10 | D55: ELE | E55: -INVCOST | I55: -Util_Rep_Batt*
B56: FLO_FUNC | C56: 1 | F56: AuxStoIN | G56: TRAELC | H56: =F56 -> AuxStoIN | I56: Tra*
CX63: ~TFM_INS
A64: *This original table seems too far from USGS evidence
A66: year | B66: attribute | C66: limtype | D66: process | E66: cset_cn | F66: Africa_North | G66: Africa_Other | H66: Australia | I66: Austria | J66: Baltics | K66: BeNeLux | L66: Brazil | M66: China | N66: CroSloven | O66: CzechSlovak | P66: France | Q66: Germany | R66: GreeceCyp | S66: HunRomBul | T66: Iceland | U66: India | V66: Ireland | W66: ItalyMal | X66: Japan | Y66: LatAm | Z66: MidEast | AA66: NorthAm | AB66: Norway | AC66: Poland | AD66: ROW | AE66: Russia | AF66: SaudiArabia | AG66: SouthAfrica | AH66: SpainPor | AI66: SweFinDen | AJ66: Switzerland | AK66: Turkey | AL66: UK | AM66: Ukraine | AN66: WestBalkans | AO66: Pset_CO | CW66: attribute | CX66: limtype | CY66: process | CZ66: cset_cn | DA66: year | DB66: AllRegions
A67: 2019, 2024 | B67: FLO_BND | C67: UP | D67: MINBatMaterials_LI | E67: m_lithium | F67: =D77/1000 -> 0 | G67: =E77/1000 -> 310 | H67: =F77/1000 -> 6200 | I67: =G77/1000 -> 0 | J67: =H77/1000 -> 0 | K67: =I77/1000 -> 0 | L67: =J77/1000 -> 250 | M67: 2000 | N67: =L77/1000 -> 0 | O67: =M77/1000 -> 0 | P67: =N77/1000 -> 0 | Q67: =O77/1000 -> 0 | R67: =P77/1000 -> 0 | S67: =Q77/1000 -> 0 | T67: =R77/1000 -> 0 | U67: =S77/1000 -> 0 | ... AM67: =AK77/1000 -> 0 | AN67: 0 | AO67: =E67 -> m_lithium | CW67: FLO_BND | CX67: UP | CY67: =D67 -> MINBatMaterials_LI | CZ67: m_lithium | DA67: 0 | DB67: 1
A68: 2019, 2024 | B68: FLO_BND | C68: UP | D68: MINBatMaterials_NI | E68: m_nickel | F68: =D78/1000 -> 0 | G68: =E78/1000 -> 0 | H68: =F78/1000 -> 21000 | I68: =G78/1000 -> 0 | J68: =H78/1000 -> 0 | K68: =I78/1000 -> 0 | L68: =J78/1000 -> 16000 | M68: =K78/1000 -> 2100 | ... AM68: =AK78/1000 -> 0 | AN68: 0 | AO68: =E68 -> m_nickel | CW68: FLO_BND | CX68: UP | CY68: =D68 -> MINBatMaterials_NI | CZ68: m_nickel | DA68: 0 | DB68: 1
A69: 2019, 2024 | B69: FLO_BND | C69: UP | D69: MINBatMaterials_COB | E69: m_cobalt | F69: 0 | G69: =E79/10000 -> 410 | H69: =F79/10000 -> 150 | I69: =G79/10000 -> 0 | J69: =H79/10000 -> 0 | K69: =I79/10000 -> 0 | L69: =J79/10000 -> 0 | M69: =K79/10000 -> 14 | N69: =L79/10000 -> 0 | ... AM69: =AK79/10000 -> 0 | AN69: 0 | AO69: =E69 -> m_cobalt | CW69: FLO_BND | CX69: UP | CY69: MINBatMaterials_COB_direct | CZ69: m_cobalt | DA69: 0 | DB69: 1
A70: 2019, 2024 | B70: FLO_BND | C70: UP | D70: MINBatMaterials_MN | E70: m_manganese | F70: =D80/1000 -> 0 | G70: =E80/1000 -> 74000 | H70: =F80/1000 -> 270000 | I70: =G80/1000 -> 0 | J70: =H80/1000 -> 0 | K70: =I80/1000 -> 0 | L70: =J80/1000 -> 270000 | M70: =K80/1000 -> 280000 | ... Z70: =X80/1000 -> 0 | AA70: 100 | AB70: =Z80/1000 -> 0 | AC70: =AA80/1000 -> 0 | AD70: =AB80/1000 -> 5000 | AE70: =AC80/1000 -> 0 | AF70: =AD80/1000 -> 0 | AG70: =AE80/1000 -> 640000 | AH70: =AF80/1000 -> 0 | AI70: =AG80/1000 -> 0 | ... AM70: =AK80/1000 -> 140000 | AN70: 0 | AO70: =E70 -> m_manganese | CW70: FLO_BND | CX70: UP | CY70: =D70 -> MINBatMaterials_MN | CZ70: m_manganese | DA70: 0 | DB70: 1
A71: 2019, 2024 | B71: FLO_BND | C71: UP | D71: MINBatMaterials_AL | E71: m_aluminum | F71: =D81/1000 -> 0 | G71: =E81/1000 -> 0 | H71: =F81/1000 -> 0 | I71: =G81/1000 -> 0 | J71: =H81/1000 -> 0 | K71: =I81/1000 -> 0 | L71: =J81/1000 -> 0 | M71: 41500 | N71: =L81/1000 -> 0 | O71: =M81/1000 -> 0 | P71: =N81/1000 -> 0 | Q71: =O81/1000 -> 0 | R71: =P81/1000 -> 0 | S71: =Q81/1000 -> 0 | T71: =R81/1000 -> 0 | U71: =S81/1000 -> 0 | ... Z71: =X81/1000 -> 0 | AA71: 3650 | AB71: =Z81/1000 -> 0 | AC71: =AA81/1000 -> 0 | AD71: =AB81/1000 -> 0 | AE71: =AC81/1000 -> 0 | AF71: =AD81/1000 -> 0 | AG71: =AE81/1000 -> 0 | AH71: =AF81/1000 -> 0 | AI71: =AG81/1000 -> 0 | ... AM71: =AK81/1000 -> 0 | AN71: 0 | AO71: =E71 -> m_aluminum | CW71: FLO_BND | CX71: UP | CY71: =D71 -> MINBatMaterials_AL | CZ71: m_aluminum | DA71: 0 | DB71: 1
A72: 2019, 2024 | B72: FLO_BND | C72: UP | D72: MINBatMaterials_COP | E72: m_copper | F72: =D82/1000 -> 0 | G72: =E82/1000 -> 50000 | H72: =F82/1000 -> 97000 | I72: =G82/1000 -> 0 | J72: =H82/1000 -> 0 | K72: =I82/1000 -> 0 | L72: =J82/1000 -> 0 | M72: =K82/1000 -> 27000 | ... AM72: =AK82/1000 -> 0 | AN72: 0 | AO72: =E72 -> m_copper | CW72: FLO_BND | CX72: UP | CY72: =D72 -> MINBatMaterials_COP | CZ72: m_copper | DA72: 0 | DB72: 1
A73: 2019, 2024 | B73: FLO_BND | C73: UP | D73: MINBatMaterials_GR | E73: m_graphite | F73: =D83/1000 -> 0 | G73: =E83/1000 -> 69000 | H73: =F83/1000 -> 0 | I73: =G83/1000 -> 0 | J73: =H83/1000 -> 0 | K73: =I83/1000 -> 0 | L73: =J83/1000 -> 74000 | M73: =K83/1000 -> 52000 | ... AM73: =AK83/1000 -> 0 | AN73: 0 | AO73: =E73 -> m_graphite | CW73: FLO_BND | CX73: UP | CY73: =D73 -> MINBatMaterials_GR | CZ73: m_graphite | DA73: 0 | DB73: 1
E75: ktonne
B77: *According to BloomBerg that ~2.5times more demand in 2024 vs. 2017 [means that 2.5 times higher demand every seven years] [https://about.bnef.com/blog/lithium-ion-battery-pack-prices-see-largest-drop-since-2017-falling-to-115-per-kilowatt-hour-bloombergnef/]; and a 18% learning rate also from Bloomberg | D77: 0 | E77: 310000 | F77: 6200000 | G77: 0 | J77: 250000 | K77: 2000000 | M77: 0 | N77: 0 | O77: 0 | P77: 0 | S77: 0 | V77: 0 | W77: 12250000 | X77: 0 | Y77: 1930000 | Z77: 0 | AA77: 0 | AB77: 3300000 | AC77: 0 | AD77: 0 | AE77: 0 | AF77: 60000 | AG77: 0 | AI77: 0 | AJ77: 0 | AK77: 0
D78: 0 | E78: 0 | F78: 21000000 | G78: 0 | J78: 16000000 | K78: 2100000 | M78: 0 | N78: 0 | O78: 0 | P78: 0 | S78: 0 | V78: 0 | W78: 16000000 | X78: 0 | Y78: 2570000 | Z78: 0 | AA78: 0 | AB78: 52900000 | AC78: 7500000 | AD78: 0 | AE78: 0 | AF78: 0 | AG78: 0 | AI78: 0 | AJ78: 0 | AK78: 0
D79: 13000 | E79: 4100000 | F79: 1500000 | G79: 0 | J79: 0 | K79: 140000 | M79: 0 | N79: 0 | O79: 0 | P79: 0 | S79: 0 | V79: 0 | W79: 500000 | X79: 36000 | Y79: 289000 | Z79: 0 | AA79: 0 | AB79: 1517000 | AC79: 250000 | AD79: 0 | AE79: 0 | AF79: 0 | AG79: 0 | AI79: 36000 | AJ79: 0 | AK79: 0
D80: 0 | E80: 74000000 | F80: 270000000 | G80: 0 | J80: 270000000 | K80: 280000000 | M80: 0 | N80: 0 | O80: 0 | P80: 0 | S80: 34000000 | V80: 0 | W80: 275000000 | X80: 0 | Y80: 0 | Z80: 0 | AA80: 0 | AB80: 5000000 | AC80: 0 | AD80: 0 | AE80: 640000000 | AF80: 0 | AG80: 0 | AI80: 0 | AJ80: 0 | AK80: 140000000
Y81: 0
D82: 0 | E82: 50000000 | F82: 97000000 | G82: 0 | J82: 0 | K82: 27000000 | M82: 0 | N82: 0 | O82: 0 | P82: 0 | S82: 0 | V82: 0 | W82: 324000000 | X82: 0 | Y82: 51600000 | Z82: 0 | AA82: 30000000 | AB82: 244000000 | AC82: 62000000 | AD82: 0 | AE82: 0 | AF82: 0 | AG82: 0 | AI82: 0 | AJ82: 0 | AK82: 0
D83: 0 | E83: 69000000 | F83: 0 | G83: 0 | J83: 74000000 | K83: 52000000 | M83: 0 | N83: 0 | O83: 0 | P83: 0 | S83: 8000000 | V83: 0 | W83: 77100000 | X83: 90000000 | Y83: 5700000 | Z83: 600000 | AA83: 0 | AB83: 12900000 | AC83: 14000000 | AD83: 0 | AE83: 0 | AF83: 0 | AG83: 0 | AI83: 90000000 | AJ83: 0 | AK83: 0
B85: ~TFM_INS | AW85: *From USGS, 2024 annual mining
A87: year | B87: attribute | C87: limtype | D87: process | E87: cset_cn | F87: Africa_North | G87: Africa_Other | H87: Australia | I87: Austria | J87: Baltics | K87: BeNeLux | L87: Brazil | M87: China | N87: CroSloven | O87: CzechSlovak | P87: France | Q87: Germany | R87: GreeceCyp | S87: HunRomBul | T87: Iceland | U87: India | V87: Ireland | W87: ItalyMal | X87: Japan | Y87: LatAm | Z87: MidEast | AA87: NorthAm | AB87: Norway | AC87: Poland | AD87: ROW | AE87: Russia | AF87: SaudiArabia | AG87: SouthAfrica | AH87: SpainPor | AI87: SweFinDen | AJ87: Switzerland | AK87: Turkey | AL87: UK | AM87: Ukraine | AN87: WestBalkans | AO87: Pset_CO | AW87: Region | AX87: Likt/yr | AY87: Cokt/yr | AZ87: Nikt/yr | BA87: Mnkt/yr | BB87: Cukt/yr | BC87: Alkt/yr | BD87: Graphitekt/yr | BH87: Region | BI87: Li | BJ87: Ni | BK87: Co | BL87: Mn | BM87: Al | BN87: Cu | BO87: Graphite | BQ87: Region | BR87: Africa_North | BS87: Africa_Other | BT87: Australia | BU87: Austria | BV87: Baltics | BW87: BeNeLux | BX87: Brazil | BY87: China | BZ87: CroSloven | CA87: CzechSlovak | CB87: France | CC87: Germany | CD87: GreeceCyp | CE87: HunRomBul | CF87: Iceland | CG87: India | CH87: Ireland | CI87: ItalyMal | CJ87: Japan | CK87: LatAm | CL87: MidEast | CM87: NorthAm | CN87: Norway | CO87: Poland | CP87: ROW | CQ87: Russia | CR87: SaudiArabia | CS87: SouthAfrica | CT87: SpainPor | CU87: SweFinDen | CV87: Switzerland | CW87: Turkey | CX87: UK | CY87: Ukraine | CZ87: World
A88: 2019 | B88: FLO_BND | C88: UP | D88: MINBatMaterials_LI | E88: m_lithium | F88: =BR88*1 -> 0 | G88: =BS88*1 -> 24.7 | H88: =BT88*1 -> 88 | I88: =BU88*1 -> 0 | J88: =BV88*1 -> 0 | K88: =BW88*1 -> 0 | L88: =BX88*1 -> 10 | M88: =BY88*1 -> 41 | ... AM88: =CY88*1 -> 0 | AN88: 0 | AO88: m_lithium | AW88: NAF | AX88: — | AY88: — | AZ88: — | BA88: — | BB88: — | BC88: — | BD88: — | BH88: Africa_North | BI88: 0 | BJ88: 0 | BK88: 0 | BL88: 0 | BM88: =Attached_sourcedAlumina_and!P12 -> 0 | BN88: 0 | BO88: 0 | BQ88: Li | BR88: 0 | BS88: 24.7 | BT88: 88 | BU88: 0 | BV88: 0 | BW88: 0 | BX88: 10 | BY88: 41 | BZ88: 0 | CA88: 0 | CB88: 0 | CC88: 0 | CD88: 0 | CE88: 0 | CF88: 0 | CG88: 0 | CH88: 0 | CI88: 0 | CJ88: 0 | CK88: 67 | CL88: 0 | CM88: 4.3 | CN88: 0 | CO88: 0 | CP88: 4.6 | CQ88: 0 | CR88: 0 | CS88: 0 | CT88: 0.4 | CU88: 0 | CV88: 0 | CW88: 0 | CX88: 0 | CY88: 0 | CZ88: 240
A89: 2019 | B89: FLO_BND | C89: UP | D89: MINBatMaterials_NI | E89: m_nickel | F89: =BR89*1 -> 0 | G89: =BS89*1 -> 0 | H89: =BT89*1 -> 110 | I89: =BU89*1 -> 0 | J89: =BV89*1 -> 0 | K89: =BW89*1 -> 0 | L89: =BX89*1 -> 77 | M89: =BY89*1 -> 120 | ... AM89: =CY89*1 -> 0 | AN89: 0 | AO89: m_nickel | AW89: SSA | AX89: 24.7 | AY89: 223 | AZ89: — | BA89: 5780 | BB89: 3980 | BC89: — | BD89: 189 | BH89: Africa_Other | BI89: 24.7 | BJ89: 0 | BK89: 222.6 | BL89: 5780 | BM89: =Attached_sourcedAlumina_and!P13 -> 159 | BN89: 3980 | BO89: 189 | BQ89: Ni | BR89: 0 | BS89: 0 | BT89: 110 | BU89: 0 | BV89: 0 | BW89: 0 | BX89: 77 | BY89: 120 | BZ89: 0 | CA89: 0 | CB89: 0 | CC89: 0 | CD89: 0 | CE89: 0 | CF89: 0 | CG89: 0 | CH89: 0 | CI89: 0 | CJ89: 0 | CK89: 0 | CL89: 0 | CM89: 198 | CN89: 0 | CO89: 0 | CP89: 2985 | CQ89: 210 | CR89: 0 | CS89: 0 | CT89: 0 | CU89: 0 | CV89: 0 | CW89: 0 | CX89: 0 | CY89: 0 | CZ89: 3700
A90: 2019 | B90: FLO_BND | C90: UP | D90: MINBatMaterials_COB_direct | E90: m_cobalt | F90: =BR90*1 -> 0 | G90: =BS90*1 -> 222.6 | H90: =BT90*1 -> 3.6 | I90: =BU90*1 -> 0 | J90: =BV90*1 -> 0 | K90: =BW90*1 -> 0 | L90: =BX90*1 -> 0 | M90: =BY90*1 -> 0 | ... AM90: =CY90*1 -> 0 | AN90: 0 | AO90: m_cobalt | AW90: AUS | AX90: 88 | AY90: 3.6 | AZ90: 110 | BA90: 2800 | BB90: 800 | BC90: 1500 | BD90: — | BH90: Australia | BI90: 88 | BJ90: 110 | BK90: 3.6 | BL90: 2800 | BM90: =Attached_sourcedAlumina_and!P14 -> 9522 | BN90: 800 | BO90: 0 | BQ90: Co | BR90: 0 | BS90: 222.6 | BT90: 3.6 | BU90: 0 | BV90: 0 | BW90: 0 | BX90: 0 | BY90: 0 | BZ90: 0 | CA90: 0 | CB90: 0 | CC90: 0 | CD90: 0 | CE90: 0 | CF90: 0 | CG90: 0 | CH90: 0 | CI90: 0 | CJ90: 0 | CK90: 3.5 | CL90: 0 | CM90: 4.8 | CN90: 0 | CO90: 0 | CP90: 43.8 | CQ90: 8.7 | CR90: 0 | CS90: 0 | CT90: 0 | CU90: 0 | CV90: 0 | CW90: 2.7 | CX90: 0 | CY90: 0 | CZ90: 290
A91: 2019 | B91: FLO_BND | C91: UP | D91: MINBatMaterials_MN | E91: m_manganese | F91: =BR91*1 -> 0 | G91: =BS91*1 -> 5780 | H91: =BT91*1 -> 2800 | I91: =BU91*1 -> 0 | J91: =BV91*1 -> 0 | K91: =BW91*1 -> 0 | L91: =BX91*1 -> 590 | M91: =BY91*1 -> 770 | ... AM91: =CY91*1 -> 0 | AN91: 0 | AO91: m_manganese | AW91: AUT | AX91: — | AY91: — | AZ91: — | BA91: — | BB91: — | BC91: — | BD91: 0.5 | BH91: Austria | BI91: 0 | BJ91: 0 | BK91: 0 | BL91: 0 | BM91: =Attached_sourcedAlumina_and!P15 -> 0 | BN91: 0 | BO91: 0.5 | BQ91: Mn | BR91: 0 | BS91: 5780 | BT91: 2800 | BU91: 0 | BV91: 0 | BW91: 0 | BX91: 590 | BY91: 770 | BZ91: 0 | CA91: 0 | CB91: 0 | CC91: 0 | CD91: 0 | CE91: 0 | CF91: 0 | CG91: 800 | CH91: 0 | CI91: 0 | CJ91: 0 | CK91: 0 | CL91: 0 | CM91: 0 | CN91: 0 | CO91: 0 | CP91: 2060 | CQ91: 0 | CR91: 0 | CS91: 7400 | CT91: 0 | CU91: 0 | CV91: 0 | CW91: 0 | CX91: 0 | CY91: 0 | CZ91: 20190
A92: 2019 | B92: FLO_BND | C92: UP | D92: MINBatMaterials_AL | E92: m_aluminum | F92: =BR92*1 -> 0 | G92: =BS92*1 -> 159 | H92: =BT92*1 -> 9522 | I92: =BU92*1 -> 0 | J92: =BV92*1 -> 0 | K92: =BW92*1 -> 0 | L92: =BX92*1 -> 5819 | M92: =BY92*1 -> 44436 | ... AM92: =CY92*1 -> 0 | AN92: 0 | AO92: m_aluminum | AW92: BAL | AX92: — | AY92: — | AZ92: — | BA92: — | BB92: — | BC92: — | BD92: — | BH92: Baltics | BI92: 0 | BJ92: 0 | BK92: 0 | BL92: 0 | BM92: =Attached_sourcedAlumina_and!P16 -> 0 | BN92: 0 | BO92: 0 | BQ92: Al | BR92: 0 | BS92: 159 | BT92: 9522 | BU92: 0 | BV92: 0 | BW92: 0 | BX92: 5819 | BY92: 44436 | BZ92: 0 | CA92: 0 | CB92: 0 | CC92: 508 | CD92: 455 | CE92: 0 | CF92: 0 | CG92: 4020 | CH92: 846 | CI92: 0 | CJ92: 0 | CK92: 0 | CL92: 1270 | CM92: 1175 | CN92: 0 | CO92: 0 | CP92: 3015 | CQ92: 1534 | CR92: 952 | CS92: 0 | CT92: 434 | CU92: 0 | CV92: 0 | CW92: 169 | CX92: 0 | CY92: 0 | CZ92: 75118
A93: 2019 | B93: FLO_BND | C93: UP | D93: MINBatMaterials_COP | E93: m_copper | F93: =BR93*1 -> 0 | G93: =BS93*1 -> 3980 | H93: =BT93*1 -> 800 | I93: =BU93*1 -> 0 | J93: =BV93*1 -> 0 | K93: =BW93*1 -> 0 | L93: =BX93*1 -> 0 | M93: =BY93*1 -> 1800 | ... AM93: =CY93*1 -> 0 | AN93: 0 | AO93: m_copper | AW93: BNL | AX93: — | AY93: — | AZ93: — | BA93: — | BB93: — | BC93: — | BD93: — | BH93: BeNeLux | BI93: 0 | BJ93: 0 | BK93: 0 | BL93: 0 | BM93: =Attached_sourcedAlumina_and!P17 -> 0 | BN93: 0 | BO93: 0 | BQ93: Cu | BR93: 0 | BS93: 3980 | BT93: 800 | BU93: 0 | BV93: 0 | BW93: 0 | BX93: 0 | BY93: 1800 | BZ93: 0 | CA93: 0 | CB93: 0 | CC93: 0 | CD93: 0 | CE93: 0 | CF93: 0 | CG93: 30 | CH93: 0 | CI93: 0 | CJ93: 0 | CK93: 7900 | CL93: 0 | CM93: 2250 | CN93: 0 | CO93: 410 | CP93: 4700 | CQ93: 930 | CR93: 0 | CS93: 0 | CT93: 0 | CU93: 0 | CV93: 0 | CW93: 0 | CX93: 0 | CY93: 0 | CZ93: 22000
A94: 2019 | B94: FLO_BND | C94: UP | D94: MINBatMaterials_GR | E94: m_graphite | F94: =BR94*1 -> 0 | G94: =BS94*1 -> 189 | H94: =BT94*1 -> 0 | I94: =BU94*1 -> 0.5 | J94: =BV94*1 -> 0 | K94: =BW94*1 -> 0 | L94: =BX94*1 -> 68 | M94: =BY94*1 -> 1270 | ... AM94: =CY94*1 -> 1.2 | AN94: 0 | AO94: m_graphite | AW94: BRA | AX94: 10 | AY94: — | AZ94: 77 | BA94: 590 | BB94: — | BC94: 1100 | BD94: 68 | BH94: Brazil | BI94: 10 | BJ94: 77 | BK94: 0 | BL94: 590 | BM94: =Attached_sourcedAlumina_and!P18 -> 5819 | BN94: 0 | BO94: 68 | BQ94: Graphite | BR94: 0 | BS94: 189 | BT94: 0 | BU94: 0.5 | BV94: 0 | BW94: 0 | BX94: 68 | BY94: 1270 | BZ94: 0 | CA94: 0 | CB94: 0 | CC94: 0.2 | CD94: 0 | CE94: 0 | CF94: 0 | CG94: 28 | CH94: 0 | CI94: 0 | CJ94: 0 | CK94: 0 | CL94: 0 | CM94: 20.9 | CN94: 7 | CO94: 0 | CP94: 22.9 | CQ94: 20 | CR94: 0 | CS94: 0 | CT94: 0 | CU94: 0 | CV94: 0 | CW94: 3 | CX94: 0 | CY94: 1.2 | CZ94: 1631
A95: =A94 -> 2019 | B95: =B94 -> FLO_BND | C95: =C94 -> UP | D95: MINBatMaterials_COB_byCop | F95: 0 | G95: 0 | H95: 0 | I95: 0 | J95: 0 | K95: 0 | L95: 0 | M95: 0 | N95: 0 | O95: 0 | P95: 0 | Q95: 0 | R95: 0 | S95: 0 | T95: 0 | U95: 0 | V95: 0 | W95: 0 | X95: 0 | Y95: 0 | Z95: 0 | AA95: 0 | AB95: 0 | AC95: 0 | AD95: 0 | AE95: 0 | AF95: 0 | AG95: 0 | AH95: 0 | AI95: 0 | AJ95: 0 | AK95: 0 | AL95: 0 | AM95: 0 | AN95: 0 | AW95: CHN | AX95: 41 | AY95: — | AZ95: 120 | BA95: 770 | BB95: 1800 | BC95: 43000 | BD95: 1270 | BH95: China | BI95: 41 | BJ95: 120 | BK95: 0 | BL95: 770 | BM95: =Attached_sourcedAlumina_and!P19 -> 44436 | BN95: 1800 | BO95: 1270
A96: =A95 -> 2019 | B96: =B95 -> FLO_BND | C96: =C95 -> UP | D96: MINBatMaterials_COB_byNI_sulfide | F96: 0 | G96: 0 | H96: 0 | I96: 0 | J96: 0 | K96: 0 | L96: 0 | M96: 0 | N96: 0 | O96: 0 | P96: 0 | Q96: 0 | R96: 0 | S96: 0 | T96: 0 | U96: 0 | V96: 0 | W96: 0 | X96: 0 | Y96: 0 | Z96: 0 | AA96: 0 | AB96: 0 | AC96: 0 | AD96: 0 | AE96: 0 | AF96: 0 | AG96: 0 | AH96: 0 | AI96: 0 | AJ96: 0 | AK96: 0 | AL96: 0 | AM96: 0 | AN96: 0 | AW96: CRS | AX96: — | AY96: — | AZ96: — | BA96: — | BB96: — | BC96: — | BD96: — | BH96: CroSloven | BI96: 0 | BJ96: 0 | BK96: 0 | BL96: 0 | BM96: =Attached_sourcedAlumina_and!P20 -> 0 | BN96: 0 | BO96: 0
A97: =A96 -> 2019 | B97: =B96 -> FLO_BND | C97: =C96 -> UP | D97: MINBatMaterials_COB_byNI_HPAL | F97: 0 | G97: 0 | H97: 0 | I97: 0 | J97: 0 | K97: 0 | L97: 0 | M97: 0 | N97: 0 | O97: 0 | P97: 0 | Q97: 0 | R97: 0 | S97: 0 | T97: 0 | U97: 0 | V97: 0 | W97: 0 | X97: 0 | Y97: 0 | Z97: 0 | AA97: 0 | AB97: 0 | AC97: 0 | AD97: 0 | AE97: 0 | AF97: 0 | AG97: 0 | AH97: 0 | AI97: 0 | AJ97: 0 | AK97: 0 | AL97: 0 | AM97: 0 | AN97: 0 | AW97: CZS | AX97: — | AY97: — | AZ97: — | BA97: — | BB97: — | BC97: — | BD97: — | BH97: CzechSlovak | BI97: 0 | BJ97: 0 | BK97: 0 | BL97: 0 | BM97: =Attached_sourcedAlumina_and!P21 -> 0 | BN97: 0 | BO97: 0
AW98: FRA | AX98: — | AY98: — | AZ98: — | BA98: — | BB98: — | BC98: — | BD98: — | BH98: France | BI98: 0 | BJ98: 0 | BK98: 0 | BL98: 0 | BM98: =Attached_sourcedAlumina_and!P22 -> 0 | BN98: 0 | BO98: 0
AW99: DEU | AX99: — | AY99: — | AZ99: — | BA99: — | BB99: — | BC99: — | BD99: 0.2 | BH99: Germany | BI99: 0 | BJ99: 0 | BK99: 0 | BL99: 0 | BM99: =Attached_sourcedAlumina_and!P23 -> 508 | BN99: 0 | BO99: 0.2
AW100: GRC | AX100: — | AY100: — | AZ100: — | BA100: — | BB100: — | BC100: — | BD100: — | BH100: GreeceCyp | BI100: 0 | BJ100: 0 | BK100: 0 | BL100: 0 | BM100: =Attached_sourcedAlumina_and!P24 -> 455 | BN100: 0 | BO100: 0
AW101: HRB | AX101: — | AY101: — | AZ101: — | BA101: — | BB101: — | BC101: — | BD101: — | BH101: HunRomBul | BI101: 0 | BJ101: 0 | BK101: 0 | BL101: 0 | BM101: =Attached_sourcedAlumina_and!P25 -> 0 | BN101: 0 | BO101: 0
D102: ~TFM_INS | O102: ~TFM_INS | AW102: ISL | AX102: — | AY102: — | AZ102: — | BA102: — | BB102: — | BC102: 780 | BD102: — | BH102: Iceland | BI102: 0 | BJ102: 0 | BK102: 0 | BL102: 0 | BM102: =Attached_sourcedAlumina_and!P26 -> 0 | BN102: 0 | BO102: 0
C103: attribute | D103: process | E103: AllRegions | F103: China | G103: NorthAm | K103: Korea | N103: attribute | O103: process | P103: AllRegions | Q103: China | R103: NorthAm | AW103: IND | AX103: — | AY103: — | AZ103: — | BA103: 800 | BB103: 30 | BC103: 4200 | BD103: 28 | BH103: India | BI103: 0 | BJ103: 0 | BK103: 0 | BL103: 800 | BM103: =Attached_sourcedAlumina_and!P27 -> 4020 | BN103: 30 | BO103: 28
C104: ACT_COST | D104: PyroRecy-LFP | E104: 7.113844 | F104: 5.4017985 | G104: 8.8554074 | K104: =E104*3-F104-G104 -> 7.0843259 | N104: ACT_COST | O104: PyroRecy-LFP | P104: =E104 -> 7.113844 | Q104: =F104 -> 5.4017985 | R104: =G104 -> 8.8554074 | AW104: IRL | AX104: — | AY104: — | AZ104: — | BA104: — | BB104: — | BC104: — | BD104: — | BH104: Ireland | BI104: 0 | BJ104: 0 | BK104: 0 | BL104: 0 | BM104: =Attached_sourcedAlumina_and!P28 -> 846 | BN104: 0 | BO104: 0
C105: ACT_COST | D105: PyroRecy-LMO | E105: 7.113844 | F105: 5.4017985 | G105: 8.8554074 | K105: =E105*3-F105-G105 -> 7.0843259 | N105: ACT_COST | O105: PyroRecy-LMO | P105: =E105 -> 7.113844 | Q105: =F105 -> 5.4017985 | R105: =G105 -> 8.8554074 | AW105: ITA | AX105: — | AY105: — | AZ105: — | BA105: — | BB105: — | BC105: — | BD105: — | BH105: ItalyMal | BI105: 0 | BJ105: 0 | BK105: 0 | BL105: 0 | BM105: =Attached_sourcedAlumina_and!P29 -> 0 | BN105: 0 | BO105: 0
C106: ACT_COST | D106: PyroRecy-NCA | E106: 7.6297545 | F106: 5.793548 | G106: 9.4976197 | K106: =E106*3-F106-G106 -> 7.5980957 | N106: ACT_COST | O106: PyroRecy-NCA | P106: =E106 -> 7.6297545 | Q106: =F106 -> 5.793548 | R106: =G106 -> 9.4976197 | AW106: JPN | AX106: — | AY106: — | AZ106: — | BA106: — | BB106: — | BC106: — | BD106: — | BH106: Japan | BI106: 0 | BJ106: 0 | BK106: 0 | BL106: 0 | BM106: =Attached_sourcedAlumina_and!P30 -> 0 | BN106: 0 | BO106: 0
C107: ACT_COST | D107: PyroRecy-NMC111 | E107: 7.4709708 | F107: 5.6729778 | G107: 9.2999637 | K107: =E107*3-F107-G107 -> 7.439971 | N107: ACT_COST | O107: PyroRecy-NMC111 | P107: =E107 -> 7.4709708 | Q107: =F107 -> 5.6729778 | R107: =G107 -> 9.2999637 | AW107: LAM | AX107: 67 | AY107: 3.5 | AZ107: — | BA107: — | BB107: 7900 | BC107: — | BD107: — | BH107: LatAm | BI107: 67 | BJ107: 0 | BK107: 3.5 | BL107: 0 | BM107: =Attached_sourcedAlumina_and!P31 -> 0 | BN107: 7900 | BO107: 0
C108: ACT_COST | D108: PyroRecy-NMC532 | E108: 7.5164352 | F108: 5.7075006 | G108: 9.3565584 | K108: =E108*3-F108-G108 -> 7.4852466 | N108: ACT_COST | O108: PyroRecy-NMC532 | P108: =E108 -> 7.5164352 | Q108: =F108 -> 5.7075006 | R108: =G108 -> 9.3565584 | AW108: MEA | AX108: — | AY108: — | AZ108: — | BA108: — | BB108: — | BC108: 4300 | BD108: — | BH108: MidEast | BI108: 0 | BJ108: 0 | BK108: 0 | BL108: 0 | BM108: =Attached_sourcedAlumina_and!P32 -> 1270 | BN108: 0 | BO108: 0
C109: ACT_COST | D109: PyroRecy-NMC622 | E109: 7.5503626 | F109: 5.7332629 | G109: 9.3987917 | K109: =E109*3-F109-G109 -> 7.5190333 | N109: ACT_COST | O109: PyroRecy-NMC622 | P109: =E109 -> 7.5503626 | Q109: =F109 -> 5.7332629 | R109: =G109 -> 9.3987917 | AW109: NAM | AX109: 4.3 | AY109: 4.8 | AZ109: 198 | BA109: — | BB109: 2250 | BC109: 3970 | BD109: 20.9 | BH109: NorthAm | BI109: 4.3 | BJ109: 198 | BK109: 4.8 | BL109: 0 | BM109: =Attached_sourcedAlumina_and!P33 -> 1175 | BN109: 2250 | BO109: 20.9
C110: ACT_COST | D110: PyroRecy-NMC811 | E110: 7.6297545 | F110: 5.793548 | G110: 9.4976197 | K110: =E110*3-F110-G110 -> 7.5980957 | N110: ACT_COST | O110: PyroRecy-NMC811 | P110: =E110 -> 7.6297545 | Q110: =F110 -> 5.793548 | R110: =G110 -> 9.4976197 | AW110: NOR | AX110: — | AY110: — | AZ110: — | BA110: — | BB110: — | BC110: 1300 | BD110: 7 | BH110: Norway | BI110: 0 | BJ110: 0 | BK110: 0 | BL110: 0 | BM110: =Attached_sourcedAlumina_and!P34 -> 0 | BN110: 0 | BO110: 7
C111: ACT_COST | D111: HydRecy-LFP | E111: 4.183846 | F111: 3.1769453 | G111: 5.2081071 | K111: =E111*3-F111-G111 -> 4.1664856 | N111: ACT_COST | O111: HydRecy-LFP | P111: =E111 -> 4.183846 | Q111: =F111 -> 3.1769453 | R111: =G111 -> 5.2081071 | AW111: POL | AX111: — | AY111: — | AZ111: — | BA111: — | BB111: 410 | BC111: — | BD111: — | BH111: Poland | BI111: 0 | BJ111: 0 | BK111: 0 | BL111: 0 | BM111: =Attached_sourcedAlumina_and!P35 -> 0 | BN111: 410 | BO111: 0
C112: ACT_COST | D112: HydRecy-LMO | E112: 4.183846 | F112: 3.1769453 | G112: 5.2081071 | K112: =E112*3-F112-G112 -> 4.1664856 | N112: ACT_COST | O112: HydRecy-LMO | P112: =E112 -> 4.183846 | Q112: =F112 -> 3.1769453 | R112: =G112 -> 5.2081071 | AW112: ROW | AX112: 4.6 | AY112: 43.8 | AZ112: 2985 | BA112: 2060 | BB112: 4700 | BC112: 8050 | BD112: 22.9 | BH112: ROW | BI112: 4.6 | BJ112: 2985 | BK112: 43.8 | BL112: 2060 | BM112: =Attached_sourcedAlumina_and!P36 -> 3015 | BN112: 4700 | BO112: 22.9
C113: ACT_COST | D113: HydRecy-NCA | E113: 4.183846 | F113: 3.1769453 | G113: 5.2081071 | K113: =E113*3-F113-G113 -> 4.1664856 | N113: ACT_COST | O113: HydRecy-NCA | P113: =E113 -> 4.183846 | Q113: =F113 -> 3.1769453 | R113: =G113 -> 5.2081071 | AW113: RUS | AX113: — | AY113: 8.7 | AZ113: 210 | BA113: — | BB113: 930 | BC113: 3800 | BD113: 20 | BH113: Russia | BI113: 0 | BJ113: 210 | BK113: 8.7 | BL113: 0 | BM113: =Attached_sourcedAlumina_and!P37 -> 1534 | BN113: 930 | BO113: 20
C114: ACT_COST | D114: HydRecy-NMC111 | E114: 4.183846 | F114: 3.1769453 | G114: 5.2081071 | K114: =E114*3-F114-G114 -> 4.1664856 | N114: ACT_COST | O114: HydRecy-NMC111 | P114: =E114 -> 4.183846 | Q114: =F114 -> 3.1769453 | R114: =G114 -> 5.2081071 | AW114: SAU | AX114: — | AY114: — | AZ114: — | BA114: — | BB114: — | BC114: — | BD114: — | BH114: SaudiArabia | BI114: 0 | BJ114: 0 | BK114: 0 | BL114: 0 | BM114: =Attached_sourcedAlumina_and!P38 -> 952 | BN114: 0 | BO114: 0
C115: ACT_COST | D115: HydRecy-NMC532 | E115: 4.183846 | F115: 3.1769453 | G115: 5.2081071 | K115: =E115*3-F115-G115 -> 4.1664856 | N115: ACT_COST | O115: HydRecy-NMC532 | P115: =E115 -> 4.183846 | Q115: =F115 -> 3.1769453 | R115: =G115 -> 5.2081071 | AW115: ZAF | AX115: — | AY115: — | AZ115: — | BA115: 7400 | BB115: — | BC115: — | BD115: — | BH115: SouthAfrica | BI115: 0 | BJ115: 0 | BK115: 0 | BL115: 7400 | BM115: =Attached_sourcedAlumina_and!P39 -> 0 | BN115: 0 | BO115: 0
C116: ACT_COST | D116: HydRecy-NMC622 | E116: 4.183846 | F116: 3.1769453 | G116: 5.2081071 | K116: =E116*3-F116-G116 -> 4.1664856 | N116: ACT_COST | O116: HydRecy-NMC622 | P116: =E116 -> 4.183846 | Q116: =F116 -> 3.1769453 | R116: =G116 -> 5.2081071 | AW116: ESP | AX116: 0.4 | AY116: — | AZ116: — | BA116: — | BB116: — | BC116: — | BD116: — | BH116: SpainPor | BI116: 0.4 | BJ116: 0 | BK116: 0 | BL116: 0 | BM116: =Attached_sourcedAlumina_and!P40 -> 434 | BN116: 0 | BO116: 0
C117: ACT_COST | D117: HydRecy-NMC811 | E117: 4.183846 | F117: 3.1769453 | G117: 5.2081071 | K117: =E117*3-F117-G117 -> 4.1664856 | N117: ACT_COST | O117: HydRecy-NMC811 | P117: =E117 -> 4.183846 | Q117: =F117 -> 3.1769453 | R117: =G117 -> 5.2081071 | AW117: SFD | AX117: — | AY117: — | AZ117: — | BA117: — | BB117: — | BC117: — | BD117: — | BH117: SweFinDen | BI117: 0 | BJ117: 0 | BK117: 0 | BL117: 0 | BM117: =Attached_sourcedAlumina_and!P41 -> 0 | BN117: 0 | BO117: 0
C118: ACT_COST | D118: DirRecy-LFP | E118: 3.5655627 | F118: 2.7074604 | G118: 4.4384598 | K118: =E118*3-F118-G118 -> 3.5507678 | N118: ACT_COST | O118: DirRecy-LFP | P118: =E118 -> 3.5655627 | Q118: =F118 -> 2.7074604 | R118: =G118 -> 4.4384598 | AW118: CHE | AX118: — | AY118: — | AZ118: — | BA118: — | BB118: — | BC118: — | BD118: — | BH118: Switzerland | BI118: 0 | BJ118: 0 | BK118: 0 | BL118: 0 | BM118: =Attached_sourcedAlumina_and!P42 -> 0 | BN118: 0 | BO118: 0
C119: ACT_COST | D119: DirRecy-LMO | E119: 3.6008771 | F119: 2.734276 | G119: 4.4824196 | K119: =E119*3-F119-G119 -> 3.5859357 | N119: ACT_COST | O119: DirRecy-LMO | P119: =E119 -> 3.6008771 | Q119: =F119 -> 2.734276 | R119: =G119 -> 4.4824196 | AW119: TUR | AX119: — | AY119: 2.7 | AZ119: — | BA119: — | BB119: — | BC119: — | BD119: 3 | BH119: Turkey | BI119: 0 | BJ119: 0 | BK119: 2.7 | BL119: 0 | BM119: =Attached_sourcedAlumina_and!P43 -> 169 | BN119: 0 | BO119: 3
C120: ACT_COST | D120: DirRecy-NCA | E120: 3.5655627 | F120: 2.7074604 | G120: 4.4384598 | K120: =E120*3-F120-G120 -> 3.5507678 | N120: ACT_COST | O120: DirRecy-NCA | P120: =E120 -> 3.5655627 | Q120: =F120 -> 2.7074604 | R120: =G120 -> 4.4384598 | AW120: UK | AX120: — | AY120: — | AZ120: — | BA120: — | BB120: — | BC120: — | BD120: — | BH120: UK | BI120: 0 | BJ120: 0 | BK120: 0 | BL120: 0 | BM120: =Attached_sourcedAlumina_and!P44 -> 0 | BN120: 0 | BO120: 0
C121: ACT_COST | D121: DirRecy-NMC111 | E121: 3.5664537 | F121: 2.7081371 | G121: 4.4395689 | K121: =E121*3-F121-G121 -> 3.5516551 | N121: ACT_COST | O121: DirRecy-NMC111 | P121: =E121 -> 3.5664537 | Q121: =F121 -> 2.7081371 | R121: =G121 -> 4.4395689 | AW121: UKR | AX121: — | AY121: — | AZ121: — | BA121: — | BB121: — | BC121: — | BD121: 1.2 | BH121: Ukraine | BI121: 0 | BJ121: 0 | BK121: 0 | BL121: 0 | BM121: =Attached_sourcedAlumina_and!P45 -> 0 | BN121: 0 | BO121: 1.2
C122: ACT_COST | D122: DirRecy-NMC532 | E122: 3.5658596 | F122: 2.7076859 | G122: 4.4388294 | K122: =E122*3-F122-G122 -> 3.5510635 | N122: ACT_COST | O122: DirRecy-NMC532 | P122: =E122 -> 3.5658596 | Q122: =F122 -> 2.7076859 | R122: =G122 -> 4.4388294 | AW122: WBK | AX122: — | AY122: — | AZ122: — | BA122: — | BB122: — | BC122: — | BD122: — | BH122: World | BI122: 240 | BJ122: 3700 | BK122: 290 | BL122: 20200 | BM122: =Attached_sourcedAlumina_and!P46 -> 75118 | BN122: 22000 | BO122: 1631
C123: ACT_COST | D123: DirRecy-NMC622 | E123: 3.5655627 | F123: 2.7074604 | G123: 4.4384598 | K123: =E123*3-F123-G123 -> 3.5507678 | N123: ACT_COST | O123: DirRecy-NMC622 | P123: =E123 -> 3.5655627 | Q123: =F123 -> 2.7074604 | R123: =G123 -> 4.4384598 | AW123: World | AX123: 240 | AY123: 290 | AZ123: 3700 | BA123: 20200 | BB123: 22000 | BC123: 72000 | BD123: 1631
C124: ACT_COST | D124: DirRecy-NMC811 | E124: 3.5649689 | F124: 2.7070096 | G124: 4.4377206 | K124: =E124*3-F124-G124 -> 3.5501765 | N124: ACT_COST | O124: DirRecy-NMC811 | P124: =E124 -> 3.5649689 | Q124: =F124 -> 2.7070096 | R124: =G124 -> 4.4377206
D132: ~TFM_INS | L132: ~TFM_INS | Q132: ~TFM_INS | AF132: ~TFM_INS
C133: =C103 -> attribute | D133: process | E133: AllRegions | G133: China | H133: NorthAm | K133: Attribute | L133: process | M133: AllRegions | O133: attribute | P133: process | Q133: AllRegions | S133: China | T133: NorthAm | AD133: year | AE133: attribute | AF133: process | AG133: AllRegions | AH133: China | AI133: NorthAm
C134: NCAP_COST | D134: PyroRecy-LFP | E134: 10 | G134: =E134*Q104/P104 -> 7.593361 | H134: =E134*R104/P104 -> 12.448133 | K134: NCAP_TLIFE | L134: PyroRecy-LFP | M134: 25 | O134: NCAP_COST | P134: Tra_EV_Batt-LFP_virgin | Q134: =E134 -> 10 | S134: =G134 -> 7.593361 | T134: =H134 -> 12.448133 | AD134: 2050 | AE134: ACT_COST | AF134: PyroRecy-LFP | AG134: =E104*0.313 -> 2.2266332 | AH134: =F104*0.313 -> 1.6907629 | AI134: =G104*0.313 -> 2.7717425
...

Sheet RoadTra_BY
A1: scenario | B1: attribute | C1: process | D1: commodity | E1: lim_type | F1: time_slice | G1: year | H1: commodity_group | I1: currency | J1: stage | K1: sow | L1: Africa_North | M1: Africa_Other | N1: Australia | O1: Austria | P1: Baltics | Q1: BeNeLux | R1: Brazil | S1: China | T1: CroSloven | U1: CzechSlovak | V1: France | W1: Germany | X1: GreeceCyp | Y1: HunRomBul | Z1: Iceland | AA1: India | AB1: Ireland | AC1: ItalyMal | AD1: Japan | AE1: LatAm | AF1: MidEast | AG1: NorthAm | AH1: Norway | AI1: Poland | AJ1: ROW | AK1: Russia | AL1: SaudiArabia | AM1: SouthAfrica | AN1: SpainPor | AO1: SweFinDen | AP1: Switzerland | AQ1: Turkey | AR1: UK | AS1: Ukraine | AT1: WestBalkans | AU1: year2
A2: BASE | B2: AF | C2: Trd_2w_elc | D2: - | E2: UP | F2: ANNUAL | G2: 2019 | H2: - | I2: - | J2: - | K2: - | L2: 7 | M2: 7 | N2: 7 | O2: 7 | P2: 7 | Q2: 7 | R2: 7 | S2: 7 | T2: 7 | U2: 7 | V2: 7 | W2: 7 | X2: 7 | Y2: 7 | Z2: 7 | AA2: 7 | AB2: 7 | AC2: 7 | AD2: 4 | AE2: 7 | AF2: 5 | AG2: 7 | AH2: 4 | AI2: 7 | AJ2: 7 | AK2: 3 | AL2: 7 | AM2: 7 | AN2: 6.5 | AO2: 7 | AP2: 7 | AQ2: 7 | AR2: 4 | AS2: 4 | AT2: 4 | AU2: -
A3: BASE | B3: AF | C3: Trd_2w_gsl | D3: - | E3: UP | F3: ANNUAL | G3: 2019 | H3: - | I3: - | J3: - | K3: - | L3: 7 | M3: 7 | N3: 7 | O3: 7 | P3: 7 | Q3: 7 | R3: 7 | S3: 7 | T3: 7 | U3: 7 | V3: 7 | W3: 7 | X3: 7 | Y3: 7 | Z3: 7 | AA3: 7 | AB3: 7 | AC3: 7 | AD3: 4 | AE3: 7 | AF3: 5 | AG3: 7 | AH3: 4 | AI3: 7 | AJ3: 7 | AK3: 3 | AL3: 7 | AM3: 7 | AN3: 6.5 | AO3: 7 | AP3: 7 | AQ3: 7 | AR3: 4 | AS3: 4 | AT3: 4 | AU3: -
A4: BASE | B4: AF | C4: Trd_3w_bdl | D4: - | E4: UP | F4: ANNUAL | G4: 2019 | H4: - | I4: - | J4: - | K4: - | L4: 15 | M4: 15 | N4: 15 | O4: 15 | P4: 15 | Q4: 15 | R4: 15 | S4: 15 | T4: 15 | U4: 15 | V4: 15 | W4: 15 | X4: 15 | Y4: 15 | Z4: 15 | AA4: 15 | AB4: 15 | AC4: 15 | AD4: 15 | AE4: 15 | AF4: 15 | AG4: 15 | AH4: 15 | AI4: 15 | AJ4: 15 | AK4: 15 | AL4: 15 | AM4: 15 | AN4: 20 | AO4: 15 | AP4: 15 | AQ4: 15 | AR4: 15 | AS4: 15 | AT4: 15 | AU4: -
A5: BASE | B5: AF | C5: Trd_3w_dsl | D5: - | E5: UP | F5: ANNUAL | G5: 2019 | H5: - | I5: - | J5: - | K5: - | L5: 15 | M5: 15 | N5: 15 | O5: 15 | P5: 15 | Q5: 15 | R5: 15 | S5: 15 | T5: 15 | U5: 15 | V5: 15 | W5: 15 | X5: 15 | Y5: 15 | Z5: 15 | AA5: 15 | AB5: 15 | AC5: 15 | AD5: 15 | AE5: 15 | AF5: 15 | AG5: 15 | AH5: 15 | AI5: 15 | AJ5: 15 | AK5: 15 | AL5: 15 | AM5: 15 | AN5: 20 | AO5: 15 | AP5: 15 | AQ5: 15 | AR5: 15 | AS5: 15 | AT5: 15 | AU5: -
A6: BASE | B6: AF | C6: Trd_3w_gsl | D6: - | E6: UP | F6: ANNUAL | G6: 2019 | H6: - | I6: - | J6: - | K6: - | L6: 15 | M6: 15 | N6: 15 | O6: 15 | P6: 15 | Q6: 15 | R6: 15 | S6: 15 | T6: 15 | U6: 15 | V6: 15 | W6: 15 | X6: 15 | Y6: 15 | Z6: 15 | AA6: 15 | AB6: 15 | AC6: 15 | AD6: 15 | AE6: 15 | AF6: 15 | AG6: 15 | AH6: 15 | AI6: 15 | AJ6: 15 | AK6: 15 | AL6: 15 | AM6: 15 | AN6: 20 | AO6: 15 | AP6: 15 | AQ6: 15 | AR6: 15 | AS6: 15 | AT6: 15 | AU6: -
A7: BASE | B7: AF | C7: Trd_bus_bdl | D7: - | E7: UP | F7: ANNUAL | G7: 2019 | H7: - | I7: - | J7: - | K7: - | L7: 35 | M7: 35 | N7: 35 | O7: 35 | P7: 35 | Q7: 35 | R7: 35 | S7: 35 | T7: 35 | U7: 35 | V7: 35 | W7: 35 | X7: 35 | Y7: 35 | Z7: 35 | AA7: 35 | AB7: 35 | AC7: 35 | AD7: 35 | AE7: 35 | AF7: 35 | AG7: 35 | AH7: 35 | AI7: 35 | AJ7: 35 | AK7: 35 | AL7: 35 | AM7: 35 | AN7: 35 | AO7: 35 | AP7: 35 | AQ7: 35 | AR7: 35 | AS7: 35 | AT7: 20 | AU7: -
A8: BASE | B8: AF | C8: Trd_bus_dsl | D8: - | E8: UP | F8: ANNUAL | G8: 2019 | H8: - | I8: - | J8: - | K8: - | L8: 35 | M8: 35 | N8: 35 | O8: 35 | P8: 35 | Q8: 35 | R8: 35 | S8: 35 | T8: 35 | U8: 35 | V8: 35 | W8: 35 | X8: 35 | Y8: 35 | Z8: 35 | AA8: 35 | AB8: 35 | AC8: 35 | AD8: 35 | AE8: 35 | AF8: 35 | AG8: 35 | AH8: 35 | AI8: 35 | AJ8: 35 | AK8: 35 | AL8: 35 | AM8: 35 | AN8: 35 | AO8: 35 | AP8: 35 | AQ8: 35 | AR8: 35 | AS8: 35 | AT8: 20 | AU8: -
A9: BASE | B9: AF | C9: Trd_bus_elc | D9: - | E9: UP | F9: ANNUAL | G9: 2019 | H9: - | I9: - | J9: - | K9: - | L9: 35 | M9: 35 | N9: 35 | O9: 35 | P9: 35 | Q9: 35 | R9: 35 | S9: 35 | T9: 35 | U9: 35 | V9: 35 | W9: 35 | X9: 35 | Y9: 35 | Z9: 35 | AA9: 35 | AB9: 35 | AC9: 35 | AD9: 35 | AE9: 35 | AF9: 35 | AG9: 35 | AH9: 35 | AI9: 35 | AJ9: 35 | AK9: 35 | AL9: 35 | AM9: 35 | AN9: 35 | AO9: 35 | AP9: 35 | AQ9: 35 | AR9: 35 | AS9: 35 | AT9: 20 | AU9: -
A10: BASE | B10: AF | C10: Trd_bus_eth | D10: - | E10: UP | F10: ANNUAL | G10: 2019 | H10: - | I10: - | J10: - | K10: - | L10: 35 | M10: 35 | N10: 35 | O10: 35 | P10: 35 | Q10: 35 | R10: 35 | S10: 35 | T10: 35 | U10: 35 | V10: 35 | W10: 35 | X10: 35 | Y10: 35 | Z10: 35 | AA10: 35 | AB10: 35 | AC10: 35 | AD10: 35 | AE10: 35 | AF10: 35 | AG10: 35 | AH10: 35 | AI10: 35 | AJ10: 35 | AK10: 35 | AL10: 35 | AM10: 35 | AN10: 35 | AO10: 35 | AP10: 35 | AQ10: 35 | AR10: 35 | AS10: 35 | AT10: 20 | AU10: -
A11: BASE | B11: AF | C11: Trd_bus_gsl | D11: - | E11: UP | F11: ANNUAL | G11: 2019 | H11: - | I11: - | J11: - | K11: - | L11: 35 | M11: 35 | N11: 35 | O11: 35 | P11: 35 | Q11: 35 | R11: 35 | S11: 35 | T11: 35 | U11: 35 | V11: 35 | W11: 35 | X11: 35 | Y11: 35 | Z11: 35 | AA11: 35 | AB11: 35 | AC11: 35 | AD11: 35 | AE11: 35 | AF11: 35 | AG11: 35 | AH11: 35 | AI11: 35 | AJ11: 35 | AK11: 35 | AL11: 35 | AM11: 35 | AN11: 35 | AO11: 35 | AP11: 35 | AQ11: 35 | AR11: 35 | AS11: 35 | AT11: 20 | AU11: -
A12: BASE | B12: AF | C12: Trd_bus_lpg | D12: - | E12: UP | F12: ANNUAL | G12: 2019 | H12: - | I12: - | J12: - | K12: - | L12: 35 | M12: 35 | N12: 35 | O12: 35 | P12: 35 | Q12: 35 | R12: 35 | S12: 35 | T12: 35 | U12: 35 | V12: 35 | W12: 35 | X12: 35 | Y12: 35 | Z12: 35 | AA12: 35 | AB12: 35 | AC12: 35 | AD12: 35 | AE12: 35 | AF12: 35 | AG12: 35 | AH12: 35 | AI12: 35 | AJ12: 35 | AK12: 35 | AL12: 35 | AM12: 35 | AN12: 35 | AO12: 35 | AP12: 35 | AQ12: 35 | AR12: 35 | AS12: 35 | AT12: 20 | AU12: -
A13: BASE | B13: AF | C13: Trd_bus_nga | D13: - | E13: UP | F13: ANNUAL | G13: 2019 | H13: - | I13: - | J13: - | K13: - | L13: 35 | M13: 35 | N13: 35 | O13: 35 | P13: 35 | Q13: 35 | R13: 35 | S13: 35 | T13: 35 | U13: 35 | V13: 35 | W13: 35 | X13: 35 | Y13: 35 | Z13: 35 | AA13: 35 | AB13: 35 | AC13: 35 | AD13: 35 | AE13: 35 | AF13: 35 | AG13: 35 | AH13: 35 | AI13: 35 | AJ13: 35 | AK13: 35 | AL13: 35 | AM13: 35 | AN13: 35 | AO13: 35 | AP13: 35 | AQ13: 35 | AR13: 35 | AS13: 35 | AT13: 20 | AU13: -
... A57: BASE | B57: EFF | C57: Trd_lcv_nga | D57: - | E57: - | F57: ANNUAL | G57: 2019 | H57: - | I57: - | J57: - | K57: - | L57: 0.32948443 | M57: 0.32948443 | N57: 0.32948443 | O57: 0.32948443 | P57: 0.32948443 | Q57: 0.32948443 | R57: 0.32948443 | S57: 0.32948443 | T57: 0.32948443 | U57: 0.32948443 | V57: 0.32948443 | W57: 0.32948443 | X57: 0.32948443 | Y57: 0.32948443 | Z57: 0.32948443 | AA57: 0.32948443 | AB57: 0.32948443 | AC57: 0.32948443 | AD57: 0.32948443 | AE57: 0.32948443 | AF57: 0.32948443 | AG57: 0.32948443 | AH57: 0.32948443 | AI57: 0.32948443 | AJ57: 0.32948443 | AK57: 0.32948443 | AL57: 0.32948443 | AM57: 0.32948443 | AN57: 0.32948443 | AO57: 0.32948443 | AP57: 0.32948443 | AQ57: 0.32948443 | AR57: 0.32948443 | AS57: 0.32948443 | AT57: 0.32948443 | AU57: -

Sheet added_EnergyUse_for_Manu
L4: ~TFM_UPD: attribute= INPUT | R4: ~TFM_UPD: attribute= INPUT | X4: ~TFM_UPD: attribute= INPUT | AD4: ~TFM_UPD: attribute= INPUT | AJ4: ~TFM_UPD: attribute= INPUT | AP4: ~TFM_UPD: attribute= INPUT | AV4: ~TFM_UPD: attribute= INPUT
J5: limtype | K5: process | L5: cset_cn | M5: NorthAm | N5: year | P5: limtype | Q5: process | R5: cset_cn | S5: NorthAm | T5: year | V5: limtype | W5: process | X5: cset_cn | Y5: NorthAm | Z5: year | AB5: limtype | AC5: process | AD5: cset_cn | AE5: NorthAm | AF5: year | AH5: limtype | AI5: process | AJ5: cset_cn | AK5: NorthAm | AL5: year | AN5: limtype | AO5: process | AP5: cset_cn | AQ5: NorthAm | AR5: year | AT5: limtype | AU5: process | AV5: cset_cn | AW5: NorthAm | AX5: year
J6: FX | K6: Tra_EV_Batt-NMC111_virgin | L6: INDELC | M6: =M16/1000 -> 0.0768 | N6: 2019 | P6: FX | Q6: Tra_EV_Batt-NMC532_virgin | R6: INDELC | S6: =S16/1000 -> 0.0713 | T6: 2019 | V6: FX | W6: Tra_EV_Batt-NMC622_virgin | X6: INDELC | Y6: =Y16/1000 -> 0.0712 | Z6: 2019 | AB6: FX | AC6: Tra_EV_Batt-NMC811_virgin | AD6: INDELC | AE6: =AE16/1000 -> 0.0725 | AF6: 2019 | AH6: FX | AI6: Tra_EV_Batt-NCA_virgin | AJ6: INDELC | AK6: =AK16/1000 -> 0.077 | AL6: 2019 | AN6: FX | AO6: Tra_EV_Batt-LMO_virgin | AP6: INDELC | AQ6: =AQ16/1000 -> 0.0424 | AR6: 2019 | AT6: FX | AU6: Tra_EV_Batt-LFP_virgin | AV6: INDELC | AW6: =AW16/1000 -> 0.0472 | AX6: 2019
J7: FX | K7: Tra_EV_Batt-NMC111_virgin | L7: INDCOA | M7: =M17/1000 -> 0.2026 | N7: 2019 | P7: FX | Q7: Tra_EV_Batt-NMC532_virgin | R7: INDCOA | S7: =S17/1000 -> 0.1913 | T7: 2019 | V7: FX | W7: Tra_EV_Batt-NMC622_virgin | X7: INDCOA | Y7: =Y17/1000 -> 0.1915 | Z7: 2019 | AB7: FX | AC7: Tra_EV_Batt-NMC811_virgin | AD7: INDCOA | AE7: =AE17/1000 -> 0.1859 | AF7: 2019 | AH7: FX | AI7: Tra_EV_Batt-NCA_virgin | AJ7: INDCOA | AK7: =AK17/1000 -> 0.1982 | AL7: 2019 | AN7: FX | AO7: Tra_EV_Batt-LMO_virgin | AP7: INDCOA | AQ7: =AQ17/1000 -> 0.0768 | AR7: 2019 | AT7: FX | AU7: Tra_EV_Batt-LFP_virgin | AV7: INDCOA | AW7: =AW17/1000 -> 0.1555 | AX7: 2019
J8: FX | K8: Tra_EV_Batt-NMC111_virgin | L8: INDNGA | M8: =M18/1000 -> 0.5838 | N8: 2019 | P8: FX | Q8: Tra_EV_Batt-NMC532_virgin | R8: INDNGA | S8: =S18/1000 -> 0.5561 | T8: 2019 | V8: FX | W8: Tra_EV_Batt-NMC622_virgin | X8: INDNGA | Y8: =Y18/1000 -> 0.5579 | Z8: 2019 | AB8: FX | AC8: Tra_EV_Batt-NMC811_virgin | AD8: INDNGA | AE8: =AE18/1000 -> 0.5505 | AF8: 2019 | AH8: FX | AI8: Tra_EV_Batt-NCA_virgin | AJ8: INDNGA | AK8: =AK18/1000 -> 0.5942 | AL8: 2019 | AN8: FX | AO8: Tra_EV_Batt-LMO_virgin | AP8: INDNGA | AQ8: =AQ18/1000 -> 0.4099 | AR8: 2019 | AT8: FX | AU8: Tra_EV_Batt-LFP_virgin | AV8: INDNGA | AW8: =AW18/1000 -> 0.477 | AX8: 2019
J9: FX | K9: Tra_EV_Batt-NMC111_virgin | L9: INDOIL | M9: =M19/1000 -> 0.1275 | N9: 2019 | P9: FX | Q9: Tra_EV_Batt-NMC532_virgin | R9: INDOIL | S9: =S19/1000 -> 0.1337 | T9: 2019 | V9: FX | W9: Tra_EV_Batt-NMC622_virgin | X9: INDOIL | Y9: =Y19/1000 -> 0.1403 | Z9: 2019 | AB9: FX | AC9: Tra_EV_Batt-NMC811_virgin | AD9: INDOIL | AE9: =AE19/1000 -> 0.1499 | AF9: 2019 | AH9: FX | AI9: Tra_EV_Batt-NCA_virgin | AJ9: INDOIL | AK9: =AK19/1000 -> 0.1608 | AL9: 2019 | AN9: FX | AO9: Tra_EV_Batt-LMO_virgin | AP9: INDOIL | AQ9: =AQ19/1000 -> 0.057 | AR9: 2019 | AT9: FX | AU9: Tra_EV_Batt-LFP_virgin | AV9: INDOIL | AW9: =AW19/1000 -> 0.0952 | AX9: 2019
M16: =T65 -> 76.8 | S16: =U65 -> 71.3 | Y16: =V65 -> 71.2 | AE16: =W65 -> 72.5 | AK16: =X65 -> 77 | AQ16: =Y65 -> 42.4 | AW16: =Z65 -> 47.2
M17: =T66 -> 202.6 | S17: =U66 -> 191.3 | Y17: =V66 -> 191.5 | AE17: =W66 -> 185.9 | AK17: =X66 -> 198.2 | AQ17: =Y66 -> 76.8 | AW17: =Z66 -> 155.5
M18: =T67 -> 583.8 | S18: =U67 -> 556.1 | Y18: =V67 -> 557.9 | AE18: =W67 -> 550.5 | AK18: =X67 -> 594.2 | AQ18: =Y67 -> 409.9 | AW18: =Z67 -> 477
M19: =T68 -> 127.5 | S19: =U68 -> 133.7 | Y19: =V68 -> 140.3 | AE19: =W68 -> 149.9 | AK19: =X68 -> 160.8 | AQ19: =Y68 -> 57 | AW19: =Z68 -> 95.2
L24: ~TFM_UPD: attribute= INPUT | R24: ~TFM_UPD: attribute= INPUT | X24: ~TFM_UPD: attribute= INPUT | AD24: ~TFM_UPD: attribute= INPUT | AJ24: ~TFM_UPD: attribute= INPUT | AP24: ~TFM_UPD: attribute= INPUT | AV24: ~TFM_UPD: attribute= INPUT
J25: limtype | K25: process | L25: cset_cn | M25: China | N25: year | P25: limtype | Q25: process | R25: cset_cn | S25: China | T25: year | V25: limtype | W25: process | X25: cset_cn | Y25: China | Z25: year | AB25: limtype | AC25: process | AD25: cset_cn | AE25: China | AF25: year | AH25: limtype | AI25: process | AJ25: cset_cn | AK25: China | AL25: year | AN25: limtype | AO25: process | AP25: cset_cn | AQ25: China | AR25: year | AT25: limtype | AU25: process | AV25: cset_cn | AW25: China | AX25: year
J26: FX | K26: =K6 -> Tra_EV_Batt-NMC111_virgin | L26: INDELC | M26: =T73/1000 -> 0.0774 | N26: 2019 | P26: FX | Q26: =Q6 -> Tra_EV_Batt-NMC532_virgin | R26: INDELC | S26: =S32/1000 -> 0.072 | T26: 2019 | V26: FX | W26: =W6 -> Tra_EV_Batt-NMC622_virgin | X26: INDELC | Y26: =Y32/1000 -> 0.0719 | Z26: 2019 | AB26: FX | AC26: =AC6 -> Tra_EV_Batt-NMC811_virgin | AD26: INDELC | AE26: =AE32/1000 -> 0.0731 | AF26: 2019 | AH26: FX | AI26: =AI6 -> Tra_EV_Batt-NCA_virgin | AJ26: INDELC | AK26: =AK32/1000 -> 0.0777 | AL26: 2019 | AN26: FX | AO26: =AO6 -> Tra_EV_Batt-LMO_virgin | AP26: INDELC | AQ26: =AQ32/1000 -> 0.0431 | AR26: 2019 | AT26: FX | AU26: =AU6 -> Tra_EV_Batt-LFP_virgin | AV26: INDELC | AW26: =AW32/1000 -> 0.0478 | AX26: 2019
J27: FX | K27: =K7 -> Tra_EV_Batt-NMC111_virgin | L27: INDCOA | M27: =T74/1000 -> 0.2366 | N27: 2019 | P27: FX | Q27: =Q7 -> Tra_EV_Batt-NMC532_virgin | R27: INDCOA | S27: =S33/1000 -> 0.2252 | T27: 2019 | V27: FX | W27: =W7 -> Tra_EV_Batt-NMC622_virgin | X27: INDCOA | Y27: =Y33/1000 -> 0.2255 | Z27: 2019 | AB27: FX | AC27: =AC7 -> Tra_EV_Batt-NMC811_virgin | AD27: INDCOA | AE27: =AE33/1000 -> 0.2198 | AF27: 2019 | AH27: FX | AI27: =AI7 -> Tra_EV_Batt-NCA_virgin | AJ27: INDCOA | AK27: =AK33/1000 -> 0.2322 | AL27: 2019 | AN27: FX | AO27: =AO7 -> Tra_EV_Batt-LMO_virgin | AP27: INDCOA | AQ27: =AQ33/1000 -> 0.1108 | AR27: 2019 | AT27: FX | AU27: =AU7 -> Tra_EV_Batt-LFP_virgin | AV27: INDCOA | AW27: =AW33/1000 -> 0.1895 | AX27: 2019
J28: FX | K28: =K8 -> Tra_EV_Batt-NMC111_virgin | L28: INDNGA | M28: =T75/1000 -> 0.5598 | N28: 2019 | P28: FX | Q28: =Q8 -> Tra_EV_Batt-NMC532_virgin | R28: INDNGA | S28: =S34/1000 -> 0.5321 | T28: 2019 | V28: FX | W28: =W8 -> Tra_EV_Batt-NMC622_virgin | X28: INDNGA | Y28: =Y34/1000 -> 0.5339 | Z28: 2019 | AB28: FX | AC28: =AC8 -> Tra_EV_Batt-NMC811_virgin | AD28: INDNGA | AE28: =AE34/1000 -> 0.5264 | AF28: 2019 | AH28: FX | AI28: =AI8 -> Tra_EV_Batt-NCA_virgin | AJ28: INDNGA | AK28: =AK34/1000 -> 0.5702 | AL28: 2019 | AN28: FX | AO28: =AO8 -> Tra_EV_Batt-LMO_virgin | AP28: INDNGA | AQ28: =AQ34/1000 -> 0.3858 | AR28: 2019 | AT28: FX | AU28: =AU8 -> Tra_EV_Batt-LFP_virgin | AV28: INDNGA | AW28: =AW34/1000 -> 0.453 | AX28: 2019
J29: FX | K29: =K9 -> Tra_EV_Batt-NMC111_virgin | L29: INDOIL | M29: =T76/1000 -> 0.1277 | N29: 2019 | P29: FX | Q29: =Q9 -> Tra_EV_Batt-NMC532_virgin | R29: INDOIL | S29: =S35/1000 -> 0.134 | T29: 2019 | V29: FX | W29: =W9 -> Tra_EV_Batt-NMC622_virgin | X29: INDOIL | Y29: =Y35/1000 -> 0.1406 | Z29: 2019 | AB29: FX | AC29: =AC9 -> Tra_EV_Batt-NMC811_virgin | AD29: INDOIL | AE29: =AE35/1000 -> 0.1502 | AF29: 2019 | AH29: FX | AI29: =AI9 -> Tra_EV_Batt-NCA_virgin | AJ29: INDOIL | AK29: =AK35/1000 -> 0.1611 | AL29: 2019 | AN29: FX | AO29: =AO9 -> Tra_EV_Batt-LMO_virgin | AP29: INDOIL | AQ29: =AQ35/1000 -> 0.0572 | AR29: 2019 | AT29: FX | AU29: =AU9 -> Tra_EV_Batt-LFP_virgin | AV29: INDOIL | AW29: =AW35/1000 -> 0.0955 | AX29: 2019
S32: =U73 -> 72 | Y32: =V73 -> 71.9 | AE32: =W73 -> 73.1 | AK32: =X73 -> 77.7 | AQ32: =Y73 -> 43.1 | AW32: =Z73 -> 47.8
S33: =U74 -> 225.2 | Y33: =V74 -> 225.5 | AE33: =W74 -> 219.8 | AK33: =X74 -> 232.2 | AQ33: =Y74 -> 110.8 | AW33: =Z74 -> 189.5
S34: =U75 -> 532.1 | Y34: =V75 -> 533.9 | AE34: =W75 -> 526.4 | AK34: =X75 -> 570.2 | AQ34: =Y75 -> 385.8 | AW34: =Z75 -> 453
S35: =U76 -> 134 | Y35: =V76 -> 140.6 | AE35: =W76 -> 150.2 | AK35: =X76 -> 161.1 | AQ35: =Y76 -> 57.2 | AW35: =Z76 -> 95.5
Q42: Original data_provided by Anna
Q43: Location | R43: Energy use (MJ/kWh battery produced) | S43: Chemistry
S44: LCO | T44: NMC111 | U44: NMC532 | V44: NMC622 | W44: NMC811 | X44: NCA | Y44: LMO | Z44: LFP
Q45: US | R45: Total Energy | S45: 1211.3 | T45: 990.7 | U45: 952.4 | V45: 961 | W45: 958.7 | X45: 1030.2 | Y45: 586.1 | Z45: 775
R46: Fossil fuels | S46: 1103.7 | T46: 913.9 | U46: 881.1 | V46: 889.8 | W46: 886.2 | X46: 953.2 | Y46: 543.7 | Z46: 727.8
R47: Coal | S47: 267.3 | T47: 202.6 | U47: 191.3 | V47: 191.5 | W47: 185.9 | X47: 198.2 | Y47: 76.8 | Z47: 155.5
R48: Natural gas | S48: 692.5 | T48: 583.8 | U48: 556.1 | V48: 557.9 | W48: 550.5 | X48: 594.2 | Y48: 409.9 | Z48: 477
R49: Petroleum | S49: 144 | T49: 127.5 | U49: 133.7 | V49: 140.3 | W49: 149.9 | X49: 160.8 | Y49: 57 | Z49: 95.2
Q50: Korea | R50: Total Energy | S50: 1217.1 | T50: 996.4 | U50: 958.2 | V50: 966.8 | W50: 964.4 | X50: 1036 | Y50: 591.9 | Z50: 780.8
R51: Fossil fuels | S51: 1109.8 | T51: 920 | U51: 887.2 | V51: 895.9 | W51: 892.3 | X51: 959.3 | Y51: 549.8 | Z51: 733.9
R52: Coal | S52: 280.2 | T52: 215.6 | U52: 204.2 | V52: 204.5 | W52: 198.8 | X52: 211.1 | Y52: 89.8 | Z52: 168.5
R53: Natural gas | S53: 684.6 | T53: 575.9 | U53: 548.2 | V53: 550 | W53: 542.6 | X53: 586.3 | Y53: 402 | Z53: 469.1
R54: Petroleum | S54: 145 | T54: 128.5 | U54: 134.7 | V54: 141.3 | W54: 150.9 | X54: 161.9 | Y54: 58 | Z54: 96.3
Q55: China | R55: Total Energy | S55: 1222.2 | T55: 1001.5 | U55: 963.3 | V55: 971.9 | W55: 969.5 | X55: 1041.1 | Y55: 597 | Z55: 785.8
R56: Fossil fuels | S56: 1113.9 | T56: 924.1 | U56: 891.3 | V56: 900 | W56: 896.4 | X56: 963.4 | Y56: 553.9 | Z56: 738
R57: Coal | S57: 301.2 | T57: 236.6 | U57: 225.2 | V57: 225.5 | W57: 219.8 | X57: 232.2 | Y57: 110.8 | Z57: 189.5
R58: Natural gas | S58: 668.4 | T58: 559.8 | U58: 532.1 | V58: 533.9 | W58: 526.4 | X58: 570.2 | Y58: 385.8 | Z58: 453
R59: Petroleum | S59: 144.2 | T59: 127.7 | U59: 134 | V59: 140.6 | W59: 150.2 | X59: 161.1 | Y59: 57.2 | Z59: 95.5
Q61: ** Assumed to be cell manufacturing
S64: LCO | T64: NMC111 | U64: NMC532 | V64: NMC622 | W64: NMC811 | X64: NCA | Y64: LMO | Z64: LFP
Q65: US | R65: ELC | S65: =S45-S46 -> 107.6 | T65: =T45-T46 -> 76.8 | U65: =U45-U46 -> 71.3 | V65: =V45-V46 -> 71.2 | W65: =W45-W46 -> 72.5 | X65: =X45-X46 -> 77 | Y65: =Y45-Y46 -> 42.4 | Z65: =Z45-Z46 -> 47.2
R66: Coal | S66: =S47 -> 267.3 | T66: =T47 -> 202.6 | U66: =U47 -> 191.3 | V66: =V47 -> 191.5 | W66: =W47 -> 185.9 | X66: =X47 -> 198.2 | Y66: =Y47 -> 76.8 | Z66: =Z47 -> 155.5
R67: Natural gas | S67: =S48 -> 692.5 | T67: =T48 -> 583.8 | U67: =U48 -> 556.1 | V67: =V48 -> 557.9 | W67: =W48 -> 550.5 | X67: =X48 -> 594.2 | Y67: =Y48 -> 409.9 | Z67: =Z48 -> 477
R68: Petroleum | S68: =S49 -> 144 | T68: =T49 -> 127.5 | U68: =U49 -> 133.7 | V68: =V49 -> 140.3 | W68: =W49 -> 149.9 | X68: =X49 -> 160.8 | Y68: =Y49 -> 57 | Z68: =Z49 -> 95.2
Q69: Korea | R69: ELC | S69: =S50-S51 -> 107.3 | T69: =T50-T51 -> 76.4 | U69: =U50-U51 -> 71 | V69: =V50-V51 -> 70.9 | W69: =W50-W51 -> 72.1 | X69: =X50-X51 -> 76.7 | Y69: =Y50-Y51 -> 42.1 | Z69: =Z50-Z51 -> 46.9
R70: Coal | S70: =S52 -> 280.2 | T70: =T52 -> 215.6 | U70: =U52 -> 204.2 | V70: =V52 -> 204.5 | W70: =W52 -> 198.8 | X70: =X52 -> 211.1 | Y70: =Y52 -> 89.8 | Z70: =Z52 -> 168.5
R71: Natural gas | S71: =S53 -> 684.6 | T71: =T53 -> 575.9 | U71: =U53 -> 548.2 | V71: =V53 -> 550 | W71: =W53 -> 542.6 | X71: =X53 -> 586.3 | Y71: =Y53 -> 402 | Z71: =Z53 -> 469.1
R72: Petroleum | S72: =S54 -> 145 | T72: =T54 -> 128.5 | U72: =U54 -> 134.7 | V72: =V54 -> 141.3 | W72: =W54 -> 150.9 | X72: =X54 -> 161.9 | Y72: =Y54 -> 58 | Z72: =Z54 -> 96.3
Q73: China | R73: ELC | S73: =S55-S56 -> 108.3 | T73: =T55-T56 -> 77.4 | U73: =U55-U56 -> 72 | V73: =V55-V56 -> 71.9 | W73: =W55-W56 -> 73.1 | X73: =X55-X56 -> 77.7 | Y73: =Y55-Y56 -> 43.1 | Z73: =Z55-Z56 -> 47.8
R74: Coal | S74: =S57 -> 301.2 | T74: =T57 -> 236.6 | U74: =U57 -> 225.2 | V74: =V57 -> 225.5 | W74: =W57 -> 219.8 | X74: =X57 -> 232.2 | Y74: =Y57 -> 110.8 | Z74: =Z57 -> 189.5
R75: Natural gas | S75: =S58 -> 668.4 | T75: =T58 -> 559.8 | U75: =U58 -> 532.1 | V75: =V58 -> 533.9 | W75: =W58 -> 526.4 | X75: =X58 -> 570.2 | Y75: =Y58 -> 385.8 | Z75: =Z58 -> 453
R76: Petroleum | S76: =S59 -> 144.2 | T76: =T59 -> 127.7 | U76: =U59 -> 134 | V76: =V59 -> 140.6 | W76: =W59 -> 150.2 | X76: =X59 -> 161.1 | Y76: =Y59 -> 57.2 | Z76: =Z59 -> 95.5
Q79: Other countries | R79: ELC | S79: =AVERAGE(S65,S69,S73) -> 107.73333 | T79: =AVERAGE(T65,T69,T73) -> 76.866667 | U79: =AVERAGE(U65,U69,U73) -> 71.433333 | V79: =AVERAGE(V65,V69,V73) -> 71.333333 | W79: =AVERAGE(W65,W69,W73) -> 72.566667 | X79: =AVERAGE(X65,X69,X73) -> 77.133333 | Y79: =AVERAGE(Y65,Y69,Y73) -> 42.533333 | Z79: =AVERAGE(Z65,Z69,Z73) -> 47.3
R80: Coal | S80: =AVERAGE(S66,S70,S74) -> 282.9 | T80: =AVERAGE(T66,T70,T74) -> 218.26667 | U80: =AVERAGE(U66,U70,U74) -> 206.9 | V80: =AVERAGE(V66,V70,V74) -> 207.16667 | W80: =AVERAGE(W66,W70,W74) -> 201.5 | X80: =AVERAGE(X66,X70,X74) -> 213.83333 | Y80: =AVERAGE(Y66,Y70,Y74) -> 92.466667 | Z80: =AVERAGE(Z66,Z70,Z74) -> 171.16667
R81: Natural gas | S81: =AVERAGE(S67,S71,S75) -> 681.83333 | T81: =AVERAGE(T67,T71,T75) -> 573.16667 | U81: =AVERAGE(U67,U71,U75) -> 545.46667 | V81: =AVERAGE(V67,V71,V75) -> 547.26667 | W81: =AVERAGE(W67,W71,W75) -> 539.83333 | X81: =AVERAGE(X67,X71,X75) -> 583.56667 | Y81: =AVERAGE(Y67,Y71,Y75) -> 399.23333 | Z81: =AVERAGE(Z67,Z71,Z75) -> 466.36667
R82: Petroleum | S82: =AVERAGE(S68,S72,S76) -> 144.4 | T82: =AVERAGE(T68,T72,T76) -> 127.9 | U82: =AVERAGE(U68,U72,U76) -> 134.13333 | V82: =AVERAGE(V68,V72,V76) -> 140.73333 | W82: =AVERAGE(W68,W72,W76) -> 150.33333 | X82: =AVERAGE(X68,X72,X76) -> 161.26667 | Y82: =AVERAGE(Y68,Y72,Y76) -> 57.4 | Z82: =AVERAGE(Z68,Z72,Z76) -> 95.666667
M94: ~TFM_UPD: attribute= INPUT | S94: ~TFM_UPD: attribute= INPUT | Y94: ~TFM_UPD: attribute= INPUT | AE94: ~TFM_UPD: attribute= INPUT | AK94: ~TFM_UPD: attribute= INPUT | AQ94: ~TFM_UPD: attribute= INPUT | AW94: ~TFM_UPD: attribute= INPUT
K95: limtype | L95: process | M95: cset_cn | N95: NorthAm | O95: year | Q95: limtype | R95: process | S95: cset_cn | T95: NorthAm | U95: year | W95: limtype | X95: process | Y95: cset_cn | Z95: NorthAm | AA95: year | AC95: limtype | AD95: process | AE95: cset_cn | AF95: NorthAm | AG95: year | AI95: limtype | AJ95: process | AK95: cset_cn | AL95: NorthAm | AM95: year | AO95: limtype | AP95: process | AQ95: cset_cn | AR95: NorthAm | AS95: year | AU95: limtype | AV95: process | AW95: cset_cn | AX95: NorthAm | AY95: year
K96: FX | L96: Tra_EV_Batt-NMC111_virgin | M96: INDELC | N96: =SUM(M6:M9) -> 0.9907 | O96: 2050, 2100 | Q96: FX | R96: Tra_EV_Batt-NMC532_virgin | S96: INDELC | T96: =SUM(S6:S9) -> 0.9524 | U96: 2050, 2100 | W96: FX | X96: Tra_EV_Batt-NMC622_virgin | Y96: INDELC | Z96: =SUM(Y6:Y9) -> 0.9609 | AA96: 2050, 2100 | AC96: FX | AD96: Tra_EV_Batt-NMC811_virgin | AE96: INDELC | AF96: =SUM(AE6:AE9) -> 0.9588 | AG96: 2050, 2100 | AI96: FX | AJ96: Tra_EV_Batt-NCA_virgin | AK96: INDELC | AL96: =SUM(AK6:AK9) -> 1.0302 | AM96: 2050, 2100 | AO96: FX | AP96: Tra_EV_Batt-LMO_virgin | AQ96: INDELC | AR96: =SUM(AQ6:AQ9) -> 0.5861 | AS96: 2050, 2100 | AU96: FX | AV96: Tra_EV_Batt-LFP_virgin | AW96: INDELC | AX96: =SUM(AW6:AW9) -> 0.7749 | AY96: 2050, 2100
K97: FX | L97: Tra_EV_Batt-NMC111_virgin | M97: INDCOA | N97: 0 | O97: 2050, 2100 | Q97: FX | R97: Tra_EV_Batt-NMC532_virgin | S97: INDCOA | T97: 0 | U97: 2050, 2100 | W97: FX | X97: Tra_EV_Batt-NMC622_virgin | Y97: INDCOA | Z97: 0 | AA97: 2050, 2100 | AC97: FX | AD97: Tra_EV_Batt-NMC811_virgin | AE97: INDCOA | AF97: 0 | AG97: 2050, 2100 | AI97: FX | AJ97: Tra_EV_Batt-NCA_virgin | AK97: INDCOA | AL97: 0 | AM97: 2050, 2100 | AO97: FX | AP97: Tra_EV_Batt-LMO_virgin | AQ97: INDCOA | AR97: 0 | AS97: 2050, 2100 | AU97: FX | AV97: Tra_EV_Batt-LFP_virgin | AW97: INDCOA | AX97: 0 | AY97: 2050, 2100
K98: FX | L98: Tra_EV_Batt-NMC111_virgin | M98: INDNGA | N98: 0 | O98: 2050, 2100 | Q98: FX | R98: Tra_EV_Batt-NMC532_virgin | S98: INDNGA | T98: 0 | U98: 2050, 2100 | W98: FX | X98: Tra_EV_Batt-NMC622_virgin | Y98: INDNGA | Z98: 0 | AA98: 2050, 2100 | AC98: FX | AD98: Tra_EV_Batt-NMC811_virgin | AE98: INDNGA | AF98: 0 | AG98: 2050, 2100 | AI98: FX | AJ98: Tra_EV_Batt-NCA_virgin | AK98: INDNGA | AL98: 0 | AM98: 2050, 2100 | AO98: FX | AP98: Tra_EV_Batt-LMO_virgin | AQ98: INDNGA | AR98: 0 | AS98: 2050, 2100 | AU98: FX | AV98: Tra_EV_Batt-LFP_virgin | AW98: INDNGA | AX98: 0 | AY98: 2050, 2100
K99: FX | L99: Tra_EV_Batt-NMC111_virgin | M99: INDOIL | N99: 0 | O99: 2050, 2100 | Q99: FX | R99: Tra_EV_Batt-NMC532_virgin | S99: INDOIL | T99: 0 | U99: 2050, 2100 | W99: FX | X99: Tra_EV_Batt-NMC622_virgin | Y99: INDOIL | Z99: 0 | AA99: 2050, 2100 | AC99: FX | AD99: Tra_EV_Batt-NMC811_virgin | AE99: INDOIL | AF99: 0 | AG99: 2050, 2100 | AI99: FX | AJ99: Tra_EV_Batt-NCA_virgin | AK99: INDOIL | AL99: 0 | AM99: 2050, 2100 | AO99: FX | AP99: Tra_EV_Batt-LMO_virgin | AQ99: INDOIL | AR99: 0 | AS99: 2050, 2100 | AU99: FX | AV99: Tra_EV_Batt-LFP_virgin | AW99: INDOIL | AX99: 0 | AY99: 2050, 2100
N106: 76.8 | T106: 71.3 | Z106: 71.2 | AF106: 71.2 | AL106: 71.2 | AR106: 71.2 | AX106: 71.2
N107: 202.6 | T107: 191.3 | Z107: 191.5 | AF107: 191.5 | AL107: 191.5 | AR107: 191.5 | AX107: 191.5
N108: 583.8 | T108: 556.1 | Z108: 557.9 | AF108: 557.9 | AL108: 557.9 | AR108: 557.9 | AX108: 557.9
N109: 127.5 | T109: 133.7 | Z109: 140.3 | AF109: 140.3 | AL109: 140.3 | AR109: 140.3 | AX109: 140.3
M114: ~TFM_UPD: attribute= INPUT | S114: ~TFM_UPD: attribute= INPUT | Y114: ~TFM_UPD: attribute= INPUT | AE114: ~TFM_UPD: attribute= INPUT | AK114: ~TFM_UPD: attribute= INPUT | AQ114: ~TFM_UPD: attribute= INPUT | AW114: ~TFM_UPD: attribute= INPUT
K115: limtype | L115: process | M115: cset_cn | N115: China | O115: year | Q115: limtype | R115: process | S115: cset_cn | T115: China | U115: year | W115: limtype | X115: process | Y115: cset_cn | Z115: China | AA115: year | AC115: limtype | AD115: process | AE115: cset_cn | AF115: China | AG115: year | AI115: limtype | AJ115: process | AK115: cset_cn | AL115: China | AM115: year | AO115: limtype | AP115: process | AQ115: cset_cn | AR115: China | AS115: year | AU115: limtype | AV115: process | AW115: cset_cn | AX115: China | AY115: year
K116: FX | L116: Tra_EV_Batt-NMC111_virgin | M116: INDELC | N116: =SUM(M26:M29) -> 1.0015 | O116: 2050, 2100 | Q116: FX | R116: Tra_EV_Batt-NMC532_virgin | S116: INDELC | T116: =SUM(S26:S29) -> 0.9633 | U116: 2050, 2100 | W116: FX | X116: Tra_EV_Batt-NMC622_virgin | Y116: INDELC | Z116: =SUM(Y26:Y29) -> 0.9719 | AA116: 2050, 2100 | AC116: FX | AD116: Tra_EV_Batt-NMC811_virgin | AE116: INDELC | AF116: =SUM(AE26:AE29) -> 0.9695 | AG116: 2050, 2100 | AI116: FX | AJ116: Tra_EV_Batt-NCA_virgin | AK116: INDELC | AL116: =SUM(AK26:AK29) -> 1.0412 | AM116: 2050, 2100 | AO116: FX | AP116: Tra_EV_Batt-LMO_virgin | AQ116: INDELC | AR116: =SUM(AQ26:AQ29) -> 0.5969 | AS116: 2050, 2100 | AU116: FX | AV116: Tra_EV_Batt-LFP_virgin | AW116: INDELC | AX116: =SUM(AW26:AW29) -> 0.7858 | AY116: 2050, 2100
K117: FX | L117: Tra_EV_Batt-NMC111_virgin | M117: INDCOA | N117: 0 | O117: 2050, 2100 | Q117: FX | R117: Tra_EV_Batt-NMC532_virgin | S117: INDCOA | T117: 0 | U117: 2050, 2100 | W117: FX | X117: Tra_EV_Batt-NMC622_virgin | Y117: INDCOA | Z117: 0 | AA117: 2050, 2100 | AC117: FX | AD117: Tra_EV_Batt-NMC811_virgin | AE117: INDCOA | AF117: 0 | AG117: 2050, 2100 | AI117: FX | AJ117: Tra_EV_Batt-NCA_virgin | AK117: INDCOA | AL117: 0 | AM117: 2050, 2100 | AO117: FX | AP117: Tra_EV_Batt-LMO_virgin | AQ117: INDCOA | AR117: 0 | AS117: 2050, 2100 | AU117: FX | AV117: Tra_EV_Batt-LFP_virgin | AW117: INDCOA | AX117: 0 | AY117: 2050, 2100
K118: FX | L118: Tra_EV_Batt-NMC111_virgin | M118: INDNGA | N118: 0 | O118: 2050, 2100 | Q118: FX | R118: Tra_EV_Batt-NMC532_virgin | S118: INDNGA | T118: 0 | U118: 2050, 2100 | W118: FX | X118: Tra_EV_Batt-NMC622_virgin | Y118: INDNGA | Z118: 0 | AA118: 2050, 2100 | AC118: FX | AD118: Tra_EV_Batt-NMC811_virgin | AE118: INDNGA | AF118: 0 | AG118: 2050, 2100 | AI118: FX | AJ118: Tra_EV_Batt-NCA_virgin | AK118: INDNGA | AL118: 0 | AM118: 2050, 2100 | AO118: FX | AP118: Tra_EV_Batt-LMO_virgin | AQ118: INDNGA | AR118: 0 | AS118: 2050, 2100 | AU118: FX | AV118: Tra_EV_Batt-LFP_virgin | AW118: INDNGA | AX118: 0 | AY118: 2050, 2100
K119: FX | L119: Tra_EV_Batt-NMC111_virgin | M119: INDOIL | N119: 0 | O119: 2050, 2100 | Q119: FX | R119: Tra_EV_Batt-NMC532_virgin | S119: INDOIL | T119: 0 | U119: 2050, 2100 | W119: FX | X119: Tra_EV_Batt-NMC622_virgin | Y119: INDOIL | Z119: 0 | AA119: 2050, 2100 | AC119: FX | AD119: Tra_EV_Batt-NMC811_virgin | AE119: INDOIL | AF119: 0 | AG119: 2050, 2100 | AI119: FX | AJ119: Tra_EV_Batt-NCA_virgin | AK119: INDOIL | AL119: 0 | AM119: 2050, 2100 | AO119: FX | AP119: Tra_EV_Batt-LMO_virgin | AQ119: INDOIL | AR119: 0 | AS119: 2050, 2100 | AU119: FX | AV119: Tra_EV_Batt-LFP_virgin | AW119: INDOIL | AX119: 0 | AY119: 2050, 2100
T122: 72 | Z122: 71.9 | AF122: 73.1 | AL122: 77.7 | AR122: 43.1 | AX122: 47.8
T123: 225.2 | Z123: 225.5 | AF123: 219.8 | AL123: 232.2 | AR123: 110.8 | AX123: 189.5
T124: 532.1 | Z124: 533.9 | AF124: 526.4 | AL124: 570.2 | AR124: 385.8 | AX124: 453
T125: 134 | Z125: 140.6 | AF125: 150.2 | AL125: 161.1 | AR125: 57.2 | AX125: 95.5

Sheet added_energyUse_for_US_1.0
A1: Pyrometallurgical | L1: ktonne/GWh | W1: if energy use for LFP and LMO=1.0*that for NMC611 | AB1: Fill the data gap of EverBatt, by using a sensitivity analysis | AF1: if energy use for LFP and LMO=1.15*that for NMC611 | AO1: if energy use for LFP and LMO=0.85*that for NMC611 | AZ1: Pyrometallurgical
A2: Location | B2: Energy use (PJ/GWh battery produced) | C2: Chemistry | V2: INPUT | AZ2: Location | BA2: Energy use (PJ/GWh battery produced) | BB2: Chemistry
C3: LCO | D3: NMC111 | E3: NMC532 | F3: NMC622 | G3: NMC811 | H3: NCA | I3: LMO | J3: LFP | L3: LCO | M3: NMC111 | N3: NMC532 | O3: NMC622 | P3: NMC811 | Q3: NCA | R3: LMO | S3: LFP | V3: PJ/ktonne | W3: NMC111 | X3: NMC532 | Y3: NMC622 | Z3: NMC811 | AA3: NCA | AB3: LMO | AC3: LFP | AF3: NMC111 | AG3: NMC532 | AH3: NMC622 | AI3: NMC811 | AJ3: NCA | AK3: LMO | AL3: LFP | AO3: NMC111 | AP3: NMC532 | AQ3: NMC622 | AR3: NMC811 | AS3: NCA | AT3: LMO | AU3: LFP | BB3: LCO | BC3: NMC111 | BD3: NMC532 | BE3: NMC622 | BF3: NMC811 | BG3: NCA | BH3: LMO | BI3: LFP
A4: US | B4: Total Energy | C4: =BB4/1000 -> 0.8374 | D4: =BC4/1000 -> 0.8081 | E4: =BD4/1000 -> 0.7705 | F4: =BE4/1000 -> 0.76 | G4: =BF4/1000 -> 0.7551 | H4: =BG4/1000 -> 0.796 | I4: =BH4/1000 -> 0.76 | J4: =BI4/1000 -> 0.76 | M4: 5.937 | N4: 5.845 | O4: 5.575 | P4: 5.276 | Q4: 5.363 | R4: 6.645 | S4: 5.654 | U4: US | V4: Total Energy | W4: =D4/M4 -> 0.13611251 | X4: =E4/N4 -> 0.13182207 | Y4: =F4/O4 -> 0.13632287 | Z4: =G4/P4 -> 0.14311979 | AA4: =H4/Q4 -> 0.14842439 | AB4: =I4/R4 -> 0.11437171 | AC4: =J4/S4 -> 0.13441811 | AF4: =W4 -> 0.13611251 | AG4: =X4 -> 0.13182207 | AH4: =Y4 -> 0.13632287 | AI4: =Z4 -> 0.14311979 | AJ4: =AA4 -> 0.14842439 | AK4: =AB4*1.15 -> 0.13152746 | AL4: =AC4*1.15 -> 0.15458083 | AO4: =W4 -> 0.13611251 | AP4: =X4 -> 0.13182207 | AQ4: =Y4 -> 0.13632287 | AR4: =Z4 -> 0.14311979 | AS4: =AA4 -> 0.14842439 | AT4: =AB4*0.85 -> 0.097215952 | AU4: =AC4*0.85 -> 0.11425539 | AZ4: US | BA4: Total Energy | BB4: 837.4 | BC4: 808.1 | BD4: 770.5 | BE4: 760 | BF4: 755.1 | BG4: 796 | BH4: 760 | BI4: 760
B5: Fossil fuels | C5: =BB5/1000 -> 0.7701 | D5: =BC5/1000 -> 0.7457 | E5: =BD5/1000 -> 0.7115 | F5: =BE5/1000 -> 0.7021 | G5: =BF5/1000 -> 0.6948 | H5: =BG5/1000 -> 0.7338 | I5: =BH5/1000 -> 0.7021 | J5: =BI5/1000 -> 0.7021 | M5: 5.937 | N5: 5.845 | O5: 5.575 | P5: 5.276 | Q5: 5.363 | R5: 6.645 | S5: 5.654 | V5: Fossil fuels | W5: =D5/M5 -> 0.12560216 | X5: =E5/N5 -> 0.12172797 | Y5: =F5/O5 -> 0.12593722 | Z5: =G5/P5 -> 0.13169067 | AA5: =H5/Q5 -> 0.1368264 | AB5: =I5/R5 -> 0.10565839 | AC5: =J5/S5 -> 0.12417757 | AF5: =W5 -> 0.12560216 | AG5: =X5 -> 0.12172797 | AH5: =Y5 -> 0.12593722 | AI5: =Z5 -> 0.13169067 | AJ5: =AA5 -> 0.1368264 | AK5: =AB5*1.15 -> 0.12150715 | AL5: =AC5*1.15 -> 0.14280421 | AO5: =W5 -> 0.12560216 | AP5: =X5 -> 0.12172797 | AQ5: =Y5 -> 0.12593722 | AR5: =Z5 -> 0.13169067 | AS5: =AA5 -> 0.1368264 | AT5: =AB5*0.85 -> 0.089809631 | AU5: =AC5*0.85 -> 0.10555094 | BA5: Fossil fuels | BB5: 770.1 | BC5: 745.7 | BD5: 711.5 | BE5: 702.1 | BF5: 694.8 | BG5: 733.8 | BH5: 702.1 | BI5: 702.1
B6: Coal | C6: =BB6/1000 -> 0.1986 | D6: =BC6/1000 -> 0.1717 | E6: =BD6/1000 -> 0.1611 | F6: =BE6/1000 -> 0.1579 | G6: =BF6/1000 -> 0.1521 | H6: =BG6/1000 -> 0.1588 | I6: =BH6/1000 -> 0.1579 | J6: =BI6/1000 -> 0.1579 | M6: 5.937 | N6: 5.845 | O6: 5.575 | P6: 5.276 | Q6: 5.363 | R6: 6.645 | S6: 5.654 | V6: Coal | W6: =D6/M6 -> 0.02892033 | X6: =E6/N6 -> 0.027562019 | Y6: =F6/O6 -> 0.02832287 | Z6: =G6/P6 -> 0.028828658 | AA6: =H6/Q6 -> 0.029610293 | AB6: =I6/R6 -> 0.023762227 | AC6: =J6/S6 -> 0.027927131 | AF6: =W6 -> 0.02892033 | AG6: =X6 -> 0.027562019 | AH6: =Y6 -> 0.02832287 | AI6: =Z6 -> 0.028828658 | AJ6: =AA6 -> 0.029610293 | AK6: =AB6*1.15 -> 0.027326561 | AL6: =AC6*1.15 -> 0.032116201 | AO6: =W6 -> 0.02892033 | AP6: =X6 -> 0.027562019 | AQ6: =Y6 -> 0.02832287 | AR6: =Z6 -> 0.028828658 | AS6: =AA6 -> 0.029610293 | AT6: =AB6*0.85 -> 0.020197893 | AU6: =AC6*0.85 -> 0.023738062 | BA6: Coal | BB6: 198.6 | BC6: 171.7 | BD6: 161.1 | BE6: 157.9 | BF6: 152.1 | BG6: 158.8 | BH6: 157.9 | BI6: 157.9
B7: Natural gas | C7: =BB7/1000 -> 0.487 | D7: =BC7/1000 -> 0.4967 | E7: =BD7/1000 -> 0.4758 | F7: =BE7/1000 -> 0.4705 | G7: =BF7/1000 -> 0.4665 | H7: =BG7/1000 -> 0.496 | I7: =BH7/1000 -> 0.4705 | J7: =BI7/1000 -> 0.4705 | M7: 5.937 | N7: 5.845 | O7: 5.575 | P7: 5.276 | Q7: 5.363 | R7: 6.645 | S7: 5.654 | V7: Natural gas | W7: =D7/M7 -> 0.083661782 | X7: =E7/N7 -> 0.081402908 | Y7: =F7/O7 -> 0.084394619 | Z7: =G7/P7 -> 0.088419257 | AA7: =H7/Q7 -> 0.092485549 | AB7: =I7/R7 -> 0.070805117 | AC7: =J7/S7 -> 0.083215423 | AF7: =W7 -> 0.083661782 | AG7: =X7 -> 0.081402908 | AH7: =Y7 -> 0.084394619 | AI7: =Z7 -> 0.088419257 | AJ7: =AA7 -> 0.092485549 | AK7: =AB7*1.15 -> 0.081425884 | AL7: =AC7*1.15 -> 0.095697736 | AO7: =W7 -> 0.083661782 | AP7: =X7 -> 0.081402908 | AQ7: =Y7 -> 0.084394619 | AR7: =Z7 -> 0.088419257 | AS7: =AA7 -> 0.092485549 | AT7: =AB7*0.85 -> 0.060184349 | AU7: =AC7*0.85 -> 0.070733109 | BA7: Natural gas | BB7: 487 | BC7: 496.7 | BD7: 475.8 | BE7: 470.5 | BF7: 466.5 | BG7: 496 | BH7: 470.5 | BI7: 470.5
B8: Petroleum | C8: =BB8/1000 -> 0.0845 | D8: =BC8/1000 -> 0.0773 | E8: =BD8/1000 -> 0.0745 | F8: =BE8/1000 -> 0.0736 | G8: =BF8/1000 -> 0.0761 | H8: =BG8/1000 -> 0.0789 | I8: =BH8/1000 -> 0.0736 | J8: =BI8/1000 -> 0.0736 | M8: 5.937 | N8: 5.845 | O8: 5.575 | P8: 5.276 | Q8: 5.363 | R8: 6.645 | S8: 5.654 | V8: Petroleum | W8: =D8/M8 -> 0.013020044 | X8: =E8/N8 -> 0.012745937 | Y8: =F8/O8 -> 0.013201794 | Z8: =G8/P8 -> 0.014423806 | AA8: =H8/Q8 -> 0.014711915 | AB8: =I8/R8 -> 0.011075997 | AC8: =J8/S8 -> 0.013017333 | AF8: =W8 -> 0.013020044 | AG8: =X8 -> 0.012745937 | AH8: =Y8 -> 0.013201794 | AI8: =Z8 -> 0.014423806 | AJ8: =AA8 -> 0.014711915 | AK8: =AB8*1.15 -> 0.012737397 | AL8: =AC8*1.15 -> 0.014969933 | AO8: =W8 -> 0.013020044 | AP8: =X8 -> 0.012745937 | AQ8: =Y8 -> 0.013201794 | AR8: =Z8 -> 0.014423806 | AS8: =AA8 -> 0.014711915 | AT8: =AB8*0.85 -> 0.0094145974 | AU8: =AC8*0.85 -> 0.011064733 | BA8: Petroleum | BB8: 84.5 | BC8: 77.3 | BD8: 74.5 | BE8: 73.6 | BF8: 76.1 | BG8: 78.9 | BH8: 73.6 | BI8: 73.6
A9: Korea | B9: Total Energy | C9: =BB9/1000 -> 0.855 | D9: =BC9/1000 -> 0.8241 | E9: =BD9/1000 -> 0.7857 | F9: =BE9/1000 -> 0.775 | G9: =BF9/1000 -> 0.7702 | H9: =BG9/1000 -> 0.8116 | I9: =BH9/1000 -> 0.775 | J9: =BI9/1000 -> 0.775 | M9: 5.937 | N9: 5.845 | O9: 5.575 | P9: 5.276 | Q9: 5.363 | R9: 6.645 | S9: 5.654 | U9: Korea | V9: Total Energy | W9: =D9/M9 -> 0.13880748 | X9: =E9/N9 -> 0.13442258 | Y9: =F9/O9 -> 0.13901345 | Z9: =G9/P9 -> 0.1459818 | AA9: =H9/Q9 -> 0.15133321 | AB9: =I9/R9 -> 0.11662904 | AC9: =J9/S9 -> 0.1370711 | AF9: =W9 -> 0.13880748 | AG9: =X9 -> 0.13442258 | AH9: =Y9 -> 0.13901345 | AI9: =Z9 -> 0.1459818 | AJ9: =AA9 -> 0.15133321 | AK9: =AB9*1.15 -> 0.1341234 | AL9: =AC9*1.15 -> 0.15763177 | AO9: =W9 -> 0.13880748 | AP9: =X9 -> 0.13442258 | AQ9: =Y9 -> 0.13901345 | AR9: =Z9 -> 0.1459818 | AS9: =AA9 -> 0.15133321 | AT9: =AB9*0.85 -> 0.099134688 | AU9: =AC9*0.85 -> 0.11651044 | AZ9: Korea | BA9: Total Energy | BB9: 855 | BC9: 824.1 | BD9: 785.7 | BE9: 775 | BF9: 770.2 | BG9: 811.6 | BH9: 775 | BI9: 775
B10: Fossil fuels | C10: =BB10/1000 -> 0.7888 | D10: =BC10/1000 -> 0.7626 | E10: =BD10/1000 -> 0.7275 | F10: =BE10/1000 -> 0.7179 | G10: =BF10/1000 -> 0.7107 | H10: =BG10/1000 -> 0.7503 | I10: =BH10/1000 -> 0.7179 | J10: =BI10/1000 -> 0.7179 | M10: 5.937 | N10: 5.845 | O10: 5.575 | P10: 5.276 | Q10: 5.363 | R10: 6.645 | S10: 5.654 | V10: Fossil fuels | W10: =D10/M10 -> 0.12844871 | X10: =E10/N10 -> 0.12446536 | Y10: =F10/O10 -> 0.1287713 | Z10: =G10/P10 -> 0.13470432 | AA10: =H10/Q10 -> 0.13990304 | AB10: =I10/R10 -> 0.10803612 | AC10: =J10/S10 -> 0.12697206 | AF10: =W10 -> 0.12844871 | AG10: =X10 -> 0.12446536 | AH10: =Y10 -> 0.1287713 | AI10: =Z10 -> 0.13470432 | AJ10: =AA10 -> 0.13990304 | AK10: =AB10*1.15 -> 0.12424153 | AL10: =AC10*1.15 -> 0.14601786 | AO10: =W10 -> 0.12844871 | AP10: =X10 -> 0.12446536 | AQ10: =Y10 -> 0.1287713 | AR10: =Z10 -> 0.13470432 | AS10: =AA10 -> 0.13990304 | AT10: =AB10*0.85 -> 0.0918307 | AU10: =AC10*0.85 -> 0.10792625 | BA10: Fossil fuels | BB10: 788.8 | BC10: 762.6 | BD10: 727.5 | BE10: 717.9 | BF10: 710.7 | BG10: 750.3 | BH10: 717.9 | BI10: 717.9
B11: Coal | C11: =BB11/1000 -> 0.2381 | D11: =BC11/1000 -> 0.2075 | E11: =BD11/1000 -> 0.1951 | F11: =BE11/1000 -> 0.1916 | G11: =BF11/1000 -> 0.186 | H11: =BG11/1000 -> 0.1938 | I11: =BH11/1000 -> 0.1916 | J11: =BI11/1000 -> 0.1916 | M11: 5.937 | N11: 5.845 | O11: 5.575 | P11: 5.276 | Q11: 5.363 | R11: 6.645 | S11: 5.654 | V11: Coal | W11: =D11/M11 -> 0.034950312 | X11: =E11/N11 -> 0.033378956 | Y11: =F11/O11 -> 0.034367713 | Z11: =G11/P11 -> 0.03525398 | AA11: =H11/Q11 -> 0.036136491 | AB11: =I11/R11 -> 0.02883371 | AC11: =J11/S11 -> 0.033887513 | AF11: =W11 -> 0.034950312 | AG11: =X11 -> 0.033378956 | AH11: =Y11 -> 0.034367713 | AI11: =Z11 -> 0.03525398 | AJ11: =AA11 -> 0.036136491 | AK11: =AB11*1.15 -> 0.033158766 | AL11: =AC11*1.15 -> 0.03897064 | AO11: =W11 -> 0.034950312 | AP11: =X11 -> 0.033378956 | AQ11: =Y11 -> 0.034367713 | AR11: =Z11 -> 0.03525398 | AS11: =AA11 -> 0.036136491 | AT11: =AB11*0.85 -> 0.024508653 | AU11: =AC11*0.85 -> 0.028804386 | BA11: Coal | BB11: 238.1 | BC11: 207.5 | BD11: 195.1 | BE11: 191.6 | BF11: 186 | BG11: 193.8 | BH11: 191.6 | BI11: 191.6
B12: Natural gas | C12: =BB12/1000 -> 0.4629 | D12: =BC12/1000 -> 0.4749 | E12: =BD12/1000 -> 0.4551 | F12: =BE12/1000 -> 0.45 | G12: =BF12/1000 -> 0.4459 | H12: =BG12/1000 -> 0.4747 | I12: =BH12/1000 -> 0.45 | J12: =BI12/1000 -> 0.45 | M12: 5.937 | N12: 5.845 | O12: 5.575 | P12: 5.276 | Q12: 5.363 | R12: 6.645 | S12: 5.654 | V12: Natural gas | W12: =D12/M12 -> 0.079989894 | X12: =E12/N12 -> 0.07786142 | Y12: =F12/O12 -> 0.080717489 | Z12: =G12/P12 -> 0.084514784 | AA12: =H12/Q12 -> 0.088513891 | AB12: =I12/R12 -> 0.06772009 | AC12: =J12/S12 -> 0.079589671 | AF12: =W12 -> 0.079989894 | AG12: =X12 -> 0.07786142 | AH12: =Y12 -> 0.080717489 | AI12: =Z12 -> 0.084514784 | AJ12: =AA12 -> 0.088513891 | AK12: =AB12*1.15 -> 0.077878104 | AL12: =AC12*1.15 -> 0.091528122 | AO12: =W12 -> 0.079989894 | AP12: =X12 -> 0.07786142 | AQ12: =Y12 -> 0.080717489 | AR12: =Z12 -> 0.084514784 | AS12: =AA12 -> 0.088513891 | AT12: =AB12*0.85 -> 0.057562077 | AU12: =AC12*0.85 -> 0.06765122 | BA12: Natural gas | BB12: 462.9 | BC12: 474.9 | BD12: 455.1 | BE12: 450 | BF12: 445.9 | BG12: 474.7 | BH12: 450 | BI12: 450
B13: Petroleum | C13: =BB13/1000 -> 0.0877 | D13: =BC13/1000 -> 0.0802 | E13: =BD13/1000 -> 0.0772 | F13: =BE13/1000 -> 0.0763 | G13: =BF13/1000 -> 0.0789 | H13: =BG13/1000 -> 0.0817 | I13: =BH13/1000 -> 0.0763 | J13: =BI13/1000 -> 0.0763 | M13: 5.937 | N13: 5.845 | O13: 5.575 | P13: 5.276 | Q13: 5.363 | R13: 6.645 | S13: 5.654 | V13: Petroleum | W13: =D13/M13 -> 0.013508506 | X13: =E13/N13 -> 0.01320787 | Y13: =F13/O13 -> 0.013686099 | Z13: =G13/P13 -> 0.014954511 | AA13: =H13/Q13 -> 0.015234011 | AB13: =I13/R13 -> 0.011482318 | AC13: =J13/S13 -> 0.013494871 | AF13: =W13 -> 0.013508506 | AG13: =X13 -> 0.01320787 | AH13: =Y13 -> 0.013686099 | AI13: =Z13 -> 0.014954511 | AJ13: =AA13 -> 0.015234011 | AK13: =AB13*1.15 -> 0.013204665 | AL13: =AC13*1.15 -> 0.015519102 | AO13: =W13 -> 0.013508506 | AP13: =X13 -> 0.01320787 | AQ13: =Y13 -> 0.013686099 | AR13: =Z13 -> 0.014954511 | AS13: =AA13 -> 0.015234011 | AT13: =AB13*0.85 -> 0.0097599699 | AU13: =AC13*0.85 -> 0.01147064 | BA13: Petroleum | BB13: 87.7 | BC13: 80.2 | BD13: 77.2 | BE13: 76.3 | BF13: 78.9 | BG13: 81.7 | BH13: 76.3 | BI13: 76.3
A14: China | B14: Total Energy | C14: =BB14/1000 -> 0.8705 | D14: =BC14/1000 -> 0.8381 | E14: =BD14/1000 -> 0.799 | F14: =BE14/1000 -> 0.7882 | G14: =BF14/1000 -> 0.7835 | H14: =BG14/1000 -> 0.8253 | I14: =BH14/1000 -> 0.7882 | J14: =BI14/1000 -> 0.7882 | M14: 5.937 | N14: 5.845 | O14: 5.575 | P14: 5.276 | Q14: 5.363 | R14: 6.645 | S14: 5.654 | U14: China | V14: Total Energy | W14: =D14/M14 -> 0.14116557 | X14: =E14/N14 -> 0.13669803 | Y14: =F14/O14 -> 0.14138117 | Z14: =G14/P14 -> 0.14850265 | AA14: =H14/Q14 -> 0.15388775 | AB14: =I14/R14 -> 0.1186155 | AC14: =J14/S14 -> 0.13940573 | AF14: =W14 -> 0.14116557 | AG14: =X14 -> 0.13669803 | AH14: =Y14 -> 0.14138117 | AI14: =Z14 -> 0.14850265 | AJ14: =AA14 -> 0.15388775 | AK14: =AB14*1.15 -> 0.13640783 | AL14: =AC14*1.15 -> 0.16031659 | AO14: =W14 -> 0.14116557 | AP14: =X14 -> 0.13669803 | AQ14: =Y14 -> 0.14138117 | AR14: =Z14 -> 0.14850265 | AS14: =AA14 -> 0.15388775 | AT14: =AB14*0.85 -> 0.10082318 | AU14: =AC14*0.85 -> 0.11849487 | AZ14: China | BA14: Total Energy | BB14: 870.5 | BC14: 838.1 | BD14: 799 | BE14: 788.2 | BF14: 783.5 | BG14: 825.3 | BH14: 788.2 | BI14: 788.2
B15: Fossil fuels | C15: =BB15/1000 -> 0.8012 | D15: =BC15/1000 -> 0.7738 | E15: =BD15/1000 -> 0.7382 | F15: =BE15/1000 -> 0.7285 | G15: =BF15/1000 -> 0.7214 | H15: =BG15/1000 -> 0.7613 | I15: =BH15/1000 -> 0.7285 | J15: =BI15/1000 -> 0.7285 | M15: 5.937 | N15: 5.845 | O15: 5.575 | P15: 5.276 | Q15: 5.363 | R15: 6.645 | S15: 5.654 | V15: Fossil fuels | W15: =D15/M15 -> 0.13033519 | X15: =E15/N15 -> 0.12629598 | Y15: =F15/O15 -> 0.13067265 | Z15: =G15/P15 -> 0.13673237 | AA15: =H15/Q15 -> 0.14195413 | AB15: =I15/R15 -> 0.1096313 | AC15: =J15/S15 -> 0.12884683 | AF15: =W15 -> 0.13033519 | AG15: =X15 -> 0.12629598 | AH15: =Y15 -> 0.13067265 | AI15: =Z15 -> 0.13673237 | AJ15: =AA15 -> 0.14195413 | AK15: =AB15*1.15 -> 0.126076 | AL15: =AC15*1.15 -> 0.14817386 | AO15: =W15 -> 0.13033519 | AP15: =X15 -> 0.12629598 | AQ15: =Y15 -> 0.13067265 | AR15: =Z15 -> 0.13673237 | AS15: =AA15 -> 0.14195413 | AT15: =AB15*0.85 -> 0.093186606 | AU15: =AC15*0.85 -> 0.10951981 | BA15: Fossil fuels | BB15: 801.2 | BC15: 773.8 | BD15: 738.2 | BE15: 728.5 | BF15: 721.4 | BG15: 761.3 | BH15: 728.5 | BI15: 728.5
B16: Coal | C16: =BB16/1000 -> 0.3021 | D16: =BC16/1000 -> 0.2654 | E16: =BD16/1000 -> 0.2502 | F16: =BE16/1000 -> 0.246 | G16: =BF16/1000 -> 0.2408 | H16: =BG16/1000 -> 0.2506 | I16: =BH16/1000 -> 0.246 | J16: =BI16/1000 -> 0.246 | M16: 5.937 | N16: 5.845 | O16: 5.575 | P16: 5.276 | Q16: 5.363 | R16: 6.645 | S16: 5.654 | V16: Coal | W16: =D16/M16 -> 0.044702712 | X16: =E16/N16 -> 0.042805817 | Y16: =F16/O16 -> 0.044125561 | Z16: =G16/P16 -> 0.045640637 | AA16: =H16/Q16 -> 0.046727578 | AB16: =I16/R16 -> 0.037020316 | AC16: =J16/S16 -> 0.04350902 | AF16: =W16 -> 0.044702712 | AG16: =X16 -> 0.042805817 | AH16: =Y16 -> 0.044125561 | AI16: =Z16 -> 0.045640637 | AJ16: =AA16 -> 0.046727578 | AK16: =AB16*1.15 -> 0.042573363 | AL16: =AC16*1.15 -> 0.050035373 | AO16: =W16 -> 0.044702712 | AP16: =X16 -> 0.042805817 | AQ16: =Y16 -> 0.044125561 | AR16: =Z16 -> 0.045640637 | AS16: =AA16 -> 0.046727578 | AT16: =AB16*0.85 -> 0.031467269 | AU16: =AC16*0.85 -> 0.036982667 | BA16: Coal | BB16: 302.1 | BC16: 265.4 | BD16: 250.2 | BE16: 246 | BF16: 240.8 | BG16: 250.6 | BH16: 246 | BI16: 246
B17: Natural gas | C17: =BB17/1000 -> 0.4137 | D17: =BC17/1000 -> 0.4304 | E17: =BD17/1000 -> 0.4127 | F17: =BE17/1000 -> 0.4081 | G17: =BF17/1000 -> 0.4037 | H17: =BG17/1000 -> 0.4311 | I17: =BH17/1000 -> 0.4081 | J17: =BI17/1000 -> 0.4081 | M17: 5.937 | N17: 5.845 | O17: 5.575 | P17: 5.276 | Q17: 5.363 | R17: 6.645 | S17: 5.654 | V17: Natural gas | W17: =D17/M17 -> 0.072494526 | X17: =E17/N17 -> 0.070607357 | Y17: =F17/O17 -> 0.073201794 | Z17: =G17/P17 -> 0.0765163 | AA17: =H17/Q17 -> 0.080384113 | AB17: =I17/R17 -> 0.061414597 | AC17: =J17/S17 -> 0.072178988 | AF17: =W17 -> 0.072494526 | AG17: =X17 -> 0.070607357 | AH17: =Y17 -> 0.073201794 | AI17: =Z17 -> 0.0765163 | AJ17: =AA17 -> 0.080384113 | AK17: =AB17*1.15 -> 0.070626787 | AL17: =AC17*1.15 -> 0.083005837 | AO17: =W17 -> 0.072494526 | AP17: =X17 -> 0.070607357 | AQ17: =Y17 -> 0.073201794 | AR17: =Z17 -> 0.0765163 | AS17: =AA17 -> 0.080384113 | AT17: =AB17*0.85 -> 0.052202408 | AU17: =AC17*0.85 -> 0.06135214 | BA17: Natural gas | BB17: 413.7 | BC17: 430.4 | BD17: 412.7 | BE17: 408.1 | BF17: 403.7 | BG17: 431.1 | BH17: 408.1 | BI17: 408.1
B18: Petroleum | C18: =BB18/1000 -> 0.0853 | D18: =BC18/1000 -> 0.0781 | E18: =BD18/1000 -> 0.0752 | F18: =BE18/1000 -> 0.0743 | G18: =BF18/1000 -> 0.0768 | H18: =BG18/1000 -> 0.0797 | I18: =BH18/1000 -> 0.0743 | J18: =BI18/1000 -> 0.0743 | M18: 5.937 | N18: 5.845 | O18: 5.575 | P18: 5.276 | Q18: 5.363 | R18: 6.645 | S18: 5.654 | V18: Petroleum | W18: =D18/M18 -> 0.013154792 | X18: =E18/N18 -> 0.012865697 | Y18: =F18/O18 -> 0.013327354 | Z18: =G18/P18 -> 0.014556482 | AA18: =H18/Q18 -> 0.014861085 | AB18: =I18/R18 -> 0.011181339 | AC18: =J18/S18 -> 0.013141139 | AF18: =W18 -> 0.013154792 | AG18: =X18 -> 0.012865697 | AH18: =Y18 -> 0.013327354 | AI18: =Z18 -> 0.014556482 | AJ18: =AA18 -> 0.014861085 | AK18: =AB18*1.15 -> 0.01285854 | AL18: =AC18*1.15 -> 0.01511231 | AO18: =W18 -> 0.013154792 | AP18: =X18 -> 0.012865697 | AQ18: =Y18 -> 0.013327354 | AR18: =Z18 -> 0.014556482 | AS18: =AA18 -> 0.014861085 | AT18: =AB18*0.85 -> 0.0095041384 | AU18: =AC18*0.85 -> 0.011169968 | BA18: Petroleum | BB18: 85.3 | BC18: 78.1 | BD18: 75.2 | BE18: 74.3 | BF18: 76.8 | BG18: 79.7 | BH18: 74.3 | BI18: 74.3
A21: Hydrometallurgical | AZ21: Hydrometallurgical
A22: Location | B22: Energy use (MJ/kWh battery produced) | C22: Chemistry | AZ22: Location | BA22: Energy use (MJ/kWh battery produced) | BB22: Chemistry
C23: LCO | D23: NMC111 | E23: NMC532 | F23: NMC622 | G23: NMC811 | H23: NCA | I23: LMO | J23: LFP | M23: NMC111 | N23: NMC532 | O23: NMC622 | P23: NMC811 | Q23: NCA | R23: LMO | S23: LFP | V23: PJ/ktonne | W23: NMC111 | X23: NMC532 | Y23: NMC622 | Z23: NMC811 | AA23: NCA | AB23: LMO | AC23: LFP | AF23: NMC111 | AG23: NMC532 | AH23: NMC622 | AI23: NMC811 | AJ23: NCA | AK23: LMO | AL23: LFP | AO23: NMC111 | AP23: NMC532 | AQ23: NMC622 | AR23: NMC811 | AS23: NCA | AT23: LMO | AU23: LFP | BB23: LCO | BC23: NMC111 | BD23: NMC532 | BE23: NMC622 | BF23: NMC811 | BG23: NCA | BH23: LMO | BI23: LFP
A24: US | B24: Total Energy | C24: =BB24/1000 -> 0.8898 | D24: =BC24/1000 -> 0.8432 | E24: =BD24/1000 -> 0.8038 | F24: =BE24/1000 -> 0.7946 | G24: =BF24/1000 -> 0.7665 | H24: =BG24/1000 -> 0.8066 | I24: =BH24/1000 -> 0.7946 | J24: =BI24/1000 -> 0.7946 | M24: 5.937 | N24: 5.845 | O24: 5.575 | P24: 5.276 | Q24: 5.363 | R24: 6.645 | S24: 5.654 | U24: US | V24: Total Energy | W24: =D24/M24 -> 0.14202459 | X24: =E24/N24 -> 0.13751925 | Y24: =F24/O24 -> 0.14252915 | Z24: =G24/P24 -> 0.14528052 | AA24: =H24/Q24 -> 0.1504009 | AB24: =I24/R24 -> 0.11957863 | AC24: =J24/S24 -> 0.14053767 | AF24: =W24 -> 0.14202459 | AG24: =X24 -> 0.13751925 | AH24: =Y24 -> 0.14252915 | AI24: =Z24 -> 0.14528052 | AJ24: =AA24 -> 0.1504009 | AK24: =AB24*1.15 -> 0.13751543 | AL24: =AC24*1.15 -> 0.16161832 | AO24: =W24 -> 0.14202459 | AP24: =X24 -> 0.13751925 | AQ24: =Y24 -> 0.14252915 | AR24: =Z24 -> 0.14528052 | AS24: =AA24 -> 0.1504009 | AT24: =AB24*0.85 -> 0.10164184 | AU24: =AC24*0.85 -> 0.11945702 | AZ24: US | BA24: Total Energy | BB24: 889.8 | BC24: 843.2 | BD24: 803.8 | BE24: 794.6 | BF24: 766.5 | BG24: 806.6 | BH24: 794.6 | BI24: 794.6
B25: Fossil fuels | C25: =BB25/1000 -> 0.8124 | D25: =BC25/1000 -> 0.7746 | E25: =BD25/1000 -> 0.739 | F25: =BE25/1000 -> 0.7307 | G25: =BF25/1000 -> 0.7045 | H25: =BG25/1000 -> 0.7424 | I25: =BH25/1000 -> 0.7307 | J25: =BI25/1000 -> 0.7307 | M25: 5.937 | N25: 5.845 | O25: 5.575 | P25: 5.276 | Q25: 5.363 | R25: 6.645 | S25: 5.654 | V25: Fossil fuels | W25: =D25/M25 -> 0.13046993 | X25: =E25/N25 -> 0.12643285 | Y25: =F25/O25 -> 0.13106726 | Z25: =G25/P25 -> 0.13352919 | AA25: =H25/Q25 -> 0.13842998 | AB25: =I25/R25 -> 0.10996238 | AC25: =J25/S25 -> 0.12923594 | AF25: =W25 -> 0.13046993 | AG25: =X25 -> 0.12643285 | AH25: =Y25 -> 0.13106726 | AI25: =Z25 -> 0.13352919 | AJ25: =AA25 -> 0.13842998 | AK25: =AB25*1.15 -> 0.12645673 | AL25: =AC25*1.15 -> 0.14862133 | AO25: =W25 -> 0.13046993 | AP25: =X25 -> 0.12643285 | AQ25: =Y25 -> 0.13106726 | AR25: =Z25 -> 0.13352919 | AS25: =AA25 -> 0.13842998 | AT25: =AB25*0.85 -> 0.093468021 | AU25: =AC25*0.85 -> 0.10985055 | BA25: Fossil fuels | BB25: 812.4 | BC25: 774.6 | BD25: 739 | BE25: 730.7 | BF25: 704.5 | BG25: 742.4 | BH25: 730.7 | BI25: 730.7
B26: Coal | C26: =BB26/1000 -> 0.1699 | D26: =BC26/1000 -> 0.1497 | E26: =BD26/1000 -> 0.1418 | F26: =BE26/1000 -> 0.1399 | G26: =BF26/1000 -> 0.1359 | H26: =BG26/1000 -> 0.1408 | I26: =BH26/1000 -> 0.1399 | J26: =BI26/1000 -> 0.1399 | M26: 5.937 | N26: 5.845 | O26: 5.575 | P26: 5.276 | Q26: 5.363 | R26: 6.645 | S26: 5.654 | V26: Coal | W26: =D26/M26 -> 0.025214755 | X26: =E26/N26 -> 0.024260051 | Y26: =F26/O26 -> 0.02509417 | Z26: =G26/P26 -> 0.02575815 | AA26: =H26/Q26 -> 0.026253962 | AB26: =I26/R26 -> 0.021053424 | AC26: =J26/S26 -> 0.024743544 | AF26: =W26 -> 0.025214755 | AG26: =X26 -> 0.024260051 | AH26: =Y26 -> 0.02509417 | AI26: =Z26 -> 0.02575815 | AJ26: =AA26 -> 0.026253962 | AK26: =AB26*1.15 -> 0.024211437 | AL26: =AC26*1.15 -> 0.028455076 | AO26: =W26 -> 0.025214755 | AP26: =X26 -> 0.024260051 | AQ26: =Y26 -> 0.02509417 | AR26: =Z26 -> 0.02575815 | AS26: =AA26 -> 0.026253962 | AT26: =AB26*0.85 -> 0.01789541 | AU26: =AC26*0.85 -> 0.021032013 | BA26: Coal | BB26: 169.9 | BC26: 149.7 | BD26: 141.8 | BE26: 139.9 | BF26: 135.9 | BG26: 140.8 | BH26: 139.9 | BI26: 139.9
B27: Natural gas | C27: =BB27/1000 -> 0.5978 | D27: =BC27/1000 -> 0.5807 | E27: =BD27/1000 -> 0.554 | F27: =BE27/1000 -> 0.5478 | G27: =BF27/1000 -> 0.526 | H27: =BG27/1000 -> 0.5575 | I27: =BH27/1000 -> 0.5478 | J27: =BI27/1000 -> 0.5478 | M27: 5.937 | N27: 5.845 | O27: 5.575 | P27: 5.276 | Q27: 5.363 | R27: 6.645 | S27: 5.654 | V27: Natural gas | W27: =D27/M27 -> 0.097810342 | X27: =E27/N27 -> 0.094781865 | Y27: =F27/O27 -> 0.09826009 | Z27: =G27/P27 -> 0.09969674 | AA27: =H27/Q27 -> 0.10395301 | AB27: =I27/R27 -> 0.082437923 | AC27: =J27/S27 -> 0.09688716 | AF27: =W27 -> 0.097810342 | AG27: =X27 -> 0.094781865 | AH27: =Y27 -> 0.09826009 | AI27: =Z27 -> 0.09969674 | AJ27: =AA27 -> 0.10395301 | AK27: =AB27*1.15 -> 0.094803612 | AL27: =AC27*1.15 -> 0.11142023 | AO27: =W27 -> 0.097810342 | AP27: =X27 -> 0.094781865 | AQ27: =Y27 -> 0.09826009 | AR27: =Z27 -> 0.09969674 | AS27: =AA27 -> 0.10395301 | AT27: =AB27*0.85 -> 0.070072235 | AU27: =AC27*0.85 -> 0.082354086 | BA27: Natural gas | BB27: 597.8 | BC27: 580.7 | BD27: 554 | BE27: 547.8 | BF27: 526 | BG27: 557.5 | BH27: 547.8 | BI27: 547.8
B28: Petroleum | C28: =BB28/1000 -> 0.085 | D28: =BC28/1000 -> 0.0786 | E28: =BD28/1000 -> 0.0763 | F28: =BE28/1000 -> 0.0759 | G28: =BF28/1000 -> 0.0737 | H28: =BG28/1000 -> 0.076 | I28: =BH28/1000 -> 0.0759 | J28: =BI28/1000 -> 0.0759 | M28: 5.937 | N28: 5.845 | O28: 5.575 | P28: 5.276 | Q28: 5.363 | R28: 6.645 | S28: 5.654 | V28: Petroleum | W28: =D28/M28 -> 0.01323901 | X28: =E28/N28 -> 0.013053892 | Y28: =F28/O28 -> 0.01361435 | Z28: =G28/P28 -> 0.013968916 | AA28: =H28/Q28 -> 0.014171173 | AB28: =I28/R28 -> 0.011422122 | AC28: =J28/S28 -> 0.013424125 | AF28: =W28 -> 0.01323901 | AG28: =X28 -> 0.013053892 | AH28: =Y28 -> 0.01361435 | AI28: =Z28 -> 0.013968916 | AJ28: =AA28 -> 0.014171173 | AK28: =AB28*1.15 -> 0.01313544 | AL28: =AC28*1.15 -> 0.015437743 | AO28: =W28 -> 0.01323901 | AP28: =X28 -> 0.013053892 | AQ28: =Y28 -> 0.01361435 | AR28: =Z28 -> 0.013968916 | AS28: =AA28 -> 0.014171173 | AT28: =AB28*0.85 -> 0.0097088036 | AU28: =AC28*0.85 -> 0.011410506 | BA28: Petroleum | BB28: 85 | BC28: 78.6 | BD28: 76.3 | BE28: 75.9 | BF28: 73.7 | BG28: 76 | BH28: 75.9 | BI28: 75.9
A29: Korea | B29: Total Energy | C29: =BB29/1000 -> 0.9068 | D29: =BC29/1000 -> 0.8586 | E29: =BD29/1000 -> 0.8184 | F29: =BE29/1000 -> 0.8091 | G29: =BF29/1000 -> 0.7811 | H29: =BG29/1000 -> 0.8217 | I29: =BH29/1000 -> 0.8091 | J29: =BI29/1000 -> 0.8091 | M29: 5.937 | N29: 5.845 | O29: 5.575 | P29: 5.276 | Q29: 5.363 | R29: 6.645 | S29: 5.654 | U29: Korea | V29: Total Energy | W29: =D29/M29 -> 0.14461849 | X29: =E29/N29 -> 0.14001711 | Y29: =F29/O29 -> 0.14513004 | Z29: =G29/P29 -> 0.14804776 | AA29: =H29/Q29 -> 0.15321648 | AB29: =I29/R29 -> 0.12176072 | AC29: =J29/S29 -> 0.14310223 | AF29: =W29 -> 0.14461849 | AG29: =X29 -> 0.14001711 | AH29: =Y29 -> 0.14513004 | AI29: =Z29 -> 0.14804776 | AJ29: =AA29 -> 0.15321648 | AK29: =AB29*1.15 -> 0.14002483 | AL29: =AC29*1.15 -> 0.16456756 | AO29: =W29 -> 0.14461849 | AP29: =X29 -> 0.14001711 | AQ29: =Y29 -> 0.14513004 | AR29: =Z29 -> 0.14804776 | AS29: =AA29 -> 0.15321648 | AT29: =AB29*0.85 -> 0.10349661 | AU29: =AC29*0.85 -> 0.12163689 | AZ29: Korea | BA29: Total Energy | BB29: 906.8 | BC29: 858.6 | BD29: 818.4 | BE29: 809.1 | BF29: 781.1 | BG29: 821.7 | BH29: 809.1 | BI29: 809.1
B30: Fossil fuels | C30: =BB30/1000 -> 0.8303 | D30: =BC30/1000 -> 0.7909 | E30: =BD30/1000 -> 0.7545 | F30: =BE30/1000 -> 0.746 | G30: =BF30/1000 -> 0.7199 | H30: =BG30/1000 -> 0.7584 | I30: =BH30/1000 -> 0.746 | J30: =BI30/1000 -> 0.746 | M30: 5.937 | N30: 5.845 | O30: 5.575 | P30: 5.276 | Q30: 5.363 | R30: 6.645 | S30: 5.654 | V30: Fossil fuels | W30: =D30/M30 -> 0.13321543 | X30: =E30/N30 -> 0.12908469 | Y30: =F30/O30 -> 0.13381166 | Z30: =G30/P30 -> 0.13644807 | AA30: =H30/Q30 -> 0.14141339 | AB30: =I30/R30 -> 0.11226486 | AC30: =J30/S30 -> 0.13194199 | AF30: =W30 -> 0.13321543 | AG30: =X30 -> 0.12908469 | AH30: =Y30 -> 0.13381166 | AI30: =Z30 -> 0.13644807 | AJ30: =AA30 -> 0.14141339 | AK30: =AB30*1.15 -> 0.12910459 | AL30: =AC30*1.15 -> 0.15173329 | AO30: =W30 -> 0.13321543 | AP30: =X30 -> 0.12908469 | AQ30: =Y30 -> 0.13381166 | AR30: =Z30 -> 0.13644807 | AS30: =AA30 -> 0.14141339 | AT30: =AB30*0.85 -> 0.095425132 | AU30: =AC30*0.85 -> 0.11215069 | BA30: Fossil fuels | BB30: 830.3 | BC30: 790.9 | BD30: 754.5 | BE30: 746 | BF30: 719.9 | BG30: 758.4 | BH30: 746 | BI30: 746
B31: Coal | C31: =BB31/1000 -> 0.2079 | D31: =BC31/1000 -> 0.1842 | E31: =BD31/1000 -> 0.1746 | F31: =BE31/1000 -> 0.1724 | G31: =BF31/1000 -> 0.1687 | H31: =BG31/1000 -> 0.1747 | I31: =BH31/1000 -> 0.1724 | J31: =BI31/1000 -> 0.1724 | M31: 5.937 | N31: 5.845 | O31: 5.575 | P31: 5.276 | Q31: 5.363 | R31: 6.645 | S31: 5.654 | V31: Coal | W31: =D31/M31 -> 0.031025771 | X31: =E31/N31 -> 0.029871685 | Y31: =F31/O31 -> 0.030923767 | Z31: =G31/P31 -> 0.031974981 | AA31: =H31/Q31 -> 0.032575051 | AB31: =I31/R31 -> 0.025944319 | AC31: =J31/S31 -> 0.030491687 | AF31: =W31 -> 0.031025771 | AG31: =X31 -> 0.029871685 | AH31: =Y31 -> 0.030923767 | AI31: =Z31 -> 0.031974981 | AJ31: =AA31 -> 0.032575051 | AK31: =AB31*1.15 -> 0.029835967 | AL31: =AC31*1.15 -> 0.03506544 | AO31: =W31 -> 0.031025771 | AP31: =X31 -> 0.029871685 | AQ31: =Y31 -> 0.030923767 | AR31: =Z31 -> 0.031974981 | AS31: =AA31 -> 0.032575051 | AT31: =AB31*0.85 -> 0.022052671 | AU31: =AC31*0.85 -> 0.025917934 | BA31: Coal | BB31: 207.9 | BC31: 184.2 | BD31: 174.6 | BE31: 172.4 | BF31: 168.7 | BG31: 174.7 | BH31: 172.4 | BI31: 172.4
B32: Natural gas | C32: =BB32/1000 -> 0.5747 | D32: =BC32/1000 -> 0.5597 | E32: =BD32/1000 -> 0.534 | F32: =BE32/1000 -> 0.528 | G32: =BF32/1000 -> 0.5061 | H32: =BG32/1000 -> 0.5369 | I32: =BH32/1000 -> 0.528 | J32: =BI32/1000 -> 0.528 | M32: 5.937 | N32: 5.845 | O32: 5.575 | P32: 5.276 | Q32: 5.363 | R32: 6.645 | S32: 5.654 | V32: Natural gas | W32: =D32/M32 -> 0.094273202 | X32: =E32/N32 -> 0.091360137 | Y32: =F32/O32 -> 0.09470852 | Z32: =G32/P32 -> 0.095924943 | AA32: =H32/Q32 -> 0.10011188 | AB32: =I32/R32 -> 0.079458239 | AC32: =J32/S32 -> 0.093385214 | AF32: =W32 -> 0.094273202 | AG32: =X32 -> 0.091360137 | AH32: =Y32 -> 0.09470852 | AI32: =Z32 -> 0.095924943 | AJ32: =AA32 -> 0.10011188 | AK32: =AB32*1.15 -> 0.091376975 | AL32: =AC32*1.15 -> 0.107393 | AO32: =W32 -> 0.094273202 | AP32: =X32 -> 0.091360137 | AQ32: =Y32 -> 0.09470852 | AR32: =Z32 -> 0.095924943 | AS32: =AA32 -> 0.10011188 | AT32: =AB32*0.85 -> 0.067539503 | AU32: =AC32*0.85 -> 0.079377432 | BA32: Natural gas | BB32: 574.7 | BC32: 559.7 | BD32: 534 | BE32: 528 | BF32: 506.1 | BG32: 536.9 | BH32: 528 | BI32: 528
B33: Petroleum | C33: =BB33/1000 -> 0.088 | D33: =BC33/1000 -> 0.0814 | E33: =BD33/1000 -> 0.079 | F33: =BE33/1000 -> 0.0785 | G33: =BF33/1000 -> 0.0764 | H33: =BG33/1000 -> 0.0787 | I33: =BH33/1000 -> 0.0785 | J33: =BI33/1000 -> 0.0785 | M33: 5.937 | N33: 5.845 | O33: 5.575 | P33: 5.276 | Q33: 5.363 | R33: 6.645 | S33: 5.654 | V33: Petroleum | W33: =D33/M33 -> 0.013710628 | X33: =E33/N33 -> 0.013515825 | Y33: =F33/O33 -> 0.014080717 | Z33: =G33/P33 -> 0.014480667 | AA33: =H33/Q33 -> 0.014674622 | AB33: =I33/R33 -> 0.011813394 | AC33: =J33/S33 -> 0.013883976 | AF33: =W33 -> 0.013710628 | AG33: =X33 -> 0.013515825 | AH33: =Y33 -> 0.014080717 | AI33: =Z33 -> 0.014480667 | AJ33: =AA33 -> 0.014674622 | AK33: =AB33*1.15 -> 0.013585403 | AL33: =AC33*1.15 -> 0.015966572 | AO33: =W33 -> 0.013710628 | AP33: =X33 -> 0.013515825 | AQ33: =Y33 -> 0.014080717 | AR33: =Z33 -> 0.014480667 | AS33: =AA33 -> 0.014674622 | AT33: =AB33*0.85 -> 0.010041384 | AU33: =AC33*0.85 -> 0.01180138 | BA33: Petroleum | BB33: 88 | BC33: 81.4 | BD33: 79 | BE33: 78.5 | BF33: 76.4 | BG33: 78.7 | BH33: 78.5 | BI33: 78.5
A34: China | B34: Total Energy | C34: =BB34/1000 -> 0.9217 | D34: =BC34/1000 -> 0.8721 | E34: =BD34/1000 -> 0.8313 | F34: =BE34/1000 -> 0.8218 | G34: =BF34/1000 -> 0.794 | H34: =BG34/1000 -> 0.835 | I34: =BH34/1000 -> 0.8218 | J34: =BI34/1000 -> 0.8218 | M34: 5.937 | N34: 5.845 | O34: 5.575 | P34: 5.276 | Q34: 5.363 | R34: 6.645 | S34: 5.654 | U34: China | V34: Total Energy | W34: =D34/M34 -> 0.14689237 | X34: =E34/N34 -> 0.14222412 | Y34: =F34/O34 -> 0.14740807 | Z34: =G34/P34 -> 0.1504928 | AA34: =H34/Q34 -> 0.15569644 | AB34: =I34/R34 -> 0.12367193 | AC34: =J34/S34 -> 0.14534843 | AF34: =W34 -> 0.14689237 | AG34: =X34 -> 0.14222412 | AH34: =Y34 -> 0.14740807 | AI34: =Z34 -> 0.1504928 | AJ34: =AA34 -> 0.15569644 | AK34: =AB34*1.15 -> 0.14222272 | AL34: =AC34*1.15 -> 0.16715069 | AO34: =W34 -> 0.14689237 | AP34: =X34 -> 0.14222412 | AQ34: =Y34 -> 0.14740807 | AR34: =Z34 -> 0.1504928 | AS34: =AA34 -> 0.15569644 | AT34: =AB34*0.85 -> 0.10512114 | AU34: =AC34*0.85 -> 0.12354616 | AZ34: China | BA34: Total Energy | BB34: 921.7 | BC34: 872.1 | BD34: 831.3 | BE34: 821.8 | BF34: 794 | BG34: 835 | BH34: 821.8 | BI34: 821.8
B35: Fossil fuels | C35: =BB35/1000 -> 0.8422 | D35: =BC35/1000 -> 0.8018 | E35: =BD35/1000 -> 0.7648 | F35: =BE35/1000 -> 0.7562 | G35: =BF35/1000 -> 0.7302 | H35: =BG35/1000 -> 0.7691 | I35: =BH35/1000 -> 0.7562 | J35: =BI35/1000 -> 0.7562 | M35: 5.937 | N35: 5.845 | O35: 5.575 | P35: 5.276 | Q35: 5.363 | R35: 6.645 | S35: 5.654 | V35: Fossil fuels | W35: =D35/M35 -> 0.13505137 | X35: =E35/N35 -> 0.13084688 | Y35: =F35/O35 -> 0.13564126 | Z35: =G35/P35 -> 0.1384003 | AA35: =H35/Q35 -> 0.14340854 | AB35: =I35/R35 -> 0.11379985 | AC35: =J35/S35 -> 0.13374602 | AF35: =W35 -> 0.13505137 | AG35: =X35 -> 0.13084688 | AH35: =Y35 -> 0.13564126 | AI35: =Z35 -> 0.1384003 | AJ35: =AA35 -> 0.14340854 | AK35: =AB35*1.15 -> 0.13086983 | AL35: =AC35*1.15 -> 0.15380792 | AO35: =W35 -> 0.13505137 | AP35: =X35 -> 0.13084688 | AQ35: =Y35 -> 0.13564126 | AR35: =Z35 -> 0.1384003 | AS35: =AA35 -> 0.14340854 | AT35: =AB35*0.85 -> 0.096729872 | AU35: =AC35*0.85 -> 0.11368412 | BA35: Fossil fuels | BB35: 842.2 | BC35: 801.8 | BD35: 764.8 | BE35: 756.2 | BF35: 730.2 | BG35: 769.1 | BH35: 756.2 | BI35: 756.2
B36: Coal | C36: =BB36/1000 -> 0.2694 | D36: =BC36/1000 -> 0.2401 | E36: =BD36/1000 -> 0.2278 | F36: =BE36/1000 -> 0.2249 | G36: =BF36/1000 -> 0.2217 | H36: =BG36/1000 -> 0.2296 | I36: =BH36/1000 -> 0.2249 | J36: =BI36/1000 -> 0.2249 | M36: 5.937 | N36: 5.845 | O36: 5.575 | P36: 5.276 | Q36: 5.363 | R36: 6.645 | S36: 5.654 | V36: Coal | W36: =D36/M36 -> 0.0404413 | X36: =E36/N36 -> 0.038973482 | Y36: =F36/O36 -> 0.040340807 | Z36: =G36/P36 -> 0.04202047 | AA36: =H36/Q36 -> 0.042811859 | AB36: =I36/R36 -> 0.033844996 | AC36: =J36/S36 -> 0.039777149 | AF36: =W36 -> 0.0404413 | AG36: =X36 -> 0.038973482 | AH36: =Y36 -> 0.040340807 | AI36: =Z36 -> 0.04202047 | AJ36: =AA36 -> 0.042811859 | AK36: =AB36*1.15 -> 0.038921746 | AL36: =AC36*1.15 -> 0.045743721 | AO36: =W36 -> 0.0404413 | AP36: =X36 -> 0.038973482 | AQ36: =Y36 -> 0.040340807 | AR36: =Z36 -> 0.04202047 | AS36: =AA36 -> 0.042811859 | AT36: =AB36*0.85 -> 0.028768247 | AU36: =AC36*0.85 -> 0.033810577 | BA36: Coal | BB36: 269.4 | BC36: 240.1 | BD36: 227.8 | BE36: 224.9 | BF36: 221.7 | BG36: 229.6 | BH36: 224.9 | BI36: 224.9
B37: Natural gas | C37: =BB37/1000 -> 0.5273 | D37: =BC37/1000 -> 0.5167 | E37: =BD37/1000 -> 0.4931 | F37: =BE37/1000 -> 0.4875 | G37: =BF37/1000 -> 0.4653 | H37: =BG37/1000 -> 0.4946 | I37: =BH37/1000 -> 0.4875 | J37: =BI37/1000 -> 0.4875 | M37: 5.937 | N37: 5.845 | O37: 5.575 | P37: 5.276 | Q37: 5.363 | R37: 6.645 | S37: 5.654 | V37: Natural gas | W37: =D37/M37 -> 0.087030487 | X37: =E37/N37 -> 0.084362703 | Y37: =F37/O37 -> 0.087443946 | Z37: =G37/P37 -> 0.088191812 | AA37: =H37/Q37 -> 0.092224501 | AB37: =I37/R37 -> 0.073363431 | AC37: =J37/S37 -> 0.086222144 | AF37: =W37 -> 0.087030487 | AG37: =X37 -> 0.084362703 | AH37: =Y37 -> 0.087443946 | AI37: =Z37 -> 0.088191812 | AJ37: =AA37 -> 0.092224501 | AK37: =AB37*1.15 -> 0.084367946 | AL37: =AC37*1.15 -> 0.099155465 | AO37: =W37 -> 0.087030487 | AP37: =X37 -> 0.084362703 | AQ37: =Y37 -> 0.087443946 | AR37: =Z37 -> 0.088191812 | AS37: =AA37 -> 0.092224501 | AT37: =AB37*0.85 -> 0.062358916 | AU37: =AC37*0.85 -> 0.073288822 | BA37: Natural gas | BB37: 527.3 | BC37: 516.7 | BD37: 493.1 | BE37: 487.5 | BF37: 465.3 | BG37: 494.6 | BH37: 487.5 | BI37: 487.5
B38: Petroleum | C38: =BB38/1000 -> 0.0858 | D38: =BC38/1000 -> 0.0793 | E38: =BD38/1000 -> 0.0771 | F38: =BE38/1000 -> 0.0766 | G38: =BF38/1000 -> 0.0744 | H38: =BG38/1000 -> 0.0767 | I38: =BH38/1000 -> 0.0766 | J38: =BI38/1000 -> 0.0766 | M38: 5.937 | N38: 5.845 | O38: 5.575 | P38: 5.276 | Q38: 5.363 | R38: 6.645 | S38: 5.654 | V38: Petroleum | W38: =D38/M38 -> 0.013356914 | X38: =E38/N38 -> 0.013190761 | Y38: =F38/O38 -> 0.01373991 | Z38: =G38/P38 -> 0.014101592 | AA38: =H38/Q38 -> 0.014301697 | AB38: =I38/R38 -> 0.011527464 | AC38: =J38/S38 -> 0.013547931 | AF38: =W38 -> 0.013356914 | AG38: =X38 -> 0.013190761 | AH38: =Y38 -> 0.01373991 | AI38: =Z38 -> 0.014101592 | AJ38: =AA38 -> 0.014301697 | AK38: =AB38*1.15 -> 0.013256584 | AL38: =AC38*1.15 -> 0.01558012 | AO38: =W38 -> 0.013356914 | AP38: =X38 -> 0.013190761 | AQ38: =Y38 -> 0.01373991 | AR38: =Z38 -> 0.014101592 | AS38: =AA38 -> 0.014301697 | AT38: =AB38*0.85 -> 0.0097983446 | AU38: =AC38*0.85 -> 0.011515741 | BA38: Petroleum | BB38: 85.8 | BC38: 79.3 | BD38: 77.1 | BE38: 76.6 | BF38: 74.4 | BG38: 76.7 | BH38: 76.6 | BI38: 76.6
A41: Direct | AZ41: Direct
A42: Location | B42: Energy use (MJ/kWh battery produced) | C42: Chemistry | AZ42: Location | BA42: Energy use (MJ/kWh battery produced) | BB42: Chemistry
C43: LCO | D43: NMC111 | E43: NMC532 | F43: NMC622 | G43: NMC811 | H43: NCA | I43: LMO | J43: LFP | M43: NMC111 | N43: NMC532 | O43: NMC622 | P43: NMC811 | Q43: NCA | R43: LMO | S43: LFP | V43: PJ/ktonne | W43: NMC111 | X43: NMC532 | Y43: NMC622 | Z43: NMC811 | AA43: NCA | AB43: LMO | AC43: LFP | AF43: NMC111 | AG43: NMC532 | AH43: NMC622 | AI43: NMC811 | AJ43: NCA | AK43: LMO | AL43: LFP | AO43: NMC111 | AP43: NMC532 | AQ43: NMC622 | AR43: NMC811 | AS43: NCA | AT43: LMO | AU43: LFP | BB43: LCO | BC43: NMC111 | BD43: NMC532 | BE43: NMC622 | BF43: NMC811 | BG43: NCA | BH43: LMO | BI43: LFP
A44: US | B44: Total Energy | C44: =BB44/1000 -> 0.6652 | D44: =BC44/1000 -> 0.5864 | E44: =BD44/1000 -> 0.5679 | F44: =BE44/1000 -> 0.5636 | G44: =BF44/1000 -> 0.5409 | H44: =BG44/1000 -> 0.5521 | I44: =BH44/1000 -> 0.5636 | J44: =BI44/1000 -> 0.5636 | M44: 5.937 | N44: 5.845 | O44: 5.575 | P44: 5.276 | Q44: 5.363 | R44: 6.645 | S44: 5.654 | U44: US | V44: Total Energy | W44: =D44/M44 -> 0.098770423 | X44: =E44/N44 -> 0.097159966 | Y44: =F44/O44 -> 0.10109417 | Z44: =G44/P44 -> 0.10252085 | AA44: =H44/Q44 -> 0.10294611 | AB44: =I44/R44 -> 0.084815651 | AC44: =J44/S44 -> 0.099681641 | AF44: =W44 -> 0.098770423 | AG44: =X44 -> 0.097159966 | AH44: =Y44 -> 0.10109417 | AI44: =Z44 -> 0.10252085 | AJ44: =AA44 -> 0.10294611 | AK44: =AB44*1.15 -> 0.097537998 | AL44: =AC44*1.15 -> 0.11463389 | AO44: =W44 -> 0.098770423 | AP44: =X44 -> 0.097159966 | AQ44: =Y44 -> 0.10109417 | AR44: =Z44 -> 0.10252085 | AS44: =AA44 -> 0.10294611 | AT44: =AB44*0.85 -> 0.072093303 | AU44: =AC44*0.85 -> 0.084729395 | AZ44: US | BA44: Total Energy | BB44: 665.2 | BC44: 586.4 | BD44: 567.9 | BE44: 563.6 | BF44: 540.9 | BG44: 552.1 | BH44: 563.6 | BI44: 563.6
B45: Fossil fuels | C45: =BB45/1000 -> 0.6092 | D45: =BC45/1000 -> 0.5396 | E45: =BD45/1000 -> 0.5232 | F45: =BE45/1000 -> 0.5193 | G45: =BF45/1000 -> 0.499 | H45: =BG45/1000 -> 0.5091 | I45: =BH45/1000 -> 0.5193 | J45: =BI45/1000 -> 0.5193 | M45: 5.937 | N45: 5.845 | O45: 5.575 | P45: 5.276 | Q45: 5.363 | R45: 6.645 | S45: 5.654 | V45: Fossil fuels | W45: =D45/M45 -> 0.090887654 | X45: =E45/N45 -> 0.089512404 | Y45: =F45/O45 -> 0.093147982 | Z45: =G45/P45 -> 0.094579227 | AA45: =H45/Q45 -> 0.094928212 | AB45: =I45/R45 -> 0.078148984 | AC45: =J45/S45 -> 0.09184648 | AF45: =W45 -> 0.090887654 | AG45: =X45 -> 0.089512404 | AH45: =Y45 -> 0.093147982 | AI45: =Z45 -> 0.094579227 | AJ45: =AA45 -> 0.094928212 | AK45: =AB45*1.15 -> 0.089871332 | AL45: =AC45*1.15 -> 0.10562345 | AO45: =W45 -> 0.090887654 | AP45: =X45 -> 0.089512404 | AQ45: =Y45 -> 0.093147982 | AR45: =Z45 -> 0.094579227 | AS45: =AA45 -> 0.094928212 | AT45: =AB45*0.85 -> 0.066426637 | AU45: =AC45*0.85 -> 0.078069508 | BA45: Fossil fuels | BB45: 609.2 | BC45: 539.6 | BD45: 523.2 | BE45: 519.3 | BF45: 499 | BG45: 509.1 | BH45: 519.3 | BI45: 519.3
B46: Coal | C46: =BB46/1000 -> 0.1429 | D46: =BC46/1000 -> 0.1194 | E46: =BD46/1000 -> 0.114 | F46: =BE46/1000 -> 0.1127 | G46: =BF46/1000 -> 0.1061 | H46: =BG46/1000 -> 0.1094 | I46: =BH46/1000 -> 0.1127 | J46: =BI46/1000 -> 0.1127 | M46: 5.937 | N46: 5.845 | O46: 5.575 | P46: 5.276 | Q46: 5.363 | R46: 6.645 | S46: 5.654 | V46: Coal | W46: =D46/M46 -> 0.020111167 | X46: =E46/N46 -> 0.019503849 | Y46: =F46/O46 -> 0.020215247 | Z46: =G46/P46 -> 0.020109932 | AA46: =H46/Q46 -> 0.02039903 | AB46: =I46/R46 -> 0.01696012 | AC46: =J46/S46 -> 0.019932791 | AF46: =W46 -> 0.020111167 | AG46: =X46 -> 0.019503849 | AH46: =Y46 -> 0.020215247 | AI46: =Z46 -> 0.020109932 | AJ46: =AA46 -> 0.02039903 | AK46: =AB46*1.15 -> 0.019504138 | AL46: =AC46*1.15 -> 0.02292271 | AO46: =W46 -> 0.020111167 | AP46: =X46 -> 0.019503849 | AQ46: =Y46 -> 0.020215247 | AR46: =Z46 -> 0.020109932 | AS46: =AA46 -> 0.02039903 | AT46: =AB46*0.85 -> 0.014416102 | AU46: =AC46*0.85 -> 0.016942872 | BA46: Coal | BB46: 142.9 | BC46: 119.4 | BD46: 114 | BE46: 112.7 | BF46: 106.1 | BG46: 109.4 | BH46: 112.7 | BI46: 112.7
