Workbook
Name Cars_12: '[1]TechRep-Doc'!#REF!
Name ddddd: [2]AGR_Fuels!$A$2
Name DISCRATE: '[1]TechRep-Doc'!#REF!
Name FID_1: [3]AGR_Fuels!$A$2
Name GROWTH: '[1]TechRep-Doc'!#REF!
Name GROWTH_TID: '[1]TechRep-Doc'!#REF!
Name INVCOST: '[1]TechRep-Doc'!#REF!
Name LIFE: '[1]TechRep-Doc'!#REF!
Name NAs_CCAR: '[1]TechRep-Doc'!#REF!
Name SETS: '[1]TechRep-Doc'!#REF!
Name TRTGAB005: '[1]TechRep-Doc'!#REF!
Name TRTGAC005: '[1]TechRep-Doc'!#REF!
Name Trucks_15: '[1]TechRep-Doc'!#REF!
Name TSUB_COST: '[1]TechRep-Doc'!#REF!
Name x: [1]AGR_Fuels!$A$2

Sheet Discuss_log
B2: Discuss log: 02/17 | C2: to input EFF for recycling processes; validate the cost (learning rate); lower and upper values [throughout should increase with time]
C3: Manufacture costs for different batteries
C4: Make sure one approach is correct, then incorporate other two
C5: Website for categorizing countries;
C6: We will keep detagling cost because amit is also not sure about decommining
C8: Migrate to Trans | D8: Flo_bound for different mining; you don't need to seperate them to different processes

Sheet Cover
B7: Techno-economic assumptions of the PRIMES-TREMOVE transport model
B10: © E3-Modelling

Sheet Small_cars
B1: Modelled economic possibilities for reducing specific energy consumption by transport mode/equipment and fuel/technology over time
B2: © E3-Modelling
B5: Reference values for Small size ICE gasoline
B6: 2015
B7: Energy consumption | C7: lt/100 km | D7: 5.4692719
B8: Capital cost | C8: Euro15 /veh | D8: 14228.271
B10: Reduction of specific energy consumption relative to 2015 gasoline vehicle (%) | C10: ICE Small size gasoline car
C13: 2020 | D13: 2030 | E13: 2040 | F13: 2050
B14: 0.14660195 | C14: 14411.641 | D14: 14288.29 | E14: 14288.29 | F14: 14288.29
B15: 0.24660195 | C15: 15078.096 | D15: 14591.542 | E15: 14591.542 | F15: 14591.542
B16: 0.34660195 | C16: 16731.894 | D16: 15344.176 | E16: 15344.176 | F16: 15344.176
B17: 0.39660195 | C17: 18944.887 | D17: 16114.335 | E17: 16114.335 | F17: 16114.335
B18: 0.44660195 | C18: 38658.679 | D18: 18014.252 | E18: 18014.252 | F18: 18014.252
B19: 0.49660195 | C19: 114048 | D19: 37206.372 | E19: 37206.372 | F19: 37206.372
B24: Reduction of specific energy consumption relative to 2015 gasoline vehicle (%) | C24: ICE Small size hybrid gasoline car
C27: 2020 | D27: 2030 | E27: 2040 | F27: 2050
B28: 0.19160195 | C28: 16485.6 | D28: 15586.91 | E28: 15586.91 | F28: 15586.91
B29: 0.29160195 | C29: 16616.3 | D29: 15731.46 | E29: 15731.46 | F29: 15731.46
B30: 0.34160195 | C30: 16732.15 | D30: 15858.84 | E30: 15858.84 | F30: 15858.84
B31: 0.39160195 | C31: 17029.8 | D31: 16087.56 | E31: 16087.56 | F31: 16087.56
B32: 0.44160195 | C32: 17472.24 | D32: 16395.8 | E32: 16395.8 | F32: 16395.8
B33: 0.49160195 | C33: 26028.09 | D33: 16921.19 | E33: 16921.19 | F33: 16921.19
B34: 0.54160195 | C34: 103040.24 | D34: 31789.08 | E34: 31789.08 | F34: 31789.08
B39: Reduction of specific energy consumption relative to 2015 gasoline vehicle (%) | C39: ICE Small size plug-in hybrid gasoline car
C42: 2020 | D42: 2030 | E42: 2040 | F42: 2050
B43: 0.72160195 | C43: 20812.713 | D43: 17365.357 | E43: 16391.882 | F43: 16107.962
B44: 0.73160195 | C44: 20851.39 | D44: 17382.308 | E44: 16398.045 | F44: 16110.409
B45: 0.74410195 | C45: 20931.943 | D45: 17404.545 | E45: 16408.443 | F45: 16116.834
B46: 0.75410195 | C46: 21037.784 | D46: 17418.007 | E46: 16417.16 | F46: 16124.089
B47: 0.76410195 | C47: 21236.317 | D47: 17424.3 | E47: 16427.426 | F47: 16136.084
B48: 0.81160195 | C48: 59492.373 | D48: 18038.155 | E48: 16838.025 | F48: 16485.136
B49: 0.81910195 | C49: 103206.42 | D49: 18410.743 | E49: 17196.049 | F49: 16848.2
B50: 0.82660195 | D50: 35985.742 | E50: 34084.03 | F50: 33973.934
B55: Reference values for small size ICE diesel
B56: 2015
B57: Energy consumption | C57: lt/100 km | D57: 4.0003418
B58: Capital cost | C58: Euro15 /veh | D58: 16512.16
B60: Reduction of specific energy consumption relative to 2015 diesel vehicle (%) | C60: ICE Small size diesel car
C63: 2020 | D63: 2030 | E63: 2040 | F63: 2050
B64: 0.23896485 | C64: 17256.927 | D64: 16675.841 | E64: 16675.841 | F64: 16675.841
B65: 0.33896485 | C65: 19112.483 | D65: 17481.945 | E65: 17481.945 | F65: 17481.945
B66: 0.38896485 | C66: 21419.927 | D66: 18276.201 | E66: 18276.201 | F66: 18276.201
B67: 0.43896485 | C67: 44400.856 | D67: 20035.427 | E67: 20035.427 | F67: 20035.427
B68: 0.48896485 | C68: 116626 | D68: 36262.297 | E68: 36262.297 | F68: 36262.297
B73: Reduction of specific energy consumption relative to 2015 diesel vehicle (%) | C73: ICE Small size hybrid diesel car
C76: 2020 | D76: 2030 | E76: 2040 | F76: 2050
B77: 0.17146485 | C77: 19066.91 | D77: 18176.84 | E77: 18176.84 | F77: 18176.84
B78: 0.27146485 | C78: 19180.33 | D78: 18254.98 | E78: 18254.98 | F78: 18254.98
B79: 0.32146485 | C79: 19323.27 | D79: 18345.73 | E79: 18345.73 | F79: 18345.73
B80: 0.37146485 | C80: 19554.53 | D80: 18467.83 | E80: 18467.83 | F80: 18467.83
B81: 0.42146485 | C81: 19974.78 | D81: 18654.37 | E81: 18654.37 | F81: 18654.37
B82: 0.47146485 | C82: 27825.81 | D82: 18925.79 | E82: 18925.79 | F82: 18925.79
B83: 0.52146485 | C83: 99526.92 | D83: 24378.61 | E83: 24378.61 | F83: 24378.61
B88: Reduction of specific energy consumption relative to 2015 diesel vehicle (%) | C88: ICE Small size plug-in hybrid diesel car
C91: 2020 | D91: 2030 | E91: 2040 | F91: 2050
B92: 0.73896485 | C92: 23212.776 | D92: 19821.21 | E92: 18883.579 | F92: 18610.113
B93: 0.74896485 | C93: 23245.172 | D93: 19835.329 | E93: 18887.394 | F93: 18610.319
B94: 0.75896485 | C94: 23332.8 | D94: 19856.709 | E94: 18901.435 | F94: 18622.116
B95: 0.76896485 | C95: 23598.521 | D95: 19920.859 | E95: 18954.95 | F95: 18673.332
B96: 0.77896485 | C96: 24105.637 | D96: 19990.49 | E96: 19029.987 | F96: 18752.478
B97: 0.82146485 | C97: 62041.575 | D97: 20649.568 | E97: 19513.091 | F97: 19185.966
B98: 0.82646485 | C98: 105784.42 | D98: 36812.187 | E98: 35043.902 | F98: 34935.424
B103: 2020
B104: Energy consumption of Small size battery electric car | C104: kWh/km | D104: 0.135
B106: Electric range (km) | C106: Small size battery electric car
C109: 2020 | D109: 2030 | E109: 2040 | F109: 2050
B110: 120 | C110: 18953.276 | D110: 15896.261 | E110: 15352.157 | F110: 15163.734
B111: 160 | C111: 20746.585 | D111: 16045.585 | E111: 15452.771 | F111: 15247.48
B112: 200 | C112: 22539.895 | D112: 16341.058 | E112: 15651.86 | F112: 15413.19
B113: 250 | C113: 24861.977 | D113: 16915.091 | E113: 16038.642 | F113: 15735.127
B114: 300 | C114: 27184.059 | D114: 17489.124 | E114: 16425.423 | F114: 16057.063
B115: 350 | C115: 30343.491 | D115: 18183.462 | E115: 16815.645 | F115: 16381.863
B116: 400 | C116: 33742.127 | D116: 18912.547 | E116: 17205.866 | F116: 16706.662
B117: 500 | C117: 41257.013 | D117: 20642.286 | E117: 18136.629 | F117: 17356.26
B121: Energy consumption (kg H2/100km) | C121: Small size hydrogen fuel cell
C124: 2020 | D124: 2030 | E124: 2040 | F124: 2050
B125: 0.82547333 | C125: 38790.251 | D125: 26275.832 | E125: 21981.459 | F125: 20924.257
B126: 0.7900959 | C126: 38995.391 | D126: 26441.686 | E126: 22123.271 | F126: 21062.236
B127: 0.75471847 | C127: 39349.341 | D127: 26607.54 | E127: 22265.083 | F127: 21200.215
B128: 0.71934104 | C128: 41112.187 | D128: 26773.393 | E128: 22406.895 | F128: 21338.194
B129: 0.6882089 | C129: 41503.385 | D129: 27942.637 | E129: 22548.707 | F129: 21476.173
B130: 0.6662749 | C130: 41725.472 | D130: 28117.475 | E130: 22690.519 | F130: 21614.152
B131: 0.64622769 | C131: 41947.559 | D131: 28292.313 | E131: 22832.331 | F131: 21752.131
B132: 0.63561446 | C132: 42169.646 | D132: 28467.151 | E132: 22974.142 | F132: 21890.11

Sheet Large_cars
B1: Modelled economic possibilities for reducing specific energy consumption by transport mode/equipment and fuel/technology over time
B2: © E3-Modelling
B5: Reference values for Large size ICE gasoline
B6: 2015
B7: Energy consumption | C7: lt/100 km | D7: 7.8951872
B8: Capital cost | C8: Euro15 /veh | D8: 37057.81
B10: Reduction of specific energy consumption relative to 2015 gasoline vehicle (%) | C10: ICE Large size gasoline car
C13: 2020 | D13: 2030 | E13: 2040 | F13: 2050
B14: 0.098944858 | C14: 37317.461 | D14: 37171.82 | E14: 37171.82 | F14: 37171.82
B15: 0.19894486 | C15: 38176.103 | D15: 37390.028 | E15: 37390.028 | F15: 37390.028
B16: 0.29894486 | C16: 40102.528 | D16: 37818.503 | E16: 37818.503 | F16: 37818.503
B17: 0.34894486 | C17: 42408.539 | D17: 38408.139 | E17: 38408.139 | F17: 38408.139
B18: 0.39894486 | C18: 48739.818 | D18: 39463.251 | E18: 39463.251 | F18: 39463.251
B19: 0.44894486 | C19: 103044.93 | D19: 42665.919 | E19: 42665.919 | F19: 42665.919
B24: Reduction of specific energy consumption relative to 2015 gasoline vehicle (%) | C24: ICE Large size hybrid gasoline car
C27: 2020 | D27: 2030 | E27: 2040 | F27: 2050
B28: 0.24644486 | C28: 40649.729 | D28: 39285.929 | E28: 39285.929 | F28: 39285.929
B29: 0.34644486 | C29: 40906.889 | D29: 39430.919 | E29: 39430.919 | F29: 39430.919
B30: 0.39644486 | C30: 41410.249 | D30: 39592.029 | E30: 39592.029 | F30: 39592.029
B31: 0.44644486 | C31: 42124.729 | D31: 39729.289 | E31: 39729.289 | F31: 39729.289
B32: 0.49644486 | C32: 44259.829 | D32: 39901.229 | E32: 39901.229 | F32: 39901.229
B33: 0.54644486 | C33: 81512.519 | D33: 40354.459 | E33: 40354.459 | F33: 40354.459
B34: 0.59644486 | C34: 136921.63 | D34: 48595.519 | E34: 48595.519 | F34: 48595.519
B39: Reduction of specific energy consumption relative to 2015 gasoline vehicle (%) | C39: ICE Large size plug-in hybrid gasoline car
C42: 2020 | D42: 2030 | E42: 2040 | F42: 2050
B43: 0.67394486 | C43: 46420.589 | D43: 41366.35 | E43: 40062.051 | F43: 39681.645
B44: 0.68394486 | C44: 46586.715 | D44: 41403.064 | E44: 40074.719 | F44: 39685.998
B45: 0.69644486 | C45: 46895.555 | D45: 41450.09 | E45: 40091.643 | F45: 39692.546
B46: 0.70644486 | C46: 47296.934 | D46: 41477.605 | E46: 40099.993 | F46: 39694.219
B47: 0.71644486 | C47: 48114.027 | D47: 41493.429 | E47: 40105.023 | F47: 39695.499
B48: 0.76394486 | C48: 108321.21 | D48: 42684.171 | E48: 40858.055 | F48: 40312.216
B49: 0.77144486 | D49: 42729.638 | E49: 40901.744 | F49: 40356.521
B55: Reference values for Large size ICE diesel
B56: 2015
B57: Energy consumption | C57: lt/100 km | D57: 6.7325109
B58: Capital cost | C58: Euro15 /veh | D58: 42530.904
B60: Reduction of specific energy consumption relative to 2015 diesel vehicle (%) | C60: ICE Large size diesel car
C63: 2020 | D63: 2030 | E63: 2040 | F63: 2050
B64: 0.18117419 | C64: 43323.557 | D64: 42722.785 | E64: 42722.785 | F64: 42722.785
B65: 0.28117419 | C65: 45065.867 | D65: 43554.306 | E65: 43554.306 | F65: 43554.306
B66: 0.33117419 | C66: 46536.114 | D66: 44274.696 | E66: 44274.696 | F66: 44274.696
B67: 0.38117419 | C67: 50470.017 | D67: 45260.77 | E67: 45260.77 | F67: 45260.77
B68: 0.43117419 | C68: 71223.764 | D68: 47971.372 | E68: 47971.372 | F68: 47971.372
B73: Reduction of specific energy consumption relative to 2015 diesel vehicle (%) | C73: ICE Large size hybrid diesel car
C76: 2020 | D76: 2030 | E76: 2040 | F76: 2050
B77: 0.19867419 | C77: 46595.729 | D77: 45231.929 | E77: 45231.929 | F77: 45231.929
B78: 0.29867419 | C78: 46781.209 | D78: 45333.649 | E78: 45333.649 | F78: 45333.649
B79: 0.34867419 | C79: 46979.609 | D79: 45448.659 | E79: 45448.659 | F79: 45448.659
B80: 0.39867419 | C80: 47323.989 | D80: 45639.799 | E80: 45639.799 | F80: 45639.799
B81: 0.44867419 | C81: 48053.099 | D81: 45910.379 | E81: 45910.379 | F81: 45910.379
B82: 0.49867419 | C82: 60232.279 | D82: 46323.459 | E82: 46323.459 | F82: 46323.459
B83: 0.54867419 | C83: 142867.63 | D83: 58030.009 | E83: 58030.009 | F83: 58030.009
B88: Reduction of specific energy consumption relative to 2015 diesel vehicle (%) | C88: ICE Large size plug-in hybrid diesel car
C91: 2020 | D91: 2030 | E91: 2040 | F91: 2050
B92: 0.68117419 | C92: 51440.746 | D92: 46706.708 | E92: 45580.134 | F92: 45251.562
B93: 0.69117419 | C93: 51577.485 | D93: 46741.39 | E93: 45593.93 | F93: 45258.217
B94: 0.70117419 | C94: 51744.739 | D94: 46767.865 | E94: 45609.606 | F94: 45270.446
B95: 0.71117419 | C95: 52142.26 | D95: 46815.239 | E95: 45655.128 | F95: 45316.609
B96: 0.72117419 | C96: 89000.577 | D96: 46947.331 | E96: 45791.821 | F96: 45458.894
B97: 0.76367419 | C97: 132026.04 | D97: 49050.935 | E97: 47340.133 | F97: 46851.329
B98: 0.76867419 | D98: 73908.59 | E98: 71226.086 | F98: 71073.554
B103: 2020
B104: Energy consumption of Large size battery electric car | C104: kWh/km | D104: 0.18
B106: Electric range (km) | C106: Large size battery electric car
C109: 2020 | D109: 2030 | E109: 2040 | F109: 2050
B110: 120 | C110: 42701.459 | D110: 38806.664 | E110: 38236.182 | F110: 38038.624
B111: 160 | C111: 45139.259 | D111: 39153.77 | E111: 38470.061 | F111: 38233.293
B112: 200 | C112: 47577.06 | D112: 39967.902 | E112: 39018.62 | F112: 38689.884
B113: 250 | C113: 50737.378 | D113: 40844.314 | E113: 39609.144 | F113: 39181.404
B114: 300 | C114: 53897.697 | D114: 41720.725 | E114: 40199.667 | F114: 39672.924
B115: 350 | C115: 58161.014 | D115: 42772.794 | E115: 40796.39 | F115: 40169.605
B116: 400 | C116: 62750.17 | D116: 43877.999 | E116: 41393.113 | F116: 40666.285
B117: 500 | C117: 72906.004 | D117: 46493.982 | E117: 42807.71 | F117: 41659.646
B121: Energy consumption (kg H2/100km) | C121: Large size hydrogen fuel cell
C124: 2020 | D124: 2030 | E124: 2040 | F124: 2050
B125: 1.2112765 | C125: 79718.091 | D125: 61463.516 | E125: 52764.062 | F125: 50622.403
B126: 1.1593647 | C126: 80087.344 | D126: 61762.052 | E126: 53019.324 | F126: 50870.765
B127: 1.1074528 | C127: 80720.835 | D127: 62060.589 | E127: 53274.585 | F127: 51119.127
B128: 1.055541 | C128: 83856.453 | D128: 62359.126 | E128: 53529.846 | F128: 51367.49
B129: 1.0036291 | C129: 84556.535 | D129: 64439.801 | E129: 53785.108 | F129: 51615.852
B130: 0.95171728 | C130: 84956.292 | D130: 64754.51 | E130: 54040.369 | F130: 51864.215
B131: 0.89980543 | C131: 85356.049 | D131: 65069.219 | E131: 54295.63 | F131: 52112.577
B132: 0.84789358 | C132: 85755.806 | D132: 65383.927 | E132: 54550.892 | F132: 52360.939

Sheet Medium_cars
B1: Modelled economic possibilities for reducing specific energy consumption by transport mode/equipment and fuel/technology over time | Q1: gsl | R1: ICE medium size gasoline car | S1: ="Trd_car_"&Q1 -> Trd_car_gsl
B2: © E3-Modelling | I2: 0.052009938 | J2: GJ/kg LNG | Q2: gsl-hyb | R2: ICE medium size hybrid gasoline car | S2: ="Trd_car_"&Q2 -> Trd_car_gsl-hyb
I3: =31536000/10^9 -> 0.031536 | J3: GJ/lt Gasoline | Q3: gsl-pih | R3: ICE medium size plug-in hybrid gasoline car | S3: ="Trd_car_"&Q3 -> Trd_car_gsl-pih
I4: 0.038 | J4: GJ/lt Diesel | Q4: dsl | R4: ICE medium size diesel car | S4: ="Trd_car_"&Q4 -> Trd_car_dsl
I5: =1.406/26.137 -> 0.053793473 | J5: GJ/kg CNG | Q5: dsl-hyb | R5: ICE medium size hybrid diesel car | S5: ="Trd_car_"&Q5 -> Trd_car_dsl-hyb
I6: 0.02559 | J6: GJ/lt LPG | Q6: dsl-pih | R6: ICE medium size plug-in hybrid diesel car | S6: ="Trd_car_"&Q6 -> Trd_car_dsl-pih
Q7: cng | R7: ICE medium size CNG car | S7: ="Trd_car_"&Q7 -> Trd_car_cng
Q8: lpg | R8: ICE medium size LPG car | S8: ="\I:Trd_car_"&Q8 -> \I:Trd_car_lpg
Q9: E85 | R9: ICE medium size E85 flex-fuel car | S9: ="\I:Trd_car_"&Q9 -> \I:Trd_car_E85
B10: Reference values for medium size ICE gasoline | Q10: elc | R10: Medium size battery electric car | S10: ="Trd_car_"&Q10 -> Trd_car_elc
B11: 2015 | Q11: hh2 | R11: Medium size hydrogen fuel cell | S11: ="Trd_car_"&Q11 -> Trd_car_hh2
B12: Energy consumption | C12: lt/100 km | D12: 6.8039045 | G12: =D12*$I$3/100*10^9/10^6 -> 2.1456793 | I12: =1/G12 -> 0.46605287
B13: Capital cost | C13: Euro15 /veh | D13: 19114.108 | I13: bvkm/PJ | S13: 0.9015
K15: ~FI_T: UP~EUR15~INVCOST | S15: ~FI_Process
I16: EFF | J16: *process | K16: Process | L16: Comm-OUT | M16: =C20 -> 2020 | N16: =D20 -> 2030 | O16: =E20 -> 2040 | P16: =F20 -> 2050 | Q16: FLO_MARK | S16: Sets | T16: TechName | U16: TechDesc | V16: Tact | W16: Tcap
B17: Reduction of specific energy consumption relative to 2015 gasoline vehicle (%) | C17: ICE medium size gasoline car | J17: =IFERROR(VLOOKUP(C17,$R$1:$S$11,2,FALSE),J16) -> Trd_car_gsl | K17: =IFERROR(IF(VALUE(C17)>2020,J17&"_"&TEXT(B17*100,"00"),"\I:"),"\I:") -> \I: | L17: =LEFT(K17,7) -> \I: | M17: =IF($K17="\I:","",C17) | N17: =IF($K17="\I:","",D17) | O17: =IF($K17="\I:","",E17) | P17: =IF($K17="\I:","",F17) | S17: DMD | T17: =K17 -> \I: | U17: =OFFSET($S$1,MATCH(J17,$S$1:$S$11,0)-1,-1)&" -- "&TEXT(B17,"00%") -> ICE medium size gasoline car -- Reduction of specific energy consumption relative to 2015 gasoline vehicle (%) | V17: Bvkm | W17: million vehicles
J18: =IFERROR(VLOOKUP(C18,$R$1:$S$11,2,FALSE),J17) -> Trd_car_gsl | K18: =IFERROR(IF(VALUE(C18)>2020,J18&"_"&TEXT(B18*100,"00"),"\I:"),"\I:") -> \I: | L18: =LEFT(K18,7) -> \I: | M18: =IF($K18="\I:","",C18) | N18: =IF($K18="\I:","",D18) | O18: =IF($K18="\I:","",E18) | P18: =IF($K18="\I:","",F18) | S18: DMD | T18: =K18 -> \I: | U18: =OFFSET($S$1,MATCH(J18,$S$1:$S$11,0)-1,-1)&" -- "&TEXT(B18,"00%") -> ICE medium size gasoline car -- 00% | V18: Bvkm | W18: million vehicles
J19: =IFERROR(VLOOKUP(C19,$R$1:$S$11,2,FALSE),J18) -> Trd_car_gsl | K19: =IFERROR(IF(VALUE(C19)>2020,J19&"_"&TEXT(B19*100,"00"),"\I:"),"\I:") -> \I: | L19: =LEFT(K19,7) -> \I: | M19: =IF($K19="\I:","",C19) | N19: =IF($K19="\I:","",D19) | O19: =IF($K19="\I:","",E19) | P19: =IF($K19="\I:","",F19) | S19: DMD | T19: =K19 -> \I: | U19: =OFFSET($S$1,MATCH(J19,$S$1:$S$11,0)-1,-1)&" -- "&TEXT(B19,"00%") -> ICE medium size gasoline car -- 00% | V19: Bvkm | W19: million vehicles
B20: 0 | C20: 2020 | D20: 2030 | E20: 2040 | F20: 2050 | I20: 1 | J20: =IFERROR(VLOOKUP(C20,$R$1:$S$11,2,FALSE),J19) -> Trd_car_gsl | K20: =IFERROR(IF(VALUE(C20)>200,J20&"_"&TEXT(B20*100,"00"),"\I:"),"\I:") -> Trd_car_gsl_00 | L20: =LEFT(K20,7) -> Trd_car | M20: =D13 -> 19114.108 | S20: DMD | T20: =K20 -> Trd_car_gsl_00 | U20: =OFFSET($S$1,MATCH(J20,$S$1:$S$11,0)-1,-1)&" -- "&TEXT(B20,"00%") -> ICE medium size gasoline car -- 00% | V20: Bvkm | W20: million vehicles
B21: 0.13362396 | C21: 19378.329 | D21: 19184.954 | E21: 19184.954 | F21: 19184.954 | I21: =(1+B21) -> 1.133624 | J21: =IFERROR(VLOOKUP(C21,$R$1:$S$11,2,FALSE),J20) -> Trd_car_gsl | K21: =IFERROR(IF(VALUE(C21)>2020,J21&"_"&TEXT(B21*100,"00"),"\I:"),"\I:") -> Trd_car_gsl_13 | L21: =LEFT(K21,7) -> Trd_car | M21: =IF($K21="\I:","",C21) -> 19378.329 | N21: =IF($K21="\I:","",D21) -> 19184.954 | O21: =IF($K21="\I:","",E21) -> 19184.954 | P21: =IF($K21="\I:","",F21) -> 19184.954 | S21: DMD | T21: =K21 -> Trd_car_gsl_13 | U21: =OFFSET($S$1,MATCH(J21,$S$1:$S$11,0)-1,-1)&" -- "&TEXT(B21,"00%") -> ICE medium size gasoline car -- 13% | V21: Bvkm | W21: million vehicles
B22: 0.23362396 | C22: 20194.176 | D22: 19445.906 | E22: 19445.906 | F22: 19445.906 | I22: =(1+B22) -> 1.233624 | J22: =IFERROR(VLOOKUP(C22,$R$1:$S$11,2,FALSE),J21) -> Trd_car_gsl | K22: =IFERROR(IF(VALUE(C22)>2020,J22&"_"&TEXT(B22*100,"00"),"\I:"),"\I:") -> Trd_car_gsl_23 | L22: =LEFT(K22,7) -> Trd_car | M22: =IF($K22="\I:","",C22) -> 20194.176 | N22: =IF($K22="\I:","",D22) -> 19445.906 | O22: =IF($K22="\I:","",E22) -> 19445.906 | P22: =IF($K22="\I:","",F22) -> 19445.906 | S22: DMD | T22: =K22 -> Trd_car_gsl_23 | U22: =OFFSET($S$1,MATCH(J22,$S$1:$S$11,0)-1,-1)&" -- "&TEXT(B22,"00%") -> ICE medium size gasoline car -- 23% | V22: Bvkm | W22: million vehicles
B23: 0.33362396 | C23: 21957.324 | D23: 20077.205 | E23: 20077.205 | F23: 20077.205 | I23: =(1+B23) -> 1.333624 | J23: =IFERROR(VLOOKUP(C23,$R$1:$S$11,2,FALSE),J22) -> Trd_car_gsl | K23: =IFERROR(IF(VALUE(C23)>2020,J23&"_"&TEXT(B23*100,"00"),"\I:"),"\I:") -> Trd_car_gsl_33 | L23: =LEFT(K23,7) -> Trd_car | M23: =IF($K23="\I:","",C23) -> 21957.324 | N23: =IF($K23="\I:","",D23) -> 20077.205 | O23: =IF($K23="\I:","",E23) -> 20077.205 | P23: =IF($K23="\I:","",F23) -> 20077.205 | S23: DMD | T23: =K23 -> Trd_car_gsl_33 | U23: =OFFSET($S$1,MATCH(J23,$S$1:$S$11,0)-1,-1)&" -- "&TEXT(B23,"00%") -> ICE medium size gasoline car -- 33% | V23: Bvkm | W23: million vehicles
B24: 0.38362396 | C24: 24470.648 | D24: 20810.347 | E24: 20810.347 | F24: 20810.347 | I24: =(1+B24) -> 1.383624 | J24: =IFERROR(VLOOKUP(C24,$R$1:$S$11,2,FALSE),J23) -> Trd_car_gsl | K24: =IFERROR(IF(VALUE(C24)>2020,J24&"_"&TEXT(B24*100,"00"),"\I:"),"\I:") -> Trd_car_gsl_38 | L24: =LEFT(K24,7) -> Trd_car | M24: =IF($K24="\I:","",C24) -> 24470.648 | N24: =IF($K24="\I:","",D24) -> 20810.347 | O24: =IF($K24="\I:","",E24) -> 20810.347 | P24: =IF($K24="\I:","",F24) -> 20810.347 | S24: DMD | T24: =K24 -> Trd_car_gsl_38 | U24: =OFFSET($S$1,MATCH(J24,$S$1:$S$11,0)-1,-1)&" -- "&TEXT(B24,"00%") -> ICE medium size gasoline car -- 38% | V24: Bvkm | W24: million vehicles
B25: 0.43362396 | C25: 53739.803 | D25: 22623.261 | E25: 22623.261 | F25: 22623.261 | I25: =(1+B25) -> 1.433624 | J25: =IFERROR(VLOOKUP(C25,$R$1:$S$11,2,FALSE),J24) -> Trd_car_gsl | K25: =IFERROR(IF(VALUE(C25)>2020,J25&"_"&TEXT(B25*100,"00"),"\I:"),"\I:") -> Trd_car_gsl_43 | L25: =LEFT(K25,7) -> Trd_car | M25: =IF($K25="\I:","",C25) -> 53739.803 | N25: =IF($K25="\I:","",D25) -> 22623.261 | O25: =IF($K25="\I:","",E25) -> 22623.261 | P25: =IF($K25="\I:","",F25) -> 22623.261 | S25: DMD | T25: =K25 -> Trd_car_gsl_43 | U25: =OFFSET($S$1,MATCH(J25,$S$1:$S$11,0)-1,-1)&" -- "&TEXT(B25,"00%") -> ICE medium size gasoline car -- 43% | V25: Bvkm | W25: million vehicles
B26: 0.48362396 | C26: 118918.12 | D26: 41097.305 | E26: 41097.305 | F26: 41097.305 | I26: =(1+B26) -> 1.483624 | J26: =IFERROR(VLOOKUP(C26,$R$1:$S$11,2,FALSE),J25) -> Trd_car_gsl | K26: =IFERROR(IF(VALUE(C26)>2020,J26&"_"&TEXT(B26*100,"00"),"\I:"),"\I:") -> Trd_car_gsl_48 | L26: =LEFT(K26,7) -> Trd_car | M26: =IF($K26="\I:","",C26) -> 118918.12 | N26: =IF($K26="\I:","",D26) -> 41097.305 | O26: =IF($K26="\I:","",E26) -> 41097.305 | P26: =IF($K26="\I:","",F26) -> 41097.305 | S26: DMD | T26: =K26 -> Trd_car_gsl_48 | U26: =OFFSET($S$1,MATCH(J26,$S$1:$S$11,0)-1,-1)&" -- "&TEXT(B26,"00%") -> ICE medium size gasoline car -- 48% | V26: Bvkm | W26: million vehicles
J27: =IFERROR(VLOOKUP(C27,$R$1:$S$11,2,FALSE),J26) -> Trd_car_gsl | K27: =IFERROR(IF(VALUE(C27)>2020,J27&"_"&TEXT(B27*100,"00"),"\I:"),"\I:") -> \I: | L27: =LEFT(K27,7) -> \I: | M27: =IF($K27="\I:","",C27) | N27: =IF($K27="\I:","",D27) | O27: =IF($K27="\I:","",E27) | P27: =IF($K27="\I:","",F27) | T27: =K27 -> \I: | U27: =OFFSET($S$1,MATCH(J27,$S$1:$S$11,0)-1,-1)&" -- "&TEXT(B27,"00%") -> ICE medium size gasoline car -- 00% | V27: Bvkm | W27: million vehicles
J28: =IFERROR(VLOOKUP(C28,$R$1:$S$11,2,FALSE),J27) -> Trd_car_gsl | K28: =IFERROR(IF(VALUE(C28)>2020,J28&"_"&TEXT(B28*100,"00"),"\I:"),"\I:") -> \I: | L28: =LEFT(K28,7) -> \I: | M28: =IF($K28="\I:","",C28) | N28: =IF($K28="\I:","",D28) | O28: =IF($K28="\I:","",E28) | P28: =IF($K28="\I:","",F28) | T28: =K28 -> \I: | U28: =OFFSET($S$1,MATCH(J28,$S$1:$S$11,0)-1,-1)&" -- "&TEXT(B28,"00%") -> ICE medium size gasoline car -- 00% | V28: Bvkm | W28: million vehicles
J29: =IFERROR(VLOOKUP(C29,$R$1:$S$11,2,FALSE),J28) -> Trd_car_gsl | K29: =IFERROR(IF(VALUE(C29)>2020,J29&"_"&TEXT(B29*100,"00"),"\I:"),"\I:") -> \I: | L29: =LEFT(K29,7) -> \I: | M29: =IF($K29="\I:","",C29) | N29: =IF($K29="\I:","",D29) | O29: =IF($K29="\I:","",E29) | P29: =IF($K29="\I:","",F29) | T29: =K29 -> \I: | U29: =OFFSET($S$1,MATCH(J29,$S$1:$S$11,0)-1,-1)&" -- "&TEXT(B29,"00%") -> ICE medium size gasoline car -- 00% | V29: Bvkm | W29: million vehicles
J30: =IFERROR(VLOOKUP(C30,$R$1:$S$11,2,FALSE),J29) -> Trd_car_gsl | K30: =IFERROR(IF(VALUE(C30)>2020,J30&"_"&TEXT(B30*100,"00"),"\I:"),"\I:") -> \I: | L30: =LEFT(K30,7) -> \I: | M30: =IF($K30="\I:","",C30) | N30: =IF($K30="\I:","",D30) | O30: =IF($K30="\I:","",E30) | P30: =IF($K30="\I:","",F30) | T30: =K30 -> \I: | U30: =OFFSET($S$1,MATCH(J30,$S$1:$S$11,0)-1,-1)&" -- "&TEXT(B30,"00%") -> ICE medium size gasoline car -- 00% | V30: Bvkm | W30: million vehicles
B31: Reduction of specific energy consumption relative to 2015 gasoline vehicle (%) | C31: ICE medium size hybrid gasoline car | J31: =IFERROR(VLOOKUP(C31,$R$1:$S$11,2,FALSE),J30) -> Trd_car_gsl-hyb | K31: =IFERROR(IF(VALUE(C31)>2020,J31&"_"&TEXT(B31*100,"00"),"\I:"),"\I:") -> \I: | L31: =LEFT(K31,7) -> \I: | M31: =IF($K31="\I:","",C31) | N31: =IF($K31="\I:","",D31) | O31: =IF($K31="\I:","",E31) | P31: =IF($K31="\I:","",F31) | T31: =K31 -> \I: | U31: =OFFSET($S$1,MATCH(J31,$S$1:$S$11,0)-1,-1)&" -- "&TEXT(B31,"00%") -> ICE medium size hybrid gasoline car -- Reduction of specific energy consumption relative to 2015 gasoline vehicle (%) | V31: Bvkm | W31: million vehicles
J32: =IFERROR(VLOOKUP(C32,$R$1:$S$11,2,FALSE),J31) -> Trd_car_gsl-hyb | K32: =IFERROR(IF(VALUE(C32)>2020,J32&"_"&TEXT(B32*100,"00"),"\I:"),"\I:") -> \I: | L32: =LEFT(K32,7) -> \I: | M32: =IF($K32="\I:","",C32) | N32: =IF($K32="\I:","",D32) | O32: =IF($K32="\I:","",E32) | P32: =IF($K32="\I:","",F32) | T32: =K32 -> \I: | U32: =OFFSET($S$1,MATCH(J32,$S$1:$S$11,0)-1,-1)&" -- "&TEXT(B32,"00%") -> ICE medium size hybrid gasoline car -- 00% | V32: Bvkm | W32: million vehicles
J33: =IFERROR(VLOOKUP(C33,$R$1:$S$11,2,FALSE),J32) -> Trd_car_gsl-hyb | K33: =IFERROR(IF(VALUE(C33)>2020,J33&"_"&TEXT(B33*100,"00"),"\I:"),"\I:") -> \I: | L33: =LEFT(K33,7) -> \I: | M33: =IF($K33="\I:","",C33) | N33: =IF($K33="\I:","",D33) | O33: =IF($K33="\I:","",E33) | P33: =IF($K33="\I:","",F33) | T33: =K33 -> \I: | U33: =OFFSET($S$1,MATCH(J33,$S$1:$S$11,0)-1,-1)&" -- "&TEXT(B33,"00%") -> ICE medium size hybrid gasoline car -- 00% | V33: Bvkm | W33: million vehicles
C34: 2020 | D34: 2030 | E34: 2040 | F34: 2050 | J34: =IFERROR(VLOOKUP(C34,$R$1:$S$11,2,FALSE),J33) -> Trd_car_gsl-hyb | K34: =IFERROR(IF(VALUE(C34)>2020,J34&"_"&TEXT(B34*100,"00"),"\I:"),"\I:") -> \I: | L34: =LEFT(K34,7) -> \I: | M34: =IF($K34="\I:","",C34) | N34: =IF($K34="\I:","",D34) | O34: =IF($K34="\I:","",E34) | P34: =IF($K34="\I:","",F34) | T34: =K34 -> \I: | U34: =OFFSET($S$1,MATCH(J34,$S$1:$S$11,0)-1,-1)&" -- "&TEXT(B34,"00%") -> ICE medium size hybrid gasoline car -- 00% | V34: Bvkm | W34: million vehicles
B35: 0.23611494 | C35: 21857.344 | D35: 20782.131 | E35: 20782.131 | F35: 20782.131 | I35: =(1+B35) -> 1.2361149 | J35: =IFERROR(VLOOKUP(C35,$R$1:$S$11,2,FALSE),J34) -> Trd_car_gsl-hyb | K35: =IFERROR(IF(VALUE(C35)>2020,J35&"_"&TEXT(B35*100,"00"),"\I:"),"\I:") -> Trd_car_gsl-hyb_24 | L35: =LEFT(K35,7) -> Trd_car | M35: =IF($K35="\I:","",C35) -> 21857.344 | N35: =IF($K35="\I:","",D35) -> 20782.131 | O35: =IF($K35="\I:","",E35) -> 20782.131 | P35: =IF($K35="\I:","",F35) -> 20782.131 | T35: =K35 -> Trd_car_gsl-hyb_24 | U35: =OFFSET($S$1,MATCH(J35,$S$1:$S$11,0)-1,-1)&" -- "&TEXT(B35,"00%") -> ICE medium size hybrid gasoline car -- 24% | V35: Bvkm | W35: million vehicles
B36: 0.33611494 | C36: 22033.117 | D36: 20950.891 | E36: 20950.891 | F36: 20950.891 | I36: =(1+B36) -> 1.3361149 | J36: =IFERROR(VLOOKUP(C36,$R$1:$S$11,2,FALSE),J35) -> Trd_car_gsl-hyb | K36: =IFERROR(IF(VALUE(C36)>2020,J36&"_"&TEXT(B36*100,"00"),"\I:"),"\I:") -> Trd_car_gsl-hyb_34 | L36: =LEFT(K36,7) -> Trd_car | M36: =IF($K36="\I:","",C36) -> 22033.117 | N36: =IF($K36="\I:","",D36) -> 20950.891 | O36: =IF($K36="\I:","",E36) -> 20950.891 | P36: =IF($K36="\I:","",F36) -> 20950.891 | T36: =K36 -> Trd_car_gsl-hyb_34 | U36: =OFFSET($S$1,MATCH(J36,$S$1:$S$11,0)-1,-1)&" -- "&TEXT(B36,"00%") -> ICE medium size hybrid gasoline car -- 34% | V36: Bvkm | W36: million vehicles
B37: 0.38611494 | C37: 22246.228 | D37: 21100.82 | E37: 21100.82 | F37: 21100.82 | I37: =(1+B37) -> 1.3861149 | J37: =IFERROR(VLOOKUP(C37,$R$1:$S$11,2,FALSE),J36) -> Trd_car_gsl-hyb | K37: =IFERROR(IF(VALUE(C37)>2020,J37&"_"&TEXT(B37*100,"00"),"\I:"),"\I:") -> Trd_car_gsl-hyb_39 | L37: =LEFT(K37,7) -> Trd_car | M37: =IF($K37="\I:","",C37) -> 22246.228 | N37: =IF($K37="\I:","",D37) -> 21100.82 | O37: =IF($K37="\I:","",E37) -> 21100.82 | P37: =IF($K37="\I:","",F37) -> 21100.82 | T37: =K37 -> Trd_car_gsl-hyb_39 | U37: =OFFSET($S$1,MATCH(J37,$S$1:$S$11,0)-1,-1)&" -- "&TEXT(B37,"00%") -> ICE medium size hybrid gasoline car -- 39% | V37: Bvkm | W37: million vehicles
B38: 0.43611494 | C38: 22681.265 | D38: 21227.425 | E38: 21227.425 | F38: 21227.425 | I38: =(1+B38) -> 1.4361149 | J38: =IFERROR(VLOOKUP(C38,$R$1:$S$11,2,FALSE),J37) -> Trd_car_gsl-hyb | K38: =IFERROR(IF(VALUE(C38)>2020,J38&"_"&TEXT(B38*100,"00"),"\I:"),"\I:") -> Trd_car_gsl-hyb_44 | L38: =LEFT(K38,7) -> Trd_car | M38: =IF($K38="\I:","",C38) -> 22681.265 | N38: =IF($K38="\I:","",D38) -> 21227.425 | O38: =IF($K38="\I:","",E38) -> 21227.425 | P38: =IF($K38="\I:","",F38) -> 21227.425 | T38: =K38 -> Trd_car_gsl-hyb_44 | U38: =OFFSET($S$1,MATCH(J38,$S$1:$S$11,0)-1,-1)&" -- "&TEXT(B38,"00%") -> ICE medium size hybrid gasoline car -- 44% | V38: Bvkm | W38: million vehicles
B39: 0.48611494 | C39: 23657.608 | D39: 21496.841 | E39: 21496.841 | F39: 21496.841 | I39: =(1+B39) -> 1.4861149 | J39: =IFERROR(VLOOKUP(C39,$R$1:$S$11,2,FALSE),J38) -> Trd_car_gsl-hyb | K39: =IFERROR(IF(VALUE(C39)>2020,J39&"_"&TEXT(B39*100,"00"),"\I:"),"\I:") -> Trd_car_gsl-hyb_49 | L39: =LEFT(K39,7) -> Trd_car | M39: =IF($K39="\I:","",C39) -> 23657.608 | N39: =IF($K39="\I:","",D39) -> 21496.841 | O39: =IF($K39="\I:","",E39) -> 21496.841 | P39: =IF($K39="\I:","",F39) -> 21496.841 | T39: =K39 -> Trd_car_gsl-hyb_49 | U39: =OFFSET($S$1,MATCH(J39,$S$1:$S$11,0)-1,-1)&" -- "&TEXT(B39,"00%") -> ICE medium size hybrid gasoline car -- 49% | V39: Bvkm | W39: million vehicles
B40: 0.53611494 | C40: 45787.585 | D40: 22147.35 | E40: 22147.35 | F40: 22147.35 | I40: =(1+B40) -> 1.5361149 | J40: =IFERROR(VLOOKUP(C40,$R$1:$S$11,2,FALSE),J39) -> Trd_car_gsl-hyb | K40: =IFERROR(IF(VALUE(C40)>2020,J40&"_"&TEXT(B40*100,"00"),"\I:"),"\I:") -> Trd_car_gsl-hyb_54 | L40: =LEFT(K40,7) -> Trd_car | M40: =IF($K40="\I:","",C40) -> 45787.585 | N40: =IF($K40="\I:","",D40) -> 22147.35 | O40: =IF($K40="\I:","",E40) -> 22147.35 | P40: =IF($K40="\I:","",F40) -> 22147.35 | T40: =K40 -> Trd_car_gsl-hyb_54 | U40: =OFFSET($S$1,MATCH(J40,$S$1:$S$11,0)-1,-1)&" -- "&TEXT(B40,"00%") -> ICE medium size hybrid gasoline car -- 54% | V40: Bvkm | W40: million vehicles
B41: 0.58611494 | C41: 118918.12 | D41: 34938.661 | E41: 34938.661 | F41: 34938.661 | I41: =(1+B41) -> 1.5861149 | J41: =IFERROR(VLOOKUP(C41,$R$1:$S$11,2,FALSE),J40) -> Trd_car_gsl-hyb | K41: =IFERROR(IF(VALUE(C41)>2020,J41&"_"&TEXT(B41*100,"00"),"\I:"),"\I:") -> Trd_car_gsl-hyb_59 | L41: =LEFT(K41,7) -> Trd_car | M41: =IF($K41="\I:","",C41) -> 118918.12 | N41: =IF($K41="\I:","",D41) -> 34938.661 | O41: =IF($K41="\I:","",E41) -> 34938.661 | P41: =IF($K41="\I:","",F41) -> 34938.661 | T41: =K41 -> Trd_car_gsl-hyb_59 | U41: =OFFSET($S$1,MATCH(J41,$S$1:$S$11,0)-1,-1)&" -- "&TEXT(B41,"00%") -> ICE medium size hybrid gasoline car -- 59% | V41: Bvkm | W41: million vehicles
J42: =IFERROR(VLOOKUP(C42,$R$1:$S$11,2,FALSE),J41) -> Trd_car_gsl-hyb | K42: =IFERROR(IF(VALUE(C42)>2020,J42&"_"&TEXT(B42*100,"00"),"\I:"),"\I:") -> \I: | L42: =LEFT(K42,7) -> \I: | M42: =IF($K42="\I:","",C42) | N42: =IF($K42="\I:","",D42) | O42: =IF($K42="\I:","",E42) | P42: =IF($K42="\I:","",F42) | T42: =K42 -> \I: | U42: =OFFSET($S$1,MATCH(J42,$S$1:$S$11,0)-1,-1)&" -- "&TEXT(B42,"00%") -> ICE medium size hybrid gasoline car -- 00% | V42: Bvkm | W42: million vehicles
J43: =IFERROR(VLOOKUP(C43,$R$1:$S$11,2,FALSE),J42) -> Trd_car_gsl-hyb | K43: =IFERROR(IF(VALUE(C43)>2020,J43&"_"&TEXT(B43*100,"00"),"\I:"),"\I:") -> \I: | L43: =LEFT(K43,7) -> \I: | M43: =IF($K43="\I:","",C43) | N43: =IF($K43="\I:","",D43) | O43: =IF($K43="\I:","",E43) | P43: =IF($K43="\I:","",F43) | T43: =K43 -> \I: | U43: =OFFSET($S$1,MATCH(J43,$S$1:$S$11,0)-1,-1)&" -- "&TEXT(B43,"00%") -> ICE medium size hybrid gasoline car -- 00% | V43: Bvkm | W43: million vehicles
J44: =IFERROR(VLOOKUP(C44,$R$1:$S$11,2,FALSE),J43) -> Trd_car_gsl-hyb | K44: =IFERROR(IF(VALUE(C44)>2020,J44&"_"&TEXT(B44*100,"00"),"\I:"),"\I:") -> \I: | L44: =LEFT(K44,7) -> \I: | M44: =IF($K44="\I:","",C44) | N44: =IF($K44="\I:","",D44) | O44: =IF($K44="\I:","",E44) | P44: =IF($K44="\I:","",F44) | T44: =K44 -> \I: | U44: =OFFSET($S$1,MATCH(J44,$S$1:$S$11,0)-1,-1)&" -- "&TEXT(B44,"00%") -> ICE medium size hybrid gasoline car -- 00% | V44: Bvkm | W44: million vehicles
J45: =IFERROR(VLOOKUP(C45,$R$1:$S$11,2,FALSE),J44) -> Trd_car_gsl-hyb | K45: =IFERROR(IF(VALUE(C45)>2020,J45&"_"&TEXT(B45*100,"00"),"\I:"),"\I:") -> \I: | L45: =LEFT(K45,7) -> \I: | M45: =IF($K45="\I:","",C45) | N45: =IF($K45="\I:","",D45) | O45: =IF($K45="\I:","",E45) | P45: =IF($K45="\I:","",F45) | T45: =K45 -> \I: | U45: =OFFSET($S$1,MATCH(J45,$S$1:$S$11,0)-1,-1)&" -- "&TEXT(B45,"00%") -> ICE medium size hybrid gasoline car -- 00% | V45: Bvkm | W45: million vehicles
B46: Reduction of specific energy consumption relative to 2015 gasoline vehicle (%) | C46: ICE medium size plug-in hybrid gasoline car | J46: =IFERROR(VLOOKUP(C46,$R$1:$S$11,2,FALSE),J45) -> Trd_car_gsl-pih | K46: =IFERROR(IF(VALUE(C46)>2020,J46&"_"&TEXT(B46*100,"00"),"\I:"),"\I:") -> \I: | L46: =LEFT(K46,7) -> \I: | M46: =IF($K46="\I:","",C46) | N46: =IF($K46="\I:","",D46) | O46: =IF($K46="\I:","",E46) | P46: =IF($K46="\I:","",F46) | T46: =K46 -> \I: | U46: =OFFSET($S$1,MATCH(J46,$S$1:$S$11,0)-1,-1)&" -- "&TEXT(B46,"00%") -> ICE medium size plug-in hybrid gasoline car -- Reduction of specific energy consumption relative to 2015 gasoline vehicle (%) | V46: Bvkm | W46: million vehicles
J47: =IFERROR(VLOOKUP(C47,$R$1:$S$11,2,FALSE),J46) -> Trd_car_gsl-pih | K47: =IFERROR(IF(VALUE(C47)>2020,J47&"_"&TEXT(B47*100,"00"),"\I:"),"\I:") -> \I: | L47: =LEFT(K47,7) -> \I: | M47: =IF($K47="\I:","",C47) | N47: =IF($K47="\I:","",D47) | O47: =IF($K47="\I:","",E47) | P47: =IF($K47="\I:","",F47) | T47: =K47 -> \I: | U47: =OFFSET($S$1,MATCH(J47,$S$1:$S$11,0)-1,-1)&" -- "&TEXT(B47,"00%") -> ICE medium size plug-in hybrid gasoline car -- 00% | V47: Bvkm | W47: million vehicles
J48: =IFERROR(VLOOKUP(C48,$R$1:$S$11,2,FALSE),J47) -> Trd_car_gsl-pih | K48: =IFERROR(IF(VALUE(C48)>2020,J48&"_"&TEXT(B48*100,"00"),"\I:"),"\I:") -> \I: | L48: =LEFT(K48,7) -> \I: | M48: =IF($K48="\I:","",C48) | N48: =IF($K48="\I:","",D48) | O48: =IF($K48="\I:","",E48) | P48: =IF($K48="\I:","",F48) | T48: =K48 -> \I: | U48: =OFFSET($S$1,MATCH(J48,$S$1:$S$11,0)-1,-1)&" -- "&TEXT(B48,"00%") -> ICE medium size plug-in hybrid gasoline car -- 00% | V48: Bvkm | W48: million vehicles
C49: 2020 | D49: 2030 | E49: 2040 | F49: 2050 | J49: =IFERROR(VLOOKUP(C49,$R$1:$S$11,2,FALSE),J48) -> Trd_car_gsl-pih | K49: =IFERROR(IF(VALUE(C49)>2020,J49&"_"&TEXT(B49*100,"00"),"\I:"),"\I:") -> \I: | L49: =LEFT(K49,7) -> \I: | M49: =IF($K49="\I:","",C49) | N49: =IF($K49="\I:","",D49) | O49: =IF($K49="\I:","",E49) | P49: =IF($K49="\I:","",F49) | T49: =K49 -> \I: | U49: =OFFSET($S$1,MATCH(J49,$S$1:$S$11,0)-1,-1)&" -- "&TEXT(B49,"00%") -> ICE medium size plug-in hybrid gasoline car -- 00% | V49: Bvkm | W49: million vehicles
B50: 0.70862396 | C50: 26539.478 | D50: 22587.578 | E50: 21510.779 | F50: 21196.725 | I50: =(1+B50) -> 1.708624 | J50: =IFERROR(VLOOKUP(C50,$R$1:$S$11,2,FALSE),J49) -> Trd_car_gsl-pih | K50: =IFERROR(IF(VALUE(C50)>2020,J50&"_"&TEXT(B50*100,"00"),"\I:"),"\I:") -> Trd_car_gsl-pih_71 | L50: =LEFT(K50,7) -> Trd_car | M50: =IF($K50="\I:","",C50) -> 26539.478 | N50: =IF($K50="\I:","",D50) -> 22587.578 | O50: =IF($K50="\I:","",E50) -> 21510.779 | P50: =IF($K50="\I:","",F50) -> 21196.725 | T50: =K50 -> Trd_car_gsl-pih_71 | U50: =OFFSET($S$1,MATCH(J50,$S$1:$S$11,0)-1,-1)&" -- "&TEXT(B50,"00%") -> ICE medium size plug-in hybrid gasoline car -- 71% | V50: Bvkm | W50: million vehicles
B51: 0.71862396 | C51: 26628.278 | D51: 22611.932 | E51: 21520.181 | F51: 21201.001 | I51: =(1+B51) -> 1.718624 | J51: =IFERROR(VLOOKUP(C51,$R$1:$S$11,2,FALSE),J50) -> Trd_car_gsl-pih | K51: =IFERROR(IF(VALUE(C51)>2020,J51&"_"&TEXT(B51*100,"00"),"\I:"),"\I:") -> Trd_car_gsl-pih_72 | L51: =LEFT(K51,7) -> Trd_car | M51: =IF($K51="\I:","",C51) -> 26628.278 | N51: =IF($K51="\I:","",D51) -> 22611.932 | O51: =IF($K51="\I:","",E51) -> 21520.181 | P51: =IF($K51="\I:","",F51) -> 21201.001 | T51: =K51 -> Trd_car_gsl-pih_72 | U51: =OFFSET($S$1,MATCH(J51,$S$1:$S$11,0)-1,-1)&" -- "&TEXT(B51,"00%") -> ICE medium size plug-in hybrid gasoline car -- 72% | V51: Bvkm | W51: million vehicles
B52: 0.73112396 | C52: 26773.523 | D52: 22633.654 | E52: 21527.053 | F52: 21202.711 | I52: =(1+B52) -> 1.731124 | J52: =IFERROR(VLOOKUP(C52,$R$1:$S$11,2,FALSE),J51) -> Trd_car_gsl-pih | K52: =IFERROR(IF(VALUE(C52)>2020,J52&"_"&TEXT(B52*100,"00"),"\I:"),"\I:") -> Trd_car_gsl-pih_73 | L52: =LEFT(K52,7) -> Trd_car | M52: =IF($K52="\I:","",C52) -> 26773.523 | N52: =IF($K52="\I:","",D52) -> 22633.654 | O52: =IF($K52="\I:","",E52) -> 21527.053 | P52: =IF($K52="\I:","",F52) -> 21202.711 | T52: =K52 -> Trd_car_gsl-pih_73 | U52: =OFFSET($S$1,MATCH(J52,$S$1:$S$11,0)-1,-1)&" -- "&TEXT(B52,"00%") -> ICE medium size plug-in hybrid gasoline car -- 73% | V52: Bvkm | W52: million vehicles
B53: 0.74112396 | C53: 26989.674 | D53: 22654.216 | E53: 21537.478 | F53: 21209.777 | I53: =(1+B53) -> 1.741124 | J53: =IFERROR(VLOOKUP(C53,$R$1:$S$11,2,FALSE),J52) -> Trd_car_gsl-pih | K53: =IFERROR(IF(VALUE(C53)>2020,J53&"_"&TEXT(B53*100,"00"),"\I:"),"\I:") -> Trd_car_gsl-pih_74 | L53: =LEFT(K53,7) -> Trd_car | M53: =IF($K53="\I:","",C53) -> 26989.674 | N53: =IF($K53="\I:","",D53) -> 22654.216 | O53: =IF($K53="\I:","",E53) -> 21537.478 | P53: =IF($K53="\I:","",F53) -> 21209.777 | T53: =K53 -> Trd_car_gsl-pih_74 | U53: =OFFSET($S$1,MATCH(J53,$S$1:$S$11,0)-1,-1)&" -- "&TEXT(B53,"00%") -> ICE medium size plug-in hybrid gasoline car -- 74% | V53: Bvkm | W53: million vehicles
B54: 0.75112396 | C54: 27401.4 | D54: 22660.397 | E54: 21543.417 | F54: 21215.8 | I54: =(1+B54) -> 1.751124 | J54: =IFERROR(VLOOKUP(C54,$R$1:$S$11,2,FALSE),J53) -> Trd_car_gsl-pih | K54: =IFERROR(IF(VALUE(C54)>2020,J54&"_"&TEXT(B54*100,"00"),"\I:"),"\I:") -> Trd_car_gsl-pih_75 | L54: =LEFT(K54,7) -> Trd_car | M54: =IF($K54="\I:","",C54) -> 27401.4 | N54: =IF($K54="\I:","",D54) -> 22660.397 | O54: =IF($K54="\I:","",E54) -> 21543.417 | P54: =IF($K54="\I:","",F54) -> 21215.8 | T54: =K54 -> Trd_car_gsl-pih_75 | U54: =OFFSET($S$1,MATCH(J54,$S$1:$S$11,0)-1,-1)&" -- "&TEXT(B54,"00%") -> ICE medium size plug-in hybrid gasoline car -- 75% | V54: Bvkm | W54: million vehicles
B55: 0.79862396 | C55: 73086.775 | D55: 23523.785 | E55: 22095.434 | F55: 21671.319 | I55: =(1+B55) -> 1.798624 | J55: =IFERROR(VLOOKUP(C55,$R$1:$S$11,2,FALSE),J54) -> Trd_car_gsl-pih | K55: =IFERROR(IF(VALUE(C55)>2020,J55&"_"&TEXT(B55*100,"00"),"\I:"),"\I:") -> Trd_car_gsl-pih_80 | L55: =LEFT(K55,7) -> Trd_car | M55: =IF($K55="\I:","",C55) -> 73086.775 | N55: =IF($K55="\I:","",D55) -> 23523.785 | O55: =IF($K55="\I:","",E55) -> 22095.434 | P55: =IF($K55="\I:","",F55) -> 21671.319 | T55: =K55 -> Trd_car_gsl-pih_80 | U55: =OFFSET($S$1,MATCH(J55,$S$1:$S$11,0)-1,-1)&" -- "&TEXT(B55,"00%") -> ICE medium size plug-in hybrid gasoline car -- 80% | V55: Bvkm | W55: million vehicles
B56: 0.80612396 | C56: 108076.54 | D56: 23678.994 | E56: 22244.576 | F56: 21822.56 | I56: =(1+B56) -> 1.806124 | J56: =IFERROR(VLOOKUP(C56,$R$1:$S$11,2,FALSE),J55) -> Trd_car_gsl-pih | K56: =IFERROR(IF(VALUE(C56)>2020,J56&"_"&TEXT(B56*100,"00"),"\I:"),"\I:") -> Trd_car_gsl-pih_81 | L56: =LEFT(K56,7) -> Trd_car | M56: =IF($K56="\I:","",C56) -> 108076.54 | N56: =IF($K56="\I:","",D56) -> 23678.994 | O56: =IF($K56="\I:","",E56) -> 22244.576 | P56: =IF($K56="\I:","",F56) -> 21822.56 | T56: =K56 -> Trd_car_gsl-pih_81 | U56: =OFFSET($S$1,MATCH(J56,$S$1:$S$11,0)-1,-1)&" -- "&TEXT(B56,"00%") -> ICE medium size plug-in hybrid gasoline car -- 81% | V56: Bvkm | W56: million vehicles
B57: 0.81562396 | C57: =C56 -> 108076.54 | D57: 42903.229 | E57: 40717.324 | F57: 40555.371 | I57: =(1+B57) -> 1.815624 | J57: =IFERROR(VLOOKUP(C57,$R$1:$S$11,2,FALSE),J56) -> Trd_car_gsl-pih | K57: =IFERROR(IF(VALUE(C57)>2020,J57&"_"&TEXT(B57*100,"00"),"\I:"),"\I:") -> Trd_car_gsl-pih_82 | L57: =LEFT(K57,7) -> Trd_car | M57: =IF($K57="\I:","",C57) -> 108076.54 | N57: =IF($K57="\I:","",D57) -> 42903.229 | O57: =IF($K57="\I:","",E57) -> 40717.324 | P57: =IF($K57="\I:","",F57) -> 40555.371 | T57: =K57 -> Trd_car_gsl-pih_82 | U57: =OFFSET($S$1,MATCH(J57,$S$1:$S$11,0)-1,-1)&" -- "&TEXT(B57,"00%") -> ICE medium size plug-in hybrid gasoline car -- 82% | V57: Bvkm | W57: million vehicles
J58: =IFERROR(VLOOKUP(C58,$R$1:$S$11,2,FALSE),J57) -> Trd_car_gsl-pih | K58: =IFERROR(IF(VALUE(C58)>2020,J58&"_"&TEXT(B58*100,"00"),"\I:"),"\I:") -> \I: | L58: =LEFT(K58,7) -> \I: | M58: =IF($K58="\I:","",C58) | N58: =IF($K58="\I:","",D58) | O58: =IF($K58="\I:","",E58) | P58: =IF($K58="\I:","",F58) | T58: =K58 -> \I: | U58: =OFFSET($S$1,MATCH(J58,$S$1:$S$11,0)-1,-1)&" -- "&TEXT(B58,"00%") -> ICE medium size plug-in hybrid gasoline car -- 00% | V58: Bvkm | W58: million vehicles
J59: =IFERROR(VLOOKUP(C59,$R$1:$S$11,2,FALSE),J58) -> Trd_car_gsl-pih | K59: =IFERROR(IF(VALUE(C59)>2020,J59&"_"&TEXT(B59*100,"00"),"\I:"),"\I:") -> \I: | L59: =LEFT(K59,7) -> \I: | M59: =IF($K59="\I:","",C59) | N59: =IF($K59="\I:","",D59) | O59: =IF($K59="\I:","",E59) | P59: =IF($K59="\I:","",F59) | T59: =K59 -> \I: | U59: =OFFSET($S$1,MATCH(J59,$S$1:$S$11,0)-1,-1)&" -- "&TEXT(B59,"00%") -> ICE medium size plug-in hybrid gasoline car -- 00% | V59: Bvkm | W59: million vehicles
J60: =IFERROR(VLOOKUP(C60,$R$1:$S$11,2,FALSE),J59) -> Trd_car_gsl-pih | K60: =IFERROR(IF(VALUE(C60)>2020,J60&"_"&TEXT(B60*100,"00"),"\I:"),"\I:") -> \I: | L60: =LEFT(K60,7) -> \I: | M60: =IF($K60="\I:","",C60) | N60: =IF($K60="\I:","",D60) | O60: =IF($K60="\I:","",E60) | P60: =IF($K60="\I:","",F60) | T60: =K60 -> \I: | U60: =OFFSET($S$1,MATCH(J60,$S$1:$S$11,0)-1,-1)&" -- "&TEXT(B60,"00%") -> ICE medium size plug-in hybrid gasoline car -- 00% | V60: Bvkm | W60: million vehicles
J61: =IFERROR(VLOOKUP(C61,$R$1:$S$11,2,FALSE),J60) -> Trd_car_gsl-pih | K61: =IFERROR(IF(VALUE(C61)>2020,J61&"_"&TEXT(B61*100,"00"),"\I:"),"\I:") -> \I: | L61: =LEFT(K61,7) -> \I: | M61: =IF($K61="\I:","",C61) | N61: =IF($K61="\I:","",D61) | O61: =IF($K61="\I:","",E61) | P61: =IF($K61="\I:","",F61) | T61: =K61 -> \I: | U61: =OFFSET($S$1,MATCH(J61,$S$1:$S$11,0)-1,-1)&" -- "&TEXT(B61,"00%") -> ICE medium size plug-in hybrid gasoline car -- 00% | V61: Bvkm | W61: million vehicles
B62: Reference values for medium size ICE diesel | J62: =IFERROR(VLOOKUP(C62,$R$1:$S$11,2,FALSE),J61) -> Trd_car_gsl-pih | K62: =IFERROR(IF(VALUE(C62)>2020,J62&"_"&TEXT(B62*100,"00"),"\I:"),"\I:") -> \I: | L62: =LEFT(K62,7) -> \I: | M62: =IF($K62="\I:","",C62) | N62: =IF($K62="\I:","",D62) | O62: =IF($K62="\I:","",E62) | P62: =IF($K62="\I:","",F62) | T62: =K62 -> \I: | U62: =OFFSET($S$1,MATCH(J62,$S$1:$S$11,0)-1,-1)&" -- "&TEXT(B62,"00%") -> ICE medium size plug-in hybrid gasoline car -- Reference values for medium size ICE diesel | V62: Bvkm | W62: million vehicles
B63: 2015 | J63: =IFERROR(VLOOKUP(C63,$R$1:$S$11,2,FALSE),J62) -> Trd_car_gsl-pih | K63: =IFERROR(IF(VALUE(C63)>2020,J63&"_"&TEXT(B63*100,"00"),"\I:"),"\I:") -> \I: | L63: =LEFT(K63,7) -> \I: | M63: =IF($K63="\I:","",C63) | N63: =IF($K63="\I:","",D63) | O63: =IF($K63="\I:","",E63) | P63: =IF($K63="\I:","",F63) | T63: =K63 -> \I: | U63: =OFFSET($S$1,MATCH(J63,$S$1:$S$11,0)-1,-1)&" -- "&TEXT(B63,"00%") -> ICE medium size plug-in hybrid gasoline car -- 201500% | V63: Bvkm | W63: million vehicles
B64: Energy consumption | C64: lt/100 km | D64: 4.986669 | G64: =D64*$I$4/100*10^9/10^6 -> 1.8949342 | I64: =1/G64 -> 0.52772281 | J64: =IFERROR(VLOOKUP(C64,$R$1:$S$11,2,FALSE),J63) -> Trd_car_gsl-pih | K64: =IFERROR(IF(VALUE(C64)>2020,J64&"_"&TEXT(B64*100,"00"),"\I:"),"\I:") -> \I: | L64: =LEFT(K64,7) -> \I: | M64: =IF($K64="\I:","",C64) | N64: =IF($K64="\I:","",D64) | O64: =IF($K64="\I:","",E64) | P64: =IF($K64="\I:","",F64) | T64: =K64 -> \I: | U64: =OFFSET($S$1,MATCH(J64,$S$1:$S$11,0)-1,-1)&" -- "&TEXT(B64,"00%") -> ICE medium size plug-in hybrid gasoline car -- Energy consumption | V64: Bvkm | W64: million vehicles
B65: Capital cost | C65: Euro15 /veh | D65: 21914.265 | I65: bvkm/PJ | J65: =IFERROR(VLOOKUP(C65,$R$1:$S$11,2,FALSE),J64) -> Trd_car_gsl-pih | K65: =IFERROR(IF(VALUE(C65)>2020,J65&"_"&TEXT(B65*100,"00"),"\I:"),"\I:") -> \I: | L65: =LEFT(K65,7) -> \I: | M65: =IF($K65="\I:","",C65) | N65: =IF($K65="\I:","",D65) | O65: =IF($K65="\I:","",E65) | P65: =IF($K65="\I:","",F65) | T65: =K65 -> \I: | U65: =OFFSET($S$1,MATCH(J65,$S$1:$S$11,0)-1,-1)&" -- "&TEXT(B65,"00%") -> ICE medium size plug-in hybrid gasoline car -- Capital cost | V65: Bvkm | W65: million vehicles
J66: =IFERROR(VLOOKUP(C66,$R$1:$S$11,2,FALSE),J65) -> Trd_car_gsl-pih | K66: =IFERROR(IF(VALUE(C66)>2020,J66&"_"&TEXT(B66*100,"00"),"\I:"),"\I:") -> \I: | L66: =LEFT(K66,7) -> \I: | M66: =IF($K66="\I:","",C66) | N66: =IF($K66="\I:","",D66) | O66: =IF($K66="\I:","",E66) | P66: =IF($K66="\I:","",F66) | T66: =K66 -> \I: | U66: =OFFSET($S$1,MATCH(J66,$S$1:$S$11,0)-1,-1)&" -- "&TEXT(B66,"00%") -> ICE medium size plug-in hybrid gasoline car -- 00% | V66: Bvkm | W66: million vehicles
B67: Reduction of specific energy consumption relative to 2015 diesel vehicle (%) | C67: ICE medium size diesel car | J67: =IFERROR(VLOOKUP(C67,$R$1:$S$11,2,FALSE),J66) -> Trd_car_dsl | K67: =IFERROR(IF(VALUE(C67)>2020,J67&"_"&TEXT(B67*100,"00"),"\I:"),"\I:") -> \I: | L67: =LEFT(K67,7) -> \I: | M67: =IF($K67="\I:","",C67) | N67: =IF($K67="\I:","",D67) | O67: =IF($K67="\I:","",E67) | P67: =IF($K67="\I:","",F67) | T67: =K67 -> \I: | U67: =OFFSET($S$1,MATCH(J67,$S$1:$S$11,0)-1,-1)&" -- "&TEXT(B67,"00%") -> ICE medium size diesel car -- Reduction of specific energy consumption relative to 2015 diesel vehicle (%) | V67: Bvkm | W67: million vehicles
J68: =IFERROR(VLOOKUP(C68,$R$1:$S$11,2,FALSE),J67) -> Trd_car_dsl | K68: =IFERROR(IF(VALUE(C68)>2020,J68&"_"&TEXT(B68*100,"00"),"\I:"),"\I:") -> \I: | L68: =LEFT(K68,7) -> \I: | M68: =IF($K68="\I:","",C68) | N68: =IF($K68="\I:","",D68) | O68: =IF($K68="\I:","",E68) | P68: =IF($K68="\I:","",F68) | T68: =K68 -> \I: | U68: =OFFSET($S$1,MATCH(J68,$S$1:$S$11,0)-1,-1)&" -- "&TEXT(B68,"00%") -> ICE medium size diesel car -- 00% | V68: Bvkm | W68: million vehicles
J69: =IFERROR(VLOOKUP(C69,$R$1:$S$11,2,FALSE),J68) -> Trd_car_dsl | K69: =IFERROR(IF(VALUE(C69)>2020,J69&"_"&TEXT(B69*100,"00"),"\I:"),"\I:") -> \I: | L69: =LEFT(K69,7) -> \I: | M69: =IF($K69="\I:","",C69) | N69: =IF($K69="\I:","",D69) | O69: =IF($K69="\I:","",E69) | P69: =IF($K69="\I:","",F69) | T69: =K69 -> \I: | U69: =OFFSET($S$1,MATCH(J69,$S$1:$S$11,0)-1,-1)&" -- "&TEXT(B69,"00%") -> ICE medium size diesel car -- 00% | V69: Bvkm | W69: million vehicles
C70: 2020 | D70: 2030 | E70: 2040 | F70: 2050 | I70: 1 | J70: =IFERROR(VLOOKUP(C70,$R$1:$S$11,2,FALSE),J69) -> Trd_car_dsl | K70: =IFERROR(IF(VALUE(C70)>200,J70&"_"&TEXT(B70*100,"00"),"\I:"),"\I:") -> Trd_car_dsl_00 | L70: =LEFT(K70,7) -> Trd_car | M70: =D65 -> 21914.265 | T70: =K70 -> Trd_car_dsl_00 | U70: =OFFSET($S$1,MATCH(J70,$S$1:$S$11,0)-1,-1)&" -- "&TEXT(B70,"00%") -> ICE medium size diesel car -- 00% | V70: Bvkm | W70: million vehicles
B71: 0.19519813 | C71: 22692.999 | D71: 22131.479 | E71: 22131.479 | F71: 22131.479 | I71: =$I$64*(1+B71)/$I$12 -> 1.3533514 | J71: =IFERROR(VLOOKUP(C71,$R$1:$S$11,2,FALSE),J70) -> Trd_car_dsl | K71: =IFERROR(IF(VALUE(C71)>2020,J71&"_"&TEXT(B71*100,"00"),"\I:"),"\I:") -> Trd_car_dsl_20 | L71: =LEFT(K71,7) -> Trd_car | M71: =IF($K71="\I:","",C71) -> 22692.999 | N71: =IF($K71="\I:","",D71) -> 22131.479 | O71: =IF($K71="\I:","",E71) -> 22131.479 | P71: =IF($K71="\I:","",F71) -> 22131.479 | T71: =K71 -> Trd_car_dsl_20 | U71: =OFFSET($S$1,MATCH(J71,$S$1:$S$11,0)-1,-1)&" -- "&TEXT(B71,"00%") -> ICE medium size diesel car -- 20% | V71: Bvkm | W71: million vehicles
B72: 0.29519813 | C72: 24299.038 | D72: 22868.831 | E72: 22868.831 | F72: 22868.831 | I72: =$I$64*(1+B72)/$I$12 -> 1.4665838 | J72: =IFERROR(VLOOKUP(C72,$R$1:$S$11,2,FALSE),J71) -> Trd_car_dsl | K72: =IFERROR(IF(VALUE(C72)>2020,J72&"_"&TEXT(B72*100,"00"),"\I:"),"\I:") -> Trd_car_dsl_30 | L72: =LEFT(K72,7) -> Trd_car | M72: =IF($K72="\I:","",C72) -> 24299.038 | N72: =IF($K72="\I:","",D72) -> 22868.831 | O72: =IF($K72="\I:","",E72) -> 22868.831 | P72: =IF($K72="\I:","",F72) -> 22868.831 | T72: =K72 -> Trd_car_dsl_30 | U72: =OFFSET($S$1,MATCH(J72,$S$1:$S$11,0)-1,-1)&" -- "&TEXT(B72,"00%") -> ICE medium size diesel car -- 30% | V72: Bvkm | W72: million vehicles
B73: 0.34519813 | C73: 26423.117 | D73: 23526.512 | E73: 23526.512 | F73: 23526.512 | I73: =$I$64*(1+B73)/$I$12 -> 1.5232 | J73: =IFERROR(VLOOKUP(C73,$R$1:$S$11,2,FALSE),J72) -> Trd_car_dsl | K73: =IFERROR(IF(VALUE(C73)>2020,J73&"_"&TEXT(B73*100,"00"),"\I:"),"\I:") -> Trd_car_dsl_35 | L73: =LEFT(K73,7) -> Trd_car | M73: =IF($K73="\I:","",C73) -> 26423.117 | N73: =IF($K73="\I:","",D73) -> 23526.512 | O73: =IF($K73="\I:","",E73) -> 23526.512 | P73: =IF($K73="\I:","",F73) -> 23526.512 | T73: =K73 -> Trd_car_dsl_35 | U73: =OFFSET($S$1,MATCH(J73,$S$1:$S$11,0)-1,-1)&" -- "&TEXT(B73,"00%") -> ICE medium size diesel car -- 35% | V73: Bvkm | W73: million vehicles
B74: 0.39519813 | C74: 39644.746 | D74: 24942.224 | E74: 24942.224 | F74: 24942.224 | I74: =$I$64*(1+B74)/$I$12 -> 1.5798162 | J74: =IFERROR(VLOOKUP(C74,$R$1:$S$11,2,FALSE),J73) -> Trd_car_dsl | K74: =IFERROR(IF(VALUE(C74)>2020,J74&"_"&TEXT(B74*100,"00"),"\I:"),"\I:") -> Trd_car_dsl_40 | L74: =LEFT(K74,7) -> Trd_car | M74: =IF($K74="\I:","",C74) -> 39644.746 | N74: =IF($K74="\I:","",D74) -> 24942.224 | O74: =IF($K74="\I:","",E74) -> 24942.224 | P74: =IF($K74="\I:","",F74) -> 24942.224 | T74: =K74 -> Trd_car_dsl_40 | U74: =OFFSET($S$1,MATCH(J74,$S$1:$S$11,0)-1,-1)&" -- "&TEXT(B74,"00%") -> ICE medium size diesel car -- 40% | V74: Bvkm | W74: million vehicles
B75: 0.44519813 | C75: 122116.43 | D75: 33656.295 | E75: 33656.295 | F75: 33656.295 | I75: =$I$64*(1+B75)/$I$12 -> 1.6364324 | J75: =IFERROR(VLOOKUP(C75,$R$1:$S$11,2,FALSE),J74) -> Trd_car_dsl | K75: =IFERROR(IF(VALUE(C75)>2020,J75&"_"&TEXT(B75*100,"00"),"\I:"),"\I:") -> Trd_car_dsl_45 | L75: =LEFT(K75,7) -> Trd_car | M75: =IF($K75="\I:","",C75) -> 122116.43 | N75: =IF($K75="\I:","",D75) -> 33656.295 | O75: =IF($K75="\I:","",E75) -> 33656.295 | P75: =IF($K75="\I:","",F75) -> 33656.295 | T75: =K75 -> Trd_car_dsl_45 | U75: =OFFSET($S$1,MATCH(J75,$S$1:$S$11,0)-1,-1)&" -- "&TEXT(B75,"00%") -> ICE medium size diesel car -- 45% | V75: Bvkm | W75: million vehicles
J76: =IFERROR(VLOOKUP(C76,$R$1:$S$11,2,FALSE),J75) -> Trd_car_dsl | K76: =IFERROR(IF(VALUE(C76)>2020,J76&"_"&TEXT(B76*100,"00"),"\I:"),"\I:") -> \I: | L76: =LEFT(K76,7) -> \I: | M76: =IF($K76="\I:","",C76) | N76: =IF($K76="\I:","",D76) | O76: =IF($K76="\I:","",E76) | P76: =IF($K76="\I:","",F76) | T76: =K76 -> \I: | U76: =OFFSET($S$1,MATCH(J76,$S$1:$S$11,0)-1,-1)&" -- "&TEXT(B76,"00%") -> ICE medium size diesel car -- 00% | V76: Bvkm | W76: million vehicles
J77: =IFERROR(VLOOKUP(C77,$R$1:$S$11,2,FALSE),J76) -> Trd_car_dsl | K77: =IFERROR(IF(VALUE(C77)>2020,J77&"_"&TEXT(B77*100,"00"),"\I:"),"\I:") -> \I: | L77: =LEFT(K77,7) -> \I: | M77: =IF($K77="\I:","",C77) | N77: =IF($K77="\I:","",D77) | O77: =IF($K77="\I:","",E77) | P77: =IF($K77="\I:","",F77) | T77: =K77 -> \I: | U77: =OFFSET($S$1,MATCH(J77,$S$1:$S$11,0)-1,-1)&" -- "&TEXT(B77,"00%") -> ICE medium size diesel car -- 00% | V77: Bvkm | W77: million vehicles
J78: =IFERROR(VLOOKUP(C78,$R$1:$S$11,2,FALSE),J77) -> Trd_car_dsl | K78: =IFERROR(IF(VALUE(C78)>2020,J78&"_"&TEXT(B78*100,"00"),"\I:"),"\I:") -> \I: | L78: =LEFT(K78,7) -> \I: | M78: =IF($K78="\I:","",C78) | N78: =IF($K78="\I:","",D78) | O78: =IF($K78="\I:","",E78) | P78: =IF($K78="\I:","",F78) | T78: =K78 -> \I: | U78: =OFFSET($S$1,MATCH(J78,$S$1:$S$11,0)-1,-1)&" -- "&TEXT(B78,"00%") -> ICE medium size diesel car -- 00% | V78: Bvkm | W78: million vehicles
J79: =IFERROR(VLOOKUP(C79,$R$1:$S$11,2,FALSE),J78) -> Trd_car_dsl | K79: =IFERROR(IF(VALUE(C79)>2020,J79&"_"&TEXT(B79*100,"00"),"\I:"),"\I:") -> \I: | L79: =LEFT(K79,7) -> \I: | M79: =IF($K79="\I:","",C79) | N79: =IF($K79="\I:","",D79) | O79: =IF($K79="\I:","",E79) | P79: =IF($K79="\I:","",F79) | T79: =K79 -> \I: | U79: =OFFSET($S$1,MATCH(J79,$S$1:$S$11,0)-1,-1)&" -- "&TEXT(B79,"00%") -> ICE medium size diesel car -- 00% | V79: Bvkm | W79: million vehicles
B80: Reduction of specific energy consumption relative to 2015 diesel vehicle (%) | C80: ICE medium size hybrid diesel car | J80: =IFERROR(VLOOKUP(C80,$R$1:$S$11,2,FALSE),J79) -> Trd_car_dsl-hyb | K80: =IFERROR(IF(VALUE(C80)>2020,J80&"_"&TEXT(B80*100,"00"),"\I:"),"\I:") -> \I: | L80: =LEFT(K80,7) -> \I: | M80: =IF($K80="\I:","",C80) | N80: =IF($K80="\I:","",D80) | O80: =IF($K80="\I:","",E80) | P80: =IF($K80="\I:","",F80) | T80: =K80 -> \I: | U80: =OFFSET($S$1,MATCH(J80,$S$1:$S$11,0)-1,-1)&" -- "&TEXT(B80,"00%") -> ICE medium size hybrid diesel car -- Reduction of specific energy consumption relative to 2015 diesel vehicle (%) | V80: Bvkm | W80: million vehicles
J81: =IFERROR(VLOOKUP(C81,$R$1:$S$11,2,FALSE),J80) -> Trd_car_dsl-hyb | K81: =IFERROR(IF(VALUE(C81)>2020,J81&"_"&TEXT(B81*100,"00"),"\I:"),"\I:") -> \I: | L81: =LEFT(K81,7) -> \I: | M81: =IF($K81="\I:","",C81) | N81: =IF($K81="\I:","",D81) | O81: =IF($K81="\I:","",E81) | P81: =IF($K81="\I:","",F81) | T81: =K81 -> \I: | U81: =OFFSET($S$1,MATCH(J81,$S$1:$S$11,0)-1,-1)&" -- "&TEXT(B81,"00%") -> ICE medium size hybrid diesel car -- 00% | V81: Bvkm | W81: million vehicles
J82: =IFERROR(VLOOKUP(C82,$R$1:$S$11,2,FALSE),J81) -> Trd_car_dsl-hyb | K82: =IFERROR(IF(VALUE(C82)>2020,J82&"_"&TEXT(B82*100,"00"),"\I:"),"\I:") -> \I: | L82: =LEFT(K82,7) -> \I: | M82: =IF($K82="\I:","",C82) | N82: =IF($K82="\I:","",D82) | O82: =IF($K82="\I:","",E82) | P82: =IF($K82="\I:","",F82) | T82: =K82 -> \I: | U82: =OFFSET($S$1,MATCH(J82,$S$1:$S$11,0)-1,-1)&" -- "&TEXT(B82,"00%") -> ICE medium size hybrid diesel car -- 00% | V82: Bvkm | W82: million vehicles
C83: 2020 | D83: 2030 | E83: 2040 | F83: 2050 | J83: =IFERROR(VLOOKUP(C83,$R$1:$S$11,2,FALSE),J82) -> Trd_car_dsl-hyb | K83: =IFERROR(IF(VALUE(C83)>2020,J83&"_"&TEXT(B83*100,"00"),"\I:"),"\I:") -> \I: | L83: =LEFT(K83,7) -> \I: | M83: =IF($K83="\I:","",C83) | N83: =IF($K83="\I:","",D83) | O83: =IF($K83="\I:","",E83) | P83: =IF($K83="\I:","",F83) | T83: =K83 -> \I: | U83: =OFFSET($S$1,MATCH(J83,$S$1:$S$11,0)-1,-1)&" -- "&TEXT(B83,"00%") -> ICE medium size hybrid diesel car -- 00% | V83: Bvkm | W83: million vehicles
B84: 0.17706636 | C84: 25058.749 | D84: 23982.688 | E84: 23982.688 | F84: 23982.688 | I84: =$I$64*(1+B84)/$I$12 -> 1.3328204 | J84: =IFERROR(VLOOKUP(C84,$R$1:$S$11,2,FALSE),J83) -> Trd_car_dsl-hyb | K84: =IFERROR(IF(VALUE(C84)>2020,J84&"_"&TEXT(B84*100,"00"),"\I:"),"\I:") -> Trd_car_dsl-hyb_18 | L84: =LEFT(K84,7) -> Trd_car | M84: =IF($K84="\I:","",C84) -> 25058.749 | N84: =IF($K84="\I:","",D84) -> 23982.688 | O84: =IF($K84="\I:","",E84) -> 23982.688 | P84: =IF($K84="\I:","",F84) -> 23982.688 | T84: =K84 -> Trd_car_dsl-hyb_18 | U84: =OFFSET($S$1,MATCH(J84,$S$1:$S$11,0)-1,-1)&" -- "&TEXT(B84,"00%") -> ICE medium size hybrid diesel car -- 18% | V84: Bvkm | W84: million vehicles
B85: 0.27706636 | C85: 25136.228 | D85: 24097.051 | E85: 24097.051 | F85: 24097.051 | I85: =$I$64*(1+B85)/$I$12 -> 1.4460528 | J85: =IFERROR(VLOOKUP(C85,$R$1:$S$11,2,FALSE),J84) -> Trd_car_dsl-hyb | K85: =IFERROR(IF(VALUE(C85)>2020,J85&"_"&TEXT(B85*100,"00"),"\I:"),"\I:") -> Trd_car_dsl-hyb_28 | L85: =LEFT(K85,7) -> Trd_car | M85: =IF($K85="\I:","",C85) -> 25136.228 | N85: =IF($K85="\I:","",D85) -> 24097.051 | O85: =IF($K85="\I:","",E85) -> 24097.051 | P85: =IF($K85="\I:","",F85) -> 24097.051 | T85: =K85 -> Trd_car_dsl-hyb_28 | U85: =OFFSET($S$1,MATCH(J85,$S$1:$S$11,0)-1,-1)&" -- "&TEXT(B85,"00%") -> ICE medium size hybrid diesel car -- 28% | V85: Bvkm | W85: million vehicles
B86: 0.32706636 | C86: 25231.537 | D86: 24214.514 | E86: 24214.514 | F86: 24214.514 | I86: =$I$64*(1+B86)/$I$12 -> 1.502669 | J86: =IFERROR(VLOOKUP(C86,$R$1:$S$11,2,FALSE),J85) -> Trd_car_dsl-hyb | K86: =IFERROR(IF(VALUE(C86)>2020,J86&"_"&TEXT(B86*100,"00"),"\I:"),"\I:") -> Trd_car_dsl-hyb_33 | L86: =LEFT(K86,7) -> Trd_car | M86: =IF($K86="\I:","",C86) -> 25231.537 | N86: =IF($K86="\I:","",D86) -> 24214.514 | O86: =IF($K86="\I:","",E86) -> 24214.514 | P86: =IF($K86="\I:","",F86) -> 24214.514 | T86: =K86 -> Trd_car_dsl-hyb_33 | U86: =OFFSET($S$1,MATCH(J86,$S$1:$S$11,0)-1,-1)&" -- "&TEXT(B86,"00%") -> ICE medium size hybrid diesel car -- 33% | V86: Bvkm | W86: million vehicles
B87: 0.37706636 | C87: 25440.788 | D87: 24383.722 | E87: 24383.722 | F87: 24383.722 | I87: =$I$64*(1+B87)/$I$12 -> 1.5592852 | J87: =IFERROR(VLOOKUP(C87,$R$1:$S$11,2,FALSE),J86) -> Trd_car_dsl-hyb | K87: =IFERROR(IF(VALUE(C87)>2020,J87&"_"&TEXT(B87*100,"00"),"\I:"),"\I:") -> Trd_car_dsl-hyb_38 | L87: =LEFT(K87,7) -> Trd_car | M87: =IF($K87="\I:","",C87) -> 25440.788 | N87: =IF($K87="\I:","",D87) -> 24383.722 | O87: =IF($K87="\I:","",E87) -> 24383.722 | P87: =IF($K87="\I:","",F87) -> 24383.722 | T87: =K87 -> Trd_car_dsl-hyb_38 | U87: =OFFSET($S$1,MATCH(J87,$S$1:$S$11,0)-1,-1)&" -- "&TEXT(B87,"00%") -> ICE medium size hybrid diesel car -- 38% | V87: Bvkm | W87: million vehicles
B88: 0.42706636 | C88: 25786.587 | D88: 24612.879 | E88: 24612.879 | F88: 24612.879 | I88: =$I$64*(1+B88)/$I$12 -> 1.6159014 | J88: =IFERROR(VLOOKUP(C88,$R$1:$S$11,2,FALSE),J87) -> Trd_car_dsl-hyb | K88: =IFERROR(IF(VALUE(C88)>2020,J88&"_"&TEXT(B88*100,"00"),"\I:"),"\I:") -> Trd_car_dsl-hyb_43 | L88: =LEFT(K88,7) -> Trd_car | M88: =IF($K88="\I:","",C88) -> 25786.587 | N88: =IF($K88="\I:","",D88) -> 24612.879 | O88: =IF($K88="\I:","",E88) -> 24612.879 | P88: =IF($K88="\I:","",F88) -> 24612.879 | T88: =K88 -> Trd_car_dsl-hyb_43 | U88: =OFFSET($S$1,MATCH(J88,$S$1:$S$11,0)-1,-1)&" -- "&TEXT(B88,"00%") -> ICE medium size hybrid diesel car -- 43% | V88: Bvkm | W88: million vehicles
B89: 0.47706636 | C89: 35085.422 | D89: 25042.69 | E89: 25042.69 | F89: 25042.69 | I89: =$I$64*(1+B89)/$I$12 -> 1.6725176 | J89: =IFERROR(VLOOKUP(C89,$R$1:$S$11,2,FALSE),J88) -> Trd_car_dsl-hyb | K89: =IFERROR(IF(VALUE(C89)>2020,J89&"_"&TEXT(B89*100,"00"),"\I:"),"\I:") -> Trd_car_dsl-hyb_48 | L89: =LEFT(K89,7) -> Trd_car | M89: =IF($K89="\I:","",C89) -> 35085.422 | N89: =IF($K89="\I:","",D89) -> 25042.69 | O89: =IF($K89="\I:","",E89) -> 25042.69 | P89: =IF($K89="\I:","",F89) -> 25042.69 | T89: =K89 -> Trd_car_dsl-hyb_48 | U89: =OFFSET($S$1,MATCH(J89,$S$1:$S$11,0)-1,-1)&" -- "&TEXT(B89,"00%") -> ICE medium size hybrid diesel car -- 48% | V89: Bvkm | W89: million vehicles
B90: 0.52706636 | C90: 117946.54 | D90: 32577.27 | E90: 32577.27 | F90: 32577.27 | I90: =$I$64*(1+B90)/$I$12 -> 1.7291338 | J90: =IFERROR(VLOOKUP(C90,$R$1:$S$11,2,FALSE),J89) -> Trd_car_dsl-hyb | K90: =IFERROR(IF(VALUE(C90)>2020,J90&"_"&TEXT(B90*100,"00"),"\I:"),"\I:") -> Trd_car_dsl-hyb_53 | L90: =LEFT(K90,7) -> Trd_car | M90: =IF($K90="\I:","",C90) -> 117946.54 | N90: =IF($K90="\I:","",D90) -> 32577.27 | O90: =IF($K90="\I:","",E90) -> 32577.27 | P90: =IF($K90="\I:","",F90) -> 32577.27 | T90: =K90 -> Trd_car_dsl-hyb_53 | U90: =OFFSET($S$1,MATCH(J90,$S$1:$S$11,0)-1,-1)&" -- "&TEXT(B90,"00%") -> ICE medium size hybrid diesel car -- 53% | V90: Bvkm | W90: million vehicles
J91: =IFERROR(VLOOKUP(C91,$R$1:$S$11,2,FALSE),J90) -> Trd_car_dsl-hyb | K91: =IFERROR(IF(VALUE(C91)>2020,J91&"_"&TEXT(B91*100,"00"),"\I:"),"\I:") -> \I: | L91: =LEFT(K91,7) -> \I: | M91: =IF($K91="\I:","",C91) | N91: =IF($K91="\I:","",D91) | O91: =IF($K91="\I:","",E91) | P91: =IF($K91="\I:","",F91) | T91: =K91 -> \I: | U91: =OFFSET($S$1,MATCH(J91,$S$1:$S$11,0)-1,-1)&" -- "&TEXT(B91,"00%") -> ICE medium size hybrid diesel car -- 00% | V91: Bvkm | W91: million vehicles
J92: =IFERROR(VLOOKUP(C92,$R$1:$S$11,2,FALSE),J91) -> Trd_car_dsl-hyb | K92: =IFERROR(IF(VALUE(C92)>2020,J92&"_"&TEXT(B92*100,"00"),"\I:"),"\I:") -> \I: | L92: =LEFT(K92,7) -> \I: | M92: =IF($K92="\I:","",C92) | N92: =IF($K92="\I:","",D92) | O92: =IF($K92="\I:","",E92) | P92: =IF($K92="\I:","",F92) | T92: =K92 -> \I: | U92: =OFFSET($S$1,MATCH(J92,$S$1:$S$11,0)-1,-1)&" -- "&TEXT(B92,"00%") -> ICE medium size hybrid diesel car -- 00% | V92: Bvkm | W92: million vehicles
J93: =IFERROR(VLOOKUP(C93,$R$1:$S$11,2,FALSE),J92) -> Trd_car_dsl-hyb | K93: =IFERROR(IF(VALUE(C93)>2020,J93&"_"&TEXT(B93*100,"00"),"\I:"),"\I:") -> \I: | L93: =LEFT(K93,7) -> \I: | M93: =IF($K93="\I:","",C93) | N93: =IF($K93="\I:","",D93) | O93: =IF($K93="\I:","",E93) | P93: =IF($K93="\I:","",F93) | T93: =K93 -> \I: | U93: =OFFSET($S$1,MATCH(J93,$S$1:$S$11,0)-1,-1)&" -- "&TEXT(B93,"00%") -> ICE medium size hybrid diesel car -- 00% | V93: Bvkm | W93: million vehicles
J94: =IFERROR(VLOOKUP(C94,$R$1:$S$11,2,FALSE),J93) -> Trd_car_dsl-hyb | K94: =IFERROR(IF(VALUE(C94)>2020,J94&"_"&TEXT(B94*100,"00"),"\I:"),"\I:") -> \I: | L94: =LEFT(K94,7) -> \I: | M94: =IF($K94="\I:","",C94) | N94: =IF($K94="\I:","",D94) | O94: =IF($K94="\I:","",E94) | P94: =IF($K94="\I:","",F94) | T94: =K94 -> \I: | U94: =OFFSET($S$1,MATCH(J94,$S$1:$S$11,0)-1,-1)&" -- "&TEXT(B94,"00%") -> ICE medium size hybrid diesel car -- 00% | V94: Bvkm | W94: million vehicles
B95: Reduction of specific energy consumption relative to 2015 diesel vehicle (%) | C95: ICE medium size plug-in hybrid diesel car | J95: =IFERROR(VLOOKUP(C95,$R$1:$S$11,2,FALSE),J94) -> Trd_car_dsl-pih | K95: =IFERROR(IF(VALUE(C95)>2020,J95&"_"&TEXT(B95*100,"00"),"\I:"),"\I:") -> \I: | L95: =LEFT(K95,7) -> \I: | M95: =IF($K95="\I:","",C95) | N95: =IF($K95="\I:","",D95) | O95: =IF($K95="\I:","",E95) | P95: =IF($K95="\I:","",F95) | T95: =K95 -> \I: | U95: =OFFSET($S$1,MATCH(J95,$S$1:$S$11,0)-1,-1)&" -- "&TEXT(B95,"00%") -> ICE medium size plug-in hybrid diesel car -- Reduction of specific energy consumption relative to 2015 diesel vehicle (%) | V95: Bvkm | W95: million vehicles
J96: =IFERROR(VLOOKUP(C96,$R$1:$S$11,2,FALSE),J95) -> Trd_car_dsl-pih | K96: =IFERROR(IF(VALUE(C96)>2020,J96&"_"&TEXT(B96*100,"00"),"\I:"),"\I:") -> \I: | L96: =LEFT(K96,7) -> \I: | M96: =IF($K96="\I:","",C96) | N96: =IF($K96="\I:","",D96) | O96: =IF($K96="\I:","",E96) | P96: =IF($K96="\I:","",F96) | T96: =K96 -> \I: | U96: =OFFSET($S$1,MATCH(J96,$S$1:$S$11,0)-1,-1)&" -- "&TEXT(B96,"00%") -> ICE medium size plug-in hybrid diesel car -- 00% | V96: Bvkm | W96: million vehicles
J97: =IFERROR(VLOOKUP(C97,$R$1:$S$11,2,FALSE),J96) -> Trd_car_dsl-pih | K97: =IFERROR(IF(VALUE(C97)>2020,J97&"_"&TEXT(B97*100,"00"),"\I:"),"\I:") -> \I: | L97: =LEFT(K97,7) -> \I: | M97: =IF($K97="\I:","",C97) | N97: =IF($K97="\I:","",D97) | O97: =IF($K97="\I:","",E97) | P97: =IF($K97="\I:","",F97) | T97: =K97 -> \I: | U97: =OFFSET($S$1,MATCH(J97,$S$1:$S$11,0)-1,-1)&" -- "&TEXT(B97,"00%") -> ICE medium size plug-in hybrid diesel car -- 00% | V97: Bvkm | W97: million vehicles
C98: 2020 | D98: 2030 | E98: 2040 | F98: 2050 | J98: =IFERROR(VLOOKUP(C98,$R$1:$S$11,2,FALSE),J97) -> Trd_car_dsl-pih | K98: =IFERROR(IF(VALUE(C98)>2020,J98&"_"&TEXT(B98*100,"00"),"\I:"),"\I:") -> \I: | L98: =LEFT(K98,7) -> \I: | M98: =IF($K98="\I:","",C98) | N98: =IF($K98="\I:","",D98) | O98: =IF($K98="\I:","",E98) | P98: =IF($K98="\I:","",F98) | T98: =K98 -> \I: | U98: =OFFSET($S$1,MATCH(J98,$S$1:$S$11,0)-1,-1)&" -- "&TEXT(B98,"00%") -> ICE medium size plug-in hybrid diesel car -- 00% | V98: Bvkm | W98: million vehicles
B99: 0.69519813 | C99: 29170.689 | D99: 25403.453 | E99: 24438.88 | F99: 24157.557 | I99: =$I$64*(1+B99)/$I$12 -> 1.9195134 | J99: =IFERROR(VLOOKUP(C99,$R$1:$S$11,2,FALSE),J98) -> Trd_car_dsl-pih | K99: =IFERROR(IF(VALUE(C99)>2020,J99&"_"&TEXT(B99*100,"00"),"\I:"),"\I:") -> Trd_car_dsl-pih_70 | L99: =LEFT(K99,7) -> Trd_car | M99: =IF($K99="\I:","",C99) -> 29170.689 | N99: =IF($K99="\I:","",D99) -> 25403.453 | O99: =IF($K99="\I:","",E99) -> 24438.88 | P99: =IF($K99="\I:","",F99) -> 24157.557 | T99: =K99 -> Trd_car_dsl-pih_70 | U99: =OFFSET($S$1,MATCH(J99,$S$1:$S$11,0)-1,-1)&" -- "&TEXT(B99,"00%") -> ICE medium size plug-in hybrid diesel car -- 70% | V99: Bvkm | W99: million vehicles
B100: 0.70519813 | C100: 29227.319 | D100: 25418.579 | E100: 24443.382 | F100: 24158.354 | I100: =$I$64*(1+B100)/$I$12 -> 1.9308366 | J100: =IFERROR(VLOOKUP(C100,$R$1:$S$11,2,FALSE),J99) -> Trd_car_dsl-pih | K100: =IFERROR(IF(VALUE(C100)>2020,J100&"_"&TEXT(B100*100,"00"),"\I:"),"\I:") -> Trd_car_dsl-pih_71 | L100: =LEFT(K100,7) -> Trd_car | M100: =IF($K100="\I:","",C100) -> 29227.319 | N100: =IF($K100="\I:","",D100) -> 25418.579 | O100: =IF($K100="\I:","",E100) -> 24443.382 | P100: =IF($K100="\I:","",F100) -> 24158.354 | T100: =K100 -> Trd_car_dsl-pih_71 | U100: =OFFSET($S$1,MATCH(J100,$S$1:$S$11,0)-1,-1)&" -- "&TEXT(B100,"00%") -> ICE medium size plug-in hybrid diesel car -- 71% | V100: Bvkm | W100: million vehicles
B101: 0.71519813 | C101: 29350.925 | D101: 25446.448 | E101: 24463.472 | F101: 24176.215 | I101: =$I$64*(1+B101)/$I$12 -> 1.9421599 | J101: =IFERROR(VLOOKUP(C101,$R$1:$S$11,2,FALSE),J100) -> Trd_car_dsl-pih | K101: =IFERROR(IF(VALUE(C101)>2020,J101&"_"&TEXT(B101*100,"00"),"\I:"),"\I:") -> Trd_car_dsl-pih_72 | L101: =LEFT(K101,7) -> Trd_car | M101: =IF($K101="\I:","",C101) -> 29350.925 | N101: =IF($K101="\I:","",D101) -> 25446.448 | O101: =IF($K101="\I:","",E101) -> 24463.472 | P101: =IF($K101="\I:","",F101) -> 24176.215 | T101: =K101 -> Trd_car_dsl-pih_72 | U101: =OFFSET($S$1,MATCH(J101,$S$1:$S$11,0)-1,-1)&" -- "&TEXT(B101,"00%") -> ICE medium size plug-in hybrid diesel car -- 72% | V101: Bvkm | W101: million vehicles
...

Sheet LCVs
B1: Modelled economic possibilities for reducing specific energy consumption by transport mode/equipment and fuel/technology over time | Q1: gsl | R1: ICE gasoline LCV | S1: ="Trd_lcv_"&Q1 -> Trd_lcv_gsl
B2: © E3-Modelling | Q2: gsl-hyb | R2: ICE gasoline hybrid LCV | S2: ="Trd_lcv_"&Q2 -> Trd_lcv_gsl-hyb
Q3: gsl-pih | R3: ICE gasoline plug-in hybrid LCV | S3: ="Trd_lcv_"&Q3 -> Trd_lcv_gsl-pih
Q4: dsl | R4: ICE diesel LCV | S4: ="Trd_lcv_"&Q4 -> Trd_lcv_dsl
Q5: dsl-hyb | R5: ICE hybrid diesel LCV | S5: ="Trd_lcv_"&Q5 -> Trd_lcv_dsl-hyb
Q6: dsl-pih | R6: ICE plug-in hybrid diesel LCV | S6: ="Trd_lcv_"&Q6 -> Trd_lcv_dsl-pih
F7: =31536000/10^9 -> 0.031536 | G7: GJ/lt Gasoline | Q7: cng | R7: ICE CNG LCV | S7: ="Trd_lcv_"&Q7 -> Trd_lcv_cng
F8: 0.038 | G8: GJ/lt Diesel | Q8: lpg | R8: ICE LPG LCV | S8: ="\I:Trd_lcv_"&Q8 -> \I:Trd_lcv_lpg
B9: Reference values for gasoline LCV | F9: =1.406/26.137 -> 0.053793473 | G9: GJ/kg CNG | Q9: elc | R9: Battery electric LCV | S9: ="Trd_lcv_"&Q9 -> Trd_lcv_elc
B10: 2015 | F10: 0.02559 | G10: GJ/lt LPG | Q10: hh2 | R10: Hydrogen fuel cell LCV | S10: ="Trd_lcv_"&Q10 -> Trd_lcv_hh2
B11: Energy consumption | C11: lt/100 km | D11: 8.5078255 | G11: =D11*$F$7/100*10^9/10^6 -> 2.6830279 | I11: =1/G11 -> 0.37271324
B12: Capital cost | C12: Euro15 /veh | D12: 17407.979 | I12: bvkm/PJ
K14: ~FI_T: UP~EUR15~INVCOST | S14: ~FI_Process
I15: EFF | J15: *process | K15: Process | L15: Comm-OUT | M15: =C19 -> 2020 | N15: =D19 -> 2030 | O15: =E19 -> 2040 | P15: =F19 -> 2050 | Q15: FLO_MARK | S15: Sets | T15: TechName | U15: TechDesc | V15: Tact | W15: Tcap
B16: Reduction of specific energy consumption relative to 2015 gasoline vehicle (%) | C16: ICE gasoline LCV | J16: =IFERROR(VLOOKUP(C16,$R$1:$S$10,2,FALSE),J14) -> Trd_lcv_gsl | K16: =IFERROR(IF(VALUE(C16)>2020,J16&"_"&TEXT(B16*100,"00"),"\I:"),"\I:") -> \I: | L16: =LEFT(K16,7) -> \I: | M16: =IF($K16="\I:","",C16) | N16: =IF($K16="\I:","",D16) | O16: =IF($K16="\I:","",E16) | P16: =IF($K16="\I:","",F16) | S16: DMD | T16: =K16 -> \I: | U16: =OFFSET($S$1,MATCH(J16,$S$1:$S$10,0)-1,-1)&" -- "&TEXT(B16,"00%") -> ICE gasoline LCV -- Reduction of specific energy consumption relative to 2015 gasoline vehicle (%) | V16: Bvkm | W16: million vehicles
J17: =IFERROR(VLOOKUP(C17,$R$1:$S$10,2,FALSE),J16) -> Trd_lcv_gsl | K17: =IFERROR(IF(VALUE(C17)>2020,J17&"_"&TEXT(B17*100,"00"),"\I:"),"\I:") -> \I: | L17: =LEFT(K17,7) -> \I: | M17: =IF($K17="\I:","",C17) | N17: =IF($K17="\I:","",D17) | O17: =IF($K17="\I:","",E17) | P17: =IF($K17="\I:","",F17) | S17: DMD | T17: =K17 -> \I: | U17: =OFFSET($S$1,MATCH(J17,$S$1:$S$10,0)-1,-1)&" -- "&TEXT(B17,"00%") -> ICE gasoline LCV -- 00% | V17: Bvkm | W17: million vehicles
J18: =IFERROR(VLOOKUP(C18,$R$1:$S$10,2,FALSE),J17) -> Trd_lcv_gsl | K18: =IFERROR(IF(VALUE(C18)>2020,J18&"_"&TEXT(B18*100,"00"),"\I:"),"\I:") -> \I: | L18: =LEFT(K18,7) -> \I: | M18: =IF($K18="\I:","",C18) | N18: =IF($K18="\I:","",D18) | O18: =IF($K18="\I:","",E18) | P18: =IF($K18="\I:","",F18) | S18: DMD | T18: =K18 -> \I: | U18: =OFFSET($S$1,MATCH(J18,$S$1:$S$10,0)-1,-1)&" -- "&TEXT(B18,"00%") -> ICE gasoline LCV -- 00% | V18: Bvkm | W18: million vehicles
C19: 2020 | D19: 2030 | E19: 2040 | F19: 2050 | I19: 1 | J19: =IFERROR(VLOOKUP(C19,$R$1:$S$11,2,FALSE),J18) -> Trd_lcv_gsl | K19: =IFERROR(IF(VALUE(C19)>200,J19&"_"&TEXT(B19*100,"00"),"\I:"),"\I:") -> Trd_lcv_gsl_00 | L19: =LEFT(K19,7) -> Trd_lcv | M19: =D12 -> 17407.979 | S19: DMD | T19: =K19 -> Trd_lcv_gsl_00 | U19: =OFFSET($S$1,MATCH(J19,$S$1:$S$10,0)-1,-1)&" -- "&TEXT(B19,"00%") -> ICE gasoline LCV -- 00% | V19: Bvkm | W19: million vehicles
B20: 0.14556058 | C20: 17878.598 | D20: 17417.427 | E20: 17417.427 | F20: 17417.427 | I20: =(1+B20) -> 1.1455606 | J20: =IFERROR(VLOOKUP(C20,$R$1:$S$10,2,FALSE),J19) -> Trd_lcv_gsl | K20: =IFERROR(IF(VALUE(C20)>2020,J20&"_"&TEXT(B20*100,"00"),"\I:"),"\I:") -> Trd_lcv_gsl_15 | L20: =LEFT(K20,7) -> Trd_lcv | M20: =IF($K20="\I:","",C20) -> 17878.598 | N20: =IF($K20="\I:","",D20) -> 17417.427 | O20: =IF($K20="\I:","",E20) -> 17417.427 | P20: =IF($K20="\I:","",F20) -> 17417.427 | S20: DMD | T20: =K20 -> Trd_lcv_gsl_15 | U20: =OFFSET($S$1,MATCH(J20,$S$1:$S$10,0)-1,-1)&" -- "&TEXT(B20,"00%") -> ICE gasoline LCV -- 15% | V20: Bvkm | W20: million vehicles
B21: 0.24556058 | C21: 19243.432 | D21: 17966.601 | E21: 17966.601 | F21: 17966.601 | I21: =(1+B21) -> 1.2455606 | J21: =IFERROR(VLOOKUP(C21,$R$1:$S$10,2,FALSE),J20) -> Trd_lcv_gsl | K21: =IFERROR(IF(VALUE(C21)>2020,J21&"_"&TEXT(B21*100,"00"),"\I:"),"\I:") -> Trd_lcv_gsl_25 | L21: =LEFT(K21,7) -> Trd_lcv | M21: =IF($K21="\I:","",C21) -> 19243.432 | N21: =IF($K21="\I:","",D21) -> 17966.601 | O21: =IF($K21="\I:","",E21) -> 17966.601 | P21: =IF($K21="\I:","",F21) -> 17966.601 | S21: DMD | T21: =K21 -> Trd_lcv_gsl_25 | U21: =OFFSET($S$1,MATCH(J21,$S$1:$S$10,0)-1,-1)&" -- "&TEXT(B21,"00%") -> ICE gasoline LCV -- 25% | V21: Bvkm | W21: million vehicles
B22: 0.34556058 | C22: 24327.604 | D22: 19194.381 | E22: 19194.381 | F22: 19194.381 | I22: =(1+B22) -> 1.3455606 | J22: =IFERROR(VLOOKUP(C22,$R$1:$S$10,2,FALSE),J21) -> Trd_lcv_gsl | K22: =IFERROR(IF(VALUE(C22)>2020,J22&"_"&TEXT(B22*100,"00"),"\I:"),"\I:") -> Trd_lcv_gsl_35 | L22: =LEFT(K22,7) -> Trd_lcv | M22: =IF($K22="\I:","",C22) -> 24327.604 | N22: =IF($K22="\I:","",D22) -> 19194.381 | O22: =IF($K22="\I:","",E22) -> 19194.381 | P22: =IF($K22="\I:","",F22) -> 19194.381 | S22: DMD | T22: =K22 -> Trd_lcv_gsl_35 | U22: =OFFSET($S$1,MATCH(J22,$S$1:$S$10,0)-1,-1)&" -- "&TEXT(B22,"00%") -> ICE gasoline LCV -- 35% | V22: Bvkm | W22: million vehicles
B23: 0.39556058 | C23: 32775.022 | D23: 21558.477 | E23: 21558.477 | F23: 21558.477 | I23: =(1+B23) -> 1.3955606 | J23: =IFERROR(VLOOKUP(C23,$R$1:$S$10,2,FALSE),J22) -> Trd_lcv_gsl | K23: =IFERROR(IF(VALUE(C23)>2020,J23&"_"&TEXT(B23*100,"00"),"\I:"),"\I:") -> Trd_lcv_gsl_40 | L23: =LEFT(K23,7) -> Trd_lcv | M23: =IF($K23="\I:","",C23) -> 32775.022 | N23: =IF($K23="\I:","",D23) -> 21558.477 | O23: =IF($K23="\I:","",E23) -> 21558.477 | P23: =IF($K23="\I:","",F23) -> 21558.477 | S23: DMD | T23: =K23 -> Trd_lcv_gsl_40 | U23: =OFFSET($S$1,MATCH(J23,$S$1:$S$10,0)-1,-1)&" -- "&TEXT(B23,"00%") -> ICE gasoline LCV -- 40% | V23: Bvkm | W23: million vehicles
B24: 0.44556058 | C24: 99589.703 | D24: 26988.331 | E24: 26988.331 | F24: 26988.331 | I24: =(1+B24) -> 1.4455606 | J24: =IFERROR(VLOOKUP(C24,$R$1:$S$10,2,FALSE),J23) -> Trd_lcv_gsl | K24: =IFERROR(IF(VALUE(C24)>2020,J24&"_"&TEXT(B24*100,"00"),"\I:"),"\I:") -> Trd_lcv_gsl_45 | L24: =LEFT(K24,7) -> Trd_lcv | M24: =IF($K24="\I:","",C24) -> 99589.703 | N24: =IF($K24="\I:","",D24) -> 26988.331 | O24: =IF($K24="\I:","",E24) -> 26988.331 | P24: =IF($K24="\I:","",F24) -> 26988.331 | S24: DMD | T24: =K24 -> Trd_lcv_gsl_45 | U24: =OFFSET($S$1,MATCH(J24,$S$1:$S$10,0)-1,-1)&" -- "&TEXT(B24,"00%") -> ICE gasoline LCV -- 45% | V24: Bvkm | W24: million vehicles
B25: 0.49556058 | C25: 116875.34 | D25: 78477.079 | E25: 78477.079 | F25: 78477.079 | I25: =(1+B25) -> 1.4955606 | J25: =IFERROR(VLOOKUP(C25,$R$1:$S$10,2,FALSE),J24) -> Trd_lcv_gsl | K25: =IFERROR(IF(VALUE(C25)>2020,J25&"_"&TEXT(B25*100,"00"),"\I:"),"\I:") -> Trd_lcv_gsl_50 | L25: =LEFT(K25,7) -> Trd_lcv | M25: =IF($K25="\I:","",C25) -> 116875.34 | N25: =IF($K25="\I:","",D25) -> 78477.079 | O25: =IF($K25="\I:","",E25) -> 78477.079 | P25: =IF($K25="\I:","",F25) -> 78477.079 | S25: DMD | T25: =K25 -> Trd_lcv_gsl_50 | U25: =OFFSET($S$1,MATCH(J25,$S$1:$S$10,0)-1,-1)&" -- "&TEXT(B25,"00%") -> ICE gasoline LCV -- 50% | V25: Bvkm | W25: million vehicles
J26: =IFERROR(VLOOKUP(C26,$R$1:$S$10,2,FALSE),J25) -> Trd_lcv_gsl | K26: =IFERROR(IF(VALUE(C26)>2020,J26&"_"&TEXT(B26*100,"00"),"\I:"),"\I:") -> \I: | L26: =LEFT(K26,7) -> \I: | M26: =IF($K26="\I:","",C26) | N26: =IF($K26="\I:","",D26) | O26: =IF($K26="\I:","",E26) | P26: =IF($K26="\I:","",F26) | T26: =K26 -> \I: | U26: =OFFSET($S$1,MATCH(J26,$S$1:$S$10,0)-1,-1)&" -- "&TEXT(B26,"00%") -> ICE gasoline LCV -- 00% | V26: Bvkm | W26: million vehicles
J27: =IFERROR(VLOOKUP(C27,$R$1:$S$10,2,FALSE),J26) -> Trd_lcv_gsl | K27: =IFERROR(IF(VALUE(C27)>2020,J27&"_"&TEXT(B27*100,"00"),"\I:"),"\I:") -> \I: | L27: =LEFT(K27,7) -> \I: | M27: =IF($K27="\I:","",C27) | N27: =IF($K27="\I:","",D27) | O27: =IF($K27="\I:","",E27) | P27: =IF($K27="\I:","",F27) | T27: =K27 -> \I: | U27: =OFFSET($S$1,MATCH(J27,$S$1:$S$10,0)-1,-1)&" -- "&TEXT(B27,"00%") -> ICE gasoline LCV -- 00% | V27: Bvkm | W27: million vehicles
J28: =IFERROR(VLOOKUP(C28,$R$1:$S$10,2,FALSE),J27) -> Trd_lcv_gsl | K28: =IFERROR(IF(VALUE(C28)>2020,J28&"_"&TEXT(B28*100,"00"),"\I:"),"\I:") -> \I: | L28: =LEFT(K28,7) -> \I: | M28: =IF($K28="\I:","",C28) | N28: =IF($K28="\I:","",D28) | O28: =IF($K28="\I:","",E28) | P28: =IF($K28="\I:","",F28) | T28: =K28 -> \I: | U28: =OFFSET($S$1,MATCH(J28,$S$1:$S$10,0)-1,-1)&" -- "&TEXT(B28,"00%") -> ICE gasoline LCV -- 00% | V28: Bvkm | W28: million vehicles
J29: =IFERROR(VLOOKUP(C29,$R$1:$S$10,2,FALSE),J28) -> Trd_lcv_gsl | K29: =IFERROR(IF(VALUE(C29)>2020,J29&"_"&TEXT(B29*100,"00"),"\I:"),"\I:") -> \I: | L29: =LEFT(K29,7) -> \I: | M29: =IF($K29="\I:","",C29) | N29: =IF($K29="\I:","",D29) | O29: =IF($K29="\I:","",E29) | P29: =IF($K29="\I:","",F29) | T29: =K29 -> \I: | U29: =OFFSET($S$1,MATCH(J29,$S$1:$S$10,0)-1,-1)&" -- "&TEXT(B29,"00%") -> ICE gasoline LCV -- 00% | V29: Bvkm | W29: million vehicles
B30: Reduction of specific energy consumption relative to 2015 gasoline vehicle (%) | C30: ICE gasoline hybrid LCV | J30: =IFERROR(VLOOKUP(C30,$R$1:$S$10,2,FALSE),J29) -> Trd_lcv_gsl-hyb | K30: =IFERROR(IF(VALUE(C30)>2020,J30&"_"&TEXT(B30*100,"00"),"\I:"),"\I:") -> \I: | L30: =LEFT(K30,7) -> \I: | M30: =IF($K30="\I:","",C30) | N30: =IF($K30="\I:","",D30) | O30: =IF($K30="\I:","",E30) | P30: =IF($K30="\I:","",F30) | T30: =K30 -> \I: | U30: =OFFSET($S$1,MATCH(J30,$S$1:$S$10,0)-1,-1)&" -- "&TEXT(B30,"00%") -> ICE gasoline hybrid LCV -- Reduction of specific energy consumption relative to 2015 gasoline vehicle (%) | V30: Bvkm | W30: million vehicles
J31: =IFERROR(VLOOKUP(C31,$R$1:$S$10,2,FALSE),J30) -> Trd_lcv_gsl-hyb | K31: =IFERROR(IF(VALUE(C31)>2020,J31&"_"&TEXT(B31*100,"00"),"\I:"),"\I:") -> \I: | L31: =LEFT(K31,7) -> \I: | M31: =IF($K31="\I:","",C31) | N31: =IF($K31="\I:","",D31) | O31: =IF($K31="\I:","",E31) | P31: =IF($K31="\I:","",F31) | T31: =K31 -> \I: | U31: =OFFSET($S$1,MATCH(J31,$S$1:$S$10,0)-1,-1)&" -- "&TEXT(B31,"00%") -> ICE gasoline hybrid LCV -- 00% | V31: Bvkm | W31: million vehicles
J32: =IFERROR(VLOOKUP(C32,$R$1:$S$10,2,FALSE),J31) -> Trd_lcv_gsl-hyb | K32: =IFERROR(IF(VALUE(C32)>2020,J32&"_"&TEXT(B32*100,"00"),"\I:"),"\I:") -> \I: | L32: =LEFT(K32,7) -> \I: | M32: =IF($K32="\I:","",C32) | N32: =IF($K32="\I:","",D32) | O32: =IF($K32="\I:","",E32) | P32: =IF($K32="\I:","",F32) | T32: =K32 -> \I: | U32: =OFFSET($S$1,MATCH(J32,$S$1:$S$10,0)-1,-1)&" -- "&TEXT(B32,"00%") -> ICE gasoline hybrid LCV -- 00% | V32: Bvkm | W32: million vehicles
C33: 2020 | D33: 2030 | E33: 2040 | F33: 2050 | J33: =IFERROR(VLOOKUP(C33,$R$1:$S$10,2,FALSE),J32) -> Trd_lcv_gsl-hyb | K33: =IFERROR(IF(VALUE(C33)>2020,J33&"_"&TEXT(B33*100,"00"),"\I:"),"\I:") -> \I: | L33: =LEFT(K33,7) -> \I: | M33: =IF($K33="\I:","",C33) | N33: =IF($K33="\I:","",D33) | O33: =IF($K33="\I:","",E33) | P33: =IF($K33="\I:","",F33) | T33: =K33 -> \I: | U33: =OFFSET($S$1,MATCH(J33,$S$1:$S$10,0)-1,-1)&" -- "&TEXT(B33,"00%") -> ICE gasoline hybrid LCV -- 00% | V33: Bvkm | W33: million vehicles
B34: 0.14185866 | C34: 20504.456 | D34: 19138.749 | E34: 19138.749 | F34: 19138.749 | I34: =(1+B34) -> 1.1418587 | J34: =IFERROR(VLOOKUP(C34,$R$1:$S$10,2,FALSE),J33) -> Trd_lcv_gsl-hyb | K34: =IFERROR(IF(VALUE(C34)>2020,J34&"_"&TEXT(B34*100,"00"),"\I:"),"\I:") -> Trd_lcv_gsl-hyb_14 | L34: =LEFT(K34,7) -> Trd_lcv | M34: =IF($K34="\I:","",C34) -> 20504.456 | N34: =IF($K34="\I:","",D34) -> 19138.749 | O34: =IF($K34="\I:","",E34) -> 19138.749 | P34: =IF($K34="\I:","",F34) -> 19138.749 | T34: =K34 -> Trd_lcv_gsl-hyb_14 | U34: =OFFSET($S$1,MATCH(J34,$S$1:$S$10,0)-1,-1)&" -- "&TEXT(B34,"00%") -> ICE gasoline hybrid LCV -- 14% | V34: Bvkm | W34: million vehicles
B35: 0.24185866 | C35: 20722.243 | D35: 19390.083 | E35: 19390.083 | F35: 19390.083 | I35: =(1+B35) -> 1.2418587 | J35: =IFERROR(VLOOKUP(C35,$R$1:$S$10,2,FALSE),J34) -> Trd_lcv_gsl-hyb | K35: =IFERROR(IF(VALUE(C35)>2020,J35&"_"&TEXT(B35*100,"00"),"\I:"),"\I:") -> Trd_lcv_gsl-hyb_24 | L35: =LEFT(K35,7) -> Trd_lcv | M35: =IF($K35="\I:","",C35) -> 20722.243 | N35: =IF($K35="\I:","",D35) -> 19390.083 | O35: =IF($K35="\I:","",E35) -> 19390.083 | P35: =IF($K35="\I:","",F35) -> 19390.083 | T35: =K35 -> Trd_lcv_gsl-hyb_24 | U35: =OFFSET($S$1,MATCH(J35,$S$1:$S$10,0)-1,-1)&" -- "&TEXT(B35,"00%") -> ICE gasoline hybrid LCV -- 24% | V35: Bvkm | W35: million vehicles
B36: 0.29185866 | C36: 20967.658 | D36: 19601.209 | E36: 19601.209 | F36: 19601.209 | I36: =(1+B36) -> 1.2918587 | J36: =IFERROR(VLOOKUP(C36,$R$1:$S$10,2,FALSE),J35) -> Trd_lcv_gsl-hyb | K36: =IFERROR(IF(VALUE(C36)>2020,J36&"_"&TEXT(B36*100,"00"),"\I:"),"\I:") -> Trd_lcv_gsl-hyb_29 | L36: =LEFT(K36,7) -> Trd_lcv | M36: =IF($K36="\I:","",C36) -> 20967.658 | N36: =IF($K36="\I:","",D36) -> 19601.209 | O36: =IF($K36="\I:","",E36) -> 19601.209 | P36: =IF($K36="\I:","",F36) -> 19601.209 | T36: =K36 -> Trd_lcv_gsl-hyb_29 | U36: =OFFSET($S$1,MATCH(J36,$S$1:$S$10,0)-1,-1)&" -- "&TEXT(B36,"00%") -> ICE gasoline hybrid LCV -- 29% | V36: Bvkm | W36: million vehicles
B37: 0.34185866 | C37: 21437.622 | D37: 19855.904 | E37: 19855.904 | F37: 19855.904 | I37: =(1+B37) -> 1.3418587 | J37: =IFERROR(VLOOKUP(C37,$R$1:$S$10,2,FALSE),J36) -> Trd_lcv_gsl-hyb | K37: =IFERROR(IF(VALUE(C37)>2020,J37&"_"&TEXT(B37*100,"00"),"\I:"),"\I:") -> Trd_lcv_gsl-hyb_34 | L37: =LEFT(K37,7) -> Trd_lcv | M37: =IF($K37="\I:","",C37) -> 21437.622 | N37: =IF($K37="\I:","",D37) -> 19855.904 | O37: =IF($K37="\I:","",E37) -> 19855.904 | P37: =IF($K37="\I:","",F37) -> 19855.904 | T37: =K37 -> Trd_lcv_gsl-hyb_34 | U37: =OFFSET($S$1,MATCH(J37,$S$1:$S$10,0)-1,-1)&" -- "&TEXT(B37,"00%") -> ICE gasoline hybrid LCV -- 34% | V37: Bvkm | W37: million vehicles
B38: 0.39185866 | C38: 22211.009 | D38: 20325.563 | E38: 20325.563 | F38: 20325.563 | I38: =(1+B38) -> 1.3918587 | J38: =IFERROR(VLOOKUP(C38,$R$1:$S$10,2,FALSE),J37) -> Trd_lcv_gsl-hyb | K38: =IFERROR(IF(VALUE(C38)>2020,J38&"_"&TEXT(B38*100,"00"),"\I:"),"\I:") -> Trd_lcv_gsl-hyb_39 | L38: =LEFT(K38,7) -> Trd_lcv | M38: =IF($K38="\I:","",C38) -> 22211.009 | N38: =IF($K38="\I:","",D38) -> 20325.563 | O38: =IF($K38="\I:","",E38) -> 20325.563 | P38: =IF($K38="\I:","",F38) -> 20325.563 | T38: =K38 -> Trd_lcv_gsl-hyb_39 | U38: =OFFSET($S$1,MATCH(J38,$S$1:$S$10,0)-1,-1)&" -- "&TEXT(B38,"00%") -> ICE gasoline hybrid LCV -- 39% | V38: Bvkm | W38: million vehicles
B39: 0.44185866 | C39: 46471.149 | D39: 26131.898 | E39: 26131.898 | F39: 26131.898 | I39: =(1+B39) -> 1.4418587 | J39: =IFERROR(VLOOKUP(C39,$R$1:$S$10,2,FALSE),J38) -> Trd_lcv_gsl-hyb | K39: =IFERROR(IF(VALUE(C39)>2020,J39&"_"&TEXT(B39*100,"00"),"\I:"),"\I:") -> Trd_lcv_gsl-hyb_44 | L39: =LEFT(K39,7) -> Trd_lcv | M39: =IF($K39="\I:","",C39) -> 46471.149 | N39: =IF($K39="\I:","",D39) -> 26131.898 | O39: =IF($K39="\I:","",E39) -> 26131.898 | P39: =IF($K39="\I:","",F39) -> 26131.898 | T39: =K39 -> Trd_lcv_gsl-hyb_44 | U39: =OFFSET($S$1,MATCH(J39,$S$1:$S$10,0)-1,-1)&" -- "&TEXT(B39,"00%") -> ICE gasoline hybrid LCV -- 44% | V39: Bvkm | W39: million vehicles
B40: 0.49185866 | C40: 108265.76 | D40: 77485.562 | E40: 77485.562 | F40: 77485.562 | I40: =(1+B40) -> 1.4918587 | J40: =IFERROR(VLOOKUP(C40,$R$1:$S$10,2,FALSE),J39) -> Trd_lcv_gsl-hyb | K40: =IFERROR(IF(VALUE(C40)>2020,J40&"_"&TEXT(B40*100,"00"),"\I:"),"\I:") -> Trd_lcv_gsl-hyb_49 | L40: =LEFT(K40,7) -> Trd_lcv | M40: =IF($K40="\I:","",C40) -> 108265.76 | N40: =IF($K40="\I:","",D40) -> 77485.562 | O40: =IF($K40="\I:","",E40) -> 77485.562 | P40: =IF($K40="\I:","",F40) -> 77485.562 | T40: =K40 -> Trd_lcv_gsl-hyb_49 | U40: =OFFSET($S$1,MATCH(J40,$S$1:$S$10,0)-1,-1)&" -- "&TEXT(B40,"00%") -> ICE gasoline hybrid LCV -- 49% | V40: Bvkm | W40: million vehicles
J41: =IFERROR(VLOOKUP(C41,$R$1:$S$10,2,FALSE),J40) -> Trd_lcv_gsl-hyb | K41: =IFERROR(IF(VALUE(C41)>2020,J41&"_"&TEXT(B41*100,"00"),"\I:"),"\I:") -> \I: | L41: =LEFT(K41,7) -> \I: | M41: =IF($K41="\I:","",C41) | N41: =IF($K41="\I:","",D41) | O41: =IF($K41="\I:","",E41) | P41: =IF($K41="\I:","",F41) | T41: =K41 -> \I: | U41: =OFFSET($S$1,MATCH(J41,$S$1:$S$10,0)-1,-1)&" -- "&TEXT(B41,"00%") -> ICE gasoline hybrid LCV -- 00% | V41: Bvkm | W41: million vehicles
J42: =IFERROR(VLOOKUP(C42,$R$1:$S$10,2,FALSE),J41) -> Trd_lcv_gsl-hyb | K42: =IFERROR(IF(VALUE(C42)>2020,J42&"_"&TEXT(B42*100,"00"),"\I:"),"\I:") -> \I: | L42: =LEFT(K42,7) -> \I: | M42: =IF($K42="\I:","",C42) | N42: =IF($K42="\I:","",D42) | O42: =IF($K42="\I:","",E42) | P42: =IF($K42="\I:","",F42) | T42: =K42 -> \I: | U42: =OFFSET($S$1,MATCH(J42,$S$1:$S$10,0)-1,-1)&" -- "&TEXT(B42,"00%") -> ICE gasoline hybrid LCV -- 00% | V42: Bvkm | W42: million vehicles
J43: =IFERROR(VLOOKUP(C43,$R$1:$S$10,2,FALSE),J42) -> Trd_lcv_gsl-hyb | K43: =IFERROR(IF(VALUE(C43)>2020,J43&"_"&TEXT(B43*100,"00"),"\I:"),"\I:") -> \I: | L43: =LEFT(K43,7) -> \I: | M43: =IF($K43="\I:","",C43) | N43: =IF($K43="\I:","",D43) | O43: =IF($K43="\I:","",E43) | P43: =IF($K43="\I:","",F43) | T43: =K43 -> \I: | U43: =OFFSET($S$1,MATCH(J43,$S$1:$S$10,0)-1,-1)&" -- "&TEXT(B43,"00%") -> ICE gasoline hybrid LCV -- 00% | V43: Bvkm | W43: million vehicles
J44: =IFERROR(VLOOKUP(C44,$R$1:$S$10,2,FALSE),J43) -> Trd_lcv_gsl-hyb | K44: =IFERROR(IF(VALUE(C44)>2020,J44&"_"&TEXT(B44*100,"00"),"\I:"),"\I:") -> \I: | L44: =LEFT(K44,7) -> \I: | M44: =IF($K44="\I:","",C44) | N44: =IF($K44="\I:","",D44) | O44: =IF($K44="\I:","",E44) | P44: =IF($K44="\I:","",F44) | T44: =K44 -> \I: | U44: =OFFSET($S$1,MATCH(J44,$S$1:$S$10,0)-1,-1)&" -- "&TEXT(B44,"00%") -> ICE gasoline hybrid LCV -- 00% | V44: Bvkm | W44: million vehicles
B45: Reduction of specific energy consumption relative to 2015 gasoline vehicle (%) | C45: ICE gasoline plug-in hybrid LCV | J45: =IFERROR(VLOOKUP(C45,$R$1:$S$10,2,FALSE),J44) -> Trd_lcv_gsl-pih | K45: =IFERROR(IF(VALUE(C45)>2020,J45&"_"&TEXT(B45*100,"00"),"\I:"),"\I:") -> \I: | L45: =LEFT(K45,7) -> \I: | M45: =IF($K45="\I:","",C45) | N45: =IF($K45="\I:","",D45) | O45: =IF($K45="\I:","",E45) | P45: =IF($K45="\I:","",F45) | T45: =K45 -> \I: | U45: =OFFSET($S$1,MATCH(J45,$S$1:$S$10,0)-1,-1)&" -- "&TEXT(B45,"00%") -> ICE gasoline plug-in hybrid LCV -- Reduction of specific energy consumption relative to 2015 gasoline vehicle (%) | V45: Bvkm | W45: million vehicles
J46: =IFERROR(VLOOKUP(C46,$R$1:$S$10,2,FALSE),J45) -> Trd_lcv_gsl-pih | K46: =IFERROR(IF(VALUE(C46)>2020,J46&"_"&TEXT(B46*100,"00"),"\I:"),"\I:") -> \I: | L46: =LEFT(K46,7) -> \I: | M46: =IF($K46="\I:","",C46) | N46: =IF($K46="\I:","",D46) | O46: =IF($K46="\I:","",E46) | P46: =IF($K46="\I:","",F46) | T46: =K46 -> \I: | U46: =OFFSET($S$1,MATCH(J46,$S$1:$S$10,0)-1,-1)&" -- "&TEXT(B46,"00%") -> ICE gasoline plug-in hybrid LCV -- 00% | V46: Bvkm | W46: million vehicles
J47: =IFERROR(VLOOKUP(C47,$R$1:$S$10,2,FALSE),J46) -> Trd_lcv_gsl-pih | K47: =IFERROR(IF(VALUE(C47)>2020,J47&"_"&TEXT(B47*100,"00"),"\I:"),"\I:") -> \I: | L47: =LEFT(K47,7) -> \I: | M47: =IF($K47="\I:","",C47) | N47: =IF($K47="\I:","",D47) | O47: =IF($K47="\I:","",E47) | P47: =IF($K47="\I:","",F47) | T47: =K47 -> \I: | U47: =OFFSET($S$1,MATCH(J47,$S$1:$S$10,0)-1,-1)&" -- "&TEXT(B47,"00%") -> ICE gasoline plug-in hybrid LCV -- 00% | V47: Bvkm | W47: million vehicles
C48: 2020 | D48: 2030 | E48: 2040 | F48: 2050 | J48: =IFERROR(VLOOKUP(C48,$R$1:$S$10,2,FALSE),J47) -> Trd_lcv_gsl-pih | K48: =IFERROR(IF(VALUE(C48)>2020,J48&"_"&TEXT(B48*100,"00"),"\I:"),"\I:") -> \I: | L48: =LEFT(K48,7) -> \I: | M48: =IF($K48="\I:","",C48) | N48: =IF($K48="\I:","",D48) | O48: =IF($K48="\I:","",E48) | P48: =IF($K48="\I:","",F48) | T48: =K48 -> \I: | U48: =OFFSET($S$1,MATCH(J48,$S$1:$S$10,0)-1,-1)&" -- "&TEXT(B48,"00%") -> ICE gasoline plug-in hybrid LCV -- 00% | V48: Bvkm | W48: million vehicles
B49: 0.825 | C49: 25855.416 | D49: 20946.014 | E49: 19751.48 | F49: 19403.087 | I49: =(1+B49) -> 1.825 | J49: =IFERROR(VLOOKUP(C49,$R$1:$S$10,2,FALSE),J48) -> Trd_lcv_gsl-pih | K49: =IFERROR(IF(VALUE(C49)>2020,J49&"_"&TEXT(B49*100,"00"),"\I:"),"\I:") -> Trd_lcv_gsl-pih_83 | L49: =LEFT(K49,7) -> Trd_lcv | M49: =IF($K49="\I:","",C49) -> 25855.416 | N49: =IF($K49="\I:","",D49) -> 20946.014 | O49: =IF($K49="\I:","",E49) -> 19751.48 | P49: =IF($K49="\I:","",F49) -> 19403.087 | T49: =K49 -> Trd_lcv_gsl-pih_83 | U49: =OFFSET($S$1,MATCH(J49,$S$1:$S$10,0)-1,-1)&" -- "&TEXT(B49,"00%") -> ICE gasoline plug-in hybrid LCV -- 83% | V49: Bvkm | W49: million vehicles
B50: 0.835 | C50: 25936.734 | D50: 20972.569 | E50: 19766.642 | F50: 19414.574 | I50: =(1+B50) -> 1.835 | J50: =IFERROR(VLOOKUP(C50,$R$1:$S$10,2,FALSE),J49) -> Trd_lcv_gsl-pih | K50: =IFERROR(IF(VALUE(C50)>2020,J50&"_"&TEXT(B50*100,"00"),"\I:"),"\I:") -> Trd_lcv_gsl-pih_84 | L50: =LEFT(K50,7) -> Trd_lcv | M50: =IF($K50="\I:","",C50) -> 25936.734 | N50: =IF($K50="\I:","",D50) -> 20972.569 | O50: =IF($K50="\I:","",E50) -> 19766.642 | P50: =IF($K50="\I:","",F50) -> 19414.574 | T50: =K50 -> Trd_lcv_gsl-pih_84 | U50: =OFFSET($S$1,MATCH(J50,$S$1:$S$10,0)-1,-1)&" -- "&TEXT(B50,"00%") -> ICE gasoline plug-in hybrid LCV -- 84% | V50: Bvkm | W50: million vehicles
B51: 0.8475 | C51: 26068.064 | D51: 20983.736 | E51: 19772.196 | F51: 19418.262 | I51: =(1+B51) -> 1.8475 | J51: =IFERROR(VLOOKUP(C51,$R$1:$S$10,2,FALSE),J50) -> Trd_lcv_gsl-pih | K51: =IFERROR(IF(VALUE(C51)>2020,J51&"_"&TEXT(B51*100,"00"),"\I:"),"\I:") -> Trd_lcv_gsl-pih_85 | L51: =LEFT(K51,7) -> Trd_lcv | M51: =IF($K51="\I:","",C51) -> 26068.064 | N51: =IF($K51="\I:","",D51) -> 20983.736 | O51: =IF($K51="\I:","",E51) -> 19772.196 | P51: =IF($K51="\I:","",F51) -> 19418.262 | T51: =K51 -> Trd_lcv_gsl-pih_85 | U51: =OFFSET($S$1,MATCH(J51,$S$1:$S$10,0)-1,-1)&" -- "&TEXT(B51,"00%") -> ICE gasoline plug-in hybrid LCV -- 85% | V51: Bvkm | W51: million vehicles
B52: 0.8575 | C52: 29189.21 | D52: 21014.101 | E52: 19796.197 | F52: 19440.656 | I52: =(1+B52) -> 1.8575 | J52: =IFERROR(VLOOKUP(C52,$R$1:$S$10,2,FALSE),J51) -> Trd_lcv_gsl-pih | K52: =IFERROR(IF(VALUE(C52)>2020,J52&"_"&TEXT(B52*100,"00"),"\I:"),"\I:") -> Trd_lcv_gsl-pih_86 | L52: =LEFT(K52,7) -> Trd_lcv | M52: =IF($K52="\I:","",C52) -> 29189.21 | N52: =IF($K52="\I:","",D52) -> 21014.101 | O52: =IF($K52="\I:","",E52) -> 19796.197 | P52: =IF($K52="\I:","",F52) -> 19440.656 | T52: =K52 -> Trd_lcv_gsl-pih_86 | U52: =OFFSET($S$1,MATCH(J52,$S$1:$S$10,0)-1,-1)&" -- "&TEXT(B52,"00%") -> ICE gasoline plug-in hybrid LCV -- 86% | V52: Bvkm | W52: million vehicles
B53: 0.8675 | C53: 44989.854 | D53: 21032.52 | E53: 19824.251 | F53: 19472.994 | I53: =(1+B53) -> 1.8675 | J53: =IFERROR(VLOOKUP(C53,$R$1:$S$10,2,FALSE),J52) -> Trd_lcv_gsl-pih | K53: =IFERROR(IF(VALUE(C53)>2020,J53&"_"&TEXT(B53*100,"00"),"\I:"),"\I:") -> Trd_lcv_gsl-pih_87 | L53: =LEFT(K53,7) -> Trd_lcv | M53: =IF($K53="\I:","",C53) -> 44989.854 | N53: =IF($K53="\I:","",D53) -> 21032.52 | O53: =IF($K53="\I:","",E53) -> 19824.251 | P53: =IF($K53="\I:","",F53) -> 19472.994 | T53: =K53 -> Trd_lcv_gsl-pih_87 | U53: =OFFSET($S$1,MATCH(J53,$S$1:$S$10,0)-1,-1)&" -- "&TEXT(B53,"00%") -> ICE gasoline plug-in hybrid LCV -- 87% | V53: Bvkm | W53: million vehicles
B54: 0.915 | C54: 61078.703 | D54: 24620.923 | E54: 22831.785 | F54: 22357.388 | I54: =(1+B54) -> 1.915 | J54: =IFERROR(VLOOKUP(C54,$R$1:$S$10,2,FALSE),J53) -> Trd_lcv_gsl-pih | K54: =IFERROR(IF(VALUE(C54)>2020,J54&"_"&TEXT(B54*100,"00"),"\I:"),"\I:") -> Trd_lcv_gsl-pih_92 | L54: =LEFT(K54,7) -> Trd_lcv | M54: =IF($K54="\I:","",C54) -> 61078.703 | N54: =IF($K54="\I:","",D54) -> 24620.923 | O54: =IF($K54="\I:","",E54) -> 22831.785 | P54: =IF($K54="\I:","",F54) -> 22357.388 | T54: =K54 -> Trd_lcv_gsl-pih_92 | U54: =OFFSET($S$1,MATCH(J54,$S$1:$S$10,0)-1,-1)&" -- "&TEXT(B54,"00%") -> ICE gasoline plug-in hybrid LCV -- 92% | V54: Bvkm | W54: million vehicles
B55: 0.9225 | C55: 61658.557 | D55: 36662.686 | E55: 34512.215 | F55: 34243.341 | I55: =(1+B55) -> 1.9225 | J55: =IFERROR(VLOOKUP(C55,$R$1:$S$10,2,FALSE),J54) -> Trd_lcv_gsl-pih | K55: =IFERROR(IF(VALUE(C55)>2020,J55&"_"&TEXT(B55*100,"00"),"\I:"),"\I:") -> Trd_lcv_gsl-pih_92 | L55: =LEFT(K55,7) -> Trd_lcv | M55: =IF($K55="\I:","",C55) -> 61658.557 | N55: =IF($K55="\I:","",D55) -> 36662.686 | O55: =IF($K55="\I:","",E55) -> 34512.215 | P55: =IF($K55="\I:","",F55) -> 34243.341 | T55: =K55 -> Trd_lcv_gsl-pih_92 | U55: =OFFSET($S$1,MATCH(J55,$S$1:$S$10,0)-1,-1)&" -- "&TEXT(B55,"00%") -> ICE gasoline plug-in hybrid LCV -- 92% | V55: Bvkm | W55: million vehicles
B56: 0.93 | C56: 99213.719 | D56: 52428.018 | E56: 50000.363 | F56: 50076.894 | I56: =(1+B56) -> 1.93 | J56: =IFERROR(VLOOKUP(C56,$R$1:$S$10,2,FALSE),J55) -> Trd_lcv_gsl-pih | K56: =IFERROR(IF(VALUE(C56)>2020,J56&"_"&TEXT(B56*100,"00"),"\I:"),"\I:") -> Trd_lcv_gsl-pih_93 | L56: =LEFT(K56,7) -> Trd_lcv | M56: =IF($K56="\I:","",C56) -> 99213.719 | N56: =IF($K56="\I:","",D56) -> 52428.018 | O56: =IF($K56="\I:","",E56) -> 50000.363 | P56: =IF($K56="\I:","",F56) -> 50076.894 | T56: =K56 -> Trd_lcv_gsl-pih_93 | U56: =OFFSET($S$1,MATCH(J56,$S$1:$S$10,0)-1,-1)&" -- "&TEXT(B56,"00%") -> ICE gasoline plug-in hybrid LCV -- 93% | V56: Bvkm | W56: million vehicles
J57: =IFERROR(VLOOKUP(C57,$R$1:$S$10,2,FALSE),J56) -> Trd_lcv_gsl-pih | K57: =IFERROR(IF(VALUE(C57)>2020,J57&"_"&TEXT(B57*100,"00"),"\I:"),"\I:") -> \I: | L57: =LEFT(K57,7) -> \I: | M57: =IF($K57="\I:","",C57) | N57: =IF($K57="\I:","",D57) | O57: =IF($K57="\I:","",E57) | P57: =IF($K57="\I:","",F57) | T57: =K57 -> \I: | U57: =OFFSET($S$1,MATCH(J57,$S$1:$S$10,0)-1,-1)&" -- "&TEXT(B57,"00%") -> ICE gasoline plug-in hybrid LCV -- 00% | V57: Bvkm | W57: million vehicles
J58: =IFERROR(VLOOKUP(C58,$R$1:$S$10,2,FALSE),J57) -> Trd_lcv_gsl-pih | K58: =IFERROR(IF(VALUE(C58)>2020,J58&"_"&TEXT(B58*100,"00"),"\I:"),"\I:") -> \I: | L58: =LEFT(K58,7) -> \I: | M58: =IF($K58="\I:","",C58) | N58: =IF($K58="\I:","",D58) | O58: =IF($K58="\I:","",E58) | P58: =IF($K58="\I:","",F58) | T58: =K58 -> \I: | U58: =OFFSET($S$1,MATCH(J58,$S$1:$S$10,0)-1,-1)&" -- "&TEXT(B58,"00%") -> ICE gasoline plug-in hybrid LCV -- 00% | V58: Bvkm | W58: million vehicles
J59: =IFERROR(VLOOKUP(C59,$R$1:$S$10,2,FALSE),J58) -> Trd_lcv_gsl-pih | K59: =IFERROR(IF(VALUE(C59)>2020,J59&"_"&TEXT(B59*100,"00"),"\I:"),"\I:") -> \I: | L59: =LEFT(K59,7) -> \I: | M59: =IF($K59="\I:","",C59) | N59: =IF($K59="\I:","",D59) | O59: =IF($K59="\I:","",E59) | P59: =IF($K59="\I:","",F59) | T59: =K59 -> \I: | U59: =OFFSET($S$1,MATCH(J59,$S$1:$S$10,0)-1,-1)&" -- "&TEXT(B59,"00%") -> ICE gasoline plug-in hybrid LCV -- 00% | V59: Bvkm | W59: million vehicles
J60: =IFERROR(VLOOKUP(C60,$R$1:$S$10,2,FALSE),J59) -> Trd_lcv_gsl-pih | K60: =IFERROR(IF(VALUE(C60)>2020,J60&"_"&TEXT(B60*100,"00"),"\I:"),"\I:") -> \I: | L60: =LEFT(K60,7) -> \I: | M60: =IF($K60="\I:","",C60) | N60: =IF($K60="\I:","",D60) | O60: =IF($K60="\I:","",E60) | P60: =IF($K60="\I:","",F60) | T60: =K60 -> \I: | U60: =OFFSET($S$1,MATCH(J60,$S$1:$S$10,0)-1,-1)&" -- "&TEXT(B60,"00%") -> ICE gasoline plug-in hybrid LCV -- 00% | V60: Bvkm | W60: million vehicles
B61: Reference values for diesel LCV | J61: =IFERROR(VLOOKUP(C61,$R$1:$S$10,2,FALSE),J60) -> Trd_lcv_gsl-pih | K61: =IFERROR(IF(VALUE(C61)>2020,J61&"_"&TEXT(B61*100,"00"),"\I:"),"\I:") -> \I: | L61: =LEFT(K61,7) -> \I: | M61: =IF($K61="\I:","",C61) | N61: =IF($K61="\I:","",D61) | O61: =IF($K61="\I:","",E61) | P61: =IF($K61="\I:","",F61) | T61: =K61 -> \I: | U61: =OFFSET($S$1,MATCH(J61,$S$1:$S$10,0)-1,-1)&" -- "&TEXT(B61,"00%") -> ICE gasoline plug-in hybrid LCV -- Reference values for diesel LCV | V61: Bvkm | W61: million vehicles
B62: 2015 | J62: =IFERROR(VLOOKUP(C62,$R$1:$S$10,2,FALSE),J61) -> Trd_lcv_gsl-pih | K62: =IFERROR(IF(VALUE(C62)>2020,J62&"_"&TEXT(B62*100,"00"),"\I:"),"\I:") -> \I: | L62: =LEFT(K62,7) -> \I: | M62: =IF($K62="\I:","",C62) | N62: =IF($K62="\I:","",D62) | O62: =IF($K62="\I:","",E62) | P62: =IF($K62="\I:","",F62) | T62: =K62 -> \I: | U62: =OFFSET($S$1,MATCH(J62,$S$1:$S$10,0)-1,-1)&" -- "&TEXT(B62,"00%") -> ICE gasoline plug-in hybrid LCV -- 201500% | V62: Bvkm | W62: million vehicles
B63: Energy consumption | C63: lt/100 km | D63: 6.9320299 | G63: =D63*F8/100*10^9/10^6 -> 2.6341714 | I63: =1/G63 -> 0.37962602 | J63: =IFERROR(VLOOKUP(C63,$R$1:$S$10,2,FALSE),J62) -> Trd_lcv_gsl-pih | K63: =IFERROR(IF(VALUE(C63)>2020,J63&"_"&TEXT(B63*100,"00"),"\I:"),"\I:") -> \I: | L63: =LEFT(K63,7) -> \I: | M63: =IF($K63="\I:","",C63) | N63: =IF($K63="\I:","",D63) | O63: =IF($K63="\I:","",E63) | P63: =IF($K63="\I:","",F63) | T63: =K63 -> \I: | U63: =OFFSET($S$1,MATCH(J63,$S$1:$S$10,0)-1,-1)&" -- "&TEXT(B63,"00%") -> ICE gasoline plug-in hybrid LCV -- Energy consumption | V63: Bvkm | W63: million vehicles
B64: Capital cost | C64: Euro15 /veh | D64: 21231.361 | I64: bvkm/PJ | J64: =IFERROR(VLOOKUP(C64,$R$1:$S$10,2,FALSE),J63) -> Trd_lcv_gsl-pih | K64: =IFERROR(IF(VALUE(C64)>2020,J64&"_"&TEXT(B64*100,"00"),"\I:"),"\I:") -> \I: | L64: =LEFT(K64,7) -> \I: | M64: =IF($K64="\I:","",C64) | N64: =IF($K64="\I:","",D64) | O64: =IF($K64="\I:","",E64) | P64: =IF($K64="\I:","",F64) | T64: =K64 -> \I: | U64: =OFFSET($S$1,MATCH(J64,$S$1:$S$10,0)-1,-1)&" -- "&TEXT(B64,"00%") -> ICE gasoline plug-in hybrid LCV -- Capital cost | V64: Bvkm | W64: million vehicles
J65: =IFERROR(VLOOKUP(C65,$R$1:$S$10,2,FALSE),J64) -> Trd_lcv_gsl-pih | K65: =IFERROR(IF(VALUE(C65)>2020,J65&"_"&TEXT(B65*100,"00"),"\I:"),"\I:") -> \I: | L65: =LEFT(K65,7) -> \I: | M65: =IF($K65="\I:","",C65) | N65: =IF($K65="\I:","",D65) | O65: =IF($K65="\I:","",E65) | P65: =IF($K65="\I:","",F65) | T65: =K65 -> \I: | U65: =OFFSET($S$1,MATCH(J65,$S$1:$S$10,0)-1,-1)&" -- "&TEXT(B65,"00%") -> ICE gasoline plug-in hybrid LCV -- 00% | V65: Bvkm | W65: million vehicles
B66: Reduction of specific energy consumption relative to 2015 diesel vehicle (%) | C66: ICE diesel LCV | J66: =IFERROR(VLOOKUP(C66,$R$1:$S$10,2,FALSE),J65) -> Trd_lcv_dsl | K66: =IFERROR(IF(VALUE(C66)>2020,J66&"_"&TEXT(B66*100,"00"),"\I:"),"\I:") -> \I: | L66: =LEFT(K66,7) -> \I: | M66: =IF($K66="\I:","",C66) | N66: =IF($K66="\I:","",D66) | O66: =IF($K66="\I:","",E66) | P66: =IF($K66="\I:","",F66) | T66: =K66 -> \I: | U66: =OFFSET($S$1,MATCH(J66,$S$1:$S$10,0)-1,-1)&" -- "&TEXT(B66,"00%") -> ICE diesel LCV -- Reduction of specific energy consumption relative to 2015 diesel vehicle (%) | V66: Bvkm | W66: million vehicles
J67: =IFERROR(VLOOKUP(C67,$R$1:$S$10,2,FALSE),J66) -> Trd_lcv_dsl | K67: =IFERROR(IF(VALUE(C67)>2020,J67&"_"&TEXT(B67*100,"00"),"\I:"),"\I:") -> \I: | L67: =LEFT(K67,7) -> \I: | M67: =IF($K67="\I:","",C67) | N67: =IF($K67="\I:","",D67) | O67: =IF($K67="\I:","",E67) | P67: =IF($K67="\I:","",F67) | T67: =K67 -> \I: | U67: =OFFSET($S$1,MATCH(J67,$S$1:$S$10,0)-1,-1)&" -- "&TEXT(B67,"00%") -> ICE diesel LCV -- 00% | V67: Bvkm | W67: million vehicles
J68: =IFERROR(VLOOKUP(C68,$R$1:$S$10,2,FALSE),J67) -> Trd_lcv_dsl | K68: =IFERROR(IF(VALUE(C68)>2020,J68&"_"&TEXT(B68*100,"00"),"\I:"),"\I:") -> \I: | L68: =LEFT(K68,7) -> \I: | M68: =IF($K68="\I:","",C68) | N68: =IF($K68="\I:","",D68) | O68: =IF($K68="\I:","",E68) | P68: =IF($K68="\I:","",F68) | T68: =K68 -> \I: | U68: =OFFSET($S$1,MATCH(J68,$S$1:$S$10,0)-1,-1)&" -- "&TEXT(B68,"00%") -> ICE diesel LCV -- 00% | V68: Bvkm | W68: million vehicles
C69: 2020 | D69: 2030 | E69: 2040 | F69: 2050 | I69: 1 | J69: =IFERROR(VLOOKUP(C69,$R$1:$S$11,2,FALSE),J68) -> Trd_lcv_dsl | K69: =IFERROR(IF(VALUE(C69)>200,J69&"_"&TEXT(B69*100,"00"),"\I:"),"\I:") -> Trd_lcv_dsl_00 | L69: =LEFT(K69,7) -> Trd_lcv | M69: =D64 -> 21231.361 | T69: =K69 -> Trd_lcv_dsl_00 | U69: =OFFSET($S$1,MATCH(J69,$S$1:$S$10,0)-1,-1)&" -- "&TEXT(B69,"00%") -> ICE diesel LCV -- 00% | V69: Bvkm | W69: million vehicles
B70: 0.2621092 | C70: 22474.228 | D70: 21602.192 | E70: 21602.192 | F70: 21602.192 | I70: =$I$63*(1+B70)/$I$11 -> 1.2855178 | J70: =IFERROR(VLOOKUP(C70,$R$1:$S$10,2,FALSE),J69) -> Trd_lcv_dsl | K70: =IFERROR(IF(VALUE(C70)>2020,J70&"_"&TEXT(B70*100,"00"),"\I:"),"\I:") -> Trd_lcv_dsl_26 | L70: =LEFT(K70,7) -> Trd_lcv | M70: =IF($K70="\I:","",C70) -> 22474.228 | N70: =IF($K70="\I:","",D70) -> 21602.192 | O70: =IF($K70="\I:","",E70) -> 21602.192 | P70: =IF($K70="\I:","",F70) -> 21602.192 | T70: =K70 -> Trd_lcv_dsl_26 | U70: =OFFSET($S$1,MATCH(J70,$S$1:$S$10,0)-1,-1)&" -- "&TEXT(B70,"00%") -> ICE diesel LCV -- 26% | V70: Bvkm | W70: million vehicles
B71: 0.3621092 | C71: 26916.534 | D71: 22758.94 | E71: 22758.94 | F71: 22758.94 | I71: =$I$63*(1+B71)/$I$11 -> 1.3873725 | J71: =IFERROR(VLOOKUP(C71,$R$1:$S$10,2,FALSE),J70) -> Trd_lcv_dsl | K71: =IFERROR(IF(VALUE(C71)>2020,J71&"_"&TEXT(B71*100,"00"),"\I:"),"\I:") -> Trd_lcv_dsl_36 | L71: =LEFT(K71,7) -> Trd_lcv | M71: =IF($K71="\I:","",C71) -> 26916.534 | N71: =IF($K71="\I:","",D71) -> 22758.94 | O71: =IF($K71="\I:","",E71) -> 22758.94 | P71: =IF($K71="\I:","",F71) -> 22758.94 | T71: =K71 -> Trd_lcv_dsl_36 | U71: =OFFSET($S$1,MATCH(J71,$S$1:$S$10,0)-1,-1)&" -- "&TEXT(B71,"00%") -> ICE diesel LCV -- 36% | V71: Bvkm | W71: million vehicles
B72: 0.4121092 | C72: 36866.504 | D72: 24797.898 | E72: 24797.898 | F72: 24797.898 | I72: =$I$63*(1+B72)/$I$11 -> 1.4382999 | J72: =IFERROR(VLOOKUP(C72,$R$1:$S$10,2,FALSE),J71) -> Trd_lcv_dsl | K72: =IFERROR(IF(VALUE(C72)>2020,J72&"_"&TEXT(B72*100,"00"),"\I:"),"\I:") -> Trd_lcv_dsl_41 | L72: =LEFT(K72,7) -> Trd_lcv | M72: =IF($K72="\I:","",C72) -> 36866.504 | N72: =IF($K72="\I:","",D72) -> 24797.898 | O72: =IF($K72="\I:","",E72) -> 24797.898 | P72: =IF($K72="\I:","",F72) -> 24797.898 | T72: =K72 -> Trd_lcv_dsl_41 | U72: =OFFSET($S$1,MATCH(J72,$S$1:$S$10,0)-1,-1)&" -- "&TEXT(B72,"00%") -> ICE diesel LCV -- 41% | V72: Bvkm | W72: million vehicles
B73: 0.4621092 | C73: 111418.88 | D73: 30833.759 | E73: 30833.759 | F73: 30833.759 | I73: =$I$63*(1+B73)/$I$11 -> 1.4892272 | J73: =IFERROR(VLOOKUP(C73,$R$1:$S$10,2,FALSE),J72) -> Trd_lcv_dsl | K73: =IFERROR(IF(VALUE(C73)>2020,J73&"_"&TEXT(B73*100,"00"),"\I:"),"\I:") -> Trd_lcv_dsl_46 | L73: =LEFT(K73,7) -> Trd_lcv | M73: =IF($K73="\I:","",C73) -> 111418.88 | N73: =IF($K73="\I:","",D73) -> 30833.759 | O73: =IF($K73="\I:","",E73) -> 30833.759 | P73: =IF($K73="\I:","",F73) -> 30833.759 | T73: =K73 -> Trd_lcv_dsl_46 | U73: =OFFSET($S$1,MATCH(J73,$S$1:$S$10,0)-1,-1)&" -- "&TEXT(B73,"00%") -> ICE diesel LCV -- 46% | V73: Bvkm | W73: million vehicles
B74: 0.5121092 | D74: 86441.801 | E74: 86441.801 | F74: 86441.801 | I74: =$I$63*(1+B74)/$I$11 -> 1.5401546 | J74: =IFERROR(VLOOKUP(C74,$R$1:$S$10,2,FALSE),J73) -> Trd_lcv_dsl | K74: =IFERROR(IF(VALUE(C74)>2020,J74&"_"&TEXT(B74*100,"00"),"\I:"),"\I:") -> \I: | L74: =LEFT(K74,7) -> \I: | M74: =IF($K74="\I:","",C74) | N74: =IF($K74="\I:","",D74) | O74: =IF($K74="\I:","",E74) | P74: =IF($K74="\I:","",F74) | T74: =K74 -> \I: | U74: =OFFSET($S$1,MATCH(J74,$S$1:$S$10,0)-1,-1)&" -- "&TEXT(B74,"00%") -> ICE diesel LCV -- 51% | V74: Bvkm | W74: million vehicles
J75: =IFERROR(VLOOKUP(C75,$R$1:$S$10,2,FALSE),J74) -> Trd_lcv_dsl | K75: =IFERROR(IF(VALUE(C75)>2020,J75&"_"&TEXT(B75*100,"00"),"\I:"),"\I:") -> \I: | L75: =LEFT(K75,7) -> \I: | M75: =IF($K75="\I:","",C75) | N75: =IF($K75="\I:","",D75) | O75: =IF($K75="\I:","",E75) | P75: =IF($K75="\I:","",F75) | T75: =K75 -> \I: | U75: =OFFSET($S$1,MATCH(J75,$S$1:$S$10,0)-1,-1)&" -- "&TEXT(B75,"00%") -> ICE diesel LCV -- 00% | V75: Bvkm | W75: million vehicles
J76: =IFERROR(VLOOKUP(C76,$R$1:$S$10,2,FALSE),J75) -> Trd_lcv_dsl | K76: =IFERROR(IF(VALUE(C76)>2020,J76&"_"&TEXT(B76*100,"00"),"\I:"),"\I:") -> \I: | L76: =LEFT(K76,7) -> \I: | M76: =IF($K76="\I:","",C76) | N76: =IF($K76="\I:","",D76) | O76: =IF($K76="\I:","",E76) | P76: =IF($K76="\I:","",F76) | T76: =K76 -> \I: | U76: =OFFSET($S$1,MATCH(J76,$S$1:$S$10,0)-1,-1)&" -- "&TEXT(B76,"00%") -> ICE diesel LCV -- 00% | V76: Bvkm | W76: million vehicles
J77: =IFERROR(VLOOKUP(C77,$R$1:$S$10,2,FALSE),J76) -> Trd_lcv_dsl | K77: =IFERROR(IF(VALUE(C77)>2020,J77&"_"&TEXT(B77*100,"00"),"\I:"),"\I:") -> \I: | L77: =LEFT(K77,7) -> \I: | M77: =IF($K77="\I:","",C77) | N77: =IF($K77="\I:","",D77) | O77: =IF($K77="\I:","",E77) | P77: =IF($K77="\I:","",F77) | T77: =K77 -> \I: | U77: =OFFSET($S$1,MATCH(J77,$S$1:$S$10,0)-1,-1)&" -- "&TEXT(B77,"00%") -> ICE diesel LCV -- 00% | V77: Bvkm | W77: million vehicles
J78: =IFERROR(VLOOKUP(C78,$R$1:$S$10,2,FALSE),J77) -> Trd_lcv_dsl | K78: =IFERROR(IF(VALUE(C78)>2020,J78&"_"&TEXT(B78*100,"00"),"\I:"),"\I:") -> \I: | L78: =LEFT(K78,7) -> \I: | M78: =IF($K78="\I:","",C78) | N78: =IF($K78="\I:","",D78) | O78: =IF($K78="\I:","",E78) | P78: =IF($K78="\I:","",F78) | T78: =K78 -> \I: | U78: =OFFSET($S$1,MATCH(J78,$S$1:$S$10,0)-1,-1)&" -- "&TEXT(B78,"00%") -> ICE diesel LCV -- 00% | V78: Bvkm | W78: million vehicles
B79: Reduction of specific energy consumption relative to 2015 diesel vehicle (%) | C79: ICE hybrid diesel LCV | J79: =IFERROR(VLOOKUP(C79,$R$1:$S$10,2,FALSE),J78) -> Trd_lcv_dsl-hyb | K79: =IFERROR(IF(VALUE(C79)>2020,J79&"_"&TEXT(B79*100,"00"),"\I:"),"\I:") -> \I: | L79: =LEFT(K79,7) -> \I: | M79: =IF($K79="\I:","",C79) | N79: =IF($K79="\I:","",D79) | O79: =IF($K79="\I:","",E79) | P79: =IF($K79="\I:","",F79) | T79: =K79 -> \I: | U79: =OFFSET($S$1,MATCH(J79,$S$1:$S$10,0)-1,-1)&" -- "&TEXT(B79,"00%") -> ICE hybrid diesel LCV -- Reduction of specific energy consumption relative to 2015 diesel vehicle (%) | V79: Bvkm | W79: million vehicles
J80: =IFERROR(VLOOKUP(C80,$R$1:$S$10,2,FALSE),J79) -> Trd_lcv_dsl-hyb | K80: =IFERROR(IF(VALUE(C80)>2020,J80&"_"&TEXT(B80*100,"00"),"\I:"),"\I:") -> \I: | L80: =LEFT(K80,7) -> \I: | M80: =IF($K80="\I:","",C80) | N80: =IF($K80="\I:","",D80) | O80: =IF($K80="\I:","",E80) | P80: =IF($K80="\I:","",F80) | T80: =K80 -> \I: | U80: =OFFSET($S$1,MATCH(J80,$S$1:$S$10,0)-1,-1)&" -- "&TEXT(B80,"00%") -> ICE hybrid diesel LCV -- 00% | V80: Bvkm | W80: million vehicles
J81: =IFERROR(VLOOKUP(C81,$R$1:$S$10,2,FALSE),J80) -> Trd_lcv_dsl-hyb | K81: =IFERROR(IF(VALUE(C81)>2020,J81&"_"&TEXT(B81*100,"00"),"\I:"),"\I:") -> \I: | L81: =LEFT(K81,7) -> \I: | M81: =IF($K81="\I:","",C81) | N81: =IF($K81="\I:","",D81) | O81: =IF($K81="\I:","",E81) | P81: =IF($K81="\I:","",F81) | T81: =K81 -> \I: | U81: =OFFSET($S$1,MATCH(J81,$S$1:$S$10,0)-1,-1)&" -- "&TEXT(B81,"00%") -> ICE hybrid diesel LCV -- 00% | V81: Bvkm | W81: million vehicles
C82: 2020 | D82: 2030 | E82: 2040 | F82: 2050 | J82: =IFERROR(VLOOKUP(C82,$R$1:$S$10,2,FALSE),J81) -> Trd_lcv_dsl-hyb | K82: =IFERROR(IF(VALUE(C82)>2020,J82&"_"&TEXT(B82*100,"00"),"\I:"),"\I:") -> \I: | L82: =LEFT(K82,7) -> \I: | M82: =IF($K82="\I:","",C82) | N82: =IF($K82="\I:","",D82) | O82: =IF($K82="\I:","",E82) | P82: =IF($K82="\I:","",F82) | T82: =K82 -> \I: | U82: =OFFSET($S$1,MATCH(J82,$S$1:$S$10,0)-1,-1)&" -- "&TEXT(B82,"00%") -> ICE hybrid diesel LCV -- 00% | V82: Bvkm | W82: million vehicles
B83: 0.1107243 | C83: 24678.667 | D83: 23366.069 | E83: 23366.069 | F83: 23366.069 | I83: =$I$63*(1+B83)/$I$11 -> 1.1313251 | J83: =IFERROR(VLOOKUP(C83,$R$1:$S$10,2,FALSE),J82) -> Trd_lcv_dsl-hyb | K83: =IFERROR(IF(VALUE(C83)>2020,J83&"_"&TEXT(B83*100,"00"),"\I:"),"\I:") -> Trd_lcv_dsl-hyb_11 | L83: =LEFT(K83,7) -> Trd_lcv | M83: =IF($K83="\I:","",C83) -> 24678.667 | N83: =IF($K83="\I:","",D83) -> 23366.069 | O83: =IF($K83="\I:","",E83) -> 23366.069 | P83: =IF($K83="\I:","",F83) -> 23366.069 | T83: =K83 -> Trd_lcv_dsl-hyb_11 | U83: =OFFSET($S$1,MATCH(J83,$S$1:$S$10,0)-1,-1)&" -- "&TEXT(B83,"00%") -> ICE hybrid diesel LCV -- 11% | V83: Bvkm | W83: million vehicles
B84: 0.2107243 | C84: 24878.633 | D84: 23501.122 | E84: 23501.122 | F84: 23501.122 | I84: =$I$63*(1+B84)/$I$11 -> 1.2331799 | J84: =IFERROR(VLOOKUP(C84,$R$1:$S$10,2,FALSE),J83) -> Trd_lcv_dsl-hyb | K84: =IFERROR(IF(VALUE(C84)>2020,J84&"_"&TEXT(B84*100,"00"),"\I:"),"\I:") -> Trd_lcv_dsl-hyb_21 | L84: =LEFT(K84,7) -> Trd_lcv | M84: =IF($K84="\I:","",C84) -> 24878.633 | N84: =IF($K84="\I:","",D84) -> 23501.122 | O84: =IF($K84="\I:","",E84) -> 23501.122 | P84: =IF($K84="\I:","",F84) -> 23501.122 | T84: =K84 -> Trd_lcv_dsl-hyb_21 | U84: =OFFSET($S$1,MATCH(J84,$S$1:$S$10,0)-1,-1)&" -- "&TEXT(B84,"00%") -> ICE hybrid diesel LCV -- 21% | V84: Bvkm | W84: million vehicles
B85: 0.2607243 | C85: 25028.965 | D85: 23634.995 | E85: 23634.995 | F85: 23634.995 | I85: =$I$63*(1+B85)/$I$11 -> 1.2841072 | J85: =IFERROR(VLOOKUP(C85,$R$1:$S$10,2,FALSE),J84) -> Trd_lcv_dsl-hyb | K85: =IFERROR(IF(VALUE(C85)>2020,J85&"_"&TEXT(B85*100,"00"),"\I:"),"\I:") -> Trd_lcv_dsl-hyb_26 | L85: =LEFT(K85,7) -> Trd_lcv | M85: =IF($K85="\I:","",C85) -> 25028.965 | N85: =IF($K85="\I:","",D85) -> 23634.995 | O85: =IF($K85="\I:","",E85) -> 23634.995 | P85: =IF($K85="\I:","",F85) -> 23634.995 | T85: =K85 -> Trd_lcv_dsl-hyb_26 | U85: =OFFSET($S$1,MATCH(J85,$S$1:$S$10,0)-1,-1)&" -- "&TEXT(B85,"00%") -> ICE hybrid diesel LCV -- 26% | V85: Bvkm | W85: million vehicles
B86: 0.3107243 | C86: 25273.029 | D86: 23801.075 | E86: 23801.075 | F86: 23801.075 | I86: =$I$63*(1+B86)/$I$11 -> 1.3350346 | J86: =IFERROR(VLOOKUP(C86,$R$1:$S$10,2,FALSE),J85) -> Trd_lcv_dsl-hyb | K86: =IFERROR(IF(VALUE(C86)>2020,J86&"_"&TEXT(B86*100,"00"),"\I:"),"\I:") -> Trd_lcv_dsl-hyb_31 | L86: =LEFT(K86,7) -> Trd_lcv | M86: =IF($K86="\I:","",C86) -> 25273.029 | N86: =IF($K86="\I:","",D86) -> 23801.075 | O86: =IF($K86="\I:","",E86) -> 23801.075 | P86: =IF($K86="\I:","",F86) -> 23801.075 | T86: =K86 -> Trd_lcv_dsl-hyb_31 | U86: =OFFSET($S$1,MATCH(J86,$S$1:$S$10,0)-1,-1)&" -- "&TEXT(B86,"00%") -> ICE hybrid diesel LCV -- 31% | V86: Bvkm | W86: million vehicles
B87: 0.3607243 | C87: 25690.606 | D87: 24014.759 | E87: 24014.759 | F87: 24014.759 | I87: =$I$63*(1+B87)/$I$11 -> 1.3859619 | J87: =IFERROR(VLOOKUP(C87,$R$1:$S$10,2,FALSE),J86) -> Trd_lcv_dsl-hyb | K87: =IFERROR(IF(VALUE(C87)>2020,J87&"_"&TEXT(B87*100,"00"),"\I:"),"\I:") -> Trd_lcv_dsl-hyb_36 | L87: =LEFT(K87,7) -> Trd_lcv | M87: =IF($K87="\I:","",C87) -> 25690.606 | N87: =IF($K87="\I:","",D87) -> 24014.759 | O87: =IF($K87="\I:","",E87) -> 24014.759 | P87: =IF($K87="\I:","",F87) -> 24014.759 | T87: =K87 -> Trd_lcv_dsl-hyb_36 | U87: =OFFSET($S$1,MATCH(J87,$S$1:$S$10,0)-1,-1)&" -- "&TEXT(B87,"00%") -> ICE hybrid diesel LCV -- 36% | V87: Bvkm | W87: million vehicles
B88: 0.4107243 | C88: 35262.655 | D88: 24332.133 | E88: 24332.133 | F88: 24332.133 | I88: =$I$63*(1+B88)/$I$11 -> 1.4368893 | J88: =IFERROR(VLOOKUP(C88,$R$1:$S$10,2,FALSE),J87) -> Trd_lcv_dsl-hyb | K88: =IFERROR(IF(VALUE(C88)>2020,J88&"_"&TEXT(B88*100,"00"),"\I:"),"\I:") -> Trd_lcv_dsl-hyb_41 | L88: =LEFT(K88,7) -> Trd_lcv | M88: =IF($K88="\I:","",C88) -> 35262.655 | N88: =IF($K88="\I:","",D88) -> 24332.133 | O88: =IF($K88="\I:","",E88) -> 24332.133 | P88: =IF($K88="\I:","",F88) -> 24332.133 | T88: =K88 -> Trd_lcv_dsl-hyb_41 | U88: =OFFSET($S$1,MATCH(J88,$S$1:$S$10,0)-1,-1)&" -- "&TEXT(B88,"00%") -> ICE hybrid diesel LCV -- 41% | V88: Bvkm | W88: million vehicles
B89: 0.4607243 | C89: 114071.89 | D89: 33470.312 | E89: 33470.312 | F89: 33470.312 | I89: =$I$63*(1+B89)/$I$11 -> 1.4878167 | J89: =IFERROR(VLOOKUP(C89,$R$1:$S$10,2,FALSE),J88) -> Trd_lcv_dsl-hyb | K89: =IFERROR(IF(VALUE(C89)>2020,J89&"_"&TEXT(B89*100,"00"),"\I:"),"\I:") -> Trd_lcv_dsl-hyb_46 | L89: =LEFT(K89,7) -> Trd_lcv | M89: =IF($K89="\I:","",C89) -> 114071.89 | N89: =IF($K89="\I:","",D89) -> 33470.312 | O89: =IF($K89="\I:","",E89) -> 33470.312 | P89: =IF($K89="\I:","",F89) -> 33470.312 | T89: =K89 -> Trd_lcv_dsl-hyb_46 | U89: =OFFSET($S$1,MATCH(J89,$S$1:$S$10,0)-1,-1)&" -- "&TEXT(B89,"00%") -> ICE hybrid diesel LCV -- 46% | V89: Bvkm | W89: million vehicles
J90: =IFERROR(VLOOKUP(C90,$R$1:$S$10,2,FALSE),J89) -> Trd_lcv_dsl-hyb | K90: =IFERROR(IF(VALUE(C90)>2020,J90&"_"&TEXT(B90*100,"00"),"\I:"),"\I:") -> \I: | L90: =LEFT(K90,7) -> \I: | M90: =IF($K90="\I:","",C90) | N90: =IF($K90="\I:","",D90) | O90: =IF($K90="\I:","",E90) | P90: =IF($K90="\I:","",F90) | T90: =K90 -> \I: | U90: =OFFSET($S$1,MATCH(J90,$S$1:$S$10,0)-1,-1)&" -- "&TEXT(B90,"00%") -> ICE hybrid diesel LCV -- 00% | V90: Bvkm | W90: million vehicles
J91: =IFERROR(VLOOKUP(C91,$R$1:$S$10,2,FALSE),J90) -> Trd_lcv_dsl-hyb | K91: =IFERROR(IF(VALUE(C91)>2020,J91&"_"&TEXT(B91*100,"00"),"\I:"),"\I:") -> \I: | L91: =LEFT(K91,7) -> \I: | M91: =IF($K91="\I:","",C91) | N91: =IF($K91="\I:","",D91) | O91: =IF($K91="\I:","",E91) | P91: =IF($K91="\I:","",F91) | T91: =K91 -> \I: | U91: =OFFSET($S$1,MATCH(J91,$S$1:$S$10,0)-1,-1)&" -- "&TEXT(B91,"00%") -> ICE hybrid diesel LCV -- 00% | V91: Bvkm | W91: million vehicles
J92: =IFERROR(VLOOKUP(C92,$R$1:$S$10,2,FALSE),J91) -> Trd_lcv_dsl-hyb | K92: =IFERROR(IF(VALUE(C92)>2020,J92&"_"&TEXT(B92*100,"00"),"\I:"),"\I:") -> \I: | L92: =LEFT(K92,7) -> \I: | M92: =IF($K92="\I:","",C92) | N92: =IF($K92="\I:","",D92) | O92: =IF($K92="\I:","",E92) | P92: =IF($K92="\I:","",F92) | T92: =K92 -> \I: | U92: =OFFSET($S$1,MATCH(J92,$S$1:$S$10,0)-1,-1)&" -- "&TEXT(B92,"00%") -> ICE hybrid diesel LCV -- 00% | V92: Bvkm | W92: million vehicles
J93: =IFERROR(VLOOKUP(C93,$R$1:$S$10,2,FALSE),J92) -> Trd_lcv_dsl-hyb | K93: =IFERROR(IF(VALUE(C93)>2020,J93&"_"&TEXT(B93*100,"00"),"\I:"),"\I:") -> \I: | L93: =LEFT(K93,7) -> \I: | M93: =IF($K93="\I:","",C93) | N93: =IF($K93="\I:","",D93) | O93: =IF($K93="\I:","",E93) | P93: =IF($K93="\I:","",F93) | T93: =K93 -> \I: | U93: =OFFSET($S$1,MATCH(J93,$S$1:$S$10,0)-1,-1)&" -- "&TEXT(B93,"00%") -> ICE hybrid diesel LCV -- 00% | V93: Bvkm | W93: million vehicles
B94: Reduction of specific energy consumption relative to 2015 diesel vehicle (%) | C94: ICE plug-in hybrid diesel LCV | J94: =IFERROR(VLOOKUP(C94,$R$1:$S$10,2,FALSE),J93) -> Trd_lcv_dsl-pih | K94: =IFERROR(IF(VALUE(C94)>2020,J94&"_"&TEXT(B94*100,"00"),"\I:"),"\I:") -> \I: | L94: =LEFT(K94,7) -> \I: | M94: =IF($K94="\I:","",C94) | N94: =IF($K94="\I:","",D94) | O94: =IF($K94="\I:","",E94) | P94: =IF($K94="\I:","",F94) | T94: =K94 -> \I: | U94: =OFFSET($S$1,MATCH(J94,$S$1:$S$10,0)-1,-1)&" -- "&TEXT(B94,"00%") -> ICE plug-in hybrid diesel LCV -- Reduction of specific energy consumption relative to 2015 diesel vehicle (%) | V94: Bvkm | W94: million vehicles
J95: =IFERROR(VLOOKUP(C95,$R$1:$S$10,2,FALSE),J94) -> Trd_lcv_dsl-pih | K95: =IFERROR(IF(VALUE(C95)>2020,J95&"_"&TEXT(B95*100,"00"),"\I:"),"\I:") -> \I: | L95: =LEFT(K95,7) -> \I: | M95: =IF($K95="\I:","",C95) | N95: =IF($K95="\I:","",D95) | O95: =IF($K95="\I:","",E95) | P95: =IF($K95="\I:","",F95) | T95: =K95 -> \I: | U95: =OFFSET($S$1,MATCH(J95,$S$1:$S$10,0)-1,-1)&" -- "&TEXT(B95,"00%") -> ICE plug-in hybrid diesel LCV -- 00% | V95: Bvkm | W95: million vehicles
J96: =IFERROR(VLOOKUP(C96,$R$1:$S$10,2,FALSE),J95) -> Trd_lcv_dsl-pih | K96: =IFERROR(IF(VALUE(C96)>2020,J96&"_"&TEXT(B96*100,"00"),"\I:"),"\I:") -> \I: | L96: =LEFT(K96,7) -> \I: | M96: =IF($K96="\I:","",C96) | N96: =IF($K96="\I:","",D96) | O96: =IF($K96="\I:","",E96) | P96: =IF($K96="\I:","",F96) | T96: =K96 -> \I: | U96: =OFFSET($S$1,MATCH(J96,$S$1:$S$10,0)-1,-1)&" -- "&TEXT(B96,"00%") -> ICE plug-in hybrid diesel LCV -- 00% | V96: Bvkm | W96: million vehicles
C97: 2020 | D97: 2030 | E97: 2040 | F97: 2050 | J97: =IFERROR(VLOOKUP(C97,$R$1:$S$10,2,FALSE),J96) -> Trd_lcv_dsl-pih | K97: =IFERROR(IF(VALUE(C97)>2020,J97&"_"&TEXT(B97*100,"00"),"\I:"),"\I:") -> \I: | L97: =LEFT(K97,7) -> \I: | M97: =IF($K97="\I:","",C97) | N97: =IF($K97="\I:","",D97) | O97: =IF($K97="\I:","",E97) | P97: =IF($K97="\I:","",F97) | T97: =K97 -> \I: | U97: =OFFSET($S$1,MATCH(J97,$S$1:$S$10,0)-1,-1)&" -- "&TEXT(B97,"00%") -> ICE plug-in hybrid diesel LCV -- 00% | V97: Bvkm | W97: million vehicles
B98: 0.85 | C98: 29234.487 | D98: 24721.623 | E98: 23657.154 | F98: 23346.695 | I98: =$I$63*(1+B98)/$I$11 -> 1.8843123 | J98: =IFERROR(VLOOKUP(C98,$R$1:$S$10,2,FALSE),J97) -> Trd_lcv_dsl-pih | K98: =IFERROR(IF(VALUE(C98)>2020,J98&"_"&TEXT(B98*100,"00"),"\I:"),"\I:") -> Trd_lcv_dsl-pih_85 | L98: =LEFT(K98,7) -> Trd_lcv | M98: =IF($K98="\I:","",C98) -> 29234.487 | N98: =IF($K98="\I:","",D98) -> 24721.623 | O98: =IF($K98="\I:","",E98) -> 23657.154 | P98: =IF($K98="\I:","",F98) -> 23346.695 | T98: =K98 -> Trd_lcv_dsl-pih_85 | U98: =OFFSET($S$1,MATCH(J98,$S$1:$S$10,0)-1,-1)&" -- "&TEXT(B98,"00%") -> ICE plug-in hybrid diesel LCV -- 85% | V98: Bvkm | W98: million vehicles
B99: 0.86 | C99: 29248.701 | D99: 24735.564 | E99: 23661.323 | F99: 23347.458 | I99: =$I$63*(1+B99)/$I$11 -> 1.8944978 | J99: =IFERROR(VLOOKUP(C99,$R$1:$S$10,2,FALSE),J98) -> Trd_lcv_dsl-pih | K99: =IFERROR(IF(VALUE(C99)>2020,J99&"_"&TEXT(B99*100,"00"),"\I:"),"\I:") -> Trd_lcv_dsl-pih_86 | L99: =LEFT(K99,7) -> Trd_lcv | M99: =IF($K99="\I:","",C99) -> 29248.701 | N99: =IF($K99="\I:","",D99) -> 24735.564 | O99: =IF($K99="\I:","",E99) -> 23661.323 | P99: =IF($K99="\I:","",F99) -> 23347.458 | T99: =K99 -> Trd_lcv_dsl-pih_86 | U99: =OFFSET($S$1,MATCH(J99,$S$1:$S$10,0)-1,-1)&" -- "&TEXT(B99,"00%") -> ICE plug-in hybrid diesel LCV -- 86% | V99: Bvkm | W99: million vehicles
B100: 0.87 | C100: 29375.518 | D100: 24752.509 | E100: 23672.992 | F100: 23357.558 | I100: =$I$63*(1+B100)/$I$11 -> 1.9046833 | J100: =IFERROR(VLOOKUP(C100,$R$1:$S$10,2,FALSE),J99) -> Trd_lcv_dsl-pih | K100: =IFERROR(IF(VALUE(C100)>2020,J100&"_"&TEXT(B100*100,"00"),"\I:"),"\I:") -> Trd_lcv_dsl-pih_87 | L100: =LEFT(K100,7) -> Trd_lcv | M100: =IF($K100="\I:","",C100) -> 29375.518 | N100: =IF($K100="\I:","",D100) -> 24752.509 | O100: =IF($K100="\I:","",E100) -> 23672.992 | P100: =IF($K100="\I:","",F100) -> 23357.558 | T100: =K100 -> Trd_lcv_dsl-pih_87 | U100: =OFFSET($S$1,MATCH(J100,$S$1:$S$10,0)-1,-1)&" -- "&TEXT(B100,"00%") -> ICE plug-in hybrid diesel LCV -- 87% | V100: Bvkm | W100: million vehicles
B101: 0.88 | C101: 29852.398 | D101: 24778.291 | E101: 23702.379 | F101: 23389.092 | I101: =$I$63*(1+B101)/$I$11 -> 1.9148687 | J101: =IFERROR(VLOOKUP(C101,$R$1:$S$10,2,FALSE),J100) -> Trd_lcv_dsl-pih | K101: =IFERROR(IF(VALUE(C101)>2020,J101&"_"&TEXT(B101*100,"00"),"\I:"),"\I:") -> Trd_lcv_dsl-pih_88 | L101: =LEFT(K101,7) -> Trd_lcv | M101: =IF($K101="\I:","",C101) -> 29852.398 | N101: =IF($K101="\I:","",D101) -> 24778.291 | O101: =IF($K101="\I:","",E101) -> 23702.379 | P101: =IF($K101="\I:","",F101) -> 23389.092 | T101: =K101 -> Trd_lcv_dsl-pih_88 | U101: =OFFSET($S$1,MATCH(J101,$S$1:$S$10,0)-1,-1)&" -- "&TEXT(B101,"00%") -> ICE plug-in hybrid diesel LCV -- 88% | V101: Bvkm | W101: million vehicles
...

Sheet Hdt
B1: Modelled economic possibilities for reducing specific energy consumption by transport mode/equipment and fuel/technology over time | Q1: dsl | R1: 7.5-16t diesel truck | S1: ="Trd_hdt_"&Q1 -> Trd_hdt_dsl
B2: © E3-Modelling | I2: 0.052009938 | J2: GJ/kg LNG | Q2: dsl-hyb | R2: 7.5-16t diesel hybrid truck | S2: ="Trd_hdt_"&Q2 -> Trd_hdt_dsl-hyb
B3: TRUCKS between 7.5-16 tons Gross Vehicle Weight | I3: =31536000/10^9 -> 0.031536 | J3: GJ/lt Gasoline | Q3: lng | R3: 7.5-16t LNG truck | S3: ="Trd_hdt_"&Q3 -> Trd_hdt_lng
I4: 0.038 | J4: GJ/lt Diesel | Q4: lpg | R4: 7.5-16t LPG truck | S4: ="\I:Trd_hdt_"&Q4 -> \I:Trd_hdt_lpg
B5: Reference values for diesel truck 7.5-16t | I5: =1.406/26.137 -> 0.053793473 | J5: GJ/kg CNG | Q5: elc | R5: 7.5-16t battery electric truck | S5: ="Trd_hdt_"&Q5 -> Trd_hdt_elc
B6: 2015 | I6: 0.02559 | J6: GJ/lt LPG | Q6: hh2 | R6: 7.5-16t Hydrogen fuel cell truck | S6: ="Trd_hdt_"&Q6 -> Trd_hdt_hh2
B7: Energy consumption | C7: lt/100 km | D7: 18.882516 | G7: =D7*$I$4/100*10^9/10^6 -> 7.1753562 | I7: =1/G7 -> 0.1393659
B8: Capital cost | C8: Euro15 /veh | D8: 79045.068 | I8: bvkm/PJ
K10: ~FI_T: UP~EUR15~INVCOST | S10: ~FI_Process
I11: EFF | J11: *process | K11: Process | L11: Comm-OUT | M11: =C15 -> 2020 | N11: =D15 -> 2030 | O11: =E15 -> 2040 | P11: =F15 -> 2050 | Q11: FLO_MARK | S11: Sets | T11: TechName | U11: TechDesc | V11: Tact | W11: Tcap
B12: Reduction of specific energy consumption relative to 2015 diesel vehicle(%) | C12: 7.5-16t diesel truck | J12: =IFERROR(VLOOKUP(C12,$R$1:$S$7,2,FALSE),J10) -> Trd_hdt_dsl | K12: =IFERROR(IF(VALUE(C12)>2020,J12&"_"&TEXT(B12*100,"00"),"\I:"),"\I:") -> \I: | L12: =LEFT(K12,7) -> \I: | M12: =IF($K12="\I:","",C12) | N12: =IF($K12="\I:","",D12) | O12: =IF($K12="\I:","",E12) | P12: =IF($K12="\I:","",F12) | S12: DMD | T12: =K12 -> \I: | U12: =OFFSET($S$1,MATCH(J12,$S$1:$S$11,0)-1,-1)&" -- "&TEXT(B12,"00%") -> 7.5-16t diesel truck -- Reduction of specific energy consumption relative to 2015 diesel vehicle(%) | V12: Bvkm | W12: million vehicles
J13: =IFERROR(VLOOKUP(C13,$R$1:$S$7,2,FALSE),J12) -> Trd_hdt_dsl | K13: =IFERROR(IF(VALUE(C13)>2020,J13&"_"&TEXT(B13*100,"00"),"\I:"),"\I:") -> \I: | L13: =LEFT(K13,7) -> \I: | M13: =IF($K13="\I:","",C13) | N13: =IF($K13="\I:","",D13) | O13: =IF($K13="\I:","",E13) | P13: =IF($K13="\I:","",F13) | S13: DMD | T13: =K13 -> \I: | U13: =OFFSET($S$1,MATCH(J13,$S$1:$S$11,0)-1,-1)&" -- "&TEXT(B13,"00%") -> 7.5-16t diesel truck -- 00% | V13: Bvkm | W13: million vehicles
J14: =IFERROR(VLOOKUP(C14,$R$1:$S$7,2,FALSE),J13) -> Trd_hdt_dsl | K14: =IFERROR(IF(VALUE(C14)>2020,J14&"_"&TEXT(B14*100,"00"),"\I:"),"\I:") -> \I: | L14: =LEFT(K14,7) -> \I: | M14: =IF($K14="\I:","",C14) | N14: =IF($K14="\I:","",D14) | O14: =IF($K14="\I:","",E14) | P14: =IF($K14="\I:","",F14) | S14: DMD | T14: =K14 -> \I: | U14: =OFFSET($S$1,MATCH(J14,$S$1:$S$11,0)-1,-1)&" -- "&TEXT(B14,"00%") -> 7.5-16t diesel truck -- 00% | V14: Bvkm | W14: million vehicles
C15: 2020 | D15: 2030 | E15: 2040 | F15: 2050 | J15: =IFERROR(VLOOKUP(C15,$R$1:$S$7,2,FALSE),J14) -> Trd_hdt_dsl | K15: =IFERROR(IF(VALUE(C15)>2020,J15&"_"&TEXT(B15*100,"00"),"\I:"),"\I:") -> \I: | L15: =LEFT(K15,7) -> \I: | M15: =IF($K15="\I:","",C15) | N15: =IF($K15="\I:","",D15) | O15: =IF($K15="\I:","",E15) | P15: =IF($K15="\I:","",F15) | S15: DMD | T15: =K15 -> \I: | U15: =OFFSET($S$1,MATCH(J15,$S$1:$S$11,0)-1,-1)&" -- "&TEXT(B15,"00%") -> 7.5-16t diesel truck -- 00% | V15: Bvkm | W15: million vehicles
B16: 0.044125814 | C16: 79927.754 | D16: 79927.754 | E16: 79927.754 | F16: 79927.754 | I16: =(1+B16) -> 1.0441258 | J16: =IFERROR(VLOOKUP(C16,$R$1:$S$7,2,FALSE),J15) -> Trd_hdt_dsl | K16: =IFERROR(IF(VALUE(C16)>2020,J16&"_"&TEXT(B16*100,"00"),"\I:"),"\I:") -> Trd_hdt_dsl_04 | L16: =LEFT(K16,7) -> Trd_hdt | M16: =IF($K16="\I:","",C16) -> 79927.754 | N16: =IF($K16="\I:","",D16) -> 79927.754 | O16: =IF($K16="\I:","",E16) -> 79927.754 | P16: =IF($K16="\I:","",F16) -> 79927.754 | S16: DMD | T16: =K16 -> Trd_hdt_dsl_04 | U16: =OFFSET($S$1,MATCH(J16,$S$1:$S$11,0)-1,-1)&" -- "&TEXT(B16,"00%") -> 7.5-16t diesel truck -- 04% | V16: Bvkm | W16: million vehicles
B17: 0.094125814 | C17: 81360.186 | D17: 80873.238 | E17: 80873.238 | F17: 80873.238 | I17: =(1+B17) -> 1.0941258 | J17: =IFERROR(VLOOKUP(C17,$R$1:$S$7,2,FALSE),J16) -> Trd_hdt_dsl | K17: =IFERROR(IF(VALUE(C17)>2020,J17&"_"&TEXT(B17*100,"00"),"\I:"),"\I:") -> Trd_hdt_dsl_09 | L17: =LEFT(K17,7) -> Trd_hdt | M17: =IF($K17="\I:","",C17) -> 81360.186 | N17: =IF($K17="\I:","",D17) -> 80873.238 | O17: =IF($K17="\I:","",E17) -> 80873.238 | P17: =IF($K17="\I:","",F17) -> 80873.238 | S17: DMD | T17: =K17 -> Trd_hdt_dsl_09 | U17: =OFFSET($S$1,MATCH(J17,$S$1:$S$11,0)-1,-1)&" -- "&TEXT(B17,"00%") -> 7.5-16t diesel truck -- 09% | V17: Bvkm | W17: million vehicles
B18: 0.14412581 | C18: 82659.163 | D18: 82265.607 | E18: 82265.607 | F18: 82265.607 | I18: =(1+B18) -> 1.1441258 | J18: =IFERROR(VLOOKUP(C18,$R$1:$S$7,2,FALSE),J17) -> Trd_hdt_dsl | K18: =IFERROR(IF(VALUE(C18)>2020,J18&"_"&TEXT(B18*100,"00"),"\I:"),"\I:") -> Trd_hdt_dsl_14 | L18: =LEFT(K18,7) -> Trd_hdt | M18: =IF($K18="\I:","",C18) -> 82659.163 | N18: =IF($K18="\I:","",D18) -> 82265.607 | O18: =IF($K18="\I:","",E18) -> 82265.607 | P18: =IF($K18="\I:","",F18) -> 82265.607 | S18: DMD | T18: =K18 -> Trd_hdt_dsl_14 | U18: =OFFSET($S$1,MATCH(J18,$S$1:$S$11,0)-1,-1)&" -- "&TEXT(B18,"00%") -> 7.5-16t diesel truck -- 14% | V18: Bvkm | W18: million vehicles
B19: 0.19412581 | C19: 88191.03 | D19: 84316.081 | E19: 84316.081 | F19: 84316.081 | I19: =(1+B19) -> 1.1941258 | J19: =IFERROR(VLOOKUP(C19,$R$1:$S$7,2,FALSE),J18) -> Trd_hdt_dsl | K19: =IFERROR(IF(VALUE(C19)>2020,J19&"_"&TEXT(B19*100,"00"),"\I:"),"\I:") -> Trd_hdt_dsl_19 | L19: =LEFT(K19,7) -> Trd_hdt | M19: =IF($K19="\I:","",C19) -> 88191.03 | N19: =IF($K19="\I:","",D19) -> 84316.081 | O19: =IF($K19="\I:","",E19) -> 84316.081 | P19: =IF($K19="\I:","",F19) -> 84316.081 | S19: DMD | T19: =K19 -> Trd_hdt_dsl_19 | U19: =OFFSET($S$1,MATCH(J19,$S$1:$S$11,0)-1,-1)&" -- "&TEXT(B19,"00%") -> 7.5-16t diesel truck -- 19% | V19: Bvkm | W19: million vehicles
B20: 0.24412581 | C20: 92499.125 | D20: 87335.716 | E20: 87335.716 | F20: 87335.716 | I20: =(1+B20) -> 1.2441258 | J20: =IFERROR(VLOOKUP(C20,$R$1:$S$7,2,FALSE),J19) -> Trd_hdt_dsl | K20: =IFERROR(IF(VALUE(C20)>2020,J20&"_"&TEXT(B20*100,"00"),"\I:"),"\I:") -> Trd_hdt_dsl_24 | L20: =LEFT(K20,7) -> Trd_hdt | M20: =IF($K20="\I:","",C20) -> 92499.125 | N20: =IF($K20="\I:","",D20) -> 87335.716 | O20: =IF($K20="\I:","",E20) -> 87335.716 | P20: =IF($K20="\I:","",F20) -> 87335.716 | S20: DMD | T20: =K20 -> Trd_hdt_dsl_24 | U20: =OFFSET($S$1,MATCH(J20,$S$1:$S$11,0)-1,-1)&" -- "&TEXT(B20,"00%") -> 7.5-16t diesel truck -- 24% | V20: Bvkm | W20: million vehicles
B21: 0.26412581 | C21: 115400.25 | D21: 91896.61 | E21: 91782.585 | F21: 91782.585 | I21: =(1+B21) -> 1.2641258 | J21: =IFERROR(VLOOKUP(C21,$R$1:$S$7,2,FALSE),J20) -> Trd_hdt_dsl | K21: =IFERROR(IF(VALUE(C21)>2020,J21&"_"&TEXT(B21*100,"00"),"\I:"),"\I:") -> Trd_hdt_dsl_26 | L21: =LEFT(K21,7) -> Trd_hdt | M21: =IF($K21="\I:","",C21) -> 115400.25 | N21: =IF($K21="\I:","",D21) -> 91896.61 | O21: =IF($K21="\I:","",E21) -> 91782.585 | P21: =IF($K21="\I:","",F21) -> 91782.585 | S21: DMD | T21: =K21 -> Trd_hdt_dsl_26 | U21: =OFFSET($S$1,MATCH(J21,$S$1:$S$11,0)-1,-1)&" -- "&TEXT(B21,"00%") -> 7.5-16t diesel truck -- 26% | V21: Bvkm | W21: million vehicles
B22: 0.29412581 | C22: 189775.23 | D22: 105837.45 | E22: 98331.275 | F22: 98331.275 | I22: =(1+B22) -> 1.2941258 | J22: =IFERROR(VLOOKUP(C22,$R$1:$S$7,2,FALSE),J21) -> Trd_hdt_dsl | K22: =IFERROR(IF(VALUE(C22)>2020,J22&"_"&TEXT(B22*100,"00"),"\I:"),"\I:") -> Trd_hdt_dsl_29 | L22: =LEFT(K22,7) -> Trd_hdt | M22: =IF($K22="\I:","",C22) -> 189775.23 | N22: =IF($K22="\I:","",D22) -> 105837.45 | O22: =IF($K22="\I:","",E22) -> 98331.275 | P22: =IF($K22="\I:","",F22) -> 98331.275 | S22: DMD | T22: =K22 -> Trd_hdt_dsl_29 | U22: =OFFSET($S$1,MATCH(J22,$S$1:$S$11,0)-1,-1)&" -- "&TEXT(B22,"00%") -> 7.5-16t diesel truck -- 29% | V22: Bvkm | W22: million vehicles
J23: =IFERROR(VLOOKUP(C23,$R$1:$S$7,2,FALSE),J22) -> Trd_hdt_dsl | K23: =IFERROR(IF(VALUE(C23)>2020,J23&"_"&TEXT(B23*100,"00"),"\I:"),"\I:") -> \I: | L23: =LEFT(K23,7) -> \I: | M23: =IF($K23="\I:","",C23) | N23: =IF($K23="\I:","",D23) | O23: =IF($K23="\I:","",E23) | P23: =IF($K23="\I:","",F23) | T23: =K23 -> \I: | U23: =OFFSET($S$1,MATCH(J23,$S$1:$S$11,0)-1,-1)&" -- "&TEXT(B23,"00%") -> 7.5-16t diesel truck -- 00% | V23: Bvkm | W23: million vehicles
J24: =IFERROR(VLOOKUP(C24,$R$1:$S$7,2,FALSE),J23) -> Trd_hdt_dsl | K24: =IFERROR(IF(VALUE(C24)>2020,J24&"_"&TEXT(B24*100,"00"),"\I:"),"\I:") -> \I: | L24: =LEFT(K24,7) -> \I: | M24: =IF($K24="\I:","",C24) | N24: =IF($K24="\I:","",D24) | O24: =IF($K24="\I:","",E24) | P24: =IF($K24="\I:","",F24) | T24: =K24 -> \I: | U24: =OFFSET($S$1,MATCH(J24,$S$1:$S$11,0)-1,-1)&" -- "&TEXT(B24,"00%") -> 7.5-16t diesel truck -- 00% | V24: Bvkm | W24: million vehicles
J25: =IFERROR(VLOOKUP(C25,$R$1:$S$7,2,FALSE),J24) -> Trd_hdt_dsl | K25: =IFERROR(IF(VALUE(C25)>2020,J25&"_"&TEXT(B25*100,"00"),"\I:"),"\I:") -> \I: | L25: =LEFT(K25,7) -> \I: | M25: =IF($K25="\I:","",C25) | N25: =IF($K25="\I:","",D25) | O25: =IF($K25="\I:","",E25) | P25: =IF($K25="\I:","",F25) | T25: =K25 -> \I: | U25: =OFFSET($S$1,MATCH(J25,$S$1:$S$11,0)-1,-1)&" -- "&TEXT(B25,"00%") -> 7.5-16t diesel truck -- 00% | V25: Bvkm | W25: million vehicles
B26: Reduction of specific energy consumption relative to 2015 diesel vehicle(%) | C26: 7.5-16t diesel hybrid truck | J26: =IFERROR(VLOOKUP(C26,$R$1:$S$7,2,FALSE),J25) -> Trd_hdt_dsl-hyb | K26: =IFERROR(IF(VALUE(C26)>2020,J26&"_"&TEXT(B26*100,"00"),"\I:"),"\I:") -> \I: | L26: =LEFT(K26,7) -> \I: | M26: =IF($K26="\I:","",C26) | N26: =IF($K26="\I:","",D26) | O26: =IF($K26="\I:","",E26) | P26: =IF($K26="\I:","",F26) | T26: =K26 -> \I: | U26: =OFFSET($S$1,MATCH(J26,$S$1:$S$11,0)-1,-1)&" -- "&TEXT(B26,"00%") -> 7.5-16t diesel hybrid truck -- Reduction of specific energy consumption relative to 2015 diesel vehicle(%) | V26: Bvkm | W26: million vehicles
J27: =IFERROR(VLOOKUP(C27,$R$1:$S$7,2,FALSE),J26) -> Trd_hdt_dsl-hyb | K27: =IFERROR(IF(VALUE(C27)>2020,J27&"_"&TEXT(B27*100,"00"),"\I:"),"\I:") -> \I: | L27: =LEFT(K27,7) -> \I: | M27: =IF($K27="\I:","",C27) | N27: =IF($K27="\I:","",D27) | O27: =IF($K27="\I:","",E27) | P27: =IF($K27="\I:","",F27) | T27: =K27 -> \I: | U27: =OFFSET($S$1,MATCH(J27,$S$1:$S$11,0)-1,-1)&" -- "&TEXT(B27,"00%") -> 7.5-16t diesel hybrid truck -- 00% | V27: Bvkm | W27: million vehicles
J28: =IFERROR(VLOOKUP(C28,$R$1:$S$7,2,FALSE),J27) -> Trd_hdt_dsl-hyb | K28: =IFERROR(IF(VALUE(C28)>2020,J28&"_"&TEXT(B28*100,"00"),"\I:"),"\I:") -> \I: | L28: =LEFT(K28,7) -> \I: | M28: =IF($K28="\I:","",C28) | N28: =IF($K28="\I:","",D28) | O28: =IF($K28="\I:","",E28) | P28: =IF($K28="\I:","",F28) | T28: =K28 -> \I: | U28: =OFFSET($S$1,MATCH(J28,$S$1:$S$11,0)-1,-1)&" -- "&TEXT(B28,"00%") -> 7.5-16t diesel hybrid truck -- 00% | V28: Bvkm | W28: million vehicles
C29: 2020 | D29: 2030 | E29: 2040 | F29: 2050 | J29: =IFERROR(VLOOKUP(C29,$R$1:$S$7,2,FALSE),J28) -> Trd_hdt_dsl-hyb | K29: =IFERROR(IF(VALUE(C29)>2020,J29&"_"&TEXT(B29*100,"00"),"\I:"),"\I:") -> \I: | L29: =LEFT(K29,7) -> \I: | M29: =IF($K29="\I:","",C29) | N29: =IF($K29="\I:","",D29) | O29: =IF($K29="\I:","",E29) | P29: =IF($K29="\I:","",F29) | T29: =K29 -> \I: | U29: =OFFSET($S$1,MATCH(J29,$S$1:$S$11,0)-1,-1)&" -- "&TEXT(B29,"00%") -> 7.5-16t diesel hybrid truck -- 00% | V29: Bvkm | W29: million vehicles
B30: 0.1 | C30: 88920.665 | D30: 85723.707 | E30: 84520.589 | F30: 83595.636 | I30: =(1+B30) -> 1.1 | J30: =IFERROR(VLOOKUP(C30,$R$1:$S$7,2,FALSE),J29) -> Trd_hdt_dsl-hyb | K30: =IFERROR(IF(VALUE(C30)>2020,J30&"_"&TEXT(B30*100,"00"),"\I:"),"\I:") -> Trd_hdt_dsl-hyb_10 | L30: =LEFT(K30,7) -> Trd_hdt | M30: =IF($K30="\I:","",C30) -> 88920.665 | N30: =IF($K30="\I:","",D30) -> 85723.707 | O30: =IF($K30="\I:","",E30) -> 84520.589 | P30: =IF($K30="\I:","",F30) -> 83595.636 | T30: =K30 -> Trd_hdt_dsl-hyb_10 | U30: =OFFSET($S$1,MATCH(J30,$S$1:$S$11,0)-1,-1)&" -- "&TEXT(B30,"00%") -> 7.5-16t diesel hybrid truck -- 10% | V30: Bvkm | W30: million vehicles
B31: 0.15 | C31: 90395.02 | D31: 85866.889 | E31: 84742.075 | F31: 83858.379 | I31: =(1+B31) -> 1.15 | J31: =IFERROR(VLOOKUP(C31,$R$1:$S$7,2,FALSE),J30) -> Trd_hdt_dsl-hyb | K31: =IFERROR(IF(VALUE(C31)>2020,J31&"_"&TEXT(B31*100,"00"),"\I:"),"\I:") -> Trd_hdt_dsl-hyb_15 | L31: =LEFT(K31,7) -> Trd_hdt | M31: =IF($K31="\I:","",C31) -> 90395.02 | N31: =IF($K31="\I:","",D31) -> 85866.889 | O31: =IF($K31="\I:","",E31) -> 84742.075 | P31: =IF($K31="\I:","",F31) -> 83858.379 | T31: =K31 -> Trd_hdt_dsl-hyb_15 | U31: =OFFSET($S$1,MATCH(J31,$S$1:$S$11,0)-1,-1)&" -- "&TEXT(B31,"00%") -> 7.5-16t diesel hybrid truck -- 15% | V31: Bvkm | W31: million vehicles
B32: 0.2 | C32: 91869.376 | D32: 86041.571 | E32: 84996.503 | F32: 84156.751 | I32: =(1+B32) -> 1.2 | J32: =IFERROR(VLOOKUP(C32,$R$1:$S$7,2,FALSE),J31) -> Trd_hdt_dsl-hyb | K32: =IFERROR(IF(VALUE(C32)>2020,J32&"_"&TEXT(B32*100,"00"),"\I:"),"\I:") -> Trd_hdt_dsl-hyb_20 | L32: =LEFT(K32,7) -> Trd_hdt | M32: =IF($K32="\I:","",C32) -> 91869.376 | N32: =IF($K32="\I:","",D32) -> 86041.571 | O32: =IF($K32="\I:","",E32) -> 84996.503 | P32: =IF($K32="\I:","",F32) -> 84156.751 | T32: =K32 -> Trd_hdt_dsl-hyb_20 | U32: =OFFSET($S$1,MATCH(J32,$S$1:$S$11,0)-1,-1)&" -- "&TEXT(B32,"00%") -> 7.5-16t diesel hybrid truck -- 20% | V32: Bvkm | W32: million vehicles
B33: 0.25 | C33: 93343.731 | D33: 86487.444 | E33: 85493.169 | F33: 84675.056 | I33: =(1+B33) -> 1.25 | J33: =IFERROR(VLOOKUP(C33,$R$1:$S$7,2,FALSE),J32) -> Trd_hdt_dsl-hyb | K33: =IFERROR(IF(VALUE(C33)>2020,J33&"_"&TEXT(B33*100,"00"),"\I:"),"\I:") -> Trd_hdt_dsl-hyb_25 | L33: =LEFT(K33,7) -> Trd_hdt | M33: =IF($K33="\I:","",C33) -> 93343.731 | N33: =IF($K33="\I:","",D33) -> 86487.444 | O33: =IF($K33="\I:","",E33) -> 85493.169 | P33: =IF($K33="\I:","",F33) -> 84675.056 | T33: =K33 -> Trd_hdt_dsl-hyb_25 | U33: =OFFSET($S$1,MATCH(J33,$S$1:$S$11,0)-1,-1)&" -- "&TEXT(B33,"00%") -> 7.5-16t diesel hybrid truck -- 25% | V33: Bvkm | W33: million vehicles
B34: 0.3 | C34: 94818.087 | D34: 87242.497 | E34: 86278.806 | F34: 85465.438 | I34: =(1+B34) -> 1.3 | J34: =IFERROR(VLOOKUP(C34,$R$1:$S$7,2,FALSE),J33) -> Trd_hdt_dsl-hyb | K34: =IFERROR(IF(VALUE(C34)>2020,J34&"_"&TEXT(B34*100,"00"),"\I:"),"\I:") -> Trd_hdt_dsl-hyb_30 | L34: =LEFT(K34,7) -> Trd_hdt | M34: =IF($K34="\I:","",C34) -> 94818.087 | N34: =IF($K34="\I:","",D34) -> 87242.497 | O34: =IF($K34="\I:","",E34) -> 86278.806 | P34: =IF($K34="\I:","",F34) -> 85465.438 | T34: =K34 -> Trd_hdt_dsl-hyb_30 | U34: =OFFSET($S$1,MATCH(J34,$S$1:$S$11,0)-1,-1)&" -- "&TEXT(B34,"00%") -> 7.5-16t diesel hybrid truck -- 30% | V34: Bvkm | W34: million vehicles
B35: 0.35 | C35: 96915.145 | D35: 88296.021 | E35: 87359.295 | F35: 86546.242 | I35: =(1+B35) -> 1.35 | J35: =IFERROR(VLOOKUP(C35,$R$1:$S$7,2,FALSE),J34) -> Trd_hdt_dsl-hyb | K35: =IFERROR(IF(VALUE(C35)>2020,J35&"_"&TEXT(B35*100,"00"),"\I:"),"\I:") -> Trd_hdt_dsl-hyb_35 | L35: =LEFT(K35,7) -> Trd_hdt | M35: =IF($K35="\I:","",C35) -> 96915.145 | N35: =IF($K35="\I:","",D35) -> 88296.021 | O35: =IF($K35="\I:","",E35) -> 87359.295 | P35: =IF($K35="\I:","",F35) -> 86546.242 | T35: =K35 -> Trd_hdt_dsl-hyb_35 | U35: =OFFSET($S$1,MATCH(J35,$S$1:$S$11,0)-1,-1)&" -- "&TEXT(B35,"00%") -> 7.5-16t diesel hybrid truck -- 35% | V35: Bvkm | W35: million vehicles
B36: 0.4 | C36: 98758.177 | D36: 91896.257 | E36: 90807.971 | F36: 89832.554 | I36: =(1+B36) -> 1.4 | J36: =IFERROR(VLOOKUP(C36,$R$1:$S$7,2,FALSE),J35) -> Trd_hdt_dsl-hyb | K36: =IFERROR(IF(VALUE(C36)>2020,J36&"_"&TEXT(B36*100,"00"),"\I:"),"\I:") -> Trd_hdt_dsl-hyb_40 | L36: =LEFT(K36,7) -> Trd_hdt | M36: =IF($K36="\I:","",C36) -> 98758.177 | N36: =IF($K36="\I:","",D36) -> 91896.257 | O36: =IF($K36="\I:","",E36) -> 90807.971 | P36: =IF($K36="\I:","",F36) -> 89832.554 | T36: =K36 -> Trd_hdt_dsl-hyb_40 | U36: =OFFSET($S$1,MATCH(J36,$S$1:$S$11,0)-1,-1)&" -- "&TEXT(B36,"00%") -> 7.5-16t diesel hybrid truck -- 40% | V36: Bvkm | W36: million vehicles
B37: 0.45 | C37: 104720.41 | D37: 97691.662 | E37: 96426.758 | F37: 95247.659 | I37: =(1+B37) -> 1.45 | J37: =IFERROR(VLOOKUP(C37,$R$1:$S$7,2,FALSE),J36) -> Trd_hdt_dsl-hyb | K37: =IFERROR(IF(VALUE(C37)>2020,J37&"_"&TEXT(B37*100,"00"),"\I:"),"\I:") -> Trd_hdt_dsl-hyb_45 | L37: =LEFT(K37,7) -> Trd_hdt | M37: =IF($K37="\I:","",C37) -> 104720.41 | N37: =IF($K37="\I:","",D37) -> 97691.662 | O37: =IF($K37="\I:","",E37) -> 96426.758 | P37: =IF($K37="\I:","",F37) -> 95247.659 | T37: =K37 -> Trd_hdt_dsl-hyb_45 | U37: =OFFSET($S$1,MATCH(J37,$S$1:$S$11,0)-1,-1)&" -- "&TEXT(B37,"00%") -> 7.5-16t diesel hybrid truck -- 45% | V37: Bvkm | W37: million vehicles
J38: =IFERROR(VLOOKUP(C38,$R$1:$S$7,2,FALSE),J37) -> Trd_hdt_dsl-hyb | K38: =IFERROR(IF(VALUE(C38)>2020,J38&"_"&TEXT(B38*100,"00"),"\I:"),"\I:") -> \I: | L38: =LEFT(K38,7) -> \I: | M38: =IF($K38="\I:","",C38) | N38: =IF($K38="\I:","",D38) | O38: =IF($K38="\I:","",E38) | P38: =IF($K38="\I:","",F38) | T38: =K38 -> \I: | U38: =OFFSET($S$1,MATCH(J38,$S$1:$S$11,0)-1,-1)&" -- "&TEXT(B38,"00%") -> 7.5-16t diesel hybrid truck -- 00% | V38: Bvkm | W38: million vehicles
J39: =IFERROR(VLOOKUP(C39,$R$1:$S$7,2,FALSE),J38) -> Trd_hdt_dsl-hyb | K39: =IFERROR(IF(VALUE(C39)>2020,J39&"_"&TEXT(B39*100,"00"),"\I:"),"\I:") -> \I: | L39: =LEFT(K39,7) -> \I: | M39: =IF($K39="\I:","",C39) | N39: =IF($K39="\I:","",D39) | O39: =IF($K39="\I:","",E39) | P39: =IF($K39="\I:","",F39) | T39: =K39 -> \I: | U39: =OFFSET($S$1,MATCH(J39,$S$1:$S$11,0)-1,-1)&" -- "&TEXT(B39,"00%") -> 7.5-16t diesel hybrid truck -- 00% | V39: Bvkm | W39: million vehicles
J40: =IFERROR(VLOOKUP(C40,$R$1:$S$7,2,FALSE),J39) -> Trd_hdt_dsl-hyb | K40: =IFERROR(IF(VALUE(C40)>2020,J40&"_"&TEXT(B40*100,"00"),"\I:"),"\I:") -> \I: | L40: =LEFT(K40,7) -> \I: | M40: =IF($K40="\I:","",C40) | N40: =IF($K40="\I:","",D40) | O40: =IF($K40="\I:","",E40) | P40: =IF($K40="\I:","",F40) | T40: =K40 -> \I: | U40: =OFFSET($S$1,MATCH(J40,$S$1:$S$11,0)-1,-1)&" -- "&TEXT(B40,"00%") -> 7.5-16t diesel hybrid truck -- 00% | V40: Bvkm | W40: million vehicles
J41: =IFERROR(VLOOKUP(C41,$R$1:$S$7,2,FALSE),J40) -> Trd_hdt_dsl-hyb | K41: =IFERROR(IF(VALUE(C41)>2020,J41&"_"&TEXT(B41*100,"00"),"\I:"),"\I:") -> \I: | L41: =LEFT(K41,7) -> \I: | M41: =IF($K41="\I:","",C41) | N41: =IF($K41="\I:","",D41) | O41: =IF($K41="\I:","",E41) | P41: =IF($K41="\I:","",F41) | T41: =K41 -> \I: | U41: =OFFSET($S$1,MATCH(J41,$S$1:$S$11,0)-1,-1)&" -- "&TEXT(B41,"00%") -> 7.5-16t diesel hybrid truck -- 00% | V41: Bvkm | W41: million vehicles
B42: Reference values for LNG truck 7.5-16t | J42: =IFERROR(VLOOKUP(C42,$R$1:$S$7,2,FALSE),J41) -> Trd_hdt_dsl-hyb | K42: =IFERROR(IF(VALUE(C42)>2020,J42&"_"&TEXT(B42*100,"00"),"\I:"),"\I:") -> \I: | L42: =LEFT(K42,7) -> \I: | M42: =IF($K42="\I:","",C42) | N42: =IF($K42="\I:","",D42) | O42: =IF($K42="\I:","",E42) | P42: =IF($K42="\I:","",F42) | T42: =K42 -> \I: | U42: =OFFSET($S$1,MATCH(J42,$S$1:$S$11,0)-1,-1)&" -- "&TEXT(B42,"00%") -> 7.5-16t diesel hybrid truck -- Reference values for LNG truck 7.5-16t | V42: Bvkm | W42: million vehicles
B43: 2015 | J43: =IFERROR(VLOOKUP(C43,$R$1:$S$7,2,FALSE),J42) -> Trd_hdt_dsl-hyb | K43: =IFERROR(IF(VALUE(C43)>2020,J43&"_"&TEXT(B43*100,"00"),"\I:"),"\I:") -> \I: | L43: =LEFT(K43,7) -> \I: | M43: =IF($K43="\I:","",C43) | N43: =IF($K43="\I:","",D43) | O43: =IF($K43="\I:","",E43) | P43: =IF($K43="\I:","",F43) | T43: =K43 -> \I: | U43: =OFFSET($S$1,MATCH(J43,$S$1:$S$11,0)-1,-1)&" -- "&TEXT(B43,"00%") -> 7.5-16t diesel hybrid truck -- 201500% | V43: Bvkm | W43: million vehicles
B44: Energy consumption | C44: kg/100 km | D44: 15.672489 | G44: =D44*$I$2/100*10^9/10^6 -> 8.1512515 | I44: =1/G44 -> 0.12268055 | J44: =IFERROR(VLOOKUP(C44,$R$1:$S$7,2,FALSE),J43) -> Trd_hdt_dsl-hyb | K44: =IFERROR(IF(VALUE(C44)>2020,J44&"_"&TEXT(B44*100,"00"),"\I:"),"\I:") -> \I: | L44: =LEFT(K44,7) -> \I: | M44: =IF($K44="\I:","",C44) | N44: =IF($K44="\I:","",D44) | O44: =IF($K44="\I:","",E44) | P44: =IF($K44="\I:","",F44) | T44: =K44 -> \I: | U44: =OFFSET($S$1,MATCH(J44,$S$1:$S$11,0)-1,-1)&" -- "&TEXT(B44,"00%") -> 7.5-16t diesel hybrid truck -- Energy consumption | V44: Bvkm | W44: million vehicles
B45: Capital cost | C45: Euro15 /veh | D45: 97834.867 | I45: bvkm/PJ | J45: =IFERROR(VLOOKUP(C45,$R$1:$S$7,2,FALSE),J44) -> Trd_hdt_dsl-hyb | K45: =IFERROR(IF(VALUE(C45)>2020,J45&"_"&TEXT(B45*100,"00"),"\I:"),"\I:") -> \I: | L45: =LEFT(K45,7) -> \I: | M45: =IF($K45="\I:","",C45) | N45: =IF($K45="\I:","",D45) | O45: =IF($K45="\I:","",E45) | P45: =IF($K45="\I:","",F45) | T45: =K45 -> \I: | U45: =OFFSET($S$1,MATCH(J45,$S$1:$S$11,0)-1,-1)&" -- "&TEXT(B45,"00%") -> 7.5-16t diesel hybrid truck -- Capital cost | V45: Bvkm | W45: million vehicles
J46: =IFERROR(VLOOKUP(C46,$R$1:$S$7,2,FALSE),J45) -> Trd_hdt_dsl-hyb | K46: =IFERROR(IF(VALUE(C46)>2020,J46&"_"&TEXT(B46*100,"00"),"\I:"),"\I:") -> \I: | L46: =LEFT(K46,7) -> \I: | M46: =IF($K46="\I:","",C46) | N46: =IF($K46="\I:","",D46) | O46: =IF($K46="\I:","",E46) | P46: =IF($K46="\I:","",F46) | T46: =K46 -> \I: | U46: =OFFSET($S$1,MATCH(J46,$S$1:$S$11,0)-1,-1)&" -- "&TEXT(B46,"00%") -> 7.5-16t diesel hybrid truck -- 00% | V46: Bvkm | W46: million vehicles
B47: Reduction of specific energy consumption relative to 2015 LNG vehicle (%) | C47: 7.5-16t LNG truck | J47: =IFERROR(VLOOKUP(C47,$R$1:$S$7,2,FALSE),J46) -> Trd_hdt_lng | K47: =IFERROR(IF(VALUE(C47)>2020,J47&"_"&TEXT(B47*100,"00"),"\I:"),"\I:") -> \I: | L47: =LEFT(K47,7) -> \I: | M47: =IF($K47="\I:","",C47) | N47: =IF($K47="\I:","",D47) | O47: =IF($K47="\I:","",E47) | P47: =IF($K47="\I:","",F47) | T47: =K47 -> \I: | U47: =OFFSET($S$1,MATCH(J47,$S$1:$S$11,0)-1,-1)&" -- "&TEXT(B47,"00%") -> 7.5-16t LNG truck -- Reduction of specific energy consumption relative to 2015 LNG vehicle (%) | V47: Bvkm | W47: million vehicles
J48: =IFERROR(VLOOKUP(C48,$R$1:$S$7,2,FALSE),J47) -> Trd_hdt_lng | K48: =IFERROR(IF(VALUE(C48)>2020,J48&"_"&TEXT(B48*100,"00"),"\I:"),"\I:") -> \I: | L48: =LEFT(K48,7) -> \I: | M48: =IF($K48="\I:","",C48) | N48: =IF($K48="\I:","",D48) | O48: =IF($K48="\I:","",E48) | P48: =IF($K48="\I:","",F48) | T48: =K48 -> \I: | U48: =OFFSET($S$1,MATCH(J48,$S$1:$S$11,0)-1,-1)&" -- "&TEXT(B48,"00%") -> 7.5-16t LNG truck -- 00% | V48: Bvkm | W48: million vehicles
J49: =IFERROR(VLOOKUP(C49,$R$1:$S$7,2,FALSE),J48) -> Trd_hdt_lng | K49: =IFERROR(IF(VALUE(C49)>2020,J49&"_"&TEXT(B49*100,"00"),"\I:"),"\I:") -> \I: | L49: =LEFT(K49,7) -> \I: | M49: =IF($K49="\I:","",C49) | N49: =IF($K49="\I:","",D49) | O49: =IF($K49="\I:","",E49) | P49: =IF($K49="\I:","",F49) | T49: =K49 -> \I: | U49: =OFFSET($S$1,MATCH(J49,$S$1:$S$11,0)-1,-1)&" -- "&TEXT(B49,"00%") -> 7.5-16t LNG truck -- 00% | V49: Bvkm | W49: million vehicles
C50: 2020 | D50: 2030 | E50: 2040 | F50: 2050 | J50: =IFERROR(VLOOKUP(C50,$R$1:$S$7,2,FALSE),J49) -> Trd_hdt_lng | K50: =IFERROR(IF(VALUE(C50)>2020,J50&"_"&TEXT(B50*100,"00"),"\I:"),"\I:") -> \I: | L50: =LEFT(K50,7) -> \I: | M50: =IF($K50="\I:","",C50) | N50: =IF($K50="\I:","",D50) | O50: =IF($K50="\I:","",E50) | P50: =IF($K50="\I:","",F50) | T50: =K50 -> \I: | U50: =OFFSET($S$1,MATCH(J50,$S$1:$S$11,0)-1,-1)&" -- "&TEXT(B50,"00%") -> 7.5-16t LNG truck -- 00% | V50: Bvkm | W50: million vehicles
B51: 0.044125814 | C51: 98717.552 | D51: 98717.552 | E51: 98717.552 | F51: 98717.552 | I51: =$I$44*(1+B51)/$I$7 -> 0.91911955 | J51: =IFERROR(VLOOKUP(C51,$R$1:$S$7,2,FALSE),J50) -> Trd_hdt_lng | K51: =IFERROR(IF(VALUE(C51)>2020,J51&"_"&TEXT(B51*100,"00"),"\I:"),"\I:") -> Trd_hdt_lng_04 | L51: =LEFT(K51,7) -> Trd_hdt | M51: =IF($K51="\I:","",C51) -> 98717.552 | N51: =IF($K51="\I:","",D51) -> 98717.552 | O51: =IF($K51="\I:","",E51) -> 98717.552 | P51: =IF($K51="\I:","",F51) -> 98717.552 | T51: =K51 -> Trd_hdt_lng_04 | U51: =OFFSET($S$1,MATCH(J51,$S$1:$S$11,0)-1,-1)&" -- "&TEXT(B51,"00%") -> 7.5-16t LNG truck -- 04% | V51: Bvkm | W51: million vehicles
B52: 0.094125814 | C52: 100149.98 | D52: 99663.036 | E52: 99663.036 | F52: 99663.036 | I52: =$I$44*(1+B52)/$I$7 -> 0.96313338 | J52: =IFERROR(VLOOKUP(C52,$R$1:$S$7,2,FALSE),J51) -> Trd_hdt_lng | K52: =IFERROR(IF(VALUE(C52)>2020,J52&"_"&TEXT(B52*100,"00"),"\I:"),"\I:") -> Trd_hdt_lng_09 | L52: =LEFT(K52,7) -> Trd_hdt | M52: =IF($K52="\I:","",C52) -> 100149.98 | N52: =IF($K52="\I:","",D52) -> 99663.036 | O52: =IF($K52="\I:","",E52) -> 99663.036 | P52: =IF($K52="\I:","",F52) -> 99663.036 | T52: =K52 -> Trd_hdt_lng_09 | U52: =OFFSET($S$1,MATCH(J52,$S$1:$S$11,0)-1,-1)&" -- "&TEXT(B52,"00%") -> 7.5-16t LNG truck -- 09% | V52: Bvkm | W52: million vehicles
B53: 0.14412581 | C53: 101448.96 | D53: 101055.41 | E53: 101055.41 | F53: 101055.41 | I53: =$I$44*(1+B53)/$I$7 -> 1.0071472 | J53: =IFERROR(VLOOKUP(C53,$R$1:$S$7,2,FALSE),J52) -> Trd_hdt_lng | K53: =IFERROR(IF(VALUE(C53)>2020,J53&"_"&TEXT(B53*100,"00"),"\I:"),"\I:") -> Trd_hdt_lng_14 | L53: =LEFT(K53,7) -> Trd_hdt | M53: =IF($K53="\I:","",C53) -> 101448.96 | N53: =IF($K53="\I:","",D53) -> 101055.41 | O53: =IF($K53="\I:","",E53) -> 101055.41 | P53: =IF($K53="\I:","",F53) -> 101055.41 | T53: =K53 -> Trd_hdt_lng_14 | U53: =OFFSET($S$1,MATCH(J53,$S$1:$S$11,0)-1,-1)&" -- "&TEXT(B53,"00%") -> 7.5-16t LNG truck -- 14% | V53: Bvkm | W53: million vehicles
B54: 0.19412581 | C54: 106980.83 | D54: 103105.88 | E54: 103105.88 | F54: 103105.88 | I54: =$I$44*(1+B54)/$I$7 -> 1.051161 | J54: =IFERROR(VLOOKUP(C54,$R$1:$S$7,2,FALSE),J53) -> Trd_hdt_lng | K54: =IFERROR(IF(VALUE(C54)>2020,J54&"_"&TEXT(B54*100,"00"),"\I:"),"\I:") -> Trd_hdt_lng_19 | L54: =LEFT(K54,7) -> Trd_hdt | M54: =IF($K54="\I:","",C54) -> 106980.83 | N54: =IF($K54="\I:","",D54) -> 103105.88 | O54: =IF($K54="\I:","",E54) -> 103105.88 | P54: =IF($K54="\I:","",F54) -> 103105.88 | T54: =K54 -> Trd_hdt_lng_19 | U54: =OFFSET($S$1,MATCH(J54,$S$1:$S$11,0)-1,-1)&" -- "&TEXT(B54,"00%") -> 7.5-16t LNG truck -- 19% | V54: Bvkm | W54: million vehicles
B55: 0.24412581 | C55: 111288.92 | D55: 106125.51 | E55: 106125.51 | F55: 106125.51 | I55: =$I$44*(1+B55)/$I$7 -> 1.0951749 | J55: =IFERROR(VLOOKUP(C55,$R$1:$S$7,2,FALSE),J54) -> Trd_hdt_lng | K55: =IFERROR(IF(VALUE(C55)>2020,J55&"_"&TEXT(B55*100,"00"),"\I:"),"\I:") -> Trd_hdt_lng_24 | L55: =LEFT(K55,7) -> Trd_hdt | M55: =IF($K55="\I:","",C55) -> 111288.92 | N55: =IF($K55="\I:","",D55) -> 106125.51 | O55: =IF($K55="\I:","",E55) -> 106125.51 | P55: =IF($K55="\I:","",F55) -> 106125.51 | T55: =K55 -> Trd_hdt_lng_24 | U55: =OFFSET($S$1,MATCH(J55,$S$1:$S$11,0)-1,-1)&" -- "&TEXT(B55,"00%") -> 7.5-16t LNG truck -- 24% | V55: Bvkm | W55: million vehicles
B56: 0.26412581 | C56: 134190.05 | D56: 110686.41 | E56: 110572.38 | F56: 110572.38 | I56: =$I$44*(1+B56)/$I$7 -> 1.1127804 | J56: =IFERROR(VLOOKUP(C56,$R$1:$S$7,2,FALSE),J55) -> Trd_hdt_lng | K56: =IFERROR(IF(VALUE(C56)>2020,J56&"_"&TEXT(B56*100,"00"),"\I:"),"\I:") -> Trd_hdt_lng_26 | L56: =LEFT(K56,7) -> Trd_hdt | M56: =IF($K56="\I:","",C56) -> 134190.05 | N56: =IF($K56="\I:","",D56) -> 110686.41 | O56: =IF($K56="\I:","",E56) -> 110572.38 | P56: =IF($K56="\I:","",F56) -> 110572.38 | T56: =K56 -> Trd_hdt_lng_26 | U56: =OFFSET($S$1,MATCH(J56,$S$1:$S$11,0)-1,-1)&" -- "&TEXT(B56,"00%") -> 7.5-16t LNG truck -- 26% | V56: Bvkm | W56: million vehicles
B57: 0.29412581 | C57: 208565.03 | D57: 124627.25 | E57: 117121.07 | F57: 117121.07 | I57: =$I$44*(1+B57)/$I$7 -> 1.1391887 | J57: =IFERROR(VLOOKUP(C57,$R$1:$S$7,2,FALSE),J56) -> Trd_hdt_lng | K57: =IFERROR(IF(VALUE(C57)>2020,J57&"_"&TEXT(B57*100,"00"),"\I:"),"\I:") -> Trd_hdt_lng_29 | L57: =LEFT(K57,7) -> Trd_hdt | M57: =IF($K57="\I:","",C57) -> 208565.03 | N57: =IF($K57="\I:","",D57) -> 124627.25 | O57: =IF($K57="\I:","",E57) -> 117121.07 | P57: =IF($K57="\I:","",F57) -> 117121.07 | T57: =K57 -> Trd_hdt_lng_29 | U57: =OFFSET($S$1,MATCH(J57,$S$1:$S$11,0)-1,-1)&" -- "&TEXT(B57,"00%") -> 7.5-16t LNG truck -- 29% | V57: Bvkm | W57: million vehicles
J58: =IFERROR(VLOOKUP(C58,$R$1:$S$7,2,FALSE),J57) -> Trd_hdt_lng | K58: =IFERROR(IF(VALUE(C58)>2020,J58&"_"&TEXT(B58*100,"00"),"\I:"),"\I:") -> \I: | L58: =LEFT(K58,7) -> \I: | M58: =IF($K58="\I:","",C58) | N58: =IF($K58="\I:","",D58) | O58: =IF($K58="\I:","",E58) | P58: =IF($K58="\I:","",F58) | T58: =K58 -> \I: | U58: =OFFSET($S$1,MATCH(J58,$S$1:$S$11,0)-1,-1)&" -- "&TEXT(B58,"00%") -> 7.5-16t LNG truck -- 00% | V58: Bvkm | W58: million vehicles
J59: =IFERROR(VLOOKUP(C59,$R$1:$S$7,2,FALSE),J58) -> Trd_hdt_lng | K59: =IFERROR(IF(VALUE(C59)>2020,J59&"_"&TEXT(B59*100,"00"),"\I:"),"\I:") -> \I: | L59: =LEFT(K59,7) -> \I: | M59: =IF($K59="\I:","",C59) | N59: =IF($K59="\I:","",D59) | O59: =IF($K59="\I:","",E59) | P59: =IF($K59="\I:","",F59) | T59: =K59 -> \I: | U59: =OFFSET($S$1,MATCH(J59,$S$1:$S$11,0)-1,-1)&" -- "&TEXT(B59,"00%") -> 7.5-16t LNG truck -- 00% | V59: Bvkm | W59: million vehicles
J60: =IFERROR(VLOOKUP(C60,$R$1:$S$7,2,FALSE),J59) -> Trd_hdt_lng | K60: =IFERROR(IF(VALUE(C60)>2020,J60&"_"&TEXT(B60*100,"00"),"\I:"),"\I:") -> \I: | L60: =LEFT(K60,7) -> \I: | M60: =IF($K60="\I:","",C60) | N60: =IF($K60="\I:","",D60) | O60: =IF($K60="\I:","",E60) | P60: =IF($K60="\I:","",F60) | T60: =K60 -> \I: | U60: =OFFSET($S$1,MATCH(J60,$S$1:$S$11,0)-1,-1)&" -- "&TEXT(B60,"00%") -> 7.5-16t LNG truck -- 00% | V60: Bvkm | W60: million vehicles
J61: =IFERROR(VLOOKUP(C61,$R$1:$S$7,2,FALSE),J60) -> Trd_hdt_lng | K61: =IFERROR(IF(VALUE(C61)>2020,J61&"_"&TEXT(B61*100,"00"),"\I:"),"\I:") -> \I: | L61: =LEFT(K61,7) -> \I: | M61: =IF($K61="\I:","",C61) | N61: =IF($K61="\I:","",D61) | O61: =IF($K61="\I:","",E61) | P61: =IF($K61="\I:","",F61) | T61: =K61 -> \I: | U61: =OFFSET($S$1,MATCH(J61,$S$1:$S$11,0)-1,-1)&" -- "&TEXT(B61,"00%") -> 7.5-16t LNG truck -- 00% | V61: Bvkm | W61: million vehicles
B62: Reference values for LPG truck 7.5-16t | J62: =IFERROR(VLOOKUP(C62,$R$1:$S$7,2,FALSE),J61) -> Trd_hdt_lng | K62: =IFERROR(IF(VALUE(C62)>2020,J62&"_"&TEXT(B62*100,"00"),"\I:"),"\I:") -> \I: | L62: =LEFT(K62,7) -> \I: | M62: =IF($K62="\I:","",C62) | N62: =IF($K62="\I:","",D62) | O62: =IF($K62="\I:","",E62) | P62: =IF($K62="\I:","",F62) | T62: =K62 -> \I: | U62: =OFFSET($S$1,MATCH(J62,$S$1:$S$11,0)-1,-1)&" -- "&TEXT(B62,"00%") -> 7.5-16t LNG truck -- Reference values for LPG truck 7.5-16t | V62: Bvkm | W62: million vehicles
B63: 2015 | J63: =IFERROR(VLOOKUP(C63,$R$1:$S$7,2,FALSE),J62) -> Trd_hdt_lng | K63: =IFERROR(IF(VALUE(C63)>2020,J63&"_"&TEXT(B63*100,"00"),"\I:"),"\I:") -> \I: | L63: =LEFT(K63,7) -> \I: | M63: =IF($K63="\I:","",C63) | N63: =IF($K63="\I:","",D63) | O63: =IF($K63="\I:","",E63) | P63: =IF($K63="\I:","",F63) | T63: =K63 -> \I: | U63: =OFFSET($S$1,MATCH(J63,$S$1:$S$11,0)-1,-1)&" -- "&TEXT(B63,"00%") -> 7.5-16t LNG truck -- 201500% | V63: Bvkm | W63: million vehicles
B64: Energy consumption | C64: lt/100 km | D64: 23.03667 | G64: =D64*$I$6/100*10^9/10^6 -> 5.8950838 | I64: =1/G64 -> 0.16963287 | J64: =IFERROR(VLOOKUP(C64,$R$1:$S$7,2,FALSE),J63) -> Trd_hdt_lng | K64: =IFERROR(IF(VALUE(C64)>2020,J64&"_"&TEXT(B64*100,"00"),"\I:"),"\I:") -> \I: | L64: =LEFT(K64,7) -> \I: | M64: =IF($K64="\I:","",C64) | N64: =IF($K64="\I:","",D64) | O64: =IF($K64="\I:","",E64) | P64: =IF($K64="\I:","",F64) | T64: =K64 -> \I: | U64: =OFFSET($S$1,MATCH(J64,$S$1:$S$11,0)-1,-1)&" -- "&TEXT(B64,"00%") -> 7.5-16t LNG truck -- Energy consumption | V64: Bvkm | W64: million vehicles
B65: Capital cost | C65: Euro15 /veh | D65: 87115.908 | I65: bvkm/PJ | J65: =IFERROR(VLOOKUP(C65,$R$1:$S$7,2,FALSE),J64) -> Trd_hdt_lng | K65: =IFERROR(IF(VALUE(C65)>2020,J65&"_"&TEXT(B65*100,"00"),"\I:"),"\I:") -> \I: | L65: =LEFT(K65,7) -> \I: | M65: =IF($K65="\I:","",C65) | N65: =IF($K65="\I:","",D65) | O65: =IF($K65="\I:","",E65) | P65: =IF($K65="\I:","",F65) | T65: =K65 -> \I: | U65: =OFFSET($S$1,MATCH(J65,$S$1:$S$11,0)-1,-1)&" -- "&TEXT(B65,"00%") -> 7.5-16t LNG truck -- Capital cost | V65: Bvkm | W65: million vehicles
J66: =IFERROR(VLOOKUP(C66,$R$1:$S$7,2,FALSE),J65) -> Trd_hdt_lng | K66: =IFERROR(IF(VALUE(C66)>2020,J66&"_"&TEXT(B66*100,"00"),"\I:"),"\I:") -> \I: | L66: =LEFT(K66,7) -> \I: | M66: =IF($K66="\I:","",C66) | N66: =IF($K66="\I:","",D66) | O66: =IF($K66="\I:","",E66) | P66: =IF($K66="\I:","",F66) | T66: =K66 -> \I: | U66: =OFFSET($S$1,MATCH(J66,$S$1:$S$11,0)-1,-1)&" -- "&TEXT(B66,"00%") -> 7.5-16t LNG truck -- 00% | V66: Bvkm | W66: million vehicles
B67: Reduction of specific energy consumption relative to 2015 LPG vehicle(%) | C67: 7.5-16t LPG truck | J67: =IFERROR(VLOOKUP(C67,$R$1:$S$7,2,FALSE),J66) -> \I:Trd_hdt_lpg | K67: =IFERROR(IF(VALUE(C67)>2020,J67&"_"&TEXT(B67*100,"00"),"\I:"),"\I:") -> \I: | L67: =LEFT(K67,7) -> \I: | M67: =IF($K67="\I:","",C67) | N67: =IF($K67="\I:","",D67) | O67: =IF($K67="\I:","",E67) | P67: =IF($K67="\I:","",F67) | T67: =K67 -> \I: | U67: =OFFSET($S$1,MATCH(J67,$S$1:$S$11,0)-1,-1)&" -- "&TEXT(B67,"00%") -> 7.5-16t LPG truck -- Reduction of specific energy consumption relative to 2015 LPG vehicle(%) | V67: Bvkm | W67: million vehicles
J68: =IFERROR(VLOOKUP(C68,$R$1:$S$7,2,FALSE),J67) -> \I:Trd_hdt_lpg | K68: =IFERROR(IF(VALUE(C68)>2020,J68&"_"&TEXT(B68*100,"00"),"\I:"),"\I:") -> \I: | L68: =LEFT(K68,7) -> \I: | M68: =IF($K68="\I:","",C68) | N68: =IF($K68="\I:","",D68) | O68: =IF($K68="\I:","",E68) | P68: =IF($K68="\I:","",F68) | T68: =K68 -> \I: | U68: =OFFSET($S$1,MATCH(J68,$S$1:$S$11,0)-1,-1)&" -- "&TEXT(B68,"00%") -> 7.5-16t LPG truck -- 00% | V68: Bvkm | W68: million vehicles
J69: =IFERROR(VLOOKUP(C69,$R$1:$S$7,2,FALSE),J68) -> \I:Trd_hdt_lpg | K69: =IFERROR(IF(VALUE(C69)>2020,J69&"_"&TEXT(B69*100,"00"),"\I:"),"\I:") -> \I: | L69: =LEFT(K69,7) -> \I: | M69: =IF($K69="\I:","",C69) | N69: =IF($K69="\I:","",D69) | O69: =IF($K69="\I:","",E69) | P69: =IF($K69="\I:","",F69) | T69: =K69 -> \I: | U69: =OFFSET($S$1,MATCH(J69,$S$1:$S$11,0)-1,-1)&" -- "&TEXT(B69,"00%") -> 7.5-16t LPG truck -- 00% | V69: Bvkm | W69: million vehicles
C70: 2020 | D70: 2030 | E70: 2040 | F70: 2050 | J70: =IFERROR(VLOOKUP(C70,$R$1:$S$7,2,FALSE),J69) -> \I:Trd_hdt_lpg | K70: =IFERROR(IF(VALUE(C70)>2020,J70&"_"&TEXT(B70*100,"00"),"\I:"),"\I:") -> \I: | L70: =LEFT(K70,7) -> \I: | M70: =IF($K70="\I:","",C70) | N70: =IF($K70="\I:","",D70) | O70: =IF($K70="\I:","",E70) | P70: =IF($K70="\I:","",F70) | T70: =K70 -> \I: | U70: =OFFSET($S$1,MATCH(J70,$S$1:$S$11,0)-1,-1)&" -- "&TEXT(B70,"00%") -> 7.5-16t LPG truck -- 00% | V70: Bvkm | W70: million vehicles
B71: 0.044125814 | C71: 87998.594 | D71: 87998.594 | E71: 87998.594 | F71: 87998.594 | I71: =$I$64*(1+B71)/$I$7 -> 1.2708852 | J71: =IFERROR(VLOOKUP(C71,$R$1:$S$7,2,FALSE),J70) -> \I:Trd_hdt_lpg | K71: =IFERROR(IF(VALUE(C71)>2020,J71&"_"&TEXT(B71*100,"00"),"\I:"),"\I:") -> \I:Trd_hdt_lpg_04 | L71: =LEFT(K71,7) -> \I:Trd_ | M71: =IF($K71="\I:","",C71) -> 87998.594 | N71: =IF($K71="\I:","",D71) -> 87998.594 | O71: =IF($K71="\I:","",E71) -> 87998.594 | P71: =IF($K71="\I:","",F71) -> 87998.594 | T71: =K71 -> \I:Trd_hdt_lpg_04 | U71: =OFFSET($S$1,MATCH(J71,$S$1:$S$11,0)-1,-1)&" -- "&TEXT(B71,"00%") -> 7.5-16t LPG truck -- 04% | V71: Bvkm | W71: million vehicles
B72: 0.094125814 | C72: 89431.026 | D72: 88944.078 | E72: 88944.078 | F72: 88944.078 | I72: =$I$64*(1+B72)/$I$7 -> 1.331744 | J72: =IFERROR(VLOOKUP(C72,$R$1:$S$7,2,FALSE),J71) -> \I:Trd_hdt_lpg | K72: =IFERROR(IF(VALUE(C72)>2020,J72&"_"&TEXT(B72*100,"00"),"\I:"),"\I:") -> \I:Trd_hdt_lpg_09 | L72: =LEFT(K72,7) -> \I:Trd_ | M72: =IF($K72="\I:","",C72) -> 89431.026 | N72: =IF($K72="\I:","",D72) -> 88944.078 | O72: =IF($K72="\I:","",E72) -> 88944.078 | P72: =IF($K72="\I:","",F72) -> 88944.078 | T72: =K72 -> \I:Trd_hdt_lpg_09 | U72: =OFFSET($S$1,MATCH(J72,$S$1:$S$11,0)-1,-1)&" -- "&TEXT(B72,"00%") -> 7.5-16t LPG truck -- 09% | V72: Bvkm | W72: million vehicles
B73: 0.14412581 | C73: 90730.003 | D73: 90336.447 | E73: 90336.447 | F73: 90336.447 | I73: =$I$64*(1+B73)/$I$7 -> 1.3926028 | J73: =IFERROR(VLOOKUP(C73,$R$1:$S$7,2,FALSE),J72) -> \I:Trd_hdt_lpg | K73: =IFERROR(IF(VALUE(C73)>2020,J73&"_"&TEXT(B73*100,"00"),"\I:"),"\I:") -> \I:Trd_hdt_lpg_14 | L73: =LEFT(K73,7) -> \I:Trd_ | M73: =IF($K73="\I:","",C73) -> 90730.003 | N73: =IF($K73="\I:","",D73) -> 90336.447 | O73: =IF($K73="\I:","",E73) -> 90336.447 | P73: =IF($K73="\I:","",F73) -> 90336.447 | T73: =K73 -> \I:Trd_hdt_lpg_14 | U73: =OFFSET($S$1,MATCH(J73,$S$1:$S$11,0)-1,-1)&" -- "&TEXT(B73,"00%") -> 7.5-16t LPG truck -- 14% | V73: Bvkm | W73: million vehicles
B74: 0.19412581 | C74: 96261.87 | D74: 92386.921 | E74: 92386.921 | F74: 92386.921 | I74: =$I$64*(1+B74)/$I$7 -> 1.4534616 | J74: =IFERROR(VLOOKUP(C74,$R$1:$S$7,2,FALSE),J73) -> \I:Trd_hdt_lpg | K74: =IFERROR(IF(VALUE(C74)>2020,J74&"_"&TEXT(B74*100,"00"),"\I:"),"\I:") -> \I:Trd_hdt_lpg_19 | L74: =LEFT(K74,7) -> \I:Trd_ | M74: =IF($K74="\I:","",C74) -> 96261.87 | N74: =IF($K74="\I:","",D74) -> 92386.921 | O74: =IF($K74="\I:","",E74) -> 92386.921 | P74: =IF($K74="\I:","",F74) -> 92386.921 | T74: =K74 -> \I:Trd_hdt_lpg_19 | U74: =OFFSET($S$1,MATCH(J74,$S$1:$S$11,0)-1,-1)&" -- "&TEXT(B74,"00%") -> 7.5-16t LPG truck -- 19% | V74: Bvkm | W74: million vehicles
B75: 0.24412581 | C75: 100569.96 | D75: 95406.556 | E75: 95406.556 | F75: 95406.556 | I75: =$I$64*(1+B75)/$I$7 -> 1.5143204 | J75: =IFERROR(VLOOKUP(C75,$R$1:$S$7,2,FALSE),J74) -> \I:Trd_hdt_lpg | K75: =IFERROR(IF(VALUE(C75)>2020,J75&"_"&TEXT(B75*100,"00"),"\I:"),"\I:") -> \I:Trd_hdt_lpg_24 | L75: =LEFT(K75,7) -> \I:Trd_ | M75: =IF($K75="\I:","",C75) -> 100569.96 | N75: =IF($K75="\I:","",D75) -> 95406.556 | O75: =IF($K75="\I:","",E75) -> 95406.556 | P75: =IF($K75="\I:","",F75) -> 95406.556 | T75: =K75 -> \I:Trd_hdt_lpg_24 | U75: =OFFSET($S$1,MATCH(J75,$S$1:$S$11,0)-1,-1)&" -- "&TEXT(B75,"00%") -> 7.5-16t LPG truck -- 24% | V75: Bvkm | W75: million vehicles
B76: 0.26412581 | C76: 123471.09 | D76: 99967.45 | E76: 99853.425 | F76: 99853.425 | I76: =$I$64*(1+B76)/$I$7 -> 1.538664 | J76: =IFERROR(VLOOKUP(C76,$R$1:$S$7,2,FALSE),J75) -> \I:Trd_hdt_lpg | K76: =IFERROR(IF(VALUE(C76)>2020,J76&"_"&TEXT(B76*100,"00"),"\I:"),"\I:") -> \I:Trd_hdt_lpg_26 | L76: =LEFT(K76,7) -> \I:Trd_ | M76: =IF($K76="\I:","",C76) -> 123471.09 | N76: =IF($K76="\I:","",D76) -> 99967.45 | O76: =IF($K76="\I:","",E76) -> 99853.425 | P76: =IF($K76="\I:","",F76) -> 99853.425 | T76: =K76 -> \I:Trd_hdt_lpg_26 | U76: =OFFSET($S$1,MATCH(J76,$S$1:$S$11,0)-1,-1)&" -- "&TEXT(B76,"00%") -> 7.5-16t LPG truck -- 26% | V76: Bvkm | W76: million vehicles
B77: 0.29412581 | C77: 197846.07 | D77: 113908.29 | E77: 106402.12 | F77: 106402.12 | I77: =$I$64*(1+B77)/$I$7 -> 1.5751792 | J77: =IFERROR(VLOOKUP(C77,$R$1:$S$7,2,FALSE),J76) -> \I:Trd_hdt_lpg | K77: =IFERROR(IF(VALUE(C77)>2020,J77&"_"&TEXT(B77*100,"00"),"\I:"),"\I:") -> \I:Trd_hdt_lpg_29 | L77: =LEFT(K77,7) -> \I:Trd_ | M77: =IF($K77="\I:","",C77) -> 197846.07 | N77: =IF($K77="\I:","",D77) -> 113908.29 | O77: =IF($K77="\I:","",E77) -> 106402.12 | P77: =IF($K77="\I:","",F77) -> 106402.12 | T77: =K77 -> \I:Trd_hdt_lpg_29 | U77: =OFFSET($S$1,MATCH(J77,$S$1:$S$11,0)-1,-1)&" -- "&TEXT(B77,"00%") -> 7.5-16t LPG truck -- 29% | V77: Bvkm | W77: million vehicles
J78: =IFERROR(VLOOKUP(C78,$R$1:$S$7,2,FALSE),J77) -> \I:Trd_hdt_lpg | K78: =IFERROR(IF(VALUE(C78)>2020,J78&"_"&TEXT(B78*100,"00"),"\I:"),"\I:") -> \I: | L78: =LEFT(K78,7) -> \I: | M78: =IF($K78="\I:","",C78) | N78: =IF($K78="\I:","",D78) | O78: =IF($K78="\I:","",E78) | P78: =IF($K78="\I:","",F78) | T78: =K78 -> \I: | U78: =OFFSET($S$1,MATCH(J78,$S$1:$S$11,0)-1,-1)&" -- "&TEXT(B78,"00%") -> 7.5-16t LPG truck -- 00% | V78: Bvkm | W78: million vehicles
J79: =IFERROR(VLOOKUP(C79,$R$1:$S$7,2,FALSE),J78) -> \I:Trd_hdt_lpg | K79: =IFERROR(IF(VALUE(C79)>2020,J79&"_"&TEXT(B79*100,"00"),"\I:"),"\I:") -> \I: | L79: =LEFT(K79,7) -> \I: | M79: =IF($K79="\I:","",C79) | N79: =IF($K79="\I:","",D79) | O79: =IF($K79="\I:","",E79) | P79: =IF($K79="\I:","",F79) | T79: =K79 -> \I: | U79: =OFFSET($S$1,MATCH(J79,$S$1:$S$11,0)-1,-1)&" -- "&TEXT(B79,"00%") -> 7.5-16t LPG truck -- 00% | V79: Bvkm | W79: million vehicles
J80: =IFERROR(VLOOKUP(C80,$R$1:$S$7,2,FALSE),J79) -> \I:Trd_hdt_lpg | K80: =IFERROR(IF(VALUE(C80)>2020,J80&"_"&TEXT(B80*100,"00"),"\I:"),"\I:") -> \I: | L80: =LEFT(K80,7) -> \I: | M80: =IF($K80="\I:","",C80) | N80: =IF($K80="\I:","",D80) | O80: =IF($K80="\I:","",E80) | P80: =IF($K80="\I:","",F80) | T80: =K80 -> \I: | U80: =OFFSET($S$1,MATCH(J80,$S$1:$S$11,0)-1,-1)&" -- "&TEXT(B80,"00%") -> 7.5-16t LPG truck -- 00% | V80: Bvkm | W80: million vehicles
B81: 2020 | J81: =IFERROR(VLOOKUP(C81,$R$1:$S$7,2,FALSE),J80) -> \I:Trd_hdt_lpg | K81: =IFERROR(IF(VALUE(C81)>2020,J81&"_"&TEXT(B81*100,"00"),"\I:"),"\I:") -> \I: | L81: =LEFT(K81,7) -> \I: | M81: =IF($K81="\I:","",C81) | N81: =IF($K81="\I:","",D81) | O81: =IF($K81="\I:","",E81) | P81: =IF($K81="\I:","",F81) | T81: =K81 -> \I: | U81: =OFFSET($S$1,MATCH(J81,$S$1:$S$11,0)-1,-1)&" -- "&TEXT(B81,"00%") -> 7.5-16t LPG truck -- 202000% | V81: Bvkm | W81: million vehicles
B82: Energy consumption of 7.5-16t battery electric truck | C82: kWh/km | D82: 0.74 | G82: =D82/3.6/100*10^9/10^6 -> 2.0555556 | I82: =1/G82-0.15 -> 0.33648649 | J82: =IFERROR(VLOOKUP(C82,$R$1:$S$7,2,FALSE),J81) -> \I:Trd_hdt_lpg | K82: =IFERROR(IF(VALUE(C82)>2020,J82&"_"&TEXT(B82*100,"00"),"\I:"),"\I:") -> \I: | L82: =LEFT(K82,7) -> \I: | M82: =IF($K82="\I:","",C82) | N82: =IF($K82="\I:","",D82) | O82: =IF($K82="\I:","",E82) | P82: =IF($K82="\I:","",F82) | T82: =K82 -> \I: | U82: =OFFSET($S$1,MATCH(J82,$S$1:$S$11,0)-1,-1)&" -- "&TEXT(B82,"00%") -> 7.5-16t LPG truck -- Energy consumption of 7.5-16t battery electric truck | V82: Bvkm | W82: million vehicles
I83: bvkm/PJ | J83: =IFERROR(VLOOKUP(C83,$R$1:$S$7,2,FALSE),J82) -> \I:Trd_hdt_lpg | K83: =IFERROR(IF(VALUE(C83)>2020,J83&"_"&TEXT(B83*100,"00"),"\I:"),"\I:") -> \I: | L83: =LEFT(K83,7) -> \I: | M83: =IF($K83="\I:","",C83) | N83: =IF($K83="\I:","",D83) | O83: =IF($K83="\I:","",E83) | P83: =IF($K83="\I:","",F83) | T83: =K83 -> \I: | U83: =OFFSET($S$1,MATCH(J83,$S$1:$S$11,0)-1,-1)&" -- "&TEXT(B83,"00%") -> 7.5-16t LPG truck -- 00% | V83: Bvkm | W83: million vehicles
J84: =IFERROR(VLOOKUP(C84,$R$1:$S$7,2,FALSE),J83) -> \I:Trd_hdt_lpg | K84: =IFERROR(IF(VALUE(C84)>2020,J84&"_"&TEXT(B84*100,"00"),"\I:"),"\I:") -> \I: | L84: =LEFT(K84,7) -> \I: | M84: =IF($K84="\I:","",C84) | N84: =IF($K84="\I:","",D84) | O84: =IF($K84="\I:","",E84) | P84: =IF($K84="\I:","",F84) | T84: =K84 -> \I: | U84: =OFFSET($S$1,MATCH(J84,$S$1:$S$11,0)-1,-1)&" -- "&TEXT(B84,"00%") -> 7.5-16t LPG truck -- 00% | V84: Bvkm | W84: million vehicles
B85: Electric range (km) | C85: 7.5-16t battery electric truck | J85: =IFERROR(VLOOKUP(C85,$R$1:$S$7,2,FALSE),J84) -> Trd_hdt_elc | K85: =IFERROR(IF(VALUE(C85)>2020,J85&"_"&TEXT(B85*100,"00"),"\I:"),"\I:") -> \I: | L85: =LEFT(K85,7) -> \I: | M85: =IF($K85="\I:","",C85) | N85: =IF($K85="\I:","",D85) | O85: =IF($K85="\I:","",E85) | P85: =IF($K85="\I:","",F85) | T85: =K85 -> \I: | U85: =OFFSET($S$1,MATCH(J85,$S$1:$S$11,0)-1,-1)&" -- "&TEXT(B85,"00%") -> 7.5-16t battery electric truck -- Electric range (km) | V85: Bvkm | W85: million vehicles
J86: =IFERROR(VLOOKUP(C86,$R$1:$S$7,2,FALSE),J85) -> Trd_hdt_elc | K86: =IFERROR(IF(VALUE(C86)>2020,J86&"_"&TEXT(B86*100,"00"),"\I:"),"\I:") -> \I: | L86: =LEFT(K86,7) -> \I: | M86: =IF($K86="\I:","",C86) | N86: =IF($K86="\I:","",D86) | O86: =IF($K86="\I:","",E86) | P86: =IF($K86="\I:","",F86) | T86: =K86 -> \I: | U86: =OFFSET($S$1,MATCH(J86,$S$1:$S$11,0)-1,-1)&" -- "&TEXT(B86,"00%") -> 7.5-16t battery electric truck -- 00% | V86: Bvkm | W86: million vehicles
J87: =IFERROR(VLOOKUP(C87,$R$1:$S$7,2,FALSE),J86) -> Trd_hdt_elc | K87: =IFERROR(IF(VALUE(C87)>2020,J87&"_"&TEXT(B87*100,"00"),"\I:"),"\I:") -> \I: | L87: =LEFT(K87,7) -> \I: | M87: =IF($K87="\I:","",C87) | N87: =IF($K87="\I:","",D87) | O87: =IF($K87="\I:","",E87) | P87: =IF($K87="\I:","",F87) | T87: =K87 -> \I: | U87: =OFFSET($S$1,MATCH(J87,$S$1:$S$11,0)-1,-1)&" -- "&TEXT(B87,"00%") -> 7.5-16t battery electric truck -- 00% | V87: Bvkm | W87: million vehicles
C88: 2020 | D88: 2030 | E88: 2040 | F88: 2050 | J88: =IFERROR(VLOOKUP(C88,$R$1:$S$7,2,FALSE),J87) -> Trd_hdt_elc | K88: =IFERROR(IF(VALUE(C88)>2020,J88&"_"&TEXT(B88*100,"00"),"\I:"),"\I:") -> \I: | L88: =LEFT(K88,7) -> \I: | M88: =IF($K88="\I:","",C88) | N88: =IF($K88="\I:","",D88) | O88: =IF($K88="\I:","",E88) | P88: =IF($K88="\I:","",F88) | T88: =K88 -> \I: | U88: =OFFSET($S$1,MATCH(J88,$S$1:$S$11,0)-1,-1)&" -- "&TEXT(B88,"00%") -> 7.5-16t battery electric truck -- 00% | V88: Bvkm | W88: million vehicles
B89: 150 | C89: 144373.91 | D89: 95780.73 | E89: 90629.907 | F89: 88752.516 | I89: =$I$82/$I$7 -> 2.4144104 | J89: =IFERROR(VLOOKUP(C89,$R$1:$S$7,2,FALSE),J88) -> Trd_hdt_elc | K89: =IFERROR(IF(VALUE(C89)>2020,J89&"_"&TEXT(B89,"00"),"\I:"),"\I:") -> Trd_hdt_elc_150 | L89: =LEFT(K89,7) -> Trd_hdt | M89: =IF($K89="\I:","",C89) -> 144373.91 | N89: =IF($K89="\I:","",D89) -> 95780.73 | O89: =IF($K89="\I:","",E89) -> 90629.907 | P89: =IF($K89="\I:","",F89) -> 88752.516 | Q89: 0.01 | T89: =K89 -> Trd_hdt_elc_150 | U89: =OFFSET($S$1,MATCH(J89,$S$1:$S$11,0)-1,-1)&" -- "&TEXT(B89,"000") -> 7.5-16t battery electric truck -- 150 | V89: Bvkm | W89: million vehicles
B90: 178.57143 | C90: 147802.36 | D90: 97793.499 | E90: 92046.749 | F90: 89776.923 | I90: =$I$82/$I$7 -> 2.4144104 | J90: =IFERROR(VLOOKUP(C90,$R$1:$S$7,2,FALSE),J89) -> Trd_hdt_elc | K90: =IFERROR(IF(VALUE(C90)>2020,J90&"_"&TEXT(B90,"00"),"\I:"),"\I:") -> Trd_hdt_elc_179 | L90: =LEFT(K90,7) -> Trd_hdt | M90: =IF($K90="\I:","",C90) -> 147802.36 | N90: =IF($K90="\I:","",D90) -> 97793.499 | O90: =IF($K90="\I:","",E90) -> 92046.749 | P90: =IF($K90="\I:","",F90) -> 89776.923 | Q90: 0.01 | T90: =K90 -> Trd_hdt_elc_179 | U90: =OFFSET($S$1,MATCH(J90,$S$1:$S$11,0)-1,-1)&" -- "&TEXT(B90,"000") -> 7.5-16t battery electric truck -- 179 | V90: Bvkm | W90: million vehicles
B91: 207.14286 | C91: 149288.81 | D91: 100585.83 | E91: 93658.439 | F91: 90964.285 | I91: =$I$82/$I$7 -> 2.4144104 | J91: =IFERROR(VLOOKUP(C91,$R$1:$S$7,2,FALSE),J90) -> Trd_hdt_elc | K91: =IFERROR(IF(VALUE(C91)>2020,J91&"_"&TEXT(B91,"00"),"\I:"),"\I:") -> Trd_hdt_elc_207 | L91: =LEFT(K91,7) -> Trd_hdt | M91: =IF($K91="\I:","",C91) -> 149288.81 | N91: =IF($K91="\I:","",D91) -> 100585.83 | O91: =IF($K91="\I:","",E91) -> 93658.439 | P91: =IF($K91="\I:","",F91) -> 90964.285 | Q91: 0.01 | T91: =K91 -> Trd_hdt_elc_207 | U91: =OFFSET($S$1,MATCH(J91,$S$1:$S$11,0)-1,-1)&" -- "&TEXT(B91,"000") -> 7.5-16t battery electric truck -- 207 | V91: Bvkm | W91: million vehicles
B92: 235.71429 | C92: 152494.11 | D92: 102554.34 | E92: 94660.014 | F92: 92014.52 | I92: =$I$82/$I$7 -> 2.4144104 | J92: =IFERROR(VLOOKUP(C92,$R$1:$S$7,2,FALSE),J91) -> Trd_hdt_elc | K92: =IFERROR(IF(VALUE(C92)>2020,J92&"_"&TEXT(B92,"00"),"\I:"),"\I:") -> Trd_hdt_elc_236 | L92: =LEFT(K92,7) -> Trd_hdt | M92: =IF($K92="\I:","",C92) -> 152494.11 | N92: =IF($K92="\I:","",D92) -> 102554.34 | O92: =IF($K92="\I:","",E92) -> 94660.014 | P92: =IF($K92="\I:","",F92) -> 92014.52 | Q92: 0.01 | T92: =K92 -> Trd_hdt_elc_236 | U92: =OFFSET($S$1,MATCH(J92,$S$1:$S$11,0)-1,-1)&" -- "&TEXT(B92,"000") -> 7.5-16t battery electric truck -- 236 | V92: Bvkm | W92: million vehicles
B93: 264.28571 | C93: 155632.35 | D93: 104580.23 | E93: 95569.823 | F93: 92930.905 | I93: =$I$82/$I$7 -> 2.4144104 | J93: =IFERROR(VLOOKUP(C93,$R$1:$S$7,2,FALSE),J92) -> Trd_hdt_elc | K93: =IFERROR(IF(VALUE(C93)>2020,J93&"_"&TEXT(B93,"00"),"\I:"),"\I:") -> Trd_hdt_elc_264 | L93: =LEFT(K93,7) -> Trd_hdt | M93: =IF($K93="\I:","",C93) -> 155632.35 | N93: =IF($K93="\I:","",D93) -> 104580.23 | O93: =IF($K93="\I:","",E93) -> 95569.823 | P93: =IF($K93="\I:","",F93) -> 92930.905 | Q93: 0.05 | T93: =K93 -> Trd_hdt_elc_264 | U93: =OFFSET($S$1,MATCH(J93,$S$1:$S$11,0)-1,-1)&" -- "&TEXT(B93,"000") -> 7.5-16t battery electric truck -- 264 | V93: Bvkm | W93: million vehicles
B94: 350 | C94: 159704.77 | D94: 107786.21 | E94: 98254.348 | F94: 95331.832 | I94: =$I$82/$I$7 -> 2.4144104 | J94: =IFERROR(VLOOKUP(C94,$R$1:$S$7,2,FALSE),J93) -> Trd_hdt_elc | K94: =IFERROR(IF(VALUE(C94)>2020,J94&"_"&TEXT(B94,"00"),"\I:"),"\I:") -> Trd_hdt_elc_350 | L94: =LEFT(K94,7) -> Trd_hdt | M94: =IF($K94="\I:","",C94) -> 159704.77 | N94: =IF($K94="\I:","",D94) -> 107786.21 | O94: =IF($K94="\I:","",E94) -> 98254.348 | P94: =IF($K94="\I:","",F94) -> 95331.832 | Q94: 0.1 | T94: =K94 -> Trd_hdt_elc_350 | U94: =OFFSET($S$1,MATCH(J94,$S$1:$S$11,0)-1,-1)&" -- "&TEXT(B94,"000") -> 7.5-16t battery electric truck -- 350 | V94: Bvkm | W94: million vehicles
B95: 500 | C95: 179612.76 | D95: 119565.16 | E95: 104086.94 | F95: 100030.34 | I95: =$I$82/$I$7 -> 2.4144104 | J95: =IFERROR(VLOOKUP(C95,$R$1:$S$7,2,FALSE),J94) -> Trd_hdt_elc | K95: =IFERROR(IF(VALUE(C95)>2020,J95&"_"&TEXT(B95,"00"),"\I:"),"\I:") -> Trd_hdt_elc_500 | L95: =LEFT(K95,7) -> Trd_hdt | M95: =IF($K95="\I:","",C95) -> 179612.76 | N95: =IF($K95="\I:","",D95) -> 119565.16 | O95: =IF($K95="\I:","",E95) -> 104086.94 | P95: =IF($K95="\I:","",F95) -> 100030.34 | Q95: 0.2 | T95: =K95 -> Trd_hdt_elc_500 | U95: =OFFSET($S$1,MATCH(J95,$S$1:$S$11,0)-1,-1)&" -- "&TEXT(B95,"000") -> 7.5-16t battery electric truck -- 500 | V95: Bvkm | W95: million vehicles
B96: 600 | C96: 193069.5 | D96: 125556.82 | E96: 111128.24 | F96: 104587.12 | I96: =$I$82/$I$7 -> 2.4144104 | J96: =IFERROR(VLOOKUP(C96,$R$1:$S$7,2,FALSE),J95) -> Trd_hdt_elc | K96: =IFERROR(IF(VALUE(C96)>2020,J96&"_"&TEXT(B96,"00"),"\I:"),"\I:") -> Trd_hdt_elc_600 | L96: =LEFT(K96,7) -> Trd_hdt | M96: =IF($K96="\I:","",C96) -> 193069.5 | N96: =IF($K96="\I:","",D96) -> 125556.82 | O96: =IF($K96="\I:","",E96) -> 111128.24 | P96: =IF($K96="\I:","",F96) -> 104587.12 | T96: =K96 -> Trd_hdt_elc_600 | U96: =OFFSET($S$1,MATCH(J96,$S$1:$S$11,0)-1,-1)&" -- "&TEXT(B96,"000") -> 7.5-16t battery electric truck -- 600 | V96: Bvkm | W96: million vehicles
J97: =IFERROR(VLOOKUP(C97,$R$1:$S$7,2,FALSE),J96) -> Trd_hdt_elc | K97: =IFERROR(IF(VALUE(C97)>2020,J97&"_"&TEXT(B97*100,"00"),"\I:"),"\I:") -> \I: | L97: =LEFT(K97,7) -> \I: | M97: =IF($K97="\I:","",C97) | N97: =IF($K97="\I:","",D97) | O97: =IF($K97="\I:","",E97) | P97: =IF($K97="\I:","",F97) | T97: =K97 -> \I: | U97: =OFFSET($S$1,MATCH(J97,$S$1:$S$11,0)-1,-1)&" -- "&TEXT(B97,"00%") -> 7.5-16t battery electric truck -- 00% | V97: Bvkm | W97: million vehicles
J98: =IFERROR(VLOOKUP(C98,$R$1:$S$7,2,FALSE),J97) -> Trd_hdt_elc | K98: =IFERROR(IF(VALUE(C98)>2020,J98&"_"&TEXT(B98*100,"00"),"\I:"),"\I:") -> \I: | L98: =LEFT(K98,7) -> \I: | M98: =IF($K98="\I:","",C98) | N98: =IF($K98="\I:","",D98) | O98: =IF($K98="\I:","",E98) | P98: =IF($K98="\I:","",F98) | T98: =K98 -> \I: | U98: =OFFSET($S$1,MATCH(J98,$S$1:$S$11,0)-1,-1)&" -- "&TEXT(B98,"00%") -> 7.5-16t battery electric truck -- 00% | V98: Bvkm | W98: million vehicles
J99: =IFERROR(VLOOKUP(C99,$R$1:$S$7,2,FALSE),J98) -> Trd_hdt_elc | K99: =IFERROR(IF(VALUE(C99)>2020,J99&"_"&TEXT(B99*100,"00"),"\I:"),"\I:") -> \I: | L99: =LEFT(K99,7) -> \I: | M99: =IF($K99="\I:","",C99) | N99: =IF($K99="\I:","",D99) | O99: =IF($K99="\I:","",E99) | P99: =IF($K99="\I:","",F99) | T99: =K99 -> \I: | U99: =OFFSET($S$1,MATCH(J99,$S$1:$S$11,0)-1,-1)&" -- "&TEXT(B99,"00%") -> 7.5-16t battery electric truck -- 00% | V99: Bvkm | W99: million vehicles
B100: Energy consumption (kg H2/100km) | C100: 7.5-16t Hydrogen fuel cell truck | J100: =IFERROR(VLOOKUP(C100,$R$1:$S$7,2,FALSE),J99) -> Trd_hdt_hh2 | K100: =IFERROR(IF(VALUE(C100)>2020,J100&"_"&TEXT(B100*100,"00"),"\I:"),"\I:") -> \I: | L100: =LEFT(K100,7) -> \I: | M100: =IF($K100="\I:","",C100) | N100: =IF($K100="\I:","",D100) | O100: =IF($K100="\I:","",E100) | P100: =IF($K100="\I:","",F100) | T100: =K100 -> \I: | U100: =OFFSET($S$1,MATCH(J100,$S$1:$S$11,0)-1,-1)&" -- "&TEXT(B100,"00%") -> 7.5-16t Hydrogen fuel cell truck -- Energy consumption (kg H2/100km) | V100: Bvkm | W100: million vehicles
J101: =IFERROR(VLOOKUP(C101,$R$1:$S$7,2,FALSE),J100) -> Trd_hdt_hh2 | K101: =IFERROR(IF(VALUE(C101)>2020,J101&"_"&TEXT(B101*100,"00"),"\I:"),"\I:") -> \I: | L101: =LEFT(K101,7) -> \I: | M101: =IF($K101="\I:","",C101) | N101: =IF($K101="\I:","",D101) | O101: =IF($K101="\I:","",E101) | P101: =IF($K101="\I:","",F101) | T101: =K101 -> \I: | U101: =OFFSET($S$1,MATCH(J101,$S$1:$S$11,0)-1,-1)&" -- "&TEXT(B101,"00%") -> 7.5-16t Hydrogen fuel cell truck -- 00% | V101: Bvkm | W101: million vehicles
...

Sheet 2-3wheelers
B1: Modelled economic possibilities for reducing specific energy consumption by transport mode/equipment and fuel/technology over time | Q1: gsl150 | R1: 4-stroke MC 50-250 cc motorcycle | S1: ="Trd_2w_"&Q1 -> Trd_2w_gsl150
B2: © E3-Modelling | Q2: gsl500 | R2: 4-stroke MC 250-750 cc motorcycle | S2: ="Trd_2w_"&Q2 -> Trd_2w_gsl500
Q3: gsl | R3: 4-stroke MC >750 cc motorcycle | S3: ="Trd_3w_"&Q3 -> Trd_3w_gsl
I4: =31536000/10^9 -> 0.031536 | J4: GJ/lt Gasoline | Q4: gsl50 | R4: Moped | S4: ="Trd_2w_"&Q4 -> Trd_2w_gsl50
B5: Reference values for 4-stroke MC 50-250 cc motorcycle | Q5: elc150 | R5: Battery electric motorcycle (equivalent to 50-250 cc motorcycle) | S5: ="Trd_2w_"&Q5 -> Trd_2w_elc150
B6: 2015 | Q6: elc500 | R6: Battery electric motorcycle (equivalent to 250-750 cc motorcycle) | S6: ="Trd_2w_"&Q6 -> Trd_2w_elc500
B7: Energy consumption | C7: lt/100 km | D7: 3.2040038 | G7: =D7*$I$4/100*10^9/10^6 -> 1.0104147 | I7: =1/G7 -> 0.98969269 | Q7: elc | R7: Battery electric motorcycle (equivalent to >750 cc motorcycle) | S7: ="Trd_3w_"&Q7 -> Trd_3w_elc
B8: Capital cost | C8: Euro15 /veh | D8: 2532.9673 | I8: bvkm/PJ | Q8: elc50 | R8: Battery electric moped | S8: ="Trd_2w_"&Q8 -> Trd_2w_elc50
K10: ~FI_T: UP~EUR15~INVCOST | S10: ~FI_Process
I11: EFF | J11: *process | K11: Process | L11: Comm-OUT | M11: =C15 -> 2020 | N11: =D15 -> 2030 | O11: =E15 -> 2040 | P11: =F15 -> 2050 | Q11: FLO_MARK | S11: Sets | T11: TechName | U11: TechDesc | V11: Tact | W11: Tcap
B12: Reduction of specific energy consumption relative to 2015 (%) | C12: 4-stroke MC 50-250 cc motorcycle | J12: =IFERROR(VLOOKUP(C12,$R$1:$S$8,2,FALSE),J11) -> Trd_2w_gsl150 | K12: =IFERROR(IF(VALUE(C12)>2020,J12&"_"&TEXT(B12*100,"00"),"\I:"),"\I:") -> \I: | L12: =LEFT(K12,6) -> \I: | M12: =IF($K12="\I:","",C12) | N12: =IF($K12="\I:","",D12) | O12: =IF($K12="\I:","",E12) | P12: =IF($K12="\I:","",F12) | S12: DMD | T12: =K12 -> \I: | U12: =OFFSET($S$1,MATCH(J12,$S$1:$S$11,0)-1,-1)&" -- "&TEXT(B12,"00%") -> 4-stroke MC 50-250 cc motorcycle -- Reduction of specific energy consumption relative to 2015 (%) | V12: Bvkm | W12: million vehicles
J13: =IFERROR(VLOOKUP(C13,$R$1:$S$8,2,FALSE),J12) -> Trd_2w_gsl150 | K13: =IFERROR(IF(VALUE(C13)>2020,J13&"_"&TEXT(B13*100,"00"),"\I:"),"\I:") -> \I: | L13: =LEFT(K13,6) -> \I: | M13: =IF($K13="\I:","",C13) | N13: =IF($K13="\I:","",D13) | O13: =IF($K13="\I:","",E13) | P13: =IF($K13="\I:","",F13) | S13: DMD | T13: =K13 -> \I: | U13: =OFFSET($S$1,MATCH(J13,$S$1:$S$11,0)-1,-1)&" -- "&TEXT(B13,"00%") -> 4-stroke MC 50-250 cc motorcycle -- 00% | V13: Bvkm | W13: million vehicles
J14: =IFERROR(VLOOKUP(C14,$R$1:$S$8,2,FALSE),J13) -> Trd_2w_gsl150 | K14: =IFERROR(IF(VALUE(C14)>2020,J14&"_"&TEXT(B14*100,"00"),"\I:"),"\I:") -> \I: | L14: =LEFT(K14,6) -> \I: | M14: =IF($K14="\I:","",C14) | N14: =IF($K14="\I:","",D14) | O14: =IF($K14="\I:","",E14) | P14: =IF($K14="\I:","",F14) | S14: DMD | T14: =K14 -> \I: | U14: =OFFSET($S$1,MATCH(J14,$S$1:$S$11,0)-1,-1)&" -- "&TEXT(B14,"00%") -> 4-stroke MC 50-250 cc motorcycle -- 00% | V14: Bvkm | W14: million vehicles
C15: 2020 | D15: 2030 | E15: 2040 | F15: 2050 | J15: =IFERROR(VLOOKUP(C15,$R$1:$S$8,2,FALSE),J14) -> Trd_2w_gsl150 | K15: =IFERROR(IF(VALUE(C15)>2020,J15&"_"&TEXT(B15*100,"00"),"\I:"),"\I:") -> \I: | L15: =LEFT(K15,6) -> \I: | M15: =IF($K15="\I:","",C15) | N15: =IF($K15="\I:","",D15) | O15: =IF($K15="\I:","",E15) | P15: =IF($K15="\I:","",F15) | S15: DMD | T15: =K15 -> \I: | U15: =OFFSET($S$1,MATCH(J15,$S$1:$S$11,0)-1,-1)&" -- "&TEXT(B15,"00%") -> 4-stroke MC 50-250 cc motorcycle -- 00% | V15: Bvkm | W15: million vehicles
B16: 0.015429671 | C16: 2548.4 | D16: 2548.4 | E16: 2548.4 | F16: 2548.4 | I16: =(1+B16) -> 1.0154297 | J16: =IFERROR(VLOOKUP(C16,$R$1:$S$8,2,FALSE),J15) -> Trd_2w_gsl150 | K16: =IFERROR(IF(VALUE(C16)>2020,J16&"_"&TEXT(B16*100,"00"),"\I:"),"\I:") -> Trd_2w_gsl150_02 | L16: =LEFT(K16,6) -> Trd_2w | M16: =IF($K16="\I:","",C16) -> 2548.4 | N16: =IF($K16="\I:","",D16) -> 2548.4 | O16: =IF($K16="\I:","",E16) -> 2548.4 | P16: =IF($K16="\I:","",F16) -> 2548.4 | S16: DMD | T16: =K16 -> Trd_2w_gsl150_02 | U16: =OFFSET($S$1,MATCH(J16,$S$1:$S$11,0)-1,-1)&" -- "&TEXT(B16,"00%") -> 4-stroke MC 50-250 cc motorcycle -- 02% | V16: Bvkm | W16: million vehicles
B17: 0.065429671 | C17: 2623.2091 | D17: 2598.4095 | E17: 2598.4095 | F17: 2598.4095 | I17: =(1+B17) -> 1.0654297 | J17: =IFERROR(VLOOKUP(C17,$R$1:$S$8,2,FALSE),J16) -> Trd_2w_gsl150 | K17: =IFERROR(IF(VALUE(C17)>2020,J17&"_"&TEXT(B17*100,"00"),"\I:"),"\I:") -> Trd_2w_gsl150_07 | L17: =LEFT(K17,6) -> Trd_2w | M17: =IF($K17="\I:","",C17) -> 2623.2091 | N17: =IF($K17="\I:","",D17) -> 2598.4095 | O17: =IF($K17="\I:","",E17) -> 2598.4095 | P17: =IF($K17="\I:","",F17) -> 2598.4095 | S17: DMD | T17: =K17 -> Trd_2w_gsl150_07 | U17: =OFFSET($S$1,MATCH(J17,$S$1:$S$11,0)-1,-1)&" -- "&TEXT(B17,"00%") -> 4-stroke MC 50-250 cc motorcycle -- 07% | V17: Bvkm | W17: million vehicles
B18: 0.11542967 | C18: 2666.5662 | D18: 2648.4191 | E18: 2648.4191 | F18: 2648.4191 | I18: =(1+B18) -> 1.1154297 | J18: =IFERROR(VLOOKUP(C18,$R$1:$S$8,2,FALSE),J17) -> Trd_2w_gsl150 | K18: =IFERROR(IF(VALUE(C18)>2020,J18&"_"&TEXT(B18*100,"00"),"\I:"),"\I:") -> Trd_2w_gsl150_12 | L18: =LEFT(K18,6) -> Trd_2w | M18: =IF($K18="\I:","",C18) -> 2666.5662 | N18: =IF($K18="\I:","",D18) -> 2648.4191 | O18: =IF($K18="\I:","",E18) -> 2648.4191 | P18: =IF($K18="\I:","",F18) -> 2648.4191 | S18: DMD | T18: =K18 -> Trd_2w_gsl150_12 | U18: =OFFSET($S$1,MATCH(J18,$S$1:$S$11,0)-1,-1)&" -- "&TEXT(B18,"00%") -> 4-stroke MC 50-250 cc motorcycle -- 12% | V18: Bvkm | W18: million vehicles
B19: 0.16542967 | C19: 2850.0904 | D19: 2698.4287 | E19: 2698.4287 | F19: 2698.4287 | I19: =(1+B19) -> 1.1654297 | J19: =IFERROR(VLOOKUP(C19,$R$1:$S$8,2,FALSE),J18) -> Trd_2w_gsl150 | K19: =IFERROR(IF(VALUE(C19)>2020,J19&"_"&TEXT(B19*100,"00"),"\I:"),"\I:") -> Trd_2w_gsl150_17 | L19: =LEFT(K19,6) -> Trd_2w | M19: =IF($K19="\I:","",C19) -> 2850.0904 | N19: =IF($K19="\I:","",D19) -> 2698.4287 | O19: =IF($K19="\I:","",E19) -> 2698.4287 | P19: =IF($K19="\I:","",F19) -> 2698.4287 | S19: DMD | T19: =K19 -> Trd_2w_gsl150_17 | U19: =OFFSET($S$1,MATCH(J19,$S$1:$S$11,0)-1,-1)&" -- "&TEXT(B19,"00%") -> 4-stroke MC 50-250 cc motorcycle -- 17% | V19: Bvkm | W19: million vehicles
B20: 0.21542967 | C20: 2913.1132 | D20: 2748.4382 | E20: 2748.4382 | F20: 2748.4382 | J20: =IFERROR(VLOOKUP(C20,$R$1:$S$8,2,FALSE),J19) -> Trd_2w_gsl150 | K20: =IFERROR(IF(VALUE(C20)>2020,J20&"_"&TEXT(B20*100,"00"),"\I:"),"\I:") -> Trd_2w_gsl150_22 | L20: =LEFT(K20,6) -> Trd_2w | M20: =IF($K20="\I:","",C20) -> 2913.1132 | N20: =IF($K20="\I:","",D20) -> 2748.4382 | O20: =IF($K20="\I:","",E20) -> 2748.4382 | P20: =IF($K20="\I:","",F20) -> 2748.4382 | S20: DMD | T20: =K20 -> Trd_2w_gsl150_22 | U20: =OFFSET($S$1,MATCH(J20,$S$1:$S$11,0)-1,-1)&" -- "&TEXT(B20,"00%") -> 4-stroke MC 50-250 cc motorcycle -- 22% | V20: Bvkm | W20: million vehicles
B21: 0.26542967 | C21: 3395.1737 | D21: 2801.3288 | E21: 2798.4478 | F21: 2798.4478 | J21: =IFERROR(VLOOKUP(C21,$R$1:$S$8,2,FALSE),J20) -> Trd_2w_gsl150 | K21: =IFERROR(IF(VALUE(C21)>2020,J21&"_"&TEXT(B21*100,"00"),"\I:"),"\I:") -> Trd_2w_gsl150_27 | L21: =LEFT(K21,6) -> Trd_2w | M21: =IF($K21="\I:","",C21) -> 3395.1737 | N21: =IF($K21="\I:","",D21) -> 2801.3288 | O21: =IF($K21="\I:","",E21) -> 2798.4478 | P21: =IF($K21="\I:","",F21) -> 2798.4478 | S21: DMD | T21: =K21 -> Trd_2w_gsl150_27 | U21: =OFFSET($S$1,MATCH(J21,$S$1:$S$11,0)-1,-1)&" -- "&TEXT(B21,"00%") -> 4-stroke MC 50-250 cc motorcycle -- 27% | V21: Bvkm | W21: million vehicles
B22: 0.31542967 | C22: 4641.4761 | D22: 2995.6373 | E22: 2848.4574 | F22: 2848.4574 | J22: =IFERROR(VLOOKUP(C22,$R$1:$S$8,2,FALSE),J21) -> Trd_2w_gsl150 | K22: =IFERROR(IF(VALUE(C22)>2020,J22&"_"&TEXT(B22*100,"00"),"\I:"),"\I:") -> Trd_2w_gsl150_32 | L22: =LEFT(K22,6) -> Trd_2w | M22: =IF($K22="\I:","",C22) -> 4641.4761 | N22: =IF($K22="\I:","",D22) -> 2995.6373 | O22: =IF($K22="\I:","",E22) -> 2848.4574 | P22: =IF($K22="\I:","",F22) -> 2848.4574 | S22: DMD | T22: =K22 -> Trd_2w_gsl150_32 | U22: =OFFSET($S$1,MATCH(J22,$S$1:$S$11,0)-1,-1)&" -- "&TEXT(B22,"00%") -> 4-stroke MC 50-250 cc motorcycle -- 32% | V22: Bvkm | W22: million vehicles
J23: =IFERROR(VLOOKUP(C23,$R$1:$S$8,2,FALSE),J22) -> Trd_2w_gsl150 | K23: =IFERROR(IF(VALUE(C23)>2020,J23&"_"&TEXT(B23*100,"00"),"\I:"),"\I:") -> \I: | L23: =LEFT(K23,6) -> \I: | M23: =IF($K23="\I:","",C23) | N23: =IF($K23="\I:","",D23) | O23: =IF($K23="\I:","",E23) | P23: =IF($K23="\I:","",F23) | S23: DMD | T23: =K23 -> \I: | U23: =OFFSET($S$1,MATCH(J23,$S$1:$S$11,0)-1,-1)&" -- "&TEXT(B23,"00%") -> 4-stroke MC 50-250 cc motorcycle -- 00% | V23: Bvkm | W23: million vehicles
J24: =IFERROR(VLOOKUP(C24,$R$1:$S$8,2,FALSE),J23) -> Trd_2w_gsl150 | K24: =IFERROR(IF(VALUE(C24)>2020,J24&"_"&TEXT(B24*100,"00"),"\I:"),"\I:") -> \I: | L24: =LEFT(K24,6) -> \I: | M24: =IF($K24="\I:","",C24) | N24: =IF($K24="\I:","",D24) | O24: =IF($K24="\I:","",E24) | P24: =IF($K24="\I:","",F24) | T24: =K24 -> \I: | U24: =OFFSET($S$1,MATCH(J24,$S$1:$S$11,0)-1,-1)&" -- "&TEXT(B24,"00%") -> 4-stroke MC 50-250 cc motorcycle -- 00% | V24: Bvkm | W24: million vehicles
J25: =IFERROR(VLOOKUP(C25,$R$1:$S$8,2,FALSE),J24) -> Trd_2w_gsl150 | K25: =IFERROR(IF(VALUE(C25)>2020,J25&"_"&TEXT(B25*100,"00"),"\I:"),"\I:") -> \I: | L25: =LEFT(K25,6) -> \I: | M25: =IF($K25="\I:","",C25) | N25: =IF($K25="\I:","",D25) | O25: =IF($K25="\I:","",E25) | P25: =IF($K25="\I:","",F25) | T25: =K25 -> \I: | U25: =OFFSET($S$1,MATCH(J25,$S$1:$S$11,0)-1,-1)&" -- "&TEXT(B25,"00%") -> 4-stroke MC 50-250 cc motorcycle -- 00% | V25: Bvkm | W25: million vehicles
J26: =IFERROR(VLOOKUP(C26,$R$1:$S$8,2,FALSE),J25) -> Trd_2w_gsl150 | K26: =IFERROR(IF(VALUE(C26)>2020,J26&"_"&TEXT(B26*100,"00"),"\I:"),"\I:") -> \I: | L26: =LEFT(K26,6) -> \I: | M26: =IF($K26="\I:","",C26) | N26: =IF($K26="\I:","",D26) | O26: =IF($K26="\I:","",E26) | P26: =IF($K26="\I:","",F26) | T26: =K26 -> \I: | U26: =OFFSET($S$1,MATCH(J26,$S$1:$S$11,0)-1,-1)&" -- "&TEXT(B26,"00%") -> 4-stroke MC 50-250 cc motorcycle -- 00% | V26: Bvkm | W26: million vehicles
B27: Reference values for 4-stroke MC 250-750 cc motorcycle | J27: =IFERROR(VLOOKUP(C27,$R$1:$S$8,2,FALSE),J26) -> Trd_2w_gsl150 | K27: =IFERROR(IF(VALUE(C27)>2020,J27&"_"&TEXT(B27*100,"00"),"\I:"),"\I:") -> \I: | L27: =LEFT(K27,6) -> \I: | M27: =IF($K27="\I:","",C27) | N27: =IF($K27="\I:","",D27) | O27: =IF($K27="\I:","",E27) | P27: =IF($K27="\I:","",F27) | T27: =K27 -> \I: | U27: =OFFSET($S$1,MATCH(J27,$S$1:$S$11,0)-1,-1)&" -- "&TEXT(B27,"00%") -> 4-stroke MC 50-250 cc motorcycle -- Reference values for 4-stroke MC 250-750 cc motorcycle | V27: Bvkm | W27: million vehicles
B28: 2015 | J28: =IFERROR(VLOOKUP(C28,$R$1:$S$8,2,FALSE),J27) -> Trd_2w_gsl150 | K28: =IFERROR(IF(VALUE(C28)>2020,J28&"_"&TEXT(B28*100,"00"),"\I:"),"\I:") -> \I: | L28: =LEFT(K28,6) -> \I: | M28: =IF($K28="\I:","",C28) | N28: =IF($K28="\I:","",D28) | O28: =IF($K28="\I:","",E28) | P28: =IF($K28="\I:","",F28) | T28: =K28 -> \I: | U28: =OFFSET($S$1,MATCH(J28,$S$1:$S$11,0)-1,-1)&" -- "&TEXT(B28,"00%") -> 4-stroke MC 50-250 cc motorcycle -- 201500% | V28: Bvkm | W28: million vehicles
B29: Energy consumption | C29: lt/100 km | D29: 4.4070545 | G29: =D29*$I$4/100*10^9/10^6 -> 1.3898087 | I29: =1/G29 -> 0.71952348 | J29: =IFERROR(VLOOKUP(C29,$R$1:$S$8,2,FALSE),J28) -> Trd_2w_gsl150 | K29: =IFERROR(IF(VALUE(C29)>2020,J29&"_"&TEXT(B29*100,"00"),"\I:"),"\I:") -> \I: | L29: =LEFT(K29,6) -> \I: | M29: =IF($K29="\I:","",C29) | N29: =IF($K29="\I:","",D29) | O29: =IF($K29="\I:","",E29) | P29: =IF($K29="\I:","",F29) | T29: =K29 -> \I: | U29: =OFFSET($S$1,MATCH(J29,$S$1:$S$11,0)-1,-1)&" -- "&TEXT(B29,"00%") -> 4-stroke MC 50-250 cc motorcycle -- Energy consumption | V29: Bvkm | W29: million vehicles
B30: Capital cost | C30: Euro15 /veh | D30: 6006.1537 | I30: bvkm/PJ | J30: =IFERROR(VLOOKUP(C30,$R$1:$S$8,2,FALSE),J29) -> Trd_2w_gsl150 | K30: =IFERROR(IF(VALUE(C30)>2020,J30&"_"&TEXT(B30*100,"00"),"\I:"),"\I:") -> \I: | L30: =LEFT(K30,6) -> \I: | M30: =IF($K30="\I:","",C30) | N30: =IF($K30="\I:","",D30) | O30: =IF($K30="\I:","",E30) | P30: =IF($K30="\I:","",F30) | T30: =K30 -> \I: | U30: =OFFSET($S$1,MATCH(J30,$S$1:$S$11,0)-1,-1)&" -- "&TEXT(B30,"00%") -> 4-stroke MC 50-250 cc motorcycle -- Capital cost | V30: Bvkm | W30: million vehicles
J31: =IFERROR(VLOOKUP(C31,$R$1:$S$8,2,FALSE),J30) -> Trd_2w_gsl150 | K31: =IFERROR(IF(VALUE(C31)>2020,J31&"_"&TEXT(B31*100,"00"),"\I:"),"\I:") -> \I: | L31: =LEFT(K31,6) -> \I: | M31: =IF($K31="\I:","",C31) | N31: =IF($K31="\I:","",D31) | O31: =IF($K31="\I:","",E31) | P31: =IF($K31="\I:","",F31) | T31: =K31 -> \I: | U31: =OFFSET($S$1,MATCH(J31,$S$1:$S$11,0)-1,-1)&" -- "&TEXT(B31,"00%") -> 4-stroke MC 50-250 cc motorcycle -- 00% | V31: Bvkm | W31: million vehicles
B32: Reduction of specific energy consumption relative to 2015 (%) | C32: 4-stroke MC 250-750 cc motorcycle | J32: =IFERROR(VLOOKUP(C32,$R$1:$S$8,2,FALSE),J31) -> Trd_2w_gsl500 | K32: =IFERROR(IF(VALUE(C32)>2020,J32&"_"&TEXT(B32*100,"00"),"\I:"),"\I:") -> \I: | L32: =LEFT(K32,6) -> \I: | M32: =IF($K32="\I:","",C32) | N32: =IF($K32="\I:","",D32) | O32: =IF($K32="\I:","",E32) | P32: =IF($K32="\I:","",F32) | T32: =K32 -> \I: | U32: =OFFSET($S$1,MATCH(J32,$S$1:$S$11,0)-1,-1)&" -- "&TEXT(B32,"00%") -> 4-stroke MC 250-750 cc motorcycle -- Reduction of specific energy consumption relative to 2015 (%) | V32: Bvkm | W32: million vehicles
J33: =IFERROR(VLOOKUP(C33,$R$1:$S$8,2,FALSE),J32) -> Trd_2w_gsl500 | K33: =IFERROR(IF(VALUE(C33)>2020,J33&"_"&TEXT(B33*100,"00"),"\I:"),"\I:") -> \I: | L33: =LEFT(K33,6) -> \I: | M33: =IF($K33="\I:","",C33) | N33: =IF($K33="\I:","",D33) | O33: =IF($K33="\I:","",E33) | P33: =IF($K33="\I:","",F33) | T33: =K33 -> \I: | U33: =OFFSET($S$1,MATCH(J33,$S$1:$S$11,0)-1,-1)&" -- "&TEXT(B33,"00%") -> 4-stroke MC 250-750 cc motorcycle -- 00% | V33: Bvkm | W33: million vehicles
J34: =IFERROR(VLOOKUP(C34,$R$1:$S$8,2,FALSE),J33) -> Trd_2w_gsl500 | K34: =IFERROR(IF(VALUE(C34)>2020,J34&"_"&TEXT(B34*100,"00"),"\I:"),"\I:") -> \I: | L34: =LEFT(K34,6) -> \I: | M34: =IF($K34="\I:","",C34) | N34: =IF($K34="\I:","",D34) | O34: =IF($K34="\I:","",E34) | P34: =IF($K34="\I:","",F34) | T34: =K34 -> \I: | U34: =OFFSET($S$1,MATCH(J34,$S$1:$S$11,0)-1,-1)&" -- "&TEXT(B34,"00%") -> 4-stroke MC 250-750 cc motorcycle -- 00% | V34: Bvkm | W34: million vehicles
C35: 2020 | D35: 2030 | E35: 2040 | F35: 2050 | J35: =IFERROR(VLOOKUP(C35,$R$1:$S$8,2,FALSE),J34) -> Trd_2w_gsl500 | K35: =IFERROR(IF(VALUE(C35)>2020,J35&"_"&TEXT(B35*100,"00"),"\I:"),"\I:") -> \I: | L35: =LEFT(K35,6) -> \I: | M35: =IF($K35="\I:","",C35) | N35: =IF($K35="\I:","",D35) | O35: =IF($K35="\I:","",E35) | P35: =IF($K35="\I:","",F35) | T35: =K35 -> \I: | U35: =OFFSET($S$1,MATCH(J35,$S$1:$S$11,0)-1,-1)&" -- "&TEXT(B35,"00%") -> 4-stroke MC 250-750 cc motorcycle -- 00% | V35: Bvkm | W35: million vehicles
B36: 0.018136358 | C36: 6040.1659 | D36: 6040.1659 | E36: 6040.1659 | F36: 6040.1659 | I36: =$I$29/$I$7*(1+B36) -> 0.74020251 | J36: =IFERROR(VLOOKUP(C36,$R$1:$S$8,2,FALSE),J35) -> Trd_2w_gsl500 | K36: =IFERROR(IF(VALUE(C36)>2020,J36&"_"&TEXT(B36*100,"00"),"\I:"),"\I:") -> Trd_2w_gsl500_02 | L36: =LEFT(K36,6) -> Trd_2w | M36: =IF($K36="\I:","",C36) -> 6040.1659 | N36: =IF($K36="\I:","",D36) -> 6040.1659 | O36: =IF($K36="\I:","",E36) -> 6040.1659 | P36: =IF($K36="\I:","",F36) -> 6040.1659 | T36: =K36 -> Trd_2w_gsl500_02 | U36: =OFFSET($S$1,MATCH(J36,$S$1:$S$11,0)-1,-1)&" -- "&TEXT(B36,"00%") -> 4-stroke MC 250-750 cc motorcycle -- 02% | V36: Bvkm | W36: million vehicles
B37: 0.068136358 | C37: 6180.4331 | D37: 6133.9338 | E37: 6133.9338 | F37: 6133.9338 | I37: =$I$29/$I$7*(1+B37) -> 0.77655336 | J37: =IFERROR(VLOOKUP(C37,$R$1:$S$8,2,FALSE),J36) -> Trd_2w_gsl500 | K37: =IFERROR(IF(VALUE(C37)>2020,J37&"_"&TEXT(B37*100,"00"),"\I:"),"\I:") -> Trd_2w_gsl500_07 | L37: =LEFT(K37,6) -> Trd_2w | M37: =IF($K37="\I:","",C37) -> 6180.4331 | N37: =IF($K37="\I:","",D37) -> 6133.9338 | O37: =IF($K37="\I:","",E37) -> 6133.9338 | P37: =IF($K37="\I:","",F37) -> 6133.9338 | T37: =K37 -> Trd_2w_gsl500_07 | U37: =OFFSET($S$1,MATCH(J37,$S$1:$S$11,0)-1,-1)&" -- "&TEXT(B37,"00%") -> 4-stroke MC 250-750 cc motorcycle -- 07% | V37: Bvkm | W37: million vehicles
B38: 0.11813636 | C38: 6261.7275 | D38: 6227.7018 | E38: 6227.7018 | F38: 6227.7018 | I38: =$I$29/$I$7*(1+B38) -> 0.81290421 | J38: =IFERROR(VLOOKUP(C38,$R$1:$S$8,2,FALSE),J37) -> Trd_2w_gsl500 | K38: =IFERROR(IF(VALUE(C38)>2020,J38&"_"&TEXT(B38*100,"00"),"\I:"),"\I:") -> Trd_2w_gsl500_12 | L38: =LEFT(K38,6) -> Trd_2w | M38: =IF($K38="\I:","",C38) -> 6261.7275 | N38: =IF($K38="\I:","",D38) -> 6227.7018 | O38: =IF($K38="\I:","",E38) -> 6227.7018 | P38: =IF($K38="\I:","",F38) -> 6227.7018 | T38: =K38 -> Trd_2w_gsl500_12 | U38: =OFFSET($S$1,MATCH(J38,$S$1:$S$11,0)-1,-1)&" -- "&TEXT(B38,"00%") -> 4-stroke MC 250-750 cc motorcycle -- 12% | V38: Bvkm | W38: million vehicles
B39: 0.16813636 | C39: 6605.8354 | D39: 6321.4697 | E39: 6321.4697 | F39: 6321.4697 | I39: =$I$29/$I$7*(1+B39) -> 0.84925507 | J39: =IFERROR(VLOOKUP(C39,$R$1:$S$8,2,FALSE),J38) -> Trd_2w_gsl500 | K39: =IFERROR(IF(VALUE(C39)>2020,J39&"_"&TEXT(B39*100,"00"),"\I:"),"\I:") -> Trd_2w_gsl500_17 | L39: =LEFT(K39,6) -> Trd_2w | M39: =IF($K39="\I:","",C39) -> 6605.8354 | N39: =IF($K39="\I:","",D39) -> 6321.4697 | O39: =IF($K39="\I:","",E39) -> 6321.4697 | P39: =IF($K39="\I:","",F39) -> 6321.4697 | T39: =K39 -> Trd_2w_gsl500_17 | U39: =OFFSET($S$1,MATCH(J39,$S$1:$S$11,0)-1,-1)&" -- "&TEXT(B39,"00%") -> 4-stroke MC 250-750 cc motorcycle -- 17% | V39: Bvkm | W39: million vehicles
B40: 0.21813636 | C40: 6724.0033 | D40: 6415.2377 | E40: 6415.2377 | F40: 6415.2377 | I40: =$I$29/$I$7*(1+B40) -> 0.88560592 | J40: =IFERROR(VLOOKUP(C40,$R$1:$S$8,2,FALSE),J39) -> Trd_2w_gsl500 | K40: =IFERROR(IF(VALUE(C40)>2020,J40&"_"&TEXT(B40*100,"00"),"\I:"),"\I:") -> Trd_2w_gsl500_22 | L40: =LEFT(K40,6) -> Trd_2w | M40: =IF($K40="\I:","",C40) -> 6724.0033 | N40: =IF($K40="\I:","",D40) -> 6415.2377 | O40: =IF($K40="\I:","",E40) -> 6415.2377 | P40: =IF($K40="\I:","",F40) -> 6415.2377 | T40: =K40 -> Trd_2w_gsl500_22 | U40: =OFFSET($S$1,MATCH(J40,$S$1:$S$11,0)-1,-1)&" -- "&TEXT(B40,"00%") -> 4-stroke MC 250-750 cc motorcycle -- 22% | V40: Bvkm | W40: million vehicles
B41: 0.26813636 | C41: 7627.8667 | D41: 6514.4074 | E41: 6509.0056 | F41: 6509.0056 | I41: =$I$29/$I$7*(1+B41) -> 0.92195677 | J41: =IFERROR(VLOOKUP(C41,$R$1:$S$8,2,FALSE),J40) -> Trd_2w_gsl500 | K41: =IFERROR(IF(VALUE(C41)>2020,J41&"_"&TEXT(B41*100,"00"),"\I:"),"\I:") -> Trd_2w_gsl500_27 | L41: =LEFT(K41,6) -> Trd_2w | M41: =IF($K41="\I:","",C41) -> 7627.8667 | N41: =IF($K41="\I:","",D41) -> 6514.4074 | O41: =IF($K41="\I:","",E41) -> 6509.0056 | P41: =IF($K41="\I:","",F41) -> 6509.0056 | T41: =K41 -> Trd_2w_gsl500_27 | U41: =OFFSET($S$1,MATCH(J41,$S$1:$S$11,0)-1,-1)&" -- "&TEXT(B41,"00%") -> 4-stroke MC 250-750 cc motorcycle -- 27% | V41: Bvkm | W41: million vehicles
B42: 0.31813636 | C42: 9964.6837 | D42: 6878.7359 | E42: 6602.7736 | F42: 6602.7736 | I42: =$I$29/$I$7*(1+B42) -> 0.95830763 | J42: =IFERROR(VLOOKUP(C42,$R$1:$S$8,2,FALSE),J41) -> Trd_2w_gsl500 | K42: =IFERROR(IF(VALUE(C42)>2020,J42&"_"&TEXT(B42*100,"00"),"\I:"),"\I:") -> Trd_2w_gsl500_32 | L42: =LEFT(K42,6) -> Trd_2w | M42: =IF($K42="\I:","",C42) -> 9964.6837 | N42: =IF($K42="\I:","",D42) -> 6878.7359 | O42: =IF($K42="\I:","",E42) -> 6602.7736 | P42: =IF($K42="\I:","",F42) -> 6602.7736 | T42: =K42 -> Trd_2w_gsl500_32 | U42: =OFFSET($S$1,MATCH(J42,$S$1:$S$11,0)-1,-1)&" -- "&TEXT(B42,"00%") -> 4-stroke MC 250-750 cc motorcycle -- 32% | V42: Bvkm | W42: million vehicles
J43: =IFERROR(VLOOKUP(C43,$R$1:$S$8,2,FALSE),J42) -> Trd_2w_gsl500 | K43: =IFERROR(IF(VALUE(C43)>2020,J43&"_"&TEXT(B43*100,"00"),"\I:"),"\I:") -> \I: | L43: =LEFT(K43,6) -> \I: | M43: =IF($K43="\I:","",C43) | N43: =IF($K43="\I:","",D43) | O43: =IF($K43="\I:","",E43) | P43: =IF($K43="\I:","",F43) | T43: =K43 -> \I: | U43: =OFFSET($S$1,MATCH(J43,$S$1:$S$11,0)-1,-1)&" -- "&TEXT(B43,"00%") -> 4-stroke MC 250-750 cc motorcycle -- 00% | V43: Bvkm | W43: million vehicles
J44: =IFERROR(VLOOKUP(C44,$R$1:$S$8,2,FALSE),J43) -> Trd_2w_gsl500 | K44: =IFERROR(IF(VALUE(C44)>2020,J44&"_"&TEXT(B44*100,"00"),"\I:"),"\I:") -> \I: | L44: =LEFT(K44,6) -> \I: | M44: =IF($K44="\I:","",C44) | N44: =IF($K44="\I:","",D44) | O44: =IF($K44="\I:","",E44) | P44: =IF($K44="\I:","",F44) | T44: =K44 -> \I: | U44: =OFFSET($S$1,MATCH(J44,$S$1:$S$11,0)-1,-1)&" -- "&TEXT(B44,"00%") -> 4-stroke MC 250-750 cc motorcycle -- 00% | V44: Bvkm | W44: million vehicles
J45: =IFERROR(VLOOKUP(C45,$R$1:$S$8,2,FALSE),J44) -> Trd_2w_gsl500 | K45: =IFERROR(IF(VALUE(C45)>2020,J45&"_"&TEXT(B45*100,"00"),"\I:"),"\I:") -> \I: | L45: =LEFT(K45,6) -> \I: | M45: =IF($K45="\I:","",C45) | N45: =IF($K45="\I:","",D45) | O45: =IF($K45="\I:","",E45) | P45: =IF($K45="\I:","",F45) | T45: =K45 -> \I: | U45: =OFFSET($S$1,MATCH(J45,$S$1:$S$11,0)-1,-1)&" -- "&TEXT(B45,"00%") -> 4-stroke MC 250-750 cc motorcycle -- 00% | V45: Bvkm | W45: million vehicles
J46: =IFERROR(VLOOKUP(C46,$R$1:$S$8,2,FALSE),J45) -> Trd_2w_gsl500 | K46: =IFERROR(IF(VALUE(C46)>2020,J46&"_"&TEXT(B46*100,"00"),"\I:"),"\I:") -> \I: | L46: =LEFT(K46,6) -> \I: | M46: =IF($K46="\I:","",C46) | N46: =IF($K46="\I:","",D46) | O46: =IF($K46="\I:","",E46) | P46: =IF($K46="\I:","",F46) | T46: =K46 -> \I: | U46: =OFFSET($S$1,MATCH(J46,$S$1:$S$11,0)-1,-1)&" -- "&TEXT(B46,"00%") -> 4-stroke MC 250-750 cc motorcycle -- 00% | V46: Bvkm | W46: million vehicles
B47: Reference values for 4-stroke MC >750 cc motorcycle | J47: =IFERROR(VLOOKUP(C47,$R$1:$S$8,2,FALSE),J46) -> Trd_2w_gsl500 | K47: =IFERROR(IF(VALUE(C47)>2020,J47&"_"&TEXT(B47*100,"00"),"\I:"),"\I:") -> \I: | L47: =LEFT(K47,6) -> \I: | M47: =IF($K47="\I:","",C47) | N47: =IF($K47="\I:","",D47) | O47: =IF($K47="\I:","",E47) | P47: =IF($K47="\I:","",F47) | T47: =K47 -> \I: | U47: =OFFSET($S$1,MATCH(J47,$S$1:$S$11,0)-1,-1)&" -- "&TEXT(B47,"00%") -> 4-stroke MC 250-750 cc motorcycle -- Reference values for 4-stroke MC >750 cc motorcycle | V47: Bvkm | W47: million vehicles
B48: 2015 | J48: =IFERROR(VLOOKUP(C48,$R$1:$S$8,2,FALSE),J47) -> Trd_2w_gsl500 | K48: =IFERROR(IF(VALUE(C48)>2020,J48&"_"&TEXT(B48*100,"00"),"\I:"),"\I:") -> \I: | L48: =LEFT(K48,6) -> \I: | M48: =IF($K48="\I:","",C48) | N48: =IF($K48="\I:","",D48) | O48: =IF($K48="\I:","",E48) | P48: =IF($K48="\I:","",F48) | T48: =K48 -> \I: | U48: =OFFSET($S$1,MATCH(J48,$S$1:$S$11,0)-1,-1)&" -- "&TEXT(B48,"00%") -> 4-stroke MC 250-750 cc motorcycle -- 201500% | V48: Bvkm | W48: million vehicles
B49: Energy consumption | C49: lt/100 km | D49: 5.4023295 | G49: =D49*$I$4/100*10^9/10^6 -> 1.7036786 | I49: =1/G49 -> 0.58696516 | J49: =IFERROR(VLOOKUP(C49,$R$1:$S$8,2,FALSE),J48) -> Trd_2w_gsl500 | K49: =IFERROR(IF(VALUE(C49)>2020,J49&"_"&TEXT(B49*100,"00"),"\I:"),"\I:") -> \I: | L49: =LEFT(K49,6) -> \I: | M49: =IF($K49="\I:","",C49) | N49: =IF($K49="\I:","",D49) | O49: =IF($K49="\I:","",E49) | P49: =IF($K49="\I:","",F49) | T49: =K49 -> \I: | U49: =OFFSET($S$1,MATCH(J49,$S$1:$S$11,0)-1,-1)&" -- "&TEXT(B49,"00%") -> 4-stroke MC 250-750 cc motorcycle -- Energy consumption | V49: Bvkm | W49: million vehicles
B50: Capital cost | C50: Euro15 /veh | D50: 11061.565 | I50: bvkm/PJ | J50: =IFERROR(VLOOKUP(C50,$R$1:$S$8,2,FALSE),J49) -> Trd_2w_gsl500 | K50: =IFERROR(IF(VALUE(C50)>2020,J50&"_"&TEXT(B50*100,"00"),"\I:"),"\I:") -> \I: | L50: =LEFT(K50,6) -> \I: | M50: =IF($K50="\I:","",C50) | N50: =IF($K50="\I:","",D50) | O50: =IF($K50="\I:","",E50) | P50: =IF($K50="\I:","",F50) | T50: =K50 -> \I: | U50: =OFFSET($S$1,MATCH(J50,$S$1:$S$11,0)-1,-1)&" -- "&TEXT(B50,"00%") -> 4-stroke MC 250-750 cc motorcycle -- Capital cost | V50: Bvkm | W50: million vehicles
J51: =IFERROR(VLOOKUP(C51,$R$1:$S$8,2,FALSE),J50) -> Trd_2w_gsl500 | K51: =IFERROR(IF(VALUE(C51)>2020,J51&"_"&TEXT(B51*100,"00"),"\I:"),"\I:") -> \I: | L51: =LEFT(K51,6) -> \I: | M51: =IF($K51="\I:","",C51) | N51: =IF($K51="\I:","",D51) | O51: =IF($K51="\I:","",E51) | P51: =IF($K51="\I:","",F51) | T51: =K51 -> \I: | U51: =OFFSET($S$1,MATCH(J51,$S$1:$S$11,0)-1,-1)&" -- "&TEXT(B51,"00%") -> 4-stroke MC 250-750 cc motorcycle -- 00% | V51: Bvkm | W51: million vehicles
B52: Reduction of specific energy consumption relative to 2015 (%) | C52: 4-stroke MC >750 cc motorcycle | J52: =IFERROR(VLOOKUP(C52,$R$1:$S$8,2,FALSE),J51) -> Trd_3w_gsl | K52: =IFERROR(IF(VALUE(C52)>2020,J52&"_"&TEXT(B52*100,"00"),"\I:"),"\I:") -> \I: | L52: =LEFT(K52,6) -> \I: | M52: =IF($K52="\I:","",C52) | N52: =IF($K52="\I:","",D52) | O52: =IF($K52="\I:","",E52) | P52: =IF($K52="\I:","",F52) | T52: =K52 -> \I: | U52: =OFFSET($S$1,MATCH(J52,$S$1:$S$11,0)-1,-1)&" -- "&TEXT(B52,"00%") -> 4-stroke MC >750 cc motorcycle -- Reduction of specific energy consumption relative to 2015 (%) | V52: Bvkm | W52: million vehicles
J53: =IFERROR(VLOOKUP(C53,$R$1:$S$8,2,FALSE),J52) -> Trd_3w_gsl | K53: =IFERROR(IF(VALUE(C53)>2020,J53&"_"&TEXT(B53*100,"00"),"\I:"),"\I:") -> \I: | L53: =LEFT(K53,6) -> \I: | M53: =IF($K53="\I:","",C53) | N53: =IF($K53="\I:","",D53) | O53: =IF($K53="\I:","",E53) | P53: =IF($K53="\I:","",F53) | T53: =K53 -> \I: | U53: =OFFSET($S$1,MATCH(J53,$S$1:$S$11,0)-1,-1)&" -- "&TEXT(B53,"00%") -> 4-stroke MC >750 cc motorcycle -- 00% | V53: Bvkm | W53: million vehicles
J54: =IFERROR(VLOOKUP(C54,$R$1:$S$8,2,FALSE),J53) -> Trd_3w_gsl | K54: =IFERROR(IF(VALUE(C54)>2020,J54&"_"&TEXT(B54*100,"00"),"\I:"),"\I:") -> \I: | L54: =LEFT(K54,6) -> \I: | M54: =IF($K54="\I:","",C54) | N54: =IF($K54="\I:","",D54) | O54: =IF($K54="\I:","",E54) | P54: =IF($K54="\I:","",F54) | T54: =K54 -> \I: | U54: =OFFSET($S$1,MATCH(J54,$S$1:$S$11,0)-1,-1)&" -- "&TEXT(B54,"00%") -> 4-stroke MC >750 cc motorcycle -- 00% | V54: Bvkm | W54: million vehicles
C55: 2020 | D55: 2030 | E55: 2040 | F55: 2050 | J55: =IFERROR(VLOOKUP(C55,$R$1:$S$8,2,FALSE),J54) -> Trd_3w_gsl | K55: =IFERROR(IF(VALUE(C55)>2020,J55&"_"&TEXT(B55*100,"00"),"\I:"),"\I:") -> \I: | L55: =LEFT(K55,6) -> \I: | M55: =IF($K55="\I:","",C55) | N55: =IF($K55="\I:","",D55) | O55: =IF($K55="\I:","",E55) | P55: =IF($K55="\I:","",F55) | T55: =K55 -> \I: | U55: =OFFSET($S$1,MATCH(J55,$S$1:$S$11,0)-1,-1)&" -- "&TEXT(B55,"00%") -> 4-stroke MC >750 cc motorcycle -- 00% | V55: Bvkm | W55: million vehicles
B56: 0.015649072 | C56: 11100.695 | D56: 11100.695 | E56: 11100.695 | F56: 11100.695 | I56: =(1+B56) -> 1.0156491 | J56: =IFERROR(VLOOKUP(C56,$R$1:$S$8,2,FALSE),J55) -> Trd_3w_gsl | K56: =IFERROR(IF(VALUE(C56)>2020,J56&"_"&TEXT(B56*100,"00"),"\I:"),"\I:") -> Trd_3w_gsl_02 | L56: =LEFT(K56,6) -> Trd_3w | M56: =IF($K56="\I:","",C56) -> 11100.695 | N56: =IF($K56="\I:","",D56) -> 11100.695 | O56: =IF($K56="\I:","",E56) -> 11100.695 | P56: =IF($K56="\I:","",F56) -> 11100.695 | T56: =K56 -> Trd_3w_gsl_02 | U56: =OFFSET($S$1,MATCH(J56,$S$1:$S$11,0)-1,-1)&" -- "&TEXT(B56,"00%") -> 4-stroke MC >750 cc motorcycle -- 02% | V56: Bvkm | W56: million vehicles
B57: 0.065649072 | C57: 11287.718 | D57: 11225.719 | E57: 11225.719 | F57: 11225.719 | I57: =(1+B57) -> 1.0656491 | J57: =IFERROR(VLOOKUP(C57,$R$1:$S$8,2,FALSE),J56) -> Trd_3w_gsl | K57: =IFERROR(IF(VALUE(C57)>2020,J57&"_"&TEXT(B57*100,"00"),"\I:"),"\I:") -> Trd_3w_gsl_07 | L57: =LEFT(K57,6) -> Trd_3w | M57: =IF($K57="\I:","",C57) -> 11287.718 | N57: =IF($K57="\I:","",D57) -> 11225.719 | O57: =IF($K57="\I:","",E57) -> 11225.719 | P57: =IF($K57="\I:","",F57) -> 11225.719 | T57: =K57 -> Trd_3w_gsl_07 | U57: =OFFSET($S$1,MATCH(J57,$S$1:$S$11,0)-1,-1)&" -- "&TEXT(B57,"00%") -> 4-stroke MC >750 cc motorcycle -- 07% | V57: Bvkm | W57: million vehicles
B58: 0.11564907 | C58: 11396.111 | D58: 11350.743 | E58: 11350.743 | F58: 11350.743 | I58: =(1+B58) -> 1.1156491 | J58: =IFERROR(VLOOKUP(C58,$R$1:$S$8,2,FALSE),J57) -> Trd_3w_gsl | K58: =IFERROR(IF(VALUE(C58)>2020,J58&"_"&TEXT(B58*100,"00"),"\I:"),"\I:") -> Trd_3w_gsl_12 | L58: =LEFT(K58,6) -> Trd_3w | M58: =IF($K58="\I:","",C58) -> 11396.111 | N58: =IF($K58="\I:","",D58) -> 11350.743 | O58: =IF($K58="\I:","",E58) -> 11350.743 | P58: =IF($K58="\I:","",F58) -> 11350.743 | T58: =K58 -> Trd_3w_gsl_12 | U58: =OFFSET($S$1,MATCH(J58,$S$1:$S$11,0)-1,-1)&" -- "&TEXT(B58,"00%") -> 4-stroke MC >750 cc motorcycle -- 12% | V58: Bvkm | W58: million vehicles
B59: 0.16564907 | C59: 11854.921 | D59: 11475.767 | E59: 11475.767 | F59: 11475.767 | I59: =(1+B59) -> 1.1656491 | J59: =IFERROR(VLOOKUP(C59,$R$1:$S$8,2,FALSE),J58) -> Trd_3w_gsl | K59: =IFERROR(IF(VALUE(C59)>2020,J59&"_"&TEXT(B59*100,"00"),"\I:"),"\I:") -> Trd_3w_gsl_17 | L59: =LEFT(K59,6) -> Trd_3w | M59: =IF($K59="\I:","",C59) -> 11854.921 | N59: =IF($K59="\I:","",D59) -> 11475.767 | O59: =IF($K59="\I:","",E59) -> 11475.767 | P59: =IF($K59="\I:","",F59) -> 11475.767 | T59: =K59 -> Trd_3w_gsl_17 | U59: =OFFSET($S$1,MATCH(J59,$S$1:$S$11,0)-1,-1)&" -- "&TEXT(B59,"00%") -> 4-stroke MC >750 cc motorcycle -- 17% | V59: Bvkm | W59: million vehicles
B60: 0.21564907 | C60: 12012.478 | D60: 11600.791 | E60: 11600.791 | F60: 11600.791 | I60: =(1+B60) -> 1.2156491 | J60: =IFERROR(VLOOKUP(C60,$R$1:$S$8,2,FALSE),J59) -> Trd_3w_gsl | K60: =IFERROR(IF(VALUE(C60)>2020,J60&"_"&TEXT(B60*100,"00"),"\I:"),"\I:") -> Trd_3w_gsl_22 | L60: =LEFT(K60,6) -> Trd_3w | M60: =IF($K60="\I:","",C60) -> 12012.478 | N60: =IF($K60="\I:","",D60) -> 11600.791 | O60: =IF($K60="\I:","",E60) -> 11600.791 | P60: =IF($K60="\I:","",F60) -> 11600.791 | T60: =K60 -> Trd_3w_gsl_22 | U60: =OFFSET($S$1,MATCH(J60,$S$1:$S$11,0)-1,-1)&" -- "&TEXT(B60,"00%") -> 4-stroke MC >750 cc motorcycle -- 22% | V60: Bvkm | W60: million vehicles
B61: 0.26564907 | C61: 13217.63 | D61: 11733.017 | E61: 11725.815 | F61: 11725.815 | I61: =(1+B61) -> 1.2656491 | J61: =IFERROR(VLOOKUP(C61,$R$1:$S$8,2,FALSE),J60) -> Trd_3w_gsl | K61: =IFERROR(IF(VALUE(C61)>2020,J61&"_"&TEXT(B61*100,"00"),"\I:"),"\I:") -> Trd_3w_gsl_27 | L61: =LEFT(K61,6) -> Trd_3w | M61: =IF($K61="\I:","",C61) -> 13217.63 | N61: =IF($K61="\I:","",D61) -> 11733.017 | O61: =IF($K61="\I:","",E61) -> 11725.815 | P61: =IF($K61="\I:","",F61) -> 11725.815 | T61: =K61 -> Trd_3w_gsl_27 | U61: =OFFSET($S$1,MATCH(J61,$S$1:$S$11,0)-1,-1)&" -- "&TEXT(B61,"00%") -> 4-stroke MC >750 cc motorcycle -- 27% | V61: Bvkm | W61: million vehicles
B62: 0.31564907 | C62: 16333.386 | D62: 12218.789 | E62: 11850.839 | F62: 11850.839 | I62: =(1+B62) -> 1.3156491 | J62: =IFERROR(VLOOKUP(C62,$R$1:$S$8,2,FALSE),J61) -> Trd_3w_gsl | K62: =IFERROR(IF(VALUE(C62)>2020,J62&"_"&TEXT(B62*100,"00"),"\I:"),"\I:") -> Trd_3w_gsl_32 | L62: =LEFT(K62,6) -> Trd_3w | M62: =IF($K62="\I:","",C62) -> 16333.386 | N62: =IF($K62="\I:","",D62) -> 12218.789 | O62: =IF($K62="\I:","",E62) -> 11850.839 | P62: =IF($K62="\I:","",F62) -> 11850.839 | T62: =K62 -> Trd_3w_gsl_32 | U62: =OFFSET($S$1,MATCH(J62,$S$1:$S$11,0)-1,-1)&" -- "&TEXT(B62,"00%") -> 4-stroke MC >750 cc motorcycle -- 32% | V62: Bvkm | W62: million vehicles
J63: =IFERROR(VLOOKUP(C63,$R$1:$S$8,2,FALSE),J62) -> Trd_3w_gsl | K63: =IFERROR(IF(VALUE(C63)>2020,J63&"_"&TEXT(B63*100,"00"),"\I:"),"\I:") -> \I: | L63: =LEFT(K63,6) -> \I: | M63: =IF($K63="\I:","",C63) | N63: =IF($K63="\I:","",D63) | O63: =IF($K63="\I:","",E63) | P63: =IF($K63="\I:","",F63) | T63: =K63 -> \I: | U63: =OFFSET($S$1,MATCH(J63,$S$1:$S$11,0)-1,-1)&" -- "&TEXT(B63,"00%") -> 4-stroke MC >750 cc motorcycle -- 00% | V63: Bvkm | W63: million vehicles
J64: =IFERROR(VLOOKUP(C64,$R$1:$S$8,2,FALSE),J63) -> Trd_3w_gsl | K64: =IFERROR(IF(VALUE(C64)>2020,J64&"_"&TEXT(B64*100,"00"),"\I:"),"\I:") -> \I: | L64: =LEFT(K64,6) -> \I: | M64: =IF($K64="\I:","",C64) | N64: =IF($K64="\I:","",D64) | O64: =IF($K64="\I:","",E64) | P64: =IF($K64="\I:","",F64) | T64: =K64 -> \I: | U64: =OFFSET($S$1,MATCH(J64,$S$1:$S$11,0)-1,-1)&" -- "&TEXT(B64,"00%") -> 4-stroke MC >750 cc motorcycle -- 00% | V64: Bvkm | W64: million vehicles
