Workbook

Sheet Scen_usingStepMining_n_mute_(2)
C4: m_lithium | D4: 12.85 | L4: ~TFM_UPD
C5: m_nickel | D5: 20 | K5: pset_pn | L5: Attribute | M5: AllRegions
C6: m_cobalt | D6: 29.3 | K6: MINBatMaterials_LI | L6: ACT_COST | M6: 99999
C7: m_manganese | D7: 2 | K7: MINBatMaterials_NI | L7: =L6 | M7: =M6
C8: m_aluminum | D8: 2.5 | K8: MINBatMaterials_COB | L8: =L7 | M8: =M7
C9: m_copper | D9: 8 | K9: MINBatMaterials_MN | L9: =L8 | M9: =M8
C10: m_graphite | D10: 1 | K10: MINBatMaterials_AL | L10: =L9 | M10: =M9
K11: MINBatMaterials_COP | L11: =L10 | M11: =M10
K12: MINBatMaterials_GR | L12: =L11 | M12: =M11
K13: MINBatMaterials_COB_byCop | L13: =L12 | M13: =M12
K14: MINBatMaterials_COB_byNI_sulfide | L14: =L13 | M14: =M13
K15: MINBatMaterials_COB_direct | L15: =L14 | M15: =M14
K16: MINBatMaterials_COB_byNI_HPAL | L16: =L15 | M16: =M15
K17: MINBatMaterials_LI | L17: NCAP_FOM | M17: =M16
K18: MINBatMaterials_NI | L18: =L17 | M18: =M17
K19: MINBatMaterials_COB | L19: =L18 | M19: =M18
K20: MINBatMaterials_MN | L20: =L19 | M20: =M19
K21: MINBatMaterials_AL | L21: =L20 | M21: =M20
K22: MINBatMaterials_COP | L22: =L21 | M22: =M21
K23: MINBatMaterials_GR | L23: =L22 | M23: =M22
K24: MINBatMaterials_COB_byCop | L24: =L23 | M24: =M23
K25: MINBatMaterials_COB_byNI_sulfide | L25: =L24 | M25: =M24
K26: MINBatMaterials_COB_direct | L26: =L25 | M26: =M25
K27: MINBatMaterials_COB_byNI_HPAL | L27: =L26 | M27: =M26
C32: Suggested by COde after reading UCD woman paper
C39: ~TFM_INS
C40: pset_pn | D40: Attribute | E40: cset_cn | F40: Africa_North | G40: Africa_Other | H40: Australia | I40: Austria | J40: Baltics | K40: BeNeLux | L40: Brazil | M40: China | N40: CroSloven | O40: CzechSlovak | P40: France | Q40: Germany | R40: GreeceCyp | S40: HunRomBul | T40: Iceland | U40: India | V40: Ireland | W40: ItalyMal | X40: Japan | Y40: LatAm | Z40: MidEast | AA40: NorthAm | AB40: Norway | AC40: Poland | AD40: ROW | AE40: Russia | AF40: SaudiArabia | AG40: SouthAfrica | AH40: SpainPor | AI40: SweFinDen | AJ40: Switzerland | AK40: Turkey | AL40: UK | AM40: Ukraine | AN40: WestBalkans | AO40: year
C41: =Codex_calc!C41 | D41: =Codex_calc!D41 | F41: =Codex_calc!F41 | G41: =Codex_calc!G41 | H41: =Codex_calc!H41 | I41: =Codex_calc!I41 | J41: =Codex_calc!J41 | K41: =Codex_calc!K41 | L41: =Codex_calc!L41 | M41: =Codex_calc!M41 | ... AO41: =Codex_calc!AO41
C42: =Codex_calc!C42 | D42: =Codex_calc!D42 | AO42: =Codex_calc!AO42
C43: =Codex_calc!C43 | D43: =Codex_calc!D43 | E43: =Codex_calc!E43 | F43: =Codex_calc!F43 | G43: =Codex_calc!G43 | H43: =Codex_calc!H43 | I43: =Codex_calc!I43 | J43: =Codex_calc!J43 | ... AO43: =Codex_calc!AO43
C44: =Codex_calc!C44 | D44: =Codex_calc!D44 | F44: =Codex_calc!F44 | G44: =Codex_calc!G44 | H44: =Codex_calc!H44 | I44: =Codex_calc!I44 | J44: =Codex_calc!J44 | K44: =Codex_calc!K44 | L44: =Codex_calc!L44 | M44: =Codex_calc!M44 | ... AO44: =Codex_calc!AO44
C45: =Codex_calc!C45 | D45: =Codex_calc!D45 | AO45: =Codex_calc!AO45
C46: =Codex_calc!C46 | D46: =Codex_calc!D46 | E46: =Codex_calc!E46 | F46: =Codex_calc!F46 | G46: =Codex_calc!G46 | H46: =Codex_calc!H46 | I46: =Codex_calc!I46 | J46: =Codex_calc!J46 | ... AO46: =Codex_calc!AO46
C47: =Codex_calc!C47 | D47: =Codex_calc!D47 | AO47: =Codex_calc!AO47
C48: =Codex_calc!C48 | D48: =Codex_calc!D48 | AO48: =Codex_calc!AO48
C49: =Codex_calc!C49 | D49: =Codex_calc!D49 | E49: =Codex_calc!E49 | F49: =Codex_calc!F49 | G49: =Codex_calc!G49 | H49: =Codex_calc!H49 | I49: =Codex_calc!I49 | J49: =Codex_calc!J49 | ... AO49: =Codex_calc!AO49
C50: * | D50: =Codex_calc!D50 | E50: =Codex_calc!E50 | F50: =Codex_calc!F50 | G50: =Codex_calc!G50 | H50: =Codex_calc!H50 | I50: =Codex_calc!I50 | J50: =Codex_calc!J50 | K50: =Codex_calc!K50 | ... AO50: =Codex_calc!AO50
C51: =Codex_calc!C51 | D51: =Codex_calc!D51 | F51: =Codex_calc!F51 | G51: =Codex_calc!G51 | H51: =Codex_calc!H51 | I51: =Codex_calc!I51 | J51: =Codex_calc!J51 | K51: =Codex_calc!K51 | L51: =Codex_calc!L51 | M51: =Codex_calc!M51 | ... AO51: =Codex_calc!AO51
C52: =Codex_calc!C52 | D52: =Codex_calc!D52 | AO52: =Codex_calc!AO52
C53: =Codex_calc!C53 | D53: =Codex_calc!D53 | E53: =Codex_calc!E53 | F53: =Codex_calc!F53 | G53: =Codex_calc!G53 | H53: =Codex_calc!H53 | I53: =Codex_calc!I53 | J53: =Codex_calc!J53 | ... AO53: =Codex_calc!AO53
C54: =Codex_calc!C54 | D54: =Codex_calc!D54 | F54: =Codex_calc!F54 | G54: =Codex_calc!G54 | H54: =Codex_calc!H54 | I54: =Codex_calc!I54 | J54: =Codex_calc!J54 | K54: =Codex_calc!K54 | L54: =Codex_calc!L54 | M54: =Codex_calc!M54 | ... AO54: =Codex_calc!AO54
C55: =Codex_calc!C55 | D55: =Codex_calc!D55 | AO55: =Codex_calc!AO55
C56: =Codex_calc!C56 | D56: =Codex_calc!D56 | E56: =Codex_calc!E56 | F56: =Codex_calc!F56 | G56: =Codex_calc!G56 | H56: =Codex_calc!H56 | I56: =Codex_calc!I56 | J56: =Codex_calc!J56 | ... AO56: =Codex_calc!AO56
C57: =Codex_calc!C57 | D57: =Codex_calc!D57 | AO57: =Codex_calc!AO57
C58: =Codex_calc!C58 | D58: =Codex_calc!D58 | AO58: =Codex_calc!AO58
C59: =Codex_calc!C59 | D59: =Codex_calc!D59 | E59: =Codex_calc!E59 | F59: =Codex_calc!F59 | G59: =Codex_calc!G59 | H59: =Codex_calc!H59 | I59: =Codex_calc!I59 | J59: =Codex_calc!J59 | ... AO59: =Codex_calc!AO59
C60: * | D60: =Codex_calc!D60 | E60: =Codex_calc!E60 | F60: =Codex_calc!F60 | G60: =Codex_calc!G60 | H60: =Codex_calc!H60 | I60: =Codex_calc!I60 | J60: =Codex_calc!J60 | K60: =Codex_calc!K60 | ... AO60: =Codex_calc!AO60
C61: =Codex_calc!C61 | D61: =Codex_calc!D61 | F61: =Codex_calc!F61 | G61: =Codex_calc!G61 | H61: =Codex_calc!H61 | I61: =Codex_calc!I61 | J61: =Codex_calc!J61 | K61: =Codex_calc!K61 | L61: =Codex_calc!L61 | M61: =Codex_calc!M61 | ... AO61: =Codex_calc!AO61
C62: =Codex_calc!C62 | D62: =Codex_calc!D62 | AO62: =Codex_calc!AO62
C63: =Codex_calc!C63 | D63: =Codex_calc!D63 | E63: =Codex_calc!E63 | F63: =Codex_calc!F63 | G63: =Codex_calc!G63 | H63: =Codex_calc!H63 | I63: =Codex_calc!I63 | J63: =Codex_calc!J63 | ... AO63: =Codex_calc!AO63
C64: =Codex_calc!C64 | D64: =Codex_calc!D64 | F64: =Codex_calc!F64 | G64: =Codex_calc!G64 | H64: =Codex_calc!H64 | I64: =Codex_calc!I64 | J64: =Codex_calc!J64 | K64: =Codex_calc!K64 | L64: =Codex_calc!L64 | M64: =Codex_calc!M64 | ... AO64: =Codex_calc!AO64
C65: =Codex_calc!C65 | D65: =Codex_calc!D65 | AO65: =Codex_calc!AO65
C66: =Codex_calc!C66 | D66: =Codex_calc!D66 | E66: =Codex_calc!E66 | F66: =Codex_calc!F66 | G66: =Codex_calc!G66 | H66: =Codex_calc!H66 | I66: =Codex_calc!I66 | J66: =Codex_calc!J66 | ... AO66: =Codex_calc!AO66
C67: =Codex_calc!C67 | D67: =Codex_calc!D67 | AO67: =Codex_calc!AO67
C68: =Codex_calc!C68 | D68: =Codex_calc!D68 | AO68: =Codex_calc!AO68
C69: =Codex_calc!C69 | D69: =Codex_calc!D69 | E69: =Codex_calc!E69 | F69: =Codex_calc!F69 | G69: =Codex_calc!G69 | H69: =Codex_calc!H69 | I69: =Codex_calc!I69 | J69: =Codex_calc!J69 | ... AO69: =Codex_calc!AO69
C70: * | D70: =Codex_calc!D70 | E70: =Codex_calc!E70 | F70: =Codex_calc!F70 | G70: =Codex_calc!G70 | H70: =Codex_calc!H70 | I70: =Codex_calc!I70 | J70: =Codex_calc!J70 | K70: =Codex_calc!K70 | ... AO70: =Codex_calc!AO70
C71: =Codex_calc!C71 | D71: =Codex_calc!D71 | F71: =Codex_calc!F71 | G71: =Codex_calc!G71 | H71: =Codex_calc!H71 | I71: =Codex_calc!I71 | J71: =Codex_calc!J71 | K71: =Codex_calc!K71 | L71: =Codex_calc!L71 | M71: =Codex_calc!M71 | ... AO71: =Codex_calc!AO71
C72: =Codex_calc!C72 | D72: =Codex_calc!D72 | AO72: =Codex_calc!AO72
C73: =Codex_calc!C73 | D73: =Codex_calc!D73 | E73: =Codex_calc!E73 | F73: =Codex_calc!F73 | G73: =Codex_calc!G73 | H73: =Codex_calc!H73 | I73: =Codex_calc!I73 | J73: =Codex_calc!J73 | ... AO73: =Codex_calc!AO73
C74: =Codex_calc!C74 | D74: =Codex_calc!D74 | F74: =Codex_calc!F74 | G74: =Codex_calc!G74 | H74: =Codex_calc!H74 | I74: =Codex_calc!I74 | J74: =Codex_calc!J74 | K74: =Codex_calc!K74 | L74: =Codex_calc!L74 | M74: =Codex_calc!M74 | ... AO74: =Codex_calc!AO74
C75: =Codex_calc!C75 | D75: =Codex_calc!D75 | AO75: =Codex_calc!AO75
C76: =Codex_calc!C76 | D76: =Codex_calc!D76 | E76: =Codex_calc!E76 | F76: =Codex_calc!F76 | G76: =Codex_calc!G76 | H76: =Codex_calc!H76 | I76: =Codex_calc!I76 | J76: =Codex_calc!J76 | ... AO76: =Codex_calc!AO76
C77: =Codex_calc!C77 | D77: =Codex_calc!D77 | AO77: =Codex_calc!AO77
C78: =Codex_calc!C78 | D78: =Codex_calc!D78 | AO78: =Codex_calc!AO78
C79: =Codex_calc!C79 | D79: =Codex_calc!D79 | E79: =Codex_calc!E79 | F79: =Codex_calc!F79 | G79: =Codex_calc!G79 | H79: =Codex_calc!H79 | I79: =Codex_calc!I79 | J79: =Codex_calc!J79 | ... AO79: =Codex_calc!AO79
C80: * | D80: =Codex_calc!D80 | E80: =Codex_calc!E80 | F80: =Codex_calc!F80 | G80: =Codex_calc!G80 | H80: =Codex_calc!H80 | I80: =Codex_calc!I80 | J80: =Codex_calc!J80 | K80: =Codex_calc!K80 | ... AO80: =Codex_calc!AO80
C81: =Codex_calc!C81 | D81: =Codex_calc!D81 | F81: =Codex_calc!F81 | G81: =Codex_calc!G81 | H81: =Codex_calc!H81 | I81: =Codex_calc!I81 | J81: =Codex_calc!J81 | K81: =Codex_calc!K81 | L81: =Codex_calc!L81 | M81: =Codex_calc!M81 | ... AO81: =Codex_calc!AO81
C82: =Codex_calc!C82 | D82: =Codex_calc!D82 | AO82: =Codex_calc!AO82
C83: =Codex_calc!C83 | D83: =Codex_calc!D83 | E83: =Codex_calc!E83 | F83: =Codex_calc!F83 | G83: =Codex_calc!G83 | H83: =Codex_calc!H83 | I83: =Codex_calc!I83 | J83: =Codex_calc!J83 | ... AO83: =Codex_calc!AO83
C84: =Codex_calc!C84 | D84: =Codex_calc!D84 | F84: =Codex_calc!F84 | G84: =Codex_calc!G84 | H84: =Codex_calc!H84 | I84: =Codex_calc!I84 | J84: =Codex_calc!J84 | K84: =Codex_calc!K84 | L84: =Codex_calc!L84 | M84: =Codex_calc!M84 | ... AO84: =Codex_calc!AO84
C85: =Codex_calc!C85 | D85: =Codex_calc!D85 | AO85: =Codex_calc!AO85
C86: =Codex_calc!C86 | D86: =Codex_calc!D86 | E86: =Codex_calc!E86 | F86: =Codex_calc!F86 | G86: =Codex_calc!G86 | H86: =Codex_calc!H86 | I86: =Codex_calc!I86 | J86: =Codex_calc!J86 | ... AO86: =Codex_calc!AO86
C87: =Codex_calc!C87 | D87: =Codex_calc!D87 | AO87: =Codex_calc!AO87
C88: =Codex_calc!C88 | D88: =Codex_calc!D88 | AO88: =Codex_calc!AO88
C89: =Codex_calc!C89 | D89: =Codex_calc!D89 | E89: =Codex_calc!E89 | F89: =Codex_calc!F89 | G89: =Codex_calc!G89 | H89: =Codex_calc!H89 | I89: =Codex_calc!I89 | J89: =Codex_calc!J89 | ... AO89: =Codex_calc!AO89
C90: * | D90: =Codex_calc!D90 | E90: =Codex_calc!E90 | F90: =Codex_calc!F90 | G90: =Codex_calc!G90 | H90: =Codex_calc!H90 | I90: =Codex_calc!I90 | J90: =Codex_calc!J90 | K90: =Codex_calc!K90 | ... AO90: =Codex_calc!AO90
C91: =Codex_calc!C91 | D91: =Codex_calc!D91 | F91: =Codex_calc!F91 | G91: =Codex_calc!G91 | H91: =Codex_calc!H91 | I91: =Codex_calc!I91 | J91: =Codex_calc!J91 | K91: =Codex_calc!K91 | L91: =Codex_calc!L91 | M91: =Codex_calc!M91 | ... AO91: =Codex_calc!AO91
C92: =Codex_calc!C92 | D92: =Codex_calc!D92 | AO92: =Codex_calc!AO92
C93: =Codex_calc!C93 | D93: =Codex_calc!D93 | E93: =Codex_calc!E93 | F93: =Codex_calc!F93 | G93: =Codex_calc!G93 | H93: =Codex_calc!H93 | I93: =Codex_calc!I93 | J93: =Codex_calc!J93 | ... AO93: =Codex_calc!AO93
C94: =Codex_calc!C94 | D94: =Codex_calc!D94 | F94: =Codex_calc!F94 | G94: =Codex_calc!G94 | H94: =Codex_calc!H94 | I94: =Codex_calc!I94 | J94: =Codex_calc!J94 | K94: =Codex_calc!K94 | L94: =Codex_calc!L94 | M94: =Codex_calc!M94 | ... AO94: =Codex_calc!AO94
C95: =Codex_calc!C95 | D95: =Codex_calc!D95 | AO95: =Codex_calc!AO95
C96: =Codex_calc!C96 | D96: =Codex_calc!D96 | E96: =Codex_calc!E96 | F96: =Codex_calc!F96 | G96: =Codex_calc!G96 | H96: =Codex_calc!H96 | I96: =Codex_calc!I96 | J96: =Codex_calc!J96 | ... AO96: =Codex_calc!AO96
C97: =Codex_calc!C97 | D97: =Codex_calc!D97 | AO97: =Codex_calc!AO97
C98: =Codex_calc!C98 | D98: =Codex_calc!D98 | AO98: =Codex_calc!AO98
C99: =Codex_calc!C99 | D99: =Codex_calc!D99 | E99: =Codex_calc!E99 | F99: =Codex_calc!F99 | G99: =Codex_calc!G99 | H99: =Codex_calc!H99 | I99: =Codex_calc!I99 | J99: =Codex_calc!J99 | ... AO99: =Codex_calc!AO99
C100: * | D100: =Codex_calc!D100 | E100: =Codex_calc!E100 | F100: =Codex_calc!F100 | G100: =Codex_calc!G100 | H100: =Codex_calc!H100 | I100: =Codex_calc!I100 | J100: =Codex_calc!J100 | K100: =Codex_calc!K100 | ... AO100: =Codex_calc!AO100
C101: =Codex_calc!C101 | D101: =Codex_calc!D101 | F101: =Codex_calc!F101 | G101: =Codex_calc!G101 | H101: =Codex_calc!H101 | I101: =Codex_calc!I101 | J101: =Codex_calc!J101 | K101: =Codex_calc!K101 | L101: =Codex_calc!L101 | M101: =Codex_calc!M101 | ... AO101: =Codex_calc!AO101
C102: =Codex_calc!C102 | D102: =Codex_calc!D102 | AO102: =Codex_calc!AO102
C103: =Codex_calc!C103 | D103: =Codex_calc!D103 | E103: =Codex_calc!E103 | F103: =Codex_calc!F103 | G103: =Codex_calc!G103 | H103: =Codex_calc!H103 | I103: =Codex_calc!I103 | J103: =Codex_calc!J103 | ... AO103: =Codex_calc!AO103
C104: =Codex_calc!C104 | D104: =Codex_calc!D104 | F104: =Codex_calc!F104 | G104: =Codex_calc!G104 | H104: =Codex_calc!H104 | I104: =Codex_calc!I104 | J104: =Codex_calc!J104 | K104: =Codex_calc!K104 | L104: =Codex_calc!L104 | M104: =Codex_calc!M104 | ... AO104: =Codex_calc!AO104
C105: =Codex_calc!C105 | D105: =Codex_calc!D105 | AO105: =Codex_calc!AO105
C106: =Codex_calc!C106 | D106: =Codex_calc!D106 | E106: =Codex_calc!E106 | F106: =Codex_calc!F106 | G106: =Codex_calc!G106 | H106: =Codex_calc!H106 | I106: =Codex_calc!I106 | J106: =Codex_calc!J106 | ... AO106: =Codex_calc!AO106
C107: =Codex_calc!C107 | D107: =Codex_calc!D107 | AO107: =Codex_calc!AO107
C108: =Codex_calc!C108 | D108: =Codex_calc!D108 | AO108: =Codex_calc!AO108
C109: =Codex_calc!C109 | D109: =Codex_calc!D109 | E109: =Codex_calc!E109 | F109: =Codex_calc!F109 | G109: =Codex_calc!G109 | H109: =Codex_calc!H109 | I109: =Codex_calc!I109 | J109: =Codex_calc!J109 | ... AO109: =Codex_calc!AO109
F113: =Codex_calc!F81 | G113: =Codex_calc!G81 | H113: =Codex_calc!H81 | I113: =Codex_calc!I81 | J113: =Codex_calc!J81 | K113: =Codex_calc!K81 | L113: =Codex_calc!L81 | M113: =Codex_calc!M81 | ... AN113: =Codex_calc!AN81
F114: =Codex_calc!F84 | G114: =Codex_calc!G84 | H114: =Codex_calc!H84 | I114: =Codex_calc!I84 | J114: =Codex_calc!J84 | K114: =Codex_calc!K84 | L114: =Codex_calc!L84 | M114: =Codex_calc!M84 | ... AN114: =Codex_calc!AN84
F115: =F82/F113 | G115: =G82/G113 | H115: =H82/H113 | I115: =I82/I113 | J115: =J82/J113 | K115: =K82/K113 | L115: =L82/L113 | M115: =M82/M113 | ... AN115: =AN82/AN113
F116: =F102/F101 | G116: =G102/G101 | H116: =H102/H101 | I116: =I102/I101 | J116: =J102/J101 | K116: =K102/K101 | L116: =L102/L101 | M116: =M102/M101 | ... AN116: =AN102/AN101
...

Sheet NOUSEattache--data--from
A1: Cumulative extraction limits (CUM) from USGS economically recoverable reserves
A2: CUM = reserves x conversion to kt x battery share x step multiplier. All values kt of contained metal.
A4: THREE ISSUES FOUND IN THE SUPPLIED RESERVES TABLE
A5: 1. UNIT INCONSISTENCY. Mn (1,700) and Cu (980) are in Mt; Li, Co, Ni and graphite are in kt. Left uncorrected these two would be 1,000x too small. A conversion factor is applied below - check it matches your source.
A6: 2. ROW IS MISSING and takes the residual. Regional entries sum to less than the world total for every material: Ni 57.5% short, Cu 22.8%, Co 18.8%, Li 9.2%, graphite 8.9%. For nickel this is almost entirely Indonesia, the largest holder, which sits in your ROW region. The residual is assigned to ROW below.
A7: 3. MANGANESE OVERSHOOTS. Listed regions sum to 1,718 Mt against a world total of 1,700 Mt (-1.1%). Small, but it means the regional and world figures come from different vintages. ROW residual is floored at zero.
A8: ALSO: Brazil has no row despite holding significant graphite, manganese and nickel reserves - confirm whether it was folded into LatAm. Aluminium is absent entirely; bauxite reserves must be added separately if m_aluminum is to be constrained.
A10: 1. MATERIAL PARAMETERS
A11: Material | B11: Commodity | C11: Prefix | D11: World reserves (as supplied) | E11: Unit supplied | F11: Factor to kt | G11: World reserves (kt) | H11: Battery share | I11: RSV2 multiplier (resources) | J11: RSV3 multiplier (speculative)
A12: Li | B12: m_lithium | C12: MINLi | D12: 30000 | E12: kt | F12: 0.7 | G12: =D12*F12 | H12: 0.87 | I12: 1 | J12: 10 | M12: 2
A13: Co | B13: m_cobalt | C13: MINCo | D13: 11000 | E13: kt | F13: 0.7 | G13: =D13*F13 | H13: 0.759 | I13: 1 | J13: 10 | M13: 1.8
A14: Ni | B14: m_nickel | C14: MINNi | D14: 130000 | E14: kt | F14: 0.7 | G14: =D14*F14 | H14: 0.154 | I14: 1 | J14: 10 | M14: 1.8
A15: Mn | B15: m_manganese | C15: MINMn | D15: 1700 | E15: Mt | F15: 0.7 | G15: =D15*F15 | H15: 0.01 | I15: 1 | J15: 10 | M15: 2
A16: Cu | B16: m_copper | C16: MINCu | D16: 980 | E16: Mt | F16: 0.7 | G16: =D16*F16 | H16: 0.026 | I16: 1 | J16: 10 | M16: 1.8
A17: Gr | B17: m_graphite | C17: MINGr | D17: 290000 | E17: kt | F17: 0.7 | G17: =D17*F17 | H17: 0.917 | I17: 1 | J17: 10 | M17: 2
A18: Battery share is derived from your own 2024 activity data divided by world mine production, so CUM is on the
A19: same scope as the model. RSV2/RSV3 multiples of reserves approximate the USGS resource hierarchy
A20: (reserves -> identified resources -> undiscovered). These two columns are the least well sourced - verify
A21: against USGS resource figures and report results across a range.
A23: 2. RESERVES BY REGION (as supplied, in the unit given above)
A24: Material | B24: Unit | C24: Listed sum | D24: Africa_North | E24: Africa_Other | F24: Australia | G24: Austria | H24: Baltics | I24: BeNeLux | J24: Brazil | K24: China | L24: CroSloven | M24: CzechSlovak | N24: France | O24: Germany | P24: GreeceCyp | Q24: HunRomBul | R24: Iceland | S24: India | T24: Ireland | U24: ItalyMal | V24: Japan | W24: LatAm | X24: MidEast | Y24: NorthAm | Z24: Norway | AA24: Poland | AB24: ROW | AC24: Russia | AD24: SaudiArabia | AE24: SouthAfrica | AF24: SpainPor | AG24: SweFinDen | AH24: Switzerland | AI24: Turkey | AJ24: UK | AK24: Ukraine | AL24: WestBalkans
A25: Li | B25: kt | C25: =SUM(D25:AL25) | D25: 0 | E25: 494 | F25: 7000 | G25: 0 | H25: 0 | I25: 0 | J25: 0 | K25: 3000 | L25: 0 | M25: 0 | N25: 0 | O25: 0 | P25: 0 | Q25: 0 | R25: 0 | S25: 0 | T25: 0 | U25: 0 | V25: 0 | W25: 13690 | X25: 0 | Y25: 3000 | Z25: 0 | AA25: 0 | AB25: =MAX(0,$D$12-(D25+E25+F25+G25+H25+I25+J25+K25+L25+M25+N25+O25+P25+Q25+R25+S25+T25+U25+V25+W25+X25+Y25+Z25+AA25+AC25+AD25+AE25+AF25+AG25+AH25+AI25+AJ25+AK25+AL25)) | AC25: 0 | AD25: 0 | AE25: 0 | AF25: 60 | AG25: 0 | AH25: 0 | AI25: 0 | AJ25: 0 | AK25: 0 | AL25: 0
A26: Co | B26: kt | C26: =SUM(D26:AL26) | D26: 0 | E26: 6100 | F26: 1700 | G26: 0 | H26: 0 | I26: 0 | J26: 0 | K26: 0 | L26: 0 | M26: 0 | N26: 0 | O26: 0 | P26: 0 | Q26: 0 | R26: 0 | S26: 0 | T26: 0 | U26: 0 | V26: 0 | W26: 500 | X26: 0 | Y26: 290 | Z26: 0 | AA26: 0 | AB26: =MAX(0,$D$13-(D26+E26+F26+G26+H26+I26+J26+K26+L26+M26+N26+O26+P26+Q26+R26+S26+T26+U26+V26+W26+X26+Y26+Z26+AA26+AC26+AD26+AE26+AF26+AG26+AH26+AI26+AJ26+AK26+AL26)) | AC26: 250 | AD26: 0 | AE26: 0 | AF26: 0 | AG26: 0 | AH26: 0 | AI26: 91 | AJ26: 0 | AK26: 0 | AL26: 0
A27: Ni | B27: kt | C27: =SUM(D27:AL27) | D27: 0 | E27: 0 | F27: 24000 | G27: 0 | H27: 0 | I27: 0 | J27: 0 | K27: 4400 | L27: 0 | M27: 0 | N27: 0 | O27: 0 | P27: 0 | Q27: 0 | R27: 0 | S27: 0 | T27: 0 | U27: 0 | V27: 0 | W27: 16000 | X27: 0 | Y27: 2510 | Z27: 0 | AA27: 0 | AB27: =MAX(0,$D$14-(D27+E27+F27+G27+H27+I27+J27+K27+L27+M27+N27+O27+P27+Q27+R27+S27+T27+U27+V27+W27+X27+Y27+Z27+AA27+AC27+AD27+AE27+AF27+AG27+AH27+AI27+AJ27+AK27+AL27)) | AC27: 8300 | AD27: 0 | AE27: 0 | AF27: 0 | AG27: 0 | AH27: 0 | AI27: 0 | AJ27: 0 | AK27: 0 | AL27: 0
A28: Mn | B28: kt | C28: =SUM(D28:AL28) | D28: =D32*1000 | E28: =E32*1000 | F28: =F32*1000 | G28: =G32*1000 | H28: =H32*1000 | I28: =I32*1000 | J28: =J32*1000 | K28: =K32*1000 | ... AL28: =AL32*1000
A29: Cu | B29: kt | C29: =SUM(D29:AL29) | D29: =D33*1000 | E29: =E33*1000 | F29: =F33*1000 | G29: =G33*1000 | H29: =H33*1000 | I29: =I33*1000 | J29: =J33*1000 | K29: =K33*1000 | ... AL29: =AL33*1000
A30: Gr | B30: kt | C30: =SUM(D30:AL30) | D30: 0 | E30: 70000 | F30: 0 | G30: 0 | H30: 0 | I30: 0 | J30: 0 | K30: 81000 | L30: 0 | M30: 0 | N30: 0 | O30: 0 | P30: 0 | Q30: 0 | R30: 0 | S30: 8600 | T30: 0 | U30: 0 | V30: 0 | W30: 77100 | X30: 0 | Y30: 5900 | Z30: 600 | AA30: 0 | AB30: =MAX(0,$D$17-(D30+E30+F30+G30+H30+I30+J30+K30+L30+M30+N30+O30+P30+Q30+R30+S30+T30+U30+V30+W30+X30+Y30+Z30+AA30+AC30+AD30+AE30+AF30+AG30+AH30+AI30+AJ30+AK30+AL30)) | AC30: 14000 | AD30: 0 | AE30: 0 | AF30: 0 | AG30: 0 | AH30: 0 | AI30: 6900 | AJ30: 0 | AK30: 0 | AL30: 0
A31: ROW cell is a formula: world total minus all other regions. It is yellow because it is inferred, not sourced.
A32: 'Listed sum' should now equal the world reserves in section 1 for every material. | D32: 0 | E32: 74 | F32: 500 | G32: 0 | H32: 0 | I32: 0 | J32: 0 | K32: 280 | L32: 0 | M32: 0 | N32: 0 | O32: 0 | P32: 0 | Q32: 0 | R32: 0 | S32: 34 | T32: 0 | U32: 0 | V32: 0 | W32: 270 | X32: 0 | Y32: 0 | Z32: 0 | AA32: 0 | AB32: =MAX(0,$D$15-(D32+E32+F32+G32+H32+I32+J32+K32+L32+M32+N32+O32+P32+Q32+R32+S32+T32+U32+V32+W32+X32+Y32+Z32+AA32+AC32+AD32+AE32+AF32+AG32+AH32+AI32+AJ32+AK32+AL32)) | AC32: 0 | AD32: 0 | AE32: 560 | AF32: 0 | AG32: 0 | AH32: 0 | AI32: 0 | AJ32: 0 | AK32: 0 | AL32: 0
D33: 0 | E33: 101 | F33: 100 | G33: 0 | H33: 0 | I33: 0 | J33: 0 | K33: 41 | L33: 0 | M33: 0 | N33: 0 | O33: 0 | P33: 0 | Q33: 0 | R33: 0 | S33: 2.2 | T33: 0 | U33: 0 | V33: 0 | W33: 290 | X33: 0 | Y33: 108.3 | Z33: 0 | AA33: 34 | AB33: =MAX(0,$D$16-(D33+E33+F33+G33+H33+I33+J33+K33+L33+M33+N33+O33+P33+Q33+R33+S33+T33+U33+V33+W33+X33+Y33+Z33+AA33+AC33+AD33+AE33+AF33+AG33+AH33+AI33+AJ33+AK33+AL33)) | AC33: 80 | AD33: 0 | AE33: 0 | AF33: 0 | AG33: 0 | AH33: 0 | AI33: 0 | AJ33: 0 | AK33: 0 | AL33: 0
A34: 3. CUM TABLE - paste into VEDA
A35: TFM_INS
A36: pset_pn | B36: Attribute | C36: cset_cn | D36: Africa_North | E36: Africa_Other | F36: Australia | G36: Austria | H36: Baltics | I36: BeNeLux | J36: Brazil | K36: China | L36: CroSloven | M36: CzechSlovak | N36: France | O36: Germany | P36: GreeceCyp | Q36: HunRomBul | R36: Iceland | S36: India | T36: Ireland | U36: ItalyMal | V36: Japan | W36: LatAm | X36: MidEast | Y36: NorthAm | Z36: Norway | AA36: Poland | AB36: ROW | AC36: Russia | AD36: SaudiArabia | AE36: SouthAfrica | AF36: SpainPor | AG36: SweFinDen | AH36: Switzerland | AI36: Turkey | AJ36: UK | AK36: Ukraine | AL36: WestBalkans
A37: MINLiRSV1 | B37: CUM | D37: =D25*$F$12*$H$12 | E37: =E25*$F$12*$H$12 | F37: =F25*$F$12*$H$12 | G37: =G25*$F$12*$H$12 | H37: =H25*$F$12*$H$12 | I37: =I25*$F$12*$H$12 | J37: =J25*$F$12*$H$12 | K37: =K25*$F$12*$H$12 | ... AL37: =AL25*$F$12*$H$12
A38: MINLiRSV2 | B38: CUM | D38: =D25*$F$12*$H$12*$I$12 | E38: =E25*$F$12*$H$12*$I$12 | F38: =F25*$F$12*$H$12*$I$12 | G38: =G25*$F$12*$H$12*$I$12 | H38: =H25*$F$12*$H$12*$I$12 | I38: =I25*$F$12*$H$12*$I$12 | J38: =J25*$F$12*$H$12*$I$12 | K38: =K25*$F$12*$H$12*$I$12 | ... AL38: =AL25*$F$12*$H$12*$I$12
A39: MINLiRSV3 | B39: CUM | D39: =D25*$F$12*$H$12*$J$12 | E39: =E25*$F$12*$H$12*$J$12 | F39: =F25*$F$12*$H$12*$J$12 | G39: =G25*$F$12*$H$12*$J$12 | H39: =H25*$F$12*$H$12*$J$12 | I39: =I25*$F$12*$H$12*$J$12 | J39: =J25*$F$12*$H$12*$J$12 | K39: =K25*$F$12*$H$12*$J$12 | ... AL39: =AL25*$F$12*$H$12*$J$12
A41: MINCoRSV1 | B41: CUM | D41: =D26*$F$13*$H$13 | E41: =E26*$F$13*$H$13 | F41: =F26*$F$13*$H$13 | G41: =G26*$F$13*$H$13 | H41: =H26*$F$13*$H$13 | I41: =I26*$F$13*$H$13 | J41: =J26*$F$13*$H$13 | K41: =K26*$F$13*$H$13 | ... AL41: =AL26*$F$13*$H$13
A42: MINCoRSV2 | B42: CUM | D42: =D26*$F$13*$H$13*$I$13 | E42: =E26*$F$13*$H$13*$I$13 | F42: =F26*$F$13*$H$13*$I$13 | G42: =G26*$F$13*$H$13*$I$13 | H42: =H26*$F$13*$H$13*$I$13 | I42: =I26*$F$13*$H$13*$I$13 | J42: =J26*$F$13*$H$13*$I$13 | K42: =K26*$F$13*$H$13*$I$13 | ... AL42: =AL26*$F$13*$H$13*$I$13
A43: MINCoRSV3 | B43: CUM | D43: =D26*$F$13*$H$13*$J$13 | E43: =E26*$F$13*$H$13*$J$13 | F43: =F26*$F$13*$H$13*$J$13 | G43: =G26*$F$13*$H$13*$J$13 | H43: =H26*$F$13*$H$13*$J$13 | I43: =I26*$F$13*$H$13*$J$13 | J43: =J26*$F$13*$H$13*$J$13 | K43: =K26*$F$13*$H$13*$J$13 | ... AL43: =AL26*$F$13*$H$13*$J$13
A45: MINNiRSV1 | B45: CUM | D45: =D27*$F$14*$H$14 | E45: =E27*$F$14*$H$14 | F45: =F27*$F$14*$H$14 | G45: =G27*$F$14*$H$14 | H45: =H27*$F$14*$H$14 | I45: =I27*$F$14*$H$14 | J45: =J27*$F$14*$H$14 | K45: =K27*$F$14*$H$14 | ... AL45: =AL27*$F$14*$H$14
A46: MINNiRSV2 | B46: CUM | D46: =D27*$F$14*$H$14*$I$14 | E46: =E27*$F$14*$H$14*$I$14 | F46: =F27*$F$14*$H$14*$I$14 | G46: =G27*$F$14*$H$14*$I$14 | H46: =H27*$F$14*$H$14*$I$14 | I46: =I27*$F$14*$H$14*$I$14 | J46: =J27*$F$14*$H$14*$I$14 | K46: =K27*$F$14*$H$14*$I$14 | ... AL46: =AL27*$F$14*$H$14*$I$14
A47: MINNiRSV3 | B47: CUM | D47: =D27*$F$14*$H$14*$J$14 | E47: =E27*$F$14*$H$14*$J$14 | F47: =F27*$F$14*$H$14*$J$14 | G47: =G27*$F$14*$H$14*$J$14 | H47: =H27*$F$14*$H$14*$J$14 | I47: =I27*$F$14*$H$14*$J$14 | J47: =J27*$F$14*$H$14*$J$14 | K47: =K27*$F$14*$H$14*$J$14 | ... AL47: =AL27*$F$14*$H$14*$J$14
A49: MINMnRSV1 | B49: CUM | D49: =D28*$F$15*$H$15 | E49: =E28*$F$15*$H$15 | F49: =F28*$F$15*$H$15 | G49: =G28*$F$15*$H$15 | H49: =H28*$F$15*$H$15 | I49: =I28*$F$15*$H$15 | J49: =J28*$F$15*$H$15 | K49: =K28*$F$15*$H$15 | ... AL49: =AL28*$F$15*$H$15
A50: MINMnRSV2 | B50: CUM | D50: =D28*$F$15*$H$15*$I$15 | E50: =E28*$F$15*$H$15*$I$15 | F50: =F28*$F$15*$H$15*$I$15 | G50: =G28*$F$15*$H$15*$I$15 | H50: =H28*$F$15*$H$15*$I$15 | I50: =I28*$F$15*$H$15*$I$15 | J50: =J28*$F$15*$H$15*$I$15 | K50: =K28*$F$15*$H$15*$I$15 | ... AL50: =AL28*$F$15*$H$15*$I$15
A51: MINMnRSV3 | B51: CUM | D51: =D28*$F$15*$H$15*$J$15 | E51: =E28*$F$15*$H$15*$J$15 | F51: =F28*$F$15*$H$15*$J$15 | G51: =G28*$F$15*$H$15*$J$15 | H51: =H28*$F$15*$H$15*$J$15 | I51: =I28*$F$15*$H$15*$J$15 | J51: =J28*$F$15*$H$15*$J$15 | K51: =K28*$F$15*$H$15*$J$15 | ... AL51: =AL28*$F$15*$H$15*$J$15
A53: MINCuRSV1 | B53: CUM | D53: =D29*$F$16*$H$16 | E53: =E29*$F$16*$H$16 | F53: =F29*$F$16*$H$16 | G53: =G29*$F$16*$H$16 | H53: =H29*$F$16*$H$16 | I53: =I29*$F$16*$H$16 | J53: =J29*$F$16*$H$16 | K53: =K29*$F$16*$H$16 | ... AL53: =AL29*$F$16*$H$16
A54: MINCuRSV2 | B54: CUM | D54: =D29*$F$16*$H$16*$I$16 | E54: =E29*$F$16*$H$16*$I$16 | F54: =F29*$F$16*$H$16*$I$16 | G54: =G29*$F$16*$H$16*$I$16 | H54: =H29*$F$16*$H$16*$I$16 | I54: =I29*$F$16*$H$16*$I$16 | J54: =J29*$F$16*$H$16*$I$16 | K54: =K29*$F$16*$H$16*$I$16 | ... AL54: =AL29*$F$16*$H$16*$I$16
A55: MINCuRSV3 | B55: CUM | D55: =D29*$F$16*$H$16*$J$16 | E55: =E29*$F$16*$H$16*$J$16 | F55: =F29*$F$16*$H$16*$J$16 | G55: =G29*$F$16*$H$16*$J$16 | H55: =H29*$F$16*$H$16*$J$16 | I55: =I29*$F$16*$H$16*$J$16 | J55: =J29*$F$16*$H$16*$J$16 | K55: =K29*$F$16*$H$16*$J$16 | ... AL55: =AL29*$F$16*$H$16*$J$16
A57: MINGrRSV1 | B57: CUM | D57: =D30*$F$17*$H$17 | E57: =E30*$F$17*$H$17 | F57: =F30*$F$17*$H$17 | G57: =G30*$F$17*$H$17 | H57: =H30*$F$17*$H$17 | I57: =I30*$F$17*$H$17 | J57: =J30*$F$17*$H$17 | K57: =K30*$F$17*$H$17 | ... AL57: =AL30*$F$17*$H$17
A58: MINGrRSV2 | B58: CUM | D58: =D30*$F$17*$H$17*$I$17 | E58: =E30*$F$17*$H$17*$I$17 | F58: =F30*$F$17*$H$17*$I$17 | G58: =G30*$F$17*$H$17*$I$17 | H58: =H30*$F$17*$H$17*$I$17 | I58: =I30*$F$17*$H$17*$I$17 | J58: =J30*$F$17*$H$17*$I$17 | K58: =K30*$F$17*$H$17*$I$17 | ... AL58: =AL30*$F$17*$H$17*$I$17
A59: MINGrRSV3 | B59: CUM | D59: =D30*$F$17*$H$17*$J$17 | E59: =E30*$F$17*$H$17*$J$17 | F59: =F30*$F$17*$H$17*$J$17 | G59: =G30*$F$17*$H$17*$J$17 | H59: =H30*$F$17*$H$17*$J$17 | I59: =I30*$F$17*$H$17*$J$17 | J59: =J30*$F$17*$H$17*$J$17 | K59: =K30*$F$17*$H$17*$J$17 | ... AL59: =AL30*$F$17*$H$17*$J$17
A62: 4. NOTES
A63: CUM maps to ACT_CUM in TIMES and needs a period range - enter year '0' for the whole horizon in VEDA, or the
A64: limit will not bind.
A65: Aluminium (m_aluminum) has no row here because the supplied table contains no bauxite reserves. Either add them
A66: or leave m_aluminum without a cumulative limit and say so in the SI.
A67: Regions showing zero hold no economically recoverable reserves in the supplied table. Zero CUM means the process
A68: exists but can never produce - this is intended, and is not the same as leaving the cell blank.
A69: Pair CUM with BNDACT (annual capacity, anchored to observed 2024 output) and a GROWTH constraint; a cumulative
A70: limit alone still permits an unrealistic production spike in a single period.

Sheet Codex_sources
A1: Auditable source parameters for redesigned mining supply curves
A2: Units: BNDACT kt/yr; CUM kt; COST million USD/kt. Formulas in Codex_calc link to these rows.
A4: Material | B4: Prefix | C4: Commodity | D4: ScopeFactor | E4: Scope numerator kt/yr | F4: World production kt/yr | G4: World reserves kt | H4: Resource total / midpoint kt | I4: Extra high/undiscovered kt | J4: RSV1 multiplier | K4: RSV2 multiplier | L4: RSV3 multiplier | M4: Cost RSV1 | N4: Cost RSV2 | O4: Cost RSV3 | P4: Cost source | Q4: Quantity source | R4: Notes
A5: Li | B5: MINLi | C5: m_lithium | D5: 0.88 | F5: 290 | G5: 37000 | H5: 150000 | J5: stage from deposit data | K5: stage from deposit data | L5: stage from deposit data | M5: 13.86 | N5: 22.45 | O5: 27.69 | P5: Busch et al. 2025 Supplementary Data S2; project extraction costs converted to MUSD/kt Li; RSV1/RSV2/RSV3 use approximately p25/p75/p90. | Q5: Busch et al. 2025 Supplementary Data S2 for deposit reserves/resources/capacity; USGS MCS 2026 for 88% battery end-use share. | R5: CUM uses deposit reserve/demonstrated/inferred stages. BNDACT uses 2030 deposit capacity split 1:2 across RSV1/RSV2.
A6: Ni | B6: MINNi | C6: m_nickel | D6: =E6/F6 | E6: 555 | F6: 3900 | G6: 140000 | H6: 350000 | I6: 0 | J6: 1 | K6: =(H6-G6)/(2*G6) | L6: =(H6-G6)/(2*G6) | M6: 14.288 | N6: 23.139 | O6: =N6*1.1 | P6: Peiseler et al. 2024 Nature Communications Source Data Fig. 4 all-in-cost Q1/Q3/max. | Q6: USGS MCS 2026 nickel production/reserves/resources. | R6: Seabed nickel resources are not included in the base curve.
A7: Co | B7: MINCo | C7: m_cobalt | D7: =E7/F7 | E7: 220.172 | F7: 310 | G7: 12000 | H7: 25000 | I7: 0 | J7: 1 | K7: =(H7-G7)/(2*G7) | L7: =(H7-G7)/(2*G7) | M7: 29.844 | N7: 42.509 | O7: =N7*1.1 | P7: Peiseler et al. 2024 Nature Communications Source Data Fig. 4 all-in-cost Q1/Q3/max. | Q7: USGS MCS 2026 cobalt production/reserves/resources. | R7: Seafloor cobalt is excluded; cobalt by-product coupling is not represented here.
A8: Mn | B8: MINMn | C8: m_manganese | D8: =E8/F8 | E8: 202 | F8: 20000 | G8: 1800000 | H8: 17000000 | I8: 0 | J8: 1 | K8: =(H8-G8)/(2*G8) | L8: =(H8-G8)/(2*G8) | M8: =4.5*100/1000 | N8: =M8*3 | O8: =N8*1.1 | P8: USGS MCS 2026 manganese ore price, 4.50 USD/metric ton unit Mn; tier multipliers are assumptions. | Q8: USGS MCS 2026 manganese production/reserves; USGS Professional Paper 1802-L for 17 billion t land resources. | R8: Cost is a price proxy, not mine-level OPEX.
A9: Al | B9: MINAl | C9: m_aluminum | D9: =E9/F9 | E9: 1486.28 | F9: 74000 | G9: 7250000 | H9: 16250000 | I9: 2500000 | J9: 1 | K9: =(H9-G9)/G9 | L9: =I9/G9 | M9: =180/100*2204.62/1000 | N9: =M9*3 | O9: =N9*1.1 | P9: USGS MCS 2026 aluminum ingot U.S. market spot price, 180 cents/lb; tier multipliers are assumptions. | Q9: USGS MCS 2026 aluminum production; bauxite reserves/resources converted using 4 t bauxite = 1 t Al. | R9: CUM is bauxite-derived aluminum equivalent, while BNDACT uses primary aluminum smelter production.
A10: Cu | B10: MINCu | C10: m_copper | D10: =E10/F10 | E10: 570 | F10: 23000 | G10: 980000 | H10: 1500000 | I10: 3500000 | J10: 1 | K10: =(H10-G10)/G10 | L10: =I10/G10 | M10: =440/100*2204.62/1000 | N10: =M10*3 | O10: =N10*1.1 | P10: USGS MCS 2026 LME grade A cash copper price, 440 cents/lb; tier multipliers are assumptions. | Q10: USGS MCS 2026 copper production/reserves; USGS global copper resource assessment cited by MCS for identified/undiscovered resources. | R10: Copper RSV3 represents undiscovered resources allocated by current reserve geography.
A11: Gr | B11: MINGr | C11: m_graphite | D11: =E11/F11 | E11: 1467.63 | F11: 1800 | G11: 310000 | H11: 800000 | I11: 0 | J11: 1 | K11: =(H11-G11)/(2*G11) | L11: =(H11-G11)/(2*G11) | M11: 1 | N11: 2.6 | O11: =N11*1.1 | P11: USGS MCS 2026 natural graphite import values for flake/lump; Benchmark 2025 article for battery-grade anode graphite high-cost proxy. | Q11: USGS MCS 2026 natural graphite production/reserves/resources. | R11: Synthetic graphite is not a mined reserve; RSV3 cost is a battery-grade anode proxy.
A14: Primary source links
A15: USGS MCS 2026 | B15: https://doi.org/10.3133/mcs2026 | M15: 13.86 | N15: 22.45 | O15: 27.69
A16: Busch et al. 2025 | B16: https://doi.org/10.1038/s41893-025-01561-5 | M16: 14.288 | N16: 23.139 | O16: 73.349
A17: Busch et al. 2025 data/code | B17: https://doi.org/10.5281/zenodo.14532951 | M17: 29.844 | N17: 42.509 | O17: 94.182
A18: Peiseler et al. 2024 | B18: https://doi.org/10.1038/s41467-024-54634-y | M18: 0.45 | N18: 1.35 | O18: 2.25
A19: Benchmark graphite article | B19: https://source.benchmarkminerals.com/article/price-correction-benchmark-to-continue-publication-of-previous-high-energy-anode-grades-and-launch-new-high-charging-rate-for-ev-variants-reversing-15-october-change-to-specifications | M19: 3.968316 | N19: 11.904948 | O19: 19.84158
A20: USGS manganese PP1802-L | B20: https://doi.org/10.3133/pp1802L | M20: 9.700328 | N20: 29.100984 | O20: 48.50164
M21: 1 | N21: 2.6 | O21: 7.245

Sheet Codex_USGS_raw
A1: Material | B1: Country | C1: TIMES region | D1: Production kt/yr | E1: Reserves kt | F1: Source | G1: Notes
A2: Ni | B2: United States | C2: NorthAm | D2: 10 | E2: 340 | F2: USGS Mineral Commodity Summaries 2026; individual commodity chapters.
A3: Ni | B3: Australia | C3: Australia | D3: 45 | E3: 25000 | F3: USGS Mineral Commodity Summaries 2026; individual commodity chapters.
A4: Ni | B4: Brazil | C4: Brazil | D4: 70 | E4: 16000 | F4: USGS Mineral Commodity Summaries 2026; individual commodity chapters.
A5: Ni | B5: Canada | C5: NorthAm | D5: 140 | E5: 2200 | F5: USGS Mineral Commodity Summaries 2026; individual commodity chapters.
A6: Ni | B6: China | C6: China | D6: 120 | E6: 4400 | F6: USGS Mineral Commodity Summaries 2026; individual commodity chapters.
A7: Ni | B7: Indonesia | C7: ROW | D7: 2600 | E7: 62000 | F7: USGS Mineral Commodity Summaries 2026; individual commodity chapters.
A8: Ni | B8: New Caledonia | C8: ROW | D8: 140 | E8: 7100 | F8: USGS Mineral Commodity Summaries 2026; individual commodity chapters.
A9: Ni | B9: Philippines | C9: ROW | D9: 270 | E9: 4800 | F9: USGS Mineral Commodity Summaries 2026; individual commodity chapters.
A10: Ni | B10: Russia | C10: Russia | D10: 200 | E10: 8300 | F10: USGS Mineral Commodity Summaries 2026; individual commodity chapters.
A11: Ni | B11: Other countries | C11: ROW | D11: 290 | E11: 9100 | F11: USGS Mineral Commodity Summaries 2026; individual commodity chapters.
A12: Co | B12: United States | C12: NorthAm | D12: 0.3 | E12: 70 | F12: USGS Mineral Commodity Summaries 2026; individual commodity chapters.
A13: Co | B13: Australia | C13: Australia | D13: 3.7 | E13: 1700 | F13: USGS Mineral Commodity Summaries 2026; individual commodity chapters.
... A71: Gr | B71: Vietnam | C71: ROW | D71: 0.5 | E71: 9700 | F71: USGS Mineral Commodity Summaries 2026; individual commodity chapters.
A72: Al | B72: United States | C72: NorthAm | D72: 660 | E72: 5000 | F72: USGS Mineral Commodity Summaries 2026; individual commodity chapters. | G72: Production is primary Al smelter; reserves are bauxite/4.
A73: Al | B73: Australia | C73: Australia | D73: 1500 | E73: 925000 | F73: USGS Mineral Commodity Summaries 2026; individual commodity chapters. | G73: Australia bauxite reserve is 3.7 billion t in USGS MCS 2026; converted using 4 t bauxite = 1 t Al.
A74: Al | B74: Bahrain | C74: MidEast | D74: 1600 | E74: 0 | F74: USGS Mineral Commodity Summaries 2026; individual commodity chapters.
A75: Al | B75: Brazil | C75: Brazil | D75: 1200 | E75: 425000 | F75: USGS Mineral Commodity Summaries 2026; individual commodity chapters.
A76: Al | B76: Canada | C76: NorthAm | D76: 3300 | E76: 0 | F76: USGS Mineral Commodity Summaries 2026; individual commodity chapters.
A77: Al | B77: China | C77: China | D77: 45000 | E77: 177500 | F77: USGS Mineral Commodity Summaries 2026; individual commodity chapters.
A78: Al | B78: Greece | C78: GreeceCyp | D78: 0 | E78: 0 | F78: USGS Mineral Commodity Summaries 2026; individual commodity chapters.
A79: Al | B79: Guinea | C79: Africa_Other | D79: 0 | E79: 1850000 | F79: USGS Mineral Commodity Summaries 2026; individual commodity chapters.
A80: Al | B80: Iceland | C80: Iceland | D80: 750 | E80: 0 | F80: USGS Mineral Commodity Summaries 2026; individual commodity chapters.
A81: Al | B81: India | C81: India | D81: 4200 | E81: 162500 | F81: USGS Mineral Commodity Summaries 2026; individual commodity chapters.
A82: Al | B82: Indonesia | C82: ROW | D82: 0 | E82: 725000 | F82: USGS Mineral Commodity Summaries 2026; individual commodity chapters.
A83: Al | B83: Ireland | C83: Ireland | D83: 0 | E83: 0 | F83: USGS Mineral Commodity Summaries 2026; individual commodity chapters.
A84: Al | B84: Jamaica | C84: LatAm | D84: 0 | E84: 500000 | F84: USGS Mineral Commodity Summaries 2026; individual commodity chapters.
A85: Al | B85: Kazakhstan | C85: ROW | D85: 0 | E85: 40000 | F85: USGS Mineral Commodity Summaries 2026; individual commodity chapters.
... A94: Al | B94: Other countries | C94: ROW | D94: 7000 | E94: 1325000 | F94: USGS Mineral Commodity Summaries 2026; individual commodity chapters.

Sheet Codex_Li_Busch
A1: Source row in Data S2 | B1: Deposit | C1: Country | D1: TIMES region | E1: Resource type | F1: Resource total kt Li | G1: Reserve kt Li | H1: Demonstrated kt Li | I1: Inferred kt Li | J1: 2030 capacity kt Li/yr | K1: Extraction Cost Original | L1: Extraction Cost Unit | M1: Inflation Adjustment 2022 | N1: Source workbook
A2: 6 | B2: Salar de Atacama (SQM) | C2: Chile | D2: LatAm | E2: Brine | F2: 10800 | G2: 360 | H2: 7840 | I2: 2600 | J2: 39.451437 | K2: 3990 | L2: USD/tonne LCE | M2: 1 | N2: Busch et al. 2025 Supplementary Data S2
A3: 7 | B3: Salar de Uyuni | C3: Bolivia | D3: LatAm | E3: Brine | F3: 10206.52 | G3: 5400 | H3: 4806.52 | I3: 0 | J3: 9.3931993 | M3: 1.1183216 | N3: Busch et al. 2025 Supplementary Data S2
A4: 8 | B4: Salton Sea (All) | C4: United States | D4: NorthAm | E4: Brine | F4: 6760 | G4: 0 | H4: 3360 | I4: 3400 | J4: 0 | M4: 0.9199632 | N4: Busch et al. 2025 Supplementary Data S2
A5: 9 | B5: Upper Rhine Valley | C5: Germany | D5: Germany | E5: Brine | F5: 5210.2604 | G5: 106.8993 | H5: 2006.4754 | I5: 3096.8858 | J5: 3.9676874 | K5: 4223.1 | L5: USD/tonne LHM (LiOH.H2O) | M5: 0.9199632 | N5: Busch et al. 2025 Supplementary Data S2
A6: 10 | B6: Cauchari | C6: Argentina | D6: LatAm | E6: Brine | F6: 4617 | G6: 682.92 | H6: 3046.78 | I6: 887.3 | J6: 7.5145595 | K6: 3579 | L6: USD/tonne LCE | M6: 1.1183216 | N6: Busch et al. 2025 Supplementary Data S2
A7: 11 | B7: Titan | C7: Tanzania | D7: Africa_Other | E7: Volcano-Sedimentary | F7: 4426 | G7: 0 | H7: 0 | I7: 4426 | J7: 0 | M7: 0.9199632 | N7: Busch et al. 2025 Supplementary Data S2
A8: 12 | B8: Salar de Olaroz (Allkem) | C8: Argentina | D8: LatAm | E8: Brine | F8: 4250 | G8: 0 | H8: 2890 | I8: 1360 | J8: 7.9842194 | K8: 4149 | L8: USD/tonne LCE | M8: 0.9199632 | N8: Busch et al. 2025 Supplementary Data S2
A9: 13 | B9: McDermitt | C9: United States | D9: NorthAm | E9: Volcano-Sedimentary | F9: 4039.2528 | G9: 0 | H9: 2085.3817 | I9: 1953.8711 | J9: 0 | M9: 0.9199632 | N9: Busch et al. 2025 Supplementary Data S2
A10: 14 | B10: Thacker Pass | C10: United States | D10: NorthAm | E10: Volcano-Sedimentary | F10: 3588.3595 | G10: 695.12723 | H10: 2329.6156 | I10: 563.61668 | J10: 14.277663 | K10: 7198 | L10: USD/tonne LCE | M10: 1 | N10: Busch et al. 2025 Supplementary Data S2
A11: 15 | B11: Bonnie Claire | C11: United States | D11: NorthAm | E11: Hard Rock | F11: 3452 | G11: 0 | H11: 0 | I11: 3452 | J11: 6.0680068 | K11: 5974 | L11: USD/tonne LCE | M11: 1.047 | N11: Busch et al. 2025 Supplementary Data S2
A12: 16 | B12: Manono-Kitotolo | C12: DR Congo | D12: Africa_Other | E12: Hard Rock | F12: 3065.8635 | G12: 682.85141 | H12: 1378.9418 | I12: 1004.0703 | J12: 19.512681 | K12: 346 | L12: USD/tonne of SC6 | M12: 1.080504 | N12: Busch et al. 2025 Supplementary Data S2
A13: 17 | B13: Salar del Hombre Muerto (POSCO) | C13: Argentina | D13: LatAm | E13: Brine | F13: 2539.4689 | G13: 2539.4689 | H13: 0 | I13: 0 | J13: 0 | K13: 3650 | L13: USD/tonne LCE | M13: 0.9199632 | N13: Busch et al. 2025 Supplementary Data S2
A14: 18 | B14: Greenbushes | C14: Australia | D14: Australia | E14: Hard Rock | F14: 2509.8273 | G14: 1668.573 | H14: 348.4943 | I14: 492.76005 | J14: 70.803119 | K14: 233.1193 | L14: USD2022/ t concentrate SC6 | M14: 1 | N14: Busch et al. 2025 Supplementary Data S2
A15: 19 | B15: Salar del Hombre Muerto (Livent) | C15: Argentina | D15: LatAm | E15: Brine | F15: 2220 | G15: 731 | H15: 597 | I15: 892 | J15: 18.786399 | K15: 4700 | L15: USD/tonne LCE | M15: 0.9199632 | N15: Busch et al. 2025 Supplementary Data S2
A16: 20 | B16: Pilgangoora | C16: Australia | D16: Australia | E16: Hard Rock | F16: 2210.534 | G16: 1184.0643 | H16: 1026.4697 | I16: 0 | J16: 26.481495 | K16: 931 | L16: USD2022/ t spodumene at 5.3% | M16: 0.9199632 | N16: Busch et al. 2025 Supplementary Data S2
A17: 21 | B17: Qaidam Basin (All Projects) | C17: China | D17: China | E17: Brine | F17: 2021.4625 | G17: 0 | H17: 0 | I17: 2021.4625 | J17: 11.37 | M17: 0.9199632 | N17: Busch et al. 2025 Supplementary Data S2
A18: 22 | B18: Kachi | C18: Argentina | D18: LatAm | E18: Brine | F18: 1991.4456 | G18: 117.4 | H18: 1254.0672 | I18: 619.97834 | J18: 6.5752395 | K18: 6047 | L18: USD/tonne LCE | M18: 0.9199632 | N18: Busch et al. 2025 Supplementary Data S2
A19: 23 | B19: Centenario Ratones | C19: Argentina | D19: LatAm | E19: Brine | F19: 1867.0742 | G19: 208.8 | H19: 777.34131 | I19: 880.93286 | J19: 4.5087357 | K19: 3500 | L19: USD/tonne LCE | M19: 1.080504 | N19: Busch et al. 2025 Supplementary Data S2
A20: 24 | B20: TLC | C20: United States | D20: NorthAm | E20: Volcano-Sedimentary | F20: 1660.04 | G20: 0 | H20: 0 | I20: 1660.04 | J20: 6.8570355 | M20: 1 | N20: Busch et al. 2025 Supplementary Data S2
A21: 25 | B21: Salar del Rincon (Rio Tinto) | C21: Argentina | D21: LatAm | E21: Brine | F21: 1559.3395 | G21: 225.44667 | H21: 432.10612 | I21: 901.78668 | J21: 9.3931993 | K21: 2968 | L21: USD/tonne LCE | M21: 0.9199632 | N21: Busch et al. 2025 Supplementary Data S2
A22: 26 | B22: Mariana | C22: Argentina | D22: LatAm | E22: Brine | F22: 1525.5225 | G22: 0 | H22: 0 | I22: 1525.5225 | J22: 3.1936878 | M22: 1 | N22: Busch et al. 2025 Supplementary Data S2
A23: 27 | B23: Salar de Atacama (Albemarle) | C23: Chile | D23: LatAm | E23: Brine | F23: 1491 | G23: 647 | H23: 712 | I23: 132 | J23: 15.780575 | K23: 3552 | L23: USD/tonne LCE | M23: 0.9199632 | N23: Busch et al. 2025 Supplementary Data S2
A24: 28 | B24: Wodgina | C24: Australia | D24: Australia | E24: Hard Rock | F24: 1408.9686 | G24: 825.56735 | H24: 246.11923 | I24: 337.28207 | J24: 20.665039 | M24: 1.1585812 | N24: Busch et al. 2025 Supplementary Data S2
A25: 29 | B25: Cinovec | C25: Czech Republic | D25: CzechSlovak | E25: Hard Rock | F25: 1388.3757 | G25: 0 | H25: 851.06118 | I25: 537.31456 | J25: 4.8581627 | K25: 610.78652 | L25: USD/tonne SC 6% | M25: 0.9199632 | N25: Busch et al. 2025 Supplementary Data S2
A26: 30 | B26: Clayton Valley (Century) | C26: United States | D26: NorthAm | E26: Volcano-Sedimentary | F26: 1359.5 | G26: 240.9 | H26: 939 | I26: 179.6 | J26: 5.1474732 | K26: 3387 | L26: USD/tonne LCE | M26: 1.080504 | N26: Busch et al. 2025 Supplementary Data S2
A27: 31 | B27: Sonora | C27: Mexico | D27: NorthAm | E27: Volcano-Sedimentary | F27: 1353.2436 | G27: 391.33785 | H27: 447.1359 | I27: 514.7699 | J27: 3.7572797 | K27: 2126 | L27: USD/tonne LCE | M27: 1.2291284 | N27: Busch et al. 2025 Supplementary Data S2
A28: 32 | B28: Sal de Vida | C28: Argentina | D28: LatAm | E28: Brine | F28: 1340 | G28: 467 | H28: 753 | I28: 120 | J28: 8.3888785 | K28: 4529 | L28: USD/tonne LCE | M28: 0.9199632 | N28: Busch et al. 2025 Supplementary Data S2
A29: 33 | B29: Mt. Holland/Earl Grey | C29: Australia | D29: Australia | E29: Hard Rock | F29: 1320.5046 | G29: 656.37349 | H29: 576.47523 | I29: 87.655823 | J29: 8.2966372 | K29: 155.4 | L29: USD/t concentrate SC5.5 | M29: 1.1183216 | N29: Busch et al. 2025 Supplementary Data S2
A30: 34 | B30: Tres Quebradas | C30: Argentina | D30: LatAm | E30: Brine | F30: 1315.1056 | G30: 244.23389 | H30: 507.25501 | I30: 563.61668 | J30: 3.7572797 | K30: 2914 | L30: USD/tonne LCE | M30: 1.047 | N30: Busch et al. 2025 Supplementary Data S2
A31: 35 | B31: Hombre Muerto West (Galan) | C31: Argentina | D31: LatAm | E31: Brine | F31: 1237 | G31: 70.2 | H31: 1004.8 | I31: 162 | J31: 0 | K31: 3963 | L31: USD/tonne LCE | M31: 0.9199632 | N31: Busch et al. 2025 Supplementary Data S2
A32: 36 | B32: Jadar | C32: Serbia | D32: WestBalkans | E32: Volcano-Sedimentary | F32: 1199.8675 | G32: 139.57111 | H32: 574.49636 | I32: 485.8 | J32: 9.8065001 | M32: 1 | N32: Busch et al. 2025 Supplementary Data S2
A33: 37 | B33: Praire | C33: Canada | D33: NorthAm | E33: Brine | F33: 1190 | G33: 0 | H33: 850 | I33: 340 | J33: 0 | K33: 2819 | L33: USD/tonne LCE | M33: 0.9199632 | N33: Busch et al. 2025 Supplementary Data S2
A34: 38 | B34: Zeus (Noram) | C34: United States | D34: NorthAm | E34: Volcano-Sedimentary | F34: 1176.757 | G34: 0 | H34: 972.079 | I34: 204.678 | J34: 5.9928612 | K34: 3355 | L34: USD/tonne LCE | M34: 1.047 | N34: Busch et al. 2025 Supplementary Data S2
A35: 39 | B35: Boardwalk | C35: Canada | D35: NorthAm | E35: Brine | F35: 1151 | G35: 0 | H35: 0 | I35: 1151 | J35: 5.1827917 | K35: 4533 | L35: USD/tonne LHM (LiOH.H2O) | M35: 0.86138877 | N35: Busch et al. 2025 Supplementary Data S2
A36: 40 | B36: Salar de Cauchari (Allkem) | C36: Argentina | D36: LatAm | E36: Brine | F36: 1120 | G36: 212 | H36: 623 | I36: 285 | J36: 0 | K36: 4081 | L36: USD/tonne LCE | M36: 0.9199632 | N36: Busch et al. 2025 Supplementary Data S2
A37: 41 | B37: Titan 2 | C37: Tanzania | D37: Africa_Other | E37: Volcano-Sedimentary | F37: 1102 | G37: 0 | H37: 0 | I37: 1102 | J37: 0 | M37: 0.9199632 | N37: Busch et al. 2025 Supplementary Data S2
A38: 42 | B38: Kathleen Valley | C38: Australia | D38: Australia | E38: Hard Rock | F38: 992.68942 | G38: 426.08209 | H38: 405.41724 | I38: 161.19009 | J38: 16.94815 | M38: 1.047 | N38: Busch et al. 2025 Supplementary Data S2
A39: 43 | B39: Nuristan | C39: Afghanistan | D39: ROW | E39: Hard Rock | F39: 987.03365 | G39: 0 | H39: 0 | I39: 987.03365 | J39: 0 | N39: Busch et al. 2025 Supplementary Data S2
A40: 44 | B40: Diablillios/Sal de Los Angeles | C40: Argentina | D40: LatAm | E40: Brine | F40: 930 | G40: 0 | H40: 0 | I40: 930 | J40: 9.3931993 | M40: 1.2291284 | N40: Busch et al. 2025 Supplementary Data S2
A41: 45 | B41: Pastos Grandes (Lithium Americas) | C41: Argentina | D41: LatAm | E41: Brine | F41: 920.19816 | G41: 177 | H41: 593.27612 | I41: 149.92204 | J41: 1.7696788 | K41: 3388 | L41: USD/tonne LCE | M41: 1.1183216 | N41: Busch et al. 2025 Supplementary Data S2
A42: 46 | B42: Falchani | C42: Peru | D42: LatAm | E42: Volcano-Sedimentary | F42: 884.87818 | G42: 0 | H42: 180.35734 | I42: 704.52084 | J42: 6.7920346 | M42: 1.1183216 | N42: Busch et al. 2025 Supplementary Data S2
A43: 47 | B43: Salar de Tambo | C43: Chile | D43: LatAm | E43: Brine | F43: 877.89779 | G43: 0 | H43: 0 | I43: 877.89779 | J43: 0 | N43: Busch et al. 2025 Supplementary Data S2
A44: 48 | B44: Salar La Isla | C44: Chile | D44: LatAm | E44: Brine | F44: 853.615 | G44: 0 | H44: 0 | I44: 853.615 | J44: 0 | M44: 1.1183216 | N44: Busch et al. 2025 Supplementary Data S2
A45: 49 | B45: Salar de Pedernales | C45: Chile | D45: LatAm | E45: Brine | F45: 807.42015 | G45: 0 | H45: 0 | I45: 807.42015 | J45: 0 | N45: Busch et al. 2025 Supplementary Data S2
A46: 50 | B46: Arizaro | C46: Argentina | D46: LatAm | E46: Brine | F46: 774.40931 | G46: 0 | H46: 469.30482 | I46: 305.10449 | J46: 0 | K46: 5197 | L46: USD/tonne LCE | M46: 0.9199632 | N46: Busch et al. 2025 Supplementary Data S2
A47: 51 | B47: Exshaw | C47: Canada | D47: NorthAm | E47: Brine | F47: 732.70168 | G47: 0 | H47: 0 | I47: 732.70168 | J47: 0 | M47: 1.047 | N47: Busch et al. 2025 Supplementary Data S2
A48: 52 | B48: Goulamina | C48: Mali | D48: Africa_Other | E48: Hard Rock | F48: 729.30388 | G48: 364.65194 | H48: 83.32912 | I48: 281.32282 | J48: 20.23746 | K48: 312 | L48: USD/tonne SC 6% | M48: 1.047 | N48: Busch et al. 2025 Supplementary Data S2
A49: 53 | B49: Corvette | C49: Canada | D49: NorthAm | E49: Hard Rock | F49: 720.01339 | G49: 0 | H49: 0 | I49: 720.01339 | J49: 0 | M49: 0.9199632 | N49: Busch et al. 2025 Supplementary Data S2
A50: 54 | B50: Salar de Cancosa | C50: Chile | D50: LatAm | E50: Brine | F50: 669.09002 | G50: 0 | H50: 0 | I50: 669.09002 | J50: 0 | N50: Busch et al. 2025 Supplementary Data S2
A51: 55 | B51: Pozuelos-Pastos Grandes (Pluspetrol) | C51: Argentina | D51: LatAm | E51: Brine | F51: 667.785 | G51: 0 | H51: 491.425 | I51: 176.36 | J51: 9.3931993 | K51: 2994 | L51: USD/tonne LCE | M51: 1.1183216 | N51: Busch et al. 2025 Supplementary Data S2
A52: 56 | B52: Beaverhill | C52: Canada | D52: NorthAm | E52: Brine | F52: 594.86396 | G52: 0 | H52: 0 | I52: 594.86396 | J52: 0 | N52: Busch et al. 2025 Supplementary Data S2
A53: 57 | B53: Smackover LANXESS | C53: United States | D53: NorthAm | E53: Brine | F53: 590.32 | G53: 0 | H53: 0 | I53: 590.32 | J53: 3.9263573 | N53: Busch et al. 2025 Supplementary Data S2
A54: 58 | B54: Salar de Maricunga | C54: Chile | D54: LatAm | E54: Brine | F54: 542 | G54: 90 | H54: 268 | I54: 184 | J54: 2.5699793 | K54: 3864 | L54: USD/tonne LCE | M54: 1.080504 | N54: Busch et al. 2025 Supplementary Data S2
A55: 59 | B55: Kings Mountain/Bessemer City | C55: United States | D55: NorthAm | E55: Hard Rock | F55: 516.98736 | G55: 0 | H55: 269.86988 | I55: 247.11748 | J55: 0 | M55: 1 | N55: Busch et al. 2025 Supplementary Data S2
A56: 60 | B56: Beauvoir | C56: France | D56: France | E56: Hard Rock | F56: 510.97724 | G56: 0 | H56: 0 | I56: 510.97724 | J56: 0 | M56: 1 | N56: Busch et al. 2025 Supplementary Data S2
A57: 61 | B57: La Corne(sayona) | C57: Canada | D57: NorthAm | E57: Hard Rock | F57: 502.15127 | G57: 130.20629 | H57: 230.63655 | I57: 141.30843 | J57: 5.6359196 | K57: 385 | L57: USD/tonne SC 6% | M57: 1 | N57: Busch et al. 2025 Supplementary Data S2
A58: 62 | B58: Zinnwald | C58: Germany | D58: Germany | E58: Hard Rock | F58: 500 | G58: 0 | H58: 429 | I58: 71 | J58: 1.9857223 | M58: 0.9199632 | N58: Busch et al. 2025 Supplementary Data S2
A59: 63 | B59: Mt. Marion | C59: Australia | D59: Australia | E59: Hard Rock | F59: 453.48766 | G59: 0 | H59: 141.21553 | I59: 312.27213 | J59: 22.543678 | M59: 1.1585812 | N59: Busch et al. 2025 Supplementary Data S2
A60: 64 | B60: Great Salt Lake | C60: United States | D60: NorthAm | E60: Brine | F60: 439.389 | G60: 0 | H60: 0 | I60: 439.389 | J60: 0 | M60: 0.9199632 | N60: Busch et al. 2025 Supplementary Data S2
A61: 65 | B61: Clearwater | C61: Canada | D61: NorthAm | E61: Brine | F61: 413.3189 | G61: 0 | H61: 0 | I61: 413.3189 | J61: 3.3064062 | K61: 3656 | L61: USD/tonne LHM (LiOH.H2O) | M61: 1.047 | N61: Busch et al. 2025 Supplementary Data S2
A62: 66 | B62: PAK/Spark | C62: Canada | D62: NorthAm | E62: Hard Rock | F62: 409.27047 | G62: 159.12296 | H62: 36.604087 | I62: 213.54343 | J62: 3.4525643 | M62: 0.9199632 | N62: Busch et al. 2025 Supplementary Data S2
A63: 67 | B63: Barraute | C63: Canada | D63: NorthAm | E63: Hard Rock | F63: 370.26788 | G63: 0 | H63: 0 | I63: 370.26788 | J63: 0 | N63: Busch et al. 2025 Supplementary Data S2
A64: 68 | B64: Arcadia | C64: Zimbabwe | D64: Africa_Other | E64: Hard Rock | F64: 357.77697 | G64: 234.12048 | H64: 68.462249 | I64: 55.194244 | J64: 4.0954349 | K64: 357 | L64: USD/ tonne SC 6% | M64: 1.047 | N64: Busch et al. 2025 Supplementary Data S2
A65: 69 | B65: Salar de Surire | C65: Chile | D65: LatAm | E65: Brine | F65: 350.47582 | G65: 0 | H65: 0 | I65: 350.47582 | J65: 0 | N65: Busch et al. 2025 Supplementary Data S2
A66: 70 | B66: Laguna Verde | C66: Chile | D66: LatAm | E66: Brine | F66: 338.17001 | G66: 0 | H66: 206.65945 | I66: 131.51056 | J66: 3.7572797 | K66: 3875 | L66: USD/tonne LCE | N66: Busch et al. 2025 Supplementary Data S2
A67: 71 | B67: Zhabuye | C67: China | D67: China | E67: Brine | F67: 335.84039 | G67: 0 | H67: 335.84039 | I67: 5.6843419e-14 | J67: 0.93931993 | K67: 3819 | L67: USD/tonne LCE | M67: 0.9199632 | N67: Busch et al. 2025 Supplementary Data S2
A68: 72 | B68: Dahongliu | C68: China | D68: China | E68: Hard Rock | F68: 316.3488 | G68: 0 | H68: 316.3488 | I68: 0 | J68: 0 | N68: Busch et al. 2025 Supplementary Data S2
A69: 73 | B69: San Jose/Valdeflores | C69: Spain | D69: SpainPor | E69: Hard Rock | F69: 312.04 | G69: 141.69863 | H69: 28.301365 | I69: 142.04 | J69: 3.223746 | K69: 5434 | L69: USD/tonne LiOH | M69: 1.1183216 | N69: Busch et al. 2025 Supplementary Data S2
A70: 74 | B70: Hombre Muerto North (Lithium South) | C70: Argentina | D70: LatAm | E70: Brine | F70: 297.4 | G70: 0 | H70: 297.4 | I70: 0 | J70: 0.93931993 | K70: 3122 | L70: USD/tonne LCE | M70: 0.9199632 | N70: Busch et al. 2025 Supplementary Data S2
A71: 75 | B71: Green River | C71: United States | D71: NorthAm | E71: Brine | F71: 295 | G71: 0 | H71: 0 | I71: 295 | J71: 0 | M71: 0.86138877 | N71: Busch et al. 2025 Supplementary Data S2
A72: 76 | B72: Silver Peak | C72: United States | D72: NorthAm | E72: Brine | F72: 293.28 | G72: 0 | H72: 0 | I72: 293.28 | J72: 3.7572797 | N72: Busch et al. 2025 Supplementary Data S2
A73: 77 | B73: Kolmorzerskoe | C73: Russia | D73: Russia | E73: Hard Rock | F73: 288.20851 | G73: 0 | H73: 0 | I73: 288.20851 | J73: 0 | N73: Busch et al. 2025 Supplementary Data S2
A74: 78 | B74: Paradox | C74: United States | D74: NorthAm | E74: Brine | F74: 282.55983 | G74: 0 | H74: 68.949107 | I74: 213.61072 | J74: 2.4561338 | K74: 4368 | L74: USD/tonne LCE | M74: 0.86138877 | N74: Busch et al. 2025 Supplementary Data S2
A75: 79 | B75: Salar de Aguilar | C75: Chile | D75: LatAm | E75: Brine | F75: 282.296 | G75: 0 | H75: 0 | I75: 282.296 | J75: 0 | M75: 1 | N75: Busch et al. 2025 Supplementary Data S2
A76: 80 | B76: Kamativi | C76: Zimbabwe | D76: Africa_Other | E76: Hard Rock | F76: 280.20272 | G76: 0 | H76: 0 | I76: 280.20272 | J76: 0 | N76: Busch et al. 2025 Supplementary Data S2
A77: 81 | B77: Uis | C77: Namibia | D77: Africa_Other | E77: Hard Rock | F77: 272.67604 | G77: 0 | H77: 126.35074 | I77: 146.3253 | J77: 0 | M77: 0.9199632 | N77: Busch et al. 2025 Supplementary Data S2
A78: 82 | B78: James Bay | C78: Canada | D78: NorthAm | E78: Hard Rock | F78: 262.08487 | G78: 224.69063 | H78: 37.394244 | I78: 0 | J78: 8.585572 | K78: 332.8 | L78: USD/tonne SC 6% | M78: 1.047 | N78: Busch et al. 2025 Supplementary Data S2
A79: 83 | B79: Whabouchi | C79: Canada | D79: NorthAm | E79: Hard Rock | F79: 260.31829 | G79: 221.02088 | H79: 39.29741 | I79: 0 | J79: 5.9133947 | M79: 1.1183216 | N79: Busch et al. 2025 Supplementary Data S2
A80: 84 | B80: Yichun 414 | C80: China | D80: China | E80: Hard Rock | F80: 255.98956 | G80: 0 | H80: 0 | I80: 255.98956 | J80: 1.8386248 | M80: 1 | N80: Busch et al. 2025 Supplementary Data S2
A81: 85 | B81: Rhyolite Ridge | C81: United States | D81: NorthAm | E81: Volcano-Sedimentary | F81: 234.4 | G81: 108.1794 | H81: 95.211102 | I81: 31.009498 | J81: 4.5087357 | K81: 2510 | L81: USD/tonne LCE | M81: 1.080504 | N81: Busch et al. 2025 Supplementary Data S2
A82: 86 | B82: Kenticha | C82: Ethiopia | D82: Africa_Other | E82: Hard Rock | F82: 228.75191 | G82: 0 | H82: 0 | I82: 228.75191 | J82: 0 | N82: Busch et al. 2025 Supplementary Data S2
A83: 87 | B83: Smackover SWA | C83: United States | D83: NorthAm | E83: Brine | F83: 224.66 | G83: 0 | H83: 0 | I83: 224.66 | J83: 4.9596092 | N83: Busch et al. 2025 Supplementary Data S2
A84: 88 | B84: Huaqiao Dagang | C84: China | D84: China | E84: Hard Rock | F84: 217.76407 | G84: 113.11179 | H84: 104.65229 | I84: 0 | J84: 0 | N84: Busch et al. 2025 Supplementary Data S2
A85: 89 | B85: Plumbago North | C85: United States | D85: NorthAm | E85: Hard Rock | F85: 217.58443 | G85: 0 | H85: 0 | I85: 217.58443 | J85: 0 | N85: Busch et al. 2025 Supplementary Data S2
A86: 90 | B86: Ewoyaa | C86: Ghana | D86: Africa_Other | E86: Hard Rock | F86: 204.97155 | G86: 145.08037 | H86: 17.044017 | I86: 42.847161 | J86: 6.2998309 | K86: 377 | L86: USD/tonne SC 6% | M86: 0.9199632 | N86: Busch et al. 2025 Supplementary Data S2
A87: 91 | B87: Jiajika | C87: China | D87: China | E87: Hard Rock | F87: 204.1477 | G87: 0 | H87: 0 | I87: 204.1477 | J87: 1.1455946 | N87: Busch et al. 2025 Supplementary Data S2
A88: 92 | B88: Wolfsberg/Koralpe | C88: Austria | D88: Austria | E88: Hard Rock | F88: 203.83347 | G88: 0 | H88: 37.161981 | I88: 166.67149 | J88: 1.4548187 | M88: 1.047 | N88: Busch et al. 2025 Supplementary Data S2
A89: 93 | B89: Grota do Cirilo (Barreiro) | C89: Brazil | D89: Brazil | E89: Hard Rock | F89: 185.78684 | G89: 137.12794 | H89: 23.953709 | I89: 24.705198 | J89: 0 | K89: 408 | L89: USD/tonne SC 6% | M89: 1 | N89: Busch et al. 2025 Supplementary Data S2
A90: 94 | B90: Grota do Cirilo (NDC) | C90: Brazil | D90: Brazil | E90: Hard Rock | F90: 185.24201 | G90: 0 | H90: 161.0065 | I90: 24.235517 | J90: 0 | M90: 1 | N90: Busch et al. 2025 Supplementary Data S2
A91: 95 | B91: Rocky | C91: Canada | D91: NorthAm | E91: Brine | F91: 174.72117 | G91: 0 | H91: 0 | I91: 174.72117 | J91: 0 | M91: 1.1968144 | N91: Busch et al. 2025 Supplementary Data S2
A92: 96 | B92: Francisco Basin | C92: Chile | D92: LatAm | E92: Brine | F92: 172.84245 | G92: 0 | H92: 82.663779 | I92: 90.178668 | J92: 0 | K92: 3641 | L92: USD/tonne LCE | N92: Busch et al. 2025 Supplementary Data S2
A93: 97 | B93: Candelas | C93: Argentina | D93: LatAm | E93: Brine | F93: 167 | G93: 0 | H93: 167 | I93: 0 | J93: 7.1388315 | K93: 4277 | L93: USD/tonne LCE | M93: 1.047 | N93: Busch et al. 2025 Supplementary Data S2
A94: 98 | B94: Bikita | C94: Zimbabwe | D94: Africa_Other | E94: Hard Rock | F94: 159.86332 | G94: 0 | H94: 0 | I94: 159.86332 | J94: 6.3873755 | M94: 0.9199632 | N94: Busch et al. 2025 Supplementary Data S2
A95: 99 | B95: Bougouni | C95: Mali | D95: Africa_Other | E95: Hard Rock | F95: 156.12677 | G95: 0 | H95: 59.923695 | I95: 96.203079 | J95: 7.8746947 | K95: 647 | L95: USD/tonne of concentrate 6% | M95: 0.86138877 | N95: Busch et al. 2025 Supplementary Data S2
A96: 100 | B96: Grota de Cirilo ( Xuxa) | C96: Brazil | D96: Brazil | E96: Hard Rock | F96: 153.2098 | G96: 84.82431 | H96: 40.467677 | I96: 27.917813 | J96: 19.777569 | K96: 386 | L96: USD/ tonne SC 6% | M96: 1 | N96: Busch et al. 2025 Supplementary Data S2
A97: 101 | B97: Manna | C97: Australia | D97: Australia | E97: Hard Rock | F97: 152.49884 | G97: 0 | H97: 88.259705 | I97: 64.23913 | J97: 5.6214541 | M97: 1 | N97: Busch et al. 2025 Supplementary Data S2
A98: 102 | B98: Karibib | C98: Namibia | D98: Africa_Other | E98: Hard Rock | F98: 150 | G98: 0 | H98: 0 | I98: 150 | J98: 0.28761976 | N98: Busch et al. 2025 Supplementary Data S2
A99: 103 | B99: Salar de Pajonales | C99: Chile | D99: LatAm | E99: Brine | F99: 149.974 | G99: 0 | H99: 0 | I99: 149.974 | J99: 0 | M99: 1.080504 | N99: Busch et al. 2025 Supplementary Data S2
A100: 104 | B100: Carolina Lithium | C100: United States | D100: NorthAm | E100: Hard Rock | F100: 143.53815 | G100: 0 | H100: 71.511839 | I100: 72.026313 | J100: 4.9596092 | K100: 201 | L100: USD/ tonne SC 6% | M100: 1 | N100: Busch et al. 2025 Supplementary Data S2
...

Sheet Codex_calc
A1: Calculation layer linked by the original scenario sheet
A2: Columns C:AO mirror the scenario table. Region cells contain formulas against Codex_sources, Codex_USGS_raw, and Codex_Li_Busch.
C4: pset_pn | D4: Attribute | E4: cset_cn | F4: Africa_North | G4: Africa_Other | H4: Australia | I4: Austria | J4: Baltics | K4: BeNeLux | L4: Brazil | M4: China | N4: CroSloven | O4: CzechSlovak | P4: France | Q4: Germany | R4: GreeceCyp | S4: HunRomBul | T4: Iceland | U4: India | V4: Ireland | W4: ItalyMal | X4: Japan | Y4: LatAm | Z4: MidEast | AA4: NorthAm | AB4: Norway | AC4: Poland | AD4: ROW | AE4: Russia | AF4: SaudiArabia | AG4: SouthAfrica | AH4: SpainPor | AI4: SweFinDen | AJ4: Switzerland | AK4: Turkey | AL4: UK | AM4: Ukraine | AN4: WestBalkans | AO4: year
C41: MINLiRSV1 | D41: BNDACT | F41: =SUMIFS(Codex_Li_Busch!$J$2:$J$161,Codex_Li_Busch!$D$2:$D$161,F$4)*Codex_sources!$D$5/3 | G41: =SUMIFS(Codex_Li_Busch!$J$2:$J$161,Codex_Li_Busch!$D$2:$D$161,G$4)*Codex_sources!$D$5/3 | H41: =SUMIFS(Codex_Li_Busch!$J$2:$J$161,Codex_Li_Busch!$D$2:$D$161,H$4)*Codex_sources!$D$5/3 | I41: =SUMIFS(Codex_Li_Busch!$J$2:$J$161,Codex_Li_Busch!$D$2:$D$161,I$4)*Codex_sources!$D$5/3 | J41: =SUMIFS(Codex_Li_Busch!$J$2:$J$161,Codex_Li_Busch!$D$2:$D$161,J$4)*Codex_sources!$D$5/3 | K41: =SUMIFS(Codex_Li_Busch!$J$2:$J$161,Codex_Li_Busch!$D$2:$D$161,K$4)*Codex_sources!$D$5/3 | L41: =SUMIFS(Codex_Li_Busch!$J$2:$J$161,Codex_Li_Busch!$D$2:$D$161,L$4)*Codex_sources!$D$5/3 | M41: =SUMIFS(Codex_Li_Busch!$J$2:$J$161,Codex_Li_Busch!$D$2:$D$161,M$4)*Codex_sources!$D$5/3 | ... AN41: =SUMIFS(Codex_Li_Busch!$J$2:$J$161,Codex_Li_Busch!$D$2:$D$161,AN$4)*Codex_sources!$D$5/3 | AO41: 2019, 2130
C42: MINLiRSV1 | D42: CUM | F42: =SUMIFS(Codex_Li_Busch!$G$2:$G$161,Codex_Li_Busch!$D$2:$D$161,F$4)*Codex_sources!$D$5 | G42: =SUMIFS(Codex_Li_Busch!$G$2:$G$161,Codex_Li_Busch!$D$2:$D$161,G$4)*Codex_sources!$D$5 | H42: =SUMIFS(Codex_Li_Busch!$G$2:$G$161,Codex_Li_Busch!$D$2:$D$161,H$4)*Codex_sources!$D$5 | I42: =SUMIFS(Codex_Li_Busch!$G$2:$G$161,Codex_Li_Busch!$D$2:$D$161,I$4)*Codex_sources!$D$5 | J42: =SUMIFS(Codex_Li_Busch!$G$2:$G$161,Codex_Li_Busch!$D$2:$D$161,J$4)*Codex_sources!$D$5 | K42: =SUMIFS(Codex_Li_Busch!$G$2:$G$161,Codex_Li_Busch!$D$2:$D$161,K$4)*Codex_sources!$D$5 | L42: =SUMIFS(Codex_Li_Busch!$G$2:$G$161,Codex_Li_Busch!$D$2:$D$161,L$4)*Codex_sources!$D$5 | M42: =SUMIFS(Codex_Li_Busch!$G$2:$G$161,Codex_Li_Busch!$D$2:$D$161,M$4)*Codex_sources!$D$5 | ... AN42: =SUMIFS(Codex_Li_Busch!$G$2:$G$161,Codex_Li_Busch!$D$2:$D$161,AN$4)*Codex_sources!$D$5 | AO42: =AO41
C43: MINLiRSV1 | D43: COST | E43: m_lithium | F43: =Codex_Regional!F7 | G43: =Codex_Regional!G7 | H43: =Codex_Regional!H7 | I43: =Codex_Regional!I7 | J43: =Codex_Regional!J7 | K43: =Codex_Regional!K7 | L43: =Codex_Regional!L7 | M43: =Codex_Regional!M7 | ... AN43: =Codex_Regional!AN7 | AO43: =AO42
C44: MINLiRSV2 | D44: BNDACT | F44: =SUMIFS(Codex_Li_Busch!$J$2:$J$161,Codex_Li_Busch!$D$2:$D$161,F$4)*Codex_sources!$D$5*2/3 | G44: =SUMIFS(Codex_Li_Busch!$J$2:$J$161,Codex_Li_Busch!$D$2:$D$161,G$4)*Codex_sources!$D$5*2/3 | H44: =SUMIFS(Codex_Li_Busch!$J$2:$J$161,Codex_Li_Busch!$D$2:$D$161,H$4)*Codex_sources!$D$5*2/3 | I44: =SUMIFS(Codex_Li_Busch!$J$2:$J$161,Codex_Li_Busch!$D$2:$D$161,I$4)*Codex_sources!$D$5*2/3 | J44: =SUMIFS(Codex_Li_Busch!$J$2:$J$161,Codex_Li_Busch!$D$2:$D$161,J$4)*Codex_sources!$D$5*2/3 | K44: =SUMIFS(Codex_Li_Busch!$J$2:$J$161,Codex_Li_Busch!$D$2:$D$161,K$4)*Codex_sources!$D$5*2/3 | L44: =SUMIFS(Codex_Li_Busch!$J$2:$J$161,Codex_Li_Busch!$D$2:$D$161,L$4)*Codex_sources!$D$5*2/3 | M44: =SUMIFS(Codex_Li_Busch!$J$2:$J$161,Codex_Li_Busch!$D$2:$D$161,M$4)*Codex_sources!$D$5*2/3 | ... AN44: =SUMIFS(Codex_Li_Busch!$J$2:$J$161,Codex_Li_Busch!$D$2:$D$161,AN$4)*Codex_sources!$D$5*2/3 | AO44: =AO43
C45: MINLiRSV2 | D45: CUM | F45: =SUMIFS(Codex_Li_Busch!$H$2:$H$161,Codex_Li_Busch!$D$2:$D$161,F$4)*Codex_sources!$D$5 | G45: =SUMIFS(Codex_Li_Busch!$H$2:$H$161,Codex_Li_Busch!$D$2:$D$161,G$4)*Codex_sources!$D$5 | H45: =SUMIFS(Codex_Li_Busch!$H$2:$H$161,Codex_Li_Busch!$D$2:$D$161,H$4)*Codex_sources!$D$5 | I45: =SUMIFS(Codex_Li_Busch!$H$2:$H$161,Codex_Li_Busch!$D$2:$D$161,I$4)*Codex_sources!$D$5 | J45: =SUMIFS(Codex_Li_Busch!$H$2:$H$161,Codex_Li_Busch!$D$2:$D$161,J$4)*Codex_sources!$D$5 | K45: =SUMIFS(Codex_Li_Busch!$H$2:$H$161,Codex_Li_Busch!$D$2:$D$161,K$4)*Codex_sources!$D$5 | L45: =SUMIFS(Codex_Li_Busch!$H$2:$H$161,Codex_Li_Busch!$D$2:$D$161,L$4)*Codex_sources!$D$5 | M45: =SUMIFS(Codex_Li_Busch!$H$2:$H$161,Codex_Li_Busch!$D$2:$D$161,M$4)*Codex_sources!$D$5 | ... AN45: =SUMIFS(Codex_Li_Busch!$H$2:$H$161,Codex_Li_Busch!$D$2:$D$161,AN$4)*Codex_sources!$D$5 | AO45: =AO44
C46: MINLiRSV2 | D46: COST | E46: m_lithium | F46: =Codex_Regional!F7*(Codex_sources!$N$5/Codex_sources!$M$5) | G46: =Codex_Regional!G7*(Codex_sources!$N$5/Codex_sources!$M$5) | H46: =Codex_Regional!H7*(Codex_sources!$N$5/Codex_sources!$M$5) | I46: =Codex_Regional!I7*(Codex_sources!$N$5/Codex_sources!$M$5) | J46: =Codex_Regional!J7*(Codex_sources!$N$5/Codex_sources!$M$5) | K46: =Codex_Regional!K7*(Codex_sources!$N$5/Codex_sources!$M$5) | L46: =Codex_Regional!L7*(Codex_sources!$N$5/Codex_sources!$M$5) | M46: =Codex_Regional!M7*(Codex_sources!$N$5/Codex_sources!$M$5) | ... AN46: =Codex_Regional!AN7*(Codex_sources!$N$5/Codex_sources!$M$5) | AO46: =AO45
C47: MINLiRSV3 | D47: BNDACT | AO47: =AO46
C48: MINLiRSV3 | D48: CUM | F48: =SUMIFS(Codex_Li_Busch!$I$2:$I$161,Codex_Li_Busch!$D$2:$D$161,F$4)*Codex_sources!$D$5 | G48: =SUMIFS(Codex_Li_Busch!$I$2:$I$161,Codex_Li_Busch!$D$2:$D$161,G$4)*Codex_sources!$D$5 | H48: =SUMIFS(Codex_Li_Busch!$I$2:$I$161,Codex_Li_Busch!$D$2:$D$161,H$4)*Codex_sources!$D$5 | I48: =SUMIFS(Codex_Li_Busch!$I$2:$I$161,Codex_Li_Busch!$D$2:$D$161,I$4)*Codex_sources!$D$5 | J48: =SUMIFS(Codex_Li_Busch!$I$2:$I$161,Codex_Li_Busch!$D$2:$D$161,J$4)*Codex_sources!$D$5 | K48: =SUMIFS(Codex_Li_Busch!$I$2:$I$161,Codex_Li_Busch!$D$2:$D$161,K$4)*Codex_sources!$D$5 | L48: =SUMIFS(Codex_Li_Busch!$I$2:$I$161,Codex_Li_Busch!$D$2:$D$161,L$4)*Codex_sources!$D$5 | M48: =SUMIFS(Codex_Li_Busch!$I$2:$I$161,Codex_Li_Busch!$D$2:$D$161,M$4)*Codex_sources!$D$5 | ... AN48: =SUMIFS(Codex_Li_Busch!$I$2:$I$161,Codex_Li_Busch!$D$2:$D$161,AN$4)*Codex_sources!$D$5 | AO48: =AO47
C49: MINLiRSV3 | D49: COST | E49: m_lithium | F49: =Codex_Regional!F7*(Codex_sources!$O$5/Codex_sources!$M$5) | G49: =Codex_Regional!G7*(Codex_sources!$O$5/Codex_sources!$M$5) | H49: =Codex_Regional!H7*(Codex_sources!$O$5/Codex_sources!$M$5) | I49: =Codex_Regional!I7*(Codex_sources!$O$5/Codex_sources!$M$5) | J49: =Codex_Regional!J7*(Codex_sources!$O$5/Codex_sources!$M$5) | K49: =Codex_Regional!K7*(Codex_sources!$O$5/Codex_sources!$M$5) | L49: =Codex_Regional!L7*(Codex_sources!$O$5/Codex_sources!$M$5) | M49: =Codex_Regional!M7*(Codex_sources!$O$5/Codex_sources!$M$5) | ... AN49: =Codex_Regional!AN7*(Codex_sources!$O$5/Codex_sources!$M$5) | AO49: =AO48
AO50: =AO49
C51: MINNiRSV1 | D51: BNDACT | F51: =SUMIFS(Codex_USGS_raw!$D$2:$D$94,Codex_USGS_raw!$A$2:$A$94,Codex_sources!$A$6,Codex_USGS_raw!$C$2:$C$94,F$4)*Codex_sources!$D$6*1 | G51: =SUMIFS(Codex_USGS_raw!$D$2:$D$94,Codex_USGS_raw!$A$2:$A$94,Codex_sources!$A$6,Codex_USGS_raw!$C$2:$C$94,G$4)*Codex_sources!$D$6*1 | H51: =SUMIFS(Codex_USGS_raw!$D$2:$D$94,Codex_USGS_raw!$A$2:$A$94,Codex_sources!$A$6,Codex_USGS_raw!$C$2:$C$94,H$4)*Codex_sources!$D$6*1 | I51: =SUMIFS(Codex_USGS_raw!$D$2:$D$94,Codex_USGS_raw!$A$2:$A$94,Codex_sources!$A$6,Codex_USGS_raw!$C$2:$C$94,I$4)*Codex_sources!$D$6*1 | J51: =SUMIFS(Codex_USGS_raw!$D$2:$D$94,Codex_USGS_raw!$A$2:$A$94,Codex_sources!$A$6,Codex_USGS_raw!$C$2:$C$94,J$4)*Codex_sources!$D$6*1 | K51: =SUMIFS(Codex_USGS_raw!$D$2:$D$94,Codex_USGS_raw!$A$2:$A$94,Codex_sources!$A$6,Codex_USGS_raw!$C$2:$C$94,K$4)*Codex_sources!$D$6*1 | L51: =SUMIFS(Codex_USGS_raw!$D$2:$D$94,Codex_USGS_raw!$A$2:$A$94,Codex_sources!$A$6,Codex_USGS_raw!$C$2:$C$94,L$4)*Codex_sources!$D$6*1 | M51: =SUMIFS(Codex_USGS_raw!$D$2:$D$94,Codex_USGS_raw!$A$2:$A$94,Codex_sources!$A$6,Codex_USGS_raw!$C$2:$C$94,M$4)*Codex_sources!$D$6*1 | ... AN51: =SUMIFS(Codex_USGS_raw!$D$2:$D$94,Codex_USGS_raw!$A$2:$A$94,Codex_sources!$A$6,Codex_USGS_raw!$C$2:$C$94,AN$4)*Codex_sources!$D$6*1 | AO51: =AO50
C52: MINNiRSV1 | D52: CUM | F52: =SUMIFS(Codex_USGS_raw!$E$2:$E$94,Codex_USGS_raw!$A$2:$A$94,Codex_sources!$A$6,Codex_USGS_raw!$C$2:$C$94,F$4)*Codex_sources!$D$6*Codex_sources!$J$6 | G52: =SUMIFS(Codex_USGS_raw!$E$2:$E$94,Codex_USGS_raw!$A$2:$A$94,Codex_sources!$A$6,Codex_USGS_raw!$C$2:$C$94,G$4)*Codex_sources!$D$6*Codex_sources!$J$6 | H52: =SUMIFS(Codex_USGS_raw!$E$2:$E$94,Codex_USGS_raw!$A$2:$A$94,Codex_sources!$A$6,Codex_USGS_raw!$C$2:$C$94,H$4)*Codex_sources!$D$6*Codex_sources!$J$6 | I52: =SUMIFS(Codex_USGS_raw!$E$2:$E$94,Codex_USGS_raw!$A$2:$A$94,Codex_sources!$A$6,Codex_USGS_raw!$C$2:$C$94,I$4)*Codex_sources!$D$6*Codex_sources!$J$6 | J52: =SUMIFS(Codex_USGS_raw!$E$2:$E$94,Codex_USGS_raw!$A$2:$A$94,Codex_sources!$A$6,Codex_USGS_raw!$C$2:$C$94,J$4)*Codex_sources!$D$6*Codex_sources!$J$6 | K52: =SUMIFS(Codex_USGS_raw!$E$2:$E$94,Codex_USGS_raw!$A$2:$A$94,Codex_sources!$A$6,Codex_USGS_raw!$C$2:$C$94,K$4)*Codex_sources!$D$6*Codex_sources!$J$6 | L52: =SUMIFS(Codex_USGS_raw!$E$2:$E$94,Codex_USGS_raw!$A$2:$A$94,Codex_sources!$A$6,Codex_USGS_raw!$C$2:$C$94,L$4)*Codex_sources!$D$6*Codex_sources!$J$6 | M52: =SUMIFS(Codex_USGS_raw!$E$2:$E$94,Codex_USGS_raw!$A$2:$A$94,Codex_sources!$A$6,Codex_USGS_raw!$C$2:$C$94,M$4)*Codex_sources!$D$6*Codex_sources!$J$6 | ... AN52: =SUMIFS(Codex_USGS_raw!$E$2:$E$94,Codex_USGS_raw!$A$2:$A$94,Codex_sources!$A$6,Codex_USGS_raw!$C$2:$C$94,AN$4)*Codex_sources!$D$6*Codex_sources!$J$6 | AO52: =AO51
C53: MINNiRSV1 | D53: COST | E53: m_nickel | F53: =Codex_Regional!F10 | G53: =Codex_Regional!G10 | H53: =Codex_Regional!H10 | I53: =Codex_Regional!I10 | J53: =Codex_Regional!J10 | K53: =Codex_Regional!K10 | L53: =Codex_Regional!L10 | M53: =Codex_Regional!M10 | ... AN53: =Codex_Regional!AN10 | AO53: =AO52
C54: MINNiRSV2 | D54: BNDACT | F54: =SUMIFS(Codex_USGS_raw!$D$2:$D$94,Codex_USGS_raw!$A$2:$A$94,Codex_sources!$A$6,Codex_USGS_raw!$C$2:$C$94,F$4)*Codex_sources!$D$6*2 | G54: =SUMIFS(Codex_USGS_raw!$D$2:$D$94,Codex_USGS_raw!$A$2:$A$94,Codex_sources!$A$6,Codex_USGS_raw!$C$2:$C$94,G$4)*Codex_sources!$D$6*2 | H54: =SUMIFS(Codex_USGS_raw!$D$2:$D$94,Codex_USGS_raw!$A$2:$A$94,Codex_sources!$A$6,Codex_USGS_raw!$C$2:$C$94,H$4)*Codex_sources!$D$6*2 | I54: =SUMIFS(Codex_USGS_raw!$D$2:$D$94,Codex_USGS_raw!$A$2:$A$94,Codex_sources!$A$6,Codex_USGS_raw!$C$2:$C$94,I$4)*Codex_sources!$D$6*2 | J54: =SUMIFS(Codex_USGS_raw!$D$2:$D$94,Codex_USGS_raw!$A$2:$A$94,Codex_sources!$A$6,Codex_USGS_raw!$C$2:$C$94,J$4)*Codex_sources!$D$6*2 | K54: =SUMIFS(Codex_USGS_raw!$D$2:$D$94,Codex_USGS_raw!$A$2:$A$94,Codex_sources!$A$6,Codex_USGS_raw!$C$2:$C$94,K$4)*Codex_sources!$D$6*2 | L54: =SUMIFS(Codex_USGS_raw!$D$2:$D$94,Codex_USGS_raw!$A$2:$A$94,Codex_sources!$A$6,Codex_USGS_raw!$C$2:$C$94,L$4)*Codex_sources!$D$6*2 | M54: =SUMIFS(Codex_USGS_raw!$D$2:$D$94,Codex_USGS_raw!$A$2:$A$94,Codex_sources!$A$6,Codex_USGS_raw!$C$2:$C$94,M$4)*Codex_sources!$D$6*2 | ... AN54: =SUMIFS(Codex_USGS_raw!$D$2:$D$94,Codex_USGS_raw!$A$2:$A$94,Codex_sources!$A$6,Codex_USGS_raw!$C$2:$C$94,AN$4)*Codex_sources!$D$6*2 | AO54: =AO53
C55: MINNiRSV2 | D55: CUM | F55: =SUMIFS(Codex_USGS_raw!$E$2:$E$94,Codex_USGS_raw!$A$2:$A$94,Codex_sources!$A$6,Codex_USGS_raw!$C$2:$C$94,F$4)*Codex_sources!$D$6*Codex_sources!$K$6 | G55: =SUMIFS(Codex_USGS_raw!$E$2:$E$94,Codex_USGS_raw!$A$2:$A$94,Codex_sources!$A$6,Codex_USGS_raw!$C$2:$C$94,G$4)*Codex_sources!$D$6*Codex_sources!$K$6 | H55: =SUMIFS(Codex_USGS_raw!$E$2:$E$94,Codex_USGS_raw!$A$2:$A$94,Codex_sources!$A$6,Codex_USGS_raw!$C$2:$C$94,H$4)*Codex_sources!$D$6*Codex_sources!$K$6 | I55: =SUMIFS(Codex_USGS_raw!$E$2:$E$94,Codex_USGS_raw!$A$2:$A$94,Codex_sources!$A$6,Codex_USGS_raw!$C$2:$C$94,I$4)*Codex_sources!$D$6*Codex_sources!$K$6 | J55: =SUMIFS(Codex_USGS_raw!$E$2:$E$94,Codex_USGS_raw!$A$2:$A$94,Codex_sources!$A$6,Codex_USGS_raw!$C$2:$C$94,J$4)*Codex_sources!$D$6*Codex_sources!$K$6 | K55: =SUMIFS(Codex_USGS_raw!$E$2:$E$94,Codex_USGS_raw!$A$2:$A$94,Codex_sources!$A$6,Codex_USGS_raw!$C$2:$C$94,K$4)*Codex_sources!$D$6*Codex_sources!$K$6 | L55: =SUMIFS(Codex_USGS_raw!$E$2:$E$94,Codex_USGS_raw!$A$2:$A$94,Codex_sources!$A$6,Codex_USGS_raw!$C$2:$C$94,L$4)*Codex_sources!$D$6*Codex_sources!$K$6 | M55: =SUMIFS(Codex_USGS_raw!$E$2:$E$94,Codex_USGS_raw!$A$2:$A$94,Codex_sources!$A$6,Codex_USGS_raw!$C$2:$C$94,M$4)*Codex_sources!$D$6*Codex_sources!$K$6 | ... AN55: =SUMIFS(Codex_USGS_raw!$E$2:$E$94,Codex_USGS_raw!$A$2:$A$94,Codex_sources!$A$6,Codex_USGS_raw!$C$2:$C$94,AN$4)*Codex_sources!$D$6*Codex_sources!$K$6 | AO55: =AO54
C56: MINNiRSV2 | D56: COST | E56: m_nickel | F56: =Codex_Regional!F10*(Codex_sources!$N$6/Codex_sources!$M$6) | G56: =Codex_Regional!G10*(Codex_sources!$N$6/Codex_sources!$M$6) | H56: =Codex_Regional!H10*(Codex_sources!$N$6/Codex_sources!$M$6) | I56: =Codex_Regional!I10*(Codex_sources!$N$6/Codex_sources!$M$6) | J56: =Codex_Regional!J10*(Codex_sources!$N$6/Codex_sources!$M$6) | K56: =Codex_Regional!K10*(Codex_sources!$N$6/Codex_sources!$M$6) | L56: =Codex_Regional!L10*(Codex_sources!$N$6/Codex_sources!$M$6) | M56: =Codex_Regional!M10*(Codex_sources!$N$6/Codex_sources!$M$6) | ... AN56: =Codex_Regional!AN10*(Codex_sources!$N$6/Codex_sources!$M$6) | AO56: =AO55
C57: MINNiRSV3 | D57: BNDACT | AO57: =AO56
C58: MINNiRSV3 | D58: CUM | F58: =SUMIFS(Codex_USGS_raw!$E$2:$E$94,Codex_USGS_raw!$A$2:$A$94,Codex_sources!$A$6,Codex_USGS_raw!$C$2:$C$94,F$4)*Codex_sources!$D$6*Codex_sources!$L$6 | G58: =SUMIFS(Codex_USGS_raw!$E$2:$E$94,Codex_USGS_raw!$A$2:$A$94,Codex_sources!$A$6,Codex_USGS_raw!$C$2:$C$94,G$4)*Codex_sources!$D$6*Codex_sources!$L$6 | H58: =SUMIFS(Codex_USGS_raw!$E$2:$E$94,Codex_USGS_raw!$A$2:$A$94,Codex_sources!$A$6,Codex_USGS_raw!$C$2:$C$94,H$4)*Codex_sources!$D$6*Codex_sources!$L$6 | I58: =SUMIFS(Codex_USGS_raw!$E$2:$E$94,Codex_USGS_raw!$A$2:$A$94,Codex_sources!$A$6,Codex_USGS_raw!$C$2:$C$94,I$4)*Codex_sources!$D$6*Codex_sources!$L$6 | J58: =SUMIFS(Codex_USGS_raw!$E$2:$E$94,Codex_USGS_raw!$A$2:$A$94,Codex_sources!$A$6,Codex_USGS_raw!$C$2:$C$94,J$4)*Codex_sources!$D$6*Codex_sources!$L$6 | K58: =SUMIFS(Codex_USGS_raw!$E$2:$E$94,Codex_USGS_raw!$A$2:$A$94,Codex_sources!$A$6,Codex_USGS_raw!$C$2:$C$94,K$4)*Codex_sources!$D$6*Codex_sources!$L$6 | L58: =SUMIFS(Codex_USGS_raw!$E$2:$E$94,Codex_USGS_raw!$A$2:$A$94,Codex_sources!$A$6,Codex_USGS_raw!$C$2:$C$94,L$4)*Codex_sources!$D$6*Codex_sources!$L$6 | M58: =SUMIFS(Codex_USGS_raw!$E$2:$E$94,Codex_USGS_raw!$A$2:$A$94,Codex_sources!$A$6,Codex_USGS_raw!$C$2:$C$94,M$4)*Codex_sources!$D$6*Codex_sources!$L$6 | ... AN58: =SUMIFS(Codex_USGS_raw!$E$2:$E$94,Codex_USGS_raw!$A$2:$A$94,Codex_sources!$A$6,Codex_USGS_raw!$C$2:$C$94,AN$4)*Codex_sources!$D$6*Codex_sources!$L$6 | AO58: =AO57
C59: MINNiRSV3 | D59: COST | E59: m_nickel | F59: =Codex_Regional!F10*(Codex_sources!$O$6/Codex_sources!$M$6) | G59: =Codex_Regional!G10*(Codex_sources!$O$6/Codex_sources!$M$6) | H59: =Codex_Regional!H10*(Codex_sources!$O$6/Codex_sources!$M$6) | I59: =Codex_Regional!I10*(Codex_sources!$O$6/Codex_sources!$M$6) | J59: =Codex_Regional!J10*(Codex_sources!$O$6/Codex_sources!$M$6) | K59: =Codex_Regional!K10*(Codex_sources!$O$6/Codex_sources!$M$6) | L59: =Codex_Regional!L10*(Codex_sources!$O$6/Codex_sources!$M$6) | M59: =Codex_Regional!M10*(Codex_sources!$O$6/Codex_sources!$M$6) | ... AN59: =Codex_Regional!AN10*(Codex_sources!$O$6/Codex_sources!$M$6) | AO59: =AO58
AO60: =AO59
C61: MINCoRSV1 | D61: BNDACT | F61: =SUMIFS(Codex_USGS_raw!$D$2:$D$94,Codex_USGS_raw!$A$2:$A$94,Codex_sources!$A$7,Codex_USGS_raw!$C$2:$C$94,F$4)*Codex_sources!$D$7*1 | G61: =SUMIFS(Codex_USGS_raw!$D$2:$D$94,Codex_USGS_raw!$A$2:$A$94,Codex_sources!$A$7,Codex_USGS_raw!$C$2:$C$94,G$4)*Codex_sources!$D$7*1 | H61: =SUMIFS(Codex_USGS_raw!$D$2:$D$94,Codex_USGS_raw!$A$2:$A$94,Codex_sources!$A$7,Codex_USGS_raw!$C$2:$C$94,H$4)*Codex_sources!$D$7*1 | I61: =SUMIFS(Codex_USGS_raw!$D$2:$D$94,Codex_USGS_raw!$A$2:$A$94,Codex_sources!$A$7,Codex_USGS_raw!$C$2:$C$94,I$4)*Codex_sources!$D$7*1 | J61: =SUMIFS(Codex_USGS_raw!$D$2:$D$94,Codex_USGS_raw!$A$2:$A$94,Codex_sources!$A$7,Codex_USGS_raw!$C$2:$C$94,J$4)*Codex_sources!$D$7*1 | K61: =SUMIFS(Codex_USGS_raw!$D$2:$D$94,Codex_USGS_raw!$A$2:$A$94,Codex_sources!$A$7,Codex_USGS_raw!$C$2:$C$94,K$4)*Codex_sources!$D$7*1 | L61: =SUMIFS(Codex_USGS_raw!$D$2:$D$94,Codex_USGS_raw!$A$2:$A$94,Codex_sources!$A$7,Codex_USGS_raw!$C$2:$C$94,L$4)*Codex_sources!$D$7*1 | M61: =SUMIFS(Codex_USGS_raw!$D$2:$D$94,Codex_USGS_raw!$A$2:$A$94,Codex_sources!$A$7,Codex_USGS_raw!$C$2:$C$94,M$4)*Codex_sources!$D$7*1 | ... AN61: =SUMIFS(Codex_USGS_raw!$D$2:$D$94,Codex_USGS_raw!$A$2:$A$94,Codex_sources!$A$7,Codex_USGS_raw!$C$2:$C$94,AN$4)*Codex_sources!$D$7*1 | AO61: =AO60
C62: MINCoRSV1 | D62: CUM | F62: =SUMIFS(Codex_USGS_raw!$E$2:$E$94,Codex_USGS_raw!$A$2:$A$94,Codex_sources!$A$7,Codex_USGS_raw!$C$2:$C$94,F$4)*Codex_sources!$D$7*Codex_sources!$J$7 | G62: =SUMIFS(Codex_USGS_raw!$E$2:$E$94,Codex_USGS_raw!$A$2:$A$94,Codex_sources!$A$7,Codex_USGS_raw!$C$2:$C$94,G$4)*Codex_sources!$D$7*Codex_sources!$J$7 | H62: =SUMIFS(Codex_USGS_raw!$E$2:$E$94,Codex_USGS_raw!$A$2:$A$94,Codex_sources!$A$7,Codex_USGS_raw!$C$2:$C$94,H$4)*Codex_sources!$D$7*Codex_sources!$J$7 | I62: =SUMIFS(Codex_USGS_raw!$E$2:$E$94,Codex_USGS_raw!$A$2:$A$94,Codex_sources!$A$7,Codex_USGS_raw!$C$2:$C$94,I$4)*Codex_sources!$D$7*Codex_sources!$J$7 | J62: =SUMIFS(Codex_USGS_raw!$E$2:$E$94,Codex_USGS_raw!$A$2:$A$94,Codex_sources!$A$7,Codex_USGS_raw!$C$2:$C$94,J$4)*Codex_sources!$D$7*Codex_sources!$J$7 | K62: =SUMIFS(Codex_USGS_raw!$E$2:$E$94,Codex_USGS_raw!$A$2:$A$94,Codex_sources!$A$7,Codex_USGS_raw!$C$2:$C$94,K$4)*Codex_sources!$D$7*Codex_sources!$J$7 | L62: =SUMIFS(Codex_USGS_raw!$E$2:$E$94,Codex_USGS_raw!$A$2:$A$94,Codex_sources!$A$7,Codex_USGS_raw!$C$2:$C$94,L$4)*Codex_sources!$D$7*Codex_sources!$J$7 | M62: =SUMIFS(Codex_USGS_raw!$E$2:$E$94,Codex_USGS_raw!$A$2:$A$94,Codex_sources!$A$7,Codex_USGS_raw!$C$2:$C$94,M$4)*Codex_sources!$D$7*Codex_sources!$J$7 | ... AN62: =SUMIFS(Codex_USGS_raw!$E$2:$E$94,Codex_USGS_raw!$A$2:$A$94,Codex_sources!$A$7,Codex_USGS_raw!$C$2:$C$94,AN$4)*Codex_sources!$D$7*Codex_sources!$J$7 | AO62: =AO61
C63: MINCoRSV1 | D63: COST | E63: m_cobalt | F63: =Codex_sources!$M$7 | G63: =Codex_sources!$M$7 | H63: =Codex_sources!$M$7 | I63: =Codex_sources!$M$7 | J63: =Codex_sources!$M$7 | K63: =Codex_sources!$M$7 | L63: =Codex_sources!$M$7 | M63: =Codex_sources!$M$7 | ... AN63: =Codex_sources!$M$7 | AO63: =AO62
C64: MINCoRSV2 | D64: BNDACT | F64: =SUMIFS(Codex_USGS_raw!$D$2:$D$94,Codex_USGS_raw!$A$2:$A$94,Codex_sources!$A$7,Codex_USGS_raw!$C$2:$C$94,F$4)*Codex_sources!$D$7*2 | G64: =SUMIFS(Codex_USGS_raw!$D$2:$D$94,Codex_USGS_raw!$A$2:$A$94,Codex_sources!$A$7,Codex_USGS_raw!$C$2:$C$94,G$4)*Codex_sources!$D$7*2 | H64: =SUMIFS(Codex_USGS_raw!$D$2:$D$94,Codex_USGS_raw!$A$2:$A$94,Codex_sources!$A$7,Codex_USGS_raw!$C$2:$C$94,H$4)*Codex_sources!$D$7*2 | I64: =SUMIFS(Codex_USGS_raw!$D$2:$D$94,Codex_USGS_raw!$A$2:$A$94,Codex_sources!$A$7,Codex_USGS_raw!$C$2:$C$94,I$4)*Codex_sources!$D$7*2 | J64: =SUMIFS(Codex_USGS_raw!$D$2:$D$94,Codex_USGS_raw!$A$2:$A$94,Codex_sources!$A$7,Codex_USGS_raw!$C$2:$C$94,J$4)*Codex_sources!$D$7*2 | K64: =SUMIFS(Codex_USGS_raw!$D$2:$D$94,Codex_USGS_raw!$A$2:$A$94,Codex_sources!$A$7,Codex_USGS_raw!$C$2:$C$94,K$4)*Codex_sources!$D$7*2 | L64: =SUMIFS(Codex_USGS_raw!$D$2:$D$94,Codex_USGS_raw!$A$2:$A$94,Codex_sources!$A$7,Codex_USGS_raw!$C$2:$C$94,L$4)*Codex_sources!$D$7*2 | M64: =SUMIFS(Codex_USGS_raw!$D$2:$D$94,Codex_USGS_raw!$A$2:$A$94,Codex_sources!$A$7,Codex_USGS_raw!$C$2:$C$94,M$4)*Codex_sources!$D$7*2 | ... AN64: =SUMIFS(Codex_USGS_raw!$D$2:$D$94,Codex_USGS_raw!$A$2:$A$94,Codex_sources!$A$7,Codex_USGS_raw!$C$2:$C$94,AN$4)*Codex_sources!$D$7*2 | AO64: =AO63
C65: MINCoRSV2 | D65: CUM | F65: =SUMIFS(Codex_USGS_raw!$E$2:$E$94,Codex_USGS_raw!$A$2:$A$94,Codex_sources!$A$7,Codex_USGS_raw!$C$2:$C$94,F$4)*Codex_sources!$D$7*Codex_sources!$K$7 | G65: =SUMIFS(Codex_USGS_raw!$E$2:$E$94,Codex_USGS_raw!$A$2:$A$94,Codex_sources!$A$7,Codex_USGS_raw!$C$2:$C$94,G$4)*Codex_sources!$D$7*Codex_sources!$K$7 | H65: =SUMIFS(Codex_USGS_raw!$E$2:$E$94,Codex_USGS_raw!$A$2:$A$94,Codex_sources!$A$7,Codex_USGS_raw!$C$2:$C$94,H$4)*Codex_sources!$D$7*Codex_sources!$K$7 | I65: =SUMIFS(Codex_USGS_raw!$E$2:$E$94,Codex_USGS_raw!$A$2:$A$94,Codex_sources!$A$7,Codex_USGS_raw!$C$2:$C$94,I$4)*Codex_sources!$D$7*Codex_sources!$K$7 | J65: =SUMIFS(Codex_USGS_raw!$E$2:$E$94,Codex_USGS_raw!$A$2:$A$94,Codex_sources!$A$7,Codex_USGS_raw!$C$2:$C$94,J$4)*Codex_sources!$D$7*Codex_sources!$K$7 | K65: =SUMIFS(Codex_USGS_raw!$E$2:$E$94,Codex_USGS_raw!$A$2:$A$94,Codex_sources!$A$7,Codex_USGS_raw!$C$2:$C$94,K$4)*Codex_sources!$D$7*Codex_sources!$K$7 | L65: =SUMIFS(Codex_USGS_raw!$E$2:$E$94,Codex_USGS_raw!$A$2:$A$94,Codex_sources!$A$7,Codex_USGS_raw!$C$2:$C$94,L$4)*Codex_sources!$D$7*Codex_sources!$K$7 | M65: =SUMIFS(Codex_USGS_raw!$E$2:$E$94,Codex_USGS_raw!$A$2:$A$94,Codex_sources!$A$7,Codex_USGS_raw!$C$2:$C$94,M$4)*Codex_sources!$D$7*Codex_sources!$K$7 | ... AN65: =SUMIFS(Codex_USGS_raw!$E$2:$E$94,Codex_USGS_raw!$A$2:$A$94,Codex_sources!$A$7,Codex_USGS_raw!$C$2:$C$94,AN$4)*Codex_sources!$D$7*Codex_sources!$K$7 | AO65: =AO64
C66: MINCoRSV2 | D66: COST | E66: m_cobalt | F66: =Codex_sources!$N$7 | G66: =Codex_sources!$N$7 | H66: =Codex_sources!$N$7 | I66: =Codex_sources!$N$7 | J66: =Codex_sources!$N$7 | K66: =Codex_sources!$N$7 | L66: =Codex_sources!$N$7 | M66: =Codex_sources!$N$7 | ... AN66: =Codex_sources!$N$7 | AO66: =AO65
C67: MINCoRSV3 | D67: BNDACT | AO67: =AO66
C68: MINCoRSV3 | D68: CUM | F68: =SUMIFS(Codex_USGS_raw!$E$2:$E$94,Codex_USGS_raw!$A$2:$A$94,Codex_sources!$A$7,Codex_USGS_raw!$C$2:$C$94,F$4)*Codex_sources!$D$7*Codex_sources!$L$7 | G68: =SUMIFS(Codex_USGS_raw!$E$2:$E$94,Codex_USGS_raw!$A$2:$A$94,Codex_sources!$A$7,Codex_USGS_raw!$C$2:$C$94,G$4)*Codex_sources!$D$7*Codex_sources!$L$7 | H68: =SUMIFS(Codex_USGS_raw!$E$2:$E$94,Codex_USGS_raw!$A$2:$A$94,Codex_sources!$A$7,Codex_USGS_raw!$C$2:$C$94,H$4)*Codex_sources!$D$7*Codex_sources!$L$7 | I68: =SUMIFS(Codex_USGS_raw!$E$2:$E$94,Codex_USGS_raw!$A$2:$A$94,Codex_sources!$A$7,Codex_USGS_raw!$C$2:$C$94,I$4)*Codex_sources!$D$7*Codex_sources!$L$7 | J68: =SUMIFS(Codex_USGS_raw!$E$2:$E$94,Codex_USGS_raw!$A$2:$A$94,Codex_sources!$A$7,Codex_USGS_raw!$C$2:$C$94,J$4)*Codex_sources!$D$7*Codex_sources!$L$7 | K68: =SUMIFS(Codex_USGS_raw!$E$2:$E$94,Codex_USGS_raw!$A$2:$A$94,Codex_sources!$A$7,Codex_USGS_raw!$C$2:$C$94,K$4)*Codex_sources!$D$7*Codex_sources!$L$7 | L68: =SUMIFS(Codex_USGS_raw!$E$2:$E$94,Codex_USGS_raw!$A$2:$A$94,Codex_sources!$A$7,Codex_USGS_raw!$C$2:$C$94,L$4)*Codex_sources!$D$7*Codex_sources!$L$7 | M68: =SUMIFS(Codex_USGS_raw!$E$2:$E$94,Codex_USGS_raw!$A$2:$A$94,Codex_sources!$A$7,Codex_USGS_raw!$C$2:$C$94,M$4)*Codex_sources!$D$7*Codex_sources!$L$7 | ... AN68: =SUMIFS(Codex_USGS_raw!$E$2:$E$94,Codex_USGS_raw!$A$2:$A$94,Codex_sources!$A$7,Codex_USGS_raw!$C$2:$C$94,AN$4)*Codex_sources!$D$7*Codex_sources!$L$7 | AO68: =AO67
C69: MINCoRSV3 | D69: COST | E69: m_cobalt | F69: =Codex_sources!$O$7 | G69: =Codex_sources!$O$7 | H69: =Codex_sources!$O$7 | I69: =Codex_sources!$O$7 | J69: =Codex_sources!$O$7 | K69: =Codex_sources!$O$7 | L69: =Codex_sources!$O$7 | M69: =Codex_sources!$O$7 | ... AN69: =Codex_sources!$O$7 | AO69: =AO68
AO70: =AO69
C71: MINMnRSV1 | D71: BNDACT | F71: =SUMIFS(Codex_USGS_raw!$D$2:$D$94,Codex_USGS_raw!$A$2:$A$94,Codex_sources!$A$8,Codex_USGS_raw!$C$2:$C$94,F$4)*Codex_sources!$D$8*1 | G71: =SUMIFS(Codex_USGS_raw!$D$2:$D$94,Codex_USGS_raw!$A$2:$A$94,Codex_sources!$A$8,Codex_USGS_raw!$C$2:$C$94,G$4)*Codex_sources!$D$8*1 | H71: =SUMIFS(Codex_USGS_raw!$D$2:$D$94,Codex_USGS_raw!$A$2:$A$94,Codex_sources!$A$8,Codex_USGS_raw!$C$2:$C$94,H$4)*Codex_sources!$D$8*1 | I71: =SUMIFS(Codex_USGS_raw!$D$2:$D$94,Codex_USGS_raw!$A$2:$A$94,Codex_sources!$A$8,Codex_USGS_raw!$C$2:$C$94,I$4)*Codex_sources!$D$8*1 | J71: =SUMIFS(Codex_USGS_raw!$D$2:$D$94,Codex_USGS_raw!$A$2:$A$94,Codex_sources!$A$8,Codex_USGS_raw!$C$2:$C$94,J$4)*Codex_sources!$D$8*1 | K71: =SUMIFS(Codex_USGS_raw!$D$2:$D$94,Codex_USGS_raw!$A$2:$A$94,Codex_sources!$A$8,Codex_USGS_raw!$C$2:$C$94,K$4)*Codex_sources!$D$8*1 | L71: =SUMIFS(Codex_USGS_raw!$D$2:$D$94,Codex_USGS_raw!$A$2:$A$94,Codex_sources!$A$8,Codex_USGS_raw!$C$2:$C$94,L$4)*Codex_sources!$D$8*1 | M71: =SUMIFS(Codex_USGS_raw!$D$2:$D$94,Codex_USGS_raw!$A$2:$A$94,Codex_sources!$A$8,Codex_USGS_raw!$C$2:$C$94,M$4)*Codex_sources!$D$8*1 | ... AN71: =SUMIFS(Codex_USGS_raw!$D$2:$D$94,Codex_USGS_raw!$A$2:$A$94,Codex_sources!$A$8,Codex_USGS_raw!$C$2:$C$94,AN$4)*Codex_sources!$D$8*1 | AO71: =AO70
C72: MINMnRSV1 | D72: CUM | F72: =SUMIFS(Codex_USGS_raw!$E$2:$E$94,Codex_USGS_raw!$A$2:$A$94,Codex_sources!$A$8,Codex_USGS_raw!$C$2:$C$94,F$4)*Codex_sources!$D$8*Codex_sources!$J$8 | G72: =SUMIFS(Codex_USGS_raw!$E$2:$E$94,Codex_USGS_raw!$A$2:$A$94,Codex_sources!$A$8,Codex_USGS_raw!$C$2:$C$94,G$4)*Codex_sources!$D$8*Codex_sources!$J$8 | H72: =SUMIFS(Codex_USGS_raw!$E$2:$E$94,Codex_USGS_raw!$A$2:$A$94,Codex_sources!$A$8,Codex_USGS_raw!$C$2:$C$94,H$4)*Codex_sources!$D$8*Codex_sources!$J$8 | I72: =SUMIFS(Codex_USGS_raw!$E$2:$E$94,Codex_USGS_raw!$A$2:$A$94,Codex_sources!$A$8,Codex_USGS_raw!$C$2:$C$94,I$4)*Codex_sources!$D$8*Codex_sources!$J$8 | J72: =SUMIFS(Codex_USGS_raw!$E$2:$E$94,Codex_USGS_raw!$A$2:$A$94,Codex_sources!$A$8,Codex_USGS_raw!$C$2:$C$94,J$4)*Codex_sources!$D$8*Codex_sources!$J$8 | K72: =SUMIFS(Codex_USGS_raw!$E$2:$E$94,Codex_USGS_raw!$A$2:$A$94,Codex_sources!$A$8,Codex_USGS_raw!$C$2:$C$94,K$4)*Codex_sources!$D$8*Codex_sources!$J$8 | L72: =SUMIFS(Codex_USGS_raw!$E$2:$E$94,Codex_USGS_raw!$A$2:$A$94,Codex_sources!$A$8,Codex_USGS_raw!$C$2:$C$94,L$4)*Codex_sources!$D$8*Codex_sources!$J$8 | M72: =SUMIFS(Codex_USGS_raw!$E$2:$E$94,Codex_USGS_raw!$A$2:$A$94,Codex_sources!$A$8,Codex_USGS_raw!$C$2:$C$94,M$4)*Codex_sources!$D$8*Codex_sources!$J$8 | ... AN72: =SUMIFS(Codex_USGS_raw!$E$2:$E$94,Codex_USGS_raw!$A$2:$A$94,Codex_sources!$A$8,Codex_USGS_raw!$C$2:$C$94,AN$4)*Codex_sources!$D$8*Codex_sources!$J$8 | AO72: =AO71
C73: MINMnRSV1 | D73: COST | E73: m_manganese | F73: =Codex_Regional!F13 | G73: =Codex_Regional!G13 | H73: =Codex_Regional!H13 | I73: =Codex_Regional!I13 | J73: =Codex_Regional!J13 | K73: =Codex_Regional!K13 | L73: =Codex_Regional!L13 | M73: =Codex_Regional!M13 | ... AN73: =Codex_Regional!AN13 | AO73: =AO72
C74: MINMnRSV2 | D74: BNDACT | F74: =SUMIFS(Codex_USGS_raw!$D$2:$D$94,Codex_USGS_raw!$A$2:$A$94,Codex_sources!$A$8,Codex_USGS_raw!$C$2:$C$94,F$4)*Codex_sources!$D$8*2 | G74: =SUMIFS(Codex_USGS_raw!$D$2:$D$94,Codex_USGS_raw!$A$2:$A$94,Codex_sources!$A$8,Codex_USGS_raw!$C$2:$C$94,G$4)*Codex_sources!$D$8*2 | H74: =SUMIFS(Codex_USGS_raw!$D$2:$D$94,Codex_USGS_raw!$A$2:$A$94,Codex_sources!$A$8,Codex_USGS_raw!$C$2:$C$94,H$4)*Codex_sources!$D$8*2 | I74: =SUMIFS(Codex_USGS_raw!$D$2:$D$94,Codex_USGS_raw!$A$2:$A$94,Codex_sources!$A$8,Codex_USGS_raw!$C$2:$C$94,I$4)*Codex_sources!$D$8*2 | J74: =SUMIFS(Codex_USGS_raw!$D$2:$D$94,Codex_USGS_raw!$A$2:$A$94,Codex_sources!$A$8,Codex_USGS_raw!$C$2:$C$94,J$4)*Codex_sources!$D$8*2 | K74: =SUMIFS(Codex_USGS_raw!$D$2:$D$94,Codex_USGS_raw!$A$2:$A$94,Codex_sources!$A$8,Codex_USGS_raw!$C$2:$C$94,K$4)*Codex_sources!$D$8*2 | L74: =SUMIFS(Codex_USGS_raw!$D$2:$D$94,Codex_USGS_raw!$A$2:$A$94,Codex_sources!$A$8,Codex_USGS_raw!$C$2:$C$94,L$4)*Codex_sources!$D$8*2 | M74: =SUMIFS(Codex_USGS_raw!$D$2:$D$94,Codex_USGS_raw!$A$2:$A$94,Codex_sources!$A$8,Codex_USGS_raw!$C$2:$C$94,M$4)*Codex_sources!$D$8*2 | ... AN74: =SUMIFS(Codex_USGS_raw!$D$2:$D$94,Codex_USGS_raw!$A$2:$A$94,Codex_sources!$A$8,Codex_USGS_raw!$C$2:$C$94,AN$4)*Codex_sources!$D$8*2 | AO74: =AO73
C75: MINMnRSV2 | D75: CUM | F75: =SUMIFS(Codex_USGS_raw!$E$2:$E$94,Codex_USGS_raw!$A$2:$A$94,Codex_sources!$A$8,Codex_USGS_raw!$C$2:$C$94,F$4)*Codex_sources!$D$8*Codex_sources!$K$8 | G75: =SUMIFS(Codex_USGS_raw!$E$2:$E$94,Codex_USGS_raw!$A$2:$A$94,Codex_sources!$A$8,Codex_USGS_raw!$C$2:$C$94,G$4)*Codex_sources!$D$8*Codex_sources!$K$8 | H75: =SUMIFS(Codex_USGS_raw!$E$2:$E$94,Codex_USGS_raw!$A$2:$A$94,Codex_sources!$A$8,Codex_USGS_raw!$C$2:$C$94,H$4)*Codex_sources!$D$8*Codex_sources!$K$8 | I75: =SUMIFS(Codex_USGS_raw!$E$2:$E$94,Codex_USGS_raw!$A$2:$A$94,Codex_sources!$A$8,Codex_USGS_raw!$C$2:$C$94,I$4)*Codex_sources!$D$8*Codex_sources!$K$8 | J75: =SUMIFS(Codex_USGS_raw!$E$2:$E$94,Codex_USGS_raw!$A$2:$A$94,Codex_sources!$A$8,Codex_USGS_raw!$C$2:$C$94,J$4)*Codex_sources!$D$8*Codex_sources!$K$8 | K75: =SUMIFS(Codex_USGS_raw!$E$2:$E$94,Codex_USGS_raw!$A$2:$A$94,Codex_sources!$A$8,Codex_USGS_raw!$C$2:$C$94,K$4)*Codex_sources!$D$8*Codex_sources!$K$8 | L75: =SUMIFS(Codex_USGS_raw!$E$2:$E$94,Codex_USGS_raw!$A$2:$A$94,Codex_sources!$A$8,Codex_USGS_raw!$C$2:$C$94,L$4)*Codex_sources!$D$8*Codex_sources!$K$8 | M75: =SUMIFS(Codex_USGS_raw!$E$2:$E$94,Codex_USGS_raw!$A$2:$A$94,Codex_sources!$A$8,Codex_USGS_raw!$C$2:$C$94,M$4)*Codex_sources!$D$8*Codex_sources!$K$8 | ... AN75: =SUMIFS(Codex_USGS_raw!$E$2:$E$94,Codex_USGS_raw!$A$2:$A$94,Codex_sources!$A$8,Codex_USGS_raw!$C$2:$C$94,AN$4)*Codex_sources!$D$8*Codex_sources!$K$8 | AO75: =AO74
C76: MINMnRSV2 | D76: COST | E76: m_manganese | F76: =Codex_Regional!F13*(Codex_sources!$N$8/Codex_sources!$M$8) | G76: =Codex_Regional!G13*(Codex_sources!$N$8/Codex_sources!$M$8) | H76: =Codex_Regional!H13*(Codex_sources!$N$8/Codex_sources!$M$8) | I76: =Codex_Regional!I13*(Codex_sources!$N$8/Codex_sources!$M$8) | J76: =Codex_Regional!J13*(Codex_sources!$N$8/Codex_sources!$M$8) | K76: =Codex_Regional!K13*(Codex_sources!$N$8/Codex_sources!$M$8) | L76: =Codex_Regional!L13*(Codex_sources!$N$8/Codex_sources!$M$8) | M76: =Codex_Regional!M13*(Codex_sources!$N$8/Codex_sources!$M$8) | ... AN76: =Codex_Regional!AN13*(Codex_sources!$N$8/Codex_sources!$M$8) | AO76: =AO75
C77: MINMnRSV3 | D77: BNDACT | AO77: =AO76
C78: MINMnRSV3 | D78: CUM | F78: =SUMIFS(Codex_USGS_raw!$E$2:$E$94,Codex_USGS_raw!$A$2:$A$94,Codex_sources!$A$8,Codex_USGS_raw!$C$2:$C$94,F$4)*Codex_sources!$D$8*Codex_sources!$L$8 | G78: =SUMIFS(Codex_USGS_raw!$E$2:$E$94,Codex_USGS_raw!$A$2:$A$94,Codex_sources!$A$8,Codex_USGS_raw!$C$2:$C$94,G$4)*Codex_sources!$D$8*Codex_sources!$L$8 | H78: =SUMIFS(Codex_USGS_raw!$E$2:$E$94,Codex_USGS_raw!$A$2:$A$94,Codex_sources!$A$8,Codex_USGS_raw!$C$2:$C$94,H$4)*Codex_sources!$D$8*Codex_sources!$L$8 | I78: =SUMIFS(Codex_USGS_raw!$E$2:$E$94,Codex_USGS_raw!$A$2:$A$94,Codex_sources!$A$8,Codex_USGS_raw!$C$2:$C$94,I$4)*Codex_sources!$D$8*Codex_sources!$L$8 | J78: =SUMIFS(Codex_USGS_raw!$E$2:$E$94,Codex_USGS_raw!$A$2:$A$94,Codex_sources!$A$8,Codex_USGS_raw!$C$2:$C$94,J$4)*Codex_sources!$D$8*Codex_sources!$L$8 | K78: =SUMIFS(Codex_USGS_raw!$E$2:$E$94,Codex_USGS_raw!$A$2:$A$94,Codex_sources!$A$8,Codex_USGS_raw!$C$2:$C$94,K$4)*Codex_sources!$D$8*Codex_sources!$L$8 | L78: =SUMIFS(Codex_USGS_raw!$E$2:$E$94,Codex_USGS_raw!$A$2:$A$94,Codex_sources!$A$8,Codex_USGS_raw!$C$2:$C$94,L$4)*Codex_sources!$D$8*Codex_sources!$L$8 | M78: =SUMIFS(Codex_USGS_raw!$E$2:$E$94,Codex_USGS_raw!$A$2:$A$94,Codex_sources!$A$8,Codex_USGS_raw!$C$2:$C$94,M$4)*Codex_sources!$D$8*Codex_sources!$L$8 | ... AN78: =SUMIFS(Codex_USGS_raw!$E$2:$E$94,Codex_USGS_raw!$A$2:$A$94,Codex_sources!$A$8,Codex_USGS_raw!$C$2:$C$94,AN$4)*Codex_sources!$D$8*Codex_sources!$L$8 | AO78: =AO77
C79: MINMnRSV3 | D79: COST | E79: m_manganese | F79: =Codex_Regional!F13*(Codex_sources!$O$8/Codex_sources!$M$8) | G79: =Codex_Regional!G13*(Codex_sources!$O$8/Codex_sources!$M$8) | H79: =Codex_Regional!H13*(Codex_sources!$O$8/Codex_sources!$M$8) | I79: =Codex_Regional!I13*(Codex_sources!$O$8/Codex_sources!$M$8) | J79: =Codex_Regional!J13*(Codex_sources!$O$8/Codex_sources!$M$8) | K79: =Codex_Regional!K13*(Codex_sources!$O$8/Codex_sources!$M$8) | L79: =Codex_Regional!L13*(Codex_sources!$O$8/Codex_sources!$M$8) | M79: =Codex_Regional!M13*(Codex_sources!$O$8/Codex_sources!$M$8) | ... AN79: =Codex_Regional!AN13*(Codex_sources!$O$8/Codex_sources!$M$8) | AO79: =AO78
AO80: =AO79
C81: MINAlRSV1 | D81: BNDACT | F81: =SUMIFS(Codex_USGS_raw!$D$2:$D$94,Codex_USGS_raw!$A$2:$A$94,Codex_sources!$A$9,Codex_USGS_raw!$C$2:$C$94,F$4)*Codex_sources!$D$9*1 | G81: =SUMIFS(Codex_USGS_raw!$D$2:$D$94,Codex_USGS_raw!$A$2:$A$94,Codex_sources!$A$9,Codex_USGS_raw!$C$2:$C$94,G$4)*Codex_sources!$D$9*1 | H81: =SUMIFS(Codex_USGS_raw!$D$2:$D$94,Codex_USGS_raw!$A$2:$A$94,Codex_sources!$A$9,Codex_USGS_raw!$C$2:$C$94,H$4)*Codex_sources!$D$9*1 | I81: =SUMIFS(Codex_USGS_raw!$D$2:$D$94,Codex_USGS_raw!$A$2:$A$94,Codex_sources!$A$9,Codex_USGS_raw!$C$2:$C$94,I$4)*Codex_sources!$D$9*1 | J81: =SUMIFS(Codex_USGS_raw!$D$2:$D$94,Codex_USGS_raw!$A$2:$A$94,Codex_sources!$A$9,Codex_USGS_raw!$C$2:$C$94,J$4)*Codex_sources!$D$9*1 | K81: =SUMIFS(Codex_USGS_raw!$D$2:$D$94,Codex_USGS_raw!$A$2:$A$94,Codex_sources!$A$9,Codex_USGS_raw!$C$2:$C$94,K$4)*Codex_sources!$D$9*1 | L81: =SUMIFS(Codex_USGS_raw!$D$2:$D$94,Codex_USGS_raw!$A$2:$A$94,Codex_sources!$A$9,Codex_USGS_raw!$C$2:$C$94,L$4)*Codex_sources!$D$9*1 | M81: =SUMIFS(Codex_USGS_raw!$D$2:$D$94,Codex_USGS_raw!$A$2:$A$94,Codex_sources!$A$9,Codex_USGS_raw!$C$2:$C$94,M$4)*Codex_sources!$D$9*1 | ... AN81: =SUMIFS(Codex_USGS_raw!$D$2:$D$94,Codex_USGS_raw!$A$2:$A$94,Codex_sources!$A$9,Codex_USGS_raw!$C$2:$C$94,AN$4)*Codex_sources!$D$9*1 | AO81: =AO80
C82: MINAlRSV1 | D82: CUM | F82: =SUMIFS(Codex_USGS_raw!$E$2:$E$94,Codex_USGS_raw!$A$2:$A$94,Codex_sources!$A$9,Codex_USGS_raw!$C$2:$C$94,F$4)*Codex_sources!$D$9*Codex_sources!$J$9 | G82: =SUMIFS(Codex_USGS_raw!$E$2:$E$94,Codex_USGS_raw!$A$2:$A$94,Codex_sources!$A$9,Codex_USGS_raw!$C$2:$C$94,G$4)*Codex_sources!$D$9*Codex_sources!$J$9 | H82: =SUMIFS(Codex_USGS_raw!$E$2:$E$94,Codex_USGS_raw!$A$2:$A$94,Codex_sources!$A$9,Codex_USGS_raw!$C$2:$C$94,H$4)*Codex_sources!$D$9*Codex_sources!$J$9 | I82: =SUMIFS(Codex_USGS_raw!$E$2:$E$94,Codex_USGS_raw!$A$2:$A$94,Codex_sources!$A$9,Codex_USGS_raw!$C$2:$C$94,I$4)*Codex_sources!$D$9*Codex_sources!$J$9 | J82: =SUMIFS(Codex_USGS_raw!$E$2:$E$94,Codex_USGS_raw!$A$2:$A$94,Codex_sources!$A$9,Codex_USGS_raw!$C$2:$C$94,J$4)*Codex_sources!$D$9*Codex_sources!$J$9 | K82: =SUMIFS(Codex_USGS_raw!$E$2:$E$94,Codex_USGS_raw!$A$2:$A$94,Codex_sources!$A$9,Codex_USGS_raw!$C$2:$C$94,K$4)*Codex_sources!$D$9*Codex_sources!$J$9 | L82: =SUMIFS(Codex_USGS_raw!$E$2:$E$94,Codex_USGS_raw!$A$2:$A$94,Codex_sources!$A$9,Codex_USGS_raw!$C$2:$C$94,L$4)*Codex_sources!$D$9*Codex_sources!$J$9 | M82: =SUMIFS(Codex_USGS_raw!$E$2:$E$94,Codex_USGS_raw!$A$2:$A$94,Codex_sources!$A$9,Codex_USGS_raw!$C$2:$C$94,M$4)*Codex_sources!$D$9*Codex_sources!$J$9 | ... AN82: =SUMIFS(Codex_USGS_raw!$E$2:$E$94,Codex_USGS_raw!$A$2:$A$94,Codex_sources!$A$9,Codex_USGS_raw!$C$2:$C$94,AN$4)*Codex_sources!$D$9*Codex_sources!$J$9 | AO82: =AO81
C83: MINAlRSV1 | D83: COST | E83: m_aluminum | F83: =Codex_Regional!F16 | G83: =Codex_Regional!G16 | H83: =Codex_Regional!H16 | I83: =Codex_Regional!I16 | J83: =Codex_Regional!J16 | K83: =Codex_Regional!K16 | L83: =Codex_Regional!L16 | M83: =Codex_Regional!M16 | ... AN83: =Codex_Regional!AN16 | AO83: =AO82
C84: MINAlRSV2 | D84: BNDACT | F84: =SUMIFS(Codex_USGS_raw!$D$2:$D$94,Codex_USGS_raw!$A$2:$A$94,Codex_sources!$A$9,Codex_USGS_raw!$C$2:$C$94,F$4)*Codex_sources!$D$9*2 | G84: =SUMIFS(Codex_USGS_raw!$D$2:$D$94,Codex_USGS_raw!$A$2:$A$94,Codex_sources!$A$9,Codex_USGS_raw!$C$2:$C$94,G$4)*Codex_sources!$D$9*2 | H84: =SUMIFS(Codex_USGS_raw!$D$2:$D$94,Codex_USGS_raw!$A$2:$A$94,Codex_sources!$A$9,Codex_USGS_raw!$C$2:$C$94,H$4)*Codex_sources!$D$9*2 | I84: =SUMIFS(Codex_USGS_raw!$D$2:$D$94,Codex_USGS_raw!$A$2:$A$94,Codex_sources!$A$9,Codex_USGS_raw!$C$2:$C$94,I$4)*Codex_sources!$D$9*2 | J84: =SUMIFS(Codex_USGS_raw!$D$2:$D$94,Codex_USGS_raw!$A$2:$A$94,Codex_sources!$A$9,Codex_USGS_raw!$C$2:$C$94,J$4)*Codex_sources!$D$9*2 | K84: =SUMIFS(Codex_USGS_raw!$D$2:$D$94,Codex_USGS_raw!$A$2:$A$94,Codex_sources!$A$9,Codex_USGS_raw!$C$2:$C$94,K$4)*Codex_sources!$D$9*2 | L84: =SUMIFS(Codex_USGS_raw!$D$2:$D$94,Codex_USGS_raw!$A$2:$A$94,Codex_sources!$A$9,Codex_USGS_raw!$C$2:$C$94,L$4)*Codex_sources!$D$9*2 | M84: =SUMIFS(Codex_USGS_raw!$D$2:$D$94,Codex_USGS_raw!$A$2:$A$94,Codex_sources!$A$9,Codex_USGS_raw!$C$2:$C$94,M$4)*Codex_sources!$D$9*2 | ... AN84: =SUMIFS(Codex_USGS_raw!$D$2:$D$94,Codex_USGS_raw!$A$2:$A$94,Codex_sources!$A$9,Codex_USGS_raw!$C$2:$C$94,AN$4)*Codex_sources!$D$9*2 | AO84: =AO83
C85: MINAlRSV2 | D85: CUM | F85: =SUMIFS(Codex_USGS_raw!$E$2:$E$94,Codex_USGS_raw!$A$2:$A$94,Codex_sources!$A$9,Codex_USGS_raw!$C$2:$C$94,F$4)*Codex_sources!$D$9*Codex_sources!$K$9 | G85: =SUMIFS(Codex_USGS_raw!$E$2:$E$94,Codex_USGS_raw!$A$2:$A$94,Codex_sources!$A$9,Codex_USGS_raw!$C$2:$C$94,G$4)*Codex_sources!$D$9*Codex_sources!$K$9 | H85: =SUMIFS(Codex_USGS_raw!$E$2:$E$94,Codex_USGS_raw!$A$2:$A$94,Codex_sources!$A$9,Codex_USGS_raw!$C$2:$C$94,H$4)*Codex_sources!$D$9*Codex_sources!$K$9 | I85: =SUMIFS(Codex_USGS_raw!$E$2:$E$94,Codex_USGS_raw!$A$2:$A$94,Codex_sources!$A$9,Codex_USGS_raw!$C$2:$C$94,I$4)*Codex_sources!$D$9*Codex_sources!$K$9 | J85: =SUMIFS(Codex_USGS_raw!$E$2:$E$94,Codex_USGS_raw!$A$2:$A$94,Codex_sources!$A$9,Codex_USGS_raw!$C$2:$C$94,J$4)*Codex_sources!$D$9*Codex_sources!$K$9 | K85: =SUMIFS(Codex_USGS_raw!$E$2:$E$94,Codex_USGS_raw!$A$2:$A$94,Codex_sources!$A$9,Codex_USGS_raw!$C$2:$C$94,K$4)*Codex_sources!$D$9*Codex_sources!$K$9 | L85: =SUMIFS(Codex_USGS_raw!$E$2:$E$94,Codex_USGS_raw!$A$2:$A$94,Codex_sources!$A$9,Codex_USGS_raw!$C$2:$C$94,L$4)*Codex_sources!$D$9*Codex_sources!$K$9 | M85: =SUMIFS(Codex_USGS_raw!$E$2:$E$94,Codex_USGS_raw!$A$2:$A$94,Codex_sources!$A$9,Codex_USGS_raw!$C$2:$C$94,M$4)*Codex_sources!$D$9*Codex_sources!$K$9 | ... AN85: =SUMIFS(Codex_USGS_raw!$E$2:$E$94,Codex_USGS_raw!$A$2:$A$94,Codex_sources!$A$9,Codex_USGS_raw!$C$2:$C$94,AN$4)*Codex_sources!$D$9*Codex_sources!$K$9 | AO85: =AO84
C86: MINAlRSV2 | D86: COST | E86: m_aluminum | F86: =Codex_Regional!F16*(Codex_sources!$N$9/Codex_sources!$M$9) | G86: =Codex_Regional!G16*(Codex_sources!$N$9/Codex_sources!$M$9) | H86: =Codex_Regional!H16*(Codex_sources!$N$9/Codex_sources!$M$9) | I86: =Codex_Regional!I16*(Codex_sources!$N$9/Codex_sources!$M$9) | J86: =Codex_Regional!J16*(Codex_sources!$N$9/Codex_sources!$M$9) | K86: =Codex_Regional!K16*(Codex_sources!$N$9/Codex_sources!$M$9) | L86: =Codex_Regional!L16*(Codex_sources!$N$9/Codex_sources!$M$9) | M86: =Codex_Regional!M16*(Codex_sources!$N$9/Codex_sources!$M$9) | ... AN86: =Codex_Regional!AN16*(Codex_sources!$N$9/Codex_sources!$M$9) | AO86: =AO85
C87: MINAlRSV3 | D87: BNDACT | AO87: =AO86
C88: MINAlRSV3 | D88: CUM | F88: =SUMIFS(Codex_USGS_raw!$E$2:$E$94,Codex_USGS_raw!$A$2:$A$94,Codex_sources!$A$9,Codex_USGS_raw!$C$2:$C$94,F$4)*Codex_sources!$D$9*Codex_sources!$L$9 | G88: =SUMIFS(Codex_USGS_raw!$E$2:$E$94,Codex_USGS_raw!$A$2:$A$94,Codex_sources!$A$9,Codex_USGS_raw!$C$2:$C$94,G$4)*Codex_sources!$D$9*Codex_sources!$L$9 | H88: =SUMIFS(Codex_USGS_raw!$E$2:$E$94,Codex_USGS_raw!$A$2:$A$94,Codex_sources!$A$9,Codex_USGS_raw!$C$2:$C$94,H$4)*Codex_sources!$D$9*Codex_sources!$L$9 | I88: =SUMIFS(Codex_USGS_raw!$E$2:$E$94,Codex_USGS_raw!$A$2:$A$94,Codex_sources!$A$9,Codex_USGS_raw!$C$2:$C$94,I$4)*Codex_sources!$D$9*Codex_sources!$L$9 | J88: =SUMIFS(Codex_USGS_raw!$E$2:$E$94,Codex_USGS_raw!$A$2:$A$94,Codex_sources!$A$9,Codex_USGS_raw!$C$2:$C$94,J$4)*Codex_sources!$D$9*Codex_sources!$L$9 | K88: =SUMIFS(Codex_USGS_raw!$E$2:$E$94,Codex_USGS_raw!$A$2:$A$94,Codex_sources!$A$9,Codex_USGS_raw!$C$2:$C$94,K$4)*Codex_sources!$D$9*Codex_sources!$L$9 | L88: =SUMIFS(Codex_USGS_raw!$E$2:$E$94,Codex_USGS_raw!$A$2:$A$94,Codex_sources!$A$9,Codex_USGS_raw!$C$2:$C$94,L$4)*Codex_sources!$D$9*Codex_sources!$L$9 | M88: =SUMIFS(Codex_USGS_raw!$E$2:$E$94,Codex_USGS_raw!$A$2:$A$94,Codex_sources!$A$9,Codex_USGS_raw!$C$2:$C$94,M$4)*Codex_sources!$D$9*Codex_sources!$L$9 | ... AN88: =SUMIFS(Codex_USGS_raw!$E$2:$E$94,Codex_USGS_raw!$A$2:$A$94,Codex_sources!$A$9,Codex_USGS_raw!$C$2:$C$94,AN$4)*Codex_sources!$D$9*Codex_sources!$L$9 | AO88: =AO87
C89: MINAlRSV3 | D89: COST | E89: m_aluminum | F89: =Codex_Regional!F16*(Codex_sources!$O$9/Codex_sources!$M$9) | G89: =Codex_Regional!G16*(Codex_sources!$O$9/Codex_sources!$M$9) | H89: =Codex_Regional!H16*(Codex_sources!$O$9/Codex_sources!$M$9) | I89: =Codex_Regional!I16*(Codex_sources!$O$9/Codex_sources!$M$9) | J89: =Codex_Regional!J16*(Codex_sources!$O$9/Codex_sources!$M$9) | K89: =Codex_Regional!K16*(Codex_sources!$O$9/Codex_sources!$M$9) | L89: =Codex_Regional!L16*(Codex_sources!$O$9/Codex_sources!$M$9) | M89: =Codex_Regional!M16*(Codex_sources!$O$9/Codex_sources!$M$9) | ... AN89: =Codex_Regional!AN16*(Codex_sources!$O$9/Codex_sources!$M$9) | AO89: =AO88
AO90: =AO89
C91: MINCuRSV1 | D91: BNDACT | F91: =SUMIFS(Codex_USGS_raw!$D$2:$D$94,Codex_USGS_raw!$A$2:$A$94,Codex_sources!$A$10,Codex_USGS_raw!$C$2:$C$94,F$4)*Codex_sources!$D$10*1 | G91: =SUMIFS(Codex_USGS_raw!$D$2:$D$94,Codex_USGS_raw!$A$2:$A$94,Codex_sources!$A$10,Codex_USGS_raw!$C$2:$C$94,G$4)*Codex_sources!$D$10*1 | H91: =SUMIFS(Codex_USGS_raw!$D$2:$D$94,Codex_USGS_raw!$A$2:$A$94,Codex_sources!$A$10,Codex_USGS_raw!$C$2:$C$94,H$4)*Codex_sources!$D$10*1 | I91: =SUMIFS(Codex_USGS_raw!$D$2:$D$94,Codex_USGS_raw!$A$2:$A$94,Codex_sources!$A$10,Codex_USGS_raw!$C$2:$C$94,I$4)*Codex_sources!$D$10*1 | J91: =SUMIFS(Codex_USGS_raw!$D$2:$D$94,Codex_USGS_raw!$A$2:$A$94,Codex_sources!$A$10,Codex_USGS_raw!$C$2:$C$94,J$4)*Codex_sources!$D$10*1 | K91: =SUMIFS(Codex_USGS_raw!$D$2:$D$94,Codex_USGS_raw!$A$2:$A$94,Codex_sources!$A$10,Codex_USGS_raw!$C$2:$C$94,K$4)*Codex_sources!$D$10*1 | L91: =SUMIFS(Codex_USGS_raw!$D$2:$D$94,Codex_USGS_raw!$A$2:$A$94,Codex_sources!$A$10,Codex_USGS_raw!$C$2:$C$94,L$4)*Codex_sources!$D$10*1 | M91: =SUMIFS(Codex_USGS_raw!$D$2:$D$94,Codex_USGS_raw!$A$2:$A$94,Codex_sources!$A$10,Codex_USGS_raw!$C$2:$C$94,M$4)*Codex_sources!$D$10*1 | ... AN91: =SUMIFS(Codex_USGS_raw!$D$2:$D$94,Codex_USGS_raw!$A$2:$A$94,Codex_sources!$A$10,Codex_USGS_raw!$C$2:$C$94,AN$4)*Codex_sources!$D$10*1 | AO91: =AO90
C92: MINCuRSV1 | D92: CUM | F92: =SUMIFS(Codex_USGS_raw!$E$2:$E$94,Codex_USGS_raw!$A$2:$A$94,Codex_sources!$A$10,Codex_USGS_raw!$C$2:$C$94,F$4)*Codex_sources!$D$10*Codex_sources!$J$10 | G92: =SUMIFS(Codex_USGS_raw!$E$2:$E$94,Codex_USGS_raw!$A$2:$A$94,Codex_sources!$A$10,Codex_USGS_raw!$C$2:$C$94,G$4)*Codex_sources!$D$10*Codex_sources!$J$10 | H92: =SUMIFS(Codex_USGS_raw!$E$2:$E$94,Codex_USGS_raw!$A$2:$A$94,Codex_sources!$A$10,Codex_USGS_raw!$C$2:$C$94,H$4)*Codex_sources!$D$10*Codex_sources!$J$10 | I92: =SUMIFS(Codex_USGS_raw!$E$2:$E$94,Codex_USGS_raw!$A$2:$A$94,Codex_sources!$A$10,Codex_USGS_raw!$C$2:$C$94,I$4)*Codex_sources!$D$10*Codex_sources!$J$10 | J92: =SUMIFS(Codex_USGS_raw!$E$2:$E$94,Codex_USGS_raw!$A$2:$A$94,Codex_sources!$A$10,Codex_USGS_raw!$C$2:$C$94,J$4)*Codex_sources!$D$10*Codex_sources!$J$10 | K92: =SUMIFS(Codex_USGS_raw!$E$2:$E$94,Codex_USGS_raw!$A$2:$A$94,Codex_sources!$A$10,Codex_USGS_raw!$C$2:$C$94,K$4)*Codex_sources!$D$10*Codex_sources!$J$10 | L92: =SUMIFS(Codex_USGS_raw!$E$2:$E$94,Codex_USGS_raw!$A$2:$A$94,Codex_sources!$A$10,Codex_USGS_raw!$C$2:$C$94,L$4)*Codex_sources!$D$10*Codex_sources!$J$10 | M92: =SUMIFS(Codex_USGS_raw!$E$2:$E$94,Codex_USGS_raw!$A$2:$A$94,Codex_sources!$A$10,Codex_USGS_raw!$C$2:$C$94,M$4)*Codex_sources!$D$10*Codex_sources!$J$10 | ... AN92: =SUMIFS(Codex_USGS_raw!$E$2:$E$94,Codex_USGS_raw!$A$2:$A$94,Codex_sources!$A$10,Codex_USGS_raw!$C$2:$C$94,AN$4)*Codex_sources!$D$10*Codex_sources!$J$10 | AO92: =AO91
C93: MINCuRSV1 | D93: COST | E93: m_copper | F93: =Codex_Regional!F19 | G93: =Codex_Regional!G19 | H93: =Codex_Regional!H19 | I93: =Codex_Regional!I19 | J93: =Codex_Regional!J19 | K93: =Codex_Regional!K19 | L93: =Codex_Regional!L19 | M93: =Codex_Regional!M19 | ... AN93: =Codex_Regional!AN19 | AO93: =AO92
C94: MINCuRSV2 | D94: BNDACT | F94: =SUMIFS(Codex_USGS_raw!$D$2:$D$94,Codex_USGS_raw!$A$2:$A$94,Codex_sources!$A$10,Codex_USGS_raw!$C$2:$C$94,F$4)*Codex_sources!$D$10*2 | G94: =SUMIFS(Codex_USGS_raw!$D$2:$D$94,Codex_USGS_raw!$A$2:$A$94,Codex_sources!$A$10,Codex_USGS_raw!$C$2:$C$94,G$4)*Codex_sources!$D$10*2 | H94: =SUMIFS(Codex_USGS_raw!$D$2:$D$94,Codex_USGS_raw!$A$2:$A$94,Codex_sources!$A$10,Codex_USGS_raw!$C$2:$C$94,H$4)*Codex_sources!$D$10*2 | I94: =SUMIFS(Codex_USGS_raw!$D$2:$D$94,Codex_USGS_raw!$A$2:$A$94,Codex_sources!$A$10,Codex_USGS_raw!$C$2:$C$94,I$4)*Codex_sources!$D$10*2 | J94: =SUMIFS(Codex_USGS_raw!$D$2:$D$94,Codex_USGS_raw!$A$2:$A$94,Codex_sources!$A$10,Codex_USGS_raw!$C$2:$C$94,J$4)*Codex_sources!$D$10*2 | K94: =SUMIFS(Codex_USGS_raw!$D$2:$D$94,Codex_USGS_raw!$A$2:$A$94,Codex_sources!$A$10,Codex_USGS_raw!$C$2:$C$94,K$4)*Codex_sources!$D$10*2 | L94: =SUMIFS(Codex_USGS_raw!$D$2:$D$94,Codex_USGS_raw!$A$2:$A$94,Codex_sources!$A$10,Codex_USGS_raw!$C$2:$C$94,L$4)*Codex_sources!$D$10*2 | M94: =SUMIFS(Codex_USGS_raw!$D$2:$D$94,Codex_USGS_raw!$A$2:$A$94,Codex_sources!$A$10,Codex_USGS_raw!$C$2:$C$94,M$4)*Codex_sources!$D$10*2 | ... AN94: =SUMIFS(Codex_USGS_raw!$D$2:$D$94,Codex_USGS_raw!$A$2:$A$94,Codex_sources!$A$10,Codex_USGS_raw!$C$2:$C$94,AN$4)*Codex_sources!$D$10*2 | AO94: =AO93
C95: MINCuRSV2 | D95: CUM | F95: =SUMIFS(Codex_USGS_raw!$E$2:$E$94,Codex_USGS_raw!$A$2:$A$94,Codex_sources!$A$10,Codex_USGS_raw!$C$2:$C$94,F$4)*Codex_sources!$D$10*Codex_sources!$K$10 | G95: =SUMIFS(Codex_USGS_raw!$E$2:$E$94,Codex_USGS_raw!$A$2:$A$94,Codex_sources!$A$10,Codex_USGS_raw!$C$2:$C$94,G$4)*Codex_sources!$D$10*Codex_sources!$K$10 | H95: =SUMIFS(Codex_USGS_raw!$E$2:$E$94,Codex_USGS_raw!$A$2:$A$94,Codex_sources!$A$10,Codex_USGS_raw!$C$2:$C$94,H$4)*Codex_sources!$D$10*Codex_sources!$K$10 | I95: =SUMIFS(Codex_USGS_raw!$E$2:$E$94,Codex_USGS_raw!$A$2:$A$94,Codex_sources!$A$10,Codex_USGS_raw!$C$2:$C$94,I$4)*Codex_sources!$D$10*Codex_sources!$K$10 | J95: =SUMIFS(Codex_USGS_raw!$E$2:$E$94,Codex_USGS_raw!$A$2:$A$94,Codex_sources!$A$10,Codex_USGS_raw!$C$2:$C$94,J$4)*Codex_sources!$D$10*Codex_sources!$K$10 | K95: =SUMIFS(Codex_USGS_raw!$E$2:$E$94,Codex_USGS_raw!$A$2:$A$94,Codex_sources!$A$10,Codex_USGS_raw!$C$2:$C$94,K$4)*Codex_sources!$D$10*Codex_sources!$K$10 | L95: =SUMIFS(Codex_USGS_raw!$E$2:$E$94,Codex_USGS_raw!$A$2:$A$94,Codex_sources!$A$10,Codex_USGS_raw!$C$2:$C$94,L$4)*Codex_sources!$D$10*Codex_sources!$K$10 | M95: =SUMIFS(Codex_USGS_raw!$E$2:$E$94,Codex_USGS_raw!$A$2:$A$94,Codex_sources!$A$10,Codex_USGS_raw!$C$2:$C$94,M$4)*Codex_sources!$D$10*Codex_sources!$K$10 | ... AN95: =SUMIFS(Codex_USGS_raw!$E$2:$E$94,Codex_USGS_raw!$A$2:$A$94,Codex_sources!$A$10,Codex_USGS_raw!$C$2:$C$94,AN$4)*Codex_sources!$D$10*Codex_sources!$K$10 | AO95: =AO94
C96: MINCuRSV2 | D96: COST | E96: m_copper | F96: =Codex_Regional!F19*(Codex_sources!$N$10/Codex_sources!$M$10) | G96: =Codex_Regional!G19*(Codex_sources!$N$10/Codex_sources!$M$10) | H96: =Codex_Regional!H19*(Codex_sources!$N$10/Codex_sources!$M$10) | I96: =Codex_Regional!I19*(Codex_sources!$N$10/Codex_sources!$M$10) | J96: =Codex_Regional!J19*(Codex_sources!$N$10/Codex_sources!$M$10) | K96: =Codex_Regional!K19*(Codex_sources!$N$10/Codex_sources!$M$10) | L96: =Codex_Regional!L19*(Codex_sources!$N$10/Codex_sources!$M$10) | M96: =Codex_Regional!M19*(Codex_sources!$N$10/Codex_sources!$M$10) | ... AN96: =Codex_Regional!AN19*(Codex_sources!$N$10/Codex_sources!$M$10) | AO96: =AO95
C97: MINCuRSV3 | D97: BNDACT | AO97: =AO96
C98: MINCuRSV3 | D98: CUM | F98: =SUMIFS(Codex_USGS_raw!$E$2:$E$94,Codex_USGS_raw!$A$2:$A$94,Codex_sources!$A$10,Codex_USGS_raw!$C$2:$C$94,F$4)*Codex_sources!$D$10*Codex_sources!$L$10 | G98: =SUMIFS(Codex_USGS_raw!$E$2:$E$94,Codex_USGS_raw!$A$2:$A$94,Codex_sources!$A$10,Codex_USGS_raw!$C$2:$C$94,G$4)*Codex_sources!$D$10*Codex_sources!$L$10 | H98: =SUMIFS(Codex_USGS_raw!$E$2:$E$94,Codex_USGS_raw!$A$2:$A$94,Codex_sources!$A$10,Codex_USGS_raw!$C$2:$C$94,H$4)*Codex_sources!$D$10*Codex_sources!$L$10 | I98: =SUMIFS(Codex_USGS_raw!$E$2:$E$94,Codex_USGS_raw!$A$2:$A$94,Codex_sources!$A$10,Codex_USGS_raw!$C$2:$C$94,I$4)*Codex_sources!$D$10*Codex_sources!$L$10 | J98: =SUMIFS(Codex_USGS_raw!$E$2:$E$94,Codex_USGS_raw!$A$2:$A$94,Codex_sources!$A$10,Codex_USGS_raw!$C$2:$C$94,J$4)*Codex_sources!$D$10*Codex_sources!$L$10 | K98: =SUMIFS(Codex_USGS_raw!$E$2:$E$94,Codex_USGS_raw!$A$2:$A$94,Codex_sources!$A$10,Codex_USGS_raw!$C$2:$C$94,K$4)*Codex_sources!$D$10*Codex_sources!$L$10 | L98: =SUMIFS(Codex_USGS_raw!$E$2:$E$94,Codex_USGS_raw!$A$2:$A$94,Codex_sources!$A$10,Codex_USGS_raw!$C$2:$C$94,L$4)*Codex_sources!$D$10*Codex_sources!$L$10 | M98: =SUMIFS(Codex_USGS_raw!$E$2:$E$94,Codex_USGS_raw!$A$2:$A$94,Codex_sources!$A$10,Codex_USGS_raw!$C$2:$C$94,M$4)*Codex_sources!$D$10*Codex_sources!$L$10 | ... AN98: =SUMIFS(Codex_USGS_raw!$E$2:$E$94,Codex_USGS_raw!$A$2:$A$94,Codex_sources!$A$10,Codex_USGS_raw!$C$2:$C$94,AN$4)*Codex_sources!$D$10*Codex_sources!$L$10 | AO98: =AO97
C99: MINCuRSV3 | D99: COST | E99: m_copper | F99: =Codex_Regional!F19*(Codex_sources!$O$10/Codex_sources!$M$10) | G99: =Codex_Regional!G19*(Codex_sources!$O$10/Codex_sources!$M$10) | H99: =Codex_Regional!H19*(Codex_sources!$O$10/Codex_sources!$M$10) | I99: =Codex_Regional!I19*(Codex_sources!$O$10/Codex_sources!$M$10) | J99: =Codex_Regional!J19*(Codex_sources!$O$10/Codex_sources!$M$10) | K99: =Codex_Regional!K19*(Codex_sources!$O$10/Codex_sources!$M$10) | L99: =Codex_Regional!L19*(Codex_sources!$O$10/Codex_sources!$M$10) | M99: =Codex_Regional!M19*(Codex_sources!$O$10/Codex_sources!$M$10) | ... AN99: =Codex_Regional!AN19*(Codex_sources!$O$10/Codex_sources!$M$10) | AO99: =AO98
AO100: =AO99
C101: MINGrRSV1 | D101: BNDACT | F101: =SUMIFS(Codex_USGS_raw!$D$2:$D$94,Codex_USGS_raw!$A$2:$A$94,Codex_sources!$A$11,Codex_USGS_raw!$C$2:$C$94,F$4)*Codex_sources!$D$11*1 | G101: =SUMIFS(Codex_USGS_raw!$D$2:$D$94,Codex_USGS_raw!$A$2:$A$94,Codex_sources!$A$11,Codex_USGS_raw!$C$2:$C$94,G$4)*Codex_sources!$D$11*1 | H101: =SUMIFS(Codex_USGS_raw!$D$2:$D$94,Codex_USGS_raw!$A$2:$A$94,Codex_sources!$A$11,Codex_USGS_raw!$C$2:$C$94,H$4)*Codex_sources!$D$11*1 | I101: =SUMIFS(Codex_USGS_raw!$D$2:$D$94,Codex_USGS_raw!$A$2:$A$94,Codex_sources!$A$11,Codex_USGS_raw!$C$2:$C$94,I$4)*Codex_sources!$D$11*1 | J101: =SUMIFS(Codex_USGS_raw!$D$2:$D$94,Codex_USGS_raw!$A$2:$A$94,Codex_sources!$A$11,Codex_USGS_raw!$C$2:$C$94,J$4)*Codex_sources!$D$11*1 | K101: =SUMIFS(Codex_USGS_raw!$D$2:$D$94,Codex_USGS_raw!$A$2:$A$94,Codex_sources!$A$11,Codex_USGS_raw!$C$2:$C$94,K$4)*Codex_sources!$D$11*1 | L101: =SUMIFS(Codex_USGS_raw!$D$2:$D$94,Codex_USGS_raw!$A$2:$A$94,Codex_sources!$A$11,Codex_USGS_raw!$C$2:$C$94,L$4)*Codex_sources!$D$11*1 | M101: =SUMIFS(Codex_USGS_raw!$D$2:$D$94,Codex_USGS_raw!$A$2:$A$94,Codex_sources!$A$11,Codex_USGS_raw!$C$2:$C$94,M$4)*Codex_sources!$D$11*1 | ... AN101: =SUMIFS(Codex_USGS_raw!$D$2:$D$94,Codex_USGS_raw!$A$2:$A$94,Codex_sources!$A$11,Codex_USGS_raw!$C$2:$C$94,AN$4)*Codex_sources!$D$11*1 | AO101: =AO100
C102: MINGrRSV1 | D102: CUM | F102: =SUMIFS(Codex_USGS_raw!$E$2:$E$94,Codex_USGS_raw!$A$2:$A$94,Codex_sources!$A$11,Codex_USGS_raw!$C$2:$C$94,F$4)*Codex_sources!$D$11*Codex_sources!$J$11 | G102: =SUMIFS(Codex_USGS_raw!$E$2:$E$94,Codex_USGS_raw!$A$2:$A$94,Codex_sources!$A$11,Codex_USGS_raw!$C$2:$C$94,G$4)*Codex_sources!$D$11*Codex_sources!$J$11 | H102: =SUMIFS(Codex_USGS_raw!$E$2:$E$94,Codex_USGS_raw!$A$2:$A$94,Codex_sources!$A$11,Codex_USGS_raw!$C$2:$C$94,H$4)*Codex_sources!$D$11*Codex_sources!$J$11 | I102: =SUMIFS(Codex_USGS_raw!$E$2:$E$94,Codex_USGS_raw!$A$2:$A$94,Codex_sources!$A$11,Codex_USGS_raw!$C$2:$C$94,I$4)*Codex_sources!$D$11*Codex_sources!$J$11 | J102: =SUMIFS(Codex_USGS_raw!$E$2:$E$94,Codex_USGS_raw!$A$2:$A$94,Codex_sources!$A$11,Codex_USGS_raw!$C$2:$C$94,J$4)*Codex_sources!$D$11*Codex_sources!$J$11 | K102: =SUMIFS(Codex_USGS_raw!$E$2:$E$94,Codex_USGS_raw!$A$2:$A$94,Codex_sources!$A$11,Codex_USGS_raw!$C$2:$C$94,K$4)*Codex_sources!$D$11*Codex_sources!$J$11 | L102: =SUMIFS(Codex_USGS_raw!$E$2:$E$94,Codex_USGS_raw!$A$2:$A$94,Codex_sources!$A$11,Codex_USGS_raw!$C$2:$C$94,L$4)*Codex_sources!$D$11*Codex_sources!$J$11 | M102: =SUMIFS(Codex_USGS_raw!$E$2:$E$94,Codex_USGS_raw!$A$2:$A$94,Codex_sources!$A$11,Codex_USGS_raw!$C$2:$C$94,M$4)*Codex_sources!$D$11*Codex_sources!$J$11 | ... AN102: =SUMIFS(Codex_USGS_raw!$E$2:$E$94,Codex_USGS_raw!$A$2:$A$94,Codex_sources!$A$11,Codex_USGS_raw!$C$2:$C$94,AN$4)*Codex_sources!$D$11*Codex_sources!$J$11 | AO102: =AO101
C103: MINGrRSV1 | D103: COST | E103: m_graphite | F103: =Codex_Regional!F22 | G103: =Codex_Regional!G22 | H103: =Codex_Regional!H22 | I103: =Codex_Regional!I22 | J103: =Codex_Regional!J22 | K103: =Codex_Regional!K22 | L103: =Codex_Regional!L22 | M103: =Codex_Regional!M22 | ... AN103: =Codex_Regional!AN22 | AO103: =AO102
C104: MINGrRSV2 | D104: BNDACT | F104: =SUMIFS(Codex_USGS_raw!$D$2:$D$94,Codex_USGS_raw!$A$2:$A$94,Codex_sources!$A$11,Codex_USGS_raw!$C$2:$C$94,F$4)*Codex_sources!$D$11*2 | G104: =SUMIFS(Codex_USGS_raw!$D$2:$D$94,Codex_USGS_raw!$A$2:$A$94,Codex_sources!$A$11,Codex_USGS_raw!$C$2:$C$94,G$4)*Codex_sources!$D$11*2 | H104: =SUMIFS(Codex_USGS_raw!$D$2:$D$94,Codex_USGS_raw!$A$2:$A$94,Codex_sources!$A$11,Codex_USGS_raw!$C$2:$C$94,H$4)*Codex_sources!$D$11*2 | I104: =SUMIFS(Codex_USGS_raw!$D$2:$D$94,Codex_USGS_raw!$A$2:$A$94,Codex_sources!$A$11,Codex_USGS_raw!$C$2:$C$94,I$4)*Codex_sources!$D$11*2 | J104: =SUMIFS(Codex_USGS_raw!$D$2:$D$94,Codex_USGS_raw!$A$2:$A$94,Codex_sources!$A$11,Codex_USGS_raw!$C$2:$C$94,J$4)*Codex_sources!$D$11*2 | K104: =SUMIFS(Codex_USGS_raw!$D$2:$D$94,Codex_USGS_raw!$A$2:$A$94,Codex_sources!$A$11,Codex_USGS_raw!$C$2:$C$94,K$4)*Codex_sources!$D$11*2 | L104: =SUMIFS(Codex_USGS_raw!$D$2:$D$94,Codex_USGS_raw!$A$2:$A$94,Codex_sources!$A$11,Codex_USGS_raw!$C$2:$C$94,L$4)*Codex_sources!$D$11*2 | M104: =SUMIFS(Codex_USGS_raw!$D$2:$D$94,Codex_USGS_raw!$A$2:$A$94,Codex_sources!$A$11,Codex_USGS_raw!$C$2:$C$94,M$4)*Codex_sources!$D$11*2 | ... AN104: =SUMIFS(Codex_USGS_raw!$D$2:$D$94,Codex_USGS_raw!$A$2:$A$94,Codex_sources!$A$11,Codex_USGS_raw!$C$2:$C$94,AN$4)*Codex_sources!$D$11*2 | AO104: =AO103
C105: MINGrRSV2 | D105: CUM | F105: =SUMIFS(Codex_USGS_raw!$E$2:$E$94,Codex_USGS_raw!$A$2:$A$94,Codex_sources!$A$11,Codex_USGS_raw!$C$2:$C$94,F$4)*Codex_sources!$D$11*Codex_sources!$K$11 | G105: =SUMIFS(Codex_USGS_raw!$E$2:$E$94,Codex_USGS_raw!$A$2:$A$94,Codex_sources!$A$11,Codex_USGS_raw!$C$2:$C$94,G$4)*Codex_sources!$D$11*Codex_sources!$K$11 | H105: =SUMIFS(Codex_USGS_raw!$E$2:$E$94,Codex_USGS_raw!$A$2:$A$94,Codex_sources!$A$11,Codex_USGS_raw!$C$2:$C$94,H$4)*Codex_sources!$D$11*Codex_sources!$K$11 | I105: =SUMIFS(Codex_USGS_raw!$E$2:$E$94,Codex_USGS_raw!$A$2:$A$94,Codex_sources!$A$11,Codex_USGS_raw!$C$2:$C$94,I$4)*Codex_sources!$D$11*Codex_sources!$K$11 | J105: =SUMIFS(Codex_USGS_raw!$E$2:$E$94,Codex_USGS_raw!$A$2:$A$94,Codex_sources!$A$11,Codex_USGS_raw!$C$2:$C$94,J$4)*Codex_sources!$D$11*Codex_sources!$K$11 | K105: =SUMIFS(Codex_USGS_raw!$E$2:$E$94,Codex_USGS_raw!$A$2:$A$94,Codex_sources!$A$11,Codex_USGS_raw!$C$2:$C$94,K$4)*Codex_sources!$D$11*Codex_sources!$K$11 | L105: =SUMIFS(Codex_USGS_raw!$E$2:$E$94,Codex_USGS_raw!$A$2:$A$94,Codex_sources!$A$11,Codex_USGS_raw!$C$2:$C$94,L$4)*Codex_sources!$D$11*Codex_sources!$K$11 | M105: =SUMIFS(Codex_USGS_raw!$E$2:$E$94,Codex_USGS_raw!$A$2:$A$94,Codex_sources!$A$11,Codex_USGS_raw!$C$2:$C$94,M$4)*Codex_sources!$D$11*Codex_sources!$K$11 | ... AN105: =SUMIFS(Codex_USGS_raw!$E$2:$E$94,Codex_USGS_raw!$A$2:$A$94,Codex_sources!$A$11,Codex_USGS_raw!$C$2:$C$94,AN$4)*Codex_sources!$D$11*Codex_sources!$K$11 | AO105: =AO104
C106: MINGrRSV2 | D106: COST | E106: m_graphite | F106: =Codex_Regional!F22*(Codex_sources!$N$11/Codex_sources!$M$11) | G106: =Codex_Regional!G22*(Codex_sources!$N$11/Codex_sources!$M$11) | H106: =Codex_Regional!H22*(Codex_sources!$N$11/Codex_sources!$M$11) | I106: =Codex_Regional!I22*(Codex_sources!$N$11/Codex_sources!$M$11) | J106: =Codex_Regional!J22*(Codex_sources!$N$11/Codex_sources!$M$11) | K106: =Codex_Regional!K22*(Codex_sources!$N$11/Codex_sources!$M$11) | L106: =Codex_Regional!L22*(Codex_sources!$N$11/Codex_sources!$M$11) | M106: =Codex_Regional!M22*(Codex_sources!$N$11/Codex_sources!$M$11) | ... AN106: =Codex_Regional!AN22*(Codex_sources!$N$11/Codex_sources!$M$11) | AO106: =AO105
C107: MINGrRSV3 | D107: BNDACT | AO107: =AO106
C108: MINGrRSV3 | D108: CUM | F108: =SUMIFS(Codex_USGS_raw!$E$2:$E$94,Codex_USGS_raw!$A$2:$A$94,Codex_sources!$A$11,Codex_USGS_raw!$C$2:$C$94,F$4)*Codex_sources!$D$11*Codex_sources!$L$11 | G108: =SUMIFS(Codex_USGS_raw!$E$2:$E$94,Codex_USGS_raw!$A$2:$A$94,Codex_sources!$A$11,Codex_USGS_raw!$C$2:$C$94,G$4)*Codex_sources!$D$11*Codex_sources!$L$11 | H108: =SUMIFS(Codex_USGS_raw!$E$2:$E$94,Codex_USGS_raw!$A$2:$A$94,Codex_sources!$A$11,Codex_USGS_raw!$C$2:$C$94,H$4)*Codex_sources!$D$11*Codex_sources!$L$11 | I108: =SUMIFS(Codex_USGS_raw!$E$2:$E$94,Codex_USGS_raw!$A$2:$A$94,Codex_sources!$A$11,Codex_USGS_raw!$C$2:$C$94,I$4)*Codex_sources!$D$11*Codex_sources!$L$11 | J108: =SUMIFS(Codex_USGS_raw!$E$2:$E$94,Codex_USGS_raw!$A$2:$A$94,Codex_sources!$A$11,Codex_USGS_raw!$C$2:$C$94,J$4)*Codex_sources!$D$11*Codex_sources!$L$11 | K108: =SUMIFS(Codex_USGS_raw!$E$2:$E$94,Codex_USGS_raw!$A$2:$A$94,Codex_sources!$A$11,Codex_USGS_raw!$C$2:$C$94,K$4)*Codex_sources!$D$11*Codex_sources!$L$11 | L108: =SUMIFS(Codex_USGS_raw!$E$2:$E$94,Codex_USGS_raw!$A$2:$A$94,Codex_sources!$A$11,Codex_USGS_raw!$C$2:$C$94,L$4)*Codex_sources!$D$11*Codex_sources!$L$11 | M108: =SUMIFS(Codex_USGS_raw!$E$2:$E$94,Codex_USGS_raw!$A$2:$A$94,Codex_sources!$A$11,Codex_USGS_raw!$C$2:$C$94,M$4)*Codex_sources!$D$11*Codex_sources!$L$11 | ... AN108: =SUMIFS(Codex_USGS_raw!$E$2:$E$94,Codex_USGS_raw!$A$2:$A$94,Codex_sources!$A$11,Codex_USGS_raw!$C$2:$C$94,AN$4)*Codex_sources!$D$11*Codex_sources!$L$11 | AO108: =AO107
C109: MINGrRSV3 | D109: COST | E109: m_graphite | F109: =Codex_Regional!F22*(Codex_sources!$O$11/Codex_sources!$M$11) | G109: =Codex_Regional!G22*(Codex_sources!$O$11/Codex_sources!$M$11) | H109: =Codex_Regional!H22*(Codex_sources!$O$11/Codex_sources!$M$11) | I109: =Codex_Regional!I22*(Codex_sources!$O$11/Codex_sources!$M$11) | J109: =Codex_Regional!J22*(Codex_sources!$O$11/Codex_sources!$M$11) | K109: =Codex_Regional!K22*(Codex_sources!$O$11/Codex_sources!$M$11) | L109: =Codex_Regional!L22*(Codex_sources!$O$11/Codex_sources!$M$11) | M109: =Codex_Regional!M22*(Codex_sources!$O$11/Codex_sources!$M$11) | ... AN109: =Codex_Regional!AN22*(Codex_sources!$O$11/Codex_sources!$M$11) | AO109: =AO108

Sheet Codex_update_notes
A1: Updated | B1: 2026-08-31T00:43:22
A2: Backup created | B2: C:\Users\xli9\OneDrive - McGill University\Desktop\manu11_Battery_ISIE\KiNESYS_BattCircularity-main\KiNESYS_BattCircularity-main-AK_July\SuppXLS\Scen_usingStepMining_n_mute_original_Min2.bak_allredesign_20260831_004322.xlsx
A3: Output workbook | B3: C:\Users\xli9\OneDrive - McGill University\Desktop\manu11_Battery_ISIE\KiNESYS_BattCircularity-main\KiNESYS_BattCircularity-main-AK_July\SuppXLS\Scen_usingStepMining_n_mute_original_Min2.xlsx
A4: Main design | B4: All MIN*RSV1/2/3 rows link to Codex_calc; Codex_calc links to auditable source sheets.
A5: CUM horizon | B5: 2020, 2100
A6: Lithium | B6: Busch et al. 2025 deposit-level capacity, reserve, demonstrated resources, inferred resources, and extraction cost quantiles; RSV3 cost uses p90 rather than the single maximum project.
A7: Nickel/cobalt | B7: USGS MCS 2026 reserves/production/resources for BNDACT/CUM; Peiseler et al. 2024 public source data for cost tiers.
A8: Mn/Al/Cu/Graphite | B8: USGS MCS 2026 production/reserves/resources and public price proxies; tier multipliers are documented in Codex_sources.
A9: Caveat | B9: Some non-lithium costs are price proxies, not mine-level OPEX, because public mine-level cost curves were not available.

Sheet Codex_Regional
A1: Region-specific RSV1 base extraction cost (MUSD/kt), derived from within-region deposit/production data.
A2: RSV2/RSV3 = this base x the material global tier ratio from Codex_sources (N/M, O/M) - preserves the RSV1/2/3 cost-escalation ladder per material while making the base level region-specific.
A3: ASSUMPTION rows flag global fallback used where no regional source was found, or where the region has zero reserves (BNDACT=0) so the cost value is non-binding.
C5: Material | D5: RowType | F5: Africa_North | G5: Africa_Other | H5: Australia | I5: Austria | J5: Baltics | K5: BeNeLux | L5: Brazil | M5: China | N5: CroSloven | O5: CzechSlovak | P5: France | Q5: Germany | R5: GreeceCyp | S5: HunRomBul | T5: Iceland | U5: India | V5: Ireland | W5: ItalyMal | X5: Japan | Y5: LatAm | Z5: MidEast | AA5: NorthAm | AB5: Norway | AC5: Poland | AD5: ROW | AE5: Russia | AF5: SaudiArabia | AG5: SouthAfrica | AH5: SpainPor | AI5: SweFinDen | AJ5: Switzerland | AK5: Turkey | AL5: UK | AM5: Ukraine | AN5: WestBalkans
A7: Lithium RSV1 base = capacity-weighted mean of Busch et al. 2025 deposit-level extraction costs (converted to MUSD/kt Li via stoichiometry) within each TIMES region. | C7: m_lithium | D7: RSV1_base_MUSDperkt | F7: 13.86 | G7: 13.6098 | H7: 14.8233 | I7: 13.86 | J7: 13.86 | K7: 13.86 | L7: 13.8482 | M7: 18.7005 | N7: 13.86 | O7: 20.1589 | P7: 13.86 | Q7: 23.4863 | R7: 13.86 | S7: 13.86 | T7: 13.86 | U7: 13.86 | V7: 13.86 | W7: 13.86 | X7: 13.86 | Y7: 20.7681 | Z7: 13.86 | AA7: 21.3822 | AB7: 13.86 | AC7: 13.86 | AD7: 13.86 | AE7: 13.86 | AF7: 13.86 | AG7: 13.86 | AH7: 20.9686 | AI7: 19.6424 | AJ7: 13.86 | AK7: 13.86 | AL7: 13.86 | AM7: 13.86 | AN7: 13.86
C8: m_lithium | D8: Flag | F8: ASSUMPTION: zero regional reserves (BNDACT=0), cost non-binding, global fallback | G8: Sourced: Busch et al. 2025 deposit-level extraction cost, capacity-weighted within region (see Codex_Li_Busch) | H8: Sourced: Busch et al. 2025 deposit-level extraction cost, capacity-weighted within region (see Codex_Li_Busch) | I8: ASSUMPTION: global fallback, no regional source found | J8: ASSUMPTION: zero regional reserves (BNDACT=0), cost non-binding, global fallback | K8: ASSUMPTION: zero regional reserves (BNDACT=0), cost non-binding, global fallback | L8: Sourced: Busch et al. 2025 deposit-level extraction cost, capacity-weighted within region (see Codex_Li_Busch) | M8: Sourced: Busch et al. 2025 deposit-level extraction cost, capacity-weighted within region (see Codex_Li_Busch) | N8: ASSUMPTION: zero regional reserves (BNDACT=0), cost non-binding, global fallback | O8: Sourced: Busch et al. 2025 deposit-level extraction cost, capacity-weighted within region (see Codex_Li_Busch) | P8: ASSUMPTION: zero regional reserves (BNDACT=0), cost non-binding, global fallback | Q8: Sourced: Busch et al. 2025 deposit-level extraction cost, capacity-weighted within region (see Codex_Li_Busch) | R8: ASSUMPTION: zero regional reserves (BNDACT=0), cost non-binding, global fallback | S8: ASSUMPTION: zero regional reserves (BNDACT=0), cost non-binding, global fallback | T8: ASSUMPTION: zero regional reserves (BNDACT=0), cost non-binding, global fallback | U8: ASSUMPTION: zero regional reserves (BNDACT=0), cost non-binding, global fallback | V8: ASSUMPTION: zero regional reserves (BNDACT=0), cost non-binding, global fallback | W8: ASSUMPTION: zero regional reserves (BNDACT=0), cost non-binding, global fallback | X8: ASSUMPTION: zero regional reserves (BNDACT=0), cost non-binding, global fallback | Y8: Sourced: Busch et al. 2025 deposit-level extraction cost, capacity-weighted within region (see Codex_Li_Busch) | Z8: ASSUMPTION: zero regional reserves (BNDACT=0), cost non-binding, global fallback | AA8: Sourced: Busch et al. 2025 deposit-level extraction cost, capacity-weighted within region (see Codex_Li_Busch) | AB8: ASSUMPTION: zero regional reserves (BNDACT=0), cost non-binding, global fallback | AC8: ASSUMPTION: zero regional reserves (BNDACT=0), cost non-binding, global fallback | AD8: ASSUMPTION: zero regional reserves (BNDACT=0), cost non-binding, global fallback | AE8: ASSUMPTION: zero regional reserves (BNDACT=0), cost non-binding, global fallback | AF8: ASSUMPTION: zero regional reserves (BNDACT=0), cost non-binding, global fallback | AG8: ASSUMPTION: zero regional reserves (BNDACT=0), cost non-binding, global fallback | AH8: Sourced: Busch et al. 2025 deposit-level extraction cost, capacity-weighted within region (see Codex_Li_Busch) | AI8: Sourced: Busch et al. 2025 deposit-level extraction cost, capacity-weighted within region (see Codex_Li_Busch) | AJ8: ASSUMPTION: zero regional reserves (BNDACT=0), cost non-binding, global fallback | AK8: ASSUMPTION: zero regional reserves (BNDACT=0), cost non-binding, global fallback | AL8: ASSUMPTION: global fallback, no regional source found | AM8: ASSUMPTION: zero regional reserves (BNDACT=0), cost non-binding, global fallback | AN8: ASSUMPTION: global fallback, no regional source found
A10: Nickel RSV1 base: Indonesia (HPAL/NPI/matte simple avg of 3 routes) drives ROW; all other regions use global fallback (no genuine per-country cash cost found for Australia/Brazil/China/NorthAm/Russia sulfide-nickel operations). | C10: m_nickel | D10: RSV1_base_MUSDperkt | F10: 14.288 | G10: 14.288 | H10: 14.288 | I10: 14.288 | J10: 14.288 | K10: 14.288 | L10: 14.288 | M10: 14.288 | N10: 14.288 | O10: 14.288 | P10: 14.288 | Q10: 14.288 | R10: 14.288 | S10: 14.288 | T10: 14.288 | U10: 14.288 | V10: 14.288 | W10: 14.288 | X10: 14.288 | Y10: 14.288 | Z10: 14.288 | AA10: 14.288 | AB10: 14.288 | AC10: 14.288 | AD10: 13.2 | AE10: 14.288 | AF10: 14.288 | AG10: 14.288 | AH10: 14.288 | AI10: 14.288 | AJ10: 14.288 | AK10: 14.288 | AL10: 14.288 | AM10: 14.288 | AN10: 14.288
C11: m_nickel | D11: Flag | F11: ASSUMPTION: zero regional reserves (BNDACT=0), cost non-binding, global fallback | G11: ASSUMPTION: zero regional reserves (BNDACT=0), cost non-binding, global fallback | H11: ASSUMPTION: global fallback, no regional source found | I11: ASSUMPTION: zero regional reserves (BNDACT=0), cost non-binding, global fallback | J11: ASSUMPTION: zero regional reserves (BNDACT=0), cost non-binding, global fallback | K11: ASSUMPTION: zero regional reserves (BNDACT=0), cost non-binding, global fallback | L11: ASSUMPTION: global fallback, no regional source found | M11: ASSUMPTION: global fallback, no regional source found | N11: ASSUMPTION: zero regional reserves (BNDACT=0), cost non-binding, global fallback | O11: ASSUMPTION: zero regional reserves (BNDACT=0), cost non-binding, global fallback | P11: ASSUMPTION: zero regional reserves (BNDACT=0), cost non-binding, global fallback | Q11: ASSUMPTION: zero regional reserves (BNDACT=0), cost non-binding, global fallback | R11: ASSUMPTION: zero regional reserves (BNDACT=0), cost non-binding, global fallback | S11: ASSUMPTION: zero regional reserves (BNDACT=0), cost non-binding, global fallback | T11: ASSUMPTION: zero regional reserves (BNDACT=0), cost non-binding, global fallback | U11: ASSUMPTION: zero regional reserves (BNDACT=0), cost non-binding, global fallback | V11: ASSUMPTION: zero regional reserves (BNDACT=0), cost non-binding, global fallback | W11: ASSUMPTION: zero regional reserves (BNDACT=0), cost non-binding, global fallback | X11: ASSUMPTION: zero regional reserves (BNDACT=0), cost non-binding, global fallback | Y11: ASSUMPTION: zero regional reserves (BNDACT=0), cost non-binding, global fallback | Z11: ASSUMPTION: zero regional reserves (BNDACT=0), cost non-binding, global fallback | AA11: ASSUMPTION: global fallback, no regional source found | AB11: ASSUMPTION: zero regional reserves (BNDACT=0), cost non-binding, global fallback | AC11: ASSUMPTION: zero regional reserves (BNDACT=0), cost non-binding, global fallback | AD11: Sourced: Indonesia HPAL/NPI/matte C1 cash cost avg (Benchmark Mineral Intelligence, via MMTA Oct 2025) - Indonesia dominates ROW Ni production (USGS MCS 2026) | AE11: ASSUMPTION: global fallback, no regional source found | AF11: ASSUMPTION: zero regional reserves (BNDACT=0), cost non-binding, global fallback | AG11: ASSUMPTION: zero regional reserves (BNDACT=0), cost non-binding, global fallback | AH11: ASSUMPTION: zero regional reserves (BNDACT=0), cost non-binding, global fallback | AI11: ASSUMPTION: zero regional reserves (BNDACT=0), cost non-binding, global fallback | AJ11: ASSUMPTION: zero regional reserves (BNDACT=0), cost non-binding, global fallback | AK11: ASSUMPTION: zero regional reserves (BNDACT=0), cost non-binding, global fallback | AL11: ASSUMPTION: zero regional reserves (BNDACT=0), cost non-binding, global fallback | AM11: ASSUMPTION: zero regional reserves (BNDACT=0), cost non-binding, global fallback | AN11: ASSUMPTION: zero regional reserves (BNDACT=0), cost non-binding, global fallback
A13: Manganese RSV1 base: South Africa/Australia/Gabon(Africa_Other) use real $/dmtu operating costs converted to $/t contained Mn (x100). Brazil/China/India/ROW use global fallback. | C13: m_manganese | D13: RSV1_base_MUSDperkt | F13: 0.45 | G13: 0.24 | H13: 0.232 | I13: 0.45 | J13: 0.45 | K13: 0.45 | L13: 0.45 | M13: 0.45 | N13: 0.45 | O13: 0.45 | P13: 0.45 | Q13: 0.45 | R13: 0.45 | S13: 0.45 | T13: 0.45 | U13: 0.45 | V13: 0.45 | W13: 0.45 | X13: 0.45 | Y13: 0.45 | Z13: 0.45 | AA13: 0.45 | AB13: 0.45 | AC13: 0.45 | AD13: 0.45 | AE13: 0.45 | AF13: 0.45 | AG13: 0.3025 | AH13: 0.45 | AI13: 0.45 | AJ13: 0.45 | AK13: 0.45 | AL13: 0.45 | AM13: 0.45 | AN13: 0.45
C14: m_manganese | D14: Flag | F14: ASSUMPTION: zero regional reserves (BNDACT=0), cost non-binding, global fallback | G14: Sourced: Eramet/Comilog (Moanda, Gabon) FOB cash cost $2.4/dmtu FY2025 (Eramet FY2025 results); Ghana/Cote d'Ivoire production in this region uses Gabon proxy (no separate source found) | H14: Sourced: South32 GEMCO (Groote Eylandt) operating unit cost $2.32/dmtu FY2024 (SMM) | I14: ASSUMPTION: zero regional reserves (BNDACT=0), cost non-binding, global fallback | J14: ASSUMPTION: zero regional reserves (BNDACT=0), cost non-binding, global fallback | K14: ASSUMPTION: zero regional reserves (BNDACT=0), cost non-binding, global fallback | L14: ASSUMPTION: global fallback, no regional source found | M14: ASSUMPTION: global fallback, no regional source found | N14: ASSUMPTION: zero regional reserves (BNDACT=0), cost non-binding, global fallback | O14: ASSUMPTION: zero regional reserves (BNDACT=0), cost non-binding, global fallback | P14: ASSUMPTION: zero regional reserves (BNDACT=0), cost non-binding, global fallback | Q14: ASSUMPTION: zero regional reserves (BNDACT=0), cost non-binding, global fallback | R14: ASSUMPTION: zero regional reserves (BNDACT=0), cost non-binding, global fallback | S14: ASSUMPTION: zero regional reserves (BNDACT=0), cost non-binding, global fallback | T14: ASSUMPTION: zero regional reserves (BNDACT=0), cost non-binding, global fallback | U14: ASSUMPTION: global fallback, no regional source found | V14: ASSUMPTION: zero regional reserves (BNDACT=0), cost non-binding, global fallback | W14: ASSUMPTION: zero regional reserves (BNDACT=0), cost non-binding, global fallback | X14: ASSUMPTION: zero regional reserves (BNDACT=0), cost non-binding, global fallback | Y14: ASSUMPTION: zero regional reserves (BNDACT=0), cost non-binding, global fallback | Z14: ASSUMPTION: zero regional reserves (BNDACT=0), cost non-binding, global fallback | AA14: ASSUMPTION: zero regional reserves (BNDACT=0), cost non-binding, global fallback | AB14: ASSUMPTION: zero regional reserves (BNDACT=0), cost non-binding, global fallback | AC14: ASSUMPTION: zero regional reserves (BNDACT=0), cost non-binding, global fallback | AD14: ASSUMPTION: global fallback, no regional source found | AE14: ASSUMPTION: zero regional reserves (BNDACT=0), cost non-binding, global fallback | AF14: ASSUMPTION: zero regional reserves (BNDACT=0), cost non-binding, global fallback | AG14: Sourced: South32 Kalahari (Mamatwan/Wessels) operating unit cost $3.00-3.05/dmtu FY2025 (South32 FY25 Operational Review via Ferro-Alloys.com) | AH14: ASSUMPTION: zero regional reserves (BNDACT=0), cost non-binding, global fallback | AI14: ASSUMPTION: zero regional reserves (BNDACT=0), cost non-binding, global fallback | AJ14: ASSUMPTION: zero regional reserves (BNDACT=0), cost non-binding, global fallback | AK14: ASSUMPTION: zero regional reserves (BNDACT=0), cost non-binding, global fallback | AL14: ASSUMPTION: zero regional reserves (BNDACT=0), cost non-binding, global fallback | AM14: ASSUMPTION: zero regional reserves (BNDACT=0), cost non-binding, global fallback | AN14: ASSUMPTION: zero regional reserves (BNDACT=0), cost non-binding, global fallback
A16: Aluminum RSV1 base: China and India use real all-in smelting cash cost. Other regions (Iceland/Norway/Canada/Gulf/Russia/Australia) had only electricity-price or cost-curve-percentile data, not $/t all-in cost - kept on global fallback rather than derive a number (no fabrication). | C16: m_aluminum | D16: RSV1_base_MUSDperkt | F16: 3.968316 | G16: 3.968316 | H16: 3.968316 | I16: 3.968316 | J16: 3.968316 | K16: 3.968316 | L16: 3.968316 | M16: 2.565 | N16: 3.968316 | O16: 3.968316 | P16: 3.968316 | Q16: 3.968316 | R16: 3.968316 | S16: 3.968316 | T16: 3.968316 | U16: 1.8143 | V16: 3.968316 | W16: 3.968316 | X16: 3.968316 | Y16: 3.968316 | Z16: 3.968316 | AA16: 3.968316 | AB16: 3.968316 | AC16: 3.968316 | AD16: 3.968316 | AE16: 3.968316 | AF16: 3.968316 | AG16: 3.968316 | AH16: 3.968316 | AI16: 3.968316 | AJ16: 3.968316 | AK16: 3.968316 | AL16: 3.968316 | AM16: 3.968316 | AN16: 3.968316
C17: m_aluminum | D17: Flag | F17: ASSUMPTION: zero regional reserves (BNDACT=0), cost non-binding, global fallback | G17: ASSUMPTION: zero regional reserves (BNDACT=0), cost non-binding, global fallback | H17: ASSUMPTION: global fallback, no regional source found | I17: ASSUMPTION: zero regional reserves (BNDACT=0), cost non-binding, global fallback | J17: ASSUMPTION: zero regional reserves (BNDACT=0), cost non-binding, global fallback | K17: ASSUMPTION: zero regional reserves (BNDACT=0), cost non-binding, global fallback | L17: ASSUMPTION: global fallback, no regional source found | M17: Sourced: All-in primary aluminum production cost ~$2,565/t, Sep 2024 (S&P Global Commodity Insights, coal-heavy grid power) | N17: ASSUMPTION: zero regional reserves (BNDACT=0), cost non-binding, global fallback | O17: ASSUMPTION: zero regional reserves (BNDACT=0), cost non-binding, global fallback | P17: ASSUMPTION: zero regional reserves (BNDACT=0), cost non-binding, global fallback | Q17: ASSUMPTION: zero regional reserves (BNDACT=0), cost non-binding, global fallback | R17: ASSUMPTION: zero regional reserves (BNDACT=0), cost non-binding, global fallback | S17: ASSUMPTION: zero regional reserves (BNDACT=0), cost non-binding, global fallback | T17: ASSUMPTION: global fallback, no regional source found | U17: Sourced: Vedanta (Odisha, captive coal power) aluminium-making/hot-metal cash cost, avg of Q2 FY2020 $1,852/t, Q1 FY2026 $1,765/t, Q2 FY2026 $1,826/t (Business Standard; AlCircle) | V17: ASSUMPTION: zero regional reserves (BNDACT=0), cost non-binding, global fallback | W17: ASSUMPTION: zero regional reserves (BNDACT=0), cost non-binding, global fallback | X17: ASSUMPTION: zero regional reserves (BNDACT=0), cost non-binding, global fallback | Y17: ASSUMPTION: zero regional reserves (BNDACT=0), cost non-binding, global fallback | Z17: ASSUMPTION: global fallback, no regional source found | AA17: ASSUMPTION: global fallback, no regional source found | AB17: ASSUMPTION: global fallback, no regional source found | AC17: ASSUMPTION: zero regional reserves (BNDACT=0), cost non-binding, global fallback | AD17: ASSUMPTION: global fallback, no regional source found | AE17: ASSUMPTION: global fallback, no regional source found | AF17: ASSUMPTION: zero regional reserves (BNDACT=0), cost non-binding, global fallback | AG17: ASSUMPTION: zero regional reserves (BNDACT=0), cost non-binding, global fallback | AH17: ASSUMPTION: zero regional reserves (BNDACT=0), cost non-binding, global fallback | AI17: ASSUMPTION: zero regional reserves (BNDACT=0), cost non-binding, global fallback | AJ17: ASSUMPTION: zero regional reserves (BNDACT=0), cost non-binding, global fallback | AK17: ASSUMPTION: zero regional reserves (BNDACT=0), cost non-binding, global fallback | AL17: ASSUMPTION: zero regional reserves (BNDACT=0), cost non-binding, global fallback | AM17: ASSUMPTION: zero regional reserves (BNDACT=0), cost non-binding, global fallback | AN17: ASSUMPTION: zero regional reserves (BNDACT=0), cost non-binding, global fallback
A19: Copper RSV1 base: real country C1/cash cost data (Cochilco, Codelco/BHP/Ivanhoe/FirstQuantum/SouthernCopper/KGHM filings), production-weighted per Codex_USGS_raw where 2+ countries. India/Russia fallback (no source found). China/ROW flagged LOW CONFIDENCE (secondary aggregator only). | C19: m_copper | D19: RSV1_base_MUSDperkt | F19: 9.700328 | G19: 4.7219 | H19: 2.6015 | I19: 9.700328 | J19: 9.700328 | K19: 9.700328 | L19: 9.700328 | M19: 5.0706 | N19: 9.700328 | O19: 9.700328 | P19: 9.700328 | Q19: 9.700328 | R19: 9.700328 | S19: 9.700328 | T19: 9.700328 | U19: 9.700328 | V19: 9.700328 | W19: 9.700328 | X19: 9.700328 | Y19: 3.422 | Z19: 9.700328 | AA19: 5.9842 | AB19: 9.700328 | AC19: 5.6989 | AD19: 2.2708 | AE19: 9.700328 | AF19: 9.700328 | AG19: 9.700328 | AH19: 9.700328 | AI19: 9.700328 | AJ19: 9.700328 | AK19: 9.700328 | AL19: 9.700328 | AM19: 9.700328 | AN19: 9.700328
C20: m_copper | D20: Flag | F20: ASSUMPTION: zero regional reserves (BNDACT=0), cost non-binding, global fallback | G20: Sourced: DR Congo (Kamoa-Kakula, Ivanhoe Mines) C1 cash cost $2.16/lb FY2025 + Zambia (Kansanshi, First Quantum) C1 avg $2.08/lb 2025, production-weighted (USGS MCS2026 country production) | H20: Sourced: BHP Olympic Dam unit cost $1.18/lb FY2025 (BHP FY2025 Operational Review) - single-mine proxy for the region | I20: ASSUMPTION: zero regional reserves (BNDACT=0), cost non-binding, global fallback | J20: ASSUMPTION: zero regional reserves (BNDACT=0), cost non-binding, global fallback | K20: ASSUMPTION: zero regional reserves (BNDACT=0), cost non-binding, global fallback | L20: ASSUMPTION: zero regional reserves (BNDACT=0), cost non-binding, global fallback | M20: ASSUMPTION/LOW CONFIDENCE: Project Blue minegate cost estimate ~$2.20-2.40+/lb for Chinese domestic mines (relayed via secondary aggregator, not independently verified) - used with low confidence flag | N20: ASSUMPTION: zero regional reserves (BNDACT=0), cost non-binding, global fallback | O20: ASSUMPTION: zero regional reserves (BNDACT=0), cost non-binding, global fallback | P20: ASSUMPTION: zero regional reserves (BNDACT=0), cost non-binding, global fallback | Q20: ASSUMPTION: zero regional reserves (BNDACT=0), cost non-binding, global fallback | R20: ASSUMPTION: zero regional reserves (BNDACT=0), cost non-binding, global fallback | S20: ASSUMPTION: zero regional reserves (BNDACT=0), cost non-binding, global fallback | T20: ASSUMPTION: zero regional reserves (BNDACT=0), cost non-binding, global fallback | U20: ASSUMPTION: global fallback, no regional source found | V20: ASSUMPTION: zero regional reserves (BNDACT=0), cost non-binding, global fallback | W20: ASSUMPTION: zero regional reserves (BNDACT=0), cost non-binding, global fallback | X20: ASSUMPTION: zero regional reserves (BNDACT=0), cost non-binding, global fallback | Y20: Sourced: Chile national weighted-avg C1 cash cost $1.808/lb FY2025 (Cochilco, 21 mines=94.4% of output) + Peru Quellaveco (Anglo American) unit cost $1.05/lb FY2024, production-weighted (USGS MCS2026 country production) | Z20: ASSUMPTION: zero regional reserves (BNDACT=0), cost non-binding, global fallback | AA20: Sourced: US (Freeport-McMoRan US mines) avg unit net cash cost $3.09/lb 9M2025 + Mexico (Southern Copper) gross operating cash cost $2.17/lb FY2025, production-weighted; Canada cost not found, weight renormalized over US+Mexico only | AB20: ASSUMPTION: zero regional reserves (BNDACT=0), cost non-binding, global fallback | AC20: Sourced: KGHM Polska Miedz Group C1 cash cost $2.57-2.60/lb, Q3 2025 (includes Poland mineral extraction tax ~$1.24/lb component) (KGHM IR release Q3 2025) | AD20: ASSUMPTION/LOW CONFIDENCE: Kazakhstan (KAZ Minerals Bozshakol) net cash cost ~$0.95-1.12/lb (unverified secondary aggregator figure) - used with low confidence flag | AE20: ASSUMPTION: global fallback, no regional source found | AF20: ASSUMPTION: zero regional reserves (BNDACT=0), cost non-binding, global fallback | AG20: ASSUMPTION: zero regional reserves (BNDACT=0), cost non-binding, global fallback | AH20: ASSUMPTION: zero regional reserves (BNDACT=0), cost non-binding, global fallback | AI20: ASSUMPTION: zero regional reserves (BNDACT=0), cost non-binding, global fallback | AJ20: ASSUMPTION: zero regional reserves (BNDACT=0), cost non-binding, global fallback | AK20: ASSUMPTION: zero regional reserves (BNDACT=0), cost non-binding, global fallback | AL20: ASSUMPTION: zero regional reserves (BNDACT=0), cost non-binding, global fallback | AM20: ASSUMPTION: zero regional reserves (BNDACT=0), cost non-binding, global fallback | AN20: ASSUMPTION: zero regional reserves (BNDACT=0), cost non-binding, global fallback
A22: Graphite RSV1 base: Africa_Other (Mozambique/Madagascar/Tanzania cash costs, prod-weighted), NorthAm (Canada PEA study cost), China (flake price proxy, not mine cash cost - flagged). Others fallback. | C22: m_graphite | D22: RSV1_base_MUSDperkt | F22: 1 | G22: 0.5719 | H22: 1 | I22: 1 | J22: 1 | K22: 1 | L22: 1 | M22: 0.46 | N22: 1 | O22: 1 | P22: 1 | Q22: 1 | R22: 1 | S22: 1 | T22: 1 | U22: 1 | V22: 1 | W22: 1 | X22: 1 | Y22: 1 | Z22: 1 | AA22: 0.435 | AB22: 1 | AC22: 1 | AD22: 1 | AE22: 1 | AF22: 1 | AG22: 1 | AH22: 1 | AI22: 1 | AJ22: 1 | AK22: 1 | AL22: 1 | AM22: 1 | AN22: 1
C23: m_graphite | D23: Flag | F23: ASSUMPTION: zero regional reserves (BNDACT=0), cost non-binding, global fallback | G23: Sourced: Mozambique (Syrah Balama) C1 cash cost $535/t FOB + Madagascar (NextSource Molo) cash cost $650/t FOB + Tanzania (Black Rock Mahenge) AISC $518/t, production-weighted (USGS MCS2026 country production) | H23: ASSUMPTION: zero regional reserves (BNDACT=0), cost non-binding, global fallback | I23: ASSUMPTION: global fallback, no regional source found | J23: ASSUMPTION: zero regional reserves (BNDACT=0), cost non-binding, global fallback | K23: ASSUMPTION: zero regional reserves (BNDACT=0), cost non-binding, global fallback | L23: ASSUMPTION: global fallback, no regional source found | M23: Price-basis proxy (not mine cash cost): Fastmarkets 94% C flake graphite FOB China price ~$450-470/t, Oct 2024 - flagged as price proxy since no mine-level cash cost was found for the dominant producer | N23: ASSUMPTION: zero regional reserves (BNDACT=0), cost non-binding, global fallback | O23: ASSUMPTION: zero regional reserves (BNDACT=0), cost non-binding, global fallback | P23: ASSUMPTION: zero regional reserves (BNDACT=0), cost non-binding, global fallback | Q23: ASSUMPTION: global fallback, no regional source found | R23: ASSUMPTION: zero regional reserves (BNDACT=0), cost non-binding, global fallback | S23: ASSUMPTION: zero regional reserves (BNDACT=0), cost non-binding, global fallback | T23: ASSUMPTION: zero regional reserves (BNDACT=0), cost non-binding, global fallback | U23: ASSUMPTION: global fallback, no regional source found | V23: ASSUMPTION: zero regional reserves (BNDACT=0), cost non-binding, global fallback | W23: ASSUMPTION: zero regional reserves (BNDACT=0), cost non-binding, global fallback | X23: ASSUMPTION: zero regional reserves (BNDACT=0), cost non-binding, global fallback | Y23: ASSUMPTION: zero regional reserves (BNDACT=0), cost non-binding, global fallback | Z23: ASSUMPTION: zero regional reserves (BNDACT=0), cost non-binding, global fallback | AA23: Sourced (project-study basis, not an operating mine): Focus Graphite Lac Knife (Quebec) PEA milling opex $67.61/t + thermal purification opex $367.45/t = $435/t (Investing News Network coverage of PEA) | AB23: ASSUMPTION: global fallback, no regional source found | AC23: ASSUMPTION: zero regional reserves (BNDACT=0), cost non-binding, global fallback | AD23: ASSUMPTION: global fallback, no regional source found | AE23: ASSUMPTION: global fallback, no regional source found | AF23: ASSUMPTION: zero regional reserves (BNDACT=0), cost non-binding, global fallback | AG23: ASSUMPTION: zero regional reserves (BNDACT=0), cost non-binding, global fallback | AH23: ASSUMPTION: zero regional reserves (BNDACT=0), cost non-binding, global fallback | AI23: ASSUMPTION: zero regional reserves (BNDACT=0), cost non-binding, global fallback | AJ23: ASSUMPTION: zero regional reserves (BNDACT=0), cost non-binding, global fallback | AK23: ASSUMPTION: global fallback, no regional source found | AL23: ASSUMPTION: zero regional reserves (BNDACT=0), cost non-binding, global fallback | AM23: ASSUMPTION: zero regional reserves (BNDACT=0), cost non-binding, global fallback | AN23: ASSUMPTION: global fallback, no regional source found
A25: m_cobalt: NOT regionally differentiated. Research (2026-09) found only a GLOBAL average AISC ($9.70/lb, 2020, S&P Global Market Intelligence) and no genuine country- or route-level (DRC vs Australia/Canada/Indonesia by-product) cobalt cash-cost figure that could be independently verified (IEA/USGS/Peiseler-linked sources were blocked or did not disaggregate by country in what could be checked). Codex_calc rows 63/66/69 are UNCHANGED (still =Codex_sources!$M/N/O$7, uniform across all regions) rather than force an unsourced regional split. This is a known limitation, not an oversight - see sources.md.
